Workbook

Sheet Info
A20: Press releases:
A21: 18.12.25: Balco sikrer kontrakt verdt 200 mill fra Meyer Werft for 3 cruise skip
A22: 27.11.25: Janu Backlund blir ny manager for Riikku Rakenteet Oy
A23: 03.10.25: Andreas Lindberg blir ny director of business development
A24: 26.08.25: Carin Bengtsson blir ny CFO
A25: 25.06.25: Får kontrakt i Drammen verdt 40 mill
A26: 17.06.25: Ordre i Frankrike verdt 80 mill
A27: 05.06.25: Balco går inn i partnerskap med Altan.dk, en av Danmarks ledende tilbyderfe av balkonger. Balco vil ta over en stor del av produksjonen av stål balkonger for Altan.dk
A28: 26.05.25: Jesper Magnusson blir ny sjef for kommunikasjon
A29: 16.05.25: Michael Grindborn, CFO, trer av som CFO
A30: 08.04.25: Balco kjøper enda 20% til i Suomen Ohutlevyasesnsy Oy
A31: 24.10.24: Balco restrukturerer Riikku Oy, i Finland har det blitt 3 businesses. Riikku Sweden vil bli inkoorporert i RK Teknik
... A33: 22.01.24: Balco kjøper Riikku Group og trykker aksjer for. Delfinansiere kjøpet. Oppkjøpet er på 15 EURm. 3 EURm vil bli betalt gjennom en emisjon og resterende 12 vil være gjeldsfinansiert. Emisjonen blir satt på 46,84

Sheet Modell
A3: Kapitalstruktur | C3: SEKm | D3: Q122 | E3: Q222 | F3: Q322 | G3: Q422 | H3: Q123 | I3: Q223 | J3: Q323 | K3: Q423 | L3: Q124 | M3: Q224 | N3: Q324 | O3: Q424 | P3: Q125 | Q3: Q225 | R3: Q325 | S3: Q425 | W3: FY 2016 | X3: FY 2017 | Y3: FY 2018 | Z3: FY 2019 | AA3: FY 2020 | AB3: FY 2021 | AC3: FY 2022 | AD3: FY 2023 | AE3: FY 2024 | AF3: FY 2025 | AG3: FY 2026 | AH3: FY 2027 | AI3: FY 2028 | AJ3: FY 2029 | AK3: FY 2030 | AL3: FY 2031 | AM3: FY 2032 | AN3: FY 2033 | AO3: FY 2034 | AP3: FY 2035
A4: Price | B4: 18.5 | C4: Revenues | D4: 288.4 | E4: 351.2 | F4: 310.8 | G4: 383.2 | H4: 325 | I4: 346.4 | J4: 253.3 | K4: 289.5 | L4: 326.4 | M4: 374 | N4: 331 | O4: 386.5 | P4: 315.9 | Q4: 331.1 | R4: 276.8 | W4: 801.613 | X4: 988.951 | Y4: 1058.052 | Z4: 1220.605 | AA4: 1200 | AB4: 1120.483 | AC4: 1333.559 | AD4: 1214.887 | AE4: 1417.917 | AF4: =AE4*0.97 -> 1375.3795
A5: S/O | B5: 23.022 | C5: Production and project costs | D5: -214.7 | E5: -275.1 | F5: -249.9 | G5: -306.3 | H5: -256.6 | I5: -274 | J5: -199.9 | K5: -239.1 | L5: -259.1 | M5: -305.1 | N5: -277.5 | O5: -328.3 | P5: -310.5 | Q5: -276.5 | R5: -234.7 | W5: -611.729 | X5: -741.117 | Y5: -804.258 | Z5: -920.602 | AA5: -910.579 | AB5: -824.21 | AC5: -1045.951 | AD5: -969.532 | AE5: -1169.952 | AF5: -1174
A6: MC SEKm | B6: =B4*B5 -> 425.907 | C6: Gross profit | D6: =SUM(D4:D5) -> 73.7 | E6: =SUM(E4:E5) -> 76.1 | F6: =SUM(F4:F5) -> 60.9 | G6: =SUM(G4:G5) -> 76.9 | H6: =SUM(H4:H5) -> 68.4 | I6: =SUM(I4:I5) -> 72.4 | J6: =SUM(J4:J5) -> 53.4 | K6: =SUM(K4:K5) -> 50.4 | ... R6: =SUM(R4:R5) -> 42.1 | W6: =SUM(W4:W5) -> 189.884 | X6: =SUM(X4:X5) -> 247.834 | Y6: =SUM(Y4:Y5) -> 253.794 | Z6: =SUM(Z4:Z5) -> 300.003 | AA6: =SUM(AA4:AA5) -> 289.421 | AB6: =SUM(AB4:AB5) -> 296.273 | AC6: =SUM(AC4:AC5) -> 287.608 | AD6: =SUM(AD4:AD5) -> 245.355 | ... AP6: =SUM(AP4:AP5) -> 0
A7: Cash SEKm | B7: =R41 -> 48.1 | C7: Sales costs | D7: -31 | E7: -32.8 | F7: -28.8 | G7: -33.8 | H7: -29.1 | I7: -27.1 | J7: -25.3 | K7: -26.8 | L7: -31.1 | M7: -33.1 | N7: -25.5 | O7: -31.2 | P7: -27.7 | Q7: -27.5 | R7: -21.7 | W7: -89 | X7: -87.566 | Y7: -94 | Z7: -94.186 | AA7: -111 | AB7: -119.6744 | AC7: -126.43 | AD7: -108.383 | AE7: -120.874 | AF7: =AE7*0.88 -> -106.36912
A8: Debt SEKm | B8: =R49+R53 -> 474.2 | C8: administration costs | D8: -16.7 | E8: -16.2 | F8: -16.2 | G8: -21.8 | H8: -19.4 | I8: -17.7 | J8: -17.2 | K8: -22.3 | L8: -25.7 | M8: -26.9 | N8: -19.8 | O8: -23.5 | P8: -22.6 | Q8: -22.8 | R8: -18.8 | W8: -38.8 | X8: -68.352 | Y8: -53.9 | Z8: -66 | AA8: -63.037 | AB8: -63.468 | AC8: -70.955 | AD8: -76.653 | AE8: -95.946 | AF8: =AE8*0.88 -> -84.43248
A9: EV SEKm | B9: =B6-B7+B8 -> 852.007 | C9: Other operating income | D9: 0 | E9: 0.4 | F9: 0 | G9: 11.9 | H9: 1.2 | I9: 1 | J9: 1.4 | K9: 6.8 | L9: 0.4 | M9: 0.6 | N9: 1.2 | O9: 1.5 | P9: 9.8 | Q9: 1.2 | R9: 0.6 | W9: 10.4 | X9: 6.8 | Y9: 0.737 | Z9: 1.565 | AA9: 0 | AB9: 4.9 | AC9: 12.3 | AD9: 10.3 | AE9: 3.7 | AF9: =AE9*0.88 -> 3.256
C10: Other opex | D10: -0.1 | E10: 0 | F10: 0 | G10: -0.1 | H10: -0.1 | I10: -0.1 | J10: -0.1 | K10: -0.1 | L10: 0 | M10: 0 | N10: 0 | O10: 0 | P10: 0 | Q10: 0 | R10: 0 | W10: -9.3 | X10: -6.5 | Y10: -0.904 | Z10: -0.933 | AA10: 0 | AB10: 0 | AC10: 0 | AD10: 0 | AE10: 0 | AF10: =AE10*0.88 -> 0
C11: Operating profit (EBIT) | D11: =SUM(D6:D10) -> 25.9 | E11: =SUM(E6:E10) -> 27.5 | F11: =SUM(F6:F10) -> 15.9 | G11: =SUM(G6:G10) -> 33.1 | H11: =SUM(H6:H10) -> 21 | I11: =SUM(I6:I10) -> 28.5 | J11: =SUM(J6:J10) -> 12.2 | K11: =SUM(K6:K10) -> 8 | ... R11: =SUM(R6:R10) -> 2.2 | W11: =SUM(W6:W10) -> 63.184 | X11: =SUM(X6:X10) -> 92.216 | Y11: =SUM(Y6:Y10) -> 105.727 | Z11: =SUM(Z6:Z10) -> 140.449 | AA11: =SUM(AA6:AA10) -> 115.384 | AB11: =SUM(AB6:AB10) -> 118.0306 | AC11: =SUM(AC6:AC10) -> 102.523 | AD11: =SUM(AD6:AD10) -> 70.619 | ... AP11: =SUM(AP6:AP10) -> 0
C12: Finance income | D12: 0 | E12: 0.1 | F12: 0.2 | G12: 0.7 | H12: 0.9 | I12: 0.9 | J12: 0.9 | K12: 1 | L12: 2 | M12: 0.2 | N12: 0.4 | O12: 1.8 | P12: 2.3 | Q12: 1.4 | R12: 1 | W12: 0 | X12: 0 | Y12: 0 | Z12: 0.828 | AA12: 0.172 | AB12: 0.165 | AC12: 0.955 | AD12: 3.7 | AE12: 4.5 | AF12: 5
C13: Finance costs | D13: -1.5 | E13: -2.1 | F13: -2.2 | G13: -3.1 | H13: -4.2 | I13: -2.7 | J13: -5.8 | K13: -5.4 | L13: -10.8 | M13: -3.8 | N13: -9.2 | O13: -10.6 | P13: -6.4 | Q13: -6.7 | R13: -8.7 | W13: -40.889 | X13: -37 | Y13: -6.2 | Z13: -9.511 | AA13: -9.8 | AB13: -6.5 | AC13: -8.8 | AD13: -18 | AE13: -34.332 | AF13: -18
C14: PTP | D14: =SUM(D11:D13) -> 24.4 | E14: =SUM(E11:E13) -> 25.5 | F14: =SUM(F11:F13) -> 13.9 | G14: =SUM(G11:G13) -> 30.7 | H14: =SUM(H11:H13) -> 17.7 | I14: =SUM(I11:I13) -> 26.7 | J14: =SUM(J11:J13) -> 7.3 | K14: =SUM(K11:K13) -> 3.6 | ... R14: =SUM(R11:R13) -> -5.5 | W14: =SUM(W11:W13) -> 22.295 | X14: =SUM(X11:X13) -> 55.216 | Y14: =SUM(Y11:Y13) -> 99.527 | Z14: =SUM(Z11:Z13) -> 131.766 | AA14: =SUM(AA11:AA13) -> 105.756 | AB14: =SUM(AB11:AB13) -> 111.6956 | AC14: =SUM(AC11:AC13) -> 94.678 | AD14: =SUM(AD11:AD13) -> 56.319 | ... AP14: =SUM(AP11:AP13) -> 0
C15: Tax | D15: -5.3 | E15: -5.2 | F15: -3.3 | G15: -4.6 | H15: -4.7 | I15: -6 | J15: -1.7 | K15: 2.9 | L15: 0.1 | M15: -2.4 | N15: 0.2 | O15: 1.7 | P15: 9.6 | Q15: 0.1 | R15: 0.7 | W15: -10.662 | X15: -17.6 | Y15: -22.75 | Z15: -28.8 | AA15: -28 | AB15: -21.4 | AC15: -18.45 | AD15: -9.5 | AE15: -0.4 | AF15: =AF14*-0.2 -> -0.166778
C16: Net income | D16: =SUM(D14:D15) -> 19.1 | E16: =SUM(E14:E15) -> 20.3 | F16: =SUM(F14:F15) -> 10.6 | G16: =SUM(G14:G15) -> 26.1 | H16: =SUM(H14:H15) -> 13 | I16: =SUM(I14:I15) -> 20.7 | J16: =SUM(J14:J15) -> 5.6 | K16: =SUM(K14:K15) -> 6.5 | ... R16: =SUM(R14:R15) -> -4.8 | W16: =SUM(W14:W15) -> 11.633 | X16: =SUM(X14:X15) -> 37.616 | Y16: =SUM(Y14:Y15) -> 76.777 | Z16: =SUM(Z14:Z15) -> 102.966 | AA16: =SUM(AA14:AA15) -> 77.756 | AB16: =SUM(AB14:AB15) -> 90.2956 | AC16: =SUM(AC14:AC15) -> 76.228 | AD16: =SUM(AD14:AD15) -> 46.819 | ... AP16: =SUM(AP14:AP15) -> 0 | AQ16: =AP16*(1+$AS$20) -> 0 | AR16: =AQ16*(1+$AS$20) -> 0 | AS16: =AR16*(1+$AS$20) -> 0 | AT16: =AS16*(1+$AS$20) -> 0 | AU16: =AT16*(1+$AS$20) -> 0 | AV16: =AU16*(1+$AS$20) -> 0 | AW16: =AV16*(1+$AS$20) -> 0 | AX16: =AW16*(1+$AS$20) -> 0 | ... MV16: =MU16*(1+$AS$20) -> 0
C17: Share | D17: 21.909 | E17: 21.909 | F17: 21.909 | G17: 21.909 | H17: 21.909 | I17: 21.909 | J17: 21.909 | K17: 23.022 | L17: 23.022 | M17: 23.022 | N17: 23.022 | O17: 23.022 | P17: 23.022 | Q17: 23.022 | R17: 23.022 | W17: 11.287 | X17: 13.7 | Y17: 21.429 | Z17: 21.461 | AA17: 21.695 | AB17: 21.909 | AC17: 21.909 | AD17: 21.909 | AE17: 22.958 | AF17: 23.022 | AG17: 23.022 | AH17: 23.022 | AI17: 23.022 | AJ17: 23.022 | AK17: 23.022 | AL17: 23.022 | AM17: 23.022 | AN17: 23.022 | AO17: 23.022 | AP17: 23.022
C18: EPS | D18: =D16/D17 -> 0.87178785 | E18: =E16/E17 -> 0.92655986 | F18: =F16/F17 -> 0.48381943 | G18: =G16/G17 -> 1.1912913 | H18: =H16/H17 -> 0.59336346 | I18: =I16/I17 -> 0.9448172 | J18: =J16/J17 -> 0.25560272 | K18: =K16/K17 -> 0.28233863 | ... R18: =R16/R17 -> -0.20849622 | W18: =W16/W17 -> 1.0306547 | X18: =X16/X17 -> 2.7456934 | Y18: =Y16/Y17 -> 3.582855 | Z18: =Z16/Z17 -> 4.7978193 | AA18: =AA16/AA17 -> 3.5840516 | AB18: =AB16/AB17 -> 4.121393 | AC18: =AC16/AC17 -> 3.4793007 | AD18: =AD16/AD17 -> 2.1369757 | ... AP18: =AP16/AP17 -> 0
AR19: Disocunt | AS19: 0.08
C20: Revenue y/y | H20: =(H4-D4)/D4 -> 0.12690707 | I20: =(I4-E4)/E4 -> -0.013667426 | J20: =(J4-F4)/F4 -> -0.18500644 | K20: =(K4-G4)/G4 -> -0.24451983 | L20: =(L4-H4)/H4 -> 0.0043076923 | M20: =(M4-I4)/I4 -> 0.079676674 | N20: =(N4-J4)/J4 -> 0.30675089 | O20: =(O4-K4)/K4 -> 0.33506045 | ... S20: =(S4-O4)/O4 -> -1 | X20: =(X4-W4)/W4 -> 0.2337013 | Y20: =(Y4-X4)/X4 -> 0.069873027 | Z20: =(Z4-Y4)/Y4 -> 0.15363423 | AA20: =(AA4-Z4)/Z4 -> -0.016880973 | AB20: =(AC4-AA4)/AA4 -> 0.11129917 | AC20: =(AC4-AB4)/AB4 -> 0.19016442 | AD20: =(AD4-AC4)/AC4 -> -0.088988939 | AE20: =(AE4-AD4)/AD4 -> 0.16711842 | AF20: =(AF4-AE4)/AE4 -> -0.03 | AG20: =(AG4-AF4)/AF4 -> -1 | AH20: =(AH4-AG4)/AG4 -> #DIV/0! | AI20: =(AI4-AH4)/AH4 -> #DIV/0! | AJ20: =(AJ4-AI4)/AI4 -> #DIV/0! | ... AP20: =(AP4-AO4)/AO4 -> #DIV/0! | AR20: TV | AS20: -0.01
C21: Gross margin | D21: =D6/D4 -> 0.25554785 | E21: =E6/E4 -> 0.21668565 | F21: =F6/F4 -> 0.19594595 | G21: =G6/G4 -> 0.2006785 | H21: =H6/H4 -> 0.21046154 | I21: =I6/I4 -> 0.20900693 | J21: =J6/J4 -> 0.21081721 | K21: =K6/K4 -> 0.17409326 | ... S21: =S6/S4 -> #DIV/0! | W21: =W6/W4 -> 0.2368774 | X21: =X6/X4 -> 0.25060291 | Y21: =Y6/Y4 -> 0.23986912 | Z21: =Z6/Z4 -> 0.24578221 | AA21: =AA6/AA4 -> 0.24118417 | AB21: =AC6/AC4 -> 0.2156695 | AC21: =AC6/AC4 -> 0.2156695 | AD21: =AD6/AD4 -> 0.20195705 | AE21: =AE6/AE4 -> 0.17487977 | AF21: =AF6/AF4 -> 0.1464174 | AG21: =AG6/AG4 -> #DIV/0! | AH21: =AH6/AH4 -> #DIV/0! | AI21: =AI6/AI4 -> #DIV/0! | AJ21: =AJ6/AJ4 -> #DIV/0! | ... AP21: =AP6/AP4 -> #DIV/0! | AR21: NPV | AS21: =NPV(AS19,AF16:MV16) -> 0.6176963
C22: EBIT margin | D22: =D11/D4 -> 0.089805825 | E22: =E11/E4 -> 0.078302961 | F22: =F11/F4 -> 0.051158301 | G22: =G11/G4 -> 0.086377871 | H22: =H11/H4 -> 0.064615385 | I22: =I11/I4 -> 0.082274827 | J22: =J11/J4 -> 0.048164232 | K22: =K11/K4 -> 0.027633851 | ... S22: =S11/S4 -> #DIV/0! | W22: =W11/W4 -> 0.078821077 | X22: =X11/X4 -> 0.093246278 | Y22: =Y11/Y4 -> 0.099926091 | Z22: =Z11/Z4 -> 0.11506507 | AA22: =AA11/AA4 -> 0.096153333 | AB22: =AC11/AC4 -> 0.076879238 | AC22: =AC11/AC4 -> 0.076879238 | AD22: =AD11/AD4 -> 0.05812804 | AE22: =AE11/AE4 -> 0.024574781 | AF22: =AF11/AF4 -> 0.010058235 | AG22: =AG11/AG4 -> #DIV/0! | AH22: =AH11/AH4 -> #DIV/0! | AI22: =AI11/AI4 -> #DIV/0! | AJ22: =AJ11/AJ4 -> #DIV/0! | ... AP22: =AP11/AP4 -> #DIV/0! | AR22: S/O | AS22: 23.022
C23: ROCE | W23: 0.168 | X23: 0.239 | Y23: 0.216 | Z23: 0.214 | AA23: 0.199 | AB23: 0.152 | AC23: 0.12 | AD23: 0.086 | AE23: 0.052 | AR23: NPV/Share | AS23: =AS21/AS22 -> 0.026830697
AR24: Opp/nedside | AS24: =(AS23-B4)/B4 -> -0.99854969
C25: Order intake | D25: 291.8 | E25: 364.1 | F25: 264.8 | G25: 187.9 | H25: 245.2 | I25: 301.4 | J25: 135.1 | K25: 295.3 | L25: 352 | M25: 380 | N25: 285.5 | O25: 359.6 | P25: 275 | Q25: 519 | R25: 221.8
C26: y/y | H26: =(H25-D25)/D25 -> -0.15969842 | I26: =(I25-E25)/E25 -> -0.17220544 | J26: =(J25-F25)/F25 -> -0.48980363 | K26: =(K25-G25)/G25 -> 0.57158063 | L26: =(L25-H25)/H25 -> 0.43556281 | M26: =(M25-I25)/I25 -> 0.26078301 | N26: =(N25-J25)/J25 -> 1.1132494 | O26: =(O25-K25)/K25 -> 0.21774467 | ... S26: =(S25-O25)/O25 -> -1
C27: Order backlog | D27: 1567.3 | E27: 1591.9 | F27: 1460.8 | G27: 1274.7 | H27: 1240.7 | I27: 1194.7 | J27: 1066.9 | K27: 1073.6 | L27: 1392 | M27: 1384 | N27: 1328.8 | O27: 1309.3 | P27: 1238 | Q27: 1439 | R27: 1376.7
C28: y/y | H28: =(H27-D27)/D27 -> -0.20838384 | I28: =(I27-E27)/E27 -> -0.24951316 | J28: =(J27-F27)/F27 -> -0.26964677 | K28: =(K27-G27)/G27 -> -0.15776261 | L28: =(L27-H27)/H27 -> 0.12194729 | M28: =(M27-I27)/I27 -> 0.15844982 | N28: =(N27-J27)/J27 -> 0.24547755 | O28: =(O27-K27)/K27 -> 0.21954173 | ... S28: =(S27-O27)/O27 -> -1
C30: Balanse SEKm
C31: Goodwill | D31: 448.1 | E31: 448.2 | F31: 448.4 | G31: 457.8 | H31: 485.3 | I31: 485.6 | J31: 485.4 | K31: 485.2 | L31: 513 | M31: 513.6 | N31: 515 | O31: 515.5 | P31: 512.9 | Q31: 532 | R31: 531.5
C32: Other intangible assets | D32: 109.4 | E32: 109.3 | F32: 109 | G32: 135.3 | H32: 144.3 | I32: 143.9 | J32: 142.2 | K32: 142.2 | L32: 283.9 | M32: 278.8 | N32: 276.6 | O32: 279.5 | P32: 274 | Q32: 283.9 | R32: 282.1
C33: Right of use assets | D33: 88.6 | E33: 85.2 | F33: 80 | G33: 82.3 | H33: 77.7 | I33: 72.7 | J33: 67.8 | K33: 70.5 | L33: 66.3 | M33: 63.8 | N33: 59 | O33: 60.7 | P33: 68.3 | Q33: 67.8 | R33: 62.1
C34: PP&E | D34: 151.1 | E34: 155.2 | F34: 153.6 | G34: 158.8 | H34: 164.9 | I34: 169.9 | J34: 162.9 | K34: 161.9 | L34: 236.7 | M34: 230.5 | N34: 224.6 | O34: 229.6 | P34: 219.6 | Q34: 218.9 | R34: 213.6
C35: Financial assets | D35: 0.2 | E35: 0 | F35: 0.1 | G35: 1 | H35: 0 | I35: 0.7 | J35: 0.7 | K35: 0 | L35: 3.6 | M35: 3.6 | N35: 3.6 | O35: 1.4 | P35: 1.3 | Q35: 1.4 | R35: 0.9
C36: Deferred tax assets | D36: 0 | E36: 63 | F36: 60.6 | G36: 58.4 | H36: 0.6 | I36: 60 | J36: 58.6 | K36: 0 | L36: 0.5 | M36: 0.8 | N36: 0.8 | O36: 6.3 | P36: 8.5 | Q36: 9.7 | R36: 9.5
C37: Inventory | D37: 55.6 | E37: 188.7 | F37: 229.8 | G37: 174.8 | H37: 61.7 | I37: 155.2 | J37: 158.6 | K37: 51.5 | L37: 73.9 | M37: 70.7 | N37: 70.7 | O37: 64.8 | P37: 60.5 | Q37: 57.2 | R37: 61.2
C38: Accounts receivables | D38: 186 | E38: 181.3 | F38: 114.9 | G38: 111.9 | H38: 154.6 | I38: 163 | J38: 156.2 | K38: 138 | L38: 221.2 | M38: 208.1 | N38: 179.8 | O38: 123.1 | P38: 157.5 | Q38: 186 | R38: 213.3
C39: Contract assets | D39: 163.8 | E39: 22.8 | F39: 33.7 | G39: 22 | H39: 144.8 | I39: 37.6 | J39: 42.2 | K39: 177.1 | L39: 203.6 | M39: 200.8 | N39: 197.1 | O39: 209.9 | P39: 222.9 | Q39: 223.2 | R39: 206.4
C40: Other curent receivables | D40: =14.9+32.6 -> 47.5 | E40: 41.8 | F40: 39.6 | G40: 42.5 | H40: =35.1+25.1 -> 60.2 | I40: 29.4 | J40: 20.5 | K40: 37.7 | L40: 46 | M40: 49.2 | N40: 51.5 | O40: 38.5 | P40: 43.6 | Q40: 58.4 | R40: 62.6
C41: Cash | D41: 21 | E41: 8.4 | F41: 140.7 | G41: 51.9 | H41: 16.4 | I41: 27.5 | J41: 21.6 | K41: 2.8 | L41: 49 | M41: 81.2 | N41: 39.4 | O41: 103.1 | P41: 23.5 | Q41: 13.8 | R41: 48.1
C42: Total assets | D42: =SUM(D31:D41) -> 1271.3 | E42: =SUM(E31:E41) -> 1303.9 | F42: =SUM(F31:F41) -> 1410.4 | G42: =SUM(G31:G41) -> 1296.7 | H42: =SUM(H31:H41) -> 1310.5 | I42: =SUM(I31:I41) -> 1345.5 | J42: =SUM(J31:J41) -> 1316.7 | K42: =SUM(K31:K41) -> 1266.9 | ... S42: =SUM(S31:S41) -> 0
C43: Share capital | D43: 131.5 | E43: 131.5 | F43: 131.5 | G43: 131.5 | H43: 131.5 | I43: 131.5 | J43: 131.5 | K43: 131.5 | L43: 138.1 | M43: 138.1 | N43: 138.1 | O43: 138.1 | P43: 138.1 | Q43: 138.1 | R43: 138.1
C44: Other capital contributions | D44: 405.1 | E44: 405.1 | F44: 406.3 | G44: 406.3 | H44: 406.3 | I44: 406.3 | J44: 406.3 | K44: 406.3 | L44: 449.9 | M44: 449.9 | N44: 450.8 | O44: 450.8 | P44: 450.8 | Q44: 450.8 | R44: 450.8
C45: Reserves | D45: 1.6 | E45: 3.8 | F45: 3.7 | G45: 8.3 | H45: 9.4 | I45: 16.2 | J45: 11.7 | K45: 11.6 | L45: 18.5 | M45: 3.7 | N45: 13.6 | O45: 17.9 | P45: 4.9 | Q45: 10.6 | R45: 8.2
C46: Retained earnings, inc profits | D46: 173.3 | E46: 171.6 | F46: 182.3 | G46: 183.7 | H46: 197.5 | I46: 201.7 | J46: 207 | K46: 196.7 | L46: 190.2 | M46: 201.7 | N46: 183.4 | O46: 190 | P46: 158.3 | Q46: 149.2 | R46: 143
C47: Non-controlling interests | D47: 0 | E47: 0 | F47: 0 | G47: 1.2 | H47: 1.1 | I47: 1.1 | J47: 1.4 | K47: 1.8 | L47: 4.6 | M47: 4.5 | N47: 4.6 | O47: 4.2 | P47: 4.4 | Q47: 3.9 | R47: 4.4
C48: Total equity | D48: =SUM(D43:D47) -> 711.5 | E48: =SUM(E43:E47) -> 712 | F48: =SUM(F43:F47) -> 723.8 | G48: =SUM(G43:G47) -> 731 | H48: =SUM(H43:H47) -> 745.8 | I48: =SUM(I43:I47) -> 756.8 | J48: =SUM(J43:J47) -> 757.9 | K48: =SUM(K43:K47) -> 747.9 | ... S48: =SUM(S43:S47) -> 0
C49: non-current liabilities to credit institutions | D49: 121.8 | E49: 122.5 | F49: 172.2 | G49: 72.6 | H49: 123.8 | I49: 176.3 | J49: 174.7 | K49: 174.2 | L49: 343.5 | M49: 356.9 | N49: 337 | O49: 362.9 | P49: 349.6 | Q49: 423.7 | R49: 474.2
C50: Leasing liabilities | D50: 69 | E50: 67.3 | F50: 64.5 | G50: 63.3 | H50: 60.1 | I50: 57.1 | J50: 54.3 | K50: 51.2 | L50: 49.4 | M50: 50.4 | N50: 48.1 | O50: 46.3 | P50: 50.3 | Q50: 50.1 | R50: 46.7
C51: Other non-current liabilities | D51: 29.1 | E51: 28.9 | F51: 29 | G51: 18.4 | H51: 18.7 | I51: 18.7 | J51: 13.8 | K51: 1.4 | L51: 38.4 | M51: 31.4 | N51: 36.6 | O51: 34.7 | P51: 12.9 | Q51: 13.1 | R51: 12.6
C52: Deferred tax liabilities | D52: 32.8 | E52: 33 | F52: 32.6 | G52: 40 | H52: 43.4 | I52: 42.5 | J52: 42.1 | K52: 41.7 | L52: 71.3 | M52: 70.1 | N52: 67.4 | O52: 66.9 | P52: 64.8 | Q52: 65.5 | R52: 65.1
C53: Current lia to credit institutions | D53: 0.4 | E53: 0.4 | F53: 0.4 | G53: 0.8 | H53: 0.4 | I53: 0.4 | J53: 0.4 | K53: 0 | L53: 15.7 | M53: 0 | N53: 0 | O53: 0 | P53: 0 | Q53: 0 | R53: 0
C54: Leasing liabilites | D54: 20 | E54: 18.7 | F54: 16.4 | G54: 20 | H54: 18.7 | I54: 16.6 | J54: 14.8 | K54: 19 | L54: 17.3 | M54: 15.5 | N54: 13.1 | O54: 16.6 | P54: 20 | Q54: 19.3 | R54: 17.2
C55: Contract liabilities | D55: 78.9 | E55: 97 | F55: 135.5 | G55: 124.9 | H55: 84 | I55: 66.3 | J55: 70.3 | K55: 50 | L55: 41.1 | M55: 65.4 | N55: 61 | O55: 38 | P55: 47.5 | Q55: 50.2 | R55: 82.8
C56: Accounts payables | D56: 112.5 | E56: 123.3 | F56: 139.1 | G56: 122.8 | H56: 118.9 | I56: 106 | J56: 101.7 | K56: 91 | L56: 160.3 | M56: 173.6 | N56: 147.1 | O56: 145.7 | P56: 143.4 | Q56: 149.9 | R56: 126.1
C57: Other current liabilities | D57: =2.3+36.6+56.4 -> 95.3 | E57: =3.7+28.6+68.7 -> 101 | F57: =4.5+36.8+55.8 -> 97.1 | G57: =3.6+38.2+61.1 -> 102.9 | H57: =1.6+29.4+65.6 -> 96.6 | I57: =5.2+32.6+66.7 -> 104.5 | J57: =4.2+31+51.4 -> 86.6 | K57: 90.7 | L57: 159.5 | M57: 139.9 | N57: 117.1 | O57: 120.5 | P57: 147.5 | Q57: 127.8 | R57: 122.3
C58: Total debt | D58: =SUM(D49:D57) -> 559.8 | E58: =SUM(E49:E57) -> 592.1 | F58: =SUM(F49:F57) -> 686.8 | G58: =SUM(G49:G57) -> 565.7 | H58: =SUM(H49:H57) -> 564.6 | I58: =SUM(I49:I57) -> 588.4 | J58: =SUM(J49:J57) -> 558.7 | K58: =SUM(K49:K57) -> 519.2 | ... R58: =SUM(R49:R57) -> 947
C59: Total E/D | D59: =D48+D58 -> 1271.3 | E59: =E48+E58 -> 1304.1 | F59: =F48+F58 -> 1410.6 | G59: =G48+G58 -> 1296.7 | H59: =H48+H58 -> 1310.4 | I59: =I48+I58 -> 1345.2 | J59: =J48+J58 -> 1316.6 | K59: =K48+K58 -> 1267.1 | ... S59: =S48+S58 -> 0
C61: Cash flow SEKm
C62: Model OP | D62: =D11 -> 25.9 | E62: =E11 -> 27.5 | F62: =F11 -> 15.9 | G62: =G11 -> 33.1 | H62: =H11 -> 21 | I62: =I11 -> 28.5 | J62: =J11 -> 12.2 | K62: =K11 -> 8 | ... S62: =S11 -> 0 | W62: =W11 -> 63.184 | X62: =X11 -> 92.216 | Y62: =Y11 -> 105.727 | Z62: =Z11 -> 140.449 | AA62: =AA11 -> 115.384 | AB62: =AB11 -> 118.0306 | AC62: =AC11 -> 102.523 | AD62: =AD11 -> 70.619 | AE62: =AE11 -> 34.845
C63: Reported OP | D63: 26 | E63: 28 | F63: 16 | G63: 33 | H63: 22 | I63: 28 | J63: 12 | K63: 8 | L63: 11 | M63: 9.5 | N63: 9.5 | O63: 5 | P63: -35 | Q63: 5.4 | R63: 2 | W63: 63.6 | X63: 92 | Y63: 106 | Z63: 140 | AA63: 115 | AB63: 118 | AC63: 103 | AD63: 71 | AE63: 35
C64: Adjustment non-cash | D64: 4.7 | E64: 4.3 | F64: 4.5 | G64: 18.8 | H64: 14 | I64: 11.1 | J64: 8.9 | K64: 4.9 | L64: 5.4 | M64: 5 | N64: 12.5 | O64: 9.6 | P64: 20.2 | Q64: 0.6 | R64: 11.1 | W64: =14.277+1.6 -> 15.877 | X64: 19.5 | Y64: 21 | Z64: =34.666+2.251 -> 36.917 | AA64: =37.587+0.972 -> 38.559 | AB64: =37.594-9.6 -> 27.994 | AC64: =42-9.788 -> 32.212 | AD64: =44.3-5.3 -> 39 | AE64: =50.22-17.569+3.5 -> 36.151
C65: Intertst received | D65: 0.2 | E65: 0.2 | F65: 0.2 | G65: 0.4 | H65: 0.9 | I65: 0.9 | J65: 0.9 | K65: 1 | L65: 1 | M65: 0.8 | N65: 0.7 | O65: 1.1 | P65: 0.9 | Q65: 1.7 | R65: 0.9 | W65: 0 | X65: 0 | Y65: 0.102 | Z65: 0.828 | AA65: 0.172 | AB65: 0.808 | AC65: 0.955 | AD65: 3.7 | AE65: -3.5
C66: Interest paid | D66: -1.5 | E66: -1.9 | F66: -2.2 | G66: -1.4 | H66: -3.7 | I66: -2.3 | J66: -5.5 | K66: -5 | L66: -5.8 | M66: -7.1 | N66: -7.5 | O66: -8.2 | P66: -6.1 | Q66: -5.7 | R66: -8 | W66: -6.961 | X66: -7.2 | Y66: -6.223 | Z66: -8.5 | AA66: -9.8 | AB66: -6.4 | AC66: -7 | AD66: -16.5 | AE66: -28.662
C67: Income tax paid | D67: -23.8 | E67: -11.7 | F67: -13.9 | G67: 8.5 | H67: -19 | I67: -6.1 | J67: -7.4 | K67: 26.6 | L67: -4.3 | M67: -4.3 | N67: -5.7 | O67: 8.2 | P67: -5.4 | Q67: -5.8 | R67: -3.8 | W67: -3 | X67: -6.2 | Y67: -9.6 | Z67: -34.461 | AA67: -35.7 | AB67: -34 | AC67: -41 | AD67: -5.7 | AE67: -6
C68: WC | D68: =-2.5-55.1+10.4 -> -47.2 | E68: =-7.1-28+31.5 -> -3.6 | F68: =2.4+28.7+47.7 -> 78.8 | G68: =2.6+57.2-22.6 -> 37.2 | H68: =-3.1+17-62.8 -> -48.9 | I68: =2.4-19.5-29.5 -> -46.6 | J68: =0.8+10-14 -> -3.2 | K68: =7.2-3.2-22 -> -18 | L68: =-4.7-17.7+28.4 -> 6 | M68: =2.7+14+17.9 -> 34.6 | N68: =22.2-51.5 -> -29.3 | O68: =6.2+53.1-21.5 -> 37.8 | P68: =3.2-47.4+24.4 -> -19.8 | Q68: =3.8-34.6-14.4 -> -45.2 | R68: =-4.2-14.1+6.7 -> -11.6 | W68: =-2.87-35.215+29.791 -> -8.294 | X68: =-4.4-32.149+93.288 -> 56.739 | Y68: =1.2-4.3-79.7 -> -82.8 | Z68: =0.423-9-29.353 -> -37.93 | AA68: =0.371-43.249+46.032 -> 3.154 | AB68: =-18+51.414-77.1 -> -43.686 | AC68: =-4.6+2.87+67 -> 65.27 | AD68: =7.3+4.2-128.505 -> -117.005 | AE68: =4.2+71.611-26.716 -> 49.095
C69: CFFO | D69: =SUM(D63:D68) -> -41.6 | E69: =SUM(E63:E68) -> 15.3 | F69: =SUM(F63:F68) -> 83.4 | G69: =SUM(G63:G68) -> 96.5 | H69: =SUM(H63:H68) -> -34.7 | I69: =SUM(I63:I68) -> -15 | J69: =SUM(J63:J68) -> 5.7 | K69: =SUM(K63:K68) -> 17.5 | ... S69: =SUM(S63:S68) -> 0 | W69: =SUM(W63:W68) -> 61.222 | X69: =SUM(X63:X68) -> 154.839 | Y69: =SUM(Y63:Y68) -> 28.479 | Z69: =SUM(Z63:Z68) -> 96.854 | AA69: =SUM(AA63:AA68) -> 111.385 | AB69: =SUM(AB63:AB68) -> 62.716 | AC69: =SUM(AC63:AC68) -> 153.437 | AD69: =SUM(AD63:AD68) -> -25.505 | AE69: =SUM(AE63:AE68) -> 82.084
C71: Capex | D71: -3.2 | E71: -6.5 | F71: -3.4 | G71: =-7-4-28.5 -> -39.5 | H71: =-2.2-2.1-39.5 -> -43.8 | I71: -4 | J71: -2 | K71: -3 | L71: =-0.9-1.4-79.7 -> -82 | M71: =-0.1-1-1.4 -> -2.5 | N71: -2 | O71: -8 | P71: =-3.8-1.3 -> -5.1 | Q71: =-7-3.1-20.4 -> -30.5 | R71: -0.5 | W71: =-24.1-0.968+1.2 -> -23.868 | X71: =-54.8-0.224-0.48 -> -55.504 | Y71: =-24-1.88+3-70.581 -> -93.461 | Z71: =-8.7-2+0.542 -> -10.158 | AA71: =-13.715-1 -> -14.715 | AB71: =-13.571-3.25-85.92 -> -102.741 | AC71: =-16.9-7.2-28.454 -> -52.554 | AD71: =-7.7-5.6-39.513 -> -52.813 | AE71: =-6.8-6.277-80.8 -> -93.877
C72: Changes in other non-current ass/lia | D72: 0.6 | E72: -0.3 | F72: -2.1 | G72: 0.5 | H72: 0 | I72: 0 | J72: 0 | K72: 0 | L72: 0 | M72: -0.4 | N72: -0.4 | O72: -1 | P72: -11.7 | Q72: 0.1 | R72: 0 | W72: -0.257 | X72: 0.417 | Y72: 0 | Z72: -0.591 | AA72: 0.544 | AB72: 0 | AC72: 0 | AD72: 0 | AE72: -1.7
C73: CFFI | D73: =SUM(D71:D72) -> -2.6 | E73: =SUM(E71:E72) -> -6.8 | F73: =SUM(F71:F72) -> -5.5 | G73: =SUM(G71:G72) -> -39 | H73: =SUM(H71:H72) -> -43.8 | I73: =SUM(I71:I72) -> -4 | J73: =SUM(J71:J72) -> -2 | K73: =SUM(K71:K72) -> -3 | ... S73: =SUM(S71:S72) -> 0 | W73: =SUM(W71:W72) -> -24.125 | X73: =SUM(X71:X72) -> -55.087 | Y73: =SUM(Y71:Y72) -> -93.461 | Z73: =SUM(Z71:Z72) -> -10.749 | AA73: =SUM(AA71:AA72) -> -14.171 | AB73: =SUM(AB71:AB72) -> -102.741 | AC73: =SUM(AC71:AC72) -> -52.554 | AD73: =SUM(AD71:AD72) -> -52.813 | AE73: =SUM(AE71:AE72) -> -95.577
C75: Changes in bank loans | D75: -50.1 | E75: -0.1 | F75: 49.9 | G75: -99.4 | H75: 49.5 | I75: 50 | J75: -5 | K75: -8.6 | L75: 123.5 | M75: -1 | N75: -14.2 | O75: 24.6 | P75: -13.4 | Q75: 75.3 | R75: 50.5 | W75: =-23.984-9.9 -> -33.884 | X75: =143.606-50.889-41.428 -> 51.289 | Y75: 80 | Z75: =0.873+0.64 -> 1.513 | AA75: -12.814 | AB75: =148.344-206.129-1.6 -> -59.385 | AC75: -99.675 | AD75: =100-14.171 -> 85.829 | AE75: 132.849
C76: Changes in leasing | D76: -2.1 | E76: 0.5 | F76: 0.3 | G76: -24.2 | H76: -6.3 | I76: -5.4 | J76: -4 | K76: -7.6 | L76: -5.1 | M76: -5.2 | N76: -4.9 | O76: -4.3 | P76: -5.8 | Q76: -4.6 | R76: -5.9 | W76: -10.2 | X76: -8.2 | Y76: -12.493 | Z76: -23.133 | AA76: 0 | AB76: 0 | AC76: -25.4 | AD76: -23.358 | AE76: -19.484
C77: New warrants issue | D77: 0 | E77: 0 | F77: 1.2 | G77: 0 | H77: 0 | I77: 0 | J77: 0 | K77: 0 | L77: 0 | M77: 0 | N77: 0.9 | O77: 0 | P77: 0 | Q77: 0 | R77: 0 | W77: 0 | X77: =3-45.938 -> -42.938 | Y77: 0 | Z77: =11.363+1.167 -> 12.53 | AA77: =10+1.7 -> 11.7 | AB77: 1.9 | AC77: 1.2 | AD77: 0.012 | AE77: 1
C78: Dividends | D78: 0 | E78: -21.9 | F78: 0 | G78: -21.9 | H78: 0 | I78: -16.4 | J78: 0 | K78: -16.4 | L78: 0 | M78: 0 | N78: -1.2 | O78: 0 | P78: 0 | Q78: 0 | R78: 0.4 | W78: 0 | X78: -15.635 | Y78: -21.429 | Z78: -42.858 | AA78: 0 | AB78: 0 | AC78: -43.819 | AD78: -32.864 | AE78: -1.2
C79: CFFF | D79: =SUM(D75:D78) -> -52.2 | E79: =SUM(E75:E78) -> -21.5 | F79: =SUM(F75:F78) -> 51.4 | G79: =SUM(G75:G78) -> -145.5 | H79: =SUM(H75:H78) -> 43.2 | I79: =SUM(I75:I78) -> 28.2 | J79: =SUM(J75:J78) -> -9 | K79: =SUM(K75:K78) -> -32.6 | ... S79: =SUM(S75:S78) -> 0 | W79: =SUM(W75:W78) -> -44.084 | X79: =SUM(X75:X78) -> -15.484 | Y79: =SUM(Y75:Y78) -> 46.078 | Z79: =SUM(Z75:Z78) -> -51.948 | AA79: =SUM(AA75:AA78) -> -1.114 | AB79: =SUM(AB75:AB78) -> -57.485 | AC79: =SUM(AC75:AC78) -> -167.694 | AD79: =SUM(AD75:AD78) -> 29.619 | AE79: =SUM(AE75:AE78) -> 113.165
C81: FX | D81: 0.1 | E81: 0.7 | F81: 0.8 | G81: 0.1 | H81: 0.2 | I81: 1.5 | J81: -0.9 | K81: 0 | L81: -3.3 | M81: 0 | N81: -0.7 | O81: -1.3 | P81: 1.4 | Q81: -0.9 | R81: -0.2 | W81: 0 | X81: 0 | Y81: 0.08 | Z81: -0.153 | AA81: -1.377 | AB81: 0.454 | AC81: 1.6 | AD81: 0.35 | AE81: -2.4
C83: CIC | D83: =D69+D73+D79+D81 -> -96.3 | E83: =E69+E73+E79+E81 -> -12.3 | F83: =F69+F73+F79+F81 -> 130.1 | G83: =G69+G73+G79+G81 -> -87.9 | H83: =H69+H73+H79+H81 -> -35.1 | I83: =I69+I73+I79+I81 -> 10.7 | J83: =J69+J73+J79+J81 -> -6.2 | K83: =K69+K73+K79+K81 -> -18.1 | ... S83: =S69+S73+S79+S81 -> 0 | W83: =W69+W73+W79+W81 -> -6.987 | X83: =X69+X73+X79+X81 -> 84.268 | Y83: =Y69+Y73+Y79+Y81 -> -18.824 | Z83: =Z69+Z73+Z79+Z81 -> 34.004 | AA83: =AA69+AA73+AA79+AA81 -> 94.723 | AB83: =AB69+AB73+AB79+AB81 -> -97.056 | AC83: =AC69+AC73+AC79+AC81 -> -65.211 | AD83: =AD69+AD73+AD79+AD81 -> -48.349 | AE83: =AE69+AE73+AE79+AE81 -> 97.272
C85: FCF | D85: =D69+D71 -> -44.8 | E85: =E69+E71 -> 8.8 | F85: =F69+F71 -> 80 | G85: =G69+G71 -> 57 | H85: =H69+H71 -> -78.5 | I85: =I69+I71 -> -19 | J85: =J69+J71 -> 3.7 | K85: =K69+K71 -> 14.5 | ... S85: =S69+S71 -> 0 | W85: =W69+W71 -> 37.354 | X85: =X69+X71 -> 99.335 | Y85: =Y69+Y71 -> -64.982 | Z85: =Z69+Z71 -> 86.696 | AA85: =AA69+AA71 -> 96.67 | AB85: =AB69+AB71 -> -40.025 | AC85: =AC69+AC71 -> 100.883 | AD85: =AD69+AD71 -> -78.318 | AE85: =AE69+AE71 -> -11.793

Sheet Segementer
B4: SEKm | C4: Q122 | D4: Q222 | E4: Q322 | F4: Q422 | G4: 2022 | H4: Q123 | I4: Q223 | J4: Q323 | K4: Q423 | L4: 2023 | M4: Q124 | N4: Q224 | O4: Q324 | P4: Q424 | Q4: 2024 | R4: Q125 | S4: Q225 | T4: Q325 | U4: Q425 | V4: 2025 | W4: Q126 | X4: Q226 | Y4: Q326 | Z4: Q426 | AA4: 2026
B5: Renovation
B6: Net sales | C6: 246.4 | D6: 305.8 | E6: 284.2 | F6: 327 | G6: =SUM(C6:F6) -> 1163.4 | H6: 299.2 | I6: 322.1 | J6: 225 | K6: 241.7 | L6: =SUM(H6:K6) -> 1088 | M6: 222 | N6: 250.8 | O6: 246.6 | P6: 280.7 | Q6: =SUM(M6:P6) -> 1000.1 | R6: 236.4 | S6: 253.1 | T6: 206.4 | V6: =SUM(R6:U6) -> 695.9 | AA6: =SUM(W6:Z6) -> 0
B7: y/y | H7: =(H6-C6)/C6 -> 0.21428571 | I7: =(I6-D6)/D6 -> 0.053302812 | J7: =(J6-E6)/E6 -> -0.20830401 | K7: =(K6-F6)/F6 -> -0.26085627 | L7: =(L6-G6)/G6 -> -0.06481004 | M7: =(M6-H6)/H6 -> -0.25802139 | N7: =(N6-I6)/I6 -> -0.22135983 | O7: =(O6-J6)/J6 -> 0.096 | ... AA7: =(AA6-V6)/V6 -> -1
B8: Adjusted EBITA | C8: 24.2 | D8: 25.5 | E8: 15 | F8: 35.4 | G8: =SUM(C8:F8) -> 100.1 | H8: 25.7 | I8: 30.3 | J8: 15.9 | K8: 11.8 | L8: =SUM(H8:K8) -> 83.7 | M8: 10.7 | N8: 10.7 | O8: 14.8 | P8: 19.7 | Q8: =SUM(M8:P8) -> 55.9 | R8: -4.6 | S8: 6 | T8: 2.4 | V8: =SUM(R8:U8) -> 3.8 | AA8: =SUM(W8:Z8) -> 0
B9: Adjusted EBITDA margin | C9: 0.098 | D9: 0.083 | E9: 0.053 | F9: 0.108 | H9: 0.086 | I9: 0.094 | J9: 0.071 | K9: 0.049 | L9: =L8/L6 -> 0.076930147 | M9: 0.048 | N9: 0.043 | O9: 0.06 | P9: 0.07 | Q9: =Q8/Q6 -> 0.055894411 | R9: -0.019 | S9: 0.024 | T9: 0.012 | V9: =V8/V6 -> 0.0054605547 | AA9: =AA8/AA6 -> #DIV/0!
B10: Order intake | C10: 239.4 | D10: 350.3 | E10: 256.2 | F10: 137.9 | G10: =SUM(C10:F10) -> 983.8 | H10: 199.2 | I10: 288.4 | J10: 82 | K10: 269.1 | L10: =SUM(H10:K10) -> 838.7 | M10: 284.9 | N10: 254.2 | O10: 250 | P10: 285.1 | Q10: =SUM(M10:P10) -> 1074.2 | R10: 208 | S10: 386.2 | T10: 188.4 | V10: =SUM(R10:U10) -> 782.6 | AA10: =SUM(W10:Z10) -> 0
B11: y/y | H11: =(H10-C10)/C10 -> -0.1679198 | I11: =(I10-D10)/D10 -> -0.17670568 | J11: =(J10-E10)/E10 -> -0.67993755 | K11: =(K10-F10)/F10 -> 0.95141407 | L11: =(L10-G10)/G10 -> -0.14748933 | M11: =(M10-H10)/H10 -> 0.43022088 | N11: =(N10-I10)/I10 -> -0.1185853 | O11: =(O10-J10)/J10 -> 2.0487805 | ... AA11: =(AA10-V10)/V10 -> -1
B12: Order backlog | C12: 1378.3 | D12: 1431 | E12: 1325.1 | F12: 1145.6 | H12: 1090.6 | I12: 1054 | J12: 898.7 | K12: 925.5 | M12: 1037.8 | N12: 1029.4 | O12: 1034.4 | P12: 1044.3 | R12: 991.1 | S12: 1133.8 | T12: 1107.5
B13: y/y | H13: =(H12-C12)/C12 -> -0.2087354 | I13: =(I12-D12)/D12 -> -0.26345213 | J13: =(J12-E12)/E12 -> -0.32178703 | K13: =(K12-F12)/F12 -> -0.1921264 | M13: =(M12-H12)/H12 -> -0.048413717 | N13: =(N12-I12)/I12 -> -0.023339658 | O13: =(O12-J12)/J12 -> 0.15099588 | P13: =(P12-K12)/K12 -> 0.12836305 | R13: =(R12-M12)/M12 -> -0.044999036 | S13: =(S12-N12)/N12 -> 0.1014183 | T13: =(T12-O12)/O12 -> 0.070668987 | U13: =(U12-P12)/P12 -> -1 | W13: =(W12-R12)/R12 -> -1 | X13: =(X12-S12)/S12 -> -1 | Y13: =(Y12-T12)/T12 -> -1 | Z13: =(Z12-U12)/U12 -> #DIV/0!
B14: New build
B15: Net sales | C15: 42 | D15: 45.3 | E15: 26.6 | F15: 56.2 | G15: =SUM(C15:F15) -> 170.1 | H15: 26.4 | I15: 24.3 | J15: 28.2 | K15: 47.9 | L15: =SUM(H15:K15) -> 126.8 | M15: 104.4 | N15: 123.2 | O15: 84.4 | P15: 105.8 | Q15: =SUM(M15:P15) -> 417.8 | R15: 79.4 | S15: 78 | T15: 70.4 | V15: =SUM(R15:U15) -> 227.8 | AA15: =SUM(W15:Z15) -> 0
B16: y/y | H16: =(H15-C15)/C15 -> -0.37142857 | I16: =(I15-D15)/D15 -> -0.46357616 | J16: =(J15-E15)/E15 -> 0.060150376 | K16: =(K15-F15)/F15 -> -0.14768683 | L16: =(L15-G15)/G15 -> -0.25455614 | M16: =(M15-H15)/H15 -> 2.9545455 | N16: =(N15-I15)/I15 -> 4.0699588 | O16: =(O15-J15)/J15 -> 1.9929078 | ... AA16: =(AA15-V15)/V15 -> -1
B17: Adjusted EBITA | C17: 2.5 | D17: 3.4 | E17: 1.5 | F17: 3.4 | G17: =SUM(C17:F17) -> 10.8 | H17: 1.4 | I17: 0.3 | J17: 1.5 | K17: 1.6 | L17: =SUM(H17:K17) -> 4.8 | M17: 5.6 | N17: 6.8 | O17: 3.2 | P17: 3 | Q17: =SUM(M17:P17) -> 18.6 | R17: 2.2 | S17: 0.7 | T17: 0.7 | V17: =SUM(R17:U17) -> 3.6 | AA17: =SUM(W17:Z17) -> 0
B18: Adjusted EBITDA margin | C18: 0.059 | D18: 0.075 | E18: 0.057 | F18: 0.06 | H18: 0.052 | I18: 0.013 | J18: 0.051 | K18: 0.034 | L18: =L17/L15 -> 0.03785489 | M18: 0.053 | N18: 0.055 | O18: 0.038 | P18: 0.028 | Q18: =Q17/Q15 -> 0.044518909 | R18: 0.028 | S18: 0.008 | T18: 0.01 | V18: =V17/V15 -> 0.015803336 | AA18: =AA17/AA15 -> #DIV/0!
B19: Order intake | C19: 52.4 | D19: 13.8 | E19: 8.6 | F19: 49.9 | G19: =SUM(C19:F19) -> 124.7 | H19: 46 | I19: 13.1 | J19: 53 | K19: 26.2 | L19: =SUM(H19:K19) -> 138.3 | M19: 67.1 | N19: 125.5 | O19: 35.4 | P19: 74.5 | Q19: =SUM(M19:P19) -> 302.5 | R19: 67 | S19: 133.3 | T19: 33.4 | V19: =SUM(R19:U19) -> 233.7 | AA19: =SUM(W19:Z19) -> 0
B20: y/y | H20: =(H19-C19)/C19 -> -0.1221374 | I20: =(I19-D19)/D19 -> -0.050724638 | J20: =(J19-E19)/E19 -> 5.1627907 | K20: =(K19-F19)/F19 -> -0.4749499 | L20: =(L19-G19)/G19 -> 0.10906175 | M20: =(M19-H19)/H19 -> 0.45869565 | N20: =(N19-I19)/I19 -> 8.5801527 | O20: =(O19-J19)/J19 -> -0.33207547 | ... AA20: =(AA19-V19)/V19 -> -1
B21: Order backlog | C21: 189 | D21: 160.9 | E21: 135.6 | F21: 129.1 | H21: 150 | I21: 140.7 | J21: 168.2 | K21: 148.1 | M21: 354.4 | N21: 354.8 | O21: 294.4 | P21: 265 | R21: 246.9 | S21: 305.3 | T21: 269.2
B22: y/y | H22: =(H21-C21)/C21 -> -0.20634921 | I22: =(I21-D21)/D21 -> -0.12554382 | J22: =(J21-E21)/E21 -> 0.24041298 | K22: =(K21-F21)/F21 -> 0.14717273 | M22: =(M21-H21)/H21 -> 1.3626667 | N22: =(N21-I21)/I21 -> 1.5216773 | O22: =(O21-J21)/J21 -> 0.75029727 | P22: =(P21-K21)/K21 -> 0.78933153 | R22: =(R21-M21)/M21 -> -0.30332957 | S22: =(S21-N21)/N21 -> -0.13951522 | T22: =(T21-O21)/O21 -> -0.085597826 | U22: =(U21-P21)/P21 -> -1 | W22: =(W21-R21)/R21 -> -1 | X22: =(X21-S21)/S21 -> -1 | Y22: =(Y21-T21)/T21 -> -1 | Z22: =(Z21-U21)/U21 -> #DIV/0!

Sheet Financial position
B4: SEKm | C4: Q122 | D4: Q222 | E4: Q322 | F4: Q422 | G4: Q123 | H4: Q223 | I4: Q323 | J4: Q423 | K4: Q124 | L4: Q224 | M4: Q324 | N4: Q424 | O4: Q125 | P4: Q225 | Q4: Q325 | R4: Q425
B5: Non-current lia to banks | C5: 121.8 | D5: 122.5 | E5: 172.2 | F5: 72.6 | G5: 123.8 | H5: 176.3 | I5: 174.7 | J5: 174.2 | K5: 343.5 | L5: 356.9 | M5: 337 | N5: 362.9 | O5: 349.6 | P5: 423.7 | Q5: 474.2
B6: Non-current lease | C6: 69 | D6: 67.3 | E6: 64.5 | F6: 63.3 | G6: 60.1 | H6: 57.1 | I6: 54.3 | J6: 51.2 | K6: 49.4 | L6: 50.4 | M6: 48.1 | N6: 46.3 | O6: 50.3 | P6: 50.1 | Q6: 46.7
B7: Current lia to banks | C7: 0.4 | D7: 0.4 | E7: 0.4 | F7: 0.8 | G7: 0.4 | H7: 0.4 | I7: 0.4 | J7: 0 | K7: 15.7 | L7: 0 | M7: 0 | N7: 0 | O7: 0 | P7: 0 | Q7: 0
B8: Current lease | C8: 20 | D8: 18.7 | E8: 16.4 | F8: 20 | G8: 18.7 | H8: 16.6 | I8: 14.8 | J8: 19 | K8: 17.3 | L8: 15.5 | M8: 13.1 | N8: 16.6 | O8: 20 | P8: 19.3 | Q8: 17.2
B9: Cash | C9: -21 | D9: -8.4 | E9: -140.7 | F9: -51.9 | G9: -16.4 | H9: -27.5 | I9: -21.6 | J9: -2.8 | K9: -49.1 | L9: -81.2 | M9: -96.1 | N9: -147.8 | O9: -64.7 | P9: -57.4 | Q9: -102.1
B10: IB Net debt | C10: =SUM(C5:C9) -> 190.2 | D10: =SUM(D5:D9) -> 200.5 | E10: =SUM(E5:E9) -> 112.8 | F10: =SUM(F5:F9) -> 104.8 | G10: =SUM(G5:G9) -> 186.6 | H10: =SUM(H5:H9) -> 222.9 | I10: =SUM(I5:I9) -> 222.6 | J10: =SUM(J5:J9) -> 241.6 | ... R10: =SUM(R5:R9) -> 0
B11: IB net debt/EBITDA (12m) | C11: 1.2 | D11: 1.3 | E11: 0.7 | F11: 0.7 | G11: 1.2 | H11: 1.5 | I11: 1.5 | J11: 1.9 | K11: 3.2 | L11: 3.3 | M11: 2.8 | N11: 2.5 | O11: 3.9 | P11: 5.6 | Q11: 6.8
C29: Kvartal | D29: NIBD/EBITDA
C30: Q122 | D30: 1.2
C31: Q222 | D31: 1.3
C32: Q322 | D32: 0.7
C33: Q422 | D33: 0.7
C34: Q123 | D34: 1.2
C35: Q223 | D35: 1.5
C36: Q323 | D36: 1.5
C37: Q423 | D37: 1.9
C38: Q124 | D38: 3.2
C39: Q224 | D39: 3.3
C40: Q324 | D40: 2.8
C41: Q424 | D41: 2.5
... C44: Q325 | D44: 6.8
C45: Q425
C46: Q126
C47: Q226
C48: Q326
C49: Q426

Sheet Nøkkeltall
D4: 2025 | E4: 2026 | F4: 2027
C5: EV/EBIT | D5: =Modell!$B$9/Modell!AF11 -> 61.588389 | E5: =Modell!$B$9/Modell!AG11 -> #DIV/0! | F5: =Modell!$B$9/Modell!AH11 -> #DIV/0!
C6: P/E | D6: =Modell!$B$4/Modell!AF18 -> 638.43403 | E6: =Modell!$B$4/Modell!AG18 -> #DIV/0! | F6: =Modell!$B$4/Modell!AH18 -> #DIV/0!

Sheet Nedsideberegning
A3: Nedside | D3: FY 2016 | E3: FY 2017 | F3: FY 2018 | G3: FY 2019 | H3: FY 2020 | I3: FY 2021 | J3: FY 2022 | K3: FY 2023 | L3: FY 2024 | M3: FY 2025 | N3: FY 2026 | O3: FY 2027 | P3: FY 2028 | Q3: FY 2029 | R3: FY 2030 | S3: FY 2031 | T3: FY 2032 | U3: FY 2033 | V3: FY 2034 | W3: FY 2035
A4: Null vekst og dårlige marginer | C4: Revenues | D4: 801.613 | E4: 988.951 | F4: 1058.052 | G4: 1220.605 | H4: 1200 | I4: 1120.483 | J4: 1333.559 | K4: 1214.887 | L4: 1417.917 | M4: =L4*0.97 -> 1375.3795 | N4: =M4 -> 1375.3795 | O4: =N4 -> 1375.3795 | P4: =O4 -> 1375.3795 | Q4: =P4 -> 1375.3795 | R4: =Q4 -> 1375.3795 | S4: =R4 -> 1375.3795 | T4: =S4 -> 1375.3795 | U4: =T4 -> 1375.3795 | ... W4: =V4 -> 1375.3795
A5: =Z23 -> 12.13298 | C5: Production and project costs | D5: -611.729 | E5: -741.117 | F5: -804.258 | G5: -920.602 | H5: -910.579 | I5: -824.21 | J5: -1045.951 | K5: -969.532 | L5: -1169.952 | M5: -1174 | N5: =N4*-0.825 -> -1134.6881 | O5: =O4*-0.825 -> -1134.6881 | P5: =P4*-0.825 -> -1134.6881 | Q5: =Q4*-0.825 -> -1134.6881 | R5: =R4*-0.825 -> -1134.6881 | S5: =S4*-0.825 -> -1134.6881 | T5: =T4*-0.825 -> -1134.6881 | U5: =U4*-0.825 -> -1134.6881 | ... W5: =W4*-0.825 -> -1134.6881
A6: =Z24 -> -0.34416324 | C6: Gross profit | D6: =SUM(D4:D5) -> 189.884 | E6: =SUM(E4:E5) -> 247.834 | F6: =SUM(F4:F5) -> 253.794 | G6: =SUM(G4:G5) -> 300.003 | H6: =SUM(H4:H5) -> 289.421 | I6: =SUM(I4:I5) -> 296.273 | J6: =SUM(J4:J5) -> 287.608 | K6: =SUM(K4:K5) -> 245.355 | ... W6: =SUM(W4:W5) -> 240.69141
C7: Sales costs | D7: -89 | E7: -87.566 | F7: -94 | G7: -94.186 | H7: -111 | I7: -119.6744 | J7: -126.43 | K7: -108.383 | L7: -120.874 | M7: =L7*0.88 -> -106.36912 | N7: =M7*1.2 -> -127.64294 | O7: =N7 -> -127.64294 | P7: =O7 -> -127.64294 | Q7: =P7 -> -127.64294 | R7: =Q7 -> -127.64294 | S7: =R7 -> -127.64294 | T7: =S7 -> -127.64294 | U7: =T7 -> -127.64294 | V7: =U7 -> -127.64294 | W7: =V7 -> -127.64294
C8: administration costs | D8: -38.8 | E8: -68.352 | F8: -53.9 | G8: -66 | H8: -63.037 | I8: -63.468 | J8: -70.955 | K8: -76.653 | L8: -95.946 | M8: =L8*0.88 -> -84.43248 | N8: =M8*1 -> -84.43248 | O8: =N8 -> -84.43248 | P8: =O8 -> -84.43248 | Q8: =P8 -> -84.43248 | R8: =Q8 -> -84.43248 | S8: =R8 -> -84.43248 | T8: =S8 -> -84.43248 | U8: =T8 -> -84.43248 | V8: =U8 -> -84.43248 | W8: =V8 -> -84.43248
C9: Other operating income | D9: 10.4 | E9: 6.8 | F9: 0.737 | G9: 1.565 | H9: 0 | I9: 4.9 | J9: 12.3 | K9: 10.3 | L9: 3.7 | M9: =L9*0.88 -> 3.256 | N9: =M9*1 -> 3.256 | O9: =N9 -> 3.256 | P9: =O9 -> 3.256 | Q9: =P9 -> 3.256 | R9: =Q9 -> 3.256 | S9: =R9 -> 3.256 | T9: =S9 -> 3.256 | U9: =T9 -> 3.256 | V9: =U9 -> 3.256 | W9: =V9 -> 3.256
C10: Other opex | D10: -9.3 | E10: -6.5 | F10: -0.904 | G10: -0.933 | H10: 0 | I10: 0 | J10: 0 | K10: 0 | L10: 0 | M10: =L10*0.88 -> 0 | N10: =M10*1 -> 0 | O10: =N10 -> 0 | P10: =O10 -> 0 | Q10: =P10 -> 0 | R10: =Q10 -> 0 | S10: =R10 -> 0 | T10: =S10 -> 0 | U10: =T10 -> 0 | V10: =U10 -> 0 | W10: =V10 -> 0
C11: Operating profit (EBIT) | D11: =SUM(D6:D10) -> 63.184 | E11: =SUM(E6:E10) -> 92.216 | F11: =SUM(F6:F10) -> 105.727 | G11: =SUM(G6:G10) -> 140.449 | H11: =SUM(H6:H10) -> 115.384 | I11: =SUM(I6:I10) -> 118.0306 | J11: =SUM(J6:J10) -> 102.523 | K11: =SUM(K6:K10) -> 70.619 | ... W11: =SUM(W6:W10) -> 31.871987
C12: Finance income | D12: 0 | E12: 0 | F12: 0 | G12: 0.828 | H12: 0.172 | I12: 0.165 | J12: 0.955 | K12: 3.7 | L12: 4.5 | M12: 5 | N12: 0 | O12: 0 | P12: 0 | Q12: 0 | R12: 0 | S12: 0 | T12: 0 | U12: 0 | V12: 0 | W12: 0
C13: Finance costs | D13: -40.889 | E13: -37 | F13: -6.2 | G13: -9.511 | H13: -9.8 | I13: -6.5 | J13: -8.8 | K13: -18 | L13: -34.332 | M13: -18 | N13: 0 | O13: 0 | P13: 0 | Q13: 0 | R13: 0 | S13: 0 | T13: 0 | U13: 0 | V13: 0 | W13: 0
C14: PTP | D14: =SUM(D11:D13) -> 22.295 | E14: =SUM(E11:E13) -> 55.216 | F14: =SUM(F11:F13) -> 99.527 | G14: =SUM(G11:G13) -> 131.766 | H14: =SUM(H11:H13) -> 105.756 | I14: =SUM(I11:I13) -> 111.6956 | J14: =SUM(J11:J13) -> 94.678 | K14: =SUM(K11:K13) -> 56.319 | ... W14: =SUM(W11:W13) -> 31.871987
C15: Tax | D15: -10.662 | E15: -17.6 | F15: -22.75 | G15: -28.8 | H15: -28 | I15: -21.4 | J15: -18.45 | K15: -9.5 | L15: -0.4 | M15: =M14*-0.2 -> -0.166778 | N15: =N14*-0.2 -> -6.3743973 | O15: =O14*-0.2 -> -6.3743973 | P15: =P14*-0.2 -> -6.3743973 | Q15: =Q14*-0.2 -> -6.3743973 | R15: =R14*-0.2 -> -6.3743973 | S15: =S14*-0.2 -> -6.3743973 | T15: =T14*-0.2 -> -6.3743973 | ... W15: =W14*-0.2 -> -6.3743973
C16: Net income | D16: =SUM(D14:D15) -> 11.633 | E16: =SUM(E14:E15) -> 37.616 | F16: =SUM(F14:F15) -> 76.777 | G16: =SUM(G14:G15) -> 102.966 | H16: =SUM(H14:H15) -> 77.756 | I16: =SUM(I14:I15) -> 90.2956 | J16: =SUM(J14:J15) -> 76.228 | K16: =SUM(K14:K15) -> 46.819 | ... W16: =SUM(W14:W15) -> 25.497589 | X16: =W16*(1+$Z$20) -> 25.242614 | Y16: =X16*(1+$Z$20) -> 24.990187 | Z16: =Y16*(1+$Z$20) -> 24.740285 | AA16: =Z16*(1+$Z$20) -> 24.492883 | AB16: =AA16*(1+$Z$20) -> 24.247954 | AC16: =AB16*(1+$Z$20) -> 24.005474 | AD16: =AC16*(1+$Z$20) -> 23.76542 | AE16: =AD16*(1+$Z$20) -> 23.527765 | ... JS16: =JR16*(1+$Z$20) -> 1.9458481
C17: Share | D17: 11.287 | E17: 13.7 | F17: 21.429 | G17: 21.461 | H17: 21.695 | I17: 21.909 | J17: 21.909 | K17: 21.909 | L17: 22.958 | M17: 22.958 | N17: 22.958 | O17: 22.958 | P17: 22.958 | Q17: 22.958 | R17: 22.958 | S17: 22.958 | T17: 22.958 | U17: 22.958 | V17: 22.958 | W17: 22.958
C18: EPS | D18: =D16/D17 -> 1.0306547 | E18: =E16/E17 -> 2.7456934 | F18: =F16/F17 -> 3.582855 | G18: =G16/G17 -> 4.7978193 | H18: =H16/H17 -> 3.5840516 | I18: =I16/I17 -> 4.121393 | J18: =J16/J17 -> 3.4793007 | K18: =K16/K17 -> 2.1369757 | ... W18: =W16/W17 -> 1.1106189
Y19: Disocunt | Z19: 0.08
C20: Revenue y/y | E20: =(E4-D4)/D4 -> 0.2337013 | F20: =(F4-E4)/E4 -> 0.069873027 | G20: =(G4-F4)/F4 -> 0.15363423 | H20: =(H4-G4)/G4 -> -0.016880973 | I20: =(J4-H4)/H4 -> 0.11129917 | J20: =(J4-I4)/I4 -> 0.19016442 | K20: =(K4-J4)/J4 -> -0.088988939 | L20: =(L4-K4)/K4 -> 0.16711842 | M20: =(M4-L4)/L4 -> -0.03 | N20: =(N4-M4)/M4 -> 0 | O20: =(O4-N4)/N4 -> 0 | P20: =(P4-O4)/O4 -> 0 | Q20: =(Q4-P4)/P4 -> 0 | ... W20: =(W4-V4)/V4 -> 0 | Y20: TV | Z20: -0.01
C21: Gross margin | D21: =D6/D4 -> 0.2368774 | E21: =E6/E4 -> 0.25060291 | F21: =F6/F4 -> 0.23986912 | G21: =G6/G4 -> 0.24578221 | H21: =H6/H4 -> 0.24118417 | I21: =J6/J4 -> 0.2156695 | J21: =J6/J4 -> 0.2156695 | K21: =K6/K4 -> 0.20195705 | L21: =L6/L4 -> 0.17487977 | M21: =M6/M4 -> 0.1464174 | N21: =N6/N4 -> 0.175 | O21: =O6/O4 -> 0.175 | P21: =P6/P4 -> 0.175 | Q21: =Q6/Q4 -> 0.175 | ... W21: =W6/W4 -> 0.175 | Y21: NPV | Z21: =NPV(Z19,M16:JS16) -> 279.32547
C22: EBIT margin | D22: =D11/D4 -> 0.078821077 | E22: =E11/E4 -> 0.093246278 | F22: =F11/F4 -> 0.099926091 | G22: =G11/G4 -> 0.11506507 | H22: =H11/H4 -> 0.096153333 | I22: =J11/J4 -> 0.076879238 | J22: =J11/J4 -> 0.076879238 | K22: =K11/K4 -> 0.05812804 | L22: =L11/L4 -> 0.024574781 | M22: =M11/M4 -> 0.010058235 | N22: =N11/N4 -> 0.023173231 | O22: =O11/O4 -> 0.023173231 | P22: =P11/P4 -> 0.023173231 | Q22: =Q11/Q4 -> 0.023173231 | ... W22: =W11/W4 -> 0.023173231 | Y22: S/O | Z22: 23.022
Y23: NPV/Share | Z23: =Z21/Z22 -> 12.13298
Y24: Opp/nedside | Z24: =(Z23-Modell!B4)/Modell!B4 -> -0.34416324
