Workbook

Sheet Info
A1: Pr nå er 15MW turbiner de største i verden.
G4: 2026 guidance: | K4: North Sea Summit 2026
G5: Revenue | H5: 854 - 944m | K5: Havvind-mål 2050 | L5: 300 GW
G6: EBITDA | H6: 420 - 510m | K6: Årlig ny kapasitet fra 2031 | L6: 15 GW/år
K7: Installert kapasitet i dag (~) | L7: ~35-40 GW
K8: Opptrapping nødvendig | L8: ~8x
G9: T&I = Transportation and installation
K10: Drivere:
G11: AR8 kommer i juli 2026 | K11: • Energisikkerhet & geopolitikk
K12: • Redusere importavhengighet
G13: Nexra er O&M pool til Cadeler | K13: • Nordsjøen som Europas vind-hub
A19: Press releases:
A20: 31.03.26: Styreleder Sohmen-Pao kjøper 715 000 aksjer til kurs 53,52
A21: 26.03.26: CADL henter 1 965 million NOK at 56kr grunnet mulig investering i to t-class nybygg og et heavy lift-vessel. All in kostand for heavy-lift fartøyet er 120 - 145 EURm. Begge t-class fartøyene kjøper for rundt 400 mill USD.
A22: Til sammenligning ble et fartyø kontrahert for 526 mill USD i februar 26. Capex vil være back-end loaded hvor majoriteten kommer etter 2029 og vil være 65% gjeldfinansiert
A23: 23.03.26: Nexra vinner enda en O&M kontrakt som skal fullføres ila 2026 med wind maker
A24: 09.02.26: Nexra, CADL dedicated service concept, Singerer en kontrakt for O&M campaign in Taiwan. Kontrakten er på 20 mull euro og skal starte mars 26 og vare 3-4 måneder av Wind Maker
A25: 28.01.26: CADL signerer preferred supplier agreement (PSA) for fundament installasjon i 2028. Kontrakten skal begynne H128 og skal kreve 2 fartøy ink et A-klasse fartøy
A26: 02.12.25: Nordea funds flagger 5,02%
A27: 0.12.25: Styreleder Sohmen-Pao kjøper aksjer for 786,2 mill kurs 44,5 (Flagger 25%, eier 27,36%)
A28: 01.12.25: CADL styrker balansen sin med en ekstra usikret grønn lånefasilitet. Fasiliteten er på 60 mill Euro med opsjon til å økes til 80 mill Euro
A29: 28.11.25: Cadeler tar levering av sitt 10 fartøy, Wind mover
A30: 10.11.25: Signerer stor kontrakt for både foundation and turbine trans and install til en verdi a 500 EURm. Fundamenetene skal bli transportert tidlig 2029 (A-class). Turbininstall skal starte tidlig 2030 (O-class) (Ikke avklart enda)
... A70: 27.03.24: Wind Scylla signerner kontrakt verdt EUR 75 - 150mill

Sheet Flåte 
A5: Flåte
C6: Class | D6: Main crain capacity tonnes | E6: Hook height (meters) | F6: Turbine installation capacity (MW) | G6: Built/expected deliv | H6: WTG | I6: FOU | J6: O&M
A7: Wind turbine installation vessels (WTIV) | B7: Wind Zaratan | C7: Z-class | D7: 800 | E7: 92 | F7: 9.5 | G7: 2012
B8: Wind Scylla | C8: S-class | D8: 1540 | E8: 105 | F8: 12-14mw | G8: 2015
B9: Wind Orca | C9: O-class | D9: 1600 | E9: 160 | F9: 15-20 | G9: 2012 | K9: Oppgraderte kranen i Q1 2024 for å kunne ta 20 MW turbin
B10: Wind Osprey | C10: O-class | D10: 1600 | E10: 160 | F10: 15-20 | G10: 2013 | K10: Oppgraderte kranen i Q1 2024 for å kunne ta 20 MW turbin
B11: Wind keeper | C11: K-class | D11: 2200 | F11: 15 | G11: Q3 2025
B12: Wind Maker | C12: M-class | D12: 2600 | E12: 174 | F12: 20+ | G12: Q1 2025
B13: Wind Mover | C13: M-class | D13: 2600 | E13: 174 | F13: 20+ | G13: Q4 2025
B14: Wind peak | C14: P-class | D14: >2600 | E14: >200 | F14: 20+ | G14: 2024
B15: Wind Pace | C15: P-class | D15: >2600 | E15: >200 | F15: 20+ | G15: Q2 2025
A16: Foundation installation vessels (FIV) | B16: Wind Ally | C16: A-class | D16: >3300 | E16: >200 | F16: 20+ & up to 6 XL foundations | G16: Q3 2025
B17: Wind Ace | C17: A-class | D17: >3300 | E17: >200 | F17: 20+ & up to 6 XL foundations | G17: Q3 2026
B18: Wind Apex | C18: A-class | D18: >3300 | E18: >200 | F18: 20+ & up to 6 XL foundations | G18: Q2 2027
B19: Wind T | C19: T-class | G19: Q2-Q3 2030
B20: Wind T | C20: T-class | G20: Q2-Q3 2031
A21: Heavy-lift vessel
H23: Capable
H24: Priority
C30: 2025 | G30: 2026 | K30: 2027 | O30: 2028 | S30: 2029 | W30: 2030 | AA30: 2031 | AE30: 2032
A31: Vessel name | B31: Class | C31: Q1 | D31: Q2 | E31: Q3 | F31: Q4 | G31: Q1 | H31: Q2 | I31: Q3 | J31: Q4 | K31: Q1 | L31: Q2 | M31: Q3 | N31: Q4 | O31: Q1 | P31: Q2 | Q31: Q3 | R31: Q4 | S31: Q1 | T31: Q2 | U31: Q3 | V31: Q4 | W31: Q1 | X31: Q2 | Y31: Q3 | Z31: Q4 | AA31: Q1 | AB31: Q2 | AC31: Q3 | AD31: Q4 | AE31: Q1 | AF31: Q2 | AG31: Q3 | AH31: Q4
A33: Wind Zaratan | B33: Z-class | C33: O&M Changfang and Xidao | G33: Upgrades in 2026, O&M in Asia, then back to Europe
A34: Wind Scylla | B34: S-class | D34: Revolution Wind | G34: Sunrise wind
A35: Wind Orca | B35: O-class | C35: O&M | D35: He Dreiht | G35: Hornsea 3 | K35: Baltyk 2 & 3 | O35: Ocean Winds
A36: Wind Osprey | B36: O-class | C36: O&M | D36: Baltic power | G36: EA3 | M36: EA Hub 2
A37: Wind Keeper | B37: K-class | G37: Vestas O&M | K37: Vestas O&M | O37: Vestas O&M | S37: Vestas O&M | W37: Vestas O&M | AA37: Vestas O&M
A38: Wind Maker | B38: M-class | D38: Changhua | G38: O&M | L38: APAC | P38: Reservation agreement
A39: Wind Mover | B39: M-class | C39: Under construction | F39: Undisclosed | G39: Baltik power project | J39: Inch cape
A40: Wind Peak | B40: P-class | C40: Sofia | J40: Hornsea 3 | O40: Undisclosed
A41: Wind Pace | B41: P-class | D41: USA O&M windyard | H41: EA Hub 3 | K41: Baltyk | M41: Baltica 2
A42: Wind Ally | B42: A-class | C42: Under construction | H42: Hornsea 3
A43: Wind Ace | B43: A-class | C43: Under construction | K43: EA Hub 2 | O43: Undiclosed
A44: Wind Apex | B44: A-class | C44: Under construction | L44: Client with a project from yard
A45: Wind T | B45: T-class | C45: Under construction
A46: Wind T | B46: T-class | C46: Under construction
A48: Firm contract
A49: Assumed options
A50: Mobilisation and pre-delivery availibility

Sheet Modell
AI1: nybygg1 | AJ1: nybygg 2
A3: Kapitalstruktur | C3: EUR million | D3: Q122 | E3: Q222 | F3: Q322 | G3: Q422 | H3: Q123 | I3: Q223 | J3: Q323 | K3: Q423 | L3: Q124 | M3: Q224 | N3: Q324 | O3: Q424 | P3: Q125 | Q3: Q225 | R3: Q325 | S3: Q425 | T3: Q126 | U3: Q226 | V3: Q326 | W3: Q426 | Y3: FY 2021 | Z3: FY 2022 | AA3: FY 2023 | AB3: FY 2024 | AC3: FY 2025 | AD3: FY 2026 | AE3: FY 2027 | AF3: FY 2028 | AG3: FY 2029 | AH3: FY 2030 | AI3: FY 2031 | AJ3: FY 2032 | AK3: FY 2033 | AL3: FY 2034 | AM3: FY 2035
A4: Price | B4: 63 | C4: Revenue | H4: 18.9 | I4: 48.873 | J4: 23.415 | L4: 19 | M4: 63 | N4: 81 | O4: =248.738-163 -> 85.738 | P4: 65.474 | Q4: =298.535-P4 -> 233.061 | R4: =452.782-Q4-P4 -> 154.247 | S4: 167.572 | T4: 124.727 | Y4: 60.938 | Z4: 106.424 | AA4: 108.622 | AB4: =SUM(L4:O4) -> 248.738 | AC4: 620 | AD4: 910 | AE4: =AD4*1.3 -> 1183 | AF4: =AE4*1.05 -> 1242.15 | AG4: =AF4*1.05 -> 1304.2575 | AH4: =AG4*1.05 -> 1369.4704 | AI4: =AH4*1.075 -> 1472.1807 | AJ4: =AI4*1.075 -> 1582.5942 | AK4: =AJ4*1.05 -> 1661.7239 | AL4: =AK4*1.05 -> 1744.8101 | AM4: =AL4*1.05 -> 1832.0506
A5: S/O | B5: 386.05334 | C5: Cost of sales | H5: -12.15 | I5: -13.072 | J5: -15.822 | L5: -26.979 | M5: -30 | N5: -33.3 | O5: =90-124.228 -> -34.228 | P5: -44.558 | Q5: =-100.234-P5 -> -55.676 | R5: =-158.826-Q5-P5 -> -58.592 | S5: -77.929 | T5: -97.964 | Y5: -38.879 | Z5: -49.537 | AA5: -59.858 | AB5: =SUM(L5:O5) -> -124.507 | AC5: -237 | AD5: -450 | AE5: =AE4*-0.45 -> -532.35 | AF5: =AF4*-0.45 -> -558.9675 | AG5: =AG4*-0.45 -> -586.91588 | AH5: =AH4*-0.45 -> -616.26167 | AI5: =AI4*-0.45 -> -662.48129 | AJ5: =AJ4*-0.45 -> -712.16739 | AK5: =AK4*-0.45 -> -747.77576 | AL5: =AL4*-0.45 -> -785.16455 | AM5: =AM4*-0.45 -> -824.42278
A6: MC NOKm | B6: =B4*B5 -> 24321.36 | C6: Gross profit | H6: =SUM(H4:H5) -> 6.75 | I6: =SUM(I4:I5) -> 35.801 | J6: =SUM(J4:J5) -> 7.593 | L6: =SUM(L4:L5) -> -7.979 | M6: =SUM(M4:M5) -> 33 | N6: =SUM(N4:N5) -> 47.7 | O6: =SUM(O4:O5) -> 51.51 | P6: =SUM(P4:P5) -> 20.916 | Q6: =SUM(Q4:Q5) -> 177.385 | R6: =SUM(R4:R5) -> 95.655 | S6: =SUM(S4:S5) -> 89.643 | T6: =SUM(T4:T5) -> 26.763 | Y6: =SUM(Y4:Y5) -> 22.059 | Z6: =SUM(Z4:Z5) -> 56.887 | AA6: =SUM(AA4:AA5) -> 48.764 | AB6: =SUM(AB4:AB5) -> 124.231 | AC6: =SUM(AC4:AC5) -> 383 | AD6: =SUM(AD4:AD5) -> 460 | AE6: =SUM(AE4:AE5) -> 650.65 | AF6: =SUM(AF4:AF5) -> 683.1825 | ... AM6: =SUM(AM4:AM5) -> 1007.6278
A7: Cash NOKm | B7: 2389.986 | C7: Other opex | H7: 0.62 | I7: -0.62 | J7: 0 | L7: 0.62 | M7: 0.127 | N7: 0.65 | O7: 0 | P7: 0 | Q7: 0 | R7: 4.5 | S7: 4.27 | T7: 0 | Y7: 0 | Z7: 0 | AA7: 0.137 | AB7: =SUM(L7:O7) -> 1.397 | AC7: 9 | AD7: -50 | AE7: =AD7*1.03 -> -51.5 | AF7: =AE7*1.03 -> -53.045 | AG7: =AF7*1.03 -> -54.63635 | AH7: =AG7*1.03 -> -56.275441 | AI7: =AH7*1.03 -> -57.963704 | AJ7: =AI7*1.03 -> -59.702615 | AK7: =AJ7*1.03 -> -61.493693 | AL7: =AK7*1.03 -> -63.338504 | AM7: =AL7*1.03 -> -65.238659
A8: Debt NOKm | B8: 17080.492 | C8: EBITDA | H8: =SUM(H6:H7) -> 7.37 | I8: =SUM(I6:I7) -> 35.181 | J8: =SUM(J6:J7) -> 7.593 | L8: =SUM(L6:L7) -> -7.359 | M8: =SUM(M6:M7) -> 33.127 | N8: =SUM(N6:N7) -> 48.35 | O8: =SUM(O6:O7) -> 51.51 | P8: =SUM(P6:P7) -> 20.916 | Q8: =SUM(Q6:Q7) -> 177.385 | R8: =SUM(R6:R7) -> 100.155 | S8: =SUM(S6:S7) -> 93.913 | T8: =SUM(T6:T7) -> 26.763 | Y8: =SUM(Y6:Y7) -> 22.059 | Z8: =SUM(Z6:Z7) -> 56.887 | AA8: =SUM(AA6:AA7) -> 48.901 | AB8: =SUM(AB6:AB7) -> 125.628 | AC8: =SUM(AC6:AC7) -> 392 | AD8: =SUM(AD6:AD7) -> 410 | AE8: =SUM(AE6:AE7) -> 599.15 | AF8: =SUM(AF6:AF7) -> 630.1375 | ... AM8: =SUM(AM6:AM7) -> 942.38918
A9: EV NOKm | B9: =B6-B7+B8 -> 39011.866 | C9: Adminstrative expenses | H9: -4.6 | I9: -8.512 | J9: -6.931 | L9: -12.797 | M9: -13.5 | N9: -15 | O9: =-14 -> -14 | P9: -16.222 | Q9: =2.8-33.2-P9 -> -14.178 | R9: =-50.828-Q9-P9 -> -20.428 | S9: -23.798 | T9: -19 | Y9: -10.925 | Z9: -15.696 | AA9: -34.458 | AB9: =SUM(L9:O9) -> -55.297 | AC9: -75 | AD9: -100 | AE9: =AD9*1.05 -> -105 | AF9: =AE9*1.05 -> -110.25 | AG9: =AF9*1.05 -> -115.7625 | AH9: =AG9*1.05 -> -121.55063 | AI9: =AH9*1.05 -> -127.62816 | AJ9: =AI9*1.05 -> -134.00956 | AK9: =AJ9*1.05 -> -140.71004 | AL9: =AK9*1.05 -> -147.74554 | AM9: =AL9*1.05 -> -155.13282
C10: EBIT | H10: =SUM(H8:H9) -> 2.77 | I10: =SUM(I8:I9) -> 26.669 | J10: =SUM(J8:J9) -> 0.662 | L10: =SUM(L8:L9) -> -20.156 | M10: =SUM(M8:M9) -> 19.627 | N10: =SUM(N8:N9) -> 33.35 | O10: =SUM(O8:O9) -> 37.51 | P10: =SUM(P8:P9) -> 4.694 | Q10: =SUM(Q8:Q9) -> 163.207 | R10: =SUM(R8:R9) -> 79.727 | S10: =SUM(S8:S9) -> 70.115 | T10: =SUM(T8:T9) -> 7.763 | Y10: =SUM(Y8:Y9) -> 11.134 | Z10: =SUM(Z8:Z9) -> 41.191 | AA10: =SUM(AA8:AA9) -> 14.443 | AB10: =SUM(AB8:AB9) -> 70.331 | AC10: =SUM(AC8:AC9) -> 317 | AD10: =SUM(AD8:AD9) -> 310 | AE10: =SUM(AE8:AE9) -> 494.15 | AF10: =SUM(AF8:AF9) -> 519.8875 | ... AM10: =SUM(AM8:AM9) -> 787.25636
C11: Finance income | H11: 0.015 | I11: 0.426 | J11: 0.285 | L11: 0.406 | M11: 4.5 | N11: -1.5 | O11: 3.2 | P11: 0.27 | Q11: 5 | R11: =4.4-Q11 -> -0.6 | S11: 2.828 | T11: 9.5 | Y11: 1.795 | Z11: 4.031 | AA11: 1.541 | AB11: =SUM(L11:O11) -> 6.606 | AC11: 7 | AD11: 10 | AE11: 10 | AF11: 10 | AG11: 10 | AH11: 10 | AI11: 10 | AJ11: 10 | AK11: 10 | AL11: 10 | AM11: 10
A12: Euro/NOK | B12: 10.8 | C12: Finance costs | H12: -0.127 | I12: -0.164 | J12: -0.337 | L12: -1.087 | M12: -1.1 | N12: -3.4 | O12: -1 | P12: -2 | Q12: 0 | R12: -12 | S12: -23.377 | T12: -24.172 | Y12: -5.491 | Z12: -9.681 | AA12: -4.486 | AB12: =SUM(L12:O12) -> -6.587 | AC12: -37 | AD12: -50 | AE12: -50 | AF12: -50 | AG12: =AF12*1.05 -> -52.5 | AH12: =AG12*1.05 -> -55.125 | AI12: =AH12*1.05 -> -57.88125 | AJ12: =AI12*1.05 -> -60.775313 | AK12: -61 | AL12: -61 | AM12: -61
C13: PTP | H13: =SUM(H10:H12) -> 2.658 | I13: =SUM(I10:I12) -> 26.931 | J13: =SUM(J10:J12) -> 0.61 | K13: =SUM(K10:K12) -> 0 | L13: =SUM(L10:L12) -> -20.837 | M13: =SUM(M10:M12) -> 23.027 | N13: =SUM(N10:N12) -> 28.45 | O13: =SUM(O10:O12) -> 39.71 | ... T13: =SUM(T10:T12) -> -6.909 | Y13: =SUM(Y10:Y12) -> 7.438 | Z13: =SUM(Z10:Z12) -> 35.541 | AA13: =SUM(AA10:AA12) -> 11.498 | AB13: =SUM(AB10:AB12) -> 70.35 | AC13: =SUM(AC10:AC12) -> 287 | AD13: =SUM(AD10:AD12) -> 270 | AE13: =SUM(AE10:AE12) -> 454.15 | AF13: =SUM(AF10:AF12) -> 479.8875 | ... AM13: =SUM(AM10:AM12) -> 736.25636
C14: tax | H14: -0.019 | I14: 0.019 | J14: 0 | L14: -0.019 | M14: -1.1 | N14: -0.5 | O14: -1 | P14: -1.2 | Q14: -2 | R14: -2.5 | S14: -1.98 | T14: 0 | Y14: 0.013 | Z14: 0 | AA14: 0 | AB14: =SUM(L14:O14) -> -2.619 | AC14: -8 | AD14: -6 | AE14: =AE13*-0.22 -> -99.913 | AF14: =AF13*-0.22 -> -105.57525 | AG14: =AG13*-0.22 -> -110.97741 | AH14: =AH13*-0.22 -> -116.65668 | AI14: =AI13*-0.22 -> -126.76977 | AJ14: =AJ13*-0.22 -> -137.70665 | AK14: =AK13*-0.22 -> -145.36377 | AL14: =AL13*-0.22 -> -153.46353 | AM14: =AM13*-0.22 -> -161.9764
A15: Bokverdi | C15: Net income | H15: =SUM(H13:H14) -> 2.639 | I15: =SUM(I13:I14) -> 26.95 | J15: =SUM(J13:J14) -> 0.61 | L15: =SUM(L13:L14) -> -20.856 | M15: =SUM(M13:M14) -> 21.927 | N15: =SUM(N13:N14) -> 27.95 | O15: =SUM(O13:O14) -> 38.71 | P15: =SUM(P13:P14) -> 1.764 | Q15: =SUM(Q13:Q14) -> 166.207 | R15: =SUM(R13:R14) -> 64.627 | S15: =SUM(S13:S14) -> 47.586 | T15: =SUM(T13:T14) -> -6.909 | Y15: =SUM(Y13:Y14) -> 7.451 | Z15: =SUM(Z13:Z14) -> 35.541 | AA15: =SUM(AA13:AA14) -> 11.498 | AB15: =SUM(AB13:AB14) -> 67.731 | AC15: =SUM(AC13:AC14) -> 279 | AD15: =SUM(AD13:AD14) -> 264 | AE15: =SUM(AE13:AE14) -> 354.237 | AF15: =SUM(AF13:AF14) -> 374.31225 | ... AM15: =SUM(AM13:AM14) -> 574.27996 | AN15: =AM15*(1+$AP$19) -> 568.53716 | AO15: =AN15*(1+$AP$19) -> 562.85179 | AP15: =AO15*(1+$AP$19) -> 557.22327 | AQ15: =AP15*(1+$AP$19) -> 551.65104 | AR15: =AQ15*(1+$AP$19) -> 546.13453 | AS15: =AR15*(1+$AP$19) -> 540.67318 | AT15: =AS15*(1+$AP$19) -> 535.26645 | AU15: =AT15*(1+$AP$19) -> 529.91378 | ... EG15: =EF15*(1+$AP$19) -> 214.47305
A16: =(T49*B12)/B5 -> 47.049689 | C16: Share | H16: 342 | I16: 342 | J16: 342 | K16: 342 | L16: 342 | M16: 342 | N16: 350.95758 | O16: 350.95758 | P16: 350.95758 | Q16: 350.95758 | R16: 350.95758 | S16: 350.95758 | T16: 350.95758 | Y16: 128 | Z16: 155 | AA16: 203.95758 | AB16: 350.95758 | AC16: 350.95758 | AD16: 386.05334 | AE16: 386.05334 | AF16: 386.05334 | AG16: 386.05334 | AH16: 386.05334 | AI16: 386.05334 | AJ16: 386.05334 | AK16: 386.05334 | AL16: 386.05334 | AM16: 386.05334
C17: EPS (NOK) | H17: =(H15/H16)*$B$12 -> 0.083336842 | I17: =(I15/I16)*$B$12 -> 0.85105263 | J17: =(J15/J16)*$B$12 -> 0.019263158 | K17: =(K15/K16)*$B$12 -> 0 | L17: =(L15/L16)*$B$12 -> -0.65861053 | M17: =(M15/M16)*$B$12 -> 0.69243158 | N17: =(N15/N16)*$B$12 -> 0.86010394 | O17: =(O15/O16)*$B$12 -> 1.1912209 | P17: 0.06 | Q17: 5.31 | R17: 2.06 | S17: 2 | T17: =(T15*10.8)/T16 -> -0.21261031 | Y17: 0.65 | Z17: 2.57 | AA17: 0.63 | AB17: 2.16 | AC17: 8.96 | AD17: =(AD15/AD16)*$B$12 -> 7.3855079 | AE17: =(AE15/AE16)*$B$12 -> 9.9099249 | AF17: =(AF15/AF16)*$B$12 -> 10.471538 | AG17: =(AG15/AG16)*$B$12 -> 11.007354 | AH17: =(AH15/AH16)*$B$12 -> 11.570656 | AI17: =(AI15/AI16)*$B$12 -> 12.573729 | AJ17: =(AJ15/AJ16)*$B$12 -> 13.658508 | AK17: =(AK15/AK16)*$B$12 -> 14.417984 | ... AM17: =(AM15/AM16)*$B$12 -> 16.065717
A18: P/B | AO18: Discount | AP18: 0.1
A19: =B4/A16 -> 1.3390099 | C19: Revenue y/y | H19: =(H4-D4)/D4 -> #DIV/0! | I19: =(I4-E4)/E4 -> #DIV/0! | J19: =(J4-F4)/F4 -> #DIV/0! | K19: =(K4-G4)/G4 -> #DIV/0! | L19: =(L4-H4)/H4 -> 0.0052910053 | M19: =(M4-I4)/I4 -> 0.28905531 | N19: =(N4-J4)/J4 -> 2.4593209 | O19: =(O4-K4)/K4 -> #DIV/0! | ... T19: =(T4-P4)/P4 -> 0.90498518 | Z19: =(Z4-Y4)/Y4 -> 0.7464308 | AA19: =(AA4-Z4)/Z4 -> 0.020653236 | AB19: =(AB4-AA4)/AA4 -> 1.2899413 | AC19: =(AC4-AB4)/AB4 -> 1.4925826 | AD19: =(AD4-AC4)/AC4 -> 0.46774194 | AE19: =(AE4-AD4)/AD4 -> 0.3 | AF19: =(AF4-AE4)/AE4 -> 0.05 | AG19: =(AG4-AF4)/AF4 -> 0.05 | ... AM19: =(AM4-AL4)/AL4 -> 0.05 | AO19: TV | AP19: -0.01
C20: Gross profit | L20: =L6/L4 -> -0.41994737 | M20: =M6/M4 -> 0.52380952 | N20: =N6/N4 -> 0.58888889 | O20: =O6/O4 -> 0.60078378 | P20: =P6/P4 -> 0.31945505 | Q20: =Q6/Q4 -> 0.76110975 | R20: =R6/R4 -> 0.62014172 | S20: =S6/S4 -> 0.53495214 | T20: =T6/T4 -> 0.21457263 | Y20: =Y6/Y4 -> 0.36199088 | Z20: =Z6/Z4 -> 0.53453168 | AA20: =AA6/AA4 -> 0.448933 | AB20: =AB6/AB4 -> 0.4994452 | AC20: =AC6/AC4 -> 0.61774194 | AD20: =AD6/AD4 -> 0.50549451 | AE20: =AE6/AE4 -> 0.55 | AF20: =AF6/AF4 -> 0.55 | ... AM20: =AM6/AM4 -> 0.55 | AO20: NPV Eur | AP20: =NPV(AP18,AD15:EG15) -> 4528.999
A21: Gearing | B21: =(T54+T62-T42)/AD10 -> 4.3878452 | C21: EBITDA margin | H21: =H8/H4 -> 0.38994709 | I21: =I8/I4 -> 0.71984531 | J21: =J8/J4 -> 0.32427931 | K21: =K8/K4 -> #DIV/0! | L21: =L8/L4 -> -0.38731579 | M21: =M8/M4 -> 0.5258254 | N21: =N8/N4 -> 0.59691358 | O21: =O8/O4 -> 0.60078378 | ... T21: =T8/T4 -> 0.21457263 | Y21: =Y8/Y4 -> 0.36199088 | Z21: =Z8/Z4 -> 0.53453168 | AA21: =AA8/AA4 -> 0.45019425 | AB21: =AB8/AB4 -> 0.50506155 | AC21: =AC8/AC4 -> 0.63225806 | AD21: =AD8/AD4 -> 0.45054945 | AE21: =AE8/AE4 -> 0.50646661 | AF21: =AF8/AF4 -> 0.50729582 | ... AM21: =AM8/AM4 -> 0.51439036 | AO21: NPV NOK | AP21: =AP20*B12 -> 48913.189
C22: EBIT margin | H22: =H10/H4 -> 0.14656085 | I22: =I10/I4 -> 0.54567962 | J22: =J10/J4 -> 0.028272475 | K22: =K10/K4 -> #DIV/0! | L22: =L10/L4 -> -1.0608421 | M22: =M10/M4 -> 0.31153968 | N22: =N10/N4 -> 0.4117284 | O22: =O10/O4 -> 0.43749563 | ... T22: =T10/T4 -> 0.062239932 | Y22: =Y10/Y4 -> 0.1827103 | Z22: =Z10/Z4 -> 0.38704616 | AA22: =AA10/AA4 -> 0.1329657 | AB22: =AB10/AB4 -> 0.28275133 | AC22: =AC10/AC4 -> 0.51129032 | AD22: =AD10/AD4 -> 0.34065934 | AE22: =AE10/AE4 -> 0.41770921 | AF22: =AF10/AF4 -> 0.41853842 | ... AM22: =AM10/AM4 -> 0.42971321 | AO22: S/O | AP22: 386.05334
C23: Utilisation | P23: 0.553 | Q23: 0.67 | R23: 0.758 | T23: 0.476 | AO23: NPV/Share | AP23: =AP21/AP22 -> 126.7006
AO24: Opp- nedside | AP24: =(AP23-B4)/B4 -> 1.0111206
C25: ROE | Y25: 0.027 | Z25: 0.083 | AA25: 0.016 | AB25: 0.06
C27: Order backlog (EUR mill) | L27: 1801 | M27: 1915 | N27: 2054 | O27: 2336 | P27: 2487 | Q27: 2492 | R27: 2387 | S27: 2827 | T27: 2705
C28: y/y | P28: =(P27-L27)/L27 -> 0.3808995 | Q28: =(Q27-M27)/M27 -> 0.30130548 | R28: =(R27-N27)/N27 -> 0.16212269 | S28: =(S27-O27)/O27 -> 0.21018836 | T28: =(T27-P27)/P27 -> 0.08765581
C30: Balanse EUR million
C31: Intangible assets | G31: 0.419 | H31: 16.947 | I31: 16.947 | K31: 16.947 | L31: 17.236 | M31: 17.44 | N31: 16.72 | O31: 18.19 | P31: 18.644 | Q31: 19 | R31: 19.283 | S31: 19.432 | T31: 19.493
C32: PP&E | G32: 606.204 | H32: 1085.632 | I32: 1085.632 | K32: 1085.632 | L32: 1188.829 | M32: 1380.924 | N32: 1612.704 | O32: 1712.266 | P32: 2188.349 | Q32: 2384.551 | R32: 2626.254 | S32: 2991.129 | T32: 3016.754
C33: Right-of-use assets | G33: 0.287 | H33: 0.973 | I33: 0.973 | K33: 0.973 | L33: 11 | M33: 11.118 | N33: 10.691 | O33: 10.337 | P33: 10.639 | Q33: 11.133 | R33: 12.428 | S33: 12.598 | T33: 12
C34: Leasehold deposits | G34: 0.238 | H34: 1.22 | I34: 1.22 | K34: 1.22 | L34: 1.226 | M34: 1.047 | N34: 1.047 | O34: 1.014 | P34: 1 | Q34: 1.09 | R34: 1.144 | S34: 1.141 | T34: 1
C35: Derivative assets | G35: 3.376 | H35: 0.338 | I35: 0.338 | K35: 0.338 | L35: 1.248 | M35: 3.192 | N35: 0.695 | O35: 6.593 | P35: 2.9 | Q35: 0.919 | R35: 1.443 | S35: 2.419 | T35: 6.6
C36: Inventories | G36: 0.549 | H36: 1.836 | I36: 1.836 | K36: 1.836 | L36: 1.86 | M36: 0.947 | N36: 1.351 | O36: 1.039 | P36: 3.5 | Q36: 2.269 | R36: 2.871 | S36: 3.54 | T36: 3.784
C37: Trade reveivables | G37: 18.235 | H37: 30.552 | I37: 30.552 | K37: 30.552 | L37: 36.528 | M37: 39.681 | N37: 46.318 | O37: 62.986 | P37: 105.817 | Q37: 111.5 | R37: 127.669 | S37: 139.029 | T37: 145.529
C38: Contract assets | G38: 19.999 | H38: 8.88 | I38: 8.88 | K38: 8.88 | L38: 1.549 | M38: 18.296 | N38: 30.564 | O38: 37.609 | P38: 24 | Q38: 154.3 | R38: 29.376 | S38: 81.923 | T38: 39.891
C39: Prepayments | G39: 1.699 | H39: 9.562 | I39: 9.562 | K39: 9.562 | L39: 15.389 | M39: 21.555 | N39: 15.627 | O39: 16.643 | P39: 13.345 | Q39: 30.8 | R39: 17.4 | S39: 13.523 | T39: 13.97
C40: Current derivate assets | G40: 0 | K40: 0 | O40: 11.875 | P40: 1 | Q40: 0.721 | R40: 0.437 | S40: 0.263 | T40: 1.158
C41: Current income tax reveivables | G41: 0.012 | H41: 0.012 | I41: 0 | K41: 0.012 | L41: 0.012 | M41: 2.278 | N41: 0 | O41: 0 | P41: 1 | Q41: 0 | R41: 0 | S41: 0 | T41: 53.55
C42: Cash | G42: 19.012 | H42: 96.608 | I42: 96.6 | K42: 96.608 | L42: 209.13 | M42: 93.05 | N42: 91.854 | O42: 58.464 | P42: 94.1 | Q42: 53 | R42: 217.757 | S42: 151.679 | T42: 221.295
C43: Total assets | D43: =SUM(D31:D42) -> 0 | E43: =SUM(E31:E42) -> 0 | F43: =SUM(F31:F42) -> 0 | G43: =SUM(G31:G42) -> 670.03 | H43: =SUM(H31:H42) -> 1252.56 | I43: =SUM(I31:I42) -> 1252.54 | J43: =SUM(J31:J42) -> 0 | K43: =SUM(K31:K42) -> 1252.56 | ... T43: =SUM(T31:T42) -> 3535.024
C44: Share capital | G44: 26.575 | H44: 41.839 | I44: 41.839 | K44: 41.839 | L44: 47.14 | M44: 47.144 | N44: 47.144 | O44: 47.144 | P44: 47.144 | Q44: 47.144 | R44: 47 | S44: 47.144 | T44: 51.841
C45: Share premium | G45: 509.542 | H45: 952.858 | I45: 952.858 | K45: 952.858 | L45: 1099.95 | M45: 1100.003 | N45: 1099.495 | O45: 1099.495 | P45: 1099.495 | Q45: 1099.495 | R45: 1099.495 | S45: 1099.495 | T45: 1265.2131
C46: Treasury shares | G46: 0 | K46: 0 | N46: -1.283 | O46: -1.283 | P46: -1.2 | Q46: -3 | R46: -3 | S46: -2.999 | T46: -3
C47: Reserves | G47: 1.343 | H47: -28.283 | I47: -28.283 | K47: -28.283 | L47: -4.061 | M47: 10.697 | N47: -34.57 | O47: 29.18 | P47: 18.4 | Q47: -0.906 | R47: 9 | S47: 18.423 | T47: 32.542
C48: Retained earnings | G48: 3.108 | H48: -7.373 | I48: -7.373 | K48: -7.373 | L48: -27.894 | M48: -6.529 | N48: 21.614 | O48: 59.358 | P48: 61.775 | Q48: 228.193 | R48: 293.318 | S48: 341.613 | T48: 335.227
C49: Total Equity | D49: =SUM(D44:D48) -> 0 | E49: =SUM(E44:E48) -> 0 | F49: =SUM(F44:F48) -> 0 | G49: =SUM(G44:G48) -> 540.568 | H49: =SUM(H44:H48) -> 959.041 | I49: =SUM(I44:I48) -> 959.041 | J49: =SUM(J44:J48) -> 0 | K49: =SUM(K44:K48) -> 959.041 | ... T49: =SUM(T44:T48) -> 1681.8231
C50: Provisons | G50: 0 | H50: 4.813 | I50: 4.813 | K50: 4.813 | L50: 4.813 | M50: 0 | N50: 0 | O50: 0 | P50: 0 | Q50: 0 | R50: 0 | S50: 0 | T50: 0
C51: Lese liabilities | G51: 0 | H51: 0.392 | I51: 0.392 | K51: 0.392 | L51: 9.858 | M51: 9.859 | N51: 9.609 | O51: 9.697 | P51: 10 | Q51: 10 | R51: 11.542 | S51: 12.482 | T51: 11.175
C52: Deferred tax liabilities | G52: 0 | H52: 10.191 | I52: 10.191 | K52: 10.191 | L52: 10.417 | M52: 11.236 | N52: 10.788 | O52: 11.972 | P52: 11.5 | Q52: 11.972 | R52: 13.77 | S52: 13.256 | T52: 12.886
C53: Deferred charter hire income | G53: 1.326 | H53: 1.778 | I53: 1.778 | K53: 1.778 | L53: 6.327 | M53: 1.734 | N53: 7.465 | O53: 1.747 | P53: 4 | Q53: 8.337 | R53: 19 | S53: 30.901 | T53: 43.918
C54: Debt to credit institutions | G54: 114.23 | H54: 204.773 | I54: 204.773 | K54: 204.773 | L54: 254.591 | M54: 335.028 | N54: 546.753 | O54: 539.854 | P54: 995.471 | Q54: 993.6 | R54: 1180.823 | S54: 1494.623 | T54: 1457.034
C55: Derivative liabilties | G55: 2.108 | H55: 17.957 | I55: 17.957 | K55: 17.957 | L55: 8.317 | M55: 3.609 | N55: 18.595 | O55: 16.205 | P55: 14 | Q55: 16.663 | R55: 13.611 | S55: 10.654 | T55: 2.608
C56: Trade an other payables | G56: 8.822 | H56: 32.636 | I56: 32.636 | K56: 32.636 | L56: 49.115 | M56: 42.279 | N56: 37.745 | O56: 43.595 | P56: 36.251 | Q56: 52.237 | R56: 46.5 | S56: 98.208 | T56: 76.955
C57: Current provisions | G57: 0 | H57: 2.086 | I57: 2 | K57: 2.086 | L57: 2.086 | M57: 4.994 | N57: 4.799 | O57: 0.841 | P57: 0.841 | Q57: 0.841 | R57: 0 | S57: 0 | T57: 0.127
C58: Payabales to related parties | G58: 0.089 | H58: 0.162 | I58: 0.162 | K58: 0.162 | L58: 0.155 | M58: 0.079 | N58: 0.15 | O58: 0.223 | P58: 0.335 | Q58: 0.2 | R58: 0.2 | S58: 0.272 | T58: 0
C59: Current deferred charter hire income | G59: 1.831 | H59: 12.103 | I59: 12.103 | K59: 12.103 | L59: 16.821 | M59: 23.186 | N59: 22.76 | O59: 45.59 | P59: 98.442 | Q59: 79.984 | R59: 72.947 | S59: 128.716 | T59: 117.871
C60: Current lease liabilties | G60: 0.279 | H60: 0.601 | I60: 0.601 | K60: 0.601 | L60: 1.418 | M60: 1.262 | N60: 1.155 | O60: 1.274 | P60: 0.835 | Q60: 1.7 | R60: 1.2 | S60: 1.057 | T60: 1.901
C61: Current income tax liabilites | G61: 0.005 | H61: 1.224 | I61: 1.224 | K61: 1.224 | L61: 1.266 | M61: 0.483 | N61: 0.369 | O61: 0.752 | P61: 2.3 | Q61: 3.8 | R61: 3.3 | S61: 3.638 | T61: 41.52
... C63: Current derivative liabilites | G63: 0 | H63: 4.004 | I63: 4.04 | K63: 4.004 | L63: 0.691 | M63: 0.12 | N63: 2.415 | O63: 0.209 | P63: 0.17 | Q63: 14.2 | R63: 7.599 | S63: 3.062 | T63: 0.596
C64: Total debt | D64: =SUM(D51:D63) -> 0 | E64: =SUM(E51:E63) -> 0 | F64: =SUM(F51:F63) -> 0 | G64: =SUM(G51:G63) -> 129.462 | H64: =SUM(H51:H63) -> 288.706 | I64: =SUM(I51:I63) -> 288.656 | J64: =SUM(J51:J63) -> 0 | K64: =SUM(K51:K63) -> 288.706 | L64: =SUM(L51:L63) -> 364.343 | M64: =SUM(M51:M62) -> 438.093 | N64: =SUM(N51:N63) -> 695.171 | O64: =SUM(O51:O63) -> 703.122 | P64: =SUM(P51:P63) -> 1237.881 | Q64: =SUM(Q51:Q63) -> 1398.319 | R64: =SUM(R51:R63) -> 1609.908 | S64: =SUM(S50:S63) -> 1913 | T64: =SUM(T50:T63) -> 1891.084
C65: Total E/D | D65: =D49+D64 -> 0 | E65: =E49+E64 -> 0 | F65: =F49+F64 -> 0 | G65: =G49+G64 -> 670.03 | H65: =H49+H64 -> 1247.747 | I65: =I49+I64 -> 1247.697 | J65: =J49+J64 -> 0 | K65: =K49+K64 -> 1247.747 | ... T65: =T49+T64 -> 3572.9071
C67: Cash flow EURm
C68: Model NI | D68: =D15 -> 0 | E68: =E15 -> 0 | F68: =F15 -> 0 | G68: =G15 -> 0 | H68: =H15 -> 2.639 | I68: =I15 -> 26.95 | J68: =J15 -> 0.61 | K68: =K15 -> 0 | ... T68: =T15 -> -6.909 | Y68: =Y15 -> 7.451 | Z68: =Z15 -> 35.541 | AA68: =AA15 -> 11.498 | AB68: =AB15 -> 67.731 | AC68: =AC15 -> 279
C69: Reported NI | H69: 2 | I69: 27.589 | J69: 0.61 | K69: -19.199 | L69: -21 | M69: 21.153 | N69: 27.663 | O69: 37.184 | P69: 2 | Q69: 166 | R69: 64.348 | S69: 47.836 | Y69: 7.4 | Z69: 36 | AA69: 11 | AB69: =65 -> 65 | AC69: 280
C70: D/A | H70: 5.9 | I70: 6.163 | J70: 3.067 | K70: 16.57 | L70: 10 | M70: 13.079 | N70: 9.913 | O70: 26.008 | P70: 18.824 | Q70: =49.961-P70 -> 31.137 | R70: 24.634 | S70: 50.15 | Y70: 16.4 | Z70: 23.9 | AA70: 31.7 | AB70: 59 | AC70: 125
C71: Interest expense/income | H71: 0.121 | I71: 0.288 | J71: 0.332 | K71: -0.741 | L71: 2.3 | M71: 2.206 | N71: -0.908 | O71: -0.398 | P71: =-0.266+0.107+0.705 -> 0.546 | Q71: 0 | R71: 0.02 | S71: 0 | Y71: 4.5 | Z71: 0 | AA71: 0 | AB71: 3.2 | AC71: 1
C72: Fair value of derivatives instruments | H72: 0.02 | I72: -0.02 | J72: -0.421 | K72: 0.421 | L72: -0.4 | M72: -0.003 | N72: 0 | O72: 0.403 | P72: 0.196 | Q72: 0 | R72: -0.682 | S72: 0 | Y72: 0 | Z72: 0 | AA72: 0 | AB72: 0 | AC72: 0
C73: Share-based comp | H73: 0.078 | I73: 0.229 | J73: 0.652 | K73: -0.959 | L73: 0.272 | M73: 0.419 | N73: 0.48 | O73: -1.171 | P73: 0.619 | Q73: 0 | R73: 0.993 | S73: 0 | Y73: -0.321 | Z73: 0 | AA73: 0 | AB73: 0 | AC73: 2
C74: WC | H74: -3.38 | I74: -20.608 | J74: 30.228 | K74: 13.86 | L74: 21.6 | M74: -32.271 | N74: -9.592 | O74: -12.25 | P74: -4.444 | Q74: -140 | R74: 118.752 | S74: 9.101 | Y74: =1.9 -> 1.9 | Z74: -30.4 | AA74: 20.1 | AB74: -32.513 | AC74: -17
C75: Income tax | H75: 0 | I75: 0 | J75: 0 | K75: 0.002 | L75: 0.015 | M75: -0.07 | N75: -0.086 | O75: -1.559 | P75: 1.6 | Q75: -4 | R75: 4.977 | S75: 1.593 | Y75: 0.158 | Z75: -0.013 | AA75: 0.002 | AB75: -1.7 | AC75: 4
C76: CFFO | D76: =SUM(D69:D75) -> 0 | E76: =SUM(E69:E75) -> 0 | F76: =SUM(F69:F75) -> 0 | G76: =SUM(G69:G75) -> 0 | H76: =SUM(H69:H75) -> 4.739 | I76: =SUM(I69:I75) -> 13.641 | J76: =SUM(J69:J75) -> 34.468 | K76: =SUM(K69:K75) -> 9.954 | ... T76: =SUM(T69:T75) -> 0 | Y76: =SUM(Y69:Y75) -> 30.037 | Z76: =SUM(Z69:Z75) -> 29.487 | AA76: =SUM(AA69:AA75) -> 62.802 | AB76: =SUM(AB69:AB75) -> 92.987 | AC76: =SUM(AC69:AC75) -> 395
C78: Capex | H78: -7.9 | I78: -7.634 | J78: -7.82 | K78: -43.545 | L78: -101.867 | M78: -194.112 | N78: -253.045 | O78: -66.518 | P78: -466.217 | Q78: =-672.217-P78 -> -206 | R78: -258.039 | S78: -332.402 | Y78: -162.941 | Z78: -224.606 | AA78: -66.899 | AB78: -615.542 | AC78: -1263 | AD78: -300 | AE78: -250
C79: Purchase of intangibles | H79: -0.039 | I79: -0.001 | J79: 0.009 | K79: 12.203 | L79: 0 | M79: -0.008 | N79: -0.061 | O79: -0.135 | P79: =-0.492-0.077 -> -0.569 | Q79: 0 | R79: -0.662 | S79: -0.275 | Y79: -0.434 | Z79: =-0.228-0.574 -> -0.802 | AA79: =10.403+1.8-0.031 -> 12.172 | AB79: =-0.41+0.206 -> -0.204 | AC79: 2
C80: CFFI | D80: =SUM(D78:D79) -> 0 | E80: =SUM(E78:E79) -> 0 | F80: =SUM(F78:F79) -> 0 | G80: =SUM(G78:G79) -> 0 | H80: =SUM(H78:H79) -> -7.939 | I80: =SUM(I78:I79) -> -7.635 | J80: =SUM(J78:J79) -> -7.811 | K80: =SUM(K78:K79) -> -31.342 | ... T80: =SUM(T78:T79) -> 0 | Y80: =SUM(Y78:Y79) -> -163.375 | Z80: =SUM(Z78:Z79) -> -225.408 | AA80: =SUM(AA78:AA79) -> -54.727 | AB80: =SUM(AB78:AB79) -> -615.746 | AC80: =SUM(AC78:AC79) -> -1261
C82: Principal repayment of lease | H82: -0.103 | I82: -0.096 | J82: -0.06 | K82: -0.301 | L82: -0.344 | M82: -0.532 | N82: -0.454 | O82: -0.57 | P82: -0.79 | Q82: 0 | R82: -0.927 | S82: -0.356 | Y82: -0.285 | Z82: -0.228 | AA82: -0.56 | AB82: -1.9 | AC82: -2
C83: Interest paid | H83: -1.38 | I83: -1.187 | J83: -3.105 | K83: -1.428 | L83: -1.34 | M83: -4.145 | N83: -7.726 | O83: -6.478 | P83: -3.7 | Q83: -17 | R83: -13.045 | S83: -24.701 | Y83: -3.9 | Z83: -4.2 | AA83: -7.1 | AB83: -19.689 | AC83: -58
C84: Proceeds from issue of share cap | H84: 0 | I84: 0 | J84: 0 | K84: 0 | L84: 154.868 | M84: 0.088 | N84: 0 | O84: -0.002 | P84: 0 | R84: 0 | S84: 0 | Y84: 79.218 | Z84: 183.25 | AA84: 0 | AB84: 154.954 | AC84: 0
C85: Transaction costs on issues of shares | H85: 0 | I85: 0 | J85: -3.135 | K85: -3.765 | L85: -2.4 | M85: -0.106 | N85: -1.791 | O85: 1.297 | P85: 0 | Q85: -2 | R85: 0.284 | S85: 0 | Y85: -2.1 | Z85: -5.1 | AA85: -6.9 | AB85: -3 | AC85: -2
C86: Proceeds from borrowing | H86: 0 | I86: 0 | J86: 0 | K86: 84.935 | L86: 50 | M86: 78.286 | N86: 241.169 | O86: -17.58 | P86: =-0.705+494.749-7.5 -> 486.544 | Q86: =644-P86 -> 157.456 | R86: 238.589 | S86: 426.617 | Y86: =8.9-10 -> -1.1 | Z86: =113.459+16-65-25 -> 39.459 | AA86: =199.935-115 -> 84.935 | AB86: =-1.2-2.3+365.975-10.6 -> 351.875 | AC86: 1309
C87: Repayment of loan | I87: 0 | J87: 0 | K87: 0 | L87: 0 | M87: 0 | N87: -3.125 | O87: 0 | P87: 0 | Q87: -23 | R87: -17.152 | S87: -239.129 | AC87: -279
C88: CFFF | D88: =SUM(D82:D86) -> 0 | E88: =SUM(E82:E86) -> 0 | F88: =SUM(F82:F86) -> 0 | G88: =SUM(G82:G86) -> 0 | H88: =SUM(H82:H86) -> -1.483 | I88: =SUM(I82:I87) -> -1.283 | J88: =SUM(J82:J87) -> -6.3 | K88: =SUM(K82:K87) -> 79.441 | L88: =SUM(L82:L87) -> 200.784 | M88: =SUM(M82:M87) -> 73.591 | N88: =SUM(N82:N87) -> 228.073 | O88: =SUM(O82:O87) -> -23.333 | P88: =SUM(P82:P87) -> 482.054 | ... T88: =SUM(T82:T87) -> 0 | Y88: =SUM(Y82:Y86) -> 71.833 | Z88: =SUM(Z82:Z86) -> 213.181 | AA88: =SUM(AA82:AA86) -> 70.375 | AB88: =SUM(AB82:AB86) -> 482.24 | AC88: =SUM(AC82:AC87) -> 968
C90: FX | H90: 0 | K90: -1.3 | L90: 0.561 | M90: 0.193 | N90: -3.634 | O90: 4.88 | P90: 0 | Q90: 0 | S90: 2.7 | Z90: 0 | AA90: -1.3 | AB90: 2 | AC90: 3
C92: CIC | D92: =D76+D80+D88+D90 -> 0 | E92: =E76+E80+E88+E90 -> 0 | F92: =F76+F80+F88+F90 -> 0 | G92: =G76+G80+G88+G90 -> 0 | H92: =H76+H80+H88+H90 -> -4.683 | I92: =I76+I80+I88+I90 -> 4.723 | J92: =J76+J80+J88+J90 -> 20.357 | K92: =K76+K80+K88+K90 -> 56.753 | ... T92: =T76+T80+T88+T90 -> 0 | Y92: =Y76+Y80+Y88+Y90 -> -61.505 | Z92: =Z76+Z80+Z88+Z90 -> 17.26 | AA92: =AA76+AA80+AA88+AA90 -> 77.15 | AB92: =AB76+AB80+AB88+AB90 -> -38.519 | AC92: =AC76+AC80+AC88+AC90 -> 105
C94: FCF | D94: =D76+D78 -> 0 | E94: =E76+E78 -> 0 | F94: =F76+F78 -> 0 | G94: =G76+G78 -> 0 | H94: =H76+H78 -> -3.161 | I94: =I76+I78 -> 6.007 | J94: =J76+J78 -> 26.648 | K94: =K76+K78 -> -33.591 | ... T94: =T76+T78 -> 0 | Y94: =Y76+Y78 -> -132.904 | Z94: =Z76+Z78 -> -195.119 | AA94: =AA76+AA78 -> -4.097 | AB94: =AB76+AB78 -> -522.555 | AC94: =AC76+AC78 -> -868

Sheet Nøkkeltall
F7: 2026 | G7: 2027 | H7: 2028
E8: EV/EBITDA | F8: =Modell!$B$9/(Modell!AD8*Modell!$B$12) -> 8.8102679 | G8: =Modell!$B$9/(Modell!AE8*Modell!$B$12) -> 6.0288906 | H8: =Modell!$B$9/(Modell!AF8*Modell!$B$12) -> 5.7324153
E9: EV/EBIT | F9: =Modell!$B$9/(Modell!AD10*Modell!$B$12) -> 11.65229 | G9: =Modell!$B$9/(Modell!AE10*Modell!$B$12) -> 7.309946 | H9: =Modell!$B$9/(Modell!AF10*Modell!$B$12) -> 6.9480605
E10: P/E | F10: =Modell!$B$4/Modell!AD17 -> 8.530219 | G10: =Modell!$B$4/Modell!AE17 -> 6.3572631 | H10: =Modell!$B$4/Modell!AF17 -> 6.0163081

Sheet SOTP
B4: New building parity
B6: Vessel name | C6: Ownership | D6: Type | E6: Built | F6: Equivalent newbuild delivery | G6: Equivalent newbuild cost (EURm) | H6: NPV of equivalent newbuld capex (EURm) | I6: NPV of cashflow advantage (EURm) | J6: Total value
B7: Wind Zaratan | C7: 1 | D7: Z-class | E7: 2012 | F7: Q128 | G7: 166 | H7: 54 | I7: 56 | J7: =SUM(H7:I7) -> 110
B8: Wind Scylla | C8: 1 | D8: S-class | E8: 2015 | F8: Q428 | G8: 258 | H8: 111 | I8: 145 | J8: =SUM(H8:I8) -> 256
B9: Wind Orca | C9: 1 | D9: O-class | E9: 2013 | F9: Q428 | G9: 313 | H9: 168 | I9: 158 | J9: =SUM(H9:I9) -> 326
B10: Wind Osprey | C10: 1 | D10: O-class | E10: 2012 | F10: Q428 | G10: 313 | H10: 157 | I10: 135 | J10: =SUM(H10:I10) -> 292
B11: Wind Keeper | C11: 1 | D11: K-class | J11: 250
B12: Wind Maker | C12: 1 | D12: M-class | E12: 2025 | F12: Q129 | G12: 391 | H12: 293 | I12: 161 | J12: =SUM(H12:I12) -> 454
B13: Wind Mover | C13: 1 | D13: M-class | E13: 2025 | F13: Q129 | G13: 391 | H13: 293 | I13: 141 | J13: =SUM(H13:I13) -> 434
B14: Wind Peak | C14: 1 | D14: P-class | E14: 2024 | F14: Q129 | G14: 391 | H14: 279 | I14: 171 | J14: =SUM(H14:I14) -> 450
B15: Wind Pace | C15: 1 | D15: P-class | E15: 2025 | F15: Q129 | G15: 391 | H15: 293 | I15: 164 | J15: =SUM(H15:I15) -> 457
B16: Wind Ally | C16: 1 | D16: A-class | E16: 2025 | F16: Q129 | G16: 391 | H16: 293 | I16: 116 | J16: =SUM(H16:I16) -> 409
B17: Wind Ace | C17: 1 | D17: A-class | E17: 2026 | F17: Q129 | G17: 391 | H17: 307 | I17: 88 | J17: =SUM(H17:I17) -> 395
B18: Wind Apex | C18: 1 | D18: A-class | E18: 2027 | F18: Q129 | G18: 391 | H18: 321 | I18: 53 | J18: =SUM(H18:I18) -> 374
B19: Asset value | J19: =SUM(J7:J18) -> 4207
B20: Foundation T&I services | D20: (5,0x EV/EBITDA) | J20: 405
B21: EV | J21: =SUM(J19:J20) -> 4612
B22: Net debt (Q325) | J22: 1202.464
B23: NPV of remaning Capex (Q325) | J23: 1200
B24: Equity value | J24: =J21-J22-J23 -> 2209.536
B25: EUR/NOK | J25: 11.77
B26: # shares | J26: 350.95758
B27: Equity value/share | J27: =(J24*J25)/J26 -> 74.100803
B29: SOTP
B31: Vessel name | C31: Dayrate (EUR 000) | D31: Util. | E31: Opex/d (EUR 000) | F31: EBITDA (EURm) | G31: Multiple | H31: EV (EURm)
B32: Wind Zaratan | C32: 250 | D32: 0.75 | E32: 40 | F32: 54 | G32: 5x | H32: =F32*5 -> 270
B33: Wind Scylla | C33: 250 | D33: 0.75 | E33: 40 | F33: 54 | G33: 5x | H33: =F33*5 -> 270
B34: Wind Orca | C34: 300 | D34: 0.75 | E34: 40 | F34: 68 | G34: 5x | H34: =F34*5 -> 340
B35: Wind Osprey | C35: 300 | D35: 0.75 | E35: 40 | F35: 68 | G35: 5x | H35: =F35*5 -> 340
B36: Wind Keeper | C36: 250 | D36: 0.75 | E36: 40 | F36: 54 | G36: 5x | H36: =F36*5 -> 270
B37: Wind Maker | C37: 300 | D37: 0.75 | E37: 40 | F37: 68 | G37: 5x | H37: =F37*5 -> 340
B38: Wind Mover | C38: 300 | D38: 0.75 | E38: 40 | F38: 68 | G38: 5x | H38: =F38*5 -> 340
B39: Wind Peak | C39: 300 | D39: 0.75 | E39: 40 | F39: 68 | G39: 5x | H39: =F39*5 -> 340
B40: Wind Pace | C40: 300 | D40: 0.75 | E40: 40 | F40: 68 | G40: 5x | H40: =F40*5 -> 340
B41: Wind Ally | C41: 350 | D41: 0.75 | E41: 40 | F41: 81 | G41: 5x | H41: =F41*5 -> 405
B42: Wind Ace | C42: 350 | D42: 0.75 | E42: 40 | F42: 81 | G42: 5x | H42: =F42*5 -> 405
B43: Wind Apex | C43: 350 | D43: 0.75 | E43: 40 | F43: 81 | G43: 5x | H43: =F43*5 -> 405
B45: T&I services EBITDA | F45: 115 | G45: 5x | H45: =115*5 -> 575
B46: SG&A | F46: -70 | G46: 5x | H46: -350
B48: EV | H48: =SUM(H32:H46) -> 4290
B49: NIBD Q325 | H49: 1202
B50: Remaining capex | H50: 1200
B51: Equity value | H51: =H48-H49-H50 -> 1888
B52: EUR/NOK | H52: 11.77
B53: # of shares | H53: 350.95758
B54: Equity value/Share | H54: =(H51*H52)/H53 -> 63.317509

Sheet Nedsidebergning
