Workbook

Sheet Info
A4: Avvikende regnskapsår:
A5: Q1: 1. sep - 30. nov
A6: Q2: 1. des - 28. feb
A7: Q3: 1. mar - 31. mai
A8: Q4: 1. jun - 30. aug
A11: Press releases:
A12: 27.05.25: Dustins emisjon er fulltegnet
A13: 02.04.25: Dustin henter 1250 SEKM for å styrke balansen og øke hastigheten mot profit igjen. Pengene ble hentet på 1,40kr
A14: 04.11.24: Styreleder Thomas Ekman stiller ikke videre som styreleder grunnet hans avgang som CEO hos Axel Johnson
A15: 11.10.23: Dustin henter 1750 SEKm for å redusere gjeld. Kurs 5,20
A16: 30.06.23: Axel Johnson kjøper seg opp til 30% og legger inn bud på 28,50kr

Sheet Modell
A3: Kapitalstruktur | C3: SEK million | D3: Q1 21/22 | E3: Q2 21/22 | F3: Q3 21/22 | G3: Q4 21/22 | H3: Q1 22/23 | I3: Q2 22/23 | J3: Q3 22/23 | K3: Q4 22/23 | L3: Q1 23/24 | M3: Q2 23/24 | N3: Q3 23/24 | O3: Q4 23/24 | P3: Q1 24/25 | Q3: Q2 24/25 | R3: Q3 24/25 | S3: Q4 24/25 | T3: Q1 25/26 | U3: Q2 25/26 | V3: Q3 25/26 | W3: Q4 25/26 | AA3: FY 16/17 | AB3: FY 17/18 | AC3: FY 18/19 | AD3: FY 19/20 | AE3: FY 20/21 | AF3: FY 21/22 | AG3: FY 22/23 | AH3: FY 23/24 | AI3: FY 24/25 | AJ3: FY 25/26 | AK3: FY 26/27 | AL3: FY 27/28 | AM3: FY 28/29 | AN3: FY 29/30 | AO3: FY 30/31 | AP3: FY31/32 | AQ3: FY 32/33 | AR3: FY 33/34 | AS3: FY 34/35
A4: Price | B4: 1.68 | C4: Revenue | D4: 5826.1 | E4: 6137.2 | F4: 5894.2 | G4: 5743.4 | H4: 6635.9 | I4: 6271.6 | J4: 5582 | K4: 5582 | L4: 5793 | M4: 5246 | N4: 5455 | O4: 4987.5 | P4: 4782 | Q4: 5480 | R4: 5089 | S4: 5056 | T4: 5487 | U4: 5481 | AA4: 9306.2 | AB4: 10300.5 | AC4: 12535.7 | AD4: 13195.4 | AE4: 15028 | AF4: 23600.9 | AG4: 23577 | AH4: 21481.8 | AI4: 20407 | AJ4: =AI4*1.075 -> 21937.525 | AK4: =AJ4*1.075 -> 23582.839 | AL4: =AK4*1.05 -> 24761.981 | AM4: =AL4*1.05 -> 26000.08 | AN4: =AM4*1.05 -> 27300.084 | AO4: =AN4*1.05 -> 28665.089 | AP4: =AO4*1.05 -> 30098.343 | AQ4: =AP4*1.05 -> 31603.26 | AR4: =AQ4*1.05 -> 33183.423 | AS4: =AR4*1.05 -> 34842.594
A5: S/O | B5: 1351.8302 | C5: COGS | D5: -4931.7 | E5: -5233.7 | F5: -5052 | G5: -4925.4 | H5: -5743.2 | I5: -5357 | J5: -4725.1 | K5: -4725.1 | L5: -4905 | M5: -4390 | N5: -4634 | O5: -4343.6 | P5: -4099 | Q5: -4718 | R5: -4409 | S5: -4414 | T5: -4766 | U5: -4757 | AA5: -7926.7 | AB5: -8663.7 | AC5: -10446.3 | AD5: -11152 | AE5: -12545 | AF5: -20143.3 | AG5: -20168.8 | AH5: -18273.2 | AI5: -17640 | AJ5: =AJ4*-0.86 -> -18866.271 | AK5: =AK4*-0.86 -> -20281.242 | AL5: =AL4*-0.86 -> -21295.304 | AM5: =AM4*-0.86 -> -22360.069 | AN5: =AN4*-0.86 -> -23478.073 | AO5: =AO4*-0.86 -> -24651.976 | AP5: =AP4*-0.86 -> -25884.575 | AQ5: =AQ4*-0.86 -> -27178.804 | ... AS5: =AS4*-0.86 -> -29964.631
A6: MC SEKm | B6: =B4*B5 -> 2271.0748 | C6: Gross profit | D6: =SUM(D4:D5) -> 894.4 | E6: =SUM(E4:E5) -> 903.5 | F6: =SUM(F4:F5) -> 842.2 | G6: =SUM(G4:G5) -> 818 | H6: =SUM(H4:H5) -> 892.7 | I6: =SUM(I4:I5) -> 914.6 | J6: =SUM(J4:J5) -> 856.9 | K6: =SUM(K4:K5) -> 856.9 | ... W6: =SUM(W4:W5) -> 0 | AA6: =SUM(AA4:AA5) -> 1379.5 | AB6: =SUM(AB4:AB5) -> 1636.8 | AC6: =SUM(AC4:AC5) -> 2089.4 | AD6: =SUM(AD4:AD5) -> 2043.4 | AE6: =SUM(AE4:AE5) -> 2483 | AF6: =SUM(AF4:AF5) -> 3457.6 | AG6: =SUM(AG4:AG5) -> 3408.2 | AH6: =SUM(AH4:AH5) -> 3208.6 | ... AS6: =SUM(AS4:AS5) -> 4877.9632
A7: Cash SEKm | B7: =T45 -> 970 | C7: Selling and admin expense | D7: -631.5 | E7: -664.7 | F7: -678.4 | G7: -653.8 | H7: -737.6 | I7: -745.5 | J7: -726.8 | K7: -726.8 | L7: -737 | M7: -696 | N7: -725 | O7: -654.6 | P7: -718 | Q7: -704 | R7: -659 | S7: -602 | T7: -672 | U7: -655 | AA7: -1016.3 | AB7: -1183.3 | AC7: -1594.3 | AD7: -1617.9 | AE7: -1825.2 | AF7: -2628.3 | AG7: -2865.3 | AH7: -2813.4 | AI7: -2683 | AJ7: =AI7*1.03 -> -2763.49 | AK7: =AJ7*1.03 -> -2846.3947 | AL7: =AK7*1.02 -> -2903.3226 | AM7: =AL7*1.05 -> -3048.4887 | AN7: =AM7*1.05 -> -3200.9132 | AO7: =AN7*1.05 -> -3360.9588 | AP7: =AO7*1.05 -> -3529.0068 | AQ7: =AP7*1.05 -> -3705.4571 | AR7: =AQ7*1.05 -> -3890.73 | AS7: =AR7*1.05 -> -4085.2664
A8: Debt SEKm | B8: =T49+T52 -> 2523 | C8: Items affecting comparability | D8: -7.2 | E8: -12.8 | F8: -18.7 | G8: -11.5 | H8: -18.9 | I8: -9.1 | J8: -25.3 | K8: -25.3 | L8: -17 | M8: -16 | N8: 0 | O8: -6.7 | P8: -10 | Q8: -55 | R8: -9 | S8: -12 | T8: -37 | U8: -26 | AA8: -7.3 | AB8: 1 | AC8: 3.5 | AD8: -31 | AE8: -73.4 | AF8: -50.1 | AG8: -73.2 | AH8: -39.7 | AI8: -86 | AJ8: =AI8*1.06 -> -91.16 | AK8: =AJ8*1.075 -> -97.997 | AL8: =AK8*1.05 -> -102.89685 | AM8: =AL8*1.05 -> -108.04169 | AN8: =AM8*1.05 -> -113.44378 | AO8: =AN8*1.05 -> -119.11597 | AP8: =AO8*1.05 -> -125.07176 | AQ8: =AP8*1.05 -> -131.32535 | AR8: =AQ8*1.05 -> -137.89162 | AS8: =AR8*1.05 -> -144.7862
A9: EV SEKm | B9: =B6-B7+B8 -> 3824.0748 | C9: Other operating income | D9: 3.1 | E9: 5.1 | F9: 6.5 | G9: 5.9 | H9: 14.9 | I9: 9.8 | J9: 6.6 | K9: 6.6 | L9: 5 | M9: 6 | N9: 5 | O9: 3 | P9: 5 | Q9: 6 | R9: 11 | S9: 5 | T9: 3 | U9: 7 | AA9: 5.9 | AB9: 6.8 | AC9: 7.6 | AD9: 14.5 | AE9: 14.1 | AF9: 20.5 | AG9: 46.5 | AH9: 18.7 | AI9: 27 | AJ9: =AI9*1.06 -> 28.62 | AK9: =AJ9*1.075 -> 30.7665 | AL9: =AK9*1.05 -> 32.304825 | AM9: =AL9*1.05 -> 33.920066 | AN9: =AM9*1.05 -> 35.61607 | AO9: =AN9*1.05 -> 37.396873 | AP9: =AO9*1.05 -> 39.266717 | AQ9: =AP9*1.05 -> 41.230053 | AR9: =AQ9*1.05 -> 43.291555 | AS9: =AR9*1.05 -> 45.456133
C10: Other opex | D10: -7.7 | E10: -11 | F10: -11.3 | G10: -11.7 | H10: -13.7 | I10: -12.3 | J10: -14.4 | K10: -14.4 | L10: -9 | M10: -8 | N10: -14 | O10: -10.7 | P10: -12 | Q10: -12 | R10: -12 | S10: -12 | T10: -8 | U10: -7 | AA10: -12.3 | AB10: -17.5 | AC10: -17.1 | AD10: -21.8 | AE10: -22.2 | AF10: -41.7 | AG10: -50.1 | AH10: -41.7 | AI10: -48 | AJ10: =AI10*1.06 -> -50.88 | AK10: =AJ10*1.075 -> -54.696 | AL10: =AK10*1.05 -> -57.4308 | AM10: =AL10*1.05 -> -60.30234 | AN10: =AM10*1.05 -> -63.317457 | AO10: =AN10*1.05 -> -66.48333 | AP10: =AO10*1.05 -> -69.807496 | AQ10: =AP10*1.05 -> -73.297871 | AR10: =AQ10*1.05 -> -76.962765 | AS10: =AR10*1.05 -> -80.810903
C11: Imapirment of acquisition-related assets | D11: 0 | E11: 0 | F11: 0 | G11: 0 | H11: 0 | I11: 0 | J11: 0 | K11: 0 | L11: 0 | M11: 0 | N11: 0 | O11: 0 | P11: 0 | Q11: -2500 | R11: 0 | S11: 0 | T11: 0 | U11: 0 | AA11: 0 | AB11: 0 | AC11: 0 | AD11: 0 | AE11: 0 | AF11: 0 | AG11: 0 | AH11: 0 | AI11: -2500 | AJ11: 0 | AK11: 0 | AL11: 0 | AM11: 0 | AN11: 0 | AO11: 0 | AP11: 0 | AQ11: 0 | AR11: 0 | AS11: 0
A12: P/B | B12: =B6/T47 -> 0.41564326 | C12: Operating profit (EBIT) | D12: =SUM(D6:D11) -> 251.1 | E12: =SUM(E6:E11) -> 220.1 | F12: =SUM(F6:F11) -> 140.3 | G12: =SUM(G6:G11) -> 146.9 | H12: =SUM(H6:H11) -> 137.4 | I12: =SUM(I6:I11) -> 157.5 | J12: =SUM(J6:J11) -> 97 | K12: =SUM(K6:K11) -> 97 | ... W12: =SUM(W6:W11) -> 0 | AA12: =SUM(AA6:AA11) -> 349.5 | AB12: =SUM(AB6:AB11) -> 443.8 | AC12: =SUM(AC6:AC11) -> 489.1 | AD12: =SUM(AD6:AD11) -> 387.2 | AE12: =SUM(AE6:AE11) -> 576.3 | AF12: =SUM(AF6:AF11) -> 758 | AG12: =SUM(AG6:AG11) -> 466.1 | AH12: =SUM(AH6:AH11) -> 332.5 | ... AS12: =SUM(AS6:AS11) -> 612.5558
C13: Financial income | D13: 0.3 | E13: 0.2 | F13: 0.3 | G13: 0.5 | H13: 0.4 | I13: 3.5 | J13: 0.6 | K13: 0.6 | L13: 1 | M13: 1 | N13: 1 | O13: 1 | P13: 1 | Q13: 17 | R13: 2 | S13: 3 | T13: 1 | U13: 12 | AA13: 1.2 | AB13: 1.1 | AC13: 0.8 | AD13: 1.3 | AE13: 1.2 | AF13: 1.2 | AG13: 9.3 | AH13: 3.5 | AI13: 23 | AJ13: 0 | AK13: 0 | AL13: 0 | AM13: 0 | AN13: 0 | AO13: 0 | AP13: 0 | AR13: 0 | AS13: 0
A14: Gearing | B14: =(B8-B7)/U28 -> 2.7341549 | C14: Financial expense | D14: -33 | E14: -33.7 | F14: -29.4 | G14: -33.7 | H14: -48.7 | I14: -53.3 | J14: -62.1 | K14: -62.1 | L14: -81 | M14: -49 | N14: -42 | O14: -47.2 | P14: -49 | Q14: -61 | R14: -57 | S14: -34 | T14: -46 | U14: -37 | AA14: -42.6 | AB14: -60.3 | AC14: -45 | AD14: -53.3 | AE14: -108.3 | AF14: -129.8 | AG14: -238.7 | AH14: -219.4 | AI14: -203 | AJ14: 0 | AK14: =AJ14*1.02 -> 0 | AL14: =AK14*1.02 -> 0 | AM14: =AL14*1.02 -> 0 | AN14: =AM14*1.02 -> 0 | AO14: =AN14*1.02 -> 0 | AP14: =AO14*1.02 -> 0 | AQ14: =AP14*1.02 -> 0 | AR14: =AQ14*1.02 -> 0 | AS14: =AR14*1.02 -> 0
C15: PTP | D15: =SUM(D12:D14) -> 218.4 | E15: =SUM(E12:E14) -> 186.6 | F15: =SUM(F12:F14) -> 111.2 | G15: =SUM(G12:G14) -> 113.7 | H15: =SUM(H12:H14) -> 89.1 | I15: =SUM(I12:I14) -> 107.7 | J15: =SUM(J12:J14) -> 35.5 | K15: =SUM(K12:K14) -> 35.5 | ... W15: =SUM(W12:W14) -> 0 | AA15: =SUM(AA12:AA14) -> 308.1 | AB15: =SUM(AB12:AB14) -> 384.6 | AC15: =SUM(AC12:AC14) -> 444.9 | AD15: =SUM(AD12:AD14) -> 335.2 | AE15: =SUM(AE12:AE14) -> 469.2 | AF15: =SUM(AF12:AF14) -> 629.4 | AG15: =SUM(AG12:AG14) -> 236.7 | AH15: =SUM(AH12:AH14) -> 116.6 | ... AS15: =SUM(AS12:AS14) -> 612.5558
C16: Tax | D16: -52.2 | E16: -42.5 | F16: -26.2 | G16: -30.8 | H16: -22.9 | I16: -25.9 | J16: -12 | K16: -12 | L16: -16 | M16: -18 | N16: -18 | O16: -11.8 | P16: 23 | Q16: 18 | R16: 17 | S16: 12 | T16: 12 | U16: -2 | AA16: -69 | AB16: -79.4 | AC16: -88.7 | AD16: -57.9 | AE16: -112.2 | AF16: -151.8 | AG16: -63.2 | AH16: -63.5 | AI16: 70 | AJ16: =AJ15*-0.206 -> -40.034761 | AK16: =AK15*-0.206 -> -68.65492 | AL16: =AL15*-0.206 -> -89.678386 | AM16: =AM15*-0.206 -> -94.162305 | AN16: =AN15*-0.206 -> -98.87042 | AO16: =AO15*-0.206 -> -103.81394 | AP16: =AP15*-0.206 -> -109.00464 | AQ16: =AQ15*-0.206 -> -114.45487 | ... AS16: =AS15*-0.206 -> -126.18649
C17: Net income | D17: =SUM(D15:D16) -> 166.2 | E17: =SUM(E15:E16) -> 144.1 | F17: =SUM(F15:F16) -> 85 | G17: =SUM(G15:G16) -> 82.9 | H17: =SUM(H15:H16) -> 66.2 | I17: =SUM(I15:I16) -> 81.8 | J17: =SUM(J15:J16) -> 23.5 | K17: =SUM(K15:K16) -> 23.5 | ... W17: =SUM(W15:W16) -> 0 | AA17: =SUM(AA15:AA16) -> 239.1 | AB17: =SUM(AB15:AB16) -> 305.2 | AC17: =SUM(AC15:AC16) -> 356.2 | AD17: =SUM(AD15:AD16) -> 277.3 | AE17: =SUM(AE15:AE16) -> 357 | AF17: =SUM(AF15:AF16) -> 477.6 | AG17: =SUM(AG15:AG16) -> 173.5 | AH17: =SUM(AH15:AH16) -> 53.1 | ... AS17: =SUM(AS15:AS16) -> 486.3693 | AT17: =AS17*(1+$AV$21) -> 481.50561 | AU17: =AT17*(1+$AV$21) -> 476.69055 | AV17: =AU17*(1+$AV$21) -> 471.92365 | AW17: =AV17*(1+$AV$21) -> 467.20441 | AX17: =AW17*(1+$AV$21) -> 462.53237 | AY17: =AX17*(1+$AV$21) -> 457.90704 | AZ17: =AY17*(1+$AV$21) -> 453.32797 | BA17: =AZ17*(1+$AV$21) -> 448.79469 | ... IZ17: =IY17*(1+$AV$21) -> 56.0445
C18: Shares | D18: 113.94378 | E18: 113.94378 | F18: 113.94378 | G18: 113.94378 | H18: 113.94378 | I18: 113.94378 | J18: 113.94378 | K18: 113.94378 | L18: 113.94378 | M18: 457.3001 | N18: 457.3001 | O18: 457.3001 | P18: 457.3001 | Q18: 457.3001 | R18: 1351.8302 | S18: 1351.8302 | T18: 1351.8302 | U18: 1352.8302 | V18: 1353.8302 | W18: 1354.8302 | AA18: 76.173115 | AB18: 77.226502 | AC18: 86.472611 | AD18: 88.647339 | AE18: 93.455077 | AF18: 113.11878 | AG18: 215.7416 | AH18: 386.50019 | AI18: 1351.8302 | AJ18: 1351.8302 | AK18: 1351.8302 | AL18: 1351.8302 | AM18: 1351.8302 | AN18: 1351.8302 | AO18: 1351.8302 | AP18: 1351.8302 | AQ18: 1351.8302 | AR18: 1351.8302 | AS18: 1351.8302
C19: EPS | D19: =D17/D18 -> 1.4586141 | E19: =E17/E18 -> 1.2646588 | F19: =F17/F18 -> 0.74598195 | G19: =G17/G18 -> 0.72755181 | H19: =H17/H18 -> 0.58098829 | I19: =I17/I18 -> 0.71789792 | J19: =J17/J18 -> 0.20624207 | K19: =K17/K18 -> 0.20624207 | ... W19: =W17/W18 -> 0 | AA19: =AA17/AA18 -> 3.1389027 | AB19: =AB17/AB18 -> 3.9520112 | AC19: =AC17/AC18 -> 4.1192234 | AD19: =AD17/AD18 -> 3.1281255 | AE19: =AE17/AE18 -> 3.8200172 | AF19: =AF17/AF18 -> 4.2221107 | AG19: =AG17/AG18 -> 0.8042028 | AH19: =AH17/AH18 -> 0.13738674 | ... AS19: =AS17/AS18 -> 0.35978579
AU20: Discount | AV20: 0.09
C21: Revenue y/y | H21: =(H4-D4)/D4 -> 0.13899521 | I21: =(I4-E4)/E4 -> 0.021899237 | J21: =(J4-F4)/F4 -> -0.052967324 | K21: =(K4-G4)/G4 -> -0.028101821 | L21: =(L4-H4)/H4 -> -0.1270212 | M21: =(M4-I4)/I4 -> -0.16353084 | N21: =(N4-J4)/J4 -> -0.022751702 | O21: =(O4-K4)/K4 -> -0.10650305 | ... W21: =(W4-S4)/S4 -> -1 | AB21: =(AB4-AA4)/AA4 -> 0.10684275 | AC21: =(AC4-AB4)/AB4 -> 0.21699917 | AD21: =(AD4-AC4)/AC4 -> 0.052625701 | AE21: =(AE4-AD4)/AD4 -> 0.13888173 | AF21: =(AF4-AE4)/AE4 -> 0.5704618 | AG21: =(AG4-AF4)/AF4 -> -0.0010126732 | AH21: =(AH4-AG4)/AG4 -> -0.088866268 | AI21: =(AI4-AH4)/AH4 -> -0.050033051 | ... AS21: =(AS4-AR4)/AR4 -> 0.05 | AU21: TV | AV21: -0.01
C22: Organisk vekst | D22: 0.082 | E22: 0.106 | F22: 0.197 | G22: 0.15 | H22: 0.085 | I22: -0.024 | J22: -0.094 | K22: -0.169 | L22: -0.162 | M22: -0.164 | N22: -0.035 | O22: 0.001 | P22: -0.162 | Q22: 0.037 | R22: -0.029 | S22: 0.036 | T22: 0.181 | U22: 0.044 | AU22: NPV | AV22: =NPV(AV20,AJ17:IZ17) -> 4278.4677
C23: Gross margin | D23: =D6/D4 -> 0.15351607 | E23: =E6/E4 -> 0.14721697 | F23: =F6/F4 -> 0.14288623 | G23: =G6/G4 -> 0.14242435 | H23: =H6/H4 -> 0.13452584 | I23: =I6/I4 -> 0.145832 | J23: =J6/J4 -> 0.15351129 | K23: =K6/K4 -> 0.15351129 | ... W23: =W6/W4 -> #DIV/0! | AA23: =AA6/AA4 -> 0.14823451 | AB23: =AB6/AB4 -> 0.15890491 | AC23: =AC6/AC4 -> 0.16667597 | AD23: =AD6/AD4 -> 0.154857 | AE23: =AE6/AE4 -> 0.16522491 | AF23: =AF6/AF4 -> 0.14650289 | AG23: =AG6/AG4 -> 0.14455614 | AH23: =AH6/AH4 -> 0.14936365 | ... AS23: =AS6/AS4 -> 0.14 | AU23: S/O | AV23: 1351.8302
C24: EBIT margin | D24: =D12/D4 -> 0.043099157 | E24: =E12/E4 -> 0.03586326 | F24: =F12/F4 -> 0.023803061 | G24: =G12/G4 -> 0.025577184 | H24: =H12/H4 -> 0.020705556 | I24: =I12/I4 -> 0.025113209 | J24: =J12/J4 -> 0.017377284 | K24: =K12/K4 -> 0.017377284 | ... W24: =W12/W4 -> #DIV/0! | AA24: =AA12/AA4 -> 0.037555608 | AB24: =AB12/AB4 -> 0.043085287 | AC24: =AC12/AC4 -> 0.039016569 | AD24: =AD12/AD4 -> 0.029343559 | AE24: =AE12/AE4 -> 0.038348416 | AF24: =AF12/AF4 -> 0.032117419 | AG24: =AG12/AG4 -> 0.019769267 | AH24: =AH12/AH4 -> 0.015478219 | ... AS24: =AS12/AS4 -> 0.01758066 | AU24: NPV/Share | AV24: =AV22/AV23 -> 3.1649446
C25: ROE | AA25: 0.161 | AB25: 0.185 | AC25: 0.145 | AD25: 0.145 | AE25: 0.076 | AF25: 0.094 | AG25: 0.032 | AH25: 0.008 | AI25: =AI17/S47 -> -0.47820559 | AU25: Opp/nedside | AV25: =(AV24-B4)/B4 -> 0.8838956
C27: EBITDA | D27: 358 | E27: 336 | F27: 260.7 | G27: 260 | H27: 259 | I27: 269 | J27: 228 | K27: 203 | L27: 256 | M27: 261 | N27: 191 | O27: 91 | P27: 84 | Q27: 173 | R27: 131 | S27: 140 | T27: 139 | U27: 158
C28: EBITDA LTM | G28: =SUM(D27:G27) -> 1214.7 | H28: =SUM(E27:H27) -> 1115.7 | I28: =SUM(F27:I27) -> 1048.7 | J28: =SUM(G27:J27) -> 1016 | K28: =SUM(H27:K27) -> 959 | L28: =SUM(I27:L27) -> 956 | M28: =SUM(J27:M27) -> 948 | N28: =SUM(K27:N27) -> 911 | ... W28: =SUM(T27:W27) -> 297
C30: Balanse SEKm
C31: Goodwill | D31: 7799.9 | E31: 8070.7 | F31: 7986.7 | G31: 8097 | H31: 8226.7 | I31: 8256.3 | J31: 8623 | K31: 8623 | L31: 8484 | M31: 8359 | N31: 8490 | O31: 8489.6 | P31: 8539 | Q31: 5886 | R31: 5767 | S31: 5832 | T31: 5797 | U31: 5693
C32: Intangible assets | D32: 731.6 | E32: 723 | F32: 693.8 | G32: 674.9 | H32: 658.2 | I32: 636 | J32: 628.8 | K32: 628.8 | L32: 572 | M32: 543 | N32: 524 | O32: 523.7 | P32: 468 | Q32: 410 | R32: 386 | S32: 372 | T32: 365 | U32: 357
C33: Other intangible assets | D33: 213.4 | E33: 243.6 | F33: 269.5 | G33: 290.7 | H33: 318.8 | I33: 355.4 | J33: 395 | K33: 395 | L33: 460 | M33: 484 | N33: 519 | O33: 518.5 | P33: 553 | Q33: 538 | R33: 540 | S33: 545 | T33: 546 | U33: 540
C34: Tangible assets | D34: 140.9 | E34: 141.1 | F34: 133.2 | G34: 130 | H34: 126.4 | I34: 116.4 | J34: 117.6 | K34: 117.6 | L34: 118 | M34: 112 | N34: 119 | O34: 118.6 | P34: 104 | Q34: 82 | R34: 75 | S34: 70 | T34: 67 | U34: 65
C35: Right-of-use assets | D35: 552.9 | E35: 565 | F35: 530.7 | G35: 512.5 | H35: 482.5 | I35: 462 | J35: 500.2 | K35: 500.2 | L35: 473 | M35: 502 | N35: 533 | O35: 533.1 | P35: 537 | Q35: 565 | R35: 531 | S35: 499 | T35: 450 | U35: 448
C36: Deferred tax assets | D36: 5.3 | E36: 5.6 | F36: 5.4 | G36: 14.5 | H36: 15.7 | I36: 15.6 | J36: 6.5 | K36: 6.5 | L36: 110 | M36: 110 | N36: 111 | O36: 110.5 | P36: 108 | Q36: 176 | R36: 153 | S36: 149 | T36: 168 | U36: 181
C37: Derivative instruments | D37: 3.4 | E37: 26.9 | F37: 88.3 | G37: 156 | H37: 192.8 | I37: 253.3 | J37: 216 | K37: 216 | L37: 178 | M37: 157 | N37: 159 | O37: 158.6 | P37: 86 | Q37: 76 | R37: 60 | S37: 41 | T37: 38 | U37: 38
C38: Other non-current assets | D38: 6.8 | E38: 9 | F38: 9 | G38: 9.5 | H38: 10.6 | I38: 10.2 | J38: 11.6 | K38: 11.6 | L38: 13 | M38: 11 | N38: 8 | O38: 8.1 | P38: 15 | Q38: 14 | R38: 13 | S38: =14+49 -> 63 | T38: 14 | U38: 44
C39: Inventories | D39: 1138 | E39: 1258.6 | F39: 1469.7 | G39: 1340.2 | H39: 1609.6 | I39: 1219.9 | J39: 1031.1 | K39: 1031.1 | L39: 939 | M39: 895 | N39: 925 | O39: 925.3 | P39: 1160 | Q39: 1063 | R39: 1098 | S39: 1086 | T39: 863 | U39: 999
C40: Account receivables | D40: 3025.2 | E40: 2840.4 | F40: 2838.7 | G40: 3165.7 | H40: 3210.9 | I40: 3077.7 | J40: 3186.9 | K40: 3186.9 | L40: 2879 | M40: 2977 | N40: 3421 | O40: 3421.3 | P40: 3414 | Q40: 3846 | R40: 3245 | S40: 3287 | T40: 3417 | U40: 3067
C41: IB receivables | D41: 0 | E41: 0 | F41: 0 | G41: 0 | H41: 0 | I41: 0 | J41: 0 | K41: 0 | L41: 8 | M41: 21 | N41: 21 | O41: 20.7 | P41: 105 | Q41: 102 | R41: 108 | S41: 63 | T41: 57 | U41: 33
C42: Derivative instruments | D42: 0 | E42: 2.9 | F42: 2.5 | G42: 5.7 | H42: 0 | I42: 0.1 | J42: 0 | K42: 0 | L42: 11 | M42: 28 | N42: 0 | O42: 0 | P42: 8 | Q42: 4 | R42: 3 | S42: 0 | T42: 0 | U42: 2
C43: Tax assets | D43: 20 | E43: 20.8 | F43: 16.2 | G43: 15.7 | H43: 20 | I43: 26.3 | J43: 45.3 | K43: 45.3 | L43: 54 | M43: 53 | N43: 65 | O43: 65.2 | P43: 9 | Q43: 17 | R43: 17 | S43: 46 | T43: 51 | U43: 84
C44: Other receivables | D44: 619.5 | E44: 568.2 | F44: 605.2 | G44: 675.8 | H44: 669.8 | I44: 635.7 | J44: 567.3 | K44: 567.3 | L44: 599 | M44: 573 | N44: 516 | O44: 515.5 | P44: 653 | Q44: 725 | R44: 789 | S44: 674 | T44: 734 | U44: 724
C45: Cash | D45: 1144.3 | E45: 1140.2 | F45: 761.8 | G45: 766.8 | H45: 972 | I45: 950.5 | J45: 1228.9 | K45: 1228.9 | L45: 1265 | M45: 1030 | N45: 1361 | O45: 1361 | P45: 728 | Q45: 839 | R45: 1864 | S45: 676 | T45: 970 | U45: 1155
C46: Total assets | D46: =SUM(D31:D45) -> 15401.2 | E46: =SUM(E31:E45) -> 15616 | F46: =SUM(F31:F45) -> 15410.7 | G46: =SUM(G31:G45) -> 15855 | H46: =SUM(H31:H45) -> 16514 | I46: =SUM(I31:I45) -> 16015.4 | J46: =SUM(J31:J45) -> 16558.2 | K46: =SUM(K31:K45) -> 16558.2 | ... U46: =SUM(U31:U45) -> 13430
C47: Total equity | D47: 4826 | E47: 4825.5 | F47: 4925 | G47: 5085 | H47: 5202.9 | I47: 5322.1 | J47: 5383.7 | K47: 5383.7 | L47: 5348 | M47: 7116 | N47: 7187 | O47: 7186.5 | P47: 6953 | Q47: 4325 | R47: 5494 | S47: 5506 | T47: 5464 | U47: 5443
C48: Deferred tax and other provisions | D48: 243.6 | E48: 239.6 | F48: 247.6 | G48: 242 | H48: 235.4 | I48: 235.6 | J48: 200.1 | K48: 200.1 | L48: 174 | M48: 179 | N48: 165 | O48: 165.2 | P48: 138 | Q48: 129 | R48: 120 | S48: 121 | T48: 122 | U48: 123
C49: Non-current liabilities to banks | D49: 4522.7 | E49: 4719.6 | F49: 4657.1 | G49: 4734.4 | H49: 4819.1 | I49: 4824.2 | J49: 0 | K49: 0 | L49: 4964 | M49: 3477 | N49: 3545 | O49: 3544.6 | P49: 3565 | Q49: 3468 | R49: 3373 | S49: 2475 | T49: 2466 | U49: 2389
C50: Non-current lease liabilities | D50: 401.8 | E50: 407.9 | F50: 379.4 | G50: 361.7 | H50: 336.1 | I50: 319.4 | J50: 347 | K50: 347 | L50: 322 | M50: 346 | N50: 362 | O50: 361.5 | P50: 372 | Q50: 405 | R50: 374 | S50: 343 | T50: 302 | U50: 296
C51: Dervative instruments | D51: 43.7 | E51: 72.7 | F51: 67.8 | G51: 92.6 | H51: 98.5 | I51: 115.6 | J51: 203.2 | K51: 203 | L51: 3 | M51: 7 | N51: 2 | O51: 2.4 | P51: 24 | Q51: 19 | R51: 19 | S51: 12 | T51: 9 | U51: 10
C52: Current liabilities to banks | D52: 7.1 | E52: 7.4 | F52: 3.6 | G52: 7.4 | H52: 407.6 | I52: 255.7 | J52: 5325.1 | K52: 5325 | L52: 263 | M52: 24 | N52: 24 | O52: 23.6 | P52: 107 | Q52: 104 | R52: 108 | S52: 63 | T52: 57 | U52: 33
C53: Other provisions | D53: 1.5 | E53: 1 | F53: 1 | G53: 0.8 | H53: 0.8 | I53: 0.8 | J53: 0.7 | K53: 0.7 | L53: 1 | M53: 1 | N53: 6 | O53: 5.7 | P53: 6 | Q53: 6 | R53: 7 | S53: 7 | T53: 7 | U53: 7
C54: Current lease liabilities | D54: 175.1 | E54: 175.6 | F54: 171.3 | G54: 171.9 | H54: 168.1 | I54: 157.9 | J54: 169.5 | K54: 169.5 | L54: 168 | M54: 172 | N54: 189 | O54: 188.6 | P54: 183 | Q54: 178 | R54: 174 | S54: 174 | T54: 165 | U54: 168
C55: Acccount payable | D55: 3713.1 | E55: 3784 | F55: 3655.2 | G55: 3790.5 | H55: 3856.1 | I55: 3428 | J55: 3504.4 | K55: 3503.4 | L55: 3623 | M55: 3308 | N55: 4028 | O55: 4028 | P55: 3591 | Q55: 4211 | R55: 3493 | S55: 3342 | T55: 3635 | U55: 3691
C56: Tax liabilities | D56: 84.1 | E56: 67 | F56: 78.7 | G56: 120 | H56: 101.2 | I56: 83.3 | J56: 60 | K56: 60 | L56: 197 | M56: 196 | N56: 148 | O56: 147.8 | P56: 38 | Q56: 118 | R56: 46 | S56: 63 | T56: 11 | U56: 10
C57: Derivative instruments | D57: 25.5 | E57: 48 | F57: 35.5 | G57: 46.1 | H57: 75.8 | I57: 58 | J57: 81.3 | K57: 81.3 | L57: 192 | M57: 130 | N57: 164 | O57: 164.3 | P57: 170 | Q57: 118 | R57: 91 | S57: 86 | T57: 70 | U57: 41
C58: Other current liabilities | D58: 1335.9 | E58: 1267.8 | F58: 1188.2 | G58: 1202.5 | H58: 1212.3 | I58: 1215 | J58: 1283.2 | K58: 1283.2 | L58: 909 | M58: 900 | N58: 952 | O58: 951.9 | P58: 1339 | Q58: 1261 | R58: 1350 | S58: 1211 | T58: 1279 | U58: 1219
C59: Total debt | D59: =SUM(D48:D58) -> 10554.1 | E59: =SUM(E48:E58) -> 10790.6 | F59: =SUM(F48:F58) -> 10485.4 | G59: =SUM(G48:G58) -> 10769.9 | H59: =SUM(H48:H58) -> 11311 | I59: =SUM(I48:I58) -> 10693.5 | J59: =SUM(J48:J58) -> 11174.5 | K59: =SUM(K48:K58) -> 11173.2 | ... U59: =SUM(U48:U58) -> 7987
C60: Total E/D | D60: =D47+D59 -> 15380.1 | E60: =E47+E59 -> 15616.1 | F60: =F47+F59 -> 15410.4 | G60: =G47+G59 -> 15854.9 | H60: =H47+H59 -> 16513.9 | I60: =I47+I59 -> 16015.6 | J60: =J47+J59 -> 16558.2 | K60: =K47+K59 -> 16556.9 | ... U60: =U47+U59 -> 13430
C62: Cashflow SEKm
C63: Model EBIT | D63: =D12 -> 251.1 | E63: =E12 -> 220.1 | F63: =F12 -> 140.3 | G63: =G12 -> 146.9 | H63: =H12 -> 137.4 | I63: =I12 -> 157.5 | J63: =J12 -> 97 | K63: =K12 -> 97 | ... U63: =U12 -> 43 | AA63: =AA12 -> 349.5 | AB63: =AB12 -> 443.8 | AC63: =AC12 -> 489.1 | AD63: =AD12 -> 387.2 | AE63: =AE12 -> 576.3 | AF63: =AF12 -> 758 | AG63: =AG12 -> 466.1 | AH63: =AH12 -> 332.5 | ... AJ63: =AJ12 -> 194.3435
C64: Reported EBIT | D64: 251 | E64: 220 | F64: 140 | G64: 147 | H64: 137.5 | I64: 157 | J64: 97 | K64: 97 | L64: 129 | M64: 142 | N64: 86 | O64: 86 | P64: -52 | Q64: -2503 | R64: 11 | S64: 21 | T64: 7 | U64: 42 | AA64: 350 | AB64: 444 | AC64: 489 | AD64: 387 | AE64: 576.2 | AF64: 758 | AG64: 466.6 | AH64: 332.5 | AI64: -2523
C65: Non-cash | D65: 104.8 | E65: 119.3 | F65: 97.2 | G65: 98.1 | H65: 99 | I65: 73.4 | J65: 115.9 | K65: 115.9 | L65: 103 | M65: 102 | N65: 108 | O65: 107.6 | P65: 126 | Q65: 2632 | R65: 112 | S65: 116 | T65: 102 | U65: 106 | AA65: 58.1 | AB65: 51.7 | AC65: 66.9 | AD65: 302.8 | AE65: 314.4 | AF65: 419.5 | AG65: 421 | AH65: 418.3 | AI65: 2986
C66: Interest received | D66: 0.3 | E66: 0.2 | F66: 0.3 | G66: 0.5 | H66: 0.4 | I66: 3.5 | J66: 0.6 | K66: 0.6 | L66: 1 | M66: 1 | N66: 1 | O66: 0.8 | P66: 1 | Q66: 17 | R66: 2 | S66: 2 | T66: 0 | U66: 14 | AA66: 1.2 | AB66: 1.1 | AC66: 0.8 | AD66: 1.3 | AE66: 1.2 | AF66: 1.2 | AG66: 9.3 | AH66: 3.5 | AI66: 21
C67: Interest paid | D67: -30.6 | E67: -32 | F67: -28.9 | G67: -34.9 | H67: -47.6 | I67: -51.8 | J67: -60.3 | K67: -60.3 | L67: -77 | M67: -45 | N67: -38 | O67: -37.9 | P67: -37 | Q67: -44 | R67: -53 | S67: -37 | T67: -33 | U67: -30 | AA67: -27.4 | AB67: -34.6 | AC67: -38.8 | AD67: -53.4 | AE67: -77.3 | AF67: -126.4 | AG67: -230.4 | AH67: -202.2 | AI67: -171
C68: Tax paid | D68: -42.9 | E68: -29.4 | F68: -25.1 | G68: 1.4 | H68: -39 | I68: -59.9 | J68: -11.4 | K68: -11.4 | L68: -48 | M68: -34 | N68: -76 | O68: -75.8 | P68: -18 | Q68: -7 | R68: -45 | S68: 12 | T68: -67 | U68: -42 | AA68: -57.9 | AB68: -99.8 | AC68: -127.7 | AD68: -90.8 | AE68: -101 | AF68: -96.1 | AG68: -88 | AH68: -174 | AI68: -57
C69: WC | D69: =-117.7-609.4+813.5 -> 86.4 | E69: =-93.7+334.5-130.9 -> 109.9 | F69: =-218.3-76.2-166.2 -> -460.7 | G69: =140.5-335.1+87 -> -107.6 | H69: =-250.7-11.6+27.4 -> -234.9 | I69: =401.2+159.1-432.6 -> 127.7 | J69: =221.7+57.2+10.6 -> 289.5 | K69: =221.7+57.2+10.6 -> 289.5 | L69: =31-393+504 -> 142 | M69: =37-122-281 -> -366 | N69: =-19-332+724 -> 373 | O69: =-19.1-332.4+724.2 -> 372.7 | P69: =-326-432+695 -> -63 | Q69: =79-635+642 -> 86 | R69: =-51+406-521 -> -166 | S69: =21+118-328 -> -189 | T69: =218-233+387 -> 372 | U69: 169 | AA69: =-28.5-143.8+62.5 -> -109.8 | AB69: =-87.1+21.8+451 -> 385.7 | AC69: =-62.2-199.5+135.5 -> -126.2 | AD69: =-23.6+238.3+105.9 -> 320.6 | AE69: =-270.3-640.9+366.1 -> -545.1 | AF69: =-289.2-686.1+603.4 -> -371.9 | AG69: =425.1+725-1109.4 -> 40.7 | AH69: =144.7-578.9+203.5 -> -230.7 | AI69: =-276-543+489 -> -330
C70: CFFO | D70: =SUM(D64:D69) -> 369 | E70: =SUM(E64:E69) -> 388 | F70: =SUM(F64:F69) -> -277.2 | G70: =SUM(G64:G69) -> 104.5 | H70: =SUM(H64:H69) -> -84.6 | I70: =SUM(I64:I69) -> 249.9 | J70: =SUM(J64:J69) -> 431.3 | K70: =SUM(K64:K69) -> 431.3 | ... U70: =SUM(U64:U69) -> 259 | AA70: =SUM(AA64:AA69) -> 214.2 | AB70: =SUM(AB64:AB69) -> 748.1 | AC70: =SUM(AC64:AC69) -> 264 | AD70: =SUM(AD64:AD69) -> 867.5 | AE70: =SUM(AE64:AE69) -> 168.4 | AF70: =SUM(AF64:AF69) -> 584.3 | AG70: =SUM(AG64:AG69) -> 619.2 | AH70: =SUM(AH64:AH69) -> 147.4 | AI70: =SUM(AI64:AI69) -> -74
C72: Capex | D72: =-25.3-14.4 -> -39.7 | E72: =-43.9-10.3 -> -54.2 | F72: =-45.7-6.1 -> -51.8 | G72: =-37.6-7.7 -> -45.3 | H72: =-43.9-7 -> -50.9 | I72: =-55.9-7.8 -> -63.7 | J72: =-49.2-8.4 -> -57.6 | K72: =-49.2-8.4 -> -57.6 | L72: -70 | M72: -58 | N72: =-48-17 -> -65 | O72: =-47.7-17.2 -> -64.9 | P72: -45 | Q72: =-41 -> -41 | R72: -47 | S72: -36 | T72: -41 | U72: -39 | AA72: =-18.1-9.2-147.2 -> -174.5 | AB72: =-27.2-24.9-1023 -> -1075.1 | AC72: =-37.3-42.1-536.1+5 -> -610.5 | AD72: =-68.5-42.8 -> -111.3 | AE72: =-49.8-35.2-3080.5 -> -3165.5 | AF72: =-152.4-38.5 -> -190.9 | AG72: =-204.9-35.2 -> -240.1 | AH72: =-197.2-47.8 -> -245 | AI72: =-156-13 -> -169
C73: Divestment of tangible assets | D73: 0 | E73: -20.7 | F73: 0 | G73: 0 | H73: 0 | I73: 0 | J73: 0 | K73: 0 | L73: 0 | M73: 0 | N73: 0 | O73: 0 | P73: 0 | Q73: 0 | R73: 0 | S73: 0 | T73: 0 | U73: 0 | AA73: -26.6 | AB73: =1.5-53.7 -> -52.2 | AC73: -31.2 | AD73: =4.7-209 -> -204.3 | AE73: 0 | AF73: -20.7 | AG73: 0 | AH73: 0.7 | AI73: 0
C74: CFFI | D74: =SUM(D72:D73) -> -39.7 | E74: =SUM(E72:E73) -> -74.9 | F74: =SUM(F72:F73) -> -51.8 | G74: =SUM(G72:G73) -> -45.3 | H74: =SUM(H72:H73) -> -50.9 | I74: =SUM(I72:I73) -> -63.7 | J74: =SUM(J72:J73) -> -57.6 | K74: =SUM(K72:K73) -> -57.6 | ... U74: =SUM(U72:U73) -> -39 | AA74: =SUM(AA72:AA73) -> -201.1 | AB74: =SUM(AB72:AB73) -> -1127.3 | AC74: =SUM(AC72:AC73) -> -641.7 | AD74: =SUM(AD72:AD73) -> -315.6 | AE74: =SUM(AE72:AE73) -> -3165.5 | AF74: =SUM(AF72:AF73) -> -211.6 | AG74: =SUM(AG72:AG73) -> -240.1 | AH74: =SUM(AH72:AH73) -> -244.3 | AI74: =SUM(AI72:AI73) -> -169
C76: Share issue | D76: 5.8 | E76: 0 | F76: 0 | G76: 0 | H76: 0 | I76: 3.9 | J76: 0 | K76: 0 | L76: -1 | M76: 1730 | N76: 0 | O76: -0.2 | P76: 0 | Q76: 0 | R76: 1240 | S76: 0 | T76: 0 | U76: 1 | AA76: 1.6 | AB76: 54.6 | AC76: 680.8 | AD76: 0 | AE76: 1187.1 | AF76: 5.8 | AG76: 3.9 | AH76: 1728.9 | AI76: 1240
C77: Buybacks/Dividends | D77: 0 | E77: 0 | F77: 0 | G77: -1.9 | H77: 0 | I77: -4.1 | J77: 0 | K77: 0 | L77: 0 | M77: -20 | N77: 0 | O77: 0 | P77: 0 | Q77: 0 | R77: 0 | S77: 0 | T77: 0 | U77: 0 | AA77: 0 | AB77: 2165 | AC77: =28.9-239.2 -> -210.3 | AD77: =4-265.9 -> -261.9 | AE77: =-7.3-195 -> -202.3 | AF77: =2.4+-250 -> -247.6 | AG77: -4.1 | AH77: =-20 -> -20 | AI77: 0
C78: New loans | D78: 4466.4 | E78: 150 | F78: 0 | G78: 0 | H78: 400 | I78: 150 | J78: 0 | K78: 0 | L78: 0 | M78: 0 | N78: 0 | O78: 0 | P78: 0 | Q78: 0 | R78: 10 | S78: 0 | T78: 0 | U78: 0 | AA78: 0 | AB78: -1383.6 | AC78: 0 | AD78: 390.1 | AE78: 3629.9 | AF78: 4466.4 | AG78: 550 | AH78: 0 | AI78: 10
C79: Repayment of loans | D79: -4445.1 | E79: -301 | F79: -3.6 | G79: -3.7 | H79: 0 | I79: -301.9 | J79: -1.9 | K79: -1.9 | L79: 0 | M79: -1647 | N79: 0 | O79: -0.4 | P79: -3 | Q79: 0 | R79: 0 | S79: -1105 | T79: -3 | U79: 0 | AA79: -3.3 | AB79: -8.4 | AC79: -71.9 | AD79: -134.4 | AE79: -1321.8 | AF79: -4452.4 | AG79: -303.8 | AH79: -1647.9 | AI79: -1008
C80: Paid borrowing expenses | D80: -15.7 | E80: -8 | F80: -1 | G80: 0 | H80: 0 | I80: -8 | J80: 0 | K80: 0 | L80: 0 | M80: 0 | N80: 0 | O80: 0 | P80: -8 | Q80: 0 | R80: -4 | S80: -7 | T80: 0 | U80: -1 | AA80: -182.8 | AB80: -213.3 | AC80: -0.6 | AD80: -1.5 | AE80: -25.5 | AF80: -16.8 | AG80: -28.3 | AH80: -12.4 | AI80: -19
C81: Repayment of lease | D81: -46.7 | E81: -44.9 | F81: -45.8 | G81: -45.2 | H81: -47 | I81: -44.9 | J81: -48.1 | K81: -48.1 | L81: -50 | M81: -49 | N81: -48 | O81: -48 | P81: -51 | Q81: -50 | R81: -51 | S81: -49 | T81: -48 | U81: -48 | AA81: -1.6 | AB81: -3.6 | AC81: -4.8 | AD81: -148.7 | AE81: -162.3 | AF81: -190 | AG81: -191 | AH81: -197.5 | AI81: -202
C82: CFFF | D82: =SUM(D76:D81) -> -35.3 | E82: =SUM(E76:E81) -> -203.9 | F82: =SUM(F76:F81) -> -50.4 | G82: =SUM(G76:G81) -> -50.8 | H82: =SUM(H76:H81) -> 353 | I82: =SUM(I76:I81) -> -205 | J82: =SUM(J76:J81) -> -50 | K82: =SUM(K76:K81) -> -50 | ... U82: =SUM(U76:U81) -> -48 | AA82: =SUM(AA76:AA81) -> -186.1 | AB82: =SUM(AB76:AB81) -> 610.7 | AC82: =SUM(AC76:AC81) -> 393.2 | AD82: =SUM(AD76:AD81) -> -156.4 | AE82: =SUM(AE76:AE81) -> 3105.1 | AF82: =SUM(AF76:AF81) -> -434.6 | AG82: =SUM(AG76:AG81) -> 26.7 | AH82: =SUM(AH76:AH81) -> -148.9 | AI82: =SUM(AI76:AI81) -> 21
C84: FX | D84: 2.9 | E84: -2.4 | F84: 1 | G84: -3.2 | H84: -12.7 | I84: -2.4 | J84: -45.1 | K84: -45.1 | L84: 28 | M84: 11 | N84: -10 | O84: -9.5 | P84: -7 | Q84: 22 | R84: 17 | S84: -18 | T84: 5 | U84: 13 | AA84: 2.2 | AB84: -25.1 | AC84: -11.8 | AD84: 53 | AE84: 9.1 | AF84: -18.6 | AG84: -64.5 | AH84: 22.1 | AI84: 14
C86: CIC | D86: =D70+D74+D82+D84 -> 296.9 | E86: =E70+E74+E82+E84 -> 106.8 | F86: =F70+F74+F82+F84 -> -378.4 | G86: =G70+G74+G82+G84 -> 5.2 | H86: =H70+H74+H82+H84 -> 204.8 | I86: =I70+I74+I82+I84 -> -21.2 | J86: =J70+J74+J82+J84 -> 278.6 | K86: =K70+K74+K82+K84 -> 278.6 | ... U86: =U70+U74+U82+U84 -> 185 | AA86: =AA70+AA74+AA82+AA84 -> -170.8 | AB86: =AB70+AB74+AB82+AB84 -> 206.4 | AC86: =AC70+AC74+AC82+AC84 -> 3.7 | AD86: =AD70+AD74+AD82+AD84 -> 448.5 | AE86: =AE70+AE74+AE82+AE84 -> 117.1 | AF86: =AF70+AF74+AF82+AF84 -> -80.5 | AG86: =AG70+AG74+AG82+AG84 -> 341.3 | AH86: =AH70+AH74+AH82+AH84 -> -223.7 | AI86: =AI70+AI74+AI82+AI84 -> -208
C88: FCF | D88: =D70+D72 -> 329.3 | E88: =E70+E72 -> 333.8 | F88: =F70+F72 -> -329 | G88: =G70+G72 -> 59.2 | H88: =H70+H72 -> -135.5 | I88: =I70+I72 -> 186.2 | J88: =J70+J72 -> 373.7 | K88: =K70+K72 -> 373.7 | ... U88: =U70+U72 -> 220 | AA88: =AA70+AA72 -> 39.7 | AB88: =AB70+AB72 -> -327 | AC88: =AC70+AC72 -> -346.5 | AD88: =AD70+AD72 -> 756.2 | AE88: =AE70+AE72 -> -2997.1 | AF88: =AF70+AF72 -> 393.4 | AG88: =AG70+AG72 -> 379.1 | AH88: =AH70+AH72 -> -97.6 | AI88: =AI70+AI72 -> -243

Sheet Segementer
B3: SEK million | C3: Q1 21/22 | D3: Q2 21/22 | E3: Q3 21/22 | F3: Q4 21/22 | G3: 21/22 | H3: Q1 22/23 | I3: Q2 22/23 | J3: Q3 22/23 | K3: Q4 22/23 | L3: 22/23 | M3: Q1 23/24 | N3: Q2 23/24 | O3: Q3 23/24 | P3: Q4 23/24 | Q3: 23/24 | R3: Q1 24/25 | S3: Q2 24/25 | T3: Q3 24/25 | U3: Q4 24/25 | V3: 24/25 | W3: Q1 25/26 | X3: Q2 25/26 | Y3: Q3 25/26 | Z3: Q4 25/26 | AA3: 25/26
B4: SMB
B5: Revenues | C5: 1852.7 | D5: 1995.6 | E5: 1973.6 | F5: 1638.7 | G5: =SUM(C5:F5) -> 7460.6 | H5: 1770.7 | I5: 1821.5 | J5: 1653.8 | K5: 1459.3 | L5: =SUM(H5:K5) -> 6705.3 | M5: 1711 | N5: 1574 | O5: 1474 | P5: 1278 | Q5: =SUM(M5:P5) -> 6037 | R5: 1553 | S5: 1540 | T5: 1396 | U5: 1178 | V5: =SUM(R5:U5) -> 5667 | W5: 1470 | X5: 1332 | AA5: =SUM(W5:Z5) -> 2802
B6: y/y | H6: =(H5-C5)/C5 -> -0.044259729 | I6: =(I5-D5)/D5 -> -0.087241932 | J6: =(J5-E5)/E5 -> -0.16203891 | K6: =(K5-F5)/F5 -> -0.10947702 | L6: =(L5-G5)/G5 -> -0.10123851 | M6: =(M5-H5)/H5 -> -0.03371548 | N6: =(N5-I5)/I5 -> -0.13587702 | O6: =(O5-J5)/J5 -> -0.10871931 | ... AA6: =(AA5-V5)/V5 -> -0.5055585
B7: Nordic | G7: =SUM(C7:F7) -> 0 | L7: =SUM(H7:K7) -> 0 | M7: 1434 | N7: 1305 | O7: 1228 | P7: 1054 | Q7: =SUM(M7:P7) -> 5021 | R7: 1310 | S7: 1297 | T7: 1179 | U7: 978 | V7: =SUM(R7:U7) -> 4764 | W7: 1256 | X7: 1122 | AA7: =SUM(W7:Z7) -> 2378
B8: Benelux | G8: =SUM(C8:F8) -> 0 | L8: =SUM(H8:K8) -> 0 | M8: 276 | N8: 269 | O8: 246 | P8: 224 | Q8: =SUM(M8:P8) -> 1015 | R8: 243 | S8: 243 | T8: 217 | U8: 200 | V8: =SUM(R8:U8) -> 903 | W8: 214 | X8: 210 | AA8: =SUM(W8:Z8) -> 424
B9: Hardware | C9: 1585.5 | D9: 1704 | E9: 1726.1 | F9: 1436.1 | G9: =SUM(C9:F9) -> 6451.7 | H9: 1550.5 | I9: 1622.1 | J9: 1461.2 | K9: 1265.6 | L9: =SUM(H9:K9) -> 5899.4 | M9: 1503 | N9: 1359 | O9: 1295 | P9: 1084 | Q9: =SUM(M9:P9) -> 5241 | R9: 1361 | S9: 1361 | T9: 1204 | U9: 1054 | V9: =SUM(R9:U9) -> 4980 | W9: 1314 | X9: 1155 | AA9: =SUM(W9:Z9) -> 2469
B10: Software and services | C10: 267.1 | D10: 291.6 | E10: 247.4 | F10: 202.6 | G10: =SUM(C10:F10) -> 1008.7 | H10: 220.3 | I10: 199.4 | J10: 192.6 | K10: 193.7 | L10: =SUM(H10:K10) -> 806 | M10: 208 | N10: 215 | O10: 180 | P10: 194 | Q10: =SUM(M10:P10) -> 797 | R10: 193 | S10: 179 | T10: 192 | U10: 123 | V10: =SUM(R10:U10) -> 687 | W10: 157 | X10: 177 | AA10: =SUM(W10:Z10) -> 334
B11: Segment results | C11: 230.1 | D11: 134.7 | E11: 108.8 | F11: 76.6 | G11: =SUM(C11:F11) -> 550.2 | H11: 179.7 | I11: 80.3 | J11: 64.6 | K11: 63.5 | L11: =SUM(H11:K11) -> 388.1 | M11: 61 | N11: 66 | O11: 37 | P11: 9 | Q11: =SUM(M11:P11) -> 173 | R11: 50 | S11: 46 | T11: 37 | U11: 34 | V11: =SUM(R11:U11) -> 167 | W11: 53 | X11: 31 | AA11: =SUM(W11:Z11) -> 84
B12: Segment margin | C12: 0.124 | D12: 0.067 | E12: 0.055 | F12: 0.047 | G12: =G11/G5 -> 0.07374742 | H12: 0.101 | I12: 0.044 | J12: 0.039 | K12: 0.044 | L12: =L11/L5 -> 0.057879588 | M12: 0.036 | N12: 0.042 | O12: 0.025 | P12: 0.007 | Q12: =Q11/Q5 -> 0.028656618 | R12: 0.032 | S12: 0.03 | T12: 0.027 | U12: 0.029 | V12: =V11/V5 -> 0.029468855 | W12: =W11/W5 -> 0.036054422 | X12: =X11/X5 -> 0.023273273 | Y12: =Y11/Y5 -> #DIV/0! | Z12: =Z11/Z5 -> #DIV/0! | AA12: =AA11/AA5 -> 0.029978587
B13: LCP
B14: Revenues | C14: 3833.9 | D14: 4141.6 | E14: 3920.7 | F14: 4104.7 | G14: =SUM(C14:F14) -> 16000.9 | H14: 4726.6 | I14: 4450 | J14: 3928.2 | K14: 3628.6 | L14: =SUM(H14:K14) -> 16733.4 | M14: 4082 | N14: 3672 | O14: 3981 | P14: 3709 | Q14: =SUM(M14:P14) -> 15444 | R14: 3228 | S14: 3940 | T14: 3693 | U14: 3878 | V14: =SUM(R14:U14) -> 14739 | W14: 4017 | X14: 4149 | AA14: =SUM(W14:Z14) -> 8166
B15: y/y | H15: =(H14-C14)/C14 -> 0.23284384 | I15: =(I14-D14)/D14 -> 0.074463975 | J15: =(J14-E14)/E14 -> 0.0019129237 | K15: =(K14-F14)/F14 -> -0.11598899 | L15: =(L14-G14)/G14 -> 0.045778675 | M15: =(M14-H14)/H14 -> -0.1363771 | N15: =(N14-I14)/I14 -> -0.17483146 | O15: =(O14-J14)/J14 -> 0.013441271 | ... AA15: =(AA14-V14)/V14 -> -0.4459597
B16: Nordic | G16: =SUM(C16:F16) -> 0 | L16: =SUM(H16:K16) -> 0 | M16: 1858 | N16: 1654 | O16: 1727 | P16: 1682 | Q16: =SUM(M16:P16) -> 6921 | R16: 1789 | S16: 1840 | T16: 1830 | U16: 1866 | V16: =SUM(R16:U16) -> 7325 | W16: 1971 | X16: 2015 | AA16: =SUM(W16:Z16) -> 3986
B17: Benelux | G17: =SUM(C17:F17) -> 0 | L17: =SUM(H17:K17) -> 0 | M17: 2225 | N17: 2019 | O17: 2254 | P17: 2027 | Q17: =SUM(M17:P17) -> 8525 | R17: 1439 | S17: 2101 | T17: 1863 | U17: 2012 | V17: =SUM(R17:U17) -> 7415 | W17: 2046 | X17: 2134 | AA17: =SUM(W17:Z17) -> 4180
B18: Hardware | C18: 3370.3 | D18: 3462.8 | E18: 3328.9 | F18: 3434.1 | G18: =SUM(C18:F18) -> 13596.1 | H18: 3818.6 | I18: 3412.1 | J18: 3111 | K18: 2921.6 | L18: =SUM(H18:K18) -> 13263.3 | M18: 3150 | N18: 2864 | O18: 3573 | P18: 3336 | Q18: =SUM(M18:P18) -> 12923 | R18: 2565 | S18: 3411 | T18: 3339 | U18: 2383 | V18: =SUM(R18:U18) -> 11698 | W18: 3632 | X18: 3661 | AA18: =SUM(W18:Z18) -> 7293
B19: Software and services | C19: 463.6 | D19: 678.9 | E19: 591.8 | F19: 670.6 | G19: =SUM(C19:F19) -> 2404.9 | H19: 908 | I19: 1037.9 | J19: 817.2 | K19: 707 | L19: =SUM(H19:K19) -> 3470.1 | M19: 932 | N19: 808 | O19: 407 | P19: 373 | Q19: =SUM(M19:P19) -> 2520 | R19: 663 | S19: 530 | T19: 354 | U19: 396 | V19: =SUM(R19:U19) -> 1943 | W19: 385 | X19: 488 | AA19: =SUM(W19:Z19) -> 873
B20: Segment results | C20: 292.9 | D20: 172.3 | E20: 119.3 | F20: 147.9 | G20: =SUM(C20:F20) -> 732.4 | H20: 279.2 | I20: 172.5 | J20: 140.6 | K20: 104.4 | L20: =SUM(H20:K20) -> 696.7 | M20: 162 | N20: 164 | O20: -36 | P20: 53 | Q20: =SUM(M20:P20) -> 343 | R20: 11 | S20: 99 | T20: -28 | U20: 80 | V20: =SUM(R20:U20) -> 162 | W20: 70 | X20: 105 | AA20: =SUM(W20:Z20) -> 175
B21: Segment margin | C21: 0.076 | D21: 0.042 | E21: 0.03 | F21: 0.036 | G21: =G20/G14 -> 0.045772425 | H21: 0.059 | I21: 0.039 | J21: 0.036 | K21: 0.029 | L21: =L20/L14 -> 0.041635292 | M21: 0.04 | N21: 0.045 | O21: -0.007 | P21: 0.014 | Q21: =Q20/Q14 -> 0.022209272 | R21: 0.003 | S21: 0.025 | T21: -0.006 | U21: 0.021 | V21: =V20/V14 -> 0.010991248 | W21: =W20/W14 -> 0.01742594 | X21: =X20/X14 -> 0.025307303 | Y21: =Y20/Y14 -> #DIV/0! | Z21: =Z20/Z14 -> #DIV/0! | AA21: =AA20/AA14 -> 0.021430321

Sheet Land
B3: SEK million | C3: Q1 21/22 | D3: Q2 21/22 | E3: Q3 21/22 | F3: Q4 21/22 | G3: 21/22 | H3: Q1 22/23 | I3: Q2 22/23 | J3: Q3 22/23 | K3: Q4 22/23 | L3: 22/23 | M3: Q1 23/24 | N3: Q2 23/24 | O3: Q3 23/24 | P3: Q4 23/24 | Q3: 23/24 | R3: Q1 24/25 | S3: Q2 24/25 | T3: Q3 24/25 | U3: Q4 24/25 | V3: 24/25 | W3: Q1 25/26 | X3: Q2 25/26 | Y3: Q3 25/26 | Z3: Q4 25/26
B4: Geographic area
B5: Sweden | C5: 1496.2 | D5: 1512.1 | E5: 1505.2 | F5: 1299.2 | G5: =SUM(C5:F5) -> 5812.7 | H5: 1548.1 | I5: 1448.1 | J5: 1337.3 | K5: 1091.7 | L5: =SUM(H5:K5) -> 5425.2 | M5: 1454 | N5: 1363 | O5: 1290 | P5: 1272 | Q5: =SUM(M5:P5) -> 5379 | R5: 1450 | S5: 1476 | T5: 1427 | U5: 1276 | V5: =SUM(R5:U5) -> 5629 | W5: 1596 | X5: 1560
B6: y/y | H6: =(H5-C5)/C5 -> 0.034687876 | I6: =(I5-D5)/D5 -> -0.042325243 | J6: =(J5-E5)/E5 -> -0.11154664 | K6: =(K5-F5)/F5 -> -0.15971367 | L6: =(L5-G5)/G5 -> -0.066664373 | M6: =(M5-H5)/H5 -> -0.060784187 | N6: =(N5-I5)/I5 -> -0.05876666 | O6: =(O5-J5)/J5 -> -0.035369775 | ... Z6: =(Z5-U5)/U5 -> -1
B7: Finland | C7: 590.8 | D7: 578.1 | E7: 596.1 | F7: 531.8 | G7: =SUM(C7:F7) -> 2296.8 | H7: 546 | I7: 625.3 | J7: 580 | K7: 605.3 | L7: =SUM(H7:K7) -> 2356.6 | M7: 624 | N7: 426 | O7: 419 | P7: 367 | Q7: =SUM(M7:P7) -> 1836 | R7: 427 | S7: 407 | T7: 472 | U7: 447 | V7: =SUM(R7:U7) -> 1753 | W7: 383 | X7: 349
B8: y/y | H8: =(H7-C7)/C7 -> -0.075829384 | I8: =(I7-D7)/D7 -> 0.081646774 | J8: =(J7-E7)/E7 -> -0.027008891 | K8: =(K7-F7)/F7 -> 0.13820985 | L8: =(L7-G7)/G7 -> 0.026036224 | M8: =(M7-H7)/H7 -> 0.14285714 | N8: =(N7-I7)/I7 -> -0.31872701 | O8: =(O7-J7)/J7 -> -0.27758621 | ... Z8: =(Z7-U7)/U7 -> -1
B9: Denmark | C9: 802.6 | D9: 841.4 | E9: 883.3 | F9: 920.8 | G9: =SUM(C9:F9) -> 3448.1 | H9: 764.4 | I9: 579.1 | J9: 475.9 | K9: 418.4 | L9: =SUM(H9:K9) -> 2237.8 | M9: 496 | N9: 472 | O9: 505 | P9: 434 | Q9: =SUM(M9:P9) -> 1907 | R9: 466 | S9: 499 | T9: 400 | U9: 371 | V9: =SUM(R9:U9) -> 1736 | W9: 498 | X9: 428
B10: y/y | H10: =(H9-C9)/C9 -> -0.047595315 | I10: =(I9-D9)/D9 -> -0.31174233 | J10: =(J9-E9)/E9 -> -0.46122495 | K10: =(K9-F9)/F9 -> -0.54561251 | L10: =(L9-G9)/G9 -> -0.3510049 | M10: =(M9-H9)/H9 -> -0.35112507 | N10: =(N9-I9)/I9 -> -0.18494215 | O10: =(O9-J9)/J9 -> 0.0611473 | ... Z10: =(Z9-U9)/U9 -> -1
B11: Netherlands | C11: 1971.3 | D11: 2265.1 | E11: 1955.9 | F11: 2044.3 | G11: =SUM(C11:F11) -> 8236.6 | H11: 2750.3 | I11: 2592.2 | J11: 2304.5 | K11: 2038 | L11: =SUM(H11:K11) -> 9685 | M11: 2291 | N11: 2072 | O11: 2302 | P11: 2070 | Q11: =SUM(M11:P11) -> 8735 | R11: 1500 | S11: 2066 | T11: 1814 | U11: 1928 | V11: =SUM(R11:U11) -> 7308 | W11: 1969 | X11: 1963
B12: y/y | H12: =(H11-C11)/C11 -> 0.3951707 | I12: =(I11-D11)/D11 -> 0.14440864 | J12: =(J11-E11)/E11 -> 0.17822997 | K12: =(K11-F11)/F11 -> -0.0030817395 | L12: =(L11-G11)/G11 -> 0.17584926 | M12: =(M11-H11)/H11 -> -0.16699996 | N12: =(N11-I11)/I11 -> -0.20067896 | O12: =(O11-J11)/J11 -> -0.001084834 | ... Z12: =(Z11-U11)/U11 -> -1
B13: Norway | C13: 769.6 | D13: 724.9 | E13: 734.4 | F13: 756.5 | G13: =SUM(C13:F13) -> 2985.4 | H13: 820.3 | I13: 758.4 | J13: 663 | K13: 728.2 | L13: =SUM(H13:K13) -> 2969.9 | M13: 717 | N13: 697 | O13: 741 | P13: 662 | Q13: =SUM(M13:P13) -> 2817 | R13: 756 | S13: 754 | T13: 709 | U13: 750 | V13: =SUM(R13:U13) -> 2969 | W13: 750 | X13: 801
B14: y/y | H14: =(H13-C13)/C13 -> 0.065878378 | I14: =(I13-D13)/D13 -> 0.046213271 | J14: =(J13-E13)/E13 -> -0.097222222 | K14: =(K13-F13)/F13 -> -0.037409121 | L14: =(L13-G13)/G13 -> -0.0051919341 | M14: =(M13-H13)/H13 -> -0.12592954 | N14: =(N13-I13)/I13 -> -0.080959916 | O14: =(O13-J13)/J13 -> 0.11764706 | ... Z14: =(Z13-U13)/U13 -> -1
B15: Belgium | C15: 195.5 | D15: 215.6 | E15: 219.3 | F15: 190.8 | G15: =SUM(C15:F15) -> 821.2 | H15: 206.7 | I15: 228.5 | J15: 221.2 | K15: 206.3 | L15: =SUM(H15:K15) -> 862.7 | M15: 210 | N15: 216 | O15: 198 | P15: 182 | Q15: =SUM(M15:P15) -> 806 | R15: 182 | S15: 278 | T15: 266 | U15: 284 | V15: =SUM(R15:U15) -> 1010 | W15: 291 | X15: 381
B16: y/y | H16: =(H15-C15)/C15 -> 0.057289003 | I16: =(I15-D15)/D15 -> 0.059833024 | J16: =(J15-E15)/E15 -> 0.0086639307 | K16: =(K15-F15)/F15 -> 0.081236897 | L16: =(L15-G15)/G15 -> 0.050535801 | M16: =(M15-H15)/H15 -> 0.015965167 | N16: =(N15-I15)/I15 -> -0.054704595 | O16: =(O15-J15)/J15 -> -0.10488246 | ... Z16: =(Z15-U15)/U15 -> -1
B17: Total | C17: =SUM(C5,C7,C9,C11,C13,C15) -> 5826 | D17: =SUM(D5,D7,D9,D11,D13,D15) -> 6137.2 | E17: =SUM(E5,E7,E9,E11,E13,E15) -> 5894.2 | F17: =SUM(F5,F7,F9,F11,F13,F15) -> 5743.4 | G17: =SUM(C17:F17) -> 23600.8 | H17: =SUM(H5,H7,H9,H11,H13,H15) -> 6635.8 | I17: =SUM(I5,I7,I9,I11,I13,I15) -> 6231.6 | J17: =SUM(J5,J7,J9,J11,J13,J15) -> 5581.9 | K17: =SUM(K5,K7,K9,K11,K13,K15) -> 5087.9 | L17: =SUM(H17:K17) -> 23537.2 | M17: =SUM(M5,M7,M9,M11,M13,M15) -> 5792 | N17: =SUM(N5,N7,N9,N11,N13,N15) -> 5246 | O17: =SUM(O5,O7,O9,O11,O13,O15) -> 5455 | P17: =SUM(P5,P7,P9,P11,P13,P15) -> 4987 | Q17: =SUM(M17:P17) -> 21480 | R17: =SUM(R5,R7,R9,R11,R13,R15) -> 4781 | S17: =SUM(S5,S7,S9,S11,S13,S15) -> 5480 | T17: =SUM(T5,T7,T9,T11,T13,T15) -> 5088 | U17: =SUM(U5,U7,U9,U11,U13,U15) -> 5056 | V17: =SUM(R17:U17) -> 20405 | W17: =SUM(W5,W7,W9,W11,W13,W15) -> 5487 | X17: =SUM(X5,X7,X9,X11,X13,X15) -> 5482 | Y17: =SUM(Y5,Y7,Y9,Y11,Y13,Y15) -> 0 | Z17: =SUM(Z5,Z7,Z9,Z11,Z13,Z15) -> 0

Sheet Nøkkeltall
D4: 25/26 | E4: 26/27 | F4: 27/28
C5: EV/EBIT | D5: =Modell!$B$9/Modell!AJ12 -> 19.676885 | E5: =Modell!$B$9/Modell!AK12 -> 11.474187 | F5: =Modell!$B$9/Modell!AL12 -> 8.7842728
C6: P/E | D6: =Modell!$B$4/Modell!AJ19 -> 14.717733 | E6: =Modell!$B$4/Modell!AK19 -> 8.5823551 | F6: =Modell!$B$4/Modell!AL19 -> 6.5703782

Sheet Nedsideberegning
A3: Nedside | D3: FY 16/17 | E3: FY 17/18 | F3: FY 18/19 | G3: FY 19/20 | H3: FY 20/21 | I3: FY 21/22 | J3: FY 22/23 | K3: FY 23/24 | L3: FY 24/25 | M3: FY 25/26 | N3: FY 26/27 | O3: FY 27/28 | P3: FY 28/29 | Q3: FY 29/30 | R3: FY 30/31 | S3: FY31/32 | T3: FY 32/33 | U3: FY 33/34 | V3: FY 34/35
A4: Nullveskt og dårligste marginer | C4: Revenue | D4: 9306.2 | E4: 10300.5 | F4: 12535.7 | G4: 13195.4 | H4: 15028 | I4: 23600.9 | J4: 23577 | K4: 21481.8 | L4: 20642 | M4: =L4*1 -> 20642 | N4: =M4*1 -> 20642 | O4: =N4*1 -> 20642 | P4: =O4*1 -> 20642 | Q4: =P4*1 -> 20642 | R4: =Q4*1 -> 20642 | S4: =R4*1 -> 20642 | T4: =S4*1 -> 20642 | ... V4: =U4*1 -> 20642
A5: =Y24 -> 1.2957633 | C5: COGS | D5: -7926.7 | E5: -8663.7 | F5: -10446.3 | G5: -11152 | H5: -12545 | I5: -20143.3 | J5: -20168.8 | K5: -18273.2 | L5: =L4*-0.865 -> -17855.33 | M5: =M4*-0.87 -> -17958.54 | N5: =N4*-0.87 -> -17958.54 | O5: =O4*-0.87 -> -17958.54 | P5: =P4*-0.87 -> -17958.54 | Q5: =Q4*-0.87 -> -17958.54 | R5: =R4*-0.87 -> -17958.54 | S5: =S4*-0.87 -> -17958.54 | T5: =T4*-0.87 -> -17958.54 | ... V5: =V4*-0.87 -> -17958.54
A6: =Y25 -> -0.2287123 | C6: Gross profit | D6: =SUM(D4:D5) -> 1379.5 | E6: =SUM(E4:E5) -> 1636.8 | F6: =SUM(F4:F5) -> 2089.4 | G6: =SUM(G4:G5) -> 2043.4 | H6: =SUM(H4:H5) -> 2483 | I6: =SUM(I4:I5) -> 3457.6 | J6: =SUM(J4:J5) -> 3408.2 | K6: =SUM(K4:K5) -> 3208.6 | ... V6: =SUM(V4:V5) -> 2683.46
C7: Selling and admin expense | D7: -1016.3 | E7: -1183.3 | F7: -1594.3 | G7: -1617.9 | H7: -1825.2 | I7: -2628.3 | J7: -2865.3 | K7: -2813.4 | L7: =K7 -> -2813.4 | M7: =L7*0.86 -> -2419.524 | N7: =M7*1 -> -2419.524 | O7: =N7*1 -> -2419.524 | P7: =O7*1 -> -2419.524 | Q7: =P7*1 -> -2419.524 | R7: =Q7*1 -> -2419.524 | S7: =R7*1 -> -2419.524 | T7: =S7*1 -> -2419.524 | U7: =T7*1 -> -2419.524 | V7: =U7*1 -> -2419.524
C8: Items affecting comparability | D8: -7.3 | E8: 1 | F8: 3.5 | G8: -31 | H8: -73.4 | I8: -50.1 | J8: -73.2 | K8: -39.7 | L8: =K8 -> -39.7 | M8: =L8*0.89 -> -35.333 | N8: =M8*1 -> -35.333 | O8: =N8*1 -> -35.333 | P8: =O8*1 -> -35.333 | Q8: =P8*1 -> -35.333 | R8: =Q8*1 -> -35.333 | S8: =R8*1 -> -35.333 | T8: =S8*1 -> -35.333 | U8: =T8*1 -> -35.333 | V8: =U8*1 -> -35.333
C9: Other operating income | D9: 5.9 | E9: 6.8 | F9: 7.6 | G9: 14.5 | H9: 14.1 | I9: 20.5 | J9: 46.5 | K9: 18.7 | L9: =K9 -> 18.7 | M9: =L9*0.89 -> 16.643 | N9: =M9*1 -> 16.643 | O9: =N9*1 -> 16.643 | P9: =O9*1 -> 16.643 | Q9: =P9*1 -> 16.643 | R9: =Q9*1 -> 16.643 | S9: =R9*1 -> 16.643 | T9: =S9*1 -> 16.643 | U9: =T9*1 -> 16.643 | V9: =U9*1 -> 16.643
C10: Other opex | D10: -12.3 | E10: -17.5 | F10: -17.1 | G10: -21.8 | H10: -22.2 | I10: -41.7 | J10: -50.1 | K10: -41.7 | L10: =K10 -> -41.7 | M10: =L10*0.89 -> -37.113 | N10: =M10*1 -> -37.113 | O10: =N10*1 -> -37.113 | P10: =O10*1 -> -37.113 | Q10: =P10*1 -> -37.113 | R10: =Q10*1 -> -37.113 | S10: =R10*1 -> -37.113 | T10: =S10*1 -> -37.113 | U10: =T10*1 -> -37.113 | V10: =U10*1 -> -37.113
C11: Imapirment of acquisition-related assets | D11: 0 | E11: 0 | F11: 0 | G11: 0 | H11: 0 | I11: 0 | J11: 0 | K11: 0 | L11: -2500 | M11: 0 | N11: 0 | O11: 0 | P11: 0 | Q11: 0 | R11: 0 | S11: 0 | T11: 0 | U11: 0 | V11: 0
C12: Operating profit (EBIT) | D12: =SUM(D6:D11) -> 349.5 | E12: =SUM(E6:E11) -> 443.8 | F12: =SUM(F6:F11) -> 489.1 | G12: =SUM(G6:G11) -> 387.2 | H12: =SUM(H6:H11) -> 576.3 | I12: =SUM(I6:I11) -> 758 | J12: =SUM(J6:J11) -> 466.1 | K12: =SUM(K6:K11) -> 332.5 | ... V12: =SUM(V6:V11) -> 208.133
C13: Financial income | D13: 1.2 | E13: 1.1 | F13: 0.8 | G13: 1.3 | H13: 1.2 | I13: 1.2 | J13: 9.3 | K13: 3.5 | L13: 38 | M13: 0 | N13: 0 | O13: 0 | P13: 0 | Q13: 0 | R13: 0 | S13: 0 | U13: 0 | V13: 0
C14: Financial expense | D14: -42.6 | E14: -60.3 | F14: -45 | G14: -53.3 | H14: -108.3 | I14: -129.8 | J14: -238.7 | K14: -219.4 | L14: -236 | M14: 0 | N14: =M14*1.02 -> 0 | O14: =N14*1.02 -> 0 | P14: =O14*1.02 -> 0 | Q14: =P14*1.02 -> 0 | R14: =Q14*1.02 -> 0 | S14: =R14*1.02 -> 0 | T14: =S14*1.02 -> 0 | U14: =T14*1.02 -> 0 | V14: =U14*1.02 -> 0
C15: PTP | D15: =SUM(D12:D14) -> 308.1 | E15: =SUM(E12:E14) -> 384.6 | F15: =SUM(F12:F14) -> 444.9 | G15: =SUM(G12:G14) -> 335.2 | H15: =SUM(H12:H14) -> 469.2 | I15: =SUM(I12:I14) -> 629.4 | J15: =SUM(J12:J14) -> 236.7 | K15: =SUM(K12:K14) -> 116.6 | ... V15: =SUM(V12:V14) -> 208.133
C16: Tax | D16: -69 | E16: -79.4 | F16: -88.7 | G16: -57.9 | H16: -112.2 | I16: -151.8 | J16: -63.2 | K16: -63.5 | L16: =L15*-0.206 -> 574.21058 | M16: =M15*-0.206 -> -42.875398 | N16: =N15*-0.206 -> -42.875398 | O16: =O15*-0.206 -> -42.875398 | P16: =P15*-0.206 -> -42.875398 | Q16: =Q15*-0.206 -> -42.875398 | R16: =R15*-0.206 -> -42.875398 | S16: =S15*-0.206 -> -42.875398 | ... V16: =V15*-0.206 -> -42.875398
C17: Net income | D17: =SUM(D15:D16) -> 239.1 | E17: =SUM(E15:E16) -> 305.2 | F17: =SUM(F15:F16) -> 356.2 | G17: =SUM(G15:G16) -> 277.3 | H17: =SUM(H15:H16) -> 357 | I17: =SUM(I15:I16) -> 477.6 | J17: =SUM(J15:J16) -> 173.5 | K17: =SUM(K15:K16) -> 53.1 | ... V17: =SUM(V15:V16) -> 165.2576 | W17: =V17*(1+$Y$21) -> 163.60503 | X17: =W17*(1+$Y$21) -> 161.96898 | Y17: =X17*(1+$Y$21) -> 160.34929 | Z17: =Y17*(1+$Y$21) -> 158.74579 | AA17: =Z17*(1+$Y$21) -> 157.15834 | AB17: =AA17*(1+$Y$21) -> 155.58675 | AC17: =AB17*(1+$Y$21) -> 154.03088 | AD17: =AC17*(1+$Y$21) -> 152.49058 | ... IC17: =IB17*(1+$Y$21) -> 19.042689
C18: Shares | D18: 76.173115 | E18: 77.226502 | F18: 86.472611 | G18: 88.647339 | H18: 93.455077 | I18: 113.11878 | J18: 215.7416 | K18: 386.50019 | L18: 1351.8302 | M18: 1351.8302 | N18: 1351.8302 | O18: 1351.8302 | P18: 1351.8302 | Q18: 1351.8302 | R18: 1351.8302 | S18: 1351.8302 | T18: 1351.8302 | U18: 1351.8302 | V18: 1351.8302
C19: EPS | D19: =D17/D18 -> 3.1389027 | E19: =E17/E18 -> 3.9520112 | F19: =F17/F18 -> 4.1192234 | G19: =G17/G18 -> 3.1281255 | H19: =H17/H18 -> 3.8200172 | I19: =I17/I18 -> 4.2221107 | J19: =J17/J18 -> 0.8042028 | K19: =K17/K18 -> 0.13738674 | ... V19: =V17/V18 -> 0.12224731
X20: Discount | Y20: 0.09
C21: Revenue y/y | E21: =(E4-D4)/D4 -> 0.10684275 | F21: =(F4-E4)/E4 -> 0.21699917 | G21: =(G4-F4)/F4 -> 0.052625701 | H21: =(H4-G4)/G4 -> 0.13888173 | I21: =(I4-H4)/H4 -> 0.5704618 | J21: =(J4-I4)/I4 -> -0.0010126732 | K21: =(K4-J4)/J4 -> -0.088866268 | L21: =(L4-K4)/K4 -> -0.039093558 | ... V21: =(V4-U4)/U4 -> 0 | X21: TV | Y21: -0.01
C22: Gross margin | D22: =D6/D4 -> 0.14823451 | E22: =E6/E4 -> 0.15890491 | F22: =F6/F4 -> 0.16667597 | G22: =G6/G4 -> 0.154857 | H22: =H6/H4 -> 0.16522491 | I22: =I6/I4 -> 0.14650289 | J22: =J6/J4 -> 0.14455614 | K22: =K6/K4 -> 0.14936365 | ... V22: =V6/V4 -> 0.13 | X22: NPV | Y22: =NPV(Y20,M17:IC17) -> 1751.652
C23: EBIT margin | D23: =D12/D4 -> 0.037555608 | E23: =E12/E4 -> 0.043085287 | F23: =F12/F4 -> 0.039016569 | G23: =G12/G4 -> 0.029343559 | H23: =H12/H4 -> 0.038348416 | I23: =I12/I4 -> 0.032117419 | J23: =J12/J4 -> 0.019769267 | K23: =K12/K4 -> 0.015478219 | ... V23: =V12/V4 -> 0.010082986 | X23: S/O | Y23: 1351.8302
C24: ROE | D24: 0.161 | E24: 0.185 | F24: 0.145 | G24: 0.145 | H24: 0.076 | I24: 0.094 | J24: 0.032 | K24: 0.008 | X24: NPV/Share | Y24: =Y22/Y23 -> 1.2957633
X25: Opp/nedside | Y25: =(Y24-Modell!B4)/Modell!B4 -> -0.2287123
