Workbook

Sheet Info
A2: Americas
A20: April 2025 åpnet ELO Little Rock i Arkansas som sitt første produksjons i USA
A21: Prosjektet kostet 70 USDm
A22: Andre produksjonslinsje skal være klar H126
A23: Oktober 2025 bestemte ELO seg å invester yttligere 28 USDm i en tredje linje som skal starte 2027
A25: Q226: En av leverandøreen til ELO opplevde en seriøs hendelse ved Nippon Dynawave paper mill i Washington noe som vil påvirke tilbudet til Elopak i Americas
A26: Papp tilbudet vil grunnet dette være begrenset gjennom H226 og mulig inn i 2027
A33: Press releases:
A34: 05.05.26: Styreleder Dag Mejdell kjøper 15 000 aksjer på 36,8NOK

Sheet Modell
A3: Kapitalstruktur | C3: EUR million | D3: Q122 | E3: Q222 | F3: Q322 | G3: Q422 | H3: Q123 | I3: Q223 | J3: Q323 | K3: Q423 | L3: Q124 | M3: Q224 | N3: Q324 | O3: Q424 | P3: Q125 | Q3: Q225 | R3: Q325 | S3: Q425 | T3: Q126 | U3: Q226 | V3: Q326 | W3: Q426 | Z3: FY 2020 | AA3: FY 2021 | AB3: FY 2022 | AC3: FY 2023 | AD3: FY 2024 | AE3: FY 2025 | AF3: FY 2026 | AG3: FY 2027 | AH3: FY 2028 | AI3: FY 2029 | AJ3: FY 2030 | AK3: FY 2031 | AL3: FY 2032 | AM3: FY 2033 | AN3: FY 2034 | AO3: FY 2035
A4: Price | B4: 33.65 | C4: Revenues | H4: 283.393 | I4: 278.024 | J4: 283.46 | K4: 287.166 | L4: 291.923 | M4: 288.384 | N4: 292.804 | O4: 283.392 | P4: 310.24 | Q4: 289.7 | R4: 289.648 | S4: 316 | T4: 298.195 | U4: 303.877 | Z4: 908.773 | AA4: 940.246 | AB4: 1023.696 | AC4: 1132.043 | AD4: 1156.502 | AE4: 1205.588 | AF4: =AE4*1.01 -> 1217.6439 | AG4: =AF4*1.04 -> 1266.3496 | AH4: =AG4*1.05 -> 1329.6671 | AI4: =AH4*1.05 -> 1396.1505 | AJ4: =AI4*1.05 -> 1465.958 | AK4: =AJ4*1.05 -> 1539.2559 | AL4: =AK4*1.05 -> 1616.2187 | AM4: =AL4*1.05 -> 1697.0296 | AN4: =AM4*1.05 -> 1781.8811 | AO4: =AN4*1.05 -> 1870.9752
A5: S/O | B5: 269.21901 | C5: other revenue | H5: 0 | I5: 0 | J5: 0.033 | K5: 0.017 | L5: 0 | M5: 0 | N5: 0.024 | O5: 0.064 | P5: 0.081 | Q5: -0.079 | R5: 0.031 | S5: 0.015 | T5: 0 | U5: 0 | Z5: 5.221 | AA5: 0.007 | AB5: 0.157 | AC5: 0.145 | AD5: 0.089 | AE5: 0.049 | AF5: 0 | AG5: 0 | AH5: 0 | AI5: 0 | AJ5: 0 | AK5: 0 | AL5: 0 | AM5: 0 | AN5: 0 | AO5: 0
A6: MC NOKm | B6: =B4*B5 -> 9059.2198 | C6: Total revenue | D6: =SUM(D4:D5) -> 0 | E6: =SUM(E4:E5) -> 0 | F6: =SUM(F4:F5) -> 0 | G6: =SUM(G4:G5) -> 0 | H6: =SUM(H4:H5) -> 283.393 | I6: =SUM(I4:I5) -> 278.024 | J6: =SUM(J4:J5) -> 283.493 | K6: =SUM(K4:K5) -> 287.183 | ... U6: =SUM(U4:U5) -> 303.877 | X6: =SUM(T6:U6)*2 -> 1204.144 | Z6: =SUM(Z4:Z5) -> 913.994 | AA6: =SUM(AA4:AA5) -> 940.253 | AB6: =SUM(AB4:AB5) -> 1023.853 | AC6: =SUM(AC4:AC5) -> 1132.188 | AD6: =SUM(AD4:AD5) -> 1156.591 | AE6: =SUM(AE4:AE5) -> 1205.637 | AF6: =SUM(AF4:AF5) -> 1217.6439 | AG6: =SUM(AG4:AG5) -> 1266.3496 | ... AO6: =SUM(AO4:AO5) -> 1870.9752
A7: Cash NOKm | B7: 675.18 | C7: COGS | H7: -182.158 | I7: -174.973 | J7: -175.449 | K7: -187.216 | L7: -181.657 | M7: -178.44 | N7: -184.835 | O7: -174.821 | P7: -196.729 | Q7: -177.68 | R7: -173.582 | S7: -199.92 | T7: -187.226 | U7: -189.477 | Z7: -576.637 | AA7: -607.913 | AB7: -681.474 | AC7: -719.796 | AD7: -719.753 | AE7: -747.911 | AF7: =AF6*-0.625 -> -761.02742 | AG7: =AG6*-0.62 -> -785.13677 | AH7: =AH6*-0.62 -> -824.39361 | AI7: =AI6*-0.62 -> -865.61329 | AJ7: =AJ6*-0.62 -> -908.89396 | AK7: =AK6*-0.62 -> -954.33866 | AL7: =AL6*-0.62 -> -1002.0556 | AM7: =AM6*-0.62 -> -1052.1584 | AN7: =AN6*-0.62 -> -1104.7663 | AO7: =AO6*-0.62 -> -1160.0046
A8: Debt NOKm | B8: 3549.67 | C8: Gross profit | D8: =SUM(D6:D7) -> 0 | E8: =SUM(E6:E7) -> 0 | F8: =SUM(F6:F7) -> 0 | G8: =SUM(G6:G7) -> 0 | H8: =SUM(H6:H7) -> 101.235 | I8: =SUM(I6:I7) -> 103.051 | J8: =SUM(J6:J7) -> 108.044 | K8: =SUM(K6:K7) -> 99.967 | ... U8: =SUM(U6:U7) -> 114.4 | Z8: =SUM(Z6:Z7) -> 337.357 | AA8: =SUM(AA6:AA7) -> 332.34 | AB8: =SUM(AB6:AB7) -> 342.379 | AC8: =SUM(AC6:AC7) -> 412.392 | AD8: =SUM(AD6:AD7) -> 436.838 | AE8: =SUM(AE6:AE7) -> 457.726 | AF8: =SUM(AF6:AF7) -> 456.61646 | AG8: =SUM(AG6:AG7) -> 481.21286 | ... AO8: =SUM(AO6:AO7) -> 710.97056
A9: EV NOKm | B9: =B6-B7+B8 -> 11933.71 | C9: Payroll expense | H9: -47.054 | I9: -47.424 | J9: -46.517 | K9: -48.627 | L9: -49.854 | M9: -51.419 | N9: -49.82 | O9: -52.149 | P9: -53.476 | Q9: -52.211 | R9: -51.57 | S9: -54.026 | T9: -55.617 | U9: -56.394 | Z9: -168.573 | AA9: -171.664 | AB9: -176.721 | AC9: -189.623 | AD9: -203.243 | AE9: -211.284 | AF9: =AE9*1.02 -> -215.50968 | AG9: =AF9*1.03 -> -221.97497 | AH9: =AG9*1.04 -> -230.85397 | AI9: =AH9*1.04 -> -240.08813 | AJ9: =AI9*1.04 -> -249.69165 | AK9: =AJ9*1.04 -> -259.67932 | AL9: =AK9*1.04 -> -270.06649 | AM9: =AL9*1.04 -> -280.86915 | AN9: =AM9*1.04 -> -292.10392 | AO9: =AN9*1.04 -> -303.78807
C10: D/A | H10: -15.223 | I10: -14.77 | J10: -15.658 | K10: -14.495 | L10: -15.885 | M10: -14.916 | N10: -16.567 | O10: -17.008 | P10: -15.895 | Q10: -15.933 | R10: -17.759 | S10: -18.552 | T10: -16.416 | U10: -17 | Z10: -52.209 | AA10: -56.45 | AB10: -61.528 | AC10: -60.147 | AD10: -64.377 | AE10: -68.139 | AF10: =AE10*1.02 -> -69.50178 | AG10: =AF10*1.04 -> -72.281851 | AH10: =AG10*1.04 -> -75.173125 | AI10: =AH10*1.04 -> -78.18005 | AJ10: =AI10*1.04 -> -81.307252 | AK10: =AJ10*1.04 -> -84.559542 | AL10: =AK10*1.04 -> -87.941924 | AM10: =AL10*1.04 -> -91.459601 | AN10: =AM10*1.04 -> -95.117985 | AO10: =AN10*1.04 -> -98.922704
C11: Impairment | H11: -0.077 | I11: -0.091 | J11: -0.4 | K11: -0.618 | L11: -0.16 | M11: -0.415 | N11: -0.097 | O11: -1.897 | P11: -0.037 | Q11: -1.034 | R11: -0.176 | S11: -0.003 | T11: 0 | U11: 0 | Z11: 0 | AA11: 0 | AB11: -6.599 | AC11: -1.186 | AD11: -2.568 | AE11: -1.248 | AF11: =AE11*1.02 -> -1.27296 | AG11: =AF11*1.04 -> -1.3238784 | AH11: =AG11*1.04 -> -1.3768335 | AI11: =AH11*1.04 -> -1.4319069 | AJ11: =AI11*1.04 -> -1.4891832 | AK11: =AJ11*1.04 -> -1.5487505 | AL11: =AK11*1.04 -> -1.6107005 | AM11: =AL11*1.04 -> -1.6751285 | AN11: =AM11*1.04 -> -1.7421337 | AO11: =AN11*1.04 -> -1.811819
A12: EUR/NOK | B12: 10.9 | C12: other opex | H12: -14.223 | I12: -15.329 | J12: -15.094 | K12: -13.974 | L12: -16.523 | M12: -17.378 | N12: -14.022 | O12: -18.372 | P12: -18.004 | Q12: -16.026 | R12: -16.814 | S12: -17.768 | T12: -17.67 | U12: -16.269 | Z12: -45.918 | AA12: -50.149 | AB12: -55.757 | AC12: -58.658 | AD12: -67.195 | AE12: -68.611 | AF12: =AE12*1.02 -> -69.98322 | AG12: =AF12*1.04 -> -72.782549 | AH12: =AG12*1.04 -> -75.693851 | AI12: =AH12*1.04 -> -78.721605 | AJ12: =AI12*1.04 -> -81.870469 | AK12: =AJ12*1.04 -> -85.145288 | AL12: =AK12*1.04 -> -88.551099 | AM12: =AL12*1.04 -> -92.093143 | AN12: =AM12*1.04 -> -95.776869 | AO12: =AN12*1.04 -> -99.607944
C13: Operating profit (EBIT) | D13: =SUM(D8:D12) -> 0 | E13: =SUM(E8:E12) -> 0 | F13: =SUM(F8:F12) -> 0 | G13: =SUM(G8:G12) -> 0 | H13: =SUM(H8:H12) -> 24.658 | I13: =SUM(I8:I12) -> 25.437 | J13: =SUM(J8:J12) -> 30.375 | K13: =SUM(K8:K12) -> 22.253 | ... U13: =SUM(U8:U12) -> 24.737 | Z13: =SUM(Z8:Z12) -> 70.657 | AA13: =SUM(AA8:AA12) -> 54.077 | AB13: =SUM(AB8:AB12) -> 41.774 | AC13: =SUM(AC8:AC12) -> 102.778 | AD13: =SUM(AD8:AD12) -> 99.455 | AE13: =SUM(AE8:AE12) -> 108.444 | AF13: =SUM(AF8:AF12) -> 100.34882 | AG13: =SUM(AG8:AG12) -> 112.84961 | ... AO13: =SUM(AO8:AO12) -> 206.84002
A14: Gearing | B14: =(B8-B7)/(U29*B12) -> 1.4832097 | C14: Net financials | H14: -5 | I14: 0 | J14: -5.543 | K14: -9.695 | L14: -2 | M14: -1 | N14: -11.517 | O14: -1.708 | P14: -6.303 | Q14: -15.222 | R14: -4.024 | S14: -4.153 | T14: -1.274 | U14: -5 | Z14: -13.602 | AA14: -7.669 | AB14: 0.255 | AC14: -24.755 | AD14: -20.4 | AE14: -29.703 | AF14: -30 | AG14: -30 | AH14: -30 | AI14: -30 | AJ14: -30 | AK14: -30 | AL14: -30 | AM14: -30 | AN14: -30 | AO14: -30
C15: Share from JV | H15: -2 | I15: 0 | J15: 1.894 | K15: 2.753 | L15: 0 | M15: 0 | N15: 2.127 | O15: 2.716 | P15: 2.535 | Q15: 0.976 | R15: 1.431 | S15: 1.877 | T15: 2 | U15: 1.178 | Z15: 3.155 | AA15: 3.575 | AB15: 4.378 | AC15: 6.855 | AD15: 9.696 | AE15: 6.819 | AF15: 7 | AG15: 7 | AH15: 7 | AI15: 7 | AJ15: 7 | AK15: 7 | AL15: 7 | AM15: 7 | AN15: 7 | AO15: 7
C16: PTP | D16: =SUM(D13:D15) -> 0 | E16: =SUM(E13:E15) -> 0 | F16: =SUM(F13:F15) -> 0 | G16: =SUM(G13:G15) -> 0 | H16: =SUM(H13:H15) -> 17.658 | I16: =SUM(I13:I15) -> 25.437 | J16: =SUM(J13:J15) -> 26.726 | K16: =SUM(K13:K15) -> 15.311 | ... U16: =SUM(U13:U15) -> 20.915 | Z16: =SUM(Z13:Z15) -> 60.21 | AA16: =SUM(AA13:AA15) -> 49.983 | AB16: =SUM(AB13:AB15) -> 46.407 | AC16: =SUM(AC13:AC15) -> 84.878 | AD16: =SUM(AD13:AD15) -> 88.751 | AE16: =SUM(AE13:AE15) -> 85.56 | AF16: =SUM(AF13:AF15) -> 77.348815 | AG16: =SUM(AG13:AG15) -> 89.849613 | ... AO16: =SUM(AO13:AO15) -> 183.84002
C17: tax | H17: -1.947 | I17: -4.275 | J17: -7.348 | K17: -1.843 | L17: -4.294 | M17: -8.561 | N17: -1.639 | O17: -12.71 | P17: -5.128 | Q17: -3.107 | R17: -9 | S17: -6.836 | T17: -5.149 | U17: -4.873 | Z17: -12.381 | AA17: -16.173 | AB17: -12.188 | AC17: -15.513 | AD17: -27.203 | AE17: -24.071 | AF17: =AF16*-0.22 -> -17.016739 | AG17: =AG16*-0.22 -> -19.766915 | AH17: =AH16*-0.22 -> -21.81866 | AI17: =AI16*-0.22 -> -24.005408 | AJ17: =AJ16*-0.22 -> -26.335206 | AK17: =AK16*-0.22 -> -28.816555 | AL17: =AL16*-0.22 -> -31.458435 | AM17: =AM16*-0.22 -> -34.270331 | ... AO17: =AO16*-0.22 -> -40.444804
C18: Net income | D18: =SUM(D16:D17) -> 0 | E18: =SUM(E16:E17) -> 0 | F18: =SUM(F16:F17) -> 0 | G18: =SUM(G16:G17) -> 0 | H18: =SUM(H16:H17) -> 15.711 | I18: =SUM(I16:I17) -> 21.162 | J18: =SUM(J16:J17) -> 19.378 | K18: =SUM(K16:K17) -> 13.468 | ... U18: =SUM(U16:U17) -> 16.042 | Z18: =SUM(Z16:Z17) -> 47.829 | AA18: =SUM(AA16:AA17) -> 33.81 | AB18: =SUM(AB16:AB17) -> 34.219 | AC18: =SUM(AC16:AC17) -> 69.365 | AD18: =SUM(AD16:AD17) -> 61.548 | AE18: =SUM(AE16:AE17) -> 61.489 | AF18: =SUM(AF16:AF17) -> 60.332076 | AG18: =SUM(AG16:AG17) -> 70.082698 | ... AO18: =SUM(AO16:AO17) -> 143.39522 | AP18: =AO18*(1+AR22) -> 141.96126 | AQ18: =AP18*(1+AS22) -> 141.96126 | AR18: =AQ18*(1+AT22) -> 141.96126 | AS18: =AR18*(1+AU22) -> 141.96126 | AT18: =AS18*(1+AV22) -> 141.96126 | AU18: =AT18*(1+AW22) -> 141.96126 | AV18: =AU18*(1+AX22) -> 141.96126 | AW18: =AV18*(1+AY22) -> 141.96126 | ... IQ18: =IP18*(1+IS22) -> 141.96126
C19: Shares | D19: 269.21901 | E19: 269.21901 | F19: 269.21901 | G19: 269.21901 | H19: 269.21901 | I19: 269.21901 | J19: 269.21901 | K19: 269.21901 | L19: 269.21901 | M19: 269.21901 | N19: 269.21901 | O19: 269.21901 | P19: 269.21901 | Q19: 269.21901 | R19: 269.21901 | S19: 269.21901 | T19: 269.21901 | U19: 269.21901 | Z19: 269.21901 | AA19: 269.21901 | AB19: 269.21901 | AC19: 269.21901 | AD19: 269.21901 | AE19: 269.21901 | AF19: 269.21901 | AG19: 269.21901 | AH19: 269.21901 | AI19: 269.21901 | AJ19: 269.21901 | AK19: 269.21901 | AL19: 269.21901 | AM19: 269.21901 | AN19: 269.21901 | AO19: 269.21901
C20: EPS | D20: =D18/D19 -> 0 | E20: =E18/E19 -> 0 | F20: =F18/F19 -> 0 | G20: =G18/G19 -> 0 | H20: =H18/H19 -> 0.058357691 | I20: =I18/I19 -> 0.078605146 | J20: =J18/J19 -> 0.071978571 | K20: =K18/K19 -> 0.050026184 | ... U20: =U18/U19 -> 0.059587173 | Z20: =Z18/Z19 -> 0.17765833 | AA20: =AA18/AA19 -> 0.12558548 | AB20: =AB18/AB19 -> 0.12710469 | AC20: =AC18/AC19 -> 0.25765268 | AD20: =AD18/AD19 -> 0.22861684 | AE20: =AE18/AE19 -> 0.22839769 | AF20: =AF18/AF19 -> 0.22410035 | AG20: =AG18/AG19 -> 0.26031853 | ... AO20: =AO18/AO19 -> 0.53263406
AQ21: Discount | AR21: 0.08
C22: Revenue y/y | H22: =(H6-D6)/D6 -> #DIV/0! | I22: =(I6-E6)/E6 -> #DIV/0! | J22: =(J6-F6)/F6 -> #DIV/0! | K22: =(K6-G6)/G6 -> #DIV/0! | L22: =(L6-H6)/H6 -> 0.030099544 | M22: =(M6-I6)/I6 -> 0.03726297 | N22: =(N6-J6)/J6 -> 0.032928503 | O22: =(O6-K6)/K6 -> -0.012977788 | ... W22: =(W6-S6)/S6 -> -1 | AA22: =(AA6-Z6)/Z6 -> 0.028729948 | AB22: =(AB6-AA6)/AA6 -> 0.08891224 | AC22: =(AC6-AB6)/AB6 -> 0.10581109 | AD22: =(AD6-AC6)/AC6 -> 0.021553841 | AE22: =(AE6-AD6)/AD6 -> 0.042405656 | AF22: =(AF6-AE6)/AE6 -> 0.0099589512 | AG22: =(AG6-AF6)/AF6 -> 0.04 | AH22: =(AH6-AG6)/AG6 -> 0.05 | ... AO22: =(AO6-AN6)/AN6 -> 0.05 | AQ22: TV | AR22: -0.01
C23: Gross margin | D23: =D8/D6 -> #DIV/0! | E23: =E8/E6 -> #DIV/0! | F23: =F8/F6 -> #DIV/0! | G23: =G8/G6 -> #DIV/0! | H23: =H8/H6 -> 0.35722477 | I23: =I8/I6 -> 0.37065505 | J23: =J8/J6 -> 0.38111699 | K23: =K8/K6 -> 0.34809512 | ... W23: =W8/W6 -> #DIV/0! | Z23: =Z8/Z6 -> 0.36910199 | AA23: =AA8/AA6 -> 0.35345806 | AB23: =AB8/AB6 -> 0.3344025 | AC23: =AC8/AC6 -> 0.36424339 | AD23: =AD8/AD6 -> 0.37769445 | AE23: =AE8/AE6 -> 0.3796549 | AF23: =AF8/AF6 -> 0.375 | AG23: =AG8/AG6 -> 0.38 | ... AO23: =AO8/AO6 -> 0.38 | AQ23: NPV | AR23: =NPV(AR21,AF18:IQ18)*B12 -> 15837.923
C24: EBIT margin | D24: =D13/D6 -> #DIV/0! | E24: =E13/E6 -> #DIV/0! | F24: =F13/F6 -> #DIV/0! | G24: =G13/G6 -> #DIV/0! | H24: =H13/H6 -> 0.087009912 | I24: =I13/I6 -> 0.091492101 | J24: =J13/J6 -> 0.1071455 | K24: =K13/K6 -> 0.077487177 | ... W24: =W13/W6 -> #DIV/0! | Z24: =Z13/Z6 -> 0.077305759 | AA24: =AA13/AA6 -> 0.057513244 | AB24: =AB13/AB6 -> 0.040800779 | AC24: =AC13/AC6 -> 0.09077821 | AD24: =AD13/AD6 -> 0.085989775 | AE24: =AE13/AE6 -> 0.089947472 | AF24: =AF13/AF6 -> 0.082412285 | AG24: =AG13/AG6 -> 0.089114104 | ... AO24: =AO13/AO6 -> 0.11055199 | AQ24: S/O | AR24: 269.21901
C25: ROCE | AB25: 0.07 | AC25: 0.167 | AD25: 0.159 | AE25: 0.157 | AQ25: NPV/Share | AR25: =AR23/AR24 -> 58.829141
AQ26: Opp/nedside | AR26: =(AR25-B4)/B4 -> 0.74826572
C27: EBITDA | L27: 46.1 | M27: 43.8 | N27: 45.4 | O27: 40.8 | P27: 44.6 | Q27: 44.7 | R27: 49 | S27: 46.2 | T27: 39.7 | U27: 42.9 | AA27: 121 | AB27: 119 | AC27: 170.9 | AD27: 176 | AE27: 185
C28: EBITDA margin | D28: =D27/D6 -> #DIV/0! | E28: =E27/E6 -> #DIV/0! | F28: =F27/F6 -> #DIV/0! | G28: =G27/G6 -> #DIV/0! | H28: =H27/H6 -> 0 | I28: =I27/I6 -> 0 | J28: =J27/J6 -> 0 | K28: =K27/K6 -> 0 | ... W28: =W27/W6 -> #DIV/0! | Z28: =Z27/Z6 -> 0 | AA28: =AA27/AA6 -> 0.12868877 | AB28: =AB27/AB6 -> 0.11622762 | AC28: =AC27/AC6 -> 0.15094666 | AD28: =AD27/AD6 -> 0.15217134 | AE28: =AE27/AE6 -> 0.15344585 | AF28: =AF27/AF6 -> 0
C29: EBITDA LTM | G29: =SUM(D27:G27) -> 0 | H29: =SUM(E27:H27) -> 0 | I29: =SUM(F27:I27) -> 0 | J29: =SUM(G27:J27) -> 0 | K29: =SUM(H27:K27) -> 0 | L29: =SUM(I27:L27) -> 46.1 | M29: =SUM(J27:M27) -> 89.9 | N29: =SUM(K27:N27) -> 135.3 | ... W29: =SUM(T27:W27) -> 82.6
C31: Balanse EURm
C32: Development cost and other intangible assets | L32: 59.532 | M32: 57.678 | N32: 54.201 | O32: 52.915 | P32: 50.731 | Q32: 48.218 | R32: 45.649 | S32: 43.149 | T32: 41.41 | U32: 39.432 | Z32: 61.211 | AA32: 56.862 | AB32: 71.331 | AC32: 62.3 | AD32: 52.915 | AE32: 43.149
C33: Deferred tax assets | L33: 21.266 | M33: 20.367 | N33: 19.883 | O33: 22.295 | P33: 21.876 | Q33: 21.262 | R33: 20.864 | S33: 16.092 | T33: 14.958 | U33: 15.564 | Z33: 23.544 | AA33: 21.64 | AB33: 22.414 | AC33: 22.883 | AD33: 22.295 | AE33: 16.092
C34: Goodwill | L34: 105.465 | M34: 106.791 | N34: 105.947 | O34: 107.584 | P34: 108.861 | Q34: 107.065 | R34: 106.753 | S34: 106.919 | T34: 106.271 | U34: 106.367 | Z34: 52.291 | AA34: 51.866 | AB34: 104.958 | AC34: 106.061 | AD34: 107.584 | AE34: 106.919
C35: PP&E | L35: 205.19 | M35: 212.158 | N35: 228.298 | O35: 265.013 | P35: 278.889 | Q35: 272.453 | R35: 270.568 | S35: 282.192 | T35: 302.306 | U35: 308.125 | Z35: 188.429 | AA35: 186.426 | AB35: 201.975 | AC35: 202.934 | AD35: 265.013 | AE35: 282.192
C36: Right-of-use assets | L36: 89.397 | M36: 94.271 | N36: 91.841 | O36: 91.979 | P36: 88.451 | Q36: 89.726 | R36: 85.669 | S36: 84.464 | T36: 94.049 | U36: 94.257 | Z36: 69.27 | AA36: 62.952 | AB36: 76.784 | AC36: 86.37 | AD36: 91.979 | AE36: 84.464
C37: Investment in JV | L37: 41.3 | M37: 41.306 | N37: 39.401 | O37: 37.793 | P37: 38.783 | Q37: 39.474 | R37: 41.193 | S37: 38.08 | T37: 37.701 | U37: 40.438 | Z37: 26.956 | AA37: 27.527 | AB37: 34.673 | AC37: 37.709 | AD37: 37.793 | AE37: 38.08
C38: Other non-current asset | L38: 14.256 | M38: 16.325 | N38: 14.105 | O38: 13.111 | P38: 18.991 | Q38: 14.998 | R38: 14.573 | S38: 14.847 | T38: 27.646 | U38: 21.293 | Z38: 14.517 | AA38: 13.501 | AB38: 19.841 | AC38: 14.892 | AD38: 13.111 | AE38: 14.846
C39: Inventory | L39: 198.792 | M39: 199.367 | N39: 191.077 | O39: 197.934 | P39: 206.535 | Q39: 194.346 | R39: 193.416 | S39: 178.299 | T39: 171.899 | U39: 167.058 | Z39: 135.523 | AA39: 145.115 | AB39: 187.207 | AC39: 192.189 | AD39: 197.934 | AE39: 178.299
C40: Trade receivables | L40: 113.685 | M40: 106.597 | N40: 114.76 | O40: 120.226 | P40: 122.184 | Q40: 110.574 | R40: 111.727 | S40: 113.501 | T40: 118.161 | U40: 113.5 | Z40: 77.958 | AA40: 91.533 | AB40: 102.197 | AC40: 110.243 | AD40: 120.226 | AE40: 113.501
C41: Other current assets | L41: 112.123 | M41: 116.46 | N41: 128.872 | O41: 118.508 | P41: 122.229 | Q41: 117.284 | R41: 125.531 | S41: 124.416 | T41: 124.23 | U41: 133.539 | Z41: 92.981 | AA41: 101.595 | AB41: 109.214 | AC41: 113.72 | AD41: 118.508 | AE41: 124.416
C42: Cash | L42: 19.895 | M42: 18.052 | N42: 21.325 | O42: 28.052 | P42: 31.017 | Q42: 34.131 | R42: 39.077 | S42: 62.168 | T42: 39.394 | U42: 44.575 | Z42: 6.443 | AA42: 24.262 | AB42: 25.883 | AC42: 13.308 | AD42: 28.052 | AE42: 62.168
C43: Total assets | L43: =SUM(L32:L42) -> 980.901 | M43: =SUM(M32:M42) -> 989.372 | N43: =SUM(N32:N42) -> 1009.71 | O43: =SUM(O32:O42) -> 1055.41 | P43: =SUM(P32:P42) -> 1088.547 | Q43: =SUM(Q32:Q42) -> 1049.531 | R43: =SUM(R32:R42) -> 1055.02 | S43: =SUM(S32:S42) -> 1064.127 | ... U43: =SUM(U32:U42) -> 1084.148 | Z43: =SUM(Z32:Z42) -> 749.123 | AA43: =SUM(AA32:AA42) -> 783.279 | AB43: =SUM(AB32:AB42) -> 956.477 | AC43: =SUM(AC32:AC42) -> 962.609 | AD43: =SUM(AD32:AD42) -> 1055.41 | AE43: =SUM(AE32:AE42) -> 1064.126
C44: Elopak shareholders | L44: 332.043 | M44: 314.969 | N44: 319.432 | O44: 342.052 | P44: 352.542 | Q44: 324.539 | R44: 342.609 | S44: 338.85 | T44: 360.804 | U44: 350.311 | Z44: 185.444 | AA44: 269.054 | AB44: 259.491 | AC44: 306.253 | AD44: 342.052 | AE44: 338.85
C45: Non-controlling interests | L45: 9.56 | M45: 10.315 | N45: 10.225 | O45: 10.6 | P45: 10.586 | Q45: 9.844 | R45: 9.543 | S45: 8.881 | T45: 8.496 | U45: 8.853 | Z45: 0 | AA45: 0 | AB45: 8.477 | AC45: 9.043 | AD45: 10.6 | AE45: 8.881
C46: Total equity | L46: =SUM(L44:L45) -> 341.603 | M46: =SUM(M44:M45) -> 325.284 | N46: =SUM(N44:N45) -> 329.657 | O46: =SUM(O44:O45) -> 352.652 | P46: =SUM(P44:P45) -> 363.128 | Q46: =SUM(Q44:Q45) -> 334.383 | R46: =SUM(R44:R45) -> 352.152 | S46: =SUM(S44:S45) -> 347.731 | ... U46: =SUM(U44:U45) -> 359.164 | Z46: =SUM(Z44:Z45) -> 185.444 | AA46: =SUM(AA44:AA45) -> 269.054 | AB46: =SUM(AB44:AB45) -> 267.968 | AC46: =SUM(AC44:AC45) -> 315.296 | AD46: =SUM(AD44:AD45) -> 352.652 | AE46: =SUM(AE44:AE45) -> 347.731
C47: Pension liabilties | L47: 2.398 | M47: 2.422 | N47: 2.314 | O47: 2.221 | P47: 2.238 | Q47: 2.109 | R47: 2.093 | S47: 2.643 | T47: 2.714 | U47: 2.665 | Z47: 2.554 | AA47: 2.563 | AB47: 2.668 | AC47: 2.502 | AD47: 2.221 | AE47: 2.643
C48: Deferred tax liabilites | L48: 13.968 | M48: 13.905 | N48: 13.495 | O48: 14.578 | P48: 14.157 | Q48: 13.62 | R48: 13.378 | S48: 9.582 | T48: 9.354 | U48: 9.149 | Z48: 11.994 | AA48: 11.488 | AB48: 17.24 | AC48: 14.041 | AD48: 14.578 | AE48: 9.582
C49: Non-current Interest bearing | L49: 204.533 | M49: 217.744 | N49: 232.708 | O49: 259.74 | P49: 288.006 | Q49: 297.941 | R49: 280.544 | S49: 322.382 | T49: 309.512 | U49: 315.362 | Z49: 213.135 | AA49: 169.433 | AB49: 304.033 | AC49: 224.433 | AD49: 259.74 | AE49: 322.382
C50: Non-current lease lia | L50: 80.924 | M50: 85.386 | N50: 83.088 | O50: 83.219 | P50: 79.842 | Q50: 81.357 | R50: 78.324 | S50: 79.141 | T50: 88.553 | U50: 88.75 | Z50: 69.09 | AA50: 62.342 | AB50: 73.536 | AC50: 78.424 | AD50: 83.219 | AE50: 79.141
C51: Other non-current lia | L51: 4.293 | M51: 4.257 | N51: 8.971 | O51: 9.216 | P51: 3.922 | Q51: 10.39 | R51: 7.838 | S51: 9.145 | T51: 2.827 | U51: 3.879 | Z51: 5.982 | AA51: 2.9 | AB51: 1.867 | AC51: 5.033 | AD51: 9.216 | AE51: 9.145
C52: Current interest bearing lia | L52: 23.184 | M52: 29.682 | N52: 52.908 | O52: 30.383 | P52: 41.674 | Q52: 37.921 | R52: 29.927 | S52: 3.575 | T52: 15.334 | U52: 22.098 | Z52: 15.552 | AA52: 14.42 | AB52: 0 | AC52: 0 | AD52: 30.383 | AE52: 3.575
C53: Current non-interest bearing lia | L53: 45.438 | M53: 44.743 | N53: 45.427 | O53: 39.782 | P53: 45.387 | Q53: 41.203 | R53: 41.465 | S53: 40.467 | T53: 43.158 | U53: 48.84 | Z53: 0 | AA53: 0 | AB53: 0 | AC53: 0 | AD53: 39.782 | AE53: 40.467
C54: Trade payables | L54: 84.069 | M54: 87.832 | N54: 70.951 | O54: 73.304 | P54: 70.586 | Q54: 56.716 | R54: 70.122 | S54: 90.356 | T54: 73.382 | U54: 67.274 | Z54: 114.273 | AA54: 119.574 | AB54: 0 | AC54: 0 | AD54: 73.304 | AE54: 90.356
C55: taxes payable | L55: 0.938 | M55: 0.331 | N55: 0.921 | O55: 5.294 | P55: 8.895 | Q55: 9.348 | R55: 13.263 | S55: 4.837 | T55: 6.52 | U55: 9.65 | Z55: 8.978 | AA55: 4.335 | AB55: 0 | AC55: 0 | AD55: 5.294 | AE55: 4.837
C56: Public duties payable | L56: 26.031 | M56: 24.533 | N56: 23.441 | O56: 25.952 | P56: 27.798 | Q56: 26.151 | R56: 24.069 | S56: 26.843 | T56: 28.105 | U56: 26.452 | Z56: 20.125 | AA56: 24.077 | AB56: 0 | AC56: 0 | AD56: 25.952 | AE56: 26.843
C57: Current lease lia | L57: 24.019 | M57: 22.806 | N57: 22.973 | O57: 23.312 | P57: 23.12 | Q57: 22.2 | R57: 21.599 | S57: 21.928 | T57: 22.85 | U57: 23.238 | Z57: 19.085 | AA57: 18.261 | AB57: 0 | AC57: 0 | AD57: 23.312 | AE57: 21.928
C58: Other current lia | L58: 129.502 | M58: 130.449 | N58: 122.858 | O58: 135.756 | P58: 119.794 | Q58: 116.193 | R58: 120.246 | S58: 105.496 | T58: 106.416 | U58: 107.628 | Z58: 82.911 | AA58: 84.832 | AB58: 289.167 | AC58: 322.88 | AD58: 135.756 | AE58: 105.496
C59: Total debt | L59: =SUM(L47:L58) -> 639.297 | M59: =SUM(M47:M58) -> 664.09 | N59: =SUM(N47:N58) -> 680.055 | O59: =SUM(O47:O58) -> 702.757 | P59: =SUM(P47:P58) -> 725.419 | Q59: =SUM(Q47:Q58) -> 715.149 | R59: =SUM(R47:R58) -> 702.868 | S59: =SUM(S47:S58) -> 716.395 | ... U59: =SUM(U47:U58) -> 724.985 | Z59: =SUM(Z47:Z58) -> 563.679 | AA59: =SUM(AA47:AA58) -> 514.225 | AB59: =SUM(AB47:AB58) -> 688.511 | AC59: =SUM(AC47:AC58) -> 647.313 | AD59: =SUM(AD47:AD58) -> 702.757 | AE59: =SUM(AE47:AE58) -> 716.395
C60: Total E/D | L60: =L46+L59 -> 980.9 | M60: =M46+M59 -> 989.374 | N60: =N46+N59 -> 1009.712 | O60: =O46+O59 -> 1055.409 | P60: =P46+P59 -> 1088.547 | Q60: =Q46+Q59 -> 1049.532 | R60: =R46+R59 -> 1055.02 | S60: =S46+S59 -> 1064.126 | ... U60: =U46+U59 -> 1084.149 | Z60: =Z46+Z59 -> 749.123 | AA60: =AA46+AA59 -> 783.279 | AB60: =AB46+AB59 -> 956.479 | AC60: =AC46+AC59 -> 962.609 | AD60: =AD46+AD59 -> 1055.409 | AE60: =AE46+AE59 -> 1064.126
C62: Cash flow EURm
C63: Model PTP | D63: =D16 -> 0 | E63: =E16 -> 0 | F63: =F16 -> 0 | G63: =G16 -> 0 | H63: =H16 -> 17.658 | I63: =I16 -> 25.437 | J63: =J16 -> 26.726 | K63: =K16 -> 15.311 | ... U63: =U16 -> 20.915 | Z63: =Z16 -> 60.21 | AA63: =AA16 -> 49.983 | AB63: =AB16 -> 46.407 | AC63: =AC16 -> 84.878 | AD63: =AD16 -> 88.751 | AE63: =AE16 -> 85.56
C64: Reported PTP | L64: 26.134 | M64: 25.076 | N64: 17.196 | O64: 20.951 | P64: 22.413 | Q64: 12.492 | R64: 27.185 | S64: 23.47 | T64: 21.986 | U64: 20.848 | Z64: 60.209 | AA64: 49.982 | AB64: 23.583 | AC64: 83.54 | AD64: 89.356 | AE64: 85.561
C65: Interest on borrowings | L65: 2.609 | M65: 4.174 | N65: 4.214 | O65: 4.307 | P65: 4.439 | Q65: 4.629 | R65: 4.52 | S65: 4.788 | T65: 4.875 | U65: 5.514 | Z65: 5.897 | AA65: 1.553 | AB65: 5.658 | AC65: 11.303 | AD65: 15.304 | AE65: 18.377
C66: Lease liablity interst | L66: 1.882 | M66: 2.004 | N66: 2.003 | O66: 2.004 | P66: 1.97 | Q66: 1.929 | R66: 1.897 | S66: 1.872 | T66: 1.987 | U66: 2.09 | Z66: 5.184 | AA66: 4.773 | AB66: 4.575 | AC66: 6.566 | AD66: 7.892 | AE66: 7.667
C67: D/A/I | L67: 16.044 | M67: 15.331 | N67: 16.664 | O67: 18.905 | P67: 15.932 | Q67: 16.967 | R67: 17.935 | S67: 18.555 | T67: 16.44 | U67: 17.011 | Z67: 52.209 | AA67: 56.45 | AB67: 76.118 | AC67: 61.332 | AD67: 66.945 | AE67: 69.388
C68: Fair value of financial assets/liabilities | L68: 2.206 | M68: -5.586 | N68: 6.981 | O68: -1.883 | P68: -9.663 | Q68: 10.399 | R68: -3.673 | S68: 1.291 | T68: -20.841 | U68: 2.772 | Z68: 0.332 | AA68: 0.5 | AB68: 0.5 | AC68: -0.399 | AD68: 1.719 | AE68: -1.645
C69: Net unrealized currency | L69: -1.482 | M69: 1.98 | N69: -2.842 | O69: -2.214 | P69: 10.738 | Q69: -2.191 | R69: 0.382 | S69: -4.065 | T69: 15.115 | U69: -2.11 | Z69: -3.951 | AA69: -2.123 | AB69: 2.297 | AC69: -0.174 | AD69: -4.558 | AE69: 4.864
C70: Income from JV Net financial sale of non-current assets | L70: -2.239 | M70: -2.605 | N70: -2.127 | O70: -2.67 | P70: -2.522 | Q70: -0.976 | R70: -1.436 | S70: -1.776 | T70: -2.017 | U70: -1.178 | Z70: -8.375 | AA70: -3.569 | AB70: -4.241 | AC70: -6.868 | AD70: -9.64 | AE70: -6.71
C71: Income tax paid | L71: -11.071 | M71: -5.799 | N71: -5.243 | O71: -5.185 | P71: -4.156 | Q71: -4.778 | R71: -7.743 | S71: -8.944 | T71: -3.539 | U71: -6.496 | Z71: -11.508 | AA71: -19.122 | AB71: -13.683 | AC71: -14.27 | AD71: -27.299 | AE71: -25.621
C72: WC | L72: -4.771 | M72: 13.655 | N72: -25.284 | O72: 10.975 | P72: -34.006 | Q72: 4.252 | R72: 15.845 | S72: 27.504 | T72: -14.226 | U72: =5.302+7.481+5.662-6.508+5.682-1.236-0.043 -> 16.34 | Z72: 3.845 | AA72: -15.244 | AB72: -69.713 | AC72: 16.159 | AD72: -0.454 | AE72: 19.198
C73: CFFO | D73: =SUM(D64:D72) -> 0 | E73: =SUM(E64:E72) -> 0 | F73: =SUM(F64:F72) -> 0 | G73: =SUM(G64:G72) -> 0 | H73: =SUM(H64:H72) -> 0 | I73: =SUM(I64:I72) -> 0 | J73: =SUM(J64:J72) -> 0 | K73: =SUM(K64:K72) -> 0 | ... U73: =SUM(U64:U72) -> 54.791 | Z73: =SUM(Z64:Z72) -> 103.842 | AA73: =SUM(AA64:AA72) -> 73.2 | AB73: =SUM(AB64:AB72) -> 25.094 | AC73: =SUM(AC64:AC72) -> 157.189 | AD73: =SUM(AD64:AD72) -> 139.265 | AE73: =SUM(AE64:AE72) -> 171.079
C75: Capex | L75: -10.584 | M75: -28.643 | N75: -28.872 | O75: -41.002 | P75: -25.033 | Q75: -20.766 | R75: -11.826 | S75: -28.026 | T75: -15.805 | U75: -27.906 | Z75: -50.152 | AA75: -37.381 | AB75: -43.714 | AC75: -40.774 | AD75: -109.101 | AE75: -85.651
C76: Proceeds from sale of non-current assets | L76: 0 | M76: 0 | N76: 0 | O76: 0 | P76: 0 | Q76: 0 | R76: 0 | S76: 0.009 | T76: 0 | U76: 0 | Z76: 6.194 | AA76: 0.015 | AB76: 1.232 | AC76: 0.122 | AD76: 0 | AE76: 0.009
C77: Proceeds from sale of fiancial assets and businesses | L77: 0 | M77: 0 | N77: 2.028 | O77: 0 | P77: 0 | Q77: 1.168 | R77: 0.253 | S77: 0 | T77: 0 | U77: 2.259 | Z77: 1.5 | AA77: 0 | AB77: 0 | AC77: 4.883 | AD77: 2.028 | AE77: 1.422
C78: Dividend from JV | L78: 4.018 | M78: 0 | N78: 0 | O78: 5.848 | P78: 0 | Q78: 0 | R78: 0 | S78: 5.376 | T78: 3.673 | U78: =-26.236-U75-U76-U77-U79 -> -0.167 | Z78: 0 | AA78: 4.965 | AB78: 0 | AC78: 2.018 | AD78: 9.866 | AE78: 5.376
C79: Change in other non-current assets | L79: 0.441 | M79: 0.37 | N79: -1.66 | O79: 0.543 | P79: -1.565 | Q79: -0.272 | R79: 0.04 | S79: -0.084 | T79: 0.502 | U79: -0.422 | Z79: 6.812 | AA79: 6.179 | AB79: -83.527 | AC79: 1.772 | AD79: -0.306 | AE79: -1.88
C80: CFFI | D80: =SUM(D75:D79) -> 0 | E80: =SUM(E75:E79) -> 0 | F80: =SUM(F75:F79) -> 0 | G80: =SUM(G75:G79) -> 0 | H80: =SUM(H75:H79) -> 0 | I80: =SUM(I75:I79) -> 0 | J80: =SUM(J75:J79) -> 0 | K80: =SUM(K75:K79) -> 0 | ... U80: =SUM(U75:U79) -> -26.236 | Z80: =SUM(Z75:Z79) -> -35.646 | AA80: =SUM(AA75:AA79) -> -26.222 | AB80: =SUM(AB75:AB79) -> -126.009 | AC80: =SUM(AC75:AC79) -> -31.979 | AD80: =SUM(AD75:AD79) -> -97.513 | AE80: =SUM(AE75:AE79) -> -80.724
C82: Proceeds from and repayments of borrowings | L82: -8.725 | M82: 22.491 | N82: 32.154 | O82: 4.651 | P82: 39.341 | Q82: 19.048 | R82: -25.574 | S82: 17.152 | T82: -19.807 | U82: 15.066 | Z82: -41.539 | AA82: -46.797 | AB82: 147.85 | AC82: -87.294 | AD82: 45.599 | AE82: 44.363
C83: Interest on borrowings | L83: -2.609 | M83: -4.174 | N83: -4.214 | O83: -4.307 | P83: -4.439 | Q83: -4.629 | R83: -4.52 | S83: -4.788 | T83: -6.862 | U83: -7.604 | Z83: -5.897 | AA83: -1.553 | AB83: -5.658 | AC83: -11.303 | AD83: -23.196 | AE83: -26.044
C84: Lease payment | L84: -5.325 | M84: -5.714 | N84: -5.952 | O84: -6.598 | P84: -5.801 | Q84: -7.348 | R84: -5.917 | S84: -5.636 | T84: -4.251 | U84: -4.643 | Z84: -20.8 | AA84: -19.969 | AB84: -19.77 | AC84: -18.359 | AD84: -15.697 | AE84: -17.036
C85: Dividend | L85: 0 | M85: -34.43 | N85: 0 | O85: 0 | P85: 0 | Q85: -21.637 | R85: 0 | S85: -21.677 | T85: 0 | U85: -27.401 | Z85: -9.48 | AA85: -9.988 | AB85: -19.623 | AC85: -19.634 | AD85: -34.43 | AE85: -43.314
C86: Buybacks | L86: 0 | M86: 0 | N86: -1.589 | O86: -0.225 | P86: -1.887 | Q86: -0.155 | R86: -1.021 | S86: -0.275 | T86: -2.619 | U86: 0 | Z86: 2.388 | AA86: 47.523 | AB86: -0.241 | AC86: -0.885 | AD86: -1.814 | AE86: -3.338
C87: CFFF | D87: =SUM(D82:D86) -> 0 | E87: =SUM(E82:E86) -> 0 | F87: =SUM(F82:F86) -> 0 | G87: =SUM(G82:G86) -> 0 | H87: =SUM(H82:H86) -> 0 | I87: =SUM(I82:I86) -> 0 | J87: =SUM(J82:J86) -> 0 | K87: =SUM(K82:K86) -> 0 | ... U87: =SUM(U82:U86) -> -24.582 | Z87: =SUM(Z82:Z86) -> -75.328 | AA87: =SUM(AA82:AA86) -> -30.784 | AB87: =SUM(AB82:AB86) -> 102.558 | AC87: =SUM(AC82:AC86) -> -137.475 | AD87: =SUM(AD82:AD86) -> -29.538 | AE87: =SUM(AE82:AE86) -> -45.369
C89: FX | L89: 0.058 | M89: 0.027 | N89: -0.185 | O89: 2.629 | P89: -2.797 | Q89: -5.019 | R89: -1.4 | S89: -1.654 | T89: 2.616 | U89: 1.208 | Z89: -1.929 | AA89: 1.625 | AB89: -0.022 | AC89: -0.31 | AD89: 2.529 | AE89: -10.87
C91: CIC | D91: =D73+D80+D87+D89 -> 0 | E91: =E73+E80+E87+E89 -> 0 | F91: =F73+F80+F87+F89 -> 0 | G91: =G73+G80+G87+G89 -> 0 | H91: =H73+H80+H87+H89 -> 0 | I91: =I73+I80+I87+I89 -> 0 | J91: =J73+J80+J87+J89 -> 0 | K91: =K73+K80+K87+K89 -> 0 | ... U91: =U73+U80+U87+U89 -> 5.181 | Z91: =Z73+Z80+Z87+Z89 -> -9.061 | AA91: =AA73+AA80+AA87+AA89 -> 17.819 | AB91: =AB73+AB80+AB87+AB89 -> 1.621 | AC91: =AC73+AC80+AC87+AC89 -> -12.575 | AD91: =AD73+AD80+AD87+AD89 -> 14.743 | AE91: =AE73+AE80+AE87+AE89 -> 34.116
C93: FCF | D93: =D73+D75 -> 0 | E93: =E73+E75 -> 0 | F93: =F73+F75 -> 0 | G93: =G73+G75 -> 0 | H93: =H73+H75 -> 0 | I93: =I73+I75 -> 0 | J93: =J73+J75 -> 0 | K93: =K73+K75 -> 0 | ... U93: =U73+U75 -> 26.885 | Z93: =Z73+Z75 -> 53.69 | AA93: =AA73+AA75 -> 35.819 | AB93: =AB73+AB75 -> -18.62 | AC93: =AC73+AC75 -> 116.415 | AD93: =AD73+AD75 -> 30.164 | AE93: =AE73+AE75 -> 85.428

Sheet Segementer
B5: EUR million | C5: Q122 | D5: Q222 | E5: Q322 | F5: Q422 | G5: 2022 | H5: Q123 | I5: Q223 | J5: Q323 | K5: Q423 | L5: 2023 | M5: Q124 | N5: Q224 | O5: Q324 | P5: Q424 | Q5: 2024 | R5: Q125 | S5: Q225 | T5: Q325 | U5: Q425 | V5: 2025 | W5: Q126 | X5: Q226 | Y5: Q326 | Z5: Q426 | AA5: 2026
B6: EMEA
B7: Revenue | C7: 175.044 | D7: 205.017 | E7: 207.904 | F7: 198.17 | G7: =SUM(C7:F7) -> 786.135 | H7: 213.511 | I7: 216.31 | J7: 221.198 | K7: 219.406 | L7: =SUM(H7:K7) -> 870.425 | M7: 230.523 | N7: 219.512 | O7: 217.703 | P7: 206.249 | Q7: =SUM(M7:P7) -> 873.987 | R7: 228.91 | S7: 219.958 | T7: 206.151 | U7: 221.822 | V7: =SUM(R7:U7) -> 876.841 | W7: 208.092 | X7: 224.111 | AA7: =SUM(W7:Z7) -> 432.203
B8: y/y | H8: =(H7-C7)/C7 -> 0.21975618 | I8: =(I7-D7)/D7 -> 0.055083237 | J8: =(J7-E7)/E7 -> 0.063942974 | K8: =(K7-F7)/F7 -> 0.10716052 | L8: =(L7-G7)/G7 -> 0.10722077 | M8: =(M7-H7)/H7 -> 0.079677394 | N8: =(N7-I7)/I7 -> 0.014802829 | O8: =(O7-J7)/J7 -> -0.015800324 | ... AA8: =(AA7-V7)/V7 -> -0.5070908
B9: Operating expenses | C9: -161.872 | D9: -177.967 | E9: -183.115 | F9: -171.031 | H9: -181.827 | I9: -181.065 | J9: -181.228 | K9: -191.011 | M9: -193.612 | N9: -183.618 | O9: -181.776 | P9: -175.021 | R9: -192.984 | S9: -185.467 | T9: -169.499 | U9: -191.025 | W9: -172.94 | X9: -185.345
B10: D/A | C10: -10.798 | D10: -14.785 | E10: -13.14 | F10: -14.123 | H10: -12.85 | I10: -12.415 | J10: -13.223 | K10: -12.101 | M10: -13.713 | N10: -12.599 | O10: -13.917 | P10: -14.787 | R10: -13.243 | S10: -13.555 | T10: -12.44 | U10: -14.976 | W10: -12 | X10: -12.112
B11: Impairment | C11: -4.256 | D11: 1.636 | E11: -1.267 | F11: -1.173 | H11: -0.077 | I11: -0.091 | J11: -0.399 | K11: -0.618 | M11: -0.16 | N11: -0.415 | O11: -0.097 | P11: -1.897 | R11: -0.037 | S11: -1.034 | T11: -0.176 | U11: 0 | W11: 0 | X11: 0
B12: Operating profit | C12: -1.882 | D12: 13.901 | E12: 10.383 | F12: 11.843 | G12: =SUM(C12:F12) -> 34.245 | H12: 18.757 | I12: 22.738 | J12: 26.348 | K12: 15.676 | L12: =SUM(H12:K12) -> 83.519 | M12: 23.039 | N12: 22.881 | O12: 21.937 | P12: 14.544 | Q12: =SUM(M12:P12) -> 82.401 | R12: 22.728 | S12: 19.823 | T12: 24.068 | U12: 15.819 | V12: =SUM(R12:U12) -> 82.438 | W12: 23.166 | X12: 26.653 | AA12: =SUM(W12:Z12) -> 49.819
B13: Operating profit margin | C13: =C12/C7 -> -0.010751582 | D13: =D12/D7 -> 0.067804133 | E13: =E12/E7 -> 0.049941319 | F13: =F12/F7 -> 0.059761821 | G13: =G12/G7 -> 0.04356122 | H13: =H12/H7 -> 0.087850275 | I13: =I12/I7 -> 0.10511766 | J13: =J12/J7 -> 0.119115 | ... AA13: =AA12/AA7 -> 0.11526759
B14: Americas
B15: Revenue | C15: 57.666 | D15: 61.329 | E15: 68.833 | F15: 72.707 | G15: =SUM(C15:F15) -> 260.535 | H15: 73.156 | I15: 64.99 | J15: 72.082 | K15: 80.456 | L15: =SUM(H15:K15) -> 290.684 | M15: 74.003 | N15: 72.869 | O15: 79.322 | P15: 84.222 | Q15: =SUM(M15:P15) -> 310.416 | R15: 93.983 | S15: 78.28 | T15: 88.193 | U15: 99.483 | V15: =SUM(R15:U15) -> 359.939 | W15: 94.479 | X15: 87.705 | AA15: =SUM(W15:Z15) -> 182.184
B16: y/y | H16: =(H15-C15)/C15 -> 0.26861582 | I16: =(I15-D15)/D15 -> 0.059694435 | J16: =(J15-E15)/E15 -> 0.047201197 | K16: =(K15-F15)/F15 -> 0.10657846 | L16: =(L15-G15)/G15 -> 0.11571958 | M16: =(M15-H15)/H15 -> 0.011577998 | N16: =(N15-I15)/I15 -> 0.12123404 | O16: =(O15-J15)/J15 -> 0.10044116 | ... AA16: =(AA15-V15)/V15 -> -0.49384757
B17: Operating expenses | C17: -47.881 | D17: -50.878 | E17: -56.773 | F17: -58.027 | H17: -57.643 | I17: -51.631 | J17: -58.619 | K17: -63.851 | M17: -58.871 | N17: -58.331 | O17: -63.852 | P17: -68.087 | R17: -77.941 | S17: -62.019 | T17: -68.354 | U17: -78.331 | W17: -75.386 | X17: -68.819
B18: D/A | C18: -1.562 | D18: -1.811 | E18: -1.94 | F18: -1.851 | H18: -1.754 | I18: -1.747 | J18: -1.831 | K18: -1.828 | M18: -1.746 | N18: -1.909 | O18: -2.255 | P18: -2.14 | R18: -2.303 | S18: -2.034 | T18: -3.604 | U18: -2.797 | W18: -2.6 | X18: -2.731
B19: Impairment | C19: 0 | D19: 0 | E19: 0 | F19: -0.261 | H19: 0 | I19: 0 | J19: 0 | K19: 0 | M19: 0 | N19: 0 | O19: 0 | P19: 0 | R19: 0 | S19: 0 | T19: 0 | U19: 0 | W19: 0 | X19: 0
B20: Operating profit | C20: 8.223 | D20: 8.64 | E20: 10.12 | F20: 12.568 | G20: =SUM(C20:F20) -> 39.551 | H20: 13.759 | I20: 11.613 | J20: 11.631 | K20: 14.778 | L20: =SUM(H20:K20) -> 51.781 | M20: 13.386 | N20: 12.629 | O20: 13.215 | P20: 13.996 | Q20: =SUM(M20:P20) -> 53.226 | R20: 13.739 | S20: 14.227 | T20: 16.235 | U20: 18.355 | V20: =SUM(R20:U20) -> 62.556 | W20: 16.477 | X20: 16.155 | AA20: =SUM(W20:Z20) -> 32.632
B21: Operating profit margin | C21: =C20/C15 -> 0.14259702 | D21: =D20/D15 -> 0.14087952 | E21: =E20/E15 -> 0.1470225 | F21: =F20/F15 -> 0.17285818 | G21: =G20/G15 -> 0.15180686 | H21: =H20/H15 -> 0.18807753 | I21: =I20/I15 -> 0.17868903 | J21: =J20/J15 -> 0.1613579 | ... AA21: =AA20/AA15 -> 0.17911562
B22: Other/Eliminations
B23: Revenue | C23: -6.949 | D23: -7.834 | E23: -4.312 | F23: -3.721 | G23: =SUM(C23:F23) -> -22.816 | H23: -3.273 | I23: -3.22 | J23: -9.842 | K23: -12.679 | L23: =SUM(H23:K23) -> -29.014 | M23: -12.603 | N23: -3.997 | O23: -4.221 | P23: -7 | Q23: =SUM(M23:P23) -> -27.821 | R23: -12.653 | S23: -8.538 | T23: -4.696 | U23: -5.29 | V23: =SUM(R23:U23) -> -31.177 | W23: -12.186 | X23: -7.939 | AA23: =SUM(W23:Z23) -> -20.125
B24: y/y | H24: =(H23-C23)/C23 -> -0.52899698 | I24: =(I23-D23)/D23 -> -0.58897115 | J24: =(J23-E23)/E23 -> 1.2824675 | K24: =(K23-F23)/F23 -> 2.4074174 | L24: =(L23-G23)/G23 -> 0.27165147 | M24: =(M23-H23)/H23 -> 2.8505958 | N24: =(N23-I23)/I23 -> 0.24130435 | O24: =(O23-J23)/J23 -> -0.57112376 | ... AA24: =(AA23-V23)/V23 -> -0.35449209
B25: Operating expenses | C25: -0.97 | D25: 0.247 | E25: -1.851 | F25: -3.836 | H25: -3.967 | I25: -5.028 | J25: 2.842 | K25: 5.045 | M25: 4.449 | N25: -5.288 | O25: -3.95 | P25: -2.234 | R25: 2.716 | S25: 1.569 | T25: -4.112 | U25: -2.357 | W25: -12.186 | X25: -7.977
B26: D/A | C26: -0.684 | D26: -0.68 | E26: -0.686 | F26: -0.749 | H26: -0.619 | I26: -0.608 | J26: -0.605 | K26: -0.566 | M26: -0.426 | N26: -0.409 | O26: -0.395 | P26: 0 | R26: -0.349 | S26: -0.344 | T26: -1.716 | U26: -0.78 | W26: -1.838 | X26: -2.168
B27: Impairment | C27: 0 | D27: 0 | E27: 0 | F27: 0 | H27: 0 | I27: 0 | J27: 0 | K27: 0 | M27: 0 | N27: 0 | O27: 0 | P27: 0 | R27: 0 | S27: 0 | T27: 0 | U27: 0 | W27: 0 | X27: 0
B28: Operating profit | C28: -8.602 | D28: -8.266 | E28: -6.85 | F28: -8.306 | G28: =SUM(C28:F28) -> -32.024 | H28: -7.859 | I28: -8.857 | J28: -7.604 | K28: -8.201 | L28: =SUM(H28:K28) -> -32.521 | M28: -8.58 | N28: -9.694 | O28: -8.567 | P28: -9.331 | Q28: =SUM(M28:P28) -> -36.172 | R28: -10.286 | S28: -7.313 | T28: -10.524 | U28: -8.427 | V28: =SUM(R28:U28) -> -36.55 | W28: -18.4 | X28: -18 | AA28: =SUM(W28:Z28) -> -36.4
B29: Operating profit margin | C29: =C28/C23 -> 1.237876 | D29: =D28/D23 -> 1.0551442 | E29: =E28/E23 -> 1.58859 | F29: =F28/F23 -> 2.2321956 | G29: =G28/G23 -> 1.4035764 | H29: =H28/H23 -> 2.401161 | I29: =I28/I23 -> 2.7506211 | J29: =J28/J23 -> 0.77260719 | ... AA29: =AA28/AA23 -> 1.8086957

Sheet SOTP
A3: EBIT 26E
A4: =Modell!AF13 -> 100.34882
D5: EBIT 26E | E5: EV/EBIT | F5: Value EURm | G5: Value/Share
C6: EMEA | D6: 85 | E6: 7.5 | F6: =D6*E6 -> 637.5 | G6: =(F6*Modell!$B$12)/Modell!$B$5 -> 25.81077
C7: Americas | D7: 65 | E7: 12 | F7: =D7*E7 -> 780 | G7: =(F7*Modell!$B$12)/Modell!$B$5 -> 31.580236
C8: Eliminations | D8: -50 | E8: 5 | F8: =D8*E8 -> -250 | G8: =(F8*Modell!$B$12)/Modell!$B$5 -> -10.121871
C9: Enterprise value | D9: =SUM(D6:D8) -> 100 | F9: =SUM(F6:F8) -> 1167.5 | G9: =SUM(G6:G8) -> 47.269135
C11: Cash | F11: =Modell!B7 -> 675.18 | G11: =F11/Modell!$B$5 -> 2.5079209
C12: Debt | F12: =Modell!B8 -> 3549.67 | G12: =-F12/Modell!$B$5 -> -13.185064
C14: Equity value | G14: =SUM(G9:G12) -> 36.591992

Sheet Nøkkeltall
D4: 2026 | E4: 2027 | F4: 2028
C5: EV/EBIT | D5: =Modell!$B$9/(Modell!AF13*Modell!$B$12) -> 10.910301 | E5: =Modell!$B$9/(Modell!AG13*Modell!$B$12) -> 9.7017237 | F5: =Modell!$B$9/(Modell!AH13*Modell!$B$12) -> 8.9611562
C6: P/E | D6: =Modell!$B$4/(Modell!AF20*Modell!$B$12) -> 13.775775 | E6: =Modell!$B$4/(Modell!AG20*Modell!$B$12) -> 11.859148 | F6: =Modell!$B$4/(Modell!AH20*Modell!$B$12) -> 10.743958

Sheet Nedsideberegning
A3: Nedside | D3: FY 2020 | E3: FY 2021 | F3: FY 2022 | G3: FY 2023 | H3: FY 2024 | I3: FY 2025 | J3: FY 2026 | K3: FY 2027 | L3: FY 2028 | M3: FY 2029 | N3: FY 2030 | O3: FY 2031 | P3: FY 2032 | Q3: FY 2033 | R3: FY 2034 | S3: FY 2035
A4: Nullvekst og ned på marginer | C4: Revenues | D4: 908.773 | E4: 940.246 | F4: 1023.696 | G4: 1132.043 | H4: 1156.502 | I4: 1205.588 | J4: =I4 -> 1205.588 | K4: =J4 -> 1205.588 | L4: =K4 -> 1205.588 | M4: =L4 -> 1205.588 | N4: =M4 -> 1205.588 | O4: =N4 -> 1205.588 | P4: =O4 -> 1205.588 | Q4: =P4 -> 1205.588 | ... S4: =R4 -> 1205.588
A5: =V25 -> 27.093614 | C5: other revenue | D5: 5.221 | E5: 0.007 | F5: 0.157 | G5: 0.145 | H5: 0.089 | I5: 0.049 | J5: 0 | K5: 0 | L5: 0 | M5: 0 | N5: 0 | O5: 0 | P5: 0 | Q5: 0 | R5: 0 | S5: 0
A6: =V26 -> -0.19484058 | C6: Total revenue | D6: =SUM(D4:D5) -> 913.994 | E6: =SUM(E4:E5) -> 940.253 | F6: =SUM(F4:F5) -> 1023.853 | G6: =SUM(G4:G5) -> 1132.188 | H6: =SUM(H4:H5) -> 1156.591 | I6: =SUM(I4:I5) -> 1205.637 | J6: =SUM(J4:J5) -> 1205.588 | K6: =SUM(K4:K5) -> 1205.588 | ... S6: =SUM(S4:S5) -> 1205.588
C7: COGS | D7: -576.637 | E7: -607.913 | F7: -681.474 | G7: -719.796 | H7: -719.753 | I7: -747.911 | J7: =J6*-0.65 -> -783.6322 | K7: =K6*-0.65 -> -783.6322 | L7: =L6*-0.65 -> -783.6322 | M7: =M6*-0.65 -> -783.6322 | N7: =N6*-0.65 -> -783.6322 | O7: =O6*-0.65 -> -783.6322 | P7: =P6*-0.65 -> -783.6322 | Q7: =Q6*-0.65 -> -783.6322 | ... S7: =S6*-0.65 -> -783.6322
C8: Gross profit | D8: =SUM(D6:D7) -> 337.357 | E8: =SUM(E6:E7) -> 332.34 | F8: =SUM(F6:F7) -> 342.379 | G8: =SUM(G6:G7) -> 412.392 | H8: =SUM(H6:H7) -> 436.838 | I8: =SUM(I6:I7) -> 457.726 | J8: =SUM(J6:J7) -> 421.9558 | K8: =SUM(K6:K7) -> 421.9558 | ... S8: =SUM(S6:S7) -> 421.9558
C9: Payroll expense | D9: -168.573 | E9: -171.664 | F9: -176.721 | G9: -189.623 | H9: -203.243 | I9: -211.284 | J9: =I9 -> -211.284 | K9: =J9 -> -211.284 | L9: =K9 -> -211.284 | M9: =L9 -> -211.284 | N9: =M9 -> -211.284 | O9: =N9 -> -211.284 | P9: =O9 -> -211.284 | Q9: =P9 -> -211.284 | ... S9: =R9 -> -211.284
C10: D/A | D10: -52.209 | E10: -56.45 | F10: -61.528 | G10: -60.147 | H10: -64.377 | I10: -68.139 | J10: =I10 -> -68.139 | K10: =J10 -> -68.139 | L10: =K10 -> -68.139 | M10: =L10 -> -68.139 | N10: =M10 -> -68.139 | O10: =N10 -> -68.139 | P10: =O10 -> -68.139 | Q10: =P10 -> -68.139 | ... S10: =R10 -> -68.139
C11: Impairment | D11: 0 | E11: 0 | F11: -6.599 | G11: -1.186 | H11: -2.568 | I11: -1.248 | J11: =I11 -> -1.248 | K11: =J11 -> -1.248 | L11: =K11 -> -1.248 | M11: =L11 -> -1.248 | N11: =M11 -> -1.248 | O11: =N11 -> -1.248 | P11: =O11 -> -1.248 | Q11: =P11 -> -1.248 | ... S11: =R11 -> -1.248
C12: other opex | D12: -45.918 | E12: -50.149 | F12: -55.757 | G12: -58.658 | H12: -67.195 | I12: -68.611 | J12: =I12 -> -68.611 | K12: =J12 -> -68.611 | L12: =K12 -> -68.611 | M12: =L12 -> -68.611 | N12: =M12 -> -68.611 | O12: =N12 -> -68.611 | P12: =O12 -> -68.611 | Q12: =P12 -> -68.611 | ... S12: =R12 -> -68.611
C13: Operating profit (EBIT) | D13: =SUM(D8:D12) -> 70.657 | E13: =SUM(E8:E12) -> 54.077 | F13: =SUM(F8:F12) -> 41.774 | G13: =SUM(G8:G12) -> 102.778 | H13: =SUM(H8:H12) -> 99.455 | I13: =SUM(I8:I12) -> 108.444 | J13: =SUM(J8:J12) -> 72.6738 | K13: =SUM(K8:K12) -> 72.6738 | ... S13: =SUM(S8:S12) -> 72.6738
C14: Net financials | D14: -13.602 | E14: -7.669 | F14: 0.255 | G14: -24.755 | H14: -20.4 | I14: -29.703 | J14: 0 | K14: 0 | L14: 0 | M14: 0 | N14: 0 | O14: 0 | P14: 0 | Q14: 0 | R14: 0 | S14: 0
C15: Share from JV | D15: 3.155 | E15: 3.575 | F15: 4.378 | G15: 6.855 | H15: 9.696 | I15: 6.819 | J15: 0 | K15: 0 | L15: 0 | M15: 0 | N15: 0 | O15: 0 | P15: 0 | Q15: 0 | R15: 0 | S15: 0
C16: PTP | D16: =SUM(D13:D15) -> 60.21 | E16: =SUM(E13:E15) -> 49.983 | F16: =SUM(F13:F15) -> 46.407 | G16: =SUM(G13:G15) -> 84.878 | H16: =SUM(H13:H15) -> 88.751 | I16: =SUM(I13:I15) -> 85.56 | J16: =SUM(J13:J15) -> 72.6738 | K16: =SUM(K13:K15) -> 72.6738 | ... S16: =SUM(S13:S15) -> 72.6738
C17: tax | D17: -12.381 | E17: -16.173 | F17: -12.188 | G17: -15.513 | H17: -27.203 | I17: -24.071 | J17: =J16*-0.22 -> -15.988236 | K17: =K16*-0.22 -> -15.988236 | L17: =L16*-0.22 -> -15.988236 | M17: =M16*-0.22 -> -15.988236 | N17: =N16*-0.22 -> -15.988236 | O17: =O16*-0.22 -> -15.988236 | P17: =P16*-0.22 -> -15.988236 | Q17: =Q16*-0.22 -> -15.988236 | ... S17: =S16*-0.22 -> -15.988236
C18: Net income | D18: =SUM(D16:D17) -> 47.829 | E18: =SUM(E16:E17) -> 33.81 | F18: =SUM(F16:F17) -> 34.219 | G18: =SUM(G16:G17) -> 69.365 | H18: =SUM(H16:H17) -> 61.548 | I18: =SUM(I16:I17) -> 61.489 | J18: =SUM(J16:J17) -> 56.685564 | K18: =SUM(K16:K17) -> 56.685564 | ... S18: =SUM(S16:S17) -> 56.685564 | T18: =S18*(1+$V$22) -> 56.118708 | U18: =T18*(1+$V$22) -> 55.557521 | V18: =U18*(1+$V$22) -> 55.001946 | W18: =V18*(1+$V$22) -> 54.451927 | X18: =W18*(1+$V$22) -> 53.907407 | Y18: =X18*(1+$V$22) -> 53.368333 | Z18: =Y18*(1+$V$22) -> 52.83465 | AA18: =Z18*(1+$V$22) -> 52.306303 | ... IM18: =IL18*(1+$V$22) -> 5.7318767
C19: Shares | H19: 269.21901 | I19: 269.21901 | J19: 269.21901 | K19: 269.21901 | L19: 269.21901 | M19: 269.21901 | N19: 269.21901 | O19: 269.21901 | P19: 269.21901 | Q19: 269.21901 | R19: 269.21901 | S19: 269.21901
C20: EPS | D20: =D18/D19 -> #DIV/0! | E20: =E18/E19 -> #DIV/0! | F20: =F18/F19 -> #DIV/0! | G20: =G18/G19 -> #DIV/0! | H20: =H18/H19 -> 0.22861684 | I20: =I18/I19 -> 0.22839769 | J20: =J18/J19 -> 0.21055557 | K20: =K18/K19 -> 0.21055557 | ... S20: =S18/S19 -> 0.21055557
U21: Discount | V21: 0.08
C22: Revenue y/y | E22: =(E6-D6)/D6 -> 0.028729948 | F22: =(F6-E6)/E6 -> 0.08891224 | G22: =(G6-F6)/F6 -> 0.10581109 | H22: =(H6-G6)/G6 -> 0.021553841 | I22: =(I6-H6)/H6 -> 0.042405656 | J22: =(J6-I6)/I6 -> -4.0642416e-05 | K22: =(K6-J6)/J6 -> 0 | L22: =(L6-K6)/K6 -> 0 | ... S22: =(S6-R6)/R6 -> 0 | U22: TV | V22: -0.01
C23: Gross margin | D23: =D8/D6 -> 0.36910199 | E23: =E8/E6 -> 0.35345806 | F23: =F8/F6 -> 0.3344025 | G23: =G8/G6 -> 0.36424339 | H23: =H8/H6 -> 0.37769445 | I23: =I8/I6 -> 0.3796549 | J23: =J8/J6 -> 0.35 | K23: =K8/K6 -> 0.35 | ... S23: =S8/S6 -> 0.35 | U23: NPV | V23: =NPV(V21,J18:HU18)*Modell!B12 -> 7294.1162
C24: EBIT margin | D24: =D13/D6 -> 0.077305759 | E24: =E13/E6 -> 0.057513244 | F24: =F13/F6 -> 0.040800779 | G24: =G13/G6 -> 0.09077821 | H24: =H13/H6 -> 0.085989775 | I24: =I13/I6 -> 0.089947472 | J24: =J13/J6 -> 0.060280792 | K24: =K13/K6 -> 0.060280792 | ... S24: =S13/S6 -> 0.060280792 | U24: S/O | V24: 269.21901
U25: NPV/Share | V25: =V23/V24 -> 27.093614
U26: Nedside | V26: =(V25-Modell!B4)/Modell!B4 -> -0.19484058
