Workbook

Sheet Info
A14: ÖoB mål 2028:
A15: Revenue | B15: 5000
A16: EBIT margin | B16: 0.05
A21: Press releases:
A22: 10.07.26: Direktør Terje Andersen har kjøpt 6 000 aksjer

Sheet Modell
A3: Kapitalstruktur | C3: NOKm | D3: Q122 | E3: Q222 | F3: Q322 | G3: Q422 | H3: Q123 | I3: Q223 | J3: Q323 | K3: Q423 | L3: Q124 | M3: Q224 | N3: Q324 | O3: Q424 | P3: Q125 | Q3: Q225 | R3: Q325 | S3: Q425 | T3: Q126 | U3: Q226 | V3: Q326 | W3: Q426 | AB3: FY 2015 | AC3: FY 2016 | AD3: FY 2017 | AE3: FY 2018 | AF3: FY 2019 | AG3: FY 2020 | AH3: FY 2021 | AI3: FY 2022 | AJ3: FY 2023 | AK3: FY 2024 | AL3: FY 2025 | AM3: FY 2026 | AN3: FY 2027 | AO3: FY 2028 | AP3: FY 2029 | AQ3: FY 2030 | AR3: FY 2031 | AS3: FY 2032 | AT3: FY 2033 | AU3: FY 2034 | AV3: FY 2035
A4: Price | B4: 81 | C4: Revenue | D4: 1715.566 | E4: 2216.164 | F4: 2050 | G4: 3034.033 | H4: 1932.691 | I4: 2310.467 | J4: 2151.957 | K4: 3071.806 | L4: 2026.201 | M4: 3108.896 | N4: 3237.505 | O4: 4377.657 | P4: 2938.173 | Q4: 3801.689 | R4: 3528.068 | S4: 4610.534 | T4: 3299.737 | U4: 3694.02 | AB4: 4629.232 | AC4: 5085.205 | AD4: 5422.53 | AE4: 5816.984 | AF4: 6234.389 | AG4: 8012.629 | AH4: 8648.177 | AI4: 9015.766 | AJ4: 9466.921 | AK4: 12750.259 | AL4: 14878 | AM4: =AL4*1.03 -> 15324.34 | AN4: =AM4*1.05 -> 16090.557 | AO4: =AN4*1.05 -> 16895.085 | AP4: =AO4*1.05 -> 17739.839 | AQ4: =AP4*1.05 -> 18626.831 | AR4: =AQ4*1.05 -> 19558.173 | AS4: =AR4*1.05 -> 20536.081 | AT4: =AS4*1.05 -> 21562.885 | AU4: =AT4*1.05 -> 22641.03 | AV4: =AU4*1.05 -> 23773.081
A5: S/O | B5: 166.96889 | C5: COGS | D5: -956.053 | E5: -1147.089 | F5: -1074.708 | G5: -1654.925 | H5: -1092.582 | I5: -1282.041 | J5: -1176.971 | K5: -1724.058 | L5: -1148.099 | M5: -1807.375 | N5: -1951.068 | O5: -2515.614 | P5: -1801.703 | Q5: -2257.327 | R5: -2091.233 | S5: -2648.695 | T5: -1997.704 | U5: -2127.016 | AB5: -2569.337 | AC5: -2903.03 | AD5: -3118.345 | AE5: -3298.296 | AF5: -3543.73 | AG5: -4534.134 | AH5: -4592.143 | AI5: -4832.783 | AJ5: -5275.676 | AK5: -7437.455 | AL5: -8799 | AM5: =AM4*-0.58 -> -8888.1172 | AN5: =AN4*-0.58 -> -9332.5231 | AO5: =AO4*-0.58 -> -9799.1492 | AP5: =AP4*-0.58 -> -10289.107 | AQ5: =AQ4*-0.58 -> -10803.562 | AR5: =AR4*-0.58 -> -11343.74 | AS5: =AS4*-0.58 -> -11910.927 | AT5: =AT4*-0.58 -> -12506.473 | ... AV5: =AV4*-0.58 -> -13788.387
A6: MC NOKm | B6: =B4*B5 -> 13524.48 | C6: Gross profit | D6: =SUM(D4:D5) -> 759.513 | E6: =SUM(E4:E5) -> 1069.075 | F6: =SUM(F4:F5) -> 975.292 | G6: =SUM(G4:G5) -> 1379.108 | H6: =SUM(H4:H5) -> 840.109 | I6: =SUM(I4:I5) -> 1028.426 | J6: =SUM(J4:J5) -> 974.986 | K6: =SUM(K4:K5) -> 1347.748 | ... U6: =SUM(U4:U5) -> 1567.004 | AB6: =SUM(AB4:AB5) -> 2059.895 | AC6: =SUM(AC4:AC5) -> 2182.175 | AD6: =SUM(AD4:AD5) -> 2304.185 | AE6: =SUM(AE4:AE5) -> 2518.688 | AF6: =SUM(AF4:AF5) -> 2690.659 | AG6: =SUM(AG4:AG5) -> 3478.495 | AH6: =SUM(AH4:AH5) -> 4056.034 | AI6: =SUM(AI4:AI5) -> 4182.983 | ... AV6: =SUM(AV4:AV5) -> 9984.694
A7: Cash NOKm | B7: =U36 -> 830.034 | C7: Employee benefit expenses | D7: -306.716 | E7: -269.986 | F7: -348.402 | G7: -370.026 | H7: -335.001 | I7: -290.549 | J7: -358.351 | K7: -389.18 | L7: -363.09 | M7: -415.26 | N7: -538.263 | O7: -548.423 | P7: -540.419 | Q7: -519.288 | R7: -569.444 | S7: -609.053 | T7: -593.43 | U7: -541.598 | AB7: -702.336 | AC7: -752.498 | AD7: -826.847 | AE7: -898.504 | AF7: -985.347 | AG7: -1138.193 | AH7: -1230.303 | AI7: -1295.131 | AJ7: -1373.081 | AK7: -1865.036 | AL7: -2238 | AM7: =AL7*1.03 -> -2305.14 | AN7: =AM7*1.04 -> -2397.3456 | AO7: =AN7*1.03 -> -2469.266 | AP7: =AO7*1.04 -> -2568.0366 | AQ7: =AP7*1.04 -> -2670.7581 | AR7: =AQ7*1.04 -> -2777.5884 | AS7: =AR7*1.05 -> -2916.4678 | AT7: =AS7*1.05 -> -3062.2912 | AU7: =AT7*1.05 -> -3215.4058 | AV7: =AU7*1.05 -> -3376.1761
A8: Debt Nokm | B8: =(U43+U45) -> 2456.99 | C8: Depreciation | D8: -151.119 | E8: -151.02 | F8: -153.608 | G8: -155.288 | H8: -166.272 | I8: -168.807 | J8: -170.261 | K8: -169.268 | L8: -174.34 | M8: -227.892 | N8: -260.227 | O8: -260.468 | P8: -260.72 | Q8: -266.876 | R8: -265.276 | S8: -267.378 | T8: -268.72 | U8: -266.612 | AB8: -71.061 | AC8: -75.089 | AD8: -82.69 | AE8: -90.743 | AF8: -515.673 | AG8: -539.927 | AH8: -571.223 | AI8: -611.035 | AJ8: -674.608 | AK8: -922.927 | AL8: -1060 | AM8: =AL8*1.03 -> -1091.8 | AN8: =AM8*1.04 -> -1135.472 | AO8: =AN8*1.03 -> -1169.5362 | AP8: =AO8*1.04 -> -1216.3176 | AQ8: =AP8*1.04 -> -1264.9703 | AR8: =AQ8*1.04 -> -1315.5691 | AS8: =AR8*1.05 -> -1381.3476 | AT8: =AS8*1.05 -> -1450.415 | AU8: =AT8*1.05 -> -1522.9357 | AV8: =AU8*1.05 -> -1599.0825
A9: EV NOKm | B9: =B6-B7+B8 -> 15151.436 | C9: Other operating expenses | D9: -175.243 | E9: -210.174 | F9: -201.716 | G9: -249.348 | H9: -193.655 | I9: -206.92 | J9: -212.15 | K9: -235.695 | L9: -234.109 | M9: -319.689 | N9: -320.363 | O9: -429.201 | P9: -372.3 | Q9: -335.674 | R9: -346.025 | S9: -408.075 | T9: -368.443 | U9: -364.807 | AB9: -753.932 | AC9: -764.59 | AD9: -842.641 | AE9: -942.369 | AF9: -611.057 | AG9: -634.794 | AH9: -742.749 | AI9: -836.461 | AJ9: -848.426 | AK9: -1288.062 | AL9: -1462 | AM9: =AL9*1.02 -> -1491.24 | AN9: =AM9*1.04 -> -1550.8896 | AO9: =AN9*1.03 -> -1597.4163 | AP9: =AO9*1.04 -> -1661.3129 | AQ9: =AP9*1.04 -> -1727.7655 | AR9: =AQ9*1.04 -> -1796.8761 | AS9: =AR9*1.05 -> -1886.7199 | AT9: =AS9*1.05 -> -1981.0559 | AU9: =AT9*1.05 -> -2080.1087 | AV9: =AU9*1.05 -> -2184.1141
C10: Operating profit (EBIT) | D10: =SUM(D6:D9) -> 126.435 | E10: =SUM(E6:E9) -> 437.895 | F10: =SUM(F6:F9) -> 271.566 | G10: =SUM(G6:G9) -> 604.446 | H10: =SUM(H6:H9) -> 145.181 | I10: =SUM(I6:I9) -> 362.15 | J10: =SUM(J6:J9) -> 234.224 | K10: =SUM(K6:K9) -> 553.605 | ... U10: =SUM(U6:U9) -> 393.987 | AB10: =SUM(AB6:AB9) -> 532.566 | AC10: =SUM(AC6:AC9) -> 589.998 | AD10: =SUM(AD6:AD9) -> 552.007 | AE10: =SUM(AE6:AE9) -> 587.072 | AF10: =SUM(AF6:AF9) -> 578.582 | AG10: =SUM(AG6:AG9) -> 1165.581 | AH10: =SUM(AH6:AH9) -> 1511.759 | AI10: =SUM(AI6:AI9) -> 1440.356 | ... AV10: =SUM(AV6:AV9) -> 2825.3214
C11: Net financials | D11: -0.862 | E11: -24.4 | F11: -32.744 | G11: -49.423 | H11: -43.751 | I11: -29.715 | J11: -44.724 | K11: -72.325 | L11: -32.812 | M11: -53.645 | N11: -60.484 | O11: -54.763 | P11: -62.905 | Q11: -66.296 | R11: -59.183 | S11: -70.01 | T11: -40.595 | U11: -66.641 | AB11: -164.956 | AC11: -41.052 | AD11: -41.682 | AE11: -40.942 | AF11: -98.172 | AG11: -139.068 | AH11: -94.395 | AI11: -107.394 | AJ11: -190.517 | AK11: -201.704 | AL11: -258 | AM11: =AL11*1.065 -> -274.77 | AN11: =AM11*1.065 -> -292.63005 | AO11: =AN11*1.01 -> -295.55635 | AP11: =AO11*1.01 -> -298.51191 | AQ11: =AP11*1.01 -> -301.49703 | AR11: =AQ11*1.01 -> -304.512 | AS11: =AR11*1.01 -> -307.55712 | AT11: =AS11*1.01 -> -310.63269 | AU11: =AT11*1.01 -> -313.73902 | AV11: =AU11*1.01 -> -316.87641
A12: Gearing | B12: =(B8-B7)/AM25 -> 0.61630791 | C12: Profit/loss from associated comps | D12: -9.226 | E12: 5.26 | F12: 1.4 | G12: 6.6 | H12: -7.915 | I12: 0 | J12: -4.5 | K12: -41.902 | L12: -10.976 | M12: 12.54 | N12: 0.029 | O12: 0.029 | P12: 0 | Q12: 0 | R12: 0 | S12: 0 | T12: 0 | U12: 0 | AB12: 0 | AC12: 0 | AD12: 0 | AE12: 6.4 | AF12: 0 | AG12: 2.6 | AH12: 0 | AI12: 4 | AJ12: -54.489 | AK12: 1.592 | AL12: 0 | AM12: 0 | AN12: 0 | AO12: 0 | AP12: 0 | AQ12: 0 | AR12: 0 | AS12: 0 | AT12: 0 | AU12: 0 | AV12: 0
C13: Change in fair value of options | D13: 0 | E13: 0 | F13: 0 | G13: 0 | H13: 0 | I13: 0 | J13: 0 | K13: 101.789 | L13: 0 | M13: 32.3 | N13: 0 | O13: 0 | P13: 0 | Q13: 0 | R13: 0 | S13: 0 | T13: 0 | U13: 0 | AB13: 0 | AC13: 0 | AD13: 0 | AE13: 0 | AF13: 0 | AG13: 0 | AH13: 0 | AI13: 0 | AJ13: 101.789 | AK13: 32.309 | AL13: 0 | AM13: 0 | AN13: 0 | AO13: 0 | AP13: 0 | AQ13: 0 | AR13: 0 | AS13: 0 | AT13: 0 | AU13: 0 | AV13: 0
A14: P/B | B14: =B6/U41 -> 3.4046195 | C14: PTP | D14: =SUM(D10:D13) -> 116.347 | E14: =SUM(E10:E13) -> 418.755 | F14: =SUM(F10:F13) -> 240.222 | G14: =SUM(G10:G13) -> 561.623 | H14: =SUM(H10:H13) -> 93.515 | I14: =SUM(I10:I13) -> 332.435 | J14: =SUM(J10:J13) -> 185 | K14: =SUM(K10:K13) -> 541.167 | ... U14: =SUM(U10:U13) -> 327.346 | AB14: =SUM(AB10:AB13) -> 367.61 | AC14: =SUM(AC10:AC13) -> 548.946 | AD14: =SUM(AD10:AD13) -> 510.325 | AE14: =SUM(AE10:AE13) -> 552.53 | AF14: =SUM(AF10:AF13) -> 480.41 | AG14: =SUM(AG10:AG13) -> 1029.113 | AH14: =SUM(AH10:AH13) -> 1417.364 | AI14: =SUM(AI10:AI13) -> 1336.962 | ... AV14: =SUM(AV10:AV13) -> 2508.445
C15: Tax | D15: -27.626 | E15: -90.969 | F15: -52.541 | G15: -122.105 | H15: -22.315 | I15: -73.136 | J15: -41.69 | K15: -106.323 | L15: -16.225 | M15: -63.924 | N15: -23.475 | O15: -125.594 | P15: 19.67 | Q15: -80 | R15: -43.214 | S15: -141.975 | T15: -25.891 | U15: -82.903 | AB15: -90 | AC15: -135.285 | AD15: -120.526 | AE15: -123.4 | AF15: -104.974 | AG15: -225.489 | AH15: -313.588 | AI15: -295.153 | AJ15: -243.06 | AK15: -230.94 | AL15: -246 | AM15: =AM14*-0.22 -> -280.12002 | AN15: =AN14*-0.22 -> -303.97327 | AO15: =AO14*-0.22 -> -344.11539 | AP15: =AP14*-0.22 -> -375.44174 | AQ15: =AQ14*-0.22 -> -408.8212 | AR15: =AR14*-0.22 -> -444.37512 | AS15: =AS14*-0.22 -> -469.27358 | AT15: =AT14*-0.22 -> -495.44376 | ... AV15: =AV14*-0.22 -> -551.8579
C16: Net income | D16: =SUM(D14:D15) -> 88.721 | E16: =SUM(E14:E15) -> 327.786 | F16: =SUM(F14:F15) -> 187.681 | G16: =SUM(G14:G15) -> 439.518 | H16: =SUM(H14:H15) -> 71.2 | I16: =SUM(I14:I15) -> 259.299 | J16: =SUM(J14:J15) -> 143.31 | K16: =SUM(K14:K15) -> 434.844 | ... U16: =SUM(U14:U15) -> 244.443 | AB16: =SUM(AB14:AB15) -> 277.61 | AC16: =SUM(AC14:AC15) -> 413.661 | AD16: =SUM(AD14:AD15) -> 389.799 | AE16: =SUM(AE14:AE15) -> 429.13 | AF16: =SUM(AF14:AF15) -> 375.436 | AG16: =SUM(AG14:AG15) -> 803.624 | AH16: =SUM(AH14:AH15) -> 1103.776 | AI16: =SUM(AI14:AI15) -> 1041.809 | ... AV16: =SUM(AV14:AV15) -> 1956.5871 | AW16: =AV16*(1+$AY$20) -> 1937.0212 | AX16: =AW16*(1+$AY$20) -> 1917.651 | AY16: =AX16*(1+$AY$20) -> 1898.4745 | AZ16: =AY16*(1+$AY$20) -> 1879.4897 | BA16: =AZ16*(1+$AY$20) -> 1860.6948 | BB16: =BA16*(1+$AY$20) -> 1842.0879 | BC16: =BB16*(1+$AY$20) -> 1823.667 | BD16: =BC16*(1+$AY$20) -> 1805.4303 | ... ET16: =ES16*(1+$AY$20) -> 701.92229
C17: Share | D17: 166.96889 | E17: 166.96889 | F17: 166.96889 | G17: 166.96889 | H17: 166.96889 | I17: 166.96889 | J17: 166.96889 | K17: 166.96889 | L17: 166.96889 | M17: 166.96889 | N17: 166.96889 | O17: 166.96889 | P17: 166.96889 | Q17: 166.96889 | R17: 166.96889 | S17: 166.96889 | T17: 166.96889 | U17: 166.96889 | AB17: 166.96889 | AC17: 166.96889 | AD17: 166.96889 | AE17: 166.96889 | AF17: 166.96889 | AG17: 166.96889 | AH17: 166.96889 | AI17: 166.96889 | AJ17: 166.96889 | AK17: 166.96889 | AL17: 166.96889 | AM17: 166.96889 | AN17: 166.96889 | AO17: 166.96889 | AP17: 166.96889 | AQ17: 166.96889 | AR17: 166.96889 | AS17: 166.96889 | AT17: 166.96889 | AU17: 166.96889 | AV17: 166.96889
C18: EPS | D18: =D16/D17 -> 0.53136247 | E18: =E16/E17 -> 1.9631562 | F18: =F16/F17 -> 1.1240477 | G18: =G16/G17 -> 2.6323347 | H18: =H16/H17 -> 0.42642675 | I18: =I16/I17 -> 1.5529779 | J18: =J16/J17 -> 0.85830361 | K18: =K16/K17 -> 2.6043415 | ... U18: =U16/U17 -> 1.4640033 | AB18: =AB16/AB17 -> 1.6626451 | AC18: =AC16/AC17 -> 2.4774735 | AD18: =AD16/AD17 -> 2.3345607 | AE18: =AE16/AE17 -> 2.5701195 | AF18: =AF16/AF17 -> 2.2485387 | AG18: =AG16/AG17 -> 4.8130164 | AH18: =AH16/AH17 -> 6.6106687 | AI18: =AI16/AI17 -> 6.2395397 | ... AV18: =AV16/AV17 -> 11.718273
AX19: Discount | AY19: 0.08
C20: Revenue y/y | H20: =(H4-D4)/D4 -> 0.12656173 | I20: =(I4-E4)/E4 -> 0.042552356 | J20: =(J4-F4)/F4 -> 0.049735122 | K20: =(K4-G4)/G4 -> 0.012449766 | L20: =(L4-H4)/H4 -> 0.048383316 | M20: =(M4-I4)/I4 -> 0.3455704 | N20: =(N4-J4)/J4 -> 0.50444688 | O20: =(O4-K4)/K4 -> 0.42510855 | ... U20: =(U4-Q4)/Q4 -> -0.028321359 | V20: =(AK29-R4)/R4 -> -1 | W20: =(W4-S4)/S4 -> -1 | AC20: =(AC4-AB4)/AB4 -> 0.098498628 | AD20: =(AD4-AC4)/AC4 -> 0.066334592 | AE20: =(AE4-AD4)/AD4 -> 0.072743535 | AF20: =(AF4-AE4)/AE4 -> 0.071756257 | AG20: =(AG4-AF4)/AF4 -> 0.28523084 | AH20: =(AH4-AG4)/AG4 -> 0.079318286 | AI20: =(AI4-AH4)/AH4 -> 0.042504796 | AJ20: =(AJ4-AI4)/AI4 -> 0.050040673 | ... AV20: =(AV4-AU4)/AU4 -> 0.05 | AX20: TV | AY20: -0.01
C21: Revenue CC | S21: 0.053 | T21: 0.116 | U21: 0.011 | AX21: NPV | AY21: =NPV(AY19,AM16:ET16) -> 19491.076
C22: Gross margin | D22: =D6/D4 -> 0.44271861 | E22: =E6/E4 -> 0.48239887 | F22: =F6/F4 -> 0.4757522 | G22: =G6/G4 -> 0.45454614 | H22: =H6/H4 -> 0.43468356 | I22: =I6/I4 -> 0.44511607 | J22: =J6/J4 -> 0.45306946 | K22: =K6/K4 -> 0.43874776 | ... U22: =U6/U4 -> 0.42420019 | V22: =AK31/AK29 -> #DIV/0! | W22: =W6/W4 -> #DIV/0! | AB22: =AB6/AB4 -> 0.44497554 | AC22: =AC6/AC4 -> 0.42912233 | AD22: =AD6/AD4 -> 0.42492803 | AE22: =AE6/AE4 -> 0.43298864 | AF22: =AF6/AF4 -> 0.43158343 | AG22: =AG6/AG4 -> 0.43412655 | AH22: =AH6/AH4 -> 0.46900451 | AI22: =AI6/AI4 -> 0.46396313 | ... AV22: =AV6/AV4 -> 0.42 | AX22: S/O | AY22: 166.96889
C23: EBIT margin | D23: =D10/D4 -> 0.073698709 | E23: =E10/E4 -> 0.19759142 | F23: =F10/F4 -> 0.13247122 | G23: =G10/G4 -> 0.19922196 | H23: =H10/H4 -> 0.075118578 | I23: =I10/I4 -> 0.1567432 | J23: =J10/J4 -> 0.10884232 | K23: =K10/K4 -> 0.18022134 | ... U23: =U10/U4 -> 0.10665535 | V23: =AK35/AK29 -> #DIV/0! | W23: =W10/W4 -> #DIV/0! | AB23: =AB10/AB4 -> 0.11504414 | AC23: =AC10/AC4 -> 0.11602246 | AD23: =AD10/AD4 -> 0.10179879 | AE23: =AE10/AE4 -> 0.10092378 | AF23: =AF10/AF4 -> 0.092804924 | AG23: =AG10/AG4 -> 0.14546799 | AH23: =AH10/AH4 -> 0.17480667 | AI23: =AI10/AI4 -> 0.15975969 | ... AV23: =AV10/AV4 -> 0.1188454 | AX23: NPV/Share | AY23: =AY21/AY22 -> 116.73478
AX24: Opp/Nedside | AY24: =(AY23-B4)/B4 -> 0.44117007
C25: EBITDA | D25: =D10-D8 -> 277.554 | E25: =E10-E8 -> 588.915 | F25: =F10-F8 -> 425.174 | G25: =G10-G8 -> 759.734 | H25: =H10-H8 -> 311.453 | I25: =I10-I8 -> 530.957 | J25: =J10-J8 -> 404.485 | K25: =K10-K8 -> 722.873 | ... U25: =U10-U8 -> 660.599 | AB25: =AB10-AB8 -> 603.627 | AC25: =AC10-AC8 -> 665.087 | AD25: =AD10-AD8 -> 634.697 | AE25: =AE10-AE8 -> 677.815 | AF25: =AF10-AF8 -> 1094.255 | AG25: =AG10-AG8 -> 1705.508 | AH25: =AH10-AH8 -> 2082.982 | AI25: =AI10-AI8 -> 2051.391 | ... AV25: =AV10-AV8 -> 4424.4039
C26: EBITDA Margin | D26: =D25/D4 -> 0.16178567 | E26: =E25/E4 -> 0.2657362 | F26: =F25/F4 -> 0.20740195 | G26: =G25/G4 -> 0.250404 | H26: =H25/H4 -> 0.16114992 | I26: =I25/I4 -> 0.22980506 | J26: =J25/J4 -> 0.18796147 | K26: =K25/K4 -> 0.23532508 | ... U26: =U25/U4 -> 0.1788293 | AB26: =AB25/AB4 -> 0.13039463 | AC26: =AC25/AC4 -> 0.13078863 | AD26: =AD25/AD4 -> 0.11704813 | AE26: =AE25/AE4 -> 0.11652344 | AF26: =AF25/AF4 -> 0.1755192 | AG26: =AG25/AG4 -> 0.21285249 | AH26: =AH25/AH4 -> 0.24085793 | AI26: =AI25/AI4 -> 0.22753374 | ... AV26: =AV25/AV4 -> 0.18610982
C27: EBITDA LTM | G27: =SUM(D25:G25) -> 2051.377 | H27: =SUM(E25:H25) -> 2085.276 | I27: =SUM(F25:I25) -> 2027.318 | J27: =SUM(G25:J25) -> 2006.629 | K27: =SUM(H25:K25) -> 1969.768 | L27: =SUM(I25:L25) -> 1939.218 | M27: =SUM(J25:M25) -> 1974.833 | N27: =SUM(K25:N25) -> 1998.159 | ... U27: =SUM(R25:U25) -> 2466.836
C29: Balanse NOKm
C30: Total intangible assets | D30: 2732.237 | E30: 2746.834 | F30: 2860.238 | G30: 2875.288 | H30: 2877.76 | I30: 2873.901 | J30: 2867.925 | K30: 2861.038 | L30: 2855.62 | M30: 3028.822 | N30: 3028.96 | O30: 3225.084 | P30: 3260.961 | Q30: 3269.968 | R30: 3268.921 | S30: 3264.029 | T30: 3233.087 | U30: 3227.933 | AB30: 2010.804 | AC30: 2016.904 | AD30: 2029.297 | AE30: 2040.688 | AF30: 2044.669 | AG30: 2063.334 | AH30: 2730.06 | AI30: 2875.288 | AJ30: 3028.96 | AK30: 3225.084 | AL30: 3264.029
C31: Total fixed assets | D31: 2812.759 | E31: 2852.435 | F31: 2812.835 | G31: 2906.989 | H31: 3080.754 | I31: 3029.143 | J31: 2991.844 | K31: 3050.724 | L31: 3018.191 | M31: 4043.876 | N31: 3931.63 | O31: 3906.721 | P31: 3945.889 | Q31: 3859.11 | R31: 3775.442 | S31: 3868.835 | T31: 3966.798 | U31: 3959.572 | AB31: 225.178 | AC31: 246.377 | AD31: 272.54 | AE31: 262.063 | AF31: 2743.235 | AG31: 2588.921 | AH31: 2814.094 | AI31: 2906.989 | AJ31: 3931.63 | AK31: 3906.721 | AL31: 3868.835
C32: Total financial assets | D32: 224.773 | E32: 241.828 | F32: 249.018 | G32: 246.617 | H32: 234.01 | I32: 257.449 | J32: 218.536 | K32: 253.91 | L32: 147.753 | M32: 79.963 | N32: 68.682 | O32: 75.56 | P32: 72.121 | Q32: 60.702 | R32: 62.299 | S32: 57.83 | T32: 62.467 | U32: 66.86 | AB32: 5.211 | AC32: 2.234 | AD32: 25.175 | AE32: 166.952 | AF32: 151.266 | AG32: 168.886 | AH32: 195.294 | AI32: 246.617 | AJ32: 68.682 | AK32: 75.56 | AL32: 57.83
C33: Inventories | D33: 2350.732 | E33: 2234.997 | F33: 2607.803 | G33: 2383.837 | H33: 2499.389 | I33: 2254.313 | J33: 2364.07 | K33: 2142.699 | L33: 2296.768 | M33: 3133.408 | N33: 3535.903 | O33: 3292.289 | P33: 3714.419 | Q33: 3581.203 | R33: 3883.102 | S33: 3580.859 | T33: 3717.858 | U33: 3369.842 | AB33: 1109.189 | AC33: 1324.103 | AD33: 1368.361 | AE33: 1573.233 | AF33: 1550.331 | AG33: 1633.927 | AH33: 1997.312 | AI33: 2383.837 | AJ33: 3535.903 | AK33: 3292.289 | AL33: 3580.859
C34: Trade receivables | D34: 145.801 | E34: 140.499 | F34: 137.581 | G34: 215.175 | H34: 157.956 | I34: 148.09 | J34: 145.909 | K34: 217.673 | L34: 170.839 | M34: 218.931 | N34: 185.87 | O34: 226.921 | P34: 184.304 | Q34: 146.994 | R34: 188.656 | S34: 218.515 | T34: 225.396 | U34: 204.439 | AB34: 239.627 | AC34: 203.346 | AD34: 207.755 | AE34: 185.712 | AF34: 181.774 | AG34: 195.287 | AH34: 215.48 | AI34: 215.175 | AJ34: 185.87 | AK34: 226.921 | AL34: 218.515
C35: Other receivables | D35: 93.643 | E35: 133.047 | F35: 172.364 | G35: 132.863 | H35: 101.585 | I35: 98.128 | J35: 122.987 | K35: 109.848 | L35: 100.407 | M35: 149.893 | N35: 153.419 | O35: 214.941 | P35: 166.1 | Q35: 180.622 | R35: 196.278 | S35: 253.141 | T35: 182.518 | U35: 206.62 | AB35: 56.877 | AC35: 66.539 | AD35: 63.586 | AE35: 101.722 | AF35: 76.417 | AG35: 87.816 | AH35: 116.551 | AI35: 132.863 | AJ35: 153.419 | AK35: 214.941 | AL35: 253.141
C36: Cash | D36: 0 | E36: 0 | F36: 0 | G36: 464.488 | H36: 0 | I36: 0 | J36: 81.196 | K36: 676.323 | L36: 186.279 | M36: 129.306 | N36: 94.454 | O36: 603.362 | P36: 146.88 | Q36: 329.44 | R36: 356.38 | S36: 988.122 | T36: 607.286 | U36: 830.034 | AB36: 447.116 | AC36: 576.964 | AD36: 581.663 | AE36: 426.967 | AF36: 568.036 | AG36: 540.056 | AH36: 570.286 | AI36: 464.488 | AJ36: 94.454 | AK36: 603.362 | AL36: 988.122
C37: Total assets | D37: =SUM(D30:D36) -> 8359.945 | E37: =SUM(E30:E36) -> 8349.64 | F37: =SUM(F30:F36) -> 8839.839 | G37: =SUM(G30:G36) -> 9225.257 | H37: =SUM(H30:H36) -> 8951.454 | I37: =SUM(I30:I36) -> 8661.024 | J37: =SUM(J30:J36) -> 8792.467 | K37: =SUM(K30:K36) -> 9312.215 | ... W37: =SUM(W30:W36) -> 0 | AB37: =SUM(AB30:AB36) -> 4094.002 | AC37: =SUM(AC30:AC36) -> 4436.467 | AD37: =SUM(AD30:AD36) -> 4548.377 | AE37: =SUM(AE30:AE36) -> 4757.337 | AF37: =SUM(AF30:AF36) -> 7315.728 | AG37: =SUM(AG30:AG36) -> 7278.227 | AH37: =SUM(AH30:AH36) -> 8639.077 | AI37: =SUM(AI30:AI36) -> 9225.257 | ... AL37: =SUM(AL30:AL36) -> 12231.331
C38: Total paid-in capital | D38: 233.342 | E38: 233.342 | F38: 234.737 | G38: 234.738 | H38: 234.738 | I38: 234.738 | J38: 235.171 | K38: 235.171 | L38: 235.171 | M38: 308.341 | N38: 308.341 | O38: 308.341 | P38: 308.341 | Q38: 308.341 | R38: 308.341 | S38: 308.341 | T38: 308.341 | U38: 308.341 | AB38: 1070.162 | AC38: 836.406 | AD38: 502.468 | AE38: 213.251 | AF38: 234.946 | AG38: 229.946 | AH38: 233.342 | AI38: 234.738 | AJ38: 308.341 | AK38: 308.341 | AL38: 308.341
C39: Total retained equity | D39: 2474.424 | E39: 2156.167 | F39: 2300.809 | G39: 2725.783 | H39: 3075.425 | I39: 2731.438 | J39: 2875.029 | K39: 3325.642 | L39: 3372.858 | M39: 3216.743 | N39: 3314.417 | O39: 3749.207 | P39: 3673.968 | Q39: 3379.027 | R39: 3532.653 | S39: 4008.598 | T39: 3987.562 | U39: 3616.648 | AB39: 458.305 | AC39: 871.966 | AD39: 1261.765 | AE39: 1575.677 | AF39: 1742.923 | AG39: 1983.662 | AH39: 2386.704 | AI39: 2725.783 | AJ39: 3314.417 | AK39: 3749.207 | AL39: 4008.598
C40: Non-controlling interests | D40: 253.357 | E40: 255.957 | F40: 300.746 | G40: 322.082 | H40: 50.726 | I40: 49.962 | J40: 49.552 | K40: 50.617 | L40: 50.564 | M40: 50.316 | N40: 60.087 | O40: 51.299 | P40: 45.896 | Q40: 45.833 | R40: 45.561 | S40: 47.11 | T40: 47.658 | U40: 47.402 | AB40: 0 | AC40: 0 | AD40: 0 | AE40: 0 | AF40: 0 | AG40: 0 | AH40: 268.68 | AI40: 322.082 | AJ40: 60.087 | AK40: 51.299 | AL40: 47.11
C41: Total equity | D41: =SUM(D38:D40) -> 2961.123 | E41: =SUM(E38:E40) -> 2645.466 | F41: =SUM(F38:F40) -> 2836.292 | G41: =SUM(G38:G40) -> 3282.603 | H41: =SUM(H38:H40) -> 3360.889 | I41: =SUM(I38:I40) -> 3016.138 | J41: =SUM(J38:J40) -> 3159.752 | K41: =SUM(K38:K40) -> 3611.43 | ... W41: =SUM(W38:W40) -> 0 | AB41: =SUM(AB38:AB40) -> 1528.467 | AC41: =SUM(AC38:AC40) -> 1708.372 | AD41: =SUM(AD38:AD40) -> 1764.233 | AE41: =SUM(AE38:AE40) -> 1788.928 | AF41: =SUM(AF38:AF40) -> 1977.869 | AG41: =SUM(AG38:AG40) -> 2213.608 | AH41: =SUM(AH38:AH40) -> 2888.726 | AI41: =SUM(AI38:AI40) -> 3282.603 | ... AL41: =SUM(AL38:AL40) -> 4364.049
C42: Provisions | D42: 79.898 | E42: 170.866 | F42: 222.653 | G42: 57.622 | H42: 79.58 | I42: 152.921 | J42: 194.611 | K42: 46.703 | L42: 62.507 | M42: 77 | N42: 95.973 | O42: 56.06 | P42: 64.02 | Q42: 153.096 | R42: 207.698 | S42: 40 | T42: 66.541 | U42: 149.8 | AB42: 57.92 | AC42: 45.575 | AD42: 48.25 | AE42: 45.146 | AF42: 31.763 | AG42: 4.726 | AH42: 52.332 | AI42: 57.622 | AJ42: 95.973 | AK42: 56.06 | AL42: 40
C43: Non-current Borrowings | D43: 1089.032 | E43: 1092.782 | F43: 1092.97 | G43: 1085.349 | H43: 1083.918 | I43: 1083.448 | J43: 1082.013 | K43: 1041.843 | L43: 1021.9 | M43: 1020.455 | N43: 1019.072 | O43: 1018.516 | P43: 998.266 | Q43: 998.266 | R43: 998.266 | S43: 996.972 | T43: 998.375 | U43: 998.375 | AB43: 1652.651 | AC43: 1648.146 | AD43: 1650.78 | AE43: 1649.428 | AF43: 14.28 | AG43: 995.082 | AH43: 1091.521 | AI43: 1085.349 | AJ43: 1019.072 | AK43: 1018.516 | AL43: 996.972
C44: Lease liabilties | D44: 1911.869 | E44: 1953.754 | F44: 1917.489 | G44: 2015.033 | H44: 2094.547 | I44: 2050.06 | J44: 2009.521 | K44: 2079.997 | L44: 2006.441 | M44: 2671.314 | N44: 2569.723 | O44: 2566.863 | P44: 2573.886 | Q44: 2499.668 | R44: 2448.366 | S44: 2520.948 | T44: 2551.413 | U44: 2502.784 | AB44: 0 | AC44: 0 | AD44: 0 | AE44: 0 | AF44: 2003.993 | AG44: 1850.561 | AH44: 1913.555 | AI44: 2015.033 | AJ44: 2569.723 | AK44: 2566.863 | AL44: 2520.948
C45: Current Borrowings | D45: 10.868 | E45: 382.598 | F45: 423.998 | G45: 5 | H45: 345.911 | I45: 533.141 | J45: 255 | K45: 5 | L45: 5 | M45: 628.679 | N45: 689.387 | O45: 304.48 | P45: 669.604 | Q45: 1174.014 | R45: 1153.232 | S45: 849.281 | T45: 911.231 | U45: 1458.615 | AB45: 0 | AC45: 0 | AD45: 0 | AE45: 0 | AF45: 1642.007 | AG45: 0 | AH45: 5 | AI45: 5 | AJ45: 689.387 | AK45: 304.48 | AL45: 849.281
C46: Current lease liabilties | D46: 519.632 | E46: 525.175 | F46: 523.962 | G46: 521.958 | H46: 582.678 | I46: 584.212 | J46: 586.248 | K46: 588.626 | L46: 607.91 | M46: 905.757 | N46: 907.421 | O46: 893.019 | P46: 919.07 | Q46: 917.021 | R46: 896.788 | S46: 913.41 | T46: 950.547 | U46: 953.418 | AB46: 0 | AC46: 0 | AD46: 0 | AE46: 0 | AF46: 414.088 | AG46: 473.739 | AH46: 490.164 | AI46: 521.958 | AJ46: 907.421 | AK46: 893.019 | AL46: 913.41
C47: Accounts payable | D47: 780.811 | E47: 737.462 | F47: 843.5 | G47: 876.419 | H47: 645.229 | I47: 648.136 | J47: 869.028 | K47: 879.851 | L47: 782.813 | M47: 1098.578 | N47: 1207.827 | O47: 1255.066 | P47: 1197.939 | Q47: 1023.912 | R47: 1145.986 | S47: 1077.064 | T47: 1228.692 | U47: 951.079 | AB47: 444.888 | AC47: 555.651 | AD47: 580.795 | AE47: 553.643 | AF47: 616.769 | AG47: 742.753 | AH47: 843.854 | AI47: 876.419 | AJ47: 1207.827 | AK47: 1255.066 | AL47: 1077.064
C48: Tax payable | D48: 183.216 | E48: 57.435 | F48: 73.164 | G48: 291.305 | H48: 120.381 | I48: -1.383 | J48: 1.295 | K48: 254.838 | L48: 118.022 | M48: -0.478 | N48: -0.448 | O48: 248.193 | P48: 125.897 | Q48: 0 | R48: 0.11 | S48: 298.427 | T48: 87.187 | U48: 50.957 | AB48: 107.985 | AC48: 145.446 | AD48: 116.767 | AE48: 124.14 | AF48: 116.38 | AG48: 251.879 | AH48: 324.057 | AI48: 291.305 | AJ48: -0.448 | AK48: 248.193 | AL48: 298.427
C49: Public duties payable | D49: 210.788 | E49: 260.921 | F49: 265.217 | G49: 393.683 | H49: 226.297 | I49: 305.968 | J49: 280.816 | K49: 396.594 | L49: 258.175 | M49: 303.61 | N49: 284.539 | O49: 417.651 | P49: 234.845 | Q49: 312.291 | R49: 346.86 | S49: 462.348 | T49: 246.239 | U49: 300.849 | AB49: 127.154 | AC49: 149.167 | AD49: 205.279 | AE49: 251.54 | AF49: 243.072 | AG49: 323.511 | AH49: 376.023 | AI49: 393.683 | AJ49: 284.539 | AK49: 417.651 | AL49: 462.348
C50: Put option liability | D50: 246.528 | E50: 246.528 | F50: 290.069 | G50: 281.221 | H50: 43.541 | I50: 43.541 | J50: 43.541 | K50: 27.98 | L50: 27.98 | M50: 27.98 | N50: 27.98 | O50: 30.39 | P50: 30.39 | Q50: 30.39 | R50: 30.39 | S50: 27.802 | T50: 27.802 | U50: 27.802 | AB50: 0 | AC50: 0 | AD50: 0 | AE50: 0 | AF50: 0 | AG50: 0 | AH50: 246.528 | AI50: 281.221 | AJ50: 27.98 | AK50: 30.39 | AL50: 27.802
C51: Other current liabilities | D51: 366.179 | E51: 276.654 | F51: 350.526 | G51: 415.063 | H51: 368.481 | I51: 244.842 | J51: 310.65 | K51: 379.353 | L51: 328.304 | M51: 475.899 | N51: 524.601 | O51: 644.792 | P51: 648.643 | Q51: 586.175 | R51: 616.829 | S51: 681.013 | T51: 583.822 | U51: 499.231 | AB51: 174.935 | AC51: 184.11 | AD51: 182.275 | AE51: 344.512 | AF51: 255.505 | AG51: 422.368 | AH51: 407.319 | AI51: 415.063 | AJ51: 524.601 | AK51: 644.792 | AL51: 681.013
C52: Total debt | D52: =SUM(D42:D51) -> 5398.821 | E52: =SUM(E42:E51) -> 5704.175 | F52: =SUM(F42:F51) -> 6003.548 | G52: =SUM(G42:G51) -> 5942.653 | H52: =SUM(H42:H51) -> 5590.563 | I52: =SUM(I42:I51) -> 5644.886 | J52: =SUM(J42:J51) -> 5632.723 | K52: =SUM(K42:K51) -> 5700.785 | ... W52: =SUM(W42:W51) -> 0 | AB52: =SUM(AB42:AB51) -> 2565.533 | AC52: =SUM(AC42:AC51) -> 2728.095 | AD52: =SUM(AD42:AD51) -> 2784.146 | AE52: =SUM(AE42:AE51) -> 2968.409 | AF52: =SUM(AF42:AF51) -> 5337.857 | AG52: =SUM(AG42:AG51) -> 5064.619 | AH52: =SUM(AH42:AH51) -> 5750.353 | AI52: =SUM(AI42:AI51) -> 5942.653 | ... AL52: =SUM(AL42:AL51) -> 7867.265
C53: Total E/D | D53: =D41+D52 -> 8359.944 | E53: =E41+E52 -> 8349.641 | F53: =F41+F52 -> 8839.84 | G53: =G41+G52 -> 9225.256 | H53: =H41+H52 -> 8951.452 | I53: =I41+I52 -> 8661.024 | J53: =J41+J52 -> 8792.475 | K53: =K41+K52 -> 9312.215 | ... W53: =W41+W52 -> 0 | AB53: =AB41+AB52 -> 4094 | AC53: =AC41+AC52 -> 4436.467 | AD53: =AD41+AD52 -> 4548.379 | AE53: =AE41+AE52 -> 4757.337 | AF53: =AF41+AF52 -> 7315.726 | AG53: =AG41+AG52 -> 7278.227 | AH53: =AH41+AH52 -> 8639.079 | AI53: =AI41+AI52 -> 9225.256 | ... AL53: =AL41+AL52 -> 12231.314
C55: Cash flow NOKm
C56: Model PTP | D56: =D14 -> 116.347 | E56: =E14 -> 418.755 | F56: =F14 -> 240.222 | G56: =G14 -> 561.623 | H56: =H14 -> 93.515 | I56: =I14 -> 332.435 | J56: =J14 -> 185 | K56: =K14 -> 541.167 | ... U56: =U14 -> 327.346 | V56: =AK39 -> 3749.207 | W56: =W14 -> 0 | AB56: =AB14 -> 367.61 | AC56: =AC14 -> 548.946 | AD56: =AD14 -> 510.325 | AE56: =AE14 -> 552.53 | AF56: =AF14 -> 480.41 | AG56: =AG14 -> 1029.113 | AH56: =AH14 -> 1417.364 | AI56: =AI14 -> 1336.962 | ... AL56: =AL14 -> 1061
C57: Reported PTP | D57: 116 | E57: 418.763 | F57: 240 | G57: 561.628 | H57: 94 | I57: 332 | J57: 185 | K57: 541.165 | L57: 63 | M57: 330.884 | N57: 107.101 | O57: 569.218 | P57: -100 | Q57: 356.228 | R57: 197 | S57: 607 | T57: 30.845 | U57: 327.345 | AB57: 367.61 | AC57: 548.946 | AD57: 510.326 | AE57: 552.531 | AF57: 480.41 | AG57: 1029.112 | AH57: 1417.551 | AI57: 1337.009 | AJ57: 1151.912 | AK57: 1068.978 | AL57: 1053.87
C58: Dep | D58: 151.119 | E58: 151.02 | F58: 153.608 | G58: 155.288 | H58: 166.272 | I58: 168.807 | J58: 170.261 | K58: 169.268 | L58: 174.34 | M58: 227.801 | N58: 260.318 | O58: 260.468 | P58: 260.72 | Q58: 266.876 | R58: 265.276 | S58: 267.378 | T58: 268.72 | U58: 266.612 | AB58: 71.061 | AC58: 75.089 | AD58: 82.69 | AE58: 90.743 | AF58: 515.673 | AG58: 539.928 | AH58: 571.223 | AI58: 611.035 | AJ58: 674.608 | AK58: 922.927 | AL58: 1060.249
C59: Change in fair value of option | D59: 0.945 | E59: 0 | F59: 0 | G59: 0 | H59: 0 | I59: 0 | J59: 0 | K59: -101.789 | L59: 0 | M59: -32.3 | N59: 0 | O59: 0 | P59: 0 | Q59: 0 | R59: 0 | S59: 0 | T59: 0 | U59: 0 | AB59: 0 | AC59: 0 | AD59: 0 | AE59: 0 | AF59: 0 | AG59: 0 | AH59: 0 | AI59: 0 | AJ59: -101.789 | AK59: -32.309 | AL59: 0
C60: Share of profit/loss | D60: 9.226 | E60: -5.266 | F60: -1.4 | G60: -6.6 | H60: 7.9 | I60: 0.158 | J60: 4.515 | K60: 41.902 | L60: 10.976 | M60: -12.54 | N60: 0 | O60: -0.029 | P60: 0 | Q60: 0 | R60: 0 | S60: 0 | T60: 0 | U60: 0 | AB60: 0 | AC60: 0 | AD60: 0 | AE60: -6.4 | AF60: 0 | AG60: -2.6 | AH60: -0.189 | AI60: -4.047 | AJ60: 54.489 | AK60: -1.592 | AL60: 0
C61: WC | D61: -597.871 | E61: 15.1 | F61: -210.652 | G61: 419.481 | H61: -464.264 | I61: 194.88 | J61: 163.207 | K61: 385.114 | L61: -391.46 | M61: 94 | N61: -210.597 | O61: 297.499 | P61: -581.397 | Q61: 13.584 | R61: -167.238 | S61: 345.869 | T61: -340.131 | U61: 119.796 | AB61: -46.141 | AC61: -47.196 | AD61: 25.447 | AE61: -172.05 | AF61: 159.791 | AG61: 255.298 | AH61: -138.705 | AI61: -373.103 | AJ61: 280.976 | AK61: -210.548 | AL61: -396.322
C62: Income tax paid | D62: -113.604 | E62: -153.353 | F62: 14.774 | G62: -71.079 | H62: -171.407 | I62: -121.764 | J62: 2.6 | K62: -0.689 | L62: -136.875 | M62: -118.491 | N62: 0 | O62: 3.72 | P62: -123.311 | Q62: -133.25 | R62: -0.835 | S62: -3.7 | T62: -122.595 | U62: -123.2 | AB62: -95.254 | AC62: -108.772 | AD62: -145.832 | AE62: -117.069 | AF62: -124.173 | AG62: -116.814 | AH62: -258.529 | AI62: -323.191 | AJ62: -291.189 | AK62: -251.645 | AL62: -247.242
C63: CFFO | D63: =SUM(D57:D62) -> -434.185 | E63: =SUM(E57:E62) -> 426.264 | F63: =SUM(F57:F62) -> 196.33 | G63: =SUM(G57:G62) -> 1058.718 | H63: =SUM(H57:H62) -> -367.499 | I63: =SUM(I57:I62) -> 574.081 | J63: =SUM(J57:J62) -> 525.583 | K63: =SUM(K57:K62) -> 1034.971 | ... W63: =SUM(W57:W62) -> 0 | AB63: =SUM(AB57:AB62) -> 297.276 | AC63: =SUM(AC57:AC62) -> 468.067 | AD63: =SUM(AD57:AD62) -> 472.631 | AE63: =SUM(AE57:AE62) -> 347.755 | AF63: =SUM(AF57:AF62) -> 1031.701 | AG63: =SUM(AG57:AG62) -> 1704.924 | AH63: =SUM(AH57:AH62) -> 1591.351 | AI63: =SUM(AI57:AI62) -> 1247.703 | ... AL63: =SUM(AL57:AL62) -> 1470.555
C65: Capex | D65: =26.021-29.76 -> -3.739 | E65: -31.931 | F65: -33.788 | G65: -47.198 | H65: -70.448 | I65: -23.296 | J65: -32.575 | K65: -15.38 | L65: -49.28 | M65: -36.826 | N65: -24.599 | O65: -27.756 | P65: -45.174 | Q65: -25.4 | R65: -24.389 | S65: -36.348 | T65: -73.747 | U65: -78.595 | AB65: -111.582 | AC65: -85.256 | AD65: -99.116 | AE65: -76.509 | AF65: -156.219 | AG65: -104.146 | AH65: -130.702 | AI65: -116.656 | AJ65: -141.617 | AK65: -138.46 | AL65: -131.312
C66: Acquisition | D66: 0.637 | E66: -5.626 | F66: -87.362 | G66: 0 | H66: -216.598 | I66: 0 | J66: 0 | K66: 0 | L66: 0.74 | M66: 18.3 | N66: 0 | O66: 0 | P66: 4.8 | Q66: 0 | R66: 0 | S66: -0.033 | T66: 0 | U66: 0 | AB66: -2.656 | AC66: -11.229 | AD66: -28.403 | AE66: -12.875 | AF66: -2.711 | AG66: -7.979 | AH66: -553.204 | AI66: -92.351 | AJ66: -216.598 | AK66: 19.047 | AL66: 4.766
C67: CFFI | D67: =SUM(D65:D66) -> -3.102 | E67: =SUM(E65:E66) -> -37.557 | F67: =SUM(F65:F66) -> -121.15 | G67: =SUM(G65:G66) -> -47.198 | H67: =SUM(H65:H66) -> -287.046 | I67: =SUM(I65:I66) -> -23.296 | J67: =SUM(J65:J66) -> -32.575 | K67: =SUM(K65:K66) -> -15.38 | ... W67: =SUM(W65:W66) -> 0 | AB67: =SUM(AB65:AB66) -> -114.238 | AC67: =SUM(AC65:AC66) -> -96.485 | AD67: =SUM(AD65:AD66) -> -127.519 | AE67: =SUM(AE65:AE66) -> -89.384 | AF67: =SUM(AF65:AF66) -> -158.93 | AG67: =SUM(AG65:AG66) -> -112.125 | AH67: =SUM(AH65:AH66) -> -683.906 | AI67: =SUM(AI65:AI66) -> -209.007 | ... AL67: =SUM(AL65:AL66) -> -126.546
C69: Net change in RFC | D69: 0 | E69: 350 | F69: -50 | G69: -300 | H69: 310 | I69: 90 | J69: -150 | K69: -250 | L69: 0 | M69: 193.346 | N69: 44.495 | O69: -379.846 | P69: 363.547 | Q69: 501.6 | R69: -20.463 | S69: -313.743 | T69: 81.175 | U69: 548.761 | AB69: 1642.318 | AC69: 0 | AD69: 0 | AE69: 0 | AF69: 0 | AG69: 1000 | AH69: 2.636 | AI69: 0 | AJ69: 0 | AK69: -142.005 | AL69: 530.941
C70: Repayment of debt | D70: -1.25 | E70: -1.25 | F70: -1.25 | G70: -1.25 | H70: -1.25 | I70: -1.25 | J70: -1.25 | K70: -41.988 | L70: -10.942 | M70: -9.6 | N70: -1.423 | O70: -0.544 | P70: -25.25 | Q70: 0 | R70: 0 | S70: -1.294 | T70: 0 | U70: 0 | AB70: -1669.541 | AC70: -7.978 | AD70: -6.475 | AE70: -8.629 | AF70: -6.84 | AG70: -1651.675 | AH70: -3.75 | AI70: -5 | AJ70: -45.738 | AK70: -24.405 | AL70: -26.544
C71: Principal paid on lease | D71: -121.463 | E71: -120.309 | F71: -118.456 | G71: -121.781 | H71: -131.335 | I71: -133.176 | J71: -133.1 | K71: -132.56 | L71: -141.268 | M71: -188.514 | N71: -209.912 | O71: -213.822 | P71: -210.891 | Q71: -223.914 | R71: -222.3 | S71: -234.227 | T71: -223.602 | U71: -224.178 | AB71: 0 | AC71: 0 | AD71: 0 | AE71: 0 | AF71: -423.169 | AG71: -401.218 | AH71: -449.162 | AI71: -482.008 | AJ71: -530.172 | AK71: -760.66 | AL71: -891.332
C72: Dividend | D72: 0 | E72: -643.886 | F72: 0 | G72: 0 | H72: 0 | I72: -603.865 | J72: 0 | K72: 0 | L72: 0 | M72: -523.403 | N72: -0.234 | O72: 0.078 | P72: 0 | Q72: -573.135 | R72: 0 | S72: 0 | T72: 0 | U72: -613.685 | AB72: 0 | AC72: -233.756 | AD72: -333.938 | AE72: -283.847 | AF72: -298.717 | AG72: -323.346 | AH72: -434.207 | AI72: -643.886 | AJ72: -603.865 | AK72: -523.559 | AL72: -573.015
C73: Sale of treasury shares | D73: 0 | E73: 0 | F73: 2.9 | G73: 0 | H73: 0 | I73: 0 | J73: 0.85 | K73: 0 | L73: 0 | M73: 1.35 | N73: 0 | O73: 0 | P73: 0 | Q73: 0 | R73: 0 | S73: 0 | T73: 0 | U73: 0 | AB73: 46.284 | AC73: 0 | AD73: 0 | AE73: -120.59 | AF73: -2.975 | AG73: -244.539 | AH73: 7.27 | AI73: 2.9 | AJ73: 0.85 | AK73: 1.35 | AL73: 0
C74: Dividend to non-controlling int | D74: -16.5 | E74: 0 | F74: 0 | G74: 0 | H74: 0 | I74: 0 | J74: -0.234 | K74: 0 | L74: 0 | M74: 0 | N74: 0 | O74: -0.078 | P74: 0 | Q74: -0.179 | R74: 0 | S74: 0 | T74: 0 | U74: 0 | AB74: 0 | AC74: 0 | AD74: 0 | AE74: 0 | AF74: 0 | AG74: 0 | AH74: 0 | AI74: -16.5 | AJ74: -20.034 | AK74: -0.078 | AL74: -0.298
C75: CFFF | D75: =SUM(D69:D74) -> -139.213 | E75: =SUM(E69:E74) -> -415.445 | F75: =SUM(F69:F74) -> -166.806 | G75: =SUM(G69:G74) -> -423.031 | H75: =SUM(H69:H74) -> 177.415 | I75: =SUM(I69:I74) -> -648.291 | J75: =SUM(J69:J74) -> -283.734 | K75: =SUM(K69:K74) -> -424.548 | ... W75: =SUM(W69:W74) -> 0 | AB75: =SUM(AB69:AB74) -> 19.061 | AC75: =SUM(AC69:AC74) -> -241.734 | AD75: =SUM(AD69:AD74) -> -340.413 | AE75: =SUM(AE69:AE74) -> -413.066 | AF75: =SUM(AF69:AF74) -> -731.701 | AG75: =SUM(AG69:AG74) -> -1620.778 | AH75: =SUM(AH69:AH74) -> -877.213 | AI75: =SUM(AI69:AI74) -> -1144.494 | ... AL75: =SUM(AL69:AL74) -> -960.248
C77: FX | D77: 0 | E77: 0 | F77: 0 | G77: 0 | H77: 0 | I77: 0 | J77: 0 | K77: 0 | L77: 0 | M77: 0 | N77: 0 | O77: 0 | P77: 0.349 | Q77: 0.149 | R77: 0 | S77: 0.519 | T77: -1.501 | U77: -0.108 | AB77: 0 | AC77: 0 | AD77: 0 | AE77: 0 | AF77: 0 | AG77: 0 | AH77: 0 | AI77: 0 | AJ77: 0 | AK77: 0 | AL77: 1
C79: CIC | D79: =D63+D67+D75+D77 -> -576.5 | E79: =E63+E67+E75+E77 -> -26.738 | F79: =F63+F67+F75+F77 -> -91.626 | G79: =G63+G67+G75+G77 -> 588.489 | H79: =H63+H67+H75+H77 -> -477.13 | I79: =I63+I67+I75+I77 -> -97.506 | J79: =J63+J67+J75+J77 -> 209.274 | K79: =K63+K67+K75+K77 -> 595.043 | ... W79: =W63+W67+W75+W77 -> 0 | AB79: =AB63+AB67+AB75+AB77 -> 202.099 | AC79: =AC63+AC67+AC75+AC77 -> 129.848 | AD79: =AD63+AD67+AD75+AD77 -> 4.699 | AE79: =AE63+AE67+AE75+AE77 -> -154.695 | AF79: =AF63+AF67+AF75+AF77 -> 141.07 | AG79: =AG63+AG67+AG75+AG77 -> -27.979 | AH79: =AH63+AH67+AH75+AH77 -> 30.232 | AI79: =AI63+AI67+AI75+AI77 -> -105.798 | ... AL79: =AL63+AL67+AL75+AL77 -> 384.761
C81: FCF | D81: =D63+D65 -> -437.924 | E81: =E63+E65 -> 394.333 | F81: =F63+F65 -> 162.542 | G81: =G63+G65 -> 1011.52 | H81: =H63+H65 -> -437.947 | I81: =I63+I65 -> 550.785 | J81: =J63+J65 -> 493.008 | K81: =K63+K65 -> 1019.591 | ... W81: =W63+W65 -> 0 | AB81: =AB63+AB65 -> 185.694 | AC81: =AC63+AC65 -> 382.811 | AD81: =AD63+AD65 -> 373.515 | AE81: =AE63+AE65 -> 271.246 | AF81: =AF63+AF65 -> 875.482 | AG81: =AG63+AG65 -> 1600.778 | AH81: =AH63+AH65 -> 1460.649 | AI81: =AI63+AI65 -> 1131.047 | ... AL81: =AL63+AL65 -> 1339.243

Sheet Segementer
B5: NOKm | C5: Q122 | D5: Q222 | E5: Q322 | F5: Q422 | G5: 2022 | H5: Q123 | I5: Q223 | J5: Q323 | K5: Q423 | L5: 2023 | M5: Q124 | N5: Q224 | O5: Q324 | P5: Q424 | Q5: 2024 | R5: Q125 | S5: Q225 | T5: Q325 | U5: Q425 | V5: 2025 | W5: Q126 | X5: Q226 | Y5: Q326 | Z5: Q426 | AA5: 2026 | AB5: Q127 | AC5: Q227 | AD5: Q327 | AE5: Q427 | AF5: 2027 | AG5: Q128 | AH5: Q228 | AI5: Q328 | AJ5: Q428 | AK5: 2028
B6: Norge
B7: Revenue | M7: 2026 | N7: 2381 | O7: 2248 | P7: 3223 | Q7: =SUM(M7:P7) -> 9878 | R7: 2050 | S7: 2660 | T7: 2508 | U7: 3372 | V7: =SUM(R7:U7) -> 10590 | W7: 2332 | X7: 2662
B8: y/y | H8: =(H7-C7)/C7 -> #DIV/0! | I8: =(I7-D7)/D7 -> #DIV/0! | J8: =(J7-E7)/E7 -> #DIV/0! | K8: =(K7-F7)/F7 -> #DIV/0! | L8: =(L7-G7)/G7 -> #DIV/0! | M8: =(M7-H7)/H7 -> #DIV/0! | N8: =(N7-I7)/I7 -> #DIV/0! | O8: =(O7-J7)/J7 -> #DIV/0! | ... AK8: =(AK7-AF7)/AF7 -> #DIV/0!
B9: y/y LC | X9: -0.009
B10: COGS | M10: 1148 | N10: 1315 | O10: 1265 | P10: 1737 | Q10: =SUM(M10:P10) -> 5465 | R10: 1170 | S10: 1466 | T10: 1388 | U10: 1832 | V10: =SUM(R10:U10) -> 5856 | W10: 1341 | X10: 1445
B11: Gross profit | C11: =C7-C10 -> 0 | D11: =D7-D10 -> 0 | E11: =E7-E10 -> 0 | F11: =F7-F10 -> 0 | G11: =G7-G10 -> 0 | H11: =H7-H10 -> 0 | I11: =I7-I10 -> 0 | J11: =J7-J10 -> 0 | ... AK11: =AK7-AK10 -> 0
B12: Gross margin | C12: =C11/C7 -> #DIV/0! | D12: =D11/D7 -> #DIV/0! | E12: =E11/E7 -> #DIV/0! | F12: =F11/F7 -> #DIV/0! | G12: =G11/G7 -> #DIV/0! | H12: =H11/H7 -> #DIV/0! | I12: =I11/I7 -> #DIV/0! | J12: =J11/J7 -> #DIV/0! | ... AK12: =AK11/AK7 -> #DIV/0!
B13: Opex | M13: 597 | N13: 540 | O13: 597 | P13: 646 | Q13: =SUM(M13:P13) -> 2380 | R13: 626 | S13: 559 | T13: 649 | U13: 714 | V13: =SUM(R13:U13) -> 2548 | W13: 665 | X13: 608
B14: Opex-to-sales | C14: =C13/C7 -> #DIV/0! | D14: =D13/D7 -> #DIV/0! | E14: =E13/E7 -> #DIV/0! | F14: =F13/F7 -> #DIV/0! | G14: =G13/G7 -> #DIV/0! | H14: =H13/H7 -> #DIV/0! | I14: =I13/I7 -> #DIV/0! | J14: =J13/J7 -> #DIV/0! | ... AK14: =AK13/AK7 -> #DIV/0!
B15: EBITDA | M15: 281 | N15: 525 | O15: 386 | P15: 840 | Q15: =SUM(M15:P15) -> 2032 | R15: 254 | S15: 635 | T15: 471 | U15: 826 | V15: =SUM(R15:U15) -> 2186 | W15: 325 | X15: 609
B16: EBITDA Margin | C16: =C15/C7 -> #DIV/0! | D16: =D15/D7 -> #DIV/0! | E16: =E15/E7 -> #DIV/0! | F16: =F15/F7 -> #DIV/0! | G16: =G15/G7 -> #DIV/0! | H16: =H15/H7 -> #DIV/0! | I16: =I15/I7 -> #DIV/0! | J16: =J15/J7 -> #DIV/0! | ... AK16: =AK15/AK7 -> #DIV/0!
B17: EBIT | M17: 107 | N17: 354 | O17: 212 | P17: 665 | Q17: =SUM(M17:P17) -> 1338 | R17: 78 | S17: 457 | T17: 293 | U17: 648 | V17: =SUM(R17:U17) -> 1476 | W17: 145 | X17: 428
B18: EBIT margin | C18: =C17/C7 -> #DIV/0! | D18: =D17/D7 -> #DIV/0! | E18: =E17/E7 -> #DIV/0! | F18: =F17/F7 -> #DIV/0! | G18: =G17/G7 -> #DIV/0! | H18: =H17/H7 -> #DIV/0! | I18: =I17/I7 -> #DIV/0! | J18: =J17/J7 -> #DIV/0! | ... AK18: =AK17/AK7 -> #DIV/0!
B19: Stores | M19: 282 | N19: 284 | O19: 284 | P19: 285 | R19: 287 | S19: 289 | T19: 290 | U19: 291 | W19: 291 | X19: 292
B20: Öob
B21: Revenue | N21: 728 | O21: 990 | P21: 1155 | Q21: =SUM(M21:P21) -> 2873 | R21: 888 | S21: 1142 | T21: 1020 | U21: 1238 | V21: =SUM(R21:U21) -> 4288 | W21: 968 | X21: 1032 | AK21: 5000
B22: y/y | H22: =(H21-C21)/C21 -> #DIV/0! | I22: =(I21-D21)/D21 -> #DIV/0! | J22: =(J21-E21)/E21 -> #DIV/0! | K22: =(K21-F21)/F21 -> #DIV/0! | L22: =(L21-G21)/G21 -> #DIV/0! | M22: =(M21-H21)/H21 -> #DIV/0! | N22: =(N21-I21)/I21 -> #DIV/0! | O22: =(O21-J21)/J21 -> #DIV/0! | ... AK22: =(AK21-AF21)/AF21 -> #DIV/0!
X23: -0.033
B24: COGS | N24: 492 | O24: 686 | P24: 778 | Q24: =SUM(M24:P24) -> 1956 | R24: 632 | S24: 791 | T24: 703 | U24: 817 | V24: =SUM(R24:U24) -> 2943 | W24: 656 | X24: 682
B25: Gross profit | C25: =C21-C24 -> 0 | D25: =D21-D24 -> 0 | E25: =E21-E24 -> 0 | F25: =F21-F24 -> 0 | G25: =G21-G24 -> 0 | H25: =H21-H24 -> 0 | I25: =I21-I24 -> 0 | J25: =J21-J24 -> 0 | ... AK25: =AK21-AK24 -> 5000
B26: Gross margin | C26: =C25/C21 -> #DIV/0! | D26: =D25/D21 -> #DIV/0! | E26: =E25/E21 -> #DIV/0! | F26: =F25/F21 -> #DIV/0! | G26: =G25/G21 -> #DIV/0! | H26: =H25/H21 -> #DIV/0! | I26: =I25/I21 -> #DIV/0! | J26: =J25/J21 -> #DIV/0! | ... AK26: =AK25/AK21 -> 1
B27: Opex | N27: 195 | O27: 262 | P27: 332 | Q27: =SUM(M27:P27) -> 789 | R27: 287 | S27: 296 | T27: 267 | U27: 303 | V27: =SUM(R27:U27) -> 1153 | W27: 297 | X27: 298
B28: Opex-to-sales | C28: =C27/C21 -> #DIV/0! | D28: =D27/D21 -> #DIV/0! | E28: =E27/E21 -> #DIV/0! | F28: =F27/F21 -> #DIV/0! | G28: =G27/G21 -> #DIV/0! | H28: =H27/H21 -> #DIV/0! | I28: =I27/I21 -> #DIV/0! | J28: =J27/J21 -> #DIV/0! | ... AK28: =AK27/AK21 -> 0
B29: EBITDA | N29: 42 | O29: 42 | P29: 45 | Q29: =SUM(M29:P29) -> 129 | R29: -30 | S29: 55 | T29: 50 | U29: 118 | V29: =SUM(R29:U29) -> 193 | W29: 15 | X29: 52
B30: EBITDA Margin | C30: =C29/C21 -> #DIV/0! | D30: =D29/D21 -> #DIV/0! | E30: =E29/E21 -> #DIV/0! | F30: =F29/F21 -> #DIV/0! | G30: =G29/G21 -> #DIV/0! | H30: =H29/H21 -> #DIV/0! | I30: =I29/I21 -> #DIV/0! | J30: =J29/J21 -> #DIV/0! | ... AK30: =AK29/AK21 -> 0
B31: EBIT | N31: -16 | O31: -45 | P31: -41 | Q31: =SUM(M31:P31) -> -102 | R31: -115 | S31: -34 | T31: -37 | U31: 30 | V31: =SUM(R31:U31) -> -156 | W31: -74 | X31: -34 | AK31: 250
B32: EBIT margin | C32: =C31/C21 -> #DIV/0! | D32: =D31/D21 -> #DIV/0! | E32: =E31/E21 -> #DIV/0! | F32: =F31/F21 -> #DIV/0! | G32: =G31/G21 -> #DIV/0! | H32: =H31/H21 -> #DIV/0! | I32: =I31/I21 -> #DIV/0! | J32: =J31/J21 -> #DIV/0! | ... AK32: =AK31/AK21 -> 0.05
B33: Stores | N33: 94 | O33: 94 | P33: 93 | R33: 92 | S33: 92 | T33: 92 | U33: 92 | W33: 92 | X33: 92
B34: Refurbished | W34: 13 | X34: 28 | Y34: 38 | Z34: 48

Sheet SOTP
A3: EBITDA 26E
A4: =Modell!AM25 -> 2639.8428
B6: NOKm | C6: EBITDA 26E | D6: Multippel | E6: Value | F6: NOK/share
B7: Norge | C7: 2278 | D7: 7 | E7: =C7*D7 -> 15946 | F7: =E7/Modell!$B$5 -> 95.502822
B8: Sverige | C8: 362 | D8: 5 | E8: =C8*D8 -> 1810 | F8: =E8/Modell!$B$5 -> 10.840343
B9: Enterprise value | C9: =SUM(C7:C8) -> 2640 | E9: =SUM(E7:E8) -> 17756 | F9: =E9/Modell!$B$5 -> 106.34316
B11: Debt | E11: =-Modell!B8 -> -2456.99 | F11: =E11/Modell!$B$5 -> -14.715256
B12: Cash | E12: =Modell!B7 -> 830.034 | F12: =E12/Modell!$B$5 -> 4.9711896
B14: SOTP EPR | E14: =SUM(E9:E12) -> 16129.044 | F14: =SUM(F9:F12) -> 96.599098

Sheet Nøkkeltall
D4: 2026 | E4: 2027 | F4: 2028
C5: EV/EBITDA | D5: =Modell!$B$9/Modell!AM25 -> 5.739522 | E5: =Modell!$B$9/Modell!AN25 -> 5.3923563 | F5: =Modell!$B$9/Modell!AO25 -> 5.0017064
C6: EV/EBIT | D6: =Modell!$B$9/Modell!AM10 -> 9.7874787 | E6: =Modell!$B$9/Modell!AN10 -> 9.0492707 | F6: =Modell!$B$9/Modell!AO10 -> 8.1471719
C7: P/E | D7: =Modell!$B$4/Modell!AM18 -> 13.617723 | E7: =Modell!$B$4/Modell!AN18 -> 12.549119 | F7: =Modell!$B$4/Modell!AO18 -> 11.085226

Sheet Nedsidebergnign
A3: Nedside | D3: FY 2015 | E3: FY 2016 | F3: FY 2017 | G3: FY 2018 | H3: FY 2019 | I3: FY 2020 | J3: FY 2021 | K3: FY 2022 | L3: FY 2023 | M3: FY 2024 | N3: FY 2025 | O3: FY 2026 | P3: FY 2027 | Q3: FY 2028 | R3: FY 2029 | S3: FY 2030 | T3: FY 2031 | U3: FY 2032 | V3: FY 2033 | W3: FY 2034 | X3: FY 2035
A4: Nullvekst og dårlige marginer | C4: Revenue | L4: 9466.921 | M4: 12750.259 | N4: 14878 | O4: =N4 -> 14878 | P4: =O4 -> 14878 | Q4: =P4 -> 14878 | R4: =Q4 -> 14878 | S4: =R4 -> 14878 | T4: =S4 -> 14878 | U4: =T4 -> 14878 | V4: =U4 -> 14878 | ... X4: =W4 -> 14878
A5: =AA23 -> 65.691847 | C5: COGS | L5: -5275.676 | M5: -7437.455 | N5: -8799 | O5: =O4*-0.6 -> -8926.8 | P5: =P4*-0.6 -> -8926.8 | Q5: =Q4*-0.6 -> -8926.8 | R5: =R4*-0.6 -> -8926.8 | S5: =S4*-0.6 -> -8926.8 | T5: =T4*-0.6 -> -8926.8 | U5: =U4*-0.6 -> -8926.8 | V5: =V4*-0.6 -> -8926.8 | ... X5: =X4*-0.6 -> -8926.8
A6: =AA24 -> -0.18898955 | C6: Gross profit | L6: =SUM(L4:L5) -> 4191.245 | M6: =SUM(M4:M5) -> 5312.804 | N6: =SUM(N4:N5) -> 6079 | O6: =SUM(O4:O5) -> 5951.2 | P6: =SUM(P4:P5) -> 5951.2 | Q6: =SUM(Q4:Q5) -> 5951.2 | R6: =SUM(R4:R5) -> 5951.2 | S6: =SUM(S4:S5) -> 5951.2 | ... X6: =SUM(X4:X5) -> 5951.2
C7: Employee benefit expenses | L7: -1373.081 | M7: -1865.036 | N7: -2238 | O7: =N7*1 -> -2238 | P7: =O7*1 -> -2238 | Q7: =P7*1 -> -2238 | R7: =Q7*1 -> -2238 | S7: =R7*1 -> -2238 | T7: =S7*1 -> -2238 | U7: =T7*1 -> -2238 | V7: =U7*1 -> -2238 | ... X7: =W7*1 -> -2238
C8: Depreciation | L8: -674.608 | M8: -922.927 | N8: -1060 | O8: =N8*1 -> -1060 | P8: =O8*1 -> -1060 | Q8: =P8*1 -> -1060 | R8: =Q8*1 -> -1060 | S8: =R8*1 -> -1060 | T8: =S8*1 -> -1060 | U8: =T8*1 -> -1060 | V8: =U8*1 -> -1060 | ... X8: =W8*1 -> -1060
C9: Other operating expenses | L9: -848.426 | M9: -1288.062 | N9: -1462 | O9: =N9*1 -> -1462 | P9: =O9*1 -> -1462 | Q9: =P9*1 -> -1462 | R9: =Q9*1 -> -1462 | S9: =R9*1 -> -1462 | T9: =S9*1 -> -1462 | U9: =T9*1 -> -1462 | V9: =U9*1 -> -1462 | ... X9: =W9*1 -> -1462
C10: Operating profit (EBIT) | L10: =SUM(L6:L9) -> 1295.13 | M10: =SUM(M6:M9) -> 1236.779 | N10: =SUM(N6:N9) -> 1319 | O10: =SUM(O6:O9) -> 1191.2 | P10: =SUM(P6:P9) -> 1191.2 | Q10: =SUM(Q6:Q9) -> 1191.2 | R10: =SUM(R6:R9) -> 1191.2 | S10: =SUM(S6:S9) -> 1191.2 | ... X10: =SUM(X6:X9) -> 1191.2
C11: Net financials | L11: -190.517 | M11: -201.704 | N11: -258 | O11: 0 | P11: 0 | Q11: 0 | R11: 0 | S11: 0 | T11: 0 | U11: 0 | V11: 0 | W11: 0 | X11: 0
C12: Profit/loss from associated comps | L12: -54.489 | M12: 1.592 | N12: 0 | O12: 0 | P12: 0 | Q12: 0 | R12: 0 | S12: 0 | T12: 0 | U12: 0 | V12: 0 | W12: 0 | X12: 0
C13: Change in fair value of options | L13: 101.789 | M13: 32.309 | N13: 0 | O13: 0 | P13: 0 | Q13: 0 | R13: 0 | S13: 0 | T13: 0 | U13: 0 | V13: 0 | W13: 0 | X13: 0
C14: PTP | L14: =SUM(L10:L13) -> 1151.913 | M14: =SUM(M10:M13) -> 1068.976 | N14: =SUM(N10:N13) -> 1061 | O14: =SUM(O10:O13) -> 1191.2 | P14: =SUM(P10:P13) -> 1191.2 | Q14: =SUM(Q10:Q13) -> 1191.2 | R14: =SUM(R10:R13) -> 1191.2 | S14: =SUM(S10:S13) -> 1191.2 | ... X14: =SUM(X10:X13) -> 1191.2
C15: Tax | L15: -243.06 | M15: -230.94 | N15: -246 | O15: =O14*-0.22 -> -262.064 | P15: =P14*-0.22 -> -262.064 | Q15: =Q14*-0.22 -> -262.064 | R15: =R14*-0.22 -> -262.064 | S15: =S14*-0.22 -> -262.064 | T15: =T14*-0.22 -> -262.064 | U15: =U14*-0.22 -> -262.064 | V15: =V14*-0.22 -> -262.064 | ... X15: =X14*-0.22 -> -262.064
C16: Net income | L16: =SUM(L14:L15) -> 908.853 | M16: =SUM(M14:M15) -> 838.036 | N16: =SUM(N14:N15) -> 815 | O16: =SUM(O14:O15) -> 929.136 | P16: =SUM(P14:P15) -> 929.136 | Q16: =SUM(Q14:Q15) -> 929.136 | R16: =SUM(R14:R15) -> 929.136 | S16: =SUM(S14:S15) -> 929.136 | ... X16: =SUM(X14:X15) -> 929.136 | Y16: =X16*(1+$AA$20) -> 919.84464 | Z16: =Y16*(1+$AA$20) -> 910.64619 | AA16: =Z16*(1+$AA$20) -> 901.53973 | AB16: =AA16*(1+$AA$20) -> 892.52433 | AC16: =AB16*(1+$AA$20) -> 883.59909 | AD16: =AC16*(1+$AA$20) -> 874.7631 | AE16: =AD16*(1+$AA$20) -> 866.01547 | AF16: =AE16*(1+$AA$20) -> 857.35531 | ... EM16: =EL16*(1+$AA$20) -> 280.97485
C17: Share | L17: 166.96889 | M17: 166.96889 | N17: 166.96889 | O17: 166.96889 | P17: 166.96889 | Q17: 166.96889 | R17: 166.96889 | S17: 166.96889 | T17: 166.96889 | U17: 166.96889 | V17: 166.96889 | W17: 166.96889 | X17: 166.96889
C18: EPS | L18: =L16/L17 -> 5.4432476 | M18: =M16/M17 -> 5.0191147 | N18: =N16/N17 -> 4.8811489 | O18: =O16/O17 -> 5.5647253 | P18: =P16/P17 -> 5.5647253 | Q18: =Q16/Q17 -> 5.5647253 | R18: =R16/R17 -> 5.5647253 | S18: =S16/S17 -> 5.5647253 | ... X18: =X16/X17 -> 5.5647253
Z19: Discount | AA19: 0.08
C20: Revenue y/y | E20: =(E4-D4)/D4 -> #DIV/0! | F20: =(F4-E4)/E4 -> #DIV/0! | G20: =(G4-F4)/F4 -> #DIV/0! | H20: =(H4-G4)/G4 -> #DIV/0! | I20: =(I4-H4)/H4 -> #DIV/0! | J20: =(J4-I4)/I4 -> #DIV/0! | K20: =(K4-J4)/J4 -> #DIV/0! | L20: =(L4-K4)/K4 -> #DIV/0! | ... X20: =(X4-W4)/W4 -> 0 | Z20: TV | AA20: -0.01
C21: Revenue CC | Z21: NPV | AA21: =NPV(AA19,O16:EM16) -> 10968.495
C22: Gross margin | D22: =D6/D4 -> #DIV/0! | E22: =E6/E4 -> #DIV/0! | F22: =F6/F4 -> #DIV/0! | G22: =G6/G4 -> #DIV/0! | H22: =H6/H4 -> #DIV/0! | I22: =I6/I4 -> #DIV/0! | J22: =J6/J4 -> #DIV/0! | K22: =K6/K4 -> #DIV/0! | ... X22: =X6/X4 -> 0.4 | Z22: S/O | AA22: 166.96889
C23: EBIT margin | D23: =D10/D4 -> #DIV/0! | E23: =E10/E4 -> #DIV/0! | F23: =F10/F4 -> #DIV/0! | G23: =G10/G4 -> #DIV/0! | H23: =H10/H4 -> #DIV/0! | I23: =I10/I4 -> #DIV/0! | J23: =J10/J4 -> #DIV/0! | K23: =K10/K4 -> #DIV/0! | ... X23: =X10/X4 -> 0.080064525 | Z23: NPV/Share | AA23: =AA21/AA22 -> 65.691847
Z24: Opp/nedside | AA24: =(AA23-Modell!B4)/Modell!B4 -> -0.18898955
