Workbook

Sheet Info
A20: Press releases:
A21: 11.08.25: Glen Instone blir ny CEO for Husqvarna
A22: 24.04.25: CEO Pavel Hajman har sammen med styret blitt enig om å gå av
A23: 09.12.24: Profit warning
A36: Forest and garden
A51: Gardena
A66: Constuction

Sheet Modell
A3: Kapitalstruktur | C3: SEKm | D3: Q122 | E3: Q222 | F3: Q322 | G3: Q422 | H3: Q123 | I3: Q223 | J3: Q323 | K3: Q423 | L3: Q124 | M3: Q224 | N3: Q324 | O3: Q424 | P3: Q125 | Q3: Q225 | R3: Q325 | S3: Q425 | T3: Q126 | U3: Q226 | V3: Q326 | W3: Q426 | Y3: FY 2015 | Z3: FY 2016 | AA3: FY 2017 | AB3: FY 2018 | AC3: FY 2019 | AD3: FY 2020 | AE3: FY 2021 | AF3: FY 2022 | AG3: FY 2023 | AH3: FY 2024 | AI3: FY 2025 | AJ3: FY 2026 | AK3: FY 2027 | AL3: FY 2028 | AM3: FY 2029 | AN3: FY 2030 | AO3: FY 2031 | AP3: FY 2032 | AQ3: FY 2033 | AR3: FY 2034 | AS3: FY 2035
A4: Price | B4: 36.5 | C4: Revenues | D4: 15685 | E4: 15792 | F4: 12206 | G4: 10353 | H4: 17167 | I4: 16976 | J4: 10512 | K4: 8605 | L4: 14719 | M4: 15430 | N4: 9739 | O4: 8464 | P4: 14704 | Q4: 15277 | R4: 9204 | S4: 7429 | T4: 13962 | U4: 14383 | Y4: 36170 | Z4: 35982 | AA4: 39394 | AB4: 41085 | AC4: 42277 | AD4: 41943 | AE4: 47059 | AF4: 54037 | AG4: 53261 | AH4: 48352 | AI4: 46614 | AJ4: =AI4*0.95 -> 44283.3 | AK4: =AJ4*1.03 -> 45611.799 | AL4: =AK4*1.03 -> 46980.153 | AM4: =AL4*1.03 -> 48389.558 | AN4: =AM4*1.03 -> 49841.244 | AO4: =AN4*1.03 -> 51336.482 | AP4: =AO4*1.03 -> 52876.576 | AQ4: =AP4*1.03 -> 54462.873 | AR4: =AQ4*1.03 -> 56096.76 | AS4: =AR4*1.03 -> 57779.662
A5: S/O | B5: 571.7 | C5: COGS | D5: -10706 | E5: -10580 | F5: -9053 | G5: -9085 | H5: -11477 | I5: -11430 | J5: -7393 | K5: -6836 | L5: -9753 | M5: -10236 | N5: -7207 | O5: -6857 | P5: -10172 | Q5: -10101 | R5: -6581 | S5: -5660 | T5: -9417 | U5: -9713 | Y5: -25996 | Z5: -24886 | AA5: -27922 | AB5: -30583 | AC5: -29748 | AD5: -29367 | AE5: -31546 | AF5: -39424 | AG5: -37136 | AH5: -34053 | AI5: -32514 | AJ5: =AJ4*-0.7 -> -30998.31 | AK5: =AK4*-0.7 -> -31928.259 | AL5: =AL4*-0.7 -> -32886.107 | AM5: =AM4*-0.7 -> -33872.69 | AN5: =AN4*-0.7 -> -34888.871 | AO5: =AO4*-0.7 -> -35935.537 | AP5: =AP4*-0.7 -> -37013.603 | AQ5: =AQ4*-0.7 -> -38124.011 | ... AS5: =AS4*-0.7 -> -40445.764
A6: MC SEKm | B6: =B4*B5 -> 20867.05 | C6: Gross profit | D6: =SUM(D4:D5) -> 4979 | E6: =SUM(E4:E5) -> 5212 | F6: =SUM(F4:F5) -> 3153 | G6: =SUM(G4:G5) -> 1268 | H6: =SUM(H4:H5) -> 5690 | I6: =SUM(I4:I5) -> 5546 | J6: =SUM(J4:J5) -> 3119 | K6: =SUM(K4:K5) -> 1769 | ... U6: =SUM(U4:U5) -> 4670 | Y6: =SUM(Y4:Y5) -> 10174 | Z6: =SUM(Z4:Z5) -> 11096 | AA6: =SUM(AA4:AA5) -> 11472 | AB6: =SUM(AB4:AB5) -> 10502 | AC6: =SUM(AC4:AC5) -> 12529 | AD6: =SUM(AD4:AD5) -> 12576 | AE6: =SUM(AE4:AE5) -> 15513 | AF6: =SUM(AF4:AF5) -> 14613 | ... AS6: =SUM(AS4:AS5) -> 17333.899
A7: Cash SEKm | B7: =U43 -> 3457 | C7: Selling expenses | D7: -2201 | E7: -2344 | F7: -2028 | G7: -2197 | H7: -2373 | I7: -2598 | J7: -2042 | K7: -2020 | L7: -2158 | M7: -2423 | N7: -1966 | O7: -2041 | P7: -2145 | Q7: -2317 | R7: -1852 | S7: -1802 | T7: -2024 | U7: -2224 | Y7: -5833 | Z7: -6168 | AA7: -5870 | AB7: -6473 | AC7: -6985 | AD7: -6596 | AE7: -7152 | AF7: -8770 | AG7: -9034 | AH7: -8587 | AI7: -8116 | AJ7: =AI7*0.97 -> -7872.52 | AK7: =AJ7*1.03 -> -8108.6956 | AL7: =AK7*1.03 -> -8351.9565 | AM7: =AL7*1.03 -> -8602.5152 | AN7: =AM7*1.03 -> -8860.5906 | AO7: =AN7*1.03 -> -9126.4083 | AP7: =AO7*1.03 -> -9400.2006 | AQ7: =AP7*1.03 -> -9682.2066 | AR7: =AQ7*1.03 -> -9972.6728 | AS7: =AR7*1.03 -> -10271.853
A8: Debt SEKm | B8: =U48+U58 -> 11120 | C8: Administrative expenses | D8: -801 | E8: -815 | F8: -575 | G8: -810 | H8: -934 | I8: -854 | J8: -687 | K8: -736 | L8: -879 | M8: -874 | N8: -665 | O8: -858 | P8: -872 | Q8: -797 | R8: -633 | S8: -772 | T8: -835 | U8: -852 | Y8: -1532 | Z8: -1707 | AA8: -1879 | AB8: -2014 | AC8: -2051 | AD8: -2335 | AE8: -2704 | AF8: -3001 | AG8: -3211 | AH8: -3275 | AI8: -3074 | AJ8: =AI8*1 -> -3074 | AK8: =AJ8*1.03 -> -3166.22 | AL8: =AK8*1.03 -> -3261.2066 | AM8: =AL8*1.03 -> -3359.0428 | AN8: =AM8*1.03 -> -3459.8141 | AO8: =AN8*1.03 -> -3563.6085 | AP8: =AO8*1.03 -> -3670.5168 | AQ8: =AP8*1.03 -> -3780.6323 | AR8: =AQ8*1.03 -> -3894.0512 | AS8: =AR8*1.03 -> -4010.8728
A9: EV SEKm | B9: =B6-B7+B8 -> 28530.05 | C9: Other operating inc/ex | D9: 182 | E9: 11 | F9: 6 | G9: 2 | H9: -19 | I9: 7 | J9: 8 | K9: 4 | L9: 1 | M9: 1 | N9: 152 | O9: 7 | P9: 16 | Q9: 0 | R9: 4 | S9: -31 | T9: 24 | U9: 7 | Y9: =23-5 -> 18 | Z9: -3 | AA9: =68-1 -> 67 | AB9: =63-8 -> 55 | AC9: =203-6 -> 197 | AD9: =26-2 -> 24 | AE9: =112-23 -> 89 | AF9: =212-11 -> 201 | AG9: 0 | AH9: 160 | AI9: -11 | AJ9: =AI9*1 -> -11 | AK9: =AJ9*1.03 -> -11.33 | AL9: =AK9*1.03 -> -11.6699 | AM9: =AL9*1.03 -> -12.019997 | AN9: =AM9*1.03 -> -12.380597 | AO9: =AN9*1.03 -> -12.752015 | AP9: =AO9*1.03 -> -13.134575 | AQ9: =AP9*1.03 -> -13.528613 | AR9: =AQ9*1.03 -> -13.934471 | AS9: =AR9*1.03 -> -14.352505
C10: Operating income | D10: =SUM(D6:D9) -> 2159 | E10: =SUM(E6:E9) -> 2064 | F10: =SUM(F6:F9) -> 556 | G10: =SUM(G6:G9) -> -1737 | H10: =SUM(H6:H9) -> 2364 | I10: =SUM(I6:I9) -> 2101 | J10: =SUM(J6:J9) -> 398 | K10: =SUM(K6:K9) -> -983 | ... U10: =SUM(U6:U9) -> 1601 | Y10: =SUM(Y6:Y9) -> 2827 | Z10: =SUM(Z6:Z9) -> 3218 | AA10: =SUM(AA6:AA9) -> 3790 | AB10: =SUM(AB6:AB9) -> 2070 | AC10: =SUM(AC6:AC9) -> 3690 | AD10: =SUM(AD6:AD9) -> 3669 | AE10: =SUM(AE6:AE9) -> 5746 | AF10: =SUM(AF6:AF9) -> 3043 | ... AS10: =SUM(AS6:AS9) -> 3036.8204
C11: Financial items | D11: -61 | E11: -87 | F11: -87 | G11: -226 | H11: -245 | I11: -247 | J11: -221 | K11: -289 | L11: -229 | M11: -258 | N11: -206 | O11: -171 | P11: -199 | Q11: -202 | R11: -182 | S11: -167 | T11: -202 | U11: -207 | Y11: =44-388 -> -344 | Z11: =29-451 -> -422 | AA11: =20-520 -> -500 | AB11: =72-581 -> -509 | AC11: =18-586 -> -568 | AD11: =38-377 -> -339 | AE11: =42-294 -> -252 | AF11: =38-499 -> -461 | AG11: =75-1077 -> -1002 | AH11: =86-950 -> -864 | AI11: -750 | AJ11: 0 | AK11: 0 | AL11: 0 | AM11: 0 | AN11: 0 | AO11: 0 | AP11: 0 | AQ11: 0 | AR11: 0 | AS11: 0
A12: Gearing | B12: =(B8-B7)/U26 -> 1.4649207 | C12: PTP | D12: =SUM(D10:D11) -> 2098 | E12: =SUM(E10:E11) -> 1977 | F12: =SUM(F10:F11) -> 469 | G12: =SUM(G10:G11) -> -1963 | H12: =SUM(H10:H11) -> 2119 | I12: =SUM(I10:I11) -> 1854 | J12: =SUM(J10:J11) -> 177 | K12: =SUM(K10:K11) -> -1272 | ... U12: =SUM(U10:U11) -> 1394 | Y12: =SUM(Y10:Y11) -> 2483 | Z12: =SUM(Z10:Z11) -> 2796 | AA12: =SUM(AA10:AA11) -> 3290 | AB12: =SUM(AB10:AB11) -> 1561 | AC12: =SUM(AC10:AC11) -> 3122 | AD12: =SUM(AD10:AD11) -> 3330 | AE12: =SUM(AE10:AE11) -> 5494 | AF12: =SUM(AF10:AF11) -> 2582 | ... AS12: =SUM(AS10:AS11) -> 3036.8204
C13: Tax | D13: -460 | E13: -561 | F13: -199 | G13: 571 | H13: -466 | I13: -443 | J13: -53 | K13: 261 | L13: -379 | M13: -369 | N13: 1 | O13: 339 | P13: -362 | Q13: -281 | R13: 31 | S13: 233 | T13: -335 | U13: -363 | Y13: -595 | Z13: -692 | AA13: -630 | AB13: -348 | AC13: -594 | AD13: -835 | AE13: -1057 | AF13: -649 | AG13: -702 | AH13: -408 | AI13: -379 | AJ13: =AJ12*-0.2 -> -465.494 | AK13: =AK12*-0.2 -> -479.45882 | AL13: =AL12*-0.2 -> -493.84258 | AM13: =AM12*-0.2 -> -508.65786 | AN13: =AN12*-0.2 -> -523.9176 | AO13: =AO12*-0.2 -> -539.63513 | AP13: =AP12*-0.2 -> -555.82418 | AQ13: =AQ12*-0.2 -> -572.49891 | ... AS13: =AS12*-0.2 -> -607.36409
A14: P/B | B14: =B6/+U47 -> 0.80983622 | C14: Net income | D14: =SUM(D12:D13) -> 1638 | E14: =SUM(E12:E13) -> 1416 | F14: =SUM(F12:F13) -> 270 | G14: =SUM(G12:G13) -> -1392 | H14: =SUM(H12:H13) -> 1653 | I14: =SUM(I12:I13) -> 1411 | J14: =SUM(J12:J13) -> 124 | K14: =SUM(K12:K13) -> -1011 | ... U14: =SUM(U12:U13) -> 1031 | Y14: =SUM(Y12:Y13) -> 1888 | Z14: =SUM(Z12:Z13) -> 2104 | AA14: =SUM(AA12:AA13) -> 2660 | AB14: =SUM(AB12:AB13) -> 1213 | AC14: =SUM(AC12:AC13) -> 2528 | AD14: =SUM(AD12:AD13) -> 2495 | AE14: =SUM(AE12:AE13) -> 4437 | AF14: =SUM(AF12:AF13) -> 1933 | ... AS14: =SUM(AS12:AS13) -> 2429.4564 | AT14: =AS14*(1+$AV$18) -> 2405.1618 | AU14: =AT14*(1+$AV$18) -> 2381.1102 | AV14: =AU14*(1+$AV$18) -> 2357.2991 | AW14: =AV14*(1+$AV$18) -> 2333.7261 | AX14: =AW14*(1+$AV$18) -> 2310.3888 | AY14: =AX14*(1+$AV$18) -> 2287.2849 | AZ14: =AY14*(1+$AV$18) -> 2264.4121 | BA14: =AZ14*(1+$AV$18) -> 2241.768 | ... GR14: =GQ14*(1+$AV$18) -> 511.63973
C15: Shares | D15: 571.6 | E15: 571.6 | F15: 571.6 | G15: 571.6 | H15: 571.6 | I15: 571.6 | J15: 571.6 | K15: 571.6 | L15: 571.6 | M15: 571.6 | N15: 571.7 | O15: 571.7 | P15: 571.7 | Q15: 571.7 | R15: 571.7 | S15: 571.7 | T15: 571.7 | U15: 571.7 | Y15: 571.7 | Z15: 571.7 | AA15: 571.7 | AB15: 571.7 | AC15: 571.7 | AD15: 571.7 | AE15: 571.7 | AF15: 571.7 | AG15: 571.7 | AH15: 571.7 | AI15: 571.7 | AJ15: 571.7 | AK15: 571.7 | AL15: 571.7 | AM15: 571.7 | AN15: 571.7 | AO15: 571.7 | AP15: 571.7 | AQ15: 571.7 | AR15: 571.7 | AS15: 571.7
C16: EPS | D16: =D14/D15 -> 2.8656403 | E16: =E14/E15 -> 2.4772568 | F16: =F14/F15 -> 0.47235829 | G16: =G14/G15 -> -2.4352694 | H16: =H14/H15 -> 2.8918824 | I16: =I14/I15 -> 2.4685094 | J16: =J14/J15 -> 0.21693492 | K16: =K14/K15 -> -1.7687194 | ... U16: =U14/U15 -> 1.8033934 | Y16: =Y14/Y15 -> 3.3024313 | Z16: =Z14/Z15 -> 3.6802519 | AA16: =AA14/AA15 -> 4.6527899 | AB16: =AB14/AB15 -> 2.1217422 | AC16: =AC14/AC15 -> 4.4218996 | AD16: =AD14/AD15 -> 4.364177 | AE16: =AE14/AE15 -> 7.7610635 | AF16: =AF14/AF15 -> 3.381144 | ... AS16: =AS14/AS15 -> 4.2495301
AU17: Disocunt | AV17: 0.08
C18: Revenue y/y | H18: =(H4-D4)/D4 -> 0.094485177 | I18: =(I4-E4)/E4 -> 0.074974671 | J18: =(J4-F4)/F4 -> -0.1387842 | K18: =(K4-G4)/G4 -> -0.16883995 | L18: =(L4-H4)/H4 -> -0.14259917 | M18: =(M4-I4)/I4 -> -0.091069746 | N18: =(N4-J4)/J4 -> -0.073535008 | O18: =(O4-K4)/K4 -> -0.016385822 | ... W18: =(W4-S4)/S4 -> -1 | Z18: =(Z4-Y4)/Y4 -> -0.0051976776 | AA18: =(AA4-Z4)/Z4 -> 0.09482519 | AB18: =(AB4-AA4)/AA4 -> 0.042925319 | AC18: =(AC4-AB4)/AB4 -> 0.029013022 | AD18: =(AD4-AC4)/AC4 -> -0.0079002767 | AE18: =(AE4-AD4)/AD4 -> 0.12197506 | AF18: =(AF4-AE4)/AE4 -> 0.14828194 | AG18: =(AG4-AF4)/AF4 -> -0.014360531 | ... AS18: =(AS4-AR4)/AR4 -> 0.03 | AU18: TV | AV18: -0.01
C19: Organic growth | D19: -0.02 | E19: 0.07 | F19: 0.01 | G19: 0.08 | H19: 0.02 | I19: 0 | J19: -0.15 | K19: -0.15 | L19: -0.11 | M19: -0.06 | N19: -0.04 | O19: -0.03 | P19: -0.01 | Q19: 0.05 | R19: 0 | S19: -0.03 | T19: 0.02 | U19: -0.04 | AU19: NPV | AV19: =NPV(AV17,AJ14:GR14) -> 26436.543
C20: Gross margin | D20: =D6/D4 -> 0.31743704 | E20: =E6/E4 -> 0.33004053 | F20: =F6/F4 -> 0.25831558 | G20: =G6/G4 -> 0.12247658 | H20: =H6/H4 -> 0.33144987 | I20: =I6/I4 -> 0.32669651 | J20: =J6/J4 -> 0.29670852 | K20: =K6/K4 -> 0.20557815 | ... W20: =W6/W4 -> #DIV/0! | Y20: =Y6/Y4 -> 0.28128283 | Z20: =Z6/Z4 -> 0.30837641 | AA20: =AA6/AA4 -> 0.29121186 | AB20: =AB6/AB4 -> 0.25561641 | AC20: =AC6/AC4 -> 0.29635499 | AD20: =AD6/AD4 -> 0.29983549 | AE20: =AE6/AE4 -> 0.32965001 | AF20: =AF6/AF4 -> 0.27042582 | ... AS20: =AS6/AS4 -> 0.3 | AU20: S/O | AV20: 571.7
C21: EBIT margin | D21: =D10/D4 -> 0.13764743 | E21: =E10/E4 -> 0.13069909 | F21: =F10/F4 -> 0.045551368 | G21: =G10/G4 -> -0.16777746 | H21: =H10/H4 -> 0.13770606 | I21: =I10/I4 -> 0.12376296 | J21: =J10/J4 -> 0.037861492 | K21: =K10/K4 -> -0.11423591 | ... W21: =W10/W4 -> #DIV/0! | Y21: =Y10/Y4 -> 0.078158695 | Z21: =Z10/Z4 -> 0.089433606 | AA21: =AA10/AA4 -> 0.096207544 | AB21: =AB10/AB4 -> 0.050383352 | AC21: =AC10/AC4 -> 0.087281501 | AD21: =AD10/AD4 -> 0.08747586 | AE21: =AE10/AE4 -> 0.12210204 | AF21: =AF10/AF4 -> 0.056313267 | ... AS21: =AS10/AS4 -> 0.052558639 | AU21: NPV/Share | AV21: =AV19/AV20 -> 46.241984
C22: ROE | Y22: 0.146 | Z22: 0.152 | AA22: 0.174 | AB22: 0.073 | AC22: 0.147 | AD22: 0.135 | AE22: 0.222 | AF22: 0.079 | AG22: 0.085 | AH22: 0.053 | AU22: Opp/nedside | AV22: =(AV21-B4)/B4 -> 0.26690368
C24: EBITDA | D24: =D10+D68 -> 4318 | E24: =E10+E68 -> 4129 | F24: =F10+F68 -> 1111 | G24: =G10+G68 -> -3474 | H24: =H10+H68 -> 4728 | I24: =I10+I68 -> 4202 | J24: =J10+J68 -> 796 | K24: =K10+K68 -> -1966 | ... U24: =U10+U68 -> 3201 | AF24: =AF10+AF68 -> 7022 | AG24: =AG10+AG68 -> 7466 | AH24: =AH10+AH68 -> 5951 | AI24: =AI10+AI68 -> 5900
C25: EBITDA margin | D25: =D24/D4 -> 0.27529487 | E25: =E24/E4 -> 0.2614615 | F25: =F24/F4 -> 0.091020809 | G25: =G24/G4 -> -0.33555491 | H25: =H24/H4 -> 0.27541213 | I25: =I24/I4 -> 0.24752592 | J25: =J24/J4 -> 0.075722983 | K25: =K24/K4 -> -0.22847182 | ... U25: =U24/U4 -> 0.2225544 | AF25: =AF24/AF4 -> 0.129948 | AG25: =AG24/AG4 -> 0.14017762 | AH25: =AH24/AH4 -> 0.1230766 | AI25: =AI24/AI4 -> 0.12657142
C26: EBITDA LTM | G26: =SUM(D24:G24) -> 6084 | H26: =SUM(E24:H24) -> 6494 | I26: =SUM(F24:I24) -> 6567 | J26: =SUM(G24:J24) -> 6252 | K26: =SUM(H24:K24) -> 7760 | L26: =SUM(I24:L24) -> 6892 | M26: =SUM(J24:M24) -> 6487 | N26: =SUM(K24:N24) -> 5796 | ... U26: =SUM(R24:U24) -> 5231
C28: Balanse SEkm
C29: PP&E | D29: 7349 | E29: 7668 | F29: 7834 | G29: 7151 | H29: 7128 | I29: 7372 | J29: 7240 | K29: 7205 | L29: 7360 | M29: 7381 | N29: 7281 | O29: 7221 | P29: 6901 | Q29: 6981 | R29: 6879 | S29: 6668 | T29: 6607 | U29: 6501 | AF29: 7151 | AG29: 7205 | AH29: 7221 | AI29: 6668
C30: Right of use assets | D30: 1779 | E30: 1786 | F30: 1856 | G30: 2288 | H30: 2202 | I30: 2207 | J30: 2209 | K30: 2068 | L30: 2147 | M30: 2058 | N30: 1914 | O30: 1975 | P30: 1767 | Q30: 1710 | R30: 1600 | S30: 1641 | T30: 1653 | U30: 1893 | AF30: 2288 | AG30: 2068 | AH30: 1975 | AI30: 1641
C31: Goodwill | D31: 9433 | E31: 10090 | F31: 10591 | G31: 10187 | H31: 10176 | I31: 10581 | J31: 10452 | K31: 9920 | L31: 10374 | M31: 10292 | N31: 10030 | O31: 10521 | P31: 9848 | Q31: 9633 | R31: 9569 | S31: 9380 | T31: 9620 | U31: 9753 | AF31: 10187 | AG31: 9920 | AH31: 10521 | AI31: 9380
C32: Other intangible assets | D32: 7756 | E32: 8114 | F32: 8384 | G32: 8408 | H32: 8447 | I32: 8785 | J32: 8639 | K32: 8400 | L32: 8667 | M32: 8624 | N32: 8487 | O32: 8911 | P32: 8513 | Q32: 8510 | R32: 8375 | S32: 8265 | T32: 8310 | U32: 8382 | AF32: 8408 | AG32: 8400 | AH32: 8911 | AI32: 8265
C33: Investments in associated comps | D33: 36 | E33: 24 | F33: 24 | G33: 16 | H33: 16 | I33: 16 | J33: 16 | K33: 14 | L33: 14 | M33: 0.13 | N33: 35 | O33: 34 | P33: 34 | Q33: 32 | R33: 32 | S33: 2 | T33: 2 | U33: 2 | AF33: 16 | AG33: 14 | AH33: 34 | AI33: 2
C34: Derivatives | D34: 29 | E34: 47 | F34: 54 | G34: 53 | H34: 29 | I34: 29 | J34: 38 | K34: 0 | L34: 0 | M34: 0 | N34: 0 | O34: 23 | P34: 19 | Q34: 0 | R34: 0 | S34: 13 | T34: 44 | U34: 2 | AF34: 53 | AG34: 0 | AH34: 23 | AI34: 13
C35: Other non-current assets | D35: 888 | E35: 1061 | F35: 1216 | G35: 913 | H35: 851 | I35: 896 | J35: 916 | K35: 843 | L35: 871 | M35: 909 | N35: 806 | O35: 840 | P35: 923 | Q35: 891 | R35: 879 | S35: 1072 | T35: 1093 | U35: 1044 | AF35: 913 | AG35: 843 | AH35: 840 | AI35: 1072
C36: Deferred tax assets | D36: 1625 | E36: 986 | F36: 878 | G36: 1834 | H36: 2379 | I36: 2452 | J36: 1758 | K36: 2143 | L36: 2243 | M36: 1984 | N36: 1806 | O36: 2418 | P36: 2051 | Q36: 1856 | R36: 1836 | S36: 1828 | T36: 1511 | U36: 1736 | AF36: 1834 | AG36: 2143 | AH36: 2418 | AI36: 1828
C37: Inventories | D37: 15192 | E37: 16455 | F37: 17612 | G37: 19334 | H37: 18670 | I37: 17949 | J37: 17090 | K37: 17184 | L37: 17094 | M37: 14720 | N37: 13521 | O37: 13828 | P37: 13024 | Q37: 11954 | R37: 12248 | S37: 13847 | T37: 13952 | U37: 12682 | AF37: 19334 | AG37: 17184 | AH37: 13828 | AI37: 13847
C38: Assets held for sale | D38: 0 | E38: 0 | F38: 0 | G38: 0 | H38: 0 | I38: 0 | J38: 0 | K38: 0 | L38: 0 | M38: 0 | N38: 0 | O38: 1410 | P38: 0 | Q38: 0 | R38: 0 | S38: 0 | T38: 0 | U38: 0 | AF38: 0 | AG38: 0 | AH38: 1410 | AI38: 0
C39: Trade receivables | D39: 8522 | E39: 8204 | F39: 6896 | G39: 6267 | H39: 10355 | I39: 9373 | J39: 6562 | K39: 5289 | L39: 11302 | M39: 10519 | N39: 6081 | O39: 5552 | P39: 10806 | Q39: 10683 | R39: 5730 | S39: 4990 | T39: 11219 | U39: 10443 | AF39: 6267 | AG39: 5289 | AH39: 5552 | AI39: 4990
C40: Derivatives | D40: 622 | E40: 622 | F40: 739 | G40: 795 | H40: 510 | I40: 500 | J40: 719 | K40: 1604 | L40: 413 | M40: 406 | N40: 409 | O40: 386 | P40: 1520 | Q40: 438 | R40: 321 | S40: 577 | T40: 308 | U40: 388 | AF40: 795 | AG40: 1604 | AH40: 386 | AI40: 577
... C43: Cash | D43: 2659 | E43: 2558 | F43: 2423 | G43: 2328 | H43: 2571 | I43: 3990 | J43: 2196 | K43: 1527 | L43: 1898 | M43: 2059 | N43: 3428 | O43: 1970 | P43: 1919 | Q43: 3475 | R43: 3895 | S43: 1707 | T43: 1708 | U43: 3457 | AF43: 2328 | AG43: 1527 | AH43: 1970 | AI43: 1707
C44: Total assets | D44: =SUM(D29:D43) -> 57189 | E44: =SUM(E29:E43) -> 59388 | F44: =SUM(F29:F43) -> 60425 | G44: =SUM(G29:G43) -> 61636 | H44: =SUM(H29:H43) -> 65567 | I44: =SUM(I29:I43) -> 66270 | J44: =SUM(J29:J43) -> 59590 | K44: =SUM(K29:K43) -> 57610 | ... U44: =SUM(U29:U43) -> 58661 | AF44: =SUM(AF29:AF43) -> 61636 | AG44: =SUM(AG29:AG43) -> 57610 | AH44: =SUM(AH29:AH43) -> 56805 | AI44: =SUM(AI29:AI43) -> 52093
C45: Equity | D45: 23657 | E45: 25021 | F45: 26461 | G45: 24002 | H45: 25807 | I45: 26276 | J45: 26127 | K45: 23770 | L45: 25961 | M45: 25512 | N45: 24700 | O45: 24619 | P45: 24163 | Q45: 24641 | R45: 24640 | S45: 23637 | T45: 25157 | U45: 25764 | AF45: 24002 | AG45: 23770 | AH45: 24619 | AI45: 23637
C46: Non-controlling interests | D46: 14 | E46: 13 | F46: 11 | G46: 10 | H46: 10 | I46: 3 | J46: 2 | K46: 2 | L46: 3 | M46: 3 | N46: 3 | O46: 3 | P46: 4 | Q46: 4 | R46: 4 | S46: 3 | T46: 4 | U46: 3 | AF46: 10 | AG46: 2 | AH46: 3 | AI46: 3
C47: Total equity | D47: =SUM(D45:D46) -> 23671 | E47: =SUM(E45:E46) -> 25034 | F47: =SUM(F45:F46) -> 26472 | G47: =SUM(G45:G46) -> 24012 | H47: =SUM(H45:H46) -> 25817 | I47: =SUM(I45:I46) -> 26279 | J47: =SUM(J45:J46) -> 26129 | K47: =SUM(K45:K46) -> 23772 | ... U47: =SUM(U45:U46) -> 25767 | AF47: =SUM(AF45:AF46) -> 24012 | AG47: =SUM(AG45:AG46) -> 23772 | AH47: =SUM(AH45:AH46) -> 24622 | AI47: =SUM(AI45:AI46) -> 23640
C48: Non-current Borrowings | D48: 2272 | E48: 3933 | F48: 3826 | G48: 8927 | H48: 11301 | I48: 12074 | J48: 12053 | K48: 8556 | L48: 11549 | M48: 11629 | N48: 8721 | O48: 10316 | P48: 10181 | Q48: 9816 | R48: 9802 | S48: 9200 | T48: 8485 | U48: 8245 | AF48: 8927 | AG48: 8556 | AH48: 10316 | AI48: 9200
C49: Lease liabilities | D49: 1330 | E49: 1312 | F49: 1349 | G49: 1708 | H49: 1642 | I49: 1613 | J49: 1610 | K49: 1436 | L49: 1473 | M49: 1390 | N49: 1269 | O49: 1315 | P49: 1146 | Q49: 1108 | R49: 1028 | S49: 1199 | T49: 1195 | U49: 1376 | AF49: 1708 | AG49: 1436 | AH49: 1315 | AI49: 1199
C50: Derivatives | D50: 60 | E50: 73 | F50: 102 | G50: 0 | H50: 0 | I50: 0 | J50: 0 | K50: 0 | L50: 0 | M50: 2 | N50: 37 | O50: 34 | P50: 28 | Q50: 49 | R50: 41 | S50: 18 | T50: 0 | U50: 10 | AF50: 0 | AG50: 0 | AH50: 34 | AI50: 18
C51: Deferred tax liabilities | D51: 2210 | E51: 1907 | F51: 2086 | G51: 2056 | H51: 2522 | I51: 2607 | J51: 2064 | K51: 2334 | L51: 2378 | M51: 2351 | N51: 2308 | O51: 2349 | P51: 2265 | Q51: 2205 | R51: 2167 | S51: 2291 | T51: 1943 | U51: 2215 | AF51: 2056 | AG51: 2334 | AH51: 2349 | AI51: 2291
C52: Provisions for pension | D52: 2215 | E52: 1701 | F52: 1631 | G52: 1681 | H52: 1599 | I52: 1713 | J52: 1637 | K52: 2209 | L52: 2229 | M52: 1935 | N52: 2110 | O52: 2056 | P52: 2005 | Q52: 2040 | R52: 1931 | S52: 1905 | T52: 2042 | U52: 2065 | AF52: 1681 | AG52: 2209 | AH52: 2056 | AI52: 1905
C53: Other provisions | D53: 635 | E53: 641 | F53: 660 | G53: 700 | H53: 710 | I53: 713 | J53: 666 | K53: 620 | L53: 677 | M53: 682 | N53: 620 | O53: 679 | P53: 634 | Q53: 641 | R53: 600 | S53: 556 | T53: 597 | U53: 612 | AF53: 700 | AG53: 620 | AH53: 679 | AI53: 556
C54: Trade payable | D54: 8224 | E54: 7918 | F54: 6843 | G54: 7111 | H54: 7613 | I54: 7017 | J54: 5016 | K54: 5487 | L54: 6841 | M54: 5934 | N54: 4341 | O54: 5896 | P54: 7892 | Q54: 6786 | R54: 5253 | S54: 5786 | T54: 6827 | U54: 6163 | AF54: 7111 | AG54: 5487 | AH54: 5896 | AI54: 5786
C55: Current tax libailities | D55: 1225 | E55: 1289 | F55: 655 | G55: 667 | H55: 785 | I55: 749 | J55: 633 | K55: 662 | L55: 728 | M55: 829 | N55: 537 | O55: 371 | P55: 505 | Q55: 786 | R55: 695 | S55: 381 | T55: 513 | U55: 598 | AF55: 667 | AG55: 662 | AH55: 371 | AI55: 381
C56: Other liabilities | D56: 4985 | E56: 5062 | F56: 4776 | G56: 4097 | H56: 5639 | I56: 6202 | J56: 4791 | K56: 3866 | L56: 5448 | M56: 4916 | N56: 4233 | O56: 4038 | P56: 4941 | Q56: 5330 | R56: 4350 | S56: 3814 | T56: 5675 | U56: 5670 | AF56: 4097 | AG56: 3866 | AH56: 4038 | AI56: 3814
C57: Dividend payable | D57: 8346 | E57: 1141 | F57: 1141 | G57: 7700 | H57: 5213 | I57: 1141 | J57: 1141 | K57: 6031 | L57: 4145 | M57: 1143 | N57: 1143 | O57: 2203 | P57: 3383 | Q57: 288 | R57: 288 | S57: 1716 | T57: 3592 | U57: 432 | AF57: 7700 | AG57: 6031 | AH57: 2203 | AI57: 1716
C58: Current borrowings | D58: 515 | E58: 6914 | F58: 8122 | G58: 649 | H58: 608 | I58: 2358 | J58: 1246 | K58: 648 | L58: 691 | M58: 1647 | N58: 3047 | O58: 687 | P58: 641 | Q58: 2492 | R58: 697 | S58: 616 | T58: 621 | U58: 2875 | AF58: 649 | AG58: 648 | AH58: 687 | AI58: 616
C59: Lease liabilities | D59: 531 | E59: 539 | F59: 574 | G59: 912 | H59: 672 | I59: 636 | J59: 636 | K59: 575 | L59: 688 | M59: 691 | N59: 671 | O59: 873 | P59: 342 | Q59: 618 | R59: 586 | S59: 249 | T59: 678 | U59: 673 | AF59: 912 | AG59: 575 | AH59: 873 | AI59: 249
... C62: Liabilities related to assets for sale | D62: 0 | E62: 0 | F62: 0 | G62: 0 | H62: 0 | I62: 0 | J62: 0 | K62: 0 | L62: 0 | M62: 0 | N62: 0 | O62: 0 | P62: 0 | Q62: 0 | R62: 0 | S62: 0 | T62: 0 | U62: 0 | AF62: 0 | AG62: 0 | AH62: 0 | AI62: 0
C63: Total debt | D63: =SUM(D48:D62) -> 33518 | E63: =SUM(E48:E62) -> 34352 | F63: =SUM(F48:F62) -> 33952 | G63: =SUM(G48:G62) -> 37624 | H63: =SUM(H48:H62) -> 39751 | I63: =SUM(I48:I62) -> 39991 | J63: =SUM(J48:J62) -> 33456 | K63: =SUM(K48:K62) -> 33839 | ... U63: =SUM(U48:U62) -> 32897 | AF63: =SUM(AF48:AF62) -> 37624 | AG63: =SUM(AG48:AG62) -> 33839 | AH63: =SUM(AH48:AH62) -> 32181 | AI63: =SUM(AI48:AI62) -> 28554
C64: Total E/D | D64: =D47+D63 -> 57189 | E64: =E47+E63 -> 59386 | F64: =F47+F63 -> 60424 | G64: =G47+G63 -> 61636 | H64: =H47+H63 -> 65568 | I64: =I47+I63 -> 66270 | J64: =J47+J63 -> 59585 | K64: =K47+K63 -> 57611 | ... U64: =U47+U63 -> 58664 | AF64: =AF47+AF63 -> 61636 | AG64: =AG47+AG63 -> 57611 | AH64: =AH47+AH63 -> 56803 | AI64: =AI47+AI63 -> 52194
C66: Cash flow SEKm | Y66: =Y10 -> 2827 | Z66: =Z10 -> 3218 | AA66: =AA10 -> 3790 | AB66: =AB10 -> 2070 | AC66: =AC10 -> 3690 | AD66: =AD10 -> 3669 | AE66: =AE10 -> 5746 | AF66: =AF10 -> 3043 | ... AI66: =AI10 -> 2899
C67: Model OI | D67: =D10 -> 2159 | E67: =E10 -> 2064 | F67: =F10 -> 556 | G67: =G10 -> -1737 | H67: =H10 -> 2364 | I67: =I10 -> 2101 | J67: =J10 -> 398 | K67: =K10 -> -983 | ... U67: =U10 -> 1601 | Y67: 2827 | Z67: 3218 | AA67: 3790 | AB67: 2070 | AC67: 3690 | AD67: 3669 | AE67: 5746 | AF67: 3043 | AG67: 3880 | AH67: 2597 | AI67: 2899
C68: Reported OI | D68: 2159 | E68: 2065 | F68: 555 | G68: -1737 | H68: 2364 | I68: 2101 | J68: 398 | K68: -983 | L68: 1930 | M68: 1899 | N68: 52 | O68: -1285 | P68: 1532 | Q68: 2063 | R68: 141 | S68: -837 | T68: 1710 | U68: 1600 | Y68: =1153+253 -> 1406 | Z68: =1164-91 -> 1073 | AA68: =1315-118 -> 1197 | AB68: =1930+676 -> 2606 | AC68: =2089+270 -> 2359 | AD68: =2537+807 -> 3344 | AE68: =2241+71 -> 2312 | AF68: =3342+637 -> 3979 | AG68: =3105+481 -> 3586 | AH68: =2908+446 -> 3354 | AI68: 3001
C69: Non-cash items | D69: 662 | E69: 433 | F69: 646 | G69: 2239 | H69: 916 | I69: 994 | J69: 399 | K69: 1276 | L69: 900 | M69: 762 | N69: 592 | O69: 1101 | P69: 790 | Q69: 905 | R69: 711 | S69: 595 | T69: 888 | U69: 1196 | Y69: -27 | Z69: -45 | AA69: -52 | AB69: -62 | AC69: -272 | AD69: -244 | AE69: -192 | AF69: -222 | AG69: -565 | AH69: -591 | AI69: -583
C70: Restructuring costs | D70: -44 | E70: -29 | F70: -39 | G70: -111 | H70: -88 | I70: -60 | J70: -143 | K70: -274 | L70: -75 | M70: -116 | N70: -88 | O70: -314 | P70: -154 | Q70: -153 | R70: -96 | S70: -181 | T70: -56 | U70: -62 | Y70: -251 | Z70: -353 | AA70: -467 | AB70: -448 | AC70: -490 | AD70: -327 | AE70: -180 | AF70: -247 | AG70: -862 | AH70: -745 | AI70: -575
C71: Net financial items | D71: -57 | E71: -29 | F71: -53 | G71: -108 | H71: -174 | I71: -195 | J71: -177 | K71: -315 | L71: -166 | M71: -234 | N71: -217 | O71: -128 | P71: -150 | Q71: -156 | R71: -141 | S71: -128 | T71: -173 | U71: -249 | Y71: -252 | Z71: -280 | AA71: -431 | AB71: -970 | AC71: -811 | AD71: -291 | AE71: -198 | AF71: -2318 | AG71: -493 | AH71: -1017 | AI71: -370
C72: Taxes paid | D72: -1013 | E72: -451 | F72: -548 | G72: -305 | H72: -620 | I72: -205 | J72: -99 | K72: 431 | L72: -253 | M72: -100 | N72: -336 | O72: -328 | P72: -121 | Q72: -133 | R72: -56 | S72: -60 | T72: -82 | U72: -208 | Y72: =-89-287-175-32 -> -583 | Z72: =-821+56+537+170 -> -58 | AA72: =-567-104+406-33 -> -298 | AB72: =-1366-69+296-70 -> -1209 | AC72: =627+114-656+347 -> 432 | AD72: =278+55+1014+584 -> 1931 | AE72: =-2695-528+1476-76 -> -1823 | AF72: =-3832-1511-336-264 -> -5943 | AG72: =1918+917-1579+264 -> 1520 | AH72: =3150-120+222-13 -> 3239 | AI72: -168
C73: WC | D73: =-847-4112+1146+1163 -> -2650 | E73: =-372+643-596-280 -> -605 | F73: =-599+1450-1224-271 -> -644 | G73: =-2014+508+338-876 -> -2044 | H73: =729-4062+479+1583 -> -1271 | I73: =1509+1336-825+340 -> 2360 | J73: =532+2586-1878-912 -> 328 | K73: =-852+1057+645-747 -> 103 | L73: =778-5716+1164+898 -> -2876 | M73: =2196+590-836+1 -> 1951 | N73: =923+4345-1540-487 -> 3241 | O73: =-748+662+1434-425 -> 923 | P73: =442-5347+1928+1218 -> -1759 | Q73: =1085-171-744+130 -> 300 | R73: =-383+4990-1542-824 -> 2241 | S73: =-1872+647+607-332 -> -950 | T73: -3192 | U73: 1476 | Y73: =SUM(Y67:Y72) -> 3120 | Z73: =SUM(Z67:Z72) -> 3555 | AA73: =SUM(AA67:AA72) -> 3739 | AB73: =SUM(AB67:AB72) -> 1987 | AC73: =SUM(AC67:AC72) -> 4908 | AD73: =SUM(AD67:AD72) -> 8082 | AE73: =SUM(AE67:AE72) -> 5665 | AF73: =SUM(AF67:AF72) -> -1708 | ... AI73: =SUM(AI67:AI72) -> 4204
C74: CFFO | D74: =SUM(D68:D73) -> -943 | E74: =SUM(E68:E73) -> 1384 | F74: =SUM(F68:F73) -> -83 | G74: =SUM(G68:G73) -> -2066 | H74: =SUM(H68:H73) -> 1127 | I74: =SUM(I68:I73) -> 4995 | J74: =SUM(J68:J73) -> 706 | K74: =SUM(K68:K73) -> 238 | ... U74: =SUM(U68:U73) -> 3753
Y75: -1325 | Z75: -1830 | AA75: -3869 | AB75: -2472 | AC75: -1939 | AD75: -2395 | AE75: -6376 | AF75: -2301 | AG75: -2652 | AH75: =-2465 -> -2465 | AI75: -1886
C76: Capex | D76: -276 | E76: -683 | F76: -563 | G76: -779 | H76: -539 | I76: -562 | J76: -570 | K76: -981 | L76: -517 | M76: -704 | N76: -351 | O76: -894 | P76: -234 | Q76: -626 | R76: -468 | S76: -558 | T76: -384 | U76: -466 | Y76: =Y75 -> -1325 | Z76: =Z75 -> -1830 | AA76: =AA75 -> -3869 | AB76: =AB75 -> -2472 | AC76: =AC75 -> -1939 | AD76: =AD75 -> -2395 | AE76: =AE75 -> -6376 | AF76: =AF75 -> -2301 | ... AI76: =AI75 -> -1886
C77: CFFI | D77: =D76 -> -276 | E77: =E76 -> -683 | F77: =F76 -> -563 | G77: =G76 -> -779 | H77: =H76 -> -539 | I77: =I76 -> -562 | J77: =J76 -> -570 | K77: =K76 -> -981 | ... U77: =U76 -> -466
Y78: -945 | Z78: -944 | AA78: -1114 | AB78: -1286 | AC78: -1287 | AD78: -1288 | AE78: -1375 | AF78: -1711 | AG78: -1714 | AH78: -1715 | AI78: -572
C79: Dividend to shareholders | D79: 0 | E79: -570 | F79: 0 | G79: -1141 | H79: 0 | I79: -571 | J79: 0 | K79: -1143 | L79: 0 | M79: -570 | N79: 0 | O79: -1144 | P79: 0 | Q79: -286 | R79: 0 | S79: -286 | T79: 0 | U79: -284 | Y79: -3 | Z79: -1 | AA79: -10 | AB79: -6 | AC79: -1 | AD79: 0 | AE79: -2 | AF79: -2 | AG79: -2 | AH79: 0 | AI79: -1
C80: Dividend to non-controlling | D80: 0 | E80: -1 | F80: 0 | G80: 0 | H80: 0 | I80: -2 | J80: 0 | K80: 0 | L80: 0 | M80: 0 | N80: 0 | O80: 0 | P80: 0 | Q80: -1 | R80: 0 | S80: 0 | T80: 0 | U80: -1 | Y80: =946-938 -> 8 | Z80: =1791-2100 -> -309 | AA80: =2412-1453 -> 959 | AB80: =4875-2950 -> 1925 | AC80: =3577-3466 -> 111 | AD80: =2601-2609 -> -8 | AE80: =2100-3803 -> -1703 | AF80: =10796-2543 -> 8253 | AG80: =5585-7650 -> -2065 | AH80: =5735-7882 -> -2147 | AI80: -1414
C81: Proceeds/repayment of borrowings | D81: 0 | E81: 113 | F81: 0 | G81: 0 | H81: 0 | I81: -2229 | J81: -1024 | K81: 1392 | L81: 971 | M81: -2370 | N81: -1398 | O81: 651 | P81: 1165 | Q81: -1320 | R81: -1759 | S81: 500 | T81: 1098 | U81: -999 | Y81: =-774-63 -> -837 | Z81: =-239-29 -> -268 | AA81: =98+55+155 -> 308 | AB81: =-1053+332 -> -721 | AC81: =-447+194-1017 -> -1270 | AD81: =-461+1003-529 -> 13 | AE81: =-478+63+137 -> -278 | AF81: =-540-2131+105 -> -2566 | AG81: =-744-157-478 -> -1379 | AH81: =-748+574+52 -> -122 | AI81: -475
C82: Other financing activities | D82: 1626 | E82: -566 | F82: 540 | G82: 3975 | H82: -337 | I82: -279 | J82: -850 | K82: -119 | L82: 393 | M82: -337 | N82: -74 | O82: -103 | P82: -1010 | Q82: 952 | R82: -145 | S82: -272 | T82: 133 | U82: -318 | Y82: =SUM(Y78:Y81) -> -1777 | Z82: =SUM(Z78:Z81) -> -1522 | AA82: =SUM(AA78:AA81) -> 143 | AB82: =SUM(AB78:AB81) -> -88 | AC82: =SUM(AC78:AC81) -> -2447 | AD82: =SUM(AD78:AD81) -> -1283 | AE82: =SUM(AE78:AE81) -> -3358 | AF82: =SUM(AF78:AF81) -> 3974 | ... AI82: =SUM(AI78:AI81) -> -2462
C83: CFFF | D83: =SUM(D79:D82) -> 1626 | E83: =SUM(E79:E82) -> -1024 | F83: =SUM(F79:F82) -> 540 | G83: =SUM(G79:G82) -> 2834 | H83: =SUM(H79:H82) -> -337 | I83: =SUM(I79:I82) -> -3081 | J83: =SUM(J79:J82) -> -1874 | K83: =SUM(K79:K82) -> 130 | ... U83: =SUM(U79:U82) -> -1602
Y84: 25 | Z84: 112 | AA84: -78 | AB84: 47 | AC84: 43 | AD84: -162 | AE84: 126 | AF84: 154 | AG84: -55 | AH84: 55 | AI84: -117
C85: FX | D85: 44 | E85: 226 | F85: -31 | G85: -84 | H85: -8 | I85: -608 | J85: -58 | K85: -57 | L85: 64 | M85: -19 | N85: -52 | O85: 63 | P85: -110 | Q85: 13 | R85: -8 | S85: -12 | T85: 33 | U85: 62
Y86: =Y73+Y76+Y82+Y84 -> 43 | Z86: =Z73+Z76+Z82+Z84 -> 315 | AA86: =AA73+AA76+AA82+AA84 -> -65 | AB86: =AB73+AB76+AB82+AB84 -> -526 | AC86: =AC73+AC76+AC82+AC84 -> 565 | AD86: =AD73+AD76+AD82+AD84 -> 4242 | AE86: =AE73+AE76+AE82+AE84 -> -3943 | AF86: =AF73+AF76+AF82+AF84 -> 119 | ... AI86: =AI73+AI76+AI82+AI84 -> -261
C87: CIC | D87: =D74+D77+D83+D85 -> 451 | E87: =E74+E77+E83+E85 -> -97 | F87: =F74+F77+F83+F85 -> -137 | G87: =G74+G77+G83+G85 -> -95 | H87: =H74+H77+H83+H85 -> 243 | I87: =I74+I77+I83+I85 -> 744 | J87: =J74+J77+J83+J85 -> -1796 | K87: =K74+K77+K83+K85 -> -670 | ... U87: =U74+U77+U83+U85 -> 1747
Y88: =Y73+Y75 -> 1795 | Z88: =Z73+Z75 -> 1725 | AA88: =AA73+AA75 -> -130 | AB88: =AB73+AB75 -> -485 | AC88: =AC73+AC75 -> 2969 | AD88: =AD73+AD75 -> 5687 | AE88: =AE73+AE75 -> -711 | AF88: =AF73+AF75 -> -4009 | ... AI88: =AI73+AI75 -> 2318
C89: FCF | D89: =D74+D76 -> -1219 | E89: =E74+E76 -> 701 | F89: =F74+F76 -> -646 | G89: =G74+G76 -> -2845 | H89: =H74+H76 -> 588 | I89: =I74+I76 -> 4433 | J89: =J74+J76 -> 136 | K89: =K74+K76 -> -743 | ... U89: =U74+U76 -> 3287

Sheet Segementer
B3: SEKm | C3: Q122 | D3: Q222 | E3: Q322 | F3: Q422 | G3: 2022 | H3: Q123 | I3: Q223 | J3: Q323 | K3: Q423 | L3: 2023 | M3: Q124 | N3: Q224 | O3: Q324 | P3: Q424 | Q3: 2024 | R3: Q125 | S3: Q225 | T3: Q325 | U3: Q425 | V3: 2025 | W3: Q126 | X3: Q226 | Y3: Q326 | Z3: Q426 | AA3: 2026
B4: Forest & Garden div
B5: Revenue | C5: 8701 | D5: 8826 | E5: 7761 | F5: 6793 | G5: =SUM(C5:F5) -> 32081 | H5: 10656 | I5: 9722 | J5: 6123 | K5: 5257 | L5: =SUM(H5:K5) -> 31758 | M5: 8272 | N5: 8722 | O5: 5825 | P5: 5332 | Q5: =SUM(M5:P5) -> 28151 | R5: 8768 | S5: 8701 | T5: 5594 | U5: 4725 | V5: =SUM(R5:U5) -> 27788 | W5: 8468 | X5: 8338 | AA5: =SUM(W5:Z5) -> 16806
B6: Growth % | H6: =(H5-C5)/C5 -> 0.22468682 | I6: =(I5-D5)/D5 -> 0.10151824 | J6: =(J5-E5)/E5 -> -0.21105528 | K6: =(K5-F5)/F5 -> -0.22611512 | L6: =(L5-G5)/G5 -> -0.010068265 | M6: =(M5-H5)/H5 -> -0.22372372 | N6: =(N5-I5)/I5 -> -0.10285949 | O6: =(O5-J5)/J5 -> -0.048668953 | ... AA6: =(AA5-V5)/V5 -> -0.39520656
B7: Organic growth % | C7: -0.07 | D7: -0.08 | E7: 0.09 | F7: 0.15 | H7: 0.14 | I7: 0.03 | J7: -0.21 | K7: -0.21 | M7: -0.17 | N7: -0.06 | O7: -0.01 | P7: 0 | R7: 0.06 | S7: 0.05 | T7: 0.01 | U7: -0.03 | W7: 0.03 | X7: -0.03
B8: Operating income | C8: 1392 | D8: 1107 | E8: 560 | F8: -1252 | G8: =SUM(C8:F8) -> 1807 | H8: 1670 | I8: 1123 | J8: 291 | K8: -379 | L8: =SUM(H8:K8) -> 2705 | M8: 1191 | N8: 1145 | O8: 144 | P8: -414 | Q8: =SUM(M8:P8) -> 2066 | R8: 1107 | S8: 1145 | T8: 222 | U8: -327 | V8: =SUM(R8:U8) -> 2147 | W8: 1308 | X8: 1099 | AA8: =SUM(W8:Z8) -> 2407
B9: Operating margin | C9: =C8/C5 -> 0.15998161 | D9: =D8/D5 -> 0.12542488 | E9: =E8/E5 -> 0.07215565 | F9: =F8/F5 -> -0.18430738 | G9: =G8/G5 -> 0.056326174 | H9: =H8/H5 -> 0.15671922 | I9: =I8/I5 -> 0.11551121 | J9: =J8/J5 -> 0.047525723 | ... AA9: =AA8/AA5 -> 0.14322266
B10: Gardena
B11: Revenue | C11: 4960 | D11: 4775 | E11: 2400 | F11: 1470 | G11: =SUM(C11:F11) -> 13605 | H11: 4321 | I11: 5031 | J11: 2287 | K11: 1326 | L11: =SUM(H11:K11) -> 12965 | M11: 4414 | N11: 4566 | O11: 2037 | P11: 1264 | Q11: =SUM(M11:P11) -> 12281 | R11: 4045 | S11: 4668 | T11: 1799 | U11: 981 | V11: =SUM(R11:U11) -> 11493 | W11: 3743 | X11: 4072 | AA11: =SUM(W11:Z11) -> 7815
B12: Growth % | H12: =(H11-C11)/C11 -> -0.12883065 | I12: =(I11-D11)/D11 -> 0.053612565 | J12: =(J11-E11)/E11 -> -0.047083333 | K12: =(K11-F11)/F11 -> -0.097959184 | L12: =(L11-G11)/G11 -> -0.047041529 | M12: =(M11-H11)/H11 -> 0.021522796 | N12: =(N11-I11)/I11 -> -0.092426953 | O12: =(O11-J11)/J11 -> -0.10931351 | ... AA12: =(AA11-V11)/V11 -> -0.32002088
B13: Organic growth % | C13: 0.05 | D13: -0.1 | E13: -0.2 | F13: -0.11 | H13: -0.2 | I13: -0.02 | J13: -0.08 | K13: -0.04 | M13: 0.02 | N13: -0.09 | O13: -0.08 | P13: -0.08 | R13: -0.09 | S13: 0.07 | T13: -0.07 | U13: -0.1 | W13: -0.01 | X13: -0.11
B14: Operating income | C14: 706 | D14: 773 | E14: -93 | F14: -468 | G14: =SUM(C14:F14) -> 918 | H14: 585 | I14: 818 | J14: -46 | K14: -407 | L14: =SUM(H14:K14) -> 950 | M14: 673 | N14: 691 | O14: -156 | P14: -467 | Q14: =SUM(M14:P14) -> 741 | R14: 451 | S14: 816 | T14: -161 | U14: -377 | V14: =SUM(R14:U14) -> 729 | W14: 447 | X14: 420 | AA14: =SUM(W14:Z14) -> 867
B15: Operating margin | C15: =C14/C11 -> 0.14233871 | D15: =D14/D11 -> 0.16188482 | E15: =E14/E11 -> -0.03875 | F15: =F14/F11 -> -0.31836735 | G15: =G14/G11 -> 0.067475193 | H15: =H14/H11 -> 0.13538533 | I15: =I14/I11 -> 0.16259193 | J15: =J14/J11 -> -0.020113686 | ... AA15: =AA14/AA11 -> 0.1109405
B16: Construction
B17: Revenue | C17: 1981 | D17: 2157 | E17: 2024 | F17: 2071 | G17: =SUM(C17:F17) -> 8233 | H17: 2177 | I17: 2192 | J17: 2061 | K17: 1968 | L17: =SUM(H17:K17) -> 8398 | M17: 2008 | N17: 2105 | O17: 1832 | P17: 1820 | Q17: =SUM(M17:P17) -> 7765 | R17: 1857 | S17: 1871 | T17: 1773 | U17: 1676 | V17: =SUM(R17:U17) -> 7177 | W17: 1712 | X17: 1928 | AA17: =SUM(W17:Z17) -> 3640
B18: Growth % | H18: =(H17-C17)/C17 -> 0.098939929 | I18: =(I17-D17)/D17 -> 0.01622624 | J18: =(J17-E17)/E17 -> 0.018280632 | K18: =(K17-F17)/F17 -> -0.049734428 | L18: =(L17-G17)/G17 -> 0.020041297 | M18: =(M17-H17)/H17 -> -0.077629766 | N18: =(N17-I17)/I17 -> -0.039689781 | O18: =(O17-J17)/J17 -> -0.11111111 | ... AA18: =(AA17-V17)/V17 -> -0.4928243
B19: Organic growth % | C19: 0.1 | D19: 0.02 | E19: -0.02 | F19: -0.01 | H19: 0 | I19: -0.05 | J19: -0.01 | K19: -0.06 | M19: -0.08 | N19: -0.03 | O19: -0.08 | P19: -0.09 | R19: -0.08 | S19: -0.04 | T19: 0.03 | U19: 0.02 | W19: 0.01 | X19: 0.05
B20: Operating income | C20: 152 | D20: 299 | E20: 183 | F20: 80 | G20: =SUM(C20:F20) -> 714 | H20: 262 | I20: 272 | J20: 225 | K20: -4 | L20: =SUM(H20:K20) -> 755 | M20: 203 | N20: 204 | O20: 150 | P20: -239 | Q20: =SUM(M20:P20) -> 318 | R20: 135 | S20: 237 | T20: 205 | U20: 63 | V20: =SUM(R20:U20) -> 640 | W20: 110 | X20: 267 | AA20: =SUM(W20:Z20) -> 377
B21: Operating margin | C21: =C20/C17 -> 0.076728925 | D21: =D20/D17 -> 0.13861845 | E21: =E20/E17 -> 0.09041502 | F21: =F20/F17 -> 0.038628682 | G21: =G20/G17 -> 0.086724159 | H21: =H20/H17 -> 0.1203491 | I21: =I20/I17 -> 0.12408759 | J21: =J20/J17 -> 0.10917031 | ... AA21: =AA20/AA17 -> 0.10357143

Sheet SOTP
A3: EBIT 26E
A4: =Modell!AJ10 -> 2327.47
C6: SEKm | E6: EBIT 26E | G6: EV/EBIT | H6: Value | I6: Per/Share
C7: Forest & Garden div | E7: 2200 | G7: 10 | H7: =E7*G7 -> 22000 | I7: =H7/Modell!$B$5 -> 38.481721
C8: Gardena | E8: 750 | G8: 8 | H8: =E8*G8 -> 6000 | I8: =H8/Modell!$B$5 -> 10.495015
C9: Construction | E9: 700 | G9: 6 | H9: =E9*G9 -> 4200 | I9: =H9/Modell!$B$5 -> 7.3465104
C10: Enterprise value | E10: =SUM(E7:E9) -> 3650 | H10: =SUM(H7:H9) -> 32200 | I10: =SUM(I7:I9) -> 56.323246
C12: Cash | H12: =Modell!B7 -> 3457 | I12: =H12/Modell!$B$5 -> 6.0468777
C13: Debt | H13: =-Modell!B8 -> -11120 | I13: =H13/Modell!$B$5 -> -19.450761
C14: Equity value | H14: =SUM(H10:H13) -> 24537 | I14: =SUM(I10:I13) -> 42.919363
A61: Forest & Garden div | B61: =I7 -> 38.481721
A62: Gardena | B62: =I8 -> 10.495015
A63: Construction | B63: =I9 -> 7.3465104
A64: Enterprise value | B64: =I10 -> 56.323246
B65: =I11 -> 0
A66: Cash | B66: =I12 -> 6.0468777
A67: Debt | B67: =I13 -> -19.450761
A68: Equity value | B68: =I14 -> 42.919363

Sheet Nøkkeltall
D4: 2026 | E4: 2027 | F4: 2028
C5: EV/EBIT | D5: =Modell!$B$9/Modell!AJ10 -> 12.257967 | E5: =Modell!$B$9/Modell!AK10 -> 11.900939 | F5: =Modell!$B$9/Modell!AL10 -> 11.554309
C6: P/E | D6: =Modell!$B$4/Modell!AJ16 -> 11.206938 | E6: =Modell!$B$4/Modell!AK16 -> 10.880523 | F6: =Modell!$B$4/Modell!AL16 -> 10.563614

Sheet Nedsideberegning
A3: Nedside | D3: FY 2015 | E3: FY 2016 | F3: FY 2017 | G3: FY 2018 | H3: FY 2019 | I3: FY 2020 | J3: FY 2021 | K3: FY 2022 | L3: FY 2023 | M3: FY 2024 | N3: FY 2025 | O3: FY 2026 | P3: FY 2027 | Q3: FY 2028 | R3: FY 2029 | S3: FY 2030 | T3: FY 2031 | U3: FY 2032 | V3: FY 2033 | W3: FY 2034 | X3: FY 2035
A4: Nullveskt og konstante dårligste marginer | C4: Revenues | D4: 36170 | E4: 35982 | F4: 39394 | G4: 41085 | H4: 42277 | I4: 41943 | J4: 47059 | K4: 54037 | L4: 53261 | M4: 48352 | N4: 46614 | O4: =N4*1 -> 46614 | P4: =O4*1 -> 46614 | Q4: =P4*1 -> 46614 | R4: =Q4*1 -> 46614 | S4: =R4*1 -> 46614 | T4: =S4*1 -> 46614 | U4: =T4*1 -> 46614 | V4: =U4*1 -> 46614 | ... X4: =W4*1 -> 46614
A5: =AA21 -> 38.720239 | C5: COGS | D5: -25996 | E5: -24886 | F5: -27922 | G5: -30583 | H5: -29748 | I5: -29367 | J5: -31546 | K5: -39424 | L5: -37136 | M5: -34053 | N5: -32514 | O5: =O4*-0.74 -> -34494.36 | P5: =P4*-0.74 -> -34494.36 | Q5: =Q4*-0.74 -> -34494.36 | R5: =R4*-0.74 -> -34494.36 | S5: =S4*-0.74 -> -34494.36 | T5: =T4*-0.74 -> -34494.36 | U5: =U4*-0.74 -> -34494.36 | V5: =V4*-0.74 -> -34494.36 | ... X5: =X4*-0.74 -> -34494.36
A6: =AA22 -> 0.060828462 | C6: Gross profit | D6: =SUM(D4:D5) -> 10174 | E6: =SUM(E4:E5) -> 11096 | F6: =SUM(F4:F5) -> 11472 | G6: =SUM(G4:G5) -> 10502 | H6: =SUM(H4:H5) -> 12529 | I6: =SUM(I4:I5) -> 12576 | J6: =SUM(J4:J5) -> 15513 | K6: =SUM(K4:K5) -> 14613 | ... X6: =SUM(X4:X5) -> 12119.64
C7: Selling expenses | D7: -5833 | E7: -6168 | F7: -5870 | G7: -6473 | H7: -6985 | I7: -6596 | J7: -7152 | K7: -8770 | L7: -9034 | M7: -8587 | N7: -8116 | O7: =N7*0.87 -> -7060.92 | P7: =O7*1 -> -7060.92 | Q7: =P7*1 -> -7060.92 | R7: =Q7*1 -> -7060.92 | S7: =R7*1 -> -7060.92 | T7: =S7*1 -> -7060.92 | U7: =T7*1 -> -7060.92 | V7: =U7*1 -> -7060.92 | W7: =V7*1 -> -7060.92 | X7: =W7*1 -> -7060.92
C8: Administrative expenses | D8: -1532 | E8: -1707 | F8: -1879 | G8: -2014 | H8: -2051 | I8: -2335 | J8: -2704 | K8: -3001 | L8: -3211 | M8: -3275 | N8: -3074 | O8: =N8*0.88 -> -2705.12 | P8: =O8*1 -> -2705.12 | Q8: =P8*1 -> -2705.12 | R8: =Q8*1 -> -2705.12 | S8: =R8*1 -> -2705.12 | T8: =S8*1 -> -2705.12 | U8: =T8*1 -> -2705.12 | V8: =U8*1 -> -2705.12 | W8: =V8*1 -> -2705.12 | X8: =W8*1 -> -2705.12
C9: Other operating inc/ex | D9: =23-5 -> 18 | E9: -3 | F9: =68-1 -> 67 | G9: =63-8 -> 55 | H9: =203-6 -> 197 | I9: =26-2 -> 24 | J9: =112-23 -> 89 | K9: =212-11 -> 201 | L9: 0 | M9: 160 | N9: -11 | O9: =N9*0.88 -> -9.68 | P9: =O9*1 -> -9.68 | Q9: =P9*1 -> -9.68 | R9: =Q9*1 -> -9.68 | S9: =R9*1 -> -9.68 | T9: =S9*1 -> -9.68 | U9: =T9*1 -> -9.68 | V9: =U9*1 -> -9.68 | W9: =V9*1 -> -9.68 | X9: =W9*1 -> -9.68
C10: Operating income | D10: =SUM(D6:D9) -> 2827 | E10: =SUM(E6:E9) -> 3218 | F10: =SUM(F6:F9) -> 3790 | G10: =SUM(G6:G9) -> 2070 | H10: =SUM(H6:H9) -> 3690 | I10: =SUM(I6:I9) -> 3669 | J10: =SUM(J6:J9) -> 5746 | K10: =SUM(K6:K9) -> 3043 | ... X10: =SUM(X6:X9) -> 2343.92
C11: Financial items | D11: =44-388 -> -344 | E11: =29-451 -> -422 | F11: =20-520 -> -500 | G11: =72-581 -> -509 | H11: =18-586 -> -568 | I11: =38-377 -> -339 | J11: =42-294 -> -252 | K11: =38-499 -> -461 | L11: =75-1077 -> -1002 | M11: =86-950 -> -864 | N11: -750 | O11: 0 | P11: 0 | Q11: 0 | R11: 0 | S11: 0 | T11: 0 | U11: 0 | V11: 0 | W11: 0 | X11: 0
C12: PTP | D12: =SUM(D10:D11) -> 2483 | E12: =SUM(E10:E11) -> 2796 | F12: =SUM(F10:F11) -> 3290 | G12: =SUM(G10:G11) -> 1561 | H12: =SUM(H10:H11) -> 3122 | I12: =SUM(I10:I11) -> 3330 | J12: =SUM(J10:J11) -> 5494 | K12: =SUM(K10:K11) -> 2582 | ... X12: =SUM(X10:X11) -> 2343.92
C13: Tax | D13: -595 | E13: -692 | F13: -630 | G13: -348 | H13: -594 | I13: -835 | J13: -1057 | K13: -649 | L13: -702 | M13: -408 | N13: -379 | O13: =O12*-0.2 -> -468.784 | P13: =P12*-0.2 -> -468.784 | Q13: =Q12*-0.2 -> -468.784 | R13: =R12*-0.2 -> -468.784 | S13: =S12*-0.2 -> -468.784 | T13: =T12*-0.2 -> -468.784 | U13: =U12*-0.2 -> -468.784 | V13: =V12*-0.2 -> -468.784 | ... X13: =X12*-0.2 -> -468.784
C14: Net income | D14: =SUM(D12:D13) -> 1888 | E14: =SUM(E12:E13) -> 2104 | F14: =SUM(F12:F13) -> 2660 | G14: =SUM(G12:G13) -> 1213 | H14: =SUM(H12:H13) -> 2528 | I14: =SUM(I12:I13) -> 2495 | J14: =SUM(J12:J13) -> 4437 | K14: =SUM(K12:K13) -> 1933 | ... X14: =SUM(X12:X13) -> 1875.136 | Y14: =X14*(1+$AA$18) -> 1856.3846 | Z14: =Y14*(1+$AA$18) -> 1837.8208 | AA14: =Z14*(1+$AA$18) -> 1819.4426 | AB14: =AA14*(1+$AA$18) -> 1801.2482 | AC14: =AB14*(1+$AA$18) -> 1783.2357 | AD14: =AC14*(1+$AA$18) -> 1765.4033 | AE14: =AD14*(1+$AA$18) -> 1747.7493 | AF14: =AE14*(1+$AA$18) -> 1730.2718 | ... FW14: =FV14*(1+$AA$18) -> 394.90073
C15: Shares | D15: 571.7 | E15: 571.7 | F15: 571.7 | G15: 571.7 | H15: 571.7 | I15: 571.7 | J15: 571.7 | K15: 571.7 | L15: 571.7 | M15: 571.7 | N15: 571.7 | O15: 571.7 | P15: 571.7 | Q15: 571.7 | R15: 571.7 | S15: 571.7 | T15: 571.7 | U15: 571.7 | V15: 571.7 | W15: 571.7 | X15: 571.7
C16: EPS | D16: =D14/D15 -> 3.3024313 | E16: =E14/E15 -> 3.6802519 | F16: =F14/F15 -> 4.6527899 | G16: =G14/G15 -> 2.1217422 | H16: =H14/H15 -> 4.4218996 | I16: =I14/I15 -> 4.364177 | J16: =J14/J15 -> 7.7610635 | K16: =K14/K15 -> 3.381144 | ... X16: =X14/X15 -> 3.27993
Z17: Disocunt | AA17: 0.08
C18: Revenue y/y | E18: =(E4-D4)/D4 -> -0.0051976776 | F18: =(F4-E4)/E4 -> 0.09482519 | G18: =(G4-F4)/F4 -> 0.042925319 | H18: =(H4-G4)/G4 -> 0.029013022 | I18: =(I4-H4)/H4 -> -0.0079002767 | J18: =(J4-I4)/I4 -> 0.12197506 | K18: =(K4-J4)/J4 -> 0.14828194 | L18: =(L4-K4)/K4 -> -0.014360531 | ... X18: =(X4-W4)/W4 -> 0 | Z18: TV | AA18: -0.01
C19: Gross margin | D19: =D6/D4 -> 0.28128283 | E19: =E6/E4 -> 0.30837641 | F19: =F6/F4 -> 0.29121186 | G19: =G6/G4 -> 0.25561641 | H19: =H6/H4 -> 0.29635499 | I19: =I6/I4 -> 0.29983549 | J19: =J6/J4 -> 0.32965001 | K19: =K6/K4 -> 0.27042582 | ... X19: =X6/X4 -> 0.26 | Z19: NPV | AA19: =NPV(AA17,O14:FW14) -> 22136.361
C20: EBIT margin | D20: =D10/D4 -> 0.078158695 | E20: =E10/E4 -> 0.089433606 | F20: =F10/F4 -> 0.096207544 | G20: =G10/G4 -> 0.050383352 | H20: =H10/H4 -> 0.087281501 | I20: =I10/I4 -> 0.08747586 | J20: =J10/J4 -> 0.12210204 | K20: =K10/K4 -> 0.056313267 | ... X20: =X10/X4 -> 0.050283606 | Z20: S/O | AA20: 571.7
Z21: NPV/Share | AA21: =AA19/AA20 -> 38.720239
Z22: Opp/nedside | AA22: =(AA21-Modell!B4)/Modell!B4 -> 0.060828462
A23: Negativ 2 vekst og konstante marginer
A24: =AA42 -> 33.598567 | D24: FY 2015 | E24: FY 2016 | F24: FY 2017 | G24: FY 2018 | H24: FY 2019 | I24: FY 2020 | J24: FY 2021 | K24: FY 2022 | L24: FY 2023 | M24: FY 2024 | N24: FY 2025 | O24: FY 2026 | P24: FY 2027 | Q24: FY 2028 | R24: FY 2029 | S24: FY 2030 | T24: FY 2031 | U24: FY 2032 | V24: FY 2033 | W24: FY 2034 | X24: FY 2035
A25: =AA43 -> -0.079491319 | C25: Revenues | D25: 36170 | E25: 35982 | F25: 39394 | G25: 41085 | H25: 42277 | I25: 41943 | J25: 47059 | K25: 54037 | L25: 53261 | M25: 48352 | N25: 46614 | O25: =N25*0.98 -> 45681.72 | P25: =O25*0.98 -> 44768.086 | Q25: =P25*0.98 -> 43872.724 | R25: =Q25*0.98 -> 42995.269 | S25: =R25*0.98 -> 42135.364 | T25: =S25*0.98 -> 41292.657 | U25: =T25*0.98 -> 40466.804 | V25: =U25*0.98 -> 39657.468 | ... X25: =W25*0.98 -> 38087.032
C26: COGS | D26: -25996 | E26: -24886 | F26: -27922 | G26: -30583 | H26: -29748 | I26: -29367 | J26: -31546 | K26: -39424 | L26: -37136 | M26: -34053 | N26: -32514 | O26: =O25*-0.74 -> -33804.473 | P26: =P25*-0.74 -> -33128.383 | Q26: =Q25*-0.74 -> -32465.816 | R26: =R25*-0.74 -> -31816.499 | S26: =S25*-0.74 -> -31180.169 | T26: =T25*-0.74 -> -30556.566 | U26: =U25*-0.74 -> -29945.435 | V26: =V25*-0.74 -> -29346.526 | ... X26: =X25*-0.74 -> -28184.404
C27: Gross profit | D27: =SUM(D25:D26) -> 10174 | E27: =SUM(E25:E26) -> 11096 | F27: =SUM(F25:F26) -> 11472 | G27: =SUM(G25:G26) -> 10502 | H27: =SUM(H25:H26) -> 12529 | I27: =SUM(I25:I26) -> 12576 | J27: =SUM(J25:J26) -> 15513 | K27: =SUM(K25:K26) -> 14613 | ... X27: =SUM(X25:X26) -> 9902.6283
C28: Selling expenses | D28: -5833 | E28: -6168 | F28: -5870 | G28: -6473 | H28: -6985 | I28: -6596 | J28: -7152 | K28: -8770 | L28: -9034 | M28: -8587 | N28: -8116 | O28: =N28*0.85 -> -6898.6 | P28: =O28*0.98 -> -6760.628 | Q28: =P28*0.98 -> -6625.4154 | R28: =Q28*0.98 -> -6492.9071 | S28: =R28*0.98 -> -6363.049 | T28: =S28*0.98 -> -6235.788 | U28: =T28*0.98 -> -6111.0722 | V28: =U28*0.98 -> -5988.8508 | W28: =V28*0.98 -> -5869.0738 | X28: =W28*0.98 -> -5751.6923
C29: Administrative expenses | D29: -1532 | E29: -1707 | F29: -1879 | G29: -2014 | H29: -2051 | I29: -2335 | J29: -2704 | K29: -3001 | L29: -3211 | M29: -3275 | N29: -3074 | O29: =N29*0.87 -> -2674.38 | P29: =O29*0.98 -> -2620.8924 | Q29: =P29*0.98 -> -2568.4746 | R29: =Q29*0.98 -> -2517.1051 | S29: =R29*0.98 -> -2466.763 | T29: =S29*0.98 -> -2417.4277 | U29: =T29*0.98 -> -2369.0791 | V29: =U29*0.98 -> -2321.6976 | W29: =V29*0.98 -> -2275.2636 | X29: =W29*0.98 -> -2229.7583
C30: Other operating inc/ex | D30: =23-5 -> 18 | E30: -3 | F30: =68-1 -> 67 | G30: =63-8 -> 55 | H30: =203-6 -> 197 | I30: =26-2 -> 24 | J30: =112-23 -> 89 | K30: =212-11 -> 201 | L30: 0 | M30: 160 | N30: -11 | O30: =N30*0.87 -> -9.57 | P30: =O30*0.98 -> -9.3786 | Q30: =P30*0.98 -> -9.191028 | R30: =Q30*0.98 -> -9.0072074 | S30: =R30*0.98 -> -8.8270633 | T30: =S30*0.98 -> -8.650522 | U30: =T30*0.98 -> -8.4775116 | V30: =U30*0.98 -> -8.3079614 | W30: =V30*0.98 -> -8.1418021 | X30: =W30*0.98 -> -7.9789661
C31: Operating income | D31: =SUM(D27:D30) -> 2827 | E31: =SUM(E27:E30) -> 3218 | F31: =SUM(F27:F30) -> 3790 | G31: =SUM(G27:G30) -> 2070 | H31: =SUM(H27:H30) -> 3690 | I31: =SUM(I27:I30) -> 3669 | J31: =SUM(J27:J30) -> 5746 | K31: =SUM(K27:K30) -> 3043 | ... X31: =SUM(X27:X30) -> 1913.1987
C32: Financial items | D32: =44-388 -> -344 | E32: =29-451 -> -422 | F32: =20-520 -> -500 | G32: =72-581 -> -509 | H32: =18-586 -> -568 | I32: =38-377 -> -339 | J32: =42-294 -> -252 | K32: =38-499 -> -461 | L32: =75-1077 -> -1002 | M32: =86-950 -> -864 | N32: -750 | O32: 0 | P32: 0 | Q32: 0 | R32: 0 | S32: 0 | T32: 0 | U32: 0 | V32: 0 | W32: 0 | X32: 0
C33: PTP | D33: =SUM(D31:D32) -> 2483 | E33: =SUM(E31:E32) -> 2796 | F33: =SUM(F31:F32) -> 3290 | G33: =SUM(G31:G32) -> 1561 | H33: =SUM(H31:H32) -> 3122 | I33: =SUM(I31:I32) -> 3330 | J33: =SUM(J31:J32) -> 5494 | K33: =SUM(K31:K32) -> 2582 | ... X33: =SUM(X31:X32) -> 1913.1987
C34: Tax | D34: -595 | E34: -692 | F34: -630 | G34: -348 | H34: -594 | I34: -835 | J34: -1057 | K34: -649 | L34: -702 | M34: -408 | N34: -379 | O34: =O33*-0.2 -> -458.93944 | P34: =P33*-0.2 -> -449.76065 | Q34: =Q33*-0.2 -> -440.76544 | R34: =R33*-0.2 -> -431.95013 | S34: =S33*-0.2 -> -423.31113 | T34: =T33*-0.2 -> -414.8449 | U34: =U33*-0.2 -> -406.54801 | V34: =V33*-0.2 -> -398.41705 | ... X34: =X33*-0.2 -> -382.63973
C35: Net income | D35: =SUM(D33:D34) -> 1888 | E35: =SUM(E33:E34) -> 2104 | F35: =SUM(F33:F34) -> 2660 | G35: =SUM(G33:G34) -> 1213 | H35: =SUM(H33:H34) -> 2528 | I35: =SUM(I33:I34) -> 2495 | J35: =SUM(J33:J34) -> 4437 | K35: =SUM(K33:K34) -> 1933 | ... X35: =SUM(X33:X34) -> 1530.5589 | Y35: =X35*(1+$AA$39) -> 1515.2533 | Z35: =Y35*(1+$AA$39) -> 1500.1008 | AA35: =Z35*(1+$AA$39) -> 1485.0998 | AB35: =AA35*(1+$AA$39) -> 1470.2488 | AC35: =AB35*(1+$AA$39) -> 1455.5463 | AD35: =AC35*(1+$AA$39) -> 1440.9908 | AE35: =AD35*(1+$AA$39) -> 1426.5809 | AF35: =AE35*(1+$AA$39) -> 1412.3151 | ... FW35: =FV35*(1+$AA$39) -> 322.33333
C36: Shares | D36: 571.7 | E36: 571.7 | F36: 571.7 | G36: 571.7 | H36: 571.7 | I36: 571.7 | J36: 571.7 | K36: 571.7 | L36: 571.7 | M36: 571.7 | N36: 571.7 | O36: 571.7 | P36: 571.7 | Q36: 571.7 | R36: 571.7 | S36: 571.7 | T36: 571.7 | U36: 571.7 | V36: 571.7 | W36: 571.7 | X36: 571.7
C37: EPS | D37: =D35/D36 -> 3.3024313 | E37: =E35/E36 -> 3.6802519 | F37: =F35/F36 -> 4.6527899 | G37: =G35/G36 -> 2.1217422 | H37: =H35/H36 -> 4.4218996 | I37: =I35/I36 -> 4.364177 | J37: =J35/J36 -> 7.7610635 | K37: =K35/K36 -> 3.381144 | ... X37: =X35/X36 -> 2.6772064
Z38: Disocunt | AA38: 0.08
C39: Revenue y/y | E39: =(E25-D25)/D25 -> -0.0051976776 | F39: =(F25-E25)/E25 -> 0.09482519 | G39: =(G25-F25)/F25 -> 0.042925319 | H39: =(H25-G25)/G25 -> 0.029013022 | I39: =(I25-H25)/H25 -> -0.0079002767 | J39: =(J25-I25)/I25 -> 0.12197506 | K39: =(K25-J25)/J25 -> 0.14828194 | L39: =(L25-K25)/K25 -> -0.014360531 | ... X39: =(X25-W25)/W25 -> -0.02 | Z39: TV | AA39: -0.01
C40: Gross margin | D40: =D27/D25 -> 0.28128283 | E40: =E27/E25 -> 0.30837641 | F40: =F27/F25 -> 0.29121186 | G40: =G27/G25 -> 0.25561641 | H40: =H27/H25 -> 0.29635499 | I40: =I27/I25 -> 0.29983549 | J40: =J27/J25 -> 0.32965001 | K40: =K27/K25 -> 0.27042582 | ... X40: =X27/X25 -> 0.26 | Z40: NPV | AA40: =NPV(AA38,O35:FW35) -> 19208.301
C41: EBIT margin | D41: =D31/D25 -> 0.078158695 | E41: =E31/E25 -> 0.089433606 | F41: =F31/F25 -> 0.096207544 | G41: =G31/G25 -> 0.050383352 | H41: =H31/H25 -> 0.087281501 | I41: =I31/I25 -> 0.08747586 | J41: =J31/J25 -> 0.12210204 | K41: =K31/K25 -> 0.056313267 | ... X41: =X31/X25 -> 0.050232285 | Z41: S/O | AA41: 571.7
Z42: NPV/Share | AA42: =AA40/AA41 -> 33.598567
Z43: Opp/nedside | AA43: =(AA42-Modell!B4)/Modell!B4 -> -0.079491319
