Workbook

Sheet Info
A2: Produksjon | F2: Q425
B3: Egne fabrikker (in-house) | C3: Lokal trykkproduksjon
A4: Hvor | B4: Portugal, Bangladesh | C4: UK, Tyskland, Vietnam, Tyrkia, Hong Kong
A5: Produkter | B5: Woven + printed labels | C5: Kun printed labels
A6: Skala | B6: Stor, dedikerte fabrikker | C6: Mindre, tilknyttet salgskontor
A7: Fordel | B7: Full kontroll, bredde | C7: Nærhet til kunde, rask levering
A10: RIS = Labels with variable information such as barcodes, care labels and RFID
A11: Retail information solutions
A14: Investeringsplan og strategiske initiativ
A16: PRODUKSJON & KAPASITET
A17: Ny fabrikk Bangladesh | B17: ~MUSD 10. Nåværende full (MSEK 80). Ferdig H1 2027, dobler kapasitet
A18: Portugal oppgradering | B18: MSEK 10 investering, øke kapasitet og servicenivå
A19: LEAN-program | B19: Innføres på alle fabrikker, startet Portugal & Bangladesh
A20: In-house trend | B20: Andelen egen produksjon øker — bedre kontroll og marginer
A22: SALG & ORGANISASJON
A23: USA-ekspansjon | B23: 3 nye selgere, akselerere Nord-Amerika
A24: Nederland | B24: Nytt datterselskap, styrke Benelux
A25: CCO (ny rolle) | B25: Chief Commercial Officer — sentralisere global salgsstrategi
A27: DIGITALISERING & NYE PRODUKTER
A28: Nilörn:CONNECT | B28: QR/NFC i etiketter, koblet til digitalt system. Svarer på EUs Digital Product Passport (DPP)
A29: Packaging-satsing | B29: Ny Category Manager rekruttert. Premium emballasje + bærekraftige materialer
A30: RFID | B30: Identifisert som stort vekstområde 2025→2030
A31: Heat Transfer | B31: Vekstambisjon i radardiagram 2025→2030
A33: MARKED & KONSOLIDERING
A34: Bransjetrend | B34: Konsolidering — store kunder vil ha færre, sterkere leverandører
A35: Nilörns respons | B35: Global dekning, digital + compliance → posisjonert for organisk vekst og oppkjøp
A37: TRANSFORMASJON 2020→2025 (gjennomført)
A38: Styrket | B38: Sustainability/CSR, Digital Solutions, Global Deliveries, Packaging, Financial Strength
A39: Endret modell | B39: Fra desentralisert → integrert organisasjon med sentralisert sourcing
A41: STRATEGISK RETNING 2025→2030
A42: Størst vekstambisjon | B42: RFID, Digital solutions, Heat Transfer, Packaging
A43: Videre vekst | B43: Own production, Global deliveries
A44: Overordnet mål | B44: Full-service leverandør med digitale løsninger, ikke bare etiketter
A46: Press releases:

Sheet Modell
A3: Kapitalstruktur | C3: SEKm | D3: Q122 | E3: Q222 | F3: Q322 | G3: Q422 | H3: Q123 | I3: Q223 | J3: Q323 | K3: Q423 | L3: Q124 | M3: Q224 | N3: Q324 | O3: Q424 | P3: Q125 | Q3: Q225 | R3: Q325 | S3: Q425 | V3: FY 2017 | W3: FY 2018 | X3: FY 2019 | Y3: FY 2020 | Z3: FY 2021 | AA3: FY 2022 | AB3: FY 2023 | AC3: FY 2024 | AD3: FY 2025 | AE3: FY 2026 | AF3: FY 2027 | AG3: FY 2028 | AH3: FY 2029 | AI3: FY 2030 | AJ3: FY 2031 | AK3: FY 2032 | AL3: FY 2033 | AM3: FY 2034 | AN3: FY 2035
A4: Price | B4: 49.95 | C4: Revenue | D4: 242.338 | E4: 269.138 | F4: 232.024 | G4: 199.311 | H4: 221.27 | I4: 230.194 | J4: 214.651 | K4: 203.654 | L4: 242.338 | M4: 262 | N4: 208.429 | O4: 231.903 | P4: 258.569 | Q4: 237.285 | R4: 230.259 | S4: 219.001 | V4: 686.527 | W4: 738.447 | X4: 720.468 | Y4: 637.359 | Z4: 800.182 | AA4: 975.258 | AB4: 895.161 | AC4: 962.864 | AD4: 945 | AE4: =AD4*1.03 -> 973.35 | AF4: =AE4*1.05 -> 1022.0175 | AG4: =AF4*1.05 -> 1073.1184 | AH4: =AG4*1.05 -> 1126.7743 | AI4: =AH4*1.05 -> 1183.113 | AJ4: =AI4*1.05 -> 1242.2687 | AK4: =AJ4*1.05 -> 1304.3821 | AL4: =AK4*1.05 -> 1369.6012 | AM4: =AL4*1.05 -> 1438.0813 | AN4: =AM4*1.05 -> 1509.9853
A5: S/O | B5: 11.402 | C5: COGS | D5: -136.186 | E5: -150.846 | F5: -127.583 | G5: -111.678 | H5: -126.063 | I5: -134.423 | J5: -117.268 | K5: -112.308 | L5: -137.613 | M5: -146.565 | N5: -108.291 | O5: -124.682 | P5: -142.846 | Q5: -130.943 | R5: -121.359 | S5: -115.629 | V5: -364.6 | W5: -396.033 | X5: -407.623 | Y5: -346.109 | Z5: -424.174 | AA5: -526.292 | AB5: -490.062 | AC5: -517.152 | AD5: -511 | AE5: =AE4*-0.54 -> -525.609 | AF5: =AF4*-0.54 -> -551.88945 | AG5: =AG4*-0.54 -> -579.48392 | AH5: =AH4*-0.54 -> -608.45812 | AI5: =AI4*-0.54 -> -638.88102 | AJ5: =AJ4*-0.54 -> -670.82508 | AK5: =AK4*-0.54 -> -704.36633 | AL5: =AL4*-0.54 -> -739.58465 | ... AN5: =AN4*-0.54 -> -815.39207
A6: MC SEKm | B6: =B4*B5 -> 569.5299 | C6: Gross profit | D6: =SUM(D4:D5) -> 106.152 | E6: =SUM(E4:E5) -> 118.292 | F6: =SUM(F4:F5) -> 104.441 | G6: =SUM(G4:G5) -> 87.633 | H6: =SUM(H4:H5) -> 95.207 | I6: =SUM(I4:I5) -> 95.771 | J6: =SUM(J4:J5) -> 97.383 | K6: =SUM(K4:K5) -> 91.346 | ... S6: =SUM(S4:S5) -> 103.372 | V6: =SUM(V4:V5) -> 321.927 | W6: =SUM(W4:W5) -> 342.414 | X6: =SUM(X4:X5) -> 312.845 | Y6: =SUM(Y4:Y5) -> 291.25 | Z6: =SUM(Z4:Z5) -> 376.008 | AA6: =SUM(AA4:AA5) -> 448.966 | AB6: =SUM(AB4:AB5) -> 405.099 | AC6: =SUM(AC4:AC5) -> 445.712 | ... AN6: =SUM(AN4:AN5) -> 694.59325
A7: Cash SEKm | B7: =S35 -> 101.682 | C7: Other revenue | D7: 2.733 | E7: 7.208 | F7: 8.192 | G7: 14.314 | H7: 4.3 | I7: 8.217 | J7: 5.486 | K7: 7.388 | L7: 4 | M7: 3.345 | N7: 2.593 | O7: 8.191 | P7: 3 | Q7: 4.039 | R7: 4.527 | S7: 1.692 | V7: 0 | W7: 0 | X7: 0 | Y7: 0 | Z7: 0 | AA7: 0 | AB7: 0 | AC7: 0 | AD7: 13 | AE7: =AD7*1.04 -> 13.52 | AF7: =AE7*1.04 -> 14.0608 | AG7: =AF7*1.04 -> 14.623232 | AH7: =AG7*1.04 -> 15.208161 | AI7: =AH7*1.04 -> 15.816488 | AJ7: =AI7*1.04 -> 16.449147 | AK7: =AJ7*1.04 -> 17.107113 | AL7: =AK7*1.04 -> 17.791398 | ... AN7: =AM7*1.04 -> 19.243176
A8: Debt SEKm | B8: =(S39+S41) -> 64.373 | C8: Other external costs | D8: -15.136 | E8: -21.766 | F8: -16 | G8: -18.265 | H8: -19.184 | I8: -20.538 | J8: -19.149 | K8: -21.522 | L8: -19.515 | M8: -21.734 | N8: -21.43 | O8: -24 | P8: -21.91 | Q8: -22.65 | R8: -20.499 | S8: -26.561 | V8: -96.462 | W8: -99.346 | X8: -65.157 | Y8: -62.686 | Z8: -61.953 | AA8: -71.173 | AB8: -80.393 | AC8: -86.759 | AD8: -92 | AE8: =AD8*1.02 -> -93.84 | AF8: =AE8*1.045 -> -98.0628 | AG8: =AF8*1.045 -> -102.47563 | AH8: =AG8*1.045 -> -107.08703 | AI8: =AH8*1.045 -> -111.90595 | AJ8: =AI8*1.045 -> -116.94171 | AK8: =AJ8*1.045 -> -122.20409 | AL8: =AK8*1.045 -> -127.70327 | AM8: =AL8*1.045 -> -133.44992 | AN8: =AM8*1.045 -> -139.45517
A9: EV SEKm | B9: =B6-B7+B8 -> 532.2209 | C9: Personnel costs | D9: -45.767 | E9: -48.717 | F9: -47.073 | G9: -52.746 | H9: -53.642 | I9: -54.396 | J9: -51.229 | K9: -55.677 | L9: -56.097 | M9: -59.279 | N9: -53.438 | O9: -57.905 | P9: -61 | Q9: -59.089 | R9: -55.772 | S9: -60.972 | V9: -133.311 | W9: -144.77 | X9: -153.753 | Y9: -146.6 | Z9: -163.876 | AA9: -194.303 | AB9: -214.944 | AC9: -226.719 | AD9: -237 | AE9: =AD9*1.02 -> -241.74 | AF9: =AE9*1.045 -> -252.6183 | AG9: =AF9*1.045 -> -263.98612 | AH9: =AG9*1.045 -> -275.8655 | AI9: =AH9*1.045 -> -288.27945 | AJ9: =AI9*1.045 -> -301.25202 | AK9: =AJ9*1.045 -> -314.80836 | AL9: =AK9*1.045 -> -328.97474 | AM9: =AL9*1.045 -> -343.7786 | AN9: =AM9*1.045 -> -359.24864
C10: D/A/I | D10: -6.913 | E10: -7.7 | F10: -8.384 | G10: -6.876 | H10: -7.34 | I10: -7.781 | J10: -8.456 | K10: -7.618 | L10: -8.28 | M10: -8.22 | N10: -8.62 | O10: -9.44 | P10: -8.499 | Q10: -8.331 | R10: -8.252 | S10: -6.979 | V10: -6.287 | W10: -8.362 | X10: -24.6 | Y10: -25.854 | Z10: -25.941 | AA10: -29.921 | AB10: -31.195 | AC10: -34.566 | AD10: -32 | AE10: =AD10*1.02 -> -32.64 | AF10: =AE10*1.045 -> -34.1088 | AG10: =AF10*1.045 -> -35.643696 | AH10: =AG10*1.045 -> -37.247662 | AI10: =AH10*1.045 -> -38.923807 | AJ10: =AI10*1.045 -> -40.675378 | AK10: =AJ10*1.045 -> -42.50577 | AL10: =AK10*1.045 -> -44.41853 | AM10: =AL10*1.045 -> -46.417364 | AN10: =AM10*1.045 -> -48.506145
C11: Other opex | D11: -0.889 | E11: -2.384 | F11: -4.121 | G11: -9.76 | H11: -2.417 | I11: -5.2 | J11: -3.224 | K11: -4.72 | L11: -2.433 | M11: -3.915 | N11: -3.959 | O11: -4.5 | P11: -4.33 | Q11: -4.3 | R11: -2.608 | S11: -2.446 | V11: -3.458 | W11: -4.66 | X11: -3.162 | Y11: -5.3 | Z11: -4.691 | AA11: -17.154 | AB11: -15.57 | AC11: -14.816 | AD11: -14 | AE11: =AD11*1.02 -> -14.28 | AF11: =AE11*1.045 -> -14.9226 | AG11: =AF11*1.045 -> -15.594117 | AH11: =AG11*1.045 -> -16.295852 | AI11: =AH11*1.045 -> -17.029166 | AJ11: =AI11*1.045 -> -17.795478 | AK11: =AJ11*1.045 -> -18.596275 | AL11: =AK11*1.045 -> -19.433107 | AM11: =AL11*1.045 -> -20.307597 | AN11: =AM11*1.045 -> -21.221439
C12: Operating profit (EBIT) | D12: =SUM(D6:D11) -> 40.18 | E12: =SUM(E6:E11) -> 44.933 | F12: =SUM(F6:F11) -> 37.055 | G12: =SUM(G6:G11) -> 14.3 | H12: =SUM(H6:H11) -> 16.924 | I12: =SUM(I6:I11) -> 16.073 | J12: =SUM(J6:J11) -> 20.811 | K12: =SUM(K6:K11) -> 9.197 | ... S12: =SUM(S6:S11) -> 8.106 | V12: =SUM(V6:V11) -> 82.409 | W12: =SUM(W6:W11) -> 85.276 | X12: =SUM(X6:X11) -> 66.173 | Y12: =SUM(Y6:Y11) -> 50.81 | Z12: =SUM(Z6:Z11) -> 119.547 | AA12: =SUM(AA6:AA11) -> 136.415 | AB12: =SUM(AB6:AB11) -> 62.997 | AC12: =SUM(AC6:AC11) -> 82.852 | ... AN12: =SUM(AN6:AN11) -> 145.40503
C13: Net financial items | D13: -0.957 | E13: -0.606 | F13: -0.417 | G13: -2 | H13: -2.475 | I13: -3.4 | J13: -2.554 | K13: -1.99 | L13: -1.267 | M13: -0.872 | N13: -2.27 | O13: -0.409 | P13: -2 | Q13: -1.826 | R13: -1.214 | S13: -1 | V13: -0.162 | W13: -1.391 | X13: -3 | Y13: -3.698 | Z13: -3.343 | AA13: -4 | AB13: =2.325-12.758 -> -10.433 | AC13: =3.834-8.652 -> -4.818 | AD13: -6 | AE13: =AD13*1.03 -> -6.18 | AF13: =AE13*1.03 -> -6.3654 | AG13: =AF13*1.03 -> -6.556362 | AH13: =AG13*1.03 -> -6.7530529 | AI13: =AH13*1.03 -> -6.9556444 | AJ13: =AI13*1.03 -> -7.1643138 | AK13: =AJ13*1.03 -> -7.3792432 | AL13: =AK13*1.03 -> -7.6006205 | ... AN13: =AM13*1.03 -> -8.0634983
C14: PTP | D14: =SUM(D12:D13) -> 39.223 | E14: =SUM(E12:E13) -> 44.327 | F14: =SUM(F12:F13) -> 36.638 | G14: =SUM(G12:G13) -> 12.3 | H14: =SUM(H12:H13) -> 14.449 | I14: =SUM(I12:I13) -> 12.673 | J14: =SUM(J12:J13) -> 18.257 | K14: =SUM(K12:K13) -> 7.207 | ... S14: =SUM(S12:S13) -> 7.106 | V14: =SUM(V12:V13) -> 82.247 | W14: =SUM(W12:W13) -> 83.885 | X14: =SUM(X12:X13) -> 63.173 | Y14: =SUM(Y12:Y13) -> 47.112 | Z14: =SUM(Z12:Z13) -> 116.204 | AA14: =SUM(AA12:AA13) -> 132.415 | AB14: =SUM(AB12:AB13) -> 52.564 | AC14: =SUM(AC12:AC13) -> 78.034 | ... AN14: =SUM(AN12:AN13) -> 137.34153
C15: Tax | D15: -11.278 | E15: -8.3 | F15: -8.661 | G15: -3.1789 | H15: -3.357 | I15: -3.457 | J15: -4.88 | K15: -1.482 | L15: -4.5 | M15: -6 | N15: -3.264 | O15: -5.3 | P15: -5.1 | Q15: -3.388 | R15: -6.167 | S15: -2 | V15: -17.219 | W15: -13.122 | X15: -15.84 | Y15: -13.551 | Z15: -28.766 | AA15: -31.417 | AB15: -13.176 | AC15: -19 | AD15: -17 | AE15: =AE14*-0.2 -> -14.5162 | AF15: =AF14*-0.2 -> -15.62219 | AG15: =AG14*-0.2 -> -16.800352 | AH15: =AH14*-0.2 -> -18.055048 | AI15: =AI14*-0.2 -> -19.390892 | AJ15: =AJ14*-0.2 -> -20.812765 | AK15: =AK14*-0.2 -> -22.325827 | AL15: =AL14*-0.2 -> -23.935535 | ... AN15: =AN14*-0.2 -> -27.468307
C16: Net income | D16: =SUM(D14:D15) -> 27.945 | E16: =SUM(E14:E15) -> 36.027 | F16: =SUM(F14:F15) -> 27.977 | G16: =SUM(G14:G15) -> 9.1211 | H16: =SUM(H14:H15) -> 11.092 | I16: =SUM(I14:I15) -> 9.216 | J16: =SUM(J14:J15) -> 13.377 | K16: =SUM(K14:K15) -> 5.725 | ... S16: =SUM(S14:S15) -> 5.106 | V16: =SUM(V14:V15) -> 65.028 | W16: =SUM(W14:W15) -> 70.763 | X16: =SUM(X14:X15) -> 47.333 | Y16: =SUM(Y14:Y15) -> 33.561 | Z16: =SUM(Z14:Z15) -> 87.438 | AA16: =SUM(AA14:AA15) -> 100.998 | AB16: =SUM(AB14:AB15) -> 39.388 | AC16: =SUM(AC14:AC15) -> 59.034 | ... AN16: =SUM(AN14:AN15) -> 109.87323 | AO16: =AN16*(1+$AQ$20) -> 108.77449 | AP16: =AO16*(1+$AQ$20) -> 107.68675 | AQ16: =AP16*(1+$AQ$20) -> 106.60988 | AR16: =AQ16*(1+$AQ$20) -> 105.54378 | AS16: =AR16*(1+$AQ$20) -> 104.48835 | AT16: =AS16*(1+$AQ$20) -> 103.44346 | AU16: =AT16*(1+$AQ$20) -> 102.40903 | AV16: =AU16*(1+$AQ$20) -> 101.38494 | ... EG16: =EF16*(1+$AQ$20) -> 41.448208
C17: Share | D17: 11.402 | E17: 11.402 | F17: 11.402 | G17: 11.402 | H17: 11.402 | I17: 11.402 | J17: 11.402 | K17: 11.402 | L17: 11.402 | M17: 11.402 | N17: 11.402 | O17: 11.402 | P17: 11.402 | Q17: 11.402 | R17: 11.402 | S17: 11.402 | V17: 11.402 | W17: 11.402 | X17: 11.402 | Y17: 11.402 | Z17: 11.402 | AA17: 11.402 | AB17: 11.402 | AC17: 11.402 | AD17: 11.402 | AE17: 11.402 | AF17: 11.402 | AG17: 11.402 | AH17: 11.402 | AI17: 11.402 | AJ17: 11.402 | AK17: 11.402 | AL17: 11.402 | AM17: 11.402 | AN17: 11.402
C18: EPS | D18: =D16/D17 -> 2.4508858 | E18: =E16/E17 -> 3.1597088 | F18: =F16/F17 -> 2.4536923 | G18: =G16/G17 -> 0.79995615 | H18: =H16/H17 -> 0.97281179 | I18: =I16/I17 -> 0.80827925 | J18: =J16/J17 -> 1.1732152 | K18: =K16/K17 -> 0.50210489 | ... S18: =S16/S17 -> 0.44781617 | V18: =V16/V17 -> 5.70321 | W18: =W16/W17 -> 6.2061919 | X18: =X16/X17 -> 4.1512892 | Y18: =Y16/Y17 -> 2.943431 | Z18: =Z16/Z17 -> 7.6686546 | AA18: =AA16/AA17 -> 8.8579197 | AB18: =AB16/AB17 -> 3.4544817 | AC18: =AC16/AC17 -> 5.1775127 | ... AN18: =AN16/AN17 -> 9.6363117
AP19: Discount | AQ19: 0.08
C20: Revenue y/y | H20: =(H4-D4)/D4 -> -0.086936428 | I20: =(I4-E4)/E4 -> -0.144699 | J20: =(J4-F4)/F4 -> -0.074875875 | K20: =(K4-G4)/G4 -> 0.021790067 | L20: =(L4-H4)/H4 -> 0.095213992 | M20: =(M4-I4)/I4 -> 0.13817041 | N20: =(N4-J4)/J4 -> -0.028986588 | O20: =(O4-K4)/K4 -> 0.13871075 | ... S20: =(S4-O4)/O4 -> -0.05563533 | W20: =(W4-V4)/V4 -> 0.075627033 | X20: =(X4-W4)/W4 -> -0.024347042 | Y20: =(Y4-X4)/X4 -> -0.11535419 | Z20: =(Z4-Y4)/Y4 -> 0.25546513 | AA20: =(AA4-Z4)/Z4 -> 0.21879522 | AB20: =(AB4-AA4)/AA4 -> -0.082129037 | AC20: =(AC4-AB4)/AB4 -> 0.075632205 | AD20: =(AD4-AC4)/AC4 -> -0.018552984 | ... AN20: =(AN4-AM4)/AM4 -> 0.05 | AP20: TV | AQ20: -0.01
C21: Organic growth | D21: 0.29 | E21: 0.39 | F21: 0.02 | G21: -0.24 | H21: -0.13 | I21: -0.18 | J21: -0.1 | K21: 0.03 | L21: 0.1 | M21: 0.14 | N21: -0.03 | O21: 0.13 | P21: 0.07 | Q21: -0.01 | R21: 0.18 | S21: 0.06 | AC21: 0.09 | AP21: NPV | AQ21: =NPV(AQ19,AE16:EG16) -> 1084.7639
C22: Gross margin | D22: =D6/D4 -> 0.43803283 | E22: =E6/E4 -> 0.43952173 | F22: =F6/F4 -> 0.45013016 | G22: =G6/G4 -> 0.4396797 | H22: =H6/H4 -> 0.43027523 | I22: =I6/I4 -> 0.41604473 | J22: =J6/J4 -> 0.45368063 | K22: =K6/K4 -> 0.44853526 | ... S22: =S6/S4 -> 0.47201611 | V22: =V6/V4 -> 0.46892111 | W22: =W6/W4 -> 0.46369475 | X22: =X6/X4 -> 0.4342247 | Y22: =Y6/Y4 -> 0.45696381 | Z22: =Z6/Z4 -> 0.4699031 | AA22: =AA6/AA4 -> 0.46035613 | AB22: =AB6/AB4 -> 0.45254317 | AC22: =AC6/AC4 -> 0.46290234 | ... AN22: =AN6/AN4 -> 0.46 | AP22: S/O | AQ22: 11.402
C23: EBIT margin | D23: =D12/D4 -> 0.16580148 | E23: =E12/E4 -> 0.16695153 | F23: =F12/F4 -> 0.15970331 | G23: =G12/G4 -> 0.071747169 | H23: =H12/H4 -> 0.076485741 | I23: =I12/I4 -> 0.069823714 | J23: =J12/J4 -> 0.096952728 | K23: =K12/K4 -> 0.045159928 | ... S23: =S12/S4 -> 0.03701353 | V23: =V12/V4 -> 0.12003752 | W23: =W12/W4 -> 0.11548019 | X23: =X12/X4 -> 0.091847244 | Y23: =Y12/Y4 -> 0.079719593 | Z23: =Z12/Z4 -> 0.14939976 | AA23: =AA12/AA4 -> 0.13987581 | AB23: =AB12/AB4 -> 0.07037505 | AC23: =AC12/AC4 -> 0.086047458 | ... AN23: =AN12/AN4 -> 0.096295659 | AP23: NPV/Share | AQ23: =AQ21/AQ22 -> 95.138041
C24: ROCE | V24: 0.472 | W24: 0.418 | X24: 0.252 | Y24: 0.172 | Z24: 0.374 | AA24: 0.35 | AB24: 0.156 | AC24: 0.207 | AP24: Opp/nedside | AQ24: =(AQ23-B4)/B4 -> 0.90466549
C26: Order intake | D26: 283 | E26: 245 | F26: 230 | G26: 228 | H26: 223 | I26: 167 | J26: 182 | K26: 256 | L26: 233 | M26: 208 | N26: 256 | O26: 238 | P26: 267 | Q26: 205 | R26: 224 | S26: 251
C27: y/y | H27: =(H26-D26)/D26 -> -0.21201413 | I27: =(I26-E26)/E26 -> -0.31836735 | J27: =(J26-F26)/F26 -> -0.20869565 | K27: =(K26-G26)/G26 -> 0.12280702 | L27: =(L26-H26)/H26 -> 0.044843049 | M27: =(M26-I26)/I26 -> 0.24550898 | N27: =(N26-J26)/J26 -> 0.40659341 | O27: =(O26-K26)/K26 -> -0.0703125 | ... S27: =(S26-O26)/O26 -> 0.054621849
C29: Balanse SEKm
C30: intangible non-current assets | D30: 26.113 | E30: 26.595 | F30: 27.211 | G30: 38.619 | H30: 41.027 | I30: 43.841 | J30: 44.75 | K30: 47.989 | L30: 49.69 | M30: 51.417 | N30: 52 | O30: 53.207 | P30: 52.511 | Q30: 52.418 | R30: 52.953 | S30: 54.305
C31: Other non-current assets | D31: 129.577 | E31: 130.638 | F31: 130.855 | G31: 122.914 | H31: 119.709 | I31: 119.547 | J31: 126.788 | K31: 120.495 | L31: 121.307 | M31: 113.806 | N31: 123.141 | O31: 146.102 | P31: 135.087 | Q31: 131.1675 | R31: 125.545 | S31: 138.917
C32: Inventories | D32: 169.694 | E32: 206.031 | F32: 213.015 | G32: 212.13 | H32: 202.322 | I32: 192.418 | J32: 181.104 | K32: 165.813 | L32: 166.176 | M32: 156.057 | N32: 158.109 | O32: 170.552 | P32: 158.501 | Q32: 150.305 | R32: 148.393 | S32: 143.971
C33: Trade receivables | D33: 144.125 | E33: 148.406 | F33: 131.806 | G33: 99 | H33: 120.749 | I33: 120.355 | J33: 124.748 | K33: 106.363 | L33: 147.32 | M33: 132.64 | N33: 129.545 | O33: 85.471 | P33: 114.345 | Q33: 96.499 | R33: 110.036 | S33: 91.71
C34: Other current assets | D34: 27.628 | E34: 32.185 | F34: 37.465 | G34: 28.222 | H34: 38.044 | I34: 43.703 | J34: 40.192 | K34: 32.47 | L34: 39.959 | M34: 37.7 | N34: 34.912 | O34: 41.346 | P34: 42.987 | Q34: 44.897 | R34: 49.56 | S34: 45.167
C35: Cash | D35: 105.838 | E35: 112.505 | F35: 115.395 | G35: 113.085 | H35: 119.727 | I35: 98.443 | J35: 108.645 | K35: 104.714 | L35: 79.259 | M35: 87.594 | N35: 107.949 | O35: 100.814 | P35: 98.608 | Q35: 104.273 | R35: 118.711 | S35: 101.682
C36: Total assets | D36: =SUM(D30:D35) -> 602.975 | E36: =SUM(E30:E35) -> 656.36 | F36: =SUM(F30:F35) -> 655.747 | G36: =SUM(G30:G35) -> 613.97 | H36: =SUM(H30:H35) -> 641.578 | I36: =SUM(I30:I35) -> 618.307 | J36: =SUM(J30:J35) -> 626.227 | K36: =SUM(K30:K35) -> 577.844 | ... S36: =SUM(S30:S35) -> 575.752
C37: Equity | D37: 306.783 | E37: 297.088 | F37: 333.288 | G37: 333.219 | H37: 344.725 | I37: 300.015 | J37: 305.618 | K37: 294.822 | L37: 322.184 | M37: 323.123 | N37: 325.625 | O37: 350.389 | P37: 343.553 | Q37: 331.98 | R37: 346.054 | S37: 344.24
C38: Total equity | D38: =D37 -> 306.783 | E38: =E37 -> 297.088 | F38: =F37 -> 333.288 | G38: =G37 -> 333.219 | H38: =H37 -> 344.725 | I38: =I37 -> 300.015 | J38: =J37 -> 305.618 | K38: =K37 -> 294.822 | ... S38: =S37 -> 344.24
C39: Long term IB liabilties | D39: 41.85 | E39: 43.266 | F39: 43.602 | G39: 30.748 | H39: 29.158 | I39: 29.724 | J39: 39.175 | K39: 31 | L39: 6.478 | M39: 4.907 | N39: 9.278 | O39: 23.156 | P39: 39 | Q39: 16.799 | R39: 14.741 | S39: 13.656
C40: Long term non-IB liabilities | D40: 5.611 | E40: 5.648 | F40: 5.37 | G40: 7 | H40: 15.211 | I40: 6.963 | J40: 6.739 | K40: 6.379 | L40: 6.189 | M40: 5.956 | N40: 5.938 | O40: 6.653 | P40: 6.272 | Q40: 5.449 | R40: 5.371 | S40: 4.694
C41: Current IB liabilities | D41: 29.486 | E41: 64.609 | F41: 55.377 | G41: 64.872 | H41: 65.201 | I41: 110.907 | J41: 90.965 | K41: 80.478 | L41: 84.92 | M41: 79.098 | N41: 87.997 | O41: 58.408 | P41: 55.769 | Q41: 5.449 | R41: 72.91 | S41: 50.717
C42: Current non-IB liabiltiies | D42: 219.245 | E42: 245.749 | F42: 218.11 | G42: 178.122 | H42: 187.293 | I42: 170.69 | J42: 183.73 | K42: 165.156 | L42: 183.94 | M42: 166.13 | N42: 176.882 | O42: 158.886 | P42: 157.352 | Q42: 77.716 | R42: 166.122 | S42: 162.445
C43: Total debt | D43: =SUM(D39:D42) -> 296.192 | E43: =SUM(E39:E42) -> 359.272 | F43: =SUM(F39:F42) -> 322.459 | G43: =SUM(G39:G42) -> 280.742 | H43: =SUM(H39:H42) -> 296.863 | I43: =SUM(I39:I42) -> 318.284 | J43: =SUM(J39:J42) -> 320.609 | K43: =SUM(K39:K42) -> 283.013 | ... P43: =SUM(P39:P42) -> 258.393 | Q43: 147.613 | R43: =SUM(R39:R42) -> 259.144 | S43: =SUM(S39:S42) -> 231.512
C44: Total E/D | D44: =D38+D43 -> 602.975 | E44: =E38+E43 -> 656.36 | F44: =F38+F43 -> 655.747 | G44: =G38+G43 -> 613.961 | H44: =H38+H43 -> 641.588 | I44: =I38+I43 -> 618.299 | J44: =J38+J43 -> 626.227 | K44: =K38+K43 -> 577.835 | ... S44: =S38+S43 -> 575.752
C46: Cash flow SEKm
C47: Model OP | D47: =D12 -> 40.18 | E47: =E12 -> 44.933 | F47: =F12 -> 37.055 | G47: =G12 -> 14.3 | H47: =H12 -> 16.924 | I47: =I12 -> 16.073 | J47: =J12 -> 20.811 | K47: =K12 -> 9.197 | ... S47: =S12 -> 8.106 | V47: =V12 -> 82.409 | W47: =W12 -> 85.276 | X47: =X12 -> 66.173 | Y47: =Y12 -> 50.81 | Z47: =Z12 -> 119.547 | AA47: =AA12 -> 136.415 | AB47: =AB12 -> 62.997 | AC47: =AC12 -> 82.852 | AD47: =AD12 -> 72
C48: Reported OP | D48: 40 | E48: 45 | F48: 37 | G48: 14.3 | H48: 17 | I48: 16 | J48: 21 | K48: 9 | L48: 22.466 | M48: 26 | N48: 15 | O48: 20 | P48: 23 | Q48: 16 | R48: 26 | S48: 8.105 | V48: 82.409 | W48: 85 | X48: 66 | Y48: 51 | Z48: 120 | AA48: 136 | AB48: 63 | AC48: 83 | AD48: 73
C49: D/A/I | D49: 6.913 | E49: 7.78 | F49: 8.384 | G49: 6.87 | H49: 7.34 | I49: 7.781 | J49: 8.456 | K49: 7.618 | L49: 8.28 | M49: 8.22 | N49: 8.62 | O49: 9.446 | P49: 8.499 | Q49: 8.331 | R49: 8.252 | S49: 6.979 | V49: 6.287 | W49: 8.3662 | X49: 24.6 | Y49: 25.854 | Z49: 25.941 | AA49: 29.921 | AB49: 31.195 | AC49: 34.566 | AD49: 32
C50: Other non-cash items | D50: -4.357 | E50: -5.535 | F50: =-5.963-0.709 -> -6.672 | G50: -3.256 | H50: -6.171 | I50: -7.423 | J50: -5.816 | K50: -2.446 | L50: 0.075 | M50: -0.3 | N50: -1.843 | O50: 1.788 | P50: -1.629 | Q50: -1.587 | R50: -0.605 | S50: -1.69 | V50: 3 | W50: 1 | X50: -16.623 | Y50: -15.663 | Z50: -18.4 | AA50: -23.865 | AB50: -7 | AC50: -0.287 | AD50: -6
C51: Interest income | D51: 0.159 | E51: 0.302 | F51: 0.124 | G51: 0.16 | H51: 0.15 | I51: 0.405 | J51: 0.074 | K51: 1.696 | L51: 0.512 | M51: 0.842 | N51: 1.4 | O51: 1.078 | P51: 0.596 | Q51: 0.747 | R51: 0.52 | S51: 1.099 | V51: 1 | W51: 0.59 | X51: 0.734 | Y51: 0.606 | Z51: 0.654 | AA51: 0.745 | AB51: 2.325 | AC51: 3.834 | AD51: 3
C52: Interest expense | D52: -0.175 | E52: -0.222 | F52: -0.384 | G52: -0.694 | H52: -0.819 | I52: -1.118 | J52: -2 | K52: -1.776 | L52: -1.854 | M52: -1.413 | N52: -1.392 | O52: -1.637 | P52: -1 | Q52: -0.989 | R52: -1.29 | S52: -1.04 | V52: -1.218 | W52: -1.98 | X52: -1.596 | Y52: -2 | Z52: -0.754 | AA52: -1.326 | AB52: -6.288 | AC52: -6.288 | AD52: -4
C53: Paid taxes | D53: -3.784 | E53: -5.232 | F53: -4.657 | G53: -19.18 | H53: -0.437 | I53: -2.894 | J53: -1.948 | K53: -5.11 | L53: -5 | M53: -4.882 | N53: 1.269 | O53: -8.485 | P53: -4.55 | Q53: -4 | R53: -6.753 | S53: -2.055 | V53: -19.831 | W53: -15.373 | X53: -13.612 | Y53: -10.442 | Z53: -12.529 | AA53: -32.853 | AB53: -23.2 | AC53: -17.208 | AD53: -17
C54: WC | D54: =-23.736-29.11-6.996-6.448+20.393 -> -45.897 | E54: =-26.177+5.689-4.557+9.697-2.911 -> -18.259 | F54: =19.568-5-23.658-11.321 -> -20.411 | G54: =-5.544+26.584+9.243-18.837-9 -> 2.446 | H54: =8.587-21.807-9.822+13.141+2.7 -> -7.201 | I54: =12.95-0.708-5.659-1.225-30.468 -> -25.11 | J54: =6.62+-3.585+3.511+8.592+9.432 -> 24.57 | K54: =3.537+7.659+7.722+4.86+0.327 -> 24.105 | L54: =4.495-34.72-7.489-8+21.629 -> -24.085 | M54: =10.056+13.356+2.25+11.2-33.513 -> 3.349 | N54: =-7.181-2+2.788+4.961+8.714 -> 7.282 | O54: =-3.583+21.642-0.542-11.516+4.379 -> 10.38 | P54: =-2.818-25.956-4.28+9.43-5.33 -> -28.954 | Q54: =2.8+36.408-4.537+5.185-24.366 -> 15.49 | R54: =-0.476-3.587-11.151+23.8-4.681 -> 3.905 | S54: =0.152-6.358+10.255-2.556+17.568 -> 19.061 | V54: =-28.513-10.267+6.6+18.277+8.352 -> -5.551 | W54: =4.911-3.577-10.93+5.462-14 -> -18.134 | X54: =-8.326+27.252+11.315-18.733-7.989 -> 3.519 | Y54: =-0.293-12.993-0.752+24.176+15.474 -> 25.612 | Z54: =-37.684-35.278+0.692+32+4.5 -> -35.77 | AA54: =-55.423+22.731-7.475-39.246-2.89 -> -82.303 | AB54: =31.694-18.441-4.248+25.368-5.237 -> 29.136 | AC54: =3.787-1.723-2.984-3.5+1.209 -> -3.211 | AD54: 10
C55: CFFO | D55: =SUM(D48:D54) -> -7.141 | E55: =SUM(E48:E54) -> 23.834 | F55: =SUM(F48:F54) -> 13.384 | G55: =SUM(G48:G54) -> 0.646 | H55: =SUM(H48:H54) -> 9.862 | I55: =SUM(I48:I54) -> -12.359 | J55: =SUM(J48:J54) -> 44.336 | K55: =SUM(K48:K54) -> 33.087 | ... S55: =SUM(S48:S54) -> 30.459 | V55: =SUM(V48:V54) -> 66.096 | W55: =SUM(W48:W54) -> 59.4692 | X55: =SUM(X48:X54) -> 63.022 | Y55: =SUM(Y48:Y54) -> 74.967 | Z55: =SUM(Z48:Z54) -> 79.142 | AA55: =SUM(AA48:AA54) -> 26.319 | AB55: =SUM(AB48:AB54) -> 89.168 | AC55: =SUM(AC48:AC54) -> 94.406 | AD55: =SUM(AD48:AD54) -> 91
C57: Capex | D57: =-3 -> -3 | E57: =-1.226-1.874 -> -3.1 | F57: =-1.8-3.978 -> -5.778 | G57: =-1.784-2.629 -> -4.413 | H57: -5 | I57: =-5 -> -5 | J57: =-1.981-1.516 -> -3.497 | K57: =-4.384-1.217 -> -5.601 | L57: =-1.656-5.114 -> -6.77 | M57: =-1.724-0.931 -> -2.655 | N57: =-4.144-0.623 -> -4.767 | O57: =-2-6.392 -> -8.392 | P57: =-0.815-1.782 -> -2.597 | Q57: =-1.288-2.5 -> -3.788 | R57: =-1.181-2.702 -> -3.883 | S57: =-1.359-18.072 -> -19.431 | V57: -22 | W57: -20 | X57: =-6.491-43.629 -> -50.12 | Y57: =-5.398-5.2 -> -10.598 | Z57: =-4.719-6.122 -> -10.841 | AA57: =-6-10.572+6.29 -> -10.282 | AB57: =-12.113-7 -> -19.113 | AC57: =-9.626-13 -> -22.626 | AD57: -30
C58: Change in long-term receivables | D58: 0 | E58: -0.509 | F58: =1.1-0.776 -> 0.324 | G58: 8 | H58: 0 | I58: 0 | J58: 0 | K58: 1.52 | L58: -0.255 | M58: 0.088 | N58: -1.438 | O58: 2.072 | P58: 0.293 | Q58: 0.362 | R58: 0.439 | S58: -1.58 | V58: 0 | W58: -8.1 | X58: -1.3 | Y58: 0.6 | Z58: -0.899 | AA58: 2 | AB58: 1.431 | AC58: 0.469 | AD58: 0
C59: CFFI | D59: =SUM(D57:D58) -> -3 | E59: =SUM(E57:E58) -> -3.609 | F59: =SUM(F57:F58) -> -5.454 | G59: =SUM(G57:G58) -> 3.587 | H59: =SUM(H57:H58) -> -5 | I59: =SUM(I57:I58) -> -5 | J59: =SUM(J57:J58) -> -3.497 | K59: =SUM(K57:K58) -> -4.081 | ... S59: =SUM(S57:S58) -> -21.011 | V59: =SUM(V57:V58) -> -22 | W59: =SUM(W57:W58) -> -28.1 | X59: =SUM(X57:X58) -> -51.42 | Y59: =SUM(Y57:Y58) -> -9.998 | Z59: =SUM(Z57:Z58) -> -11.74 | AA59: =SUM(AA57:AA58) -> -8.282 | AB59: =SUM(AB57:AB58) -> -17.682 | AC59: =SUM(AC57:AC58) -> -22.157 | AD59: =SUM(AD57:AD58) -> -30
C61: Amortization of IB debt | D61: -0.894 | E61: 37.664 | F61: -6.447 | G61: 3.725 | H61: 2.659 | I61: 50.458 | J61: -21.118 | K61: -18.329 | L61: -16 | M61: -2.911 | N61: 5.821 | O61: -32.636 | P61: 17.891 | Q61: 2.133 | R61: -3.542 | S61: -21.982 | V61: 10.177 | W61: 5.5 | X61: 26.91 | Y61: -24.32 | Z61: 0.861 | AA61: 33.816 | AB61: =17.824-3.51 -> 14.314 | AC61: -45.5 | AD61: -6
C62: Amortization of lease | D62: 0 | E62: 0 | F62: 0 | G62: -4 | H62: 0 | I62: 0 | J62: 0 | K62: -4.7 | L62: 0 | M62: -4.987 | N62: -5.286 | O62: -6.844 | P62: 0 | Q62: -4.858 | R62: -4.754 | S62: -4.335 | V62: 0 | W62: 0 | X62: 0 | Y62: 0 | Z62: 0 | AA62: 0 | AB62: -19.557 | AC62: -22.401 | AD62: -14
C63: Dividend | D63: 0 | E63: -57 | F63: 0 | G63: 0 | H63: 0 | I63: -57 | J63: -0.682 | K63: 0 | L63: 0 | M63: -11.4 | N63: 0 | O63: 0 | P63: 0 | Q63: -17 | R63: -0.487 | S63: 0 | V63: -41.047 | W63: -45.606 | X63: -45 | Y63: 0 | Z63: -22.806 | AA63: -57 | AB63: -57.692 | AC63: -11.4 | AD63: -17
C64: CFFF | D64: =SUM(D61:D63) -> -0.894 | E64: =SUM(E61:E63) -> -19.336 | F64: =SUM(F61:F63) -> -6.447 | G64: =SUM(G61:G63) -> -0.275 | H64: =SUM(H61:H63) -> 2.659 | I64: =SUM(I61:I63) -> -6.542 | J64: =SUM(J61:J63) -> -21.8 | K64: =SUM(K61:K63) -> -23.029 | ... S64: =SUM(S61:S63) -> -26.317 | V64: =SUM(V61:V63) -> -30.87 | W64: =SUM(W61:W63) -> -40.106 | X64: =SUM(X61:X63) -> -18.09 | Y64: =SUM(Y61:Y63) -> -24.32 | Z64: =SUM(Z61:Z63) -> -21.945 | AA64: =SUM(AA61:AA63) -> -23.184 | AB64: =SUM(AB61:AB63) -> -62.935 | AC64: =SUM(AC61:AC63) -> -79.301 | AD64: =SUM(AD61:AD63) -> -37
C66: FX | E66: 5.935 | F66: 1.484 | G66: -6.6 | H66: -1 | I66: 3 | J66: -8.666 | K66: -10 | L66: 2.815 | M66: -1.26 | N66: -4.596 | O66: 6.723 | P66: -8.65 | Q66: -5 | R66: -3.821 | S66: -0.16 | V66: -3 | W66: 1.646 | X66: 1.2 | Y66: -6.438 | Z66: 4.951 | AA66: 1.547 | AB66: -16.8 | AC66: 3.682 | AD66: -18
C68: CIC | D68: =D55+D59+D64+D66 -> -11.035 | E68: =E55+E59+E64+E66 -> 6.824 | F68: =F55+F59+F64+F66 -> 2.967 | G68: =G55+G59+G64+G66 -> -2.642 | H68: =H55+H59+H64+H66 -> 6.521 | I68: =I55+I59+I64+I66 -> -20.901 | J68: =J55+J59+J64+J66 -> 10.373 | K68: =K55+K59+K64+K66 -> -4.023 | ... S68: =S55+S59+S64+S66 -> -17.029 | V68: =V55+V59+V64+V66 -> 10.226 | W68: =W55+W59+W64+W66 -> -7.0908 | X68: =X55+X59+X64+X66 -> -5.288 | Y68: =Y55+Y59+Y64+Y66 -> 34.211 | Z68: =Z55+Z59+Z64+Z66 -> 50.408 | AA68: =AA55+AA59+AA64+AA66 -> -3.6 | AB68: =AB55+AB59+AB64+AB66 -> -8.249 | AC68: =AC55+AC59+AC64+AC66 -> -3.37 | AD68: =AD55+AD59+AD64+AD66 -> 6
C70: FCF | D70: =D55+D57 -> -10.141 | E70: =E55+E57 -> 20.734 | F70: =F55+F57 -> 7.606 | G70: =G55+G57 -> -3.767 | H70: =H55+H57 -> 4.862 | I70: =I55+I57 -> -17.359 | J70: =J55+J57 -> 40.839 | K70: =K55+K57 -> 27.486 | ... S70: =S55+S57 -> 11.028 | V70: =V55+V57 -> 44.096 | W70: =W55+W57 -> 39.4692 | X70: =X55+X57 -> 12.902 | Y70: =Y55+Y57 -> 64.369 | Z70: =Z55+Z57 -> 68.301 | AA70: =AA55+AA57 -> 16.037 | AB70: =AB55+AB57 -> 70.055 | AC70: =AC55+AC57 -> 71.78 | AD70: =AD55+AD57 -> 61

Sheet Region
B5: SEKm | C5: Q122 | D5: Q222 | E5: Q322 | F5: Q422 | G5: 2022 | H5: Q123 | I5: Q223 | J5: Q323 | K5: Q423 | L5: 2023 | M5: Q124 | N5: Q224 | O5: Q324 | P5: Q424 | Q5: 2024 | R5: Q125 | S5: Q225 | T5: Q325 | U5: Q425 | V5: 2025 | W5: Q126 | X5: Q226 | Y5: Q326 | Z5: Q426 | AA5: 2026
B6: Sweden
B7: Revenue | C7: 11.624 | D7: 15.861 | E7: 10.29 | F7: 14.586 | G7: =SUM(C7:F7) -> 52.361 | H7: 9.859 | I7: 10.489 | J7: 11.151 | K7: 11 | L7: =SUM(H7:K7) -> 42.499 | M7: 8.32 | N7: 11.024 | O7: 6.344 | P7: 12.419 | Q7: =SUM(M7:P7) -> 38.107 | R7: 9.637 | S7: 14.546 | T7: 8.976 | U7: 14.823 | V7: =SUM(R7:U7) -> 47.982 | AA7: =SUM(W7:Z7) -> 0
B8: y/y | H8: =(H7-C7)/C7 -> -0.15184102 | I8: =(I7-D7)/D7 -> -0.33869239 | J8: =(J7-E7)/E7 -> 0.083673469 | K8: =(K7-F7)/F7 -> -0.24585219 | L8: =(L7-G7)/G7 -> -0.18834629 | M8: =(M7-H7)/H7 -> -0.15610102 | N8: =(N7-I7)/I7 -> 0.051005816 | O8: =(O7-J7)/J7 -> -0.43108241 | ... AA8: =(AA7-V7)/V7 -> -1
B9: Depreciation | C9: 0 | D9: 0 | E9: 0 | F9: 0 | G9: =SUM(C9:F9) -> 0 | H9: 0 | I9: 0 | J9: 0 | K9: 0 | L9: =SUM(H9:K9) -> 0 | M9: 0 | N9: 0 | O9: 0 | P9: -0.8 | Q9: =SUM(M9:P9) -> -0.8 | R9: 0 | S9: 0 | T9: 0 | U9: -0.535 | V9: =SUM(R9:U9) -> -0.535 | AA9: =SUM(W9:Z9) -> 0
B10: EBIT | C10: 4.619 | D10: 4.998 | E10: 3.469 | F10: 0.516 | G10: =SUM(C10:F10) -> 13.602 | H10: 2.103 | I10: 1.933 | J10: 2.366 | K10: -0.316 | L10: =SUM(H10:K10) -> 6.086 | M10: 0.618 | N10: 0.808 | O10: 0.878 | P10: 2.628 | Q10: =SUM(M10:P10) -> 4.932 | R10: 1.791 | S10: 2.317 | T10: -0.119 | U10: -0.76 | V10: =SUM(R10:U10) -> 3.229 | AA10: =SUM(W10:Z10) -> 0
B11: EBIT margin | C11: =C10/C7 -> 0.39736752 | D11: =D10/D7 -> 0.31511254 | E11: =E10/E7 -> 0.33712342 | F11: =F10/F7 -> 0.035376388 | G11: =G10/G7 -> 0.2597735 | H11: =H10/H7 -> 0.21330764 | I11: =I10/I7 -> 0.1842883 | J11: =J10/J7 -> 0.21217828 | ... AA11: =AA10/AA7 -> #DIV/0!
B12: Europe
B13: Revenue | C13: 87.101 | D13: 94.484 | E13: 71.355 | F13: 74.951 | G13: =SUM(C13:F13) -> 327.891 | H13: 81.709 | I13: 114.918 | J13: 82.817 | K13: 77.32 | L13: =SUM(H13:K13) -> 356.764 | M13: 104.393 | N13: 103.454 | O13: 66.647 | P13: 74.363 | Q13: =SUM(M13:P13) -> 348.857 | R13: 89.418 | S13: 88.909 | T13: 72.471 | U13: 68.812 | V13: =SUM(R13:U13) -> 319.61 | AA13: =SUM(W13:Z13) -> 0
B14: y/y | H14: =(H13-C13)/C13 -> -0.061905145 | I14: =(I13-D13)/D13 -> 0.21626942 | J14: =(J13-E13)/E13 -> 0.16063345 | K14: =(K13-F13)/F13 -> 0.031607317 | L14: =(L13-G13)/G13 -> 0.088056702 | M14: =(M13-H13)/H13 -> 0.27761936 | N14: =(N13-I13)/I13 -> -0.099758088 | O14: =(O13-J13)/J13 -> -0.19524977 | ... AA14: =(AA13-V13)/V13 -> -1
B15: Depreciation | C15: 0 | D15: 0 | E15: 0 | F15: 0 | G15: =SUM(C15:F15) -> 0 | H15: 0 | I15: 0 | J15: 0 | K15: 0 | L15: =SUM(H15:K15) -> 0 | M15: 0 | N15: 0 | O15: 0 | P15: -2.581 | Q15: =SUM(M15:P15) -> -2.581 | R15: 0 | S15: 0 | T15: 0 | U15: -2.812 | V15: =SUM(R15:U15) -> -2.812 | AA15: =SUM(W15:Z15) -> 0
B16: EBIT | C16: 16.92 | D16: 16.214 | E16: 11.753 | F16: 7 | G16: =SUM(C16:F16) -> 51.887 | H16: 8.124 | I16: 12.564 | J16: 8.166 | K16: -5 | L16: =SUM(H16:K16) -> 23.854 | M16: 11.928 | N16: 12.366 | O16: 2.15 | P16: 0.611 | Q16: =SUM(M16:P16) -> 27.055 | R16: 6.445 | S16: 9.447 | T16: 9.94 | U16: -9.938 | V16: =SUM(R16:U16) -> 15.894 | AA16: =SUM(W16:Z16) -> 0
B17: EBIT margin | C17: =C16/C13 -> 0.19425724 | D17: =D16/D13 -> 0.17160577 | E17: =E16/E13 -> 0.16471165 | F17: =F16/F13 -> 0.093394351 | G17: =G16/G13 -> 0.15824466 | H17: =H16/H13 -> 0.099426012 | I17: =I16/I13 -> 0.10933013 | J17: =J16/J13 -> 0.098602944 | ... AA17: =AA16/AA13 -> #DIV/0!
B18: Asia
B19: Revenue | C19: 143.613 | D19: 158.793 | E19: 150.379 | F19: 109.774 | G19: =SUM(C19:F19) -> 562.559 | H19: 129.702 | I19: 104.787 | J19: 120.682 | K19: 115.3 | L19: =SUM(H19:K19) -> 470.471 | M19: 129.625 | N19: 147.522 | O19: 135.438 | P19: 145.121 | Q19: =SUM(M19:P19) -> 557.706 | R19: 159.514 | S19: 133.83 | T19: 148.812 | U19: 135.367 | V19: =SUM(R19:U19) -> 577.523 | AA19: =SUM(W19:Z19) -> 0
B20: y/y | H20: =(H19-C19)/C19 -> -0.09686449 | I20: =(I19-D19)/D19 -> -0.34010315 | J20: =(J19-E19)/E19 -> -0.19748103 | K20: =(K19-F19)/F19 -> 0.050339789 | L20: =(L19-G19)/G19 -> -0.16369483 | M20: =(M19-H19)/H19 -> -0.00059366856 | N20: =(N19-I19)/I19 -> 0.40782731 | O20: =(O19-J19)/J19 -> 0.12227176 | ... AA20: =(AA19-V19)/V19 -> -1
B21: Depreciation | C21: 0 | D21: 0 | E21: 0 | F21: 0 | G21: =SUM(C21:F21) -> 0 | H21: 0 | I21: 0 | J21: 0 | K21: 0 | L21: =SUM(H21:K21) -> 0 | M21: 0 | N21: 0 | O21: 0 | P21: -6 | Q21: =SUM(M21:P21) -> -6 | R21: 0 | S21: 0 | T21: 0 | U21: -3.632 | V21: =SUM(R21:U21) -> -3.632 | AA21: =SUM(W21:Z21) -> 0
B22: EBIT | C22: 19.755 | D22: 24.731 | E22: 21.261 | F22: 7 | G22: =SUM(C22:F22) -> 72.747 | H22: 8.488 | I22: 2.404 | J22: 9.637 | K22: 14.72 | L22: =SUM(H22:K22) -> 35.249 | M22: 10.406 | N22: 13.962 | O22: 13.417 | P22: 17.397 | Q22: =SUM(M22:P22) -> 55.182 | R22: 16.214 | S22: 7.212 | T22: 13.309 | U22: 20.488 | V22: =SUM(R22:U22) -> 57.223 | AA22: =SUM(W22:Z22) -> 0
B23: EBIT margin | C23: =C22/C19 -> 0.13755718 | D23: =D22/D19 -> 0.15574364 | E23: =E22/E19 -> 0.14138277 | F23: =F22/F19 -> 0.063767377 | G23: =G22/G19 -> 0.12931444 | H23: =H22/H19 -> 0.065442322 | I23: =I22/I19 -> 0.022941777 | J23: =J22/J19 -> 0.079854494 | ... AA23: =AA22/AA19 -> #DIV/0!

Sheet SOTP
B3: SEKm | C3: EBIT 26E | D3: EV/EBIT | E3: Value | F3: SEK/Share
B4: Sweden | C4: 4 | D4: 8.5 | E4: =C4*D4 -> 34 | F4: =E4/Modell!$B$5 -> 2.981933
B5: Europe | C5: 20 | D5: 6.5 | E5: =C5*D5 -> 130 | F5: =E5/Modell!$B$5 -> 11.401509
B6: Asia | C6: 60 | D6: 9 | E6: =C6*D6 -> 540 | F6: =E6/Modell!$B$5 -> 47.360112
B7: Enterprise value | E7: =SUM(E4:E6) -> 704 | F7: =SUM(F4:F6) -> 61.743554
B9: Cash | E9: =Modell!B7 -> 101.682 | F9: =E9/Modell!$B$5 -> 8.9179091
B10: Debt | E10: =Modell!B8 -> 64.373 | F10: =-E10/Modell!$B$5 -> -5.6457639
B12: Equity value | F12: =SUM(F7:F10) -> 65.015699
A36: Sweden | B36: 2.981933
A37: Europe | B37: 12.278548
A38: Asia | B38: 47.360112
A39: Enterprise value | B39: 62.620593
A41: Cash | B41: 8.9179091
A42: Debt | B42: -5.6457639
A44: Equity value | B44: 65.892738

Sheet Nøkkeltall
D4: 2026 | E4: 2027 | F4: 2028
C5: EV/EBIT | D5: =Modell!$B$9/Modell!AE12 -> 6.7574167 | E5: =Modell!$B$9/Modell!AF12 -> 6.3002355 | F5: =Modell!$B$9/Modell!AG12 -> 5.8771194
C6: P/E | D6: =Modell!$B$4/Modell!AE18 -> 9.8085225 | E6: =Modell!$B$4/Modell!AF18 -> 9.1141175 | F6: =Modell!$B$4/Modell!AG18 -> 8.4749698

Sheet Nedsideberegning
A3: Nedside | D3: FY 2015 | E3: FY 2016 | F3: FY 2017 | G3: FY 2018 | H3: FY 2019 | I3: FY 2020 | J3: FY 2021 | K3: FY 2022 | L3: FY 2023 | M3: FY 2024 | N3: FY 2025 | O3: FY 2026 | P3: FY 2027 | Q3: FY 2028 | R3: FY 2029 | S3: FY 2030 | T3: FY 2031 | U3: FY 2032 | V3: FY 2033 | W3: FY 2034 | X3: FY 2035
A4: Nullvekst og flate marginer | C4: Revenue | H4: 720.468 | I4: 637.359 | J4: 800.182 | K4: 975.258 | L4: 895.161 | M4: 962.864 | N4: 945 | O4: =N4 -> 945 | P4: =O4 -> 945 | Q4: =P4 -> 945 | R4: =Q4 -> 945 | S4: =R4 -> 945 | T4: =S4 -> 945 | U4: =T4 -> 945 | V4: =U4 -> 945 | ... X4: =W4 -> 945
A5: =AA23 -> 50.052904 | C5: COGS | H5: -407.623 | I5: -346.109 | J5: -424.174 | K5: -526.292 | L5: -490.062 | M5: -517.152 | N5: -511 | O5: =O4*-0.56 -> -529.2 | P5: =P4*-0.56 -> -529.2 | Q5: =Q4*-0.56 -> -529.2 | R5: =R4*-0.56 -> -529.2 | S5: =S4*-0.56 -> -529.2 | T5: =T4*-0.56 -> -529.2 | U5: =U4*-0.56 -> -529.2 | V5: =V4*-0.56 -> -529.2 | ... X5: =X4*-0.56 -> -529.2
A6: =AA24 -> 0.0020601461 | C6: Gross profit | H6: =SUM(H4:H5) -> 312.845 | I6: =SUM(I4:I5) -> 291.25 | J6: =SUM(J4:J5) -> 376.008 | K6: =SUM(K4:K5) -> 448.966 | L6: =SUM(L4:L5) -> 405.099 | M6: =SUM(M4:M5) -> 445.712 | N6: =SUM(N4:N5) -> 434 | O6: =SUM(O4:O5) -> 415.8 | ... X6: =SUM(X4:X5) -> 415.8
C7: Other revenue | H7: 0 | I7: 0 | J7: 0 | K7: 0 | L7: 0 | M7: 0 | N7: 13 | O7: =N7*1 -> 13 | P7: =O7 -> 13 | Q7: =P7 -> 13 | R7: =Q7 -> 13 | S7: =R7 -> 13 | T7: =S7 -> 13 | U7: =T7 -> 13 | V7: =U7 -> 13 | W7: =V7 -> 13 | X7: =W7 -> 13
C8: Other external costs | H8: -65.157 | I8: -62.686 | J8: -61.953 | K8: -71.173 | L8: -80.393 | M8: -86.759 | N8: -92 | O8: =N8*0.96 -> -88.32 | P8: =O8 -> -88.32 | Q8: =P8 -> -88.32 | R8: =Q8 -> -88.32 | S8: =R8 -> -88.32 | T8: =S8 -> -88.32 | U8: =T8 -> -88.32 | V8: =U8 -> -88.32 | W8: =V8 -> -88.32 | X8: =W8 -> -88.32
C9: Personnel costs | H9: -153.753 | I9: -146.6 | J9: -163.876 | K9: -194.303 | L9: -214.944 | M9: -226.719 | N9: -237 | O9: =N9*0.97 -> -229.89 | P9: =O9 -> -229.89 | Q9: =P9 -> -229.89 | R9: =Q9 -> -229.89 | S9: =R9 -> -229.89 | T9: =S9 -> -229.89 | U9: =T9 -> -229.89 | V9: =U9 -> -229.89 | W9: =V9 -> -229.89 | X9: =W9 -> -229.89
C10: D/A/I | H10: -24.6 | I10: -25.854 | J10: -25.941 | K10: -29.921 | L10: -31.195 | M10: -34.566 | N10: -32 | O10: =N10*0.96 -> -30.72 | P10: =O10 -> -30.72 | Q10: =P10 -> -30.72 | R10: =Q10 -> -30.72 | S10: =R10 -> -30.72 | T10: =S10 -> -30.72 | U10: =T10 -> -30.72 | V10: =U10 -> -30.72 | W10: =V10 -> -30.72 | X10: =W10 -> -30.72
C11: Other opex | H11: -3.162 | I11: -5.3 | J11: -4.691 | K11: -17.154 | L11: -15.57 | M11: -14.816 | N11: -14 | O11: =N11*0.96 -> -13.44 | P11: =O11 -> -13.44 | Q11: =P11 -> -13.44 | R11: =Q11 -> -13.44 | S11: =R11 -> -13.44 | T11: =S11 -> -13.44 | U11: =T11 -> -13.44 | V11: =U11 -> -13.44 | W11: =V11 -> -13.44 | X11: =W11 -> -13.44
C12: Operating profit (EBIT) | H12: =SUM(H6:H11) -> 66.173 | I12: =SUM(I6:I11) -> 50.81 | J12: =SUM(J6:J11) -> 119.547 | K12: =SUM(K6:K11) -> 136.415 | L12: =SUM(L6:L11) -> 62.997 | M12: =SUM(M6:M11) -> 82.852 | N12: =SUM(N6:N11) -> 72 | O12: =SUM(O6:O11) -> 66.43 | ... X12: =SUM(X6:X11) -> 66.43
C13: Net financial items | H13: -3 | I13: -3.698 | J13: -3.343 | K13: -4 | L13: =2.325-12.758 -> -10.433 | M13: =3.834-8.652 -> -4.818 | N13: -6 | O13: -6 | P13: -6 | Q13: -6 | R13: -6 | S13: -6 | T13: -6 | U13: -6 | V13: -6 | W13: -6 | X13: -6
C14: PTP | H14: =SUM(H12:H13) -> 63.173 | I14: =SUM(I12:I13) -> 47.112 | J14: =SUM(J12:J13) -> 116.204 | K14: =SUM(K12:K13) -> 132.415 | L14: =SUM(L12:L13) -> 52.564 | M14: =SUM(M12:M13) -> 78.034 | N14: =SUM(N12:N13) -> 66 | O14: =SUM(O12:O13) -> 60.43 | ... X14: =SUM(X12:X13) -> 60.43
C15: Tax | H15: -15.84 | I15: -13.551 | J15: -28.766 | K15: -31.417 | L15: -13.176 | M15: -19 | N15: -17 | O15: =O14*-0.2 -> -12.086 | P15: =P14*-0.2 -> -12.086 | Q15: =Q14*-0.2 -> -12.086 | R15: =R14*-0.2 -> -12.086 | S15: =S14*-0.2 -> -12.086 | T15: =T14*-0.2 -> -12.086 | U15: =U14*-0.2 -> -12.086 | V15: =V14*-0.2 -> -12.086 | ... X15: =X14*-0.2 -> -12.086
C16: Net income | H16: =SUM(H14:H15) -> 47.333 | I16: =SUM(I14:I15) -> 33.561 | J16: =SUM(J14:J15) -> 87.438 | K16: =SUM(K14:K15) -> 100.998 | L16: =SUM(L14:L15) -> 39.388 | M16: =SUM(M14:M15) -> 59.034 | N16: =SUM(N14:N15) -> 49 | O16: =SUM(O14:O15) -> 48.344 | ... X16: =SUM(X14:X15) -> 48.344 | Y16: =X16*(1+$AA$20) -> 47.86056 | Z16: =Y16*(1+$AA$20) -> 47.381954 | AA16: =Z16*(1+$AA$20) -> 46.908135 | AB16: =AA16*(1+$AA$20) -> 46.439054 | AC16: =AB16*(1+$AA$20) -> 45.974663 | AD16: =AC16*(1+$AA$20) -> 45.514916 | AE16: =AD16*(1+$AA$20) -> 45.059767 | AF16: =AE16*(1+$AA$20) -> 44.60917 | ... EM16: =EL16*(1+$AA$20) -> 14.61944
C17: Share | H17: 11.402 | I17: 11.402 | J17: 11.402 | K17: 11.402 | L17: 11.402 | M17: 11.402 | N17: 11.402 | O17: 11.402 | P17: 11.402 | Q17: 11.402 | R17: 11.402 | S17: 11.402 | T17: 11.402 | U17: 11.402 | V17: 11.402 | W17: 11.402 | X17: 11.402
C18: EPS | H18: =H16/H17 -> 4.1512892 | I18: =I16/I17 -> 2.943431 | J18: =J16/J17 -> 7.6686546 | K18: =K16/K17 -> 8.8579197 | L18: =L16/L17 -> 3.4544817 | M18: =M16/M17 -> 5.1775127 | N18: =N16/N17 -> 4.2974917 | O18: =O16/O17 -> 4.2399579 | ... X18: =X16/X17 -> 4.2399579
Z19: Discount | AA19: 0.08
C20: Revenue y/y | E20: =(E4-D4)/D4 -> #DIV/0! | F20: =(F4-E4)/E4 -> #DIV/0! | G20: =(G4-F4)/F4 -> #DIV/0! | H20: =(H4-G4)/G4 -> #DIV/0! | I20: =(I4-H4)/H4 -> -0.11535419 | J20: =(J4-I4)/I4 -> 0.25546513 | K20: =(K4-J4)/J4 -> 0.21879522 | L20: =(L4-K4)/K4 -> -0.082129037 | ... X20: =(X4-W4)/W4 -> 0 | Z20: TV | AA20: -0.01
C21: Organic growth | Z21: NPV | AA21: =NPV(AA19,O16:EM16) -> 570.70321
C22: Gross margin | D22: =D6/D4 -> #DIV/0! | E22: =E6/E4 -> #DIV/0! | F22: =F6/F4 -> #DIV/0! | G22: =G6/G4 -> #DIV/0! | H22: =H6/H4 -> 0.4342247 | I22: =I6/I4 -> 0.45696381 | J22: =J6/J4 -> 0.4699031 | K22: =K6/K4 -> 0.46035613 | ... X22: =X6/X4 -> 0.44 | Z22: S/O | AA22: 11.402
C23: EBIT margin | D23: =D12/D4 -> #DIV/0! | E23: =E12/E4 -> #DIV/0! | F23: =F12/F4 -> #DIV/0! | G23: =G12/G4 -> #DIV/0! | H23: =H12/H4 -> 0.091847244 | I23: =I12/I4 -> 0.079719593 | J23: =J12/J4 -> 0.14939976 | K23: =K12/K4 -> 0.13987581 | ... X23: =X12/X4 -> 0.070296296 | Z23: NPV/Share | AA23: =AA21/AA22 -> 50.052904
Z24: Opp/nedside | AA24: =(AA23-Modell!B4)/Modell!B4 -> 0.0020601461
