Workbook

Sheet Info
X3: Nordax tilbyr:
X4: Forbrukslån (Private loan)
X5: Boliglån (Secured)
X7: Bank Norwegian tilbyr:
X8: kredittkort
X9: Forbrukslån (Private loan)
X10: Grønt lån (Private loan)
X11: Rammelån (Secured/Priavte loan)
X13: Svensk hypotekspension tilbyr:
X14: Pantesikret equity release eller reverese mortgage
X15: Øker belåningen på boligen din og får ut EK
X16: Ingen amort eller renter, betales tilbake når huset selges eller ved dødsfall
... X20: Bedriftslån fr 5-50 SEKm, 4,5% + STIBOR (Private loan)
A23: NOBA er heldigital
A24: NPL = Non perfoming loans
A26: Private loans | E26: Credit cards | I26: Secured loans
M27: Nordic capital er i styret, Christopher Ekdahl
M28: Sampo er i styret, Richard Wennerklint
A38: Press releases:
A39: 22.09.26: Sampo hat gjort et nedsalg på 14,7 mill aksjer til ish 85,2 SEK, eier nå 10,01%
A40: 04.09.26: NOBA har utstedt en subordnated tier 2 bond. Verdien er 350 SEKm med løpetid 10,4 år med mulig først call etter 5,1 år som betaler STIBOR + 2,22%
A41: 01.07.26: NOBA utsteder senior preferred bonds. Bonds er på 200 SEKm med forfall 2029. Renten er 3 månender STIBOR + 1%
A42: 23.06.26: NOBA utsteder 2 Senior Preferred bonds med verdi på 500 SEKm. Renten er STIBOR/NIBOR + 1,10%
A43: 17.06.26: NOBA utsteder AT1 bond på 750 SEKm. Renten er STIBOR + 3,75%
A44: 10.02.26: Nordic cap og Sampo selger 50 mill aksjer total til 100SEK/aksje. Nordic cap 40 og Sampo 10.
A45: 03.02.26: NOBA fullfører oppkjøpet av DBT Capital AB.
A46: 19.12.26: NOBA utsteder Senior preferred Bonds på 300 SEKm, renten er STIBOR + 1,25%
A47: 18.12.26. NOBA kjøper DBT Capital AB som er spesialisert i utlån til small and medium-sized enterprises. Prisen er 403 SEKm

Sheet Modell
A3: Kapitalstruktur | C3: SEKm | D3: Q122 | E3: Q222 | F3: Q322 | G3: Q422 | H3: Q123 | I3: Q223 | J3: Q323 | K3: Q423 | L3: Q124 | M3: Q224 | N3: Q324 | O3: Q424 | P3: Q125 | Q3: Q225 | R3: Q325 | S3: Q425 | T3: Q126 | U3: Q226 | V3: Q326 | W3: Q426 | Y3: FY 2021 | Z3: FY 2022 | AA3: FY 2023 | AB3: FY 2024 | AC3: FY 2025 | AD3: FY 2026 | AE3: FY 2027 | AF3: FY 2028 | AG3: FY 2029 | AH3: FY 2030 | AI3: FY 2031 | AJ3: FY 2032 | AK3: FY 2033 | AL3: FY 2034 | AM3: FY 2035
A4: Price | B4: 86 | C4: Interest income | G4: 2260 | J4: 3079 | K4: 3249 | L4: 3352 | M4: 3485 | N4: 3601 | O4: 3706 | P4: 3600 | Q4: 3518 | R4: 3648 | S4: 3654 | T4: 3641 | U4: 3864 | Y4: 3011 | Z4: 8025 | AA4: 11507 | AB4: 14144 | AC4: 14420 | AD4: =AC4*1.04 -> 14996.8 | AE4: =AD4*1.11 -> 16646.448 | AF4: =AE4*1.1 -> 18311.093 | AG4: =AF4*1.1 -> 20142.202 | AH4: =AG4*1.1 -> 22156.422 | AI4: =AH4*1.1 -> 24372.065 | AJ4: =AI4*1.1 -> 26809.271 | AK4: =AJ4*1.1 -> 29490.198 | AL4: =AK4*1.1 -> 32439.218 | AM4: =AL4*1.1 -> 35683.14
A5: S/O | B5: 500 | C5: Interest expense | G5: -478 | J5: -1011 | K5: -1120 | L5: -1205 | M5: -1239 | N5: -1234 | O5: -1171 | P5: -1073 | Q5: -969 | R5: -936 | S5: -910 | T5: -919 | U5: -997 | Y5: -479 | Z5: -1278 | AA5: -3514 | AB5: -4849 | AC5: -3888 | AD5: =AC5*0.98 -> -3810.24 | AE5: =AD5*1 -> -3810.24 | AF5: =AE5*1.03 -> -3924.5472 | AG5: =AF5*1.04 -> -4081.5291 | AH5: =AG5*1.04 -> -4244.7903 | AI5: =AH5*1.04 -> -4414.5819 | AJ5: =AI5*1.05 -> -4635.311 | AK5: =AJ5*1.1 -> -5098.8421 | AL5: =AK5*1.1 -> -5608.7263 | AM5: =AL5*1.1 -> -6169.5989
A6: MC NOKm | B6: =B4*B5 -> 43000 | C6: Total net interest income | D6: =SUM(D4:D5) -> 0 | E6: =SUM(E4:E5) -> 0 | F6: =SUM(F4:F5) -> 0 | G6: =SUM(G4:G5) -> 1782 | H6: =SUM(H4:H5) -> 0 | I6: =SUM(I4:I5) -> 0 | J6: =SUM(J4:J5) -> 2068 | K6: =SUM(K4:K5) -> 2129 | ... U6: =SUM(U4:U5) -> 2867 | Y6: =SUM(Y4:Y5) -> 2532 | Z6: =SUM(Z4:Z5) -> 6747 | AA6: =SUM(AA4:AA5) -> 7993 | AB6: =SUM(AB4:AB5) -> 9295 | AC6: =SUM(AC4:AC5) -> 10532 | AD6: =SUM(AD4:AD5) -> 11186.56 | AE6: =SUM(AE4:AE5) -> 12836.208 | AF6: =SUM(AF4:AF5) -> 14386.546 | ... AM6: =SUM(AM4:AM5) -> 29513.541
A7: Cash NOKm | C7: Commission income | G7: 163 | J7: 201 | K7: 180 | L7: 205 | M7: 248 | N7: 238 | O7: 246 | P7: 282 | Q7: 285 | R7: 307 | S7: 286 | T7: 296 | U7: 317 | Y7: 166 | Z7: 414 | AA7: 727 | AB7: 937 | AC7: 1160 | AD7: 900 | AE7: =AD7*1.03 -> 927 | AF7: =AE7*1.03 -> 954.81 | AG7: =AF7*1.03 -> 983.4543 | AH7: =AG7*1.03 -> 1012.9579 | AI7: =AH7*1.03 -> 1043.3467 | AJ7: =AI7*1.03 -> 1074.6471 | AK7: =AJ7*1.03 -> 1106.8865 | AL7: =AK7*1.03 -> 1140.0931 | AM7: =AL7*1.03 -> 1174.2959
A8: Debt NOKm | C8: Commission expenses | G8: -46 | J8: -58 | K8: -71 | L8: -68 | M8: -76 | N8: -71 | O8: -77 | P8: -73 | Q8: -87 | R8: -73 | S8: -86 | T8: -89 | U8: -99 | Y8: 0 | Z8: 0 | AA8: -226 | AB8: -292 | AC8: -319 | AD8: -350 | AE8: =AD8*1.03 -> -360.5 | AF8: =AE8*1.03 -> -371.315 | AG8: =AF8*1.03 -> -382.45445 | AH8: =AG8*1.03 -> -393.92808 | AI8: =AH8*1.03 -> -405.74593 | AJ8: =AI8*1.03 -> -417.9183 | AK8: =AJ8*1.03 -> -430.45585 | AL8: =AK8*1.03 -> -443.36953 | AM8: =AL8*1.03 -> -456.67061
A9: EV NOKm | B9: =B6-B7+B8 -> 43000 | C9: Net profit from finanivial transactions | G9: 26 | J9: 5 | K9: 17 | L9: -8 | M9: -20 | N9: -13 | O9: -15 | P9: -1 | Q9: -48 | R9: -32 | S9: -16 | T9: 12 | U9: -30 | Y9: -68 | Z9: -207 | AA9: 9 | AB9: -56 | AC9: -97 | AD9: 50 | AE9: =AD9*1.03 -> 51.5 | AF9: =AE9*1.03 -> 53.045 | AG9: =AF9*1.03 -> 54.63635 | AH9: =AG9*1.03 -> 56.275441 | AI9: =AH9*1.03 -> 57.963704 | AJ9: =AI9*1.03 -> 59.702615 | AK9: =AJ9*1.03 -> 61.493693 | AL9: =AK9*1.03 -> 63.338504 | AM9: =AL9*1.03 -> 65.238659
C10: Total operating income | D10: =SUM(D6:D9) -> 0 | E10: =SUM(E6:E9) -> 0 | F10: =SUM(F6:F9) -> 0 | G10: =SUM(G6:G9) -> 1925 | H10: =SUM(H6:H9) -> 0 | I10: =SUM(I6:I9) -> 0 | J10: =SUM(J6:J9) -> 2216 | K10: =SUM(K6:K9) -> 2255 | ... U10: =SUM(U6:U9) -> 3055 | Y10: =SUM(Y6:Y9) -> 2630 | Z10: =SUM(Z6:Z9) -> 6954 | AA10: =SUM(AA6:AA9) -> 8503 | AB10: =SUM(AB6:AB9) -> 9884 | AC10: =SUM(AC6:AC9) -> 11276 | AD10: =SUM(AD6:AD9) -> 11786.56 | AE10: =SUM(AE6:AE9) -> 13454.208 | AF10: =SUM(AF6:AF9) -> 15023.086 | ... AM10: =SUM(AM6:AM9) -> 30296.405
C11: General adminstrative expenses | G11: -434 | J11: -374 | K11: -391 | L11: -398 | M11: -430 | N11: -449 | O11: -528 | P11: -411 | Q11: -439 | R11: -560 | S11: -464 | T11: -451 | U11: -458 | Y11: -1319 | Z11: -1876 | AA11: -1509 | AB11: -1805 | AC11: -1874 | AD11: =AC11*1.01 -> -1892.74 | AE11: =AD11 -> -1892.74 | AF11: =AE11*1.03 -> -1949.5222 | AG11: =AF11*1.1 -> -2144.4744 | AH11: =AG11*1.1 -> -2358.9219 | AI11: =AH11*1.1 -> -2594.814 | AJ11: =AI11*1.1 -> -2854.2955 | AK11: =AJ11*1.1 -> -3139.725 | AL11: =AK11*1.1 -> -3453.6975 | AM11: =AL11*1.1 -> -3799.0672
C12: D/A/I | G12: -226 | J12: -14 | K12: -23 | L12: -15 | M12: -16 | N12: -16 | O12: -17 | P12: -18 | Q12: -18 | R12: -21 | S12: -22 | T12: -24 | U12: -30 | Y12: -62 | Z12: -449 | AA12: -149 | AB12: -64 | AC12: -79 | AD12: =AC12*1.01 -> -79.79 | AE12: =AD12 -> -79.79 | AF12: =AE12*1.03 -> -82.1837 | AG12: =AF12*1.1 -> -90.40207 | AH12: =AG12*1.1 -> -99.442277 | AI12: =AH12*1.1 -> -109.3865 | AJ12: =AI12*1.1 -> -120.32516 | AK12: =AJ12*1.1 -> -132.35767 | AL12: =AK12*1.1 -> -145.59344 | AM12: =AL12*1.1 -> -160.15278
A13: Bok/Aksje | B13: =U74/B5 -> 55.748 | C13: Other operating expenses | G13: -297 | J13: -315 | K13: -420 | L13: -204 | M13: -221 | N13: -230 | O13: -199 | P13: -201 | Q13: -172 | R13: -222 | S13: -210 | T13: -191 | U13: -215 | Y13: -269 | Z13: -875 | AA13: -1287 | AB13: -854 | AC13: -805 | AD13: =AC13*1.01 -> -813.05 | AE13: =AD13 -> -813.05 | AF13: =AE13*1.03 -> -837.4415 | AG13: =AF13*1.1 -> -921.18565 | AH13: =AG13*1.1 -> -1013.3042 | AI13: =AH13*1.1 -> -1114.6346 | AJ13: =AI13*1.1 -> -1226.0981 | AK13: =AJ13*1.1 -> -1348.7079 | AL13: =AK13*1.1 -> -1483.5787 | AM13: =AL13*1.1 -> -1631.9366
C14: Profit before credit losses | D14: =SUM(D10:D13) -> 0 | E14: =SUM(E10:E13) -> 0 | F14: =SUM(F10:F13) -> 0 | G14: =SUM(G10:G13) -> 968 | H14: =SUM(H10:H13) -> 0 | I14: =SUM(I10:I13) -> 0 | J14: =SUM(J10:J13) -> 1513 | K14: =SUM(K10:K13) -> 1421 | ... U14: =SUM(U10:U13) -> 2352 | Y14: =SUM(Y10:Y13) -> 980 | Z14: =SUM(Z10:Z13) -> 3754 | AA14: =SUM(AA10:AA13) -> 5558 | AB14: =SUM(AB10:AB13) -> 7161 | AC14: =SUM(AC10:AC13) -> 8518 | AD14: =SUM(AD10:AD13) -> 9000.98 | AE14: =SUM(AE10:AE13) -> 10668.628 | AF14: =SUM(AF10:AF13) -> 12153.938 | ... AM14: =SUM(AM10:AM13) -> 24705.248
A15: P/B | B15: =B4/B13 -> 1.5426562 | C15: Net credit losses | G15: -855 | J15: -1105 | K15: -1139 | L15: -1091 | M15: -932 | N15: -985 | O15: -1141 | P15: -1023 | Q15: -909 | R15: -918 | S15: -930 | T15: -913 | U15: -883 | Y15: -1013 | Z15: -2425 | AA15: -3907 | AB15: -4149 | AC15: -3780 | AD15: -3652 | AE15: =AD15*1.15 -> -4199.8 | AF15: =AE15*1.15 -> -4829.77 | AG15: =AF15*1.12 -> -5409.3424 | AH15: =AG15*1.11 -> -6004.3701 | AI15: =AH15*1.11 -> -6664.8508 | AJ15: =AI15*1.11 -> -7397.9844 | AK15: =AJ15*1.1 -> -8137.7828 | AL15: =AK15*1.1 -> -8951.5611 | AM15: =AL15*1.1 -> -9846.7172
C16: Operating profit before amort of transaction surplus values | D16: =SUM(D14:D15) -> 0 | E16: =SUM(E14:E15) -> 0 | F16: =SUM(F14:F15) -> 0 | G16: =SUM(G14:G15) -> 113 | H16: =SUM(H14:H15) -> 0 | I16: =SUM(I14:I15) -> 0 | J16: =SUM(J14:J15) -> 408 | K16: =SUM(K14:K15) -> 282 | ... U16: =SUM(U14:U15) -> 1469 | Y16: =SUM(Y14:Y15) -> -33 | Z16: =SUM(Z14:Z15) -> 1329 | AA16: =SUM(AA14:AA15) -> 1651 | AB16: =SUM(AB14:AB15) -> 3012 | AC16: =SUM(AC14:AC15) -> 4738 | AD16: =SUM(AD14:AD15) -> 5348.98 | AE16: =SUM(AE14:AE15) -> 6468.828 | AF16: =SUM(AF14:AF15) -> 7324.1682 | ... AM16: =SUM(AM14:AM15) -> 14858.531
C17: Amort of transaction surplus values | G17: -36 | J17: -35 | K17: -33 | L17: -33 | M17: -34 | N17: -34 | O17: -33 | P17: -33 | Q17: -31 | R17: -32 | S17: -32 | T17: -32 | U17: -34 | AA17: -136 | AB17: -134 | AC17: -128 | AD17: -128 | AE17: -130 | AF17: -130 | AG17: -130 | AH17: -130 | AI17: -130 | AJ17: -130 | AK17: -130 | AL17: -130 | AM17: -130
C18: Operating profit | D18: =SUM(D16:D17) -> 0 | E18: =SUM(E16:E17) -> 0 | F18: =SUM(F16:F17) -> 0 | G18: =SUM(G16:G17) -> 77 | H18: =SUM(H16:H17) -> 0 | I18: =SUM(I16:I17) -> 0 | J18: =SUM(J16:J17) -> 373 | K18: =SUM(K16:K17) -> 249 | ... U18: =SUM(U16:U17) -> 1435 | Y18: =SUM(Y16:Y17) -> -33 | Z18: =SUM(Z16:Z17) -> 1329 | AA18: =SUM(AA16:AA17) -> 1515 | AB18: =SUM(AB16:AB17) -> 2878 | AC18: =SUM(AC16:AC17) -> 4610 | AD18: =SUM(AD16:AD17) -> 5220.98 | AE18: =SUM(AE16:AE17) -> 6338.828 | AF18: =SUM(AF16:AF17) -> 7194.1682 | ... AM18: =SUM(AM16:AM17) -> 14728.531
C19: Tax | G19: -62 | J19: -63 | K19: -62 | L19: -130 | M19: -187 | N19: -211 | O19: -148 | P19: -228 | Q19: -248 | R19: -257 | S19: -266 | T19: -327 | U19: -326 | Y19: 10 | Z19: -356 | AA19: -328 | AB19: -676 | AC19: -999 | AD19: =AD18*-0.2 -> -1044.196 | AE19: =AE18*-0.2 -> -1267.7656 | AF19: =AF18*-0.2 -> -1438.8336 | AG19: =AG18*-0.2 -> -1604.1809 | AH19: =AH18*-0.2 -> -1796.1798 | AI19: =AI18*-0.2 -> -2007.8722 | AJ19: =AJ18*-0.2 -> -2232.3377 | AK19: =AK18*-0.2 -> -2448.1414 | ... AM19: =AM18*-0.2 -> -2945.7062
C20: Net income | D20: =SUM(D18:D19) -> 0 | E20: =SUM(E18:E19) -> 0 | F20: =SUM(F18:F19) -> 0 | G20: =SUM(G18:G19) -> 15 | H20: =SUM(H18:H19) -> 0 | I20: =SUM(I18:I19) -> 0 | J20: =SUM(J18:J19) -> 310 | K20: =SUM(K18:K19) -> 187 | ... U20: =SUM(U18:U19) -> 1109 | Y20: =SUM(Y18:Y19) -> -23 | Z20: =SUM(Z18:Z19) -> 973 | AA20: =SUM(AA18:AA19) -> 1187 | AB20: =SUM(AB18:AB19) -> 2202 | AC20: =SUM(AC18:AC19) -> 3611 | AD20: =SUM(AD18:AD19) -> 4176.784 | AE20: =SUM(AE18:AE19) -> 5071.0624 | AF20: =SUM(AF18:AF19) -> 5755.3346 | ... AM20: =SUM(AM18:AM19) -> 11782.825 | AN20: =AM20*(1+$AP$24) -> 11664.996 | AO20: =AN20*(1+$AP$24) -> 11548.347 | AP20: =AO20*(1+$AP$24) -> 11432.863 | AQ20: =AP20*(1+$AP$24) -> 11318.534 | AR20: =AQ20*(1+$AP$24) -> 11205.349 | AS20: =AR20*(1+$AP$24) -> 11093.296 | AT20: =AS20*(1+$AP$24) -> 10982.363 | AU20: =AT20*(1+$AP$24) -> 10872.539 | ... HF20: =HE20*(1+$AP$24) -> 2029.5907
C21: Shares | J21: 500 | K21: 500 | L21: 500 | M21: 500 | N21: 500 | O21: 500 | P21: 500 | Q21: 500 | R21: 500 | S21: 500 | T21: 500 | U21: 500 | Y21: 500 | Z21: 500 | AA21: 500 | AB21: 500 | AC21: 500 | AD21: 500 | AE21: 500 | AF21: 500 | AG21: 500 | AH21: 500 | AI21: 500 | AJ21: 500 | AK21: 500 | AL21: 500 | AM21: 500
C22: EPS | D22: =D20/D21 -> #DIV/0! | E22: =E20/E21 -> #DIV/0! | F22: =F20/F21 -> #DIV/0! | G22: =G20/G21 -> #DIV/0! | H22: =H20/H21 -> #DIV/0! | I22: =I20/I21 -> #DIV/0! | J22: =J20/J21 -> 0.62 | K22: =K20/K21 -> 0.374 | ... U22: =U20/U21 -> 2.218 | Y22: =Y20/Y21 -> -0.046 | Z22: =Z20/Z21 -> 1.946 | AA22: =AA20/AA21 -> 2.374 | AB22: =AB20/AB21 -> 4.404 | AC22: =AC20/AC21 -> 7.222 | AD22: =AD20/AD21 -> 8.353568 | AE22: =AE20/AE21 -> 10.142125 | AF22: =AF20/AF21 -> 11.510669 | ... AM22: =AM20/AM21 -> 23.565649
AO23: Disocunt | AP23: 0.1
C24: Revenue y/y | H24: =(H10-D10)/D10 -> #DIV/0! | I24: =(I10-E10)/E10 -> #DIV/0! | J24: =(J10-F10)/F10 -> #DIV/0! | K24: =(K10-G10)/G10 -> 0.17142857 | L24: =(L10-H10)/H10 -> #DIV/0! | M24: =(M10-I10)/I10 -> #DIV/0! | N24: =(N10-J10)/J10 -> 0.13763538 | O24: =(O10-K10)/K10 -> 0.1924612 | ... U24: =(U10-Q10)/Q10 -> 0.1319007 | Z24: =(Z10-Y10)/Y10 -> 1.6441065 | AA24: =(AA10-Z10)/Z10 -> 0.2227495 | AB24: =(AB10-AA10)/AA10 -> 0.16241327 | AC24: =(AC10-AB10)/AB10 -> 0.14083367 | AD24: =(AD10-AC10)/AC10 -> 0.045278468 | AE24: =(AE10-AD10)/AD10 -> 0.14148725 | AF24: =(AF10-AE10)/AE10 -> 0.11660869 | AG24: =(AG10-AF10)/AF10 -> 0.11270811 | ... AM24: =(AM10-AL10)/AL10 -> 0.098071646 | AO24: TV | AP24: -0.01
C25: Operating profit margin | D25: =D18/D10 -> #DIV/0! | E25: =E18/E10 -> #DIV/0! | F25: =F18/F10 -> #DIV/0! | G25: =G18/G10 -> 0.04 | H25: =H18/H10 -> #DIV/0! | I25: =I18/I10 -> #DIV/0! | J25: =J18/J10 -> 0.1683213 | K25: =K18/K10 -> 0.11042129 | ... U25: =U18/U10 -> 0.46972177 | Y25: =Y18/Y10 -> -0.012547529 | Z25: =Z18/Z10 -> 0.19111303 | AA25: =AA18/AA10 -> 0.17817241 | AB25: =AB18/AB10 -> 0.29117766 | AC25: =AC18/AC10 -> 0.40883292 | AD25: =AD18/AD10 -> 0.44296046 | AE25: =AE18/AE10 -> 0.47114092 | AF25: =AF18/AF10 -> 0.47887421 | ... AM25: =AM18/AM10 -> 0.48614781 | AO25: NPV | AP25: =NPV(AP23,AD20:HF20) -> 84823.077
C26: Common Equity Tier 1 capital ratio (CET1) | L26: 0.132 | M26: 0.134 | N26: 0.131 | O26: 0.132 | P26: 0.138 | Q26: 0.14 | R26: 0.141 | S26: 0.137 | T26: 0.133 | U26: 0.134 | AO26: S/O | AP26: 500
C27: Total capital ratio | L27: 0.172 | M27: 0.172 | N27: 0.172 | O27: 0.172 | P27: 0.179 | Q27: 0.18 | R27: 0.179 | S27: 0.175 | T27: 0.17 | U27: 0.183 | AO27: NPV/Share | AP27: =AP25/AP26 -> 169.64615
C28: Net interest margin | L28: =L6*4/AVERAGE(K47:L47) -> 0.076485309 | M28: =M6*4/AVERAGE(L47:M47) -> 0.077609516 | N28: =N6*4/AVERAGE(M47:N47) -> 0.079472533 | O28: =O6*4/AVERAGE(N47:O47) -> 0.082557827 | P28: =P6*4/AVERAGE(O47:P47) -> 0.081407148 | Q28: =Q6*4/AVERAGE(P47:Q47) -> 0.081097956 | R28: =R6*4/AVERAGE(Q47:R47) -> 0.083760578 | S28: =S6*4/AVERAGE(R47:S47) -> 0.083214556 | ... U28: =U6*4/AVERAGE(T47:U47) -> 0.081181622 | Z28: =Z6/AVERAGE(Y47:Z47) -> 0.08463531 | AA28: =AA6/AVERAGE(Z47:AA47) -> 0.080381341 | AB28: =AB6/AVERAGE(AA47:AB47) -> 0.079251734 | AC28: =AC6/AVERAGE(AB47:AC47) -> 0.082028436 | AD28: =AD6/AVERAGE(AC47:AD47) -> 0.079630996 | AE28: =AE6/AVERAGE(AD47:AE47) -> 0.081481068 | AF28: =AF6/AVERAGE(AE47:AF47) -> 0.081537703 | AG28: =AG6/AVERAGE(AF47:AG47) -> 0.081273256 | ... AM28: =AM6/AVERAGE(AL47:AM47) -> 0.08209468 | AO28: Opp/nedside | AP28: =(AP27-B4)/B4 -> 0.9726297
C29: C/I ratio | L29: 0.277 | M29: 0.278 | N29: 0.276 | O29: 0.277 | P29: 0.23 | Q29: 0.233 | R29: 0.276 | S29: 0.237 | T29: 0.226 | U29: 0.23 | Y29: =-SUM(Y11:Y13)/Y10 -> 0.62737643 | Z29: =-SUM(Z11:Z13)/Z10 -> 0.46016681 | AA29: =-SUM(AA11:AA13)/AA10 -> 0.34634835 | AB29: =-SUM(AB11:AB13)/AB10 -> 0.27549575 | AC29: =-SUM(AC11:AC13)/AC10 -> 0.24459028 | AD29: =-SUM(AD11:AD13)/AD10 -> 0.23633528 | AE29: =-SUM(AE11:AE13)/AE10 -> 0.20704154 | AF29: =-SUM(AF11:AF13)/AF10 -> 0.19098256 | ... AM29: =-SUM(AM11:AM13)/AM10 -> 0.18454852
C30: Credit loss ratio | L30: 0.037 | M30: 0.032 | N30: 0.033 | O30: 0.037 | P30: 0.033 | Q30: 0.029 | R30: 0.028 | S30: 0.028 | T30: 0.027 | U30: 0.025 | Z30: =-Z15/AVERAGE(Y47:Z47) -> 0.030419539 | AA30: =-AA15/AVERAGE(Z47:AA47) -> 0.039290617 | AB30: =-AB15/AVERAGE(AA47:AB47) -> 0.035375519 | AC30: =-AC15/AVERAGE(AB47:AC47) -> 0.029440513 | AD30: =-AD15/AVERAGE(AC47:AD47) -> 0.025996588 | AE30: =-AE15/AVERAGE(AD47:AE47) -> 0.02665929 | AF30: =-AF15/AVERAGE(AE47:AF47) -> 0.027373378 | AG30: =-AG15/AVERAGE(AF47:AG47) -> 0.027373378 | ... AM30: =-AM15/AVERAGE(AL47:AM47) -> 0.027389567
C31: ROTE | L31: 0.186 | M31: 0.187 | N31: 0.185 | O31: 0.186 | P31: 0.239 | Q31: 0.245 | R31: 0.237 | S31: 0.249 | T31: 0.234 | U31: 0.269 | Y31: -0.011 | Z31: 0.102 | AA31: 0.107 | AB31: 0.175 | AC31: 0.242
C32: ROE | L32: =(L20*4)/AVERAGE(K74:L74) -> 0.078811024 | M32: =(M20*4)/AVERAGE(L74:M74) -> 0.10800206 | N32: =(N20*4)/AVERAGE(M74:N74) -> 0.10896542 | O32: =(O20*4)/AVERAGE(N74:O74) -> 0.11139671 | P32: =(P20*4)/AVERAGE(O74:P74) -> 0.14289133 | Q32: =(Q20*4)/AVERAGE(P74:Q74) -> 0.14958977 | R32: =(R20*4)/AVERAGE(Q74:R74) -> 0.14850408 | S32: =(S20*4)/AVERAGE(R74:S74) -> 0.15727433 | ... U32: =(U20*4)/AVERAGE(T74:U74) -> 0.15970335 | Y32: =Y20/Y74 -> -0.0012135282 | Z32: =Z20/Z74 -> 0.049255847 | AA32: =AA20/AA74 -> 0.05937672 | AB32: =AB20/AB74 -> 0.09709851 | AC32: =AC20/AC74 -> 0.13754619
C34: Risk weighted assets | G34: 71148 | I34: 80815 | J34: 85086 | K34: 87643 | L34: 91174 | M34: 93145 | N34: 96255 | O34: 99296 | P34: 97219 | Q34: 100878 | R34: 103581 | S34: 104237 | T34: 109709 | U34: 112782 | Z34: 71148 | AA34: 87643 | AB34: 99296 | AC34: 104237
C35: y/y | K35: =(K34-G34)/G34 -> 0.23184067 | M35: =(M34-I34)/I34 -> 0.15257069 | N35: =(N34-J34)/J34 -> 0.13126719 | O35: =(O34-K34)/K34 -> 0.13295985 | P35: =(P34-L34)/L34 -> 0.066301797 | Q35: =(Q34-M34)/M34 -> 0.083021096 | R35: =(R34-N34)/N34 -> 0.076110332 | S35: =(S34-O34)/O34 -> 0.049760313 | T35: =(T34-P34)/P34 -> 0.12847283 | U35: =(U34-Q34)/Q34 -> 0.11800393 | AA35: =(AA34-Z34)/Z34 -> 0.23184067 | AB35: =(AB34-AA34)/AA34 -> 0.13295985 | AC35: =(AC34-AB34)/AB34 -> 0.049760313
C36: RWA/Book | K36: =K34/K47 -> 0.79587908 | L36: =L34/L47 -> 0.79666215 | M36: =M34/M47 -> 0.7956147 | N36: =N34/N47 -> 0.79419627 | O36: =O34/O47 -> 0.79789149 | P36: =P34/P47 -> 0.78475832 | Q36: =Q34/Q47 -> 0.79079685 | R36: =R34/R47 -> 0.78793388 | ... U36: =U34/U47 -> 0.78677066 | AA36: =AA34/AA47 -> 0.79587908 | AB36: =AB34/AB47 -> 0.79789149 | AC36: =AC34/AC47 -> 0.78763951
C38: Loan loss delta y/y | K38: =(K15-G15)/G15 -> 0.33216374 | N38: =(N15-J15)/J15 -> -0.10859729 | O38: =(O15-K15)/K15 -> 0.0017559263 | P38: =(P15-L15)/L15 -> -0.062328139 | Q38: =(Q15-M15)/M15 -> -0.024678112 | R38: =(R15-N15)/N15 -> -0.068020305 | S38: =(S15-O15)/O15 -> -0.1849255 | T38: =(T15-P15)/P15 -> -0.10752688 | U38: =(U15-Q15)/Q15 -> -0.02860286
C40: Loan growth | O40: =(O47-K47)/K47 -> 0.13010234 | P40: =(P47-L47)/L47 -> 0.082476299 | Q40: =(Q47-M47)/M47 -> 0.089619297 | R40: =(R47-N47)/N47 -> 0.084663113 | S40: =(S47-O47)/O47 -> 0.063424081 | T40: =(T47-P47)/P47 -> 0.12346227 | U40: =(U47-Q47)/Q47 -> 0.12372516 | Z40: =(Z47-Y47)/Y47 -> 0.25572643 | AA40: =(AA47-Z47)/Z47 -> 0.24071612 | AB40: =(AB47-AA47)/AA47 -> 0.13010234 | AC40: =(AC47-AB47)/AB47 -> 0.063424081 | AD40: =(AD47-AC47)/AC47 -> 0.123 | AE40: =(AE47-AD47)/AD47 -> 0.12 | AF40: =(AF47-AE47)/AE47 -> 0.12 | AG40: =(AG47-AF47)/AF47 -> 0.12 | ... AM40: =(AM47-AL47)/AL47 -> 0.1
C43: Balanse SEKm
C44: Cash with central banks | K44: 1173 | L44: 1435 | M44: 3401 | N44: 2325 | O44: 9309 | P44: 5278 | Q44: 500 | R44: 400 | S44: 1146 | T44: 368 | U44: 450 | Y44: 1924 | Z44: 3723 | AA44: 1173 | AB44: 9309 | AC44: 1146
C45: Treasury bills eligible for repayment | K45: 1200 | L45: 4998 | M45: 1999 | N45: 330 | O45: 1643 | P45: 1787 | Q45: 1584 | R45: 1810 | S45: 1698 | T45: 1584 | U45: 1743 | AA45: 1200 | AB45: 1643 | AC45: 1698
C46: Lending to credit institutions | K46: 3165 | L46: 3415 | M46: 2149 | N46: 2107 | O46: 2768 | P46: 2002 | Q46: 7564 | R46: 6846 | S46: 5339 | T46: 5729 | U46: 6814 | Y46: 3080 | Z46: 3332 | AA46: 3165 | AB46: 2768 | AC46: 5339
C47: Lending to the public | K47: 110121 | L47: 114445 | M47: 117073 | N47: 121198 | O47: 124448 | P47: 123884 | Q47: 127565 | R47: 131459 | S47: 132341 | T47: 139179 | U47: 143348 | Y47: 70681 | Z47: 88756 | AA47: 110121 | AB47: 124448 | AC47: 132341 | AD47: =AC47*1.123 -> 148618.94 | AE47: =AD47*1.12 -> 166453.22 | AF47: =AE47*1.12 -> 186427.6 | AG47: =AF47*1.12 -> 208798.91 | AH47: =AG47*1.12 -> 233854.78 | AI47: =AH47*1.1 -> 257240.26 | AJ47: =AI47*1.1 -> 282964.29 | AK47: =AJ47*1.1 -> 311260.72 | AL47: =AK47*1.1 -> 342386.79 | AM47: =AL47*1.1 -> 376625.47
C48: Bonds and other fixed-income securites | K48: 13172 | L48: 14577 | M48: 15256 | N48: 15893 | O48: 12190 | P48: 15744 | Q48: 16316 | R48: 17110 | S48: 13557 | T48: 14244 | U48: 14145 | Y48: 23318 | Z48: 13608 | AA48: 13172 | AB48: 12190 | AC48: 13557
C49: Other shares | K49: 150 | L49: 152 | M49: 153 | N49: 113 | O49: 102 | P49: 93 | Q49: 62 | R49: 63 | S49: 7 | T49: 8 | U49: 8 | Y49: 154 | Z49: 168 | AA49: 150 | AB49: 102 | AC49: 7
C50: Dervatives | K50: 324 | L50: 509 | M50: 262 | N50: 393 | O50: 255 | P50: 338 | Q50: 711 | R50: 214 | S50: 452 | T50: 606 | U50: 788 | Y50: 140 | Z50: 419 | AA50: 324 | AB50: 255 | AC50: 452
C51: Intangible assets | K51: 8208 | L51: 8135 | M51: 8178 | N51: 7919 | O51: 7965 | P51: 7851 | Q51: 7752 | R51: 7781 | S51: 7587 | T51: 8182 | U51: 8212 | Y51: 9044 | Z51: 8892 | AA51: 8208 | AB51: 7965 | AC51: 7587
C52: PP&E | K52: 62 | L52: 56 | M52: 56 | N52: 95 | O52: 91 | P52: 87 | Q52: 184 | R52: 176 | S52: 168 | T52: 162 | U52: 160 | Y52: 93 | Z52: 77 | AA52: 62 | AB52: 91 | AC52: 168
C53: Current tax assets | K53: 4 | L53: 5 | M53: 4 | N53: 11 | O53: 19 | P53: 39 | Q53: 23 | R53: 23 | S53: 23 | T53: 24 | U53: 24 | Y53: 2 | Z53: 2 | AA53: 4 | AB53: 19 | AC53: 23
C54: Deferred tax assets | K54: 136 | L54: 133 | M54: 121 | N54: 115 | O54: 108 | P54: 103 | Q54: 105 | R54: 108 | S54: 105 | T54: 148 | U54: 145 | AA54: 136 | AB54: 108 | AC54: 105
C55: Other assets | K55: 285 | L55: 207 | M55: 273 | N55: 163 | O55: 165 | P55: 1147 | Q55: 155 | R55: 491 | S55: 413 | T55: 908 | U55: 420 | Y55: 81 | Z55: 282 | AA55: 285 | AB55: 165 | AC55: 413
C56: Prepaid expenses and accrued income | K56: 65 | L56: 68 | M56: 101 | N56: 88 | O56: 80 | P56: 84 | Q56: 84 | R56: 98 | S56: 74 | T56: 102 | U56: 125 | Y56: 63 | Z56: 66 | AA56: 65 | AB56: 80 | AC56: 74
C57: Total assets | D57: =SUM(D44:D56) -> 0 | E57: =SUM(E44:E56) -> 0 | F57: =SUM(F44:F56) -> 0 | G57: =SUM(G44:G56) -> 0 | H57: =SUM(H44:H56) -> 0 | I57: =SUM(I44:I56) -> 0 | J57: =SUM(J44:J56) -> 0 | K57: =SUM(K44:K56) -> 138065 | ... N57: =SUM(N44:N56) -> 150750 | O57: 159143 | P57: =SUM(P44:P56) -> 158437 | Q57: =SUM(Q44:Q56) -> 162605 | R57: =SUM(R44:R56) -> 166579 | S57: =SUM(S44:S56) -> 162910 | T57: =SUM(T44:T56) -> 171244 | U57: =SUM(U44:U56) -> 176382 | Y57: 108580 | Z57: 119325 | AA57: 138065 | AB57: 159143 | AC57: 162909
C58: Liabilities to credit institutions | K58: 10995 | L58: 13756 | M58: 13712 | N58: 14705 | O58: 16501 | P58: 16333 | Q58: 17918 | R58: 20943 | S58: 19351 | T58: 20973 | U58: 21776 | Y58: 6609 | Z58: 9739 | AA58: 10995 | AB58: 16501 | AC58: 19351
C59: Deposits from the public | K59: 96788 | L59: 105167 | M59: 107352 | N59: 107837 | O59: 113439 | P59: 110987 | Q59: 113318 | R59: 111704 | S59: 107870 | T59: 112415 | U59: 115055 | Y59: 67424 | Z59: 77104 | AA59: 96788 | AB59: 113439 | AC59: 107870
C60: Issued securities | K60: 5581 | L60: 2745 | M60: 1605 | N60: 1648 | O60: 1945 | P60: 2626 | Q60: 2613 | R60: 4086 | S60: 4375 | T60: 5021 | U60: 6688 | Y60: 10866 | Z60: 8416 | AA60: 5581 | AB60: 1945 | AC60: 4375
C61: Derivatives | K61: 425 | L61: 126 | M61: 311 | N61: 289 | O61: 272 | P61: 1124 | Q61: 135 | R61: 329 | S61: 409 | T61: 909 | U61: 652 | Y61: 437 | Z61: 307 | AA61: 425 | AB61: 272 | AC61: 409
C62: Current tax liabilities | K62: 190 | L62: 125 | M62: 91 | N62: 208 | O62: 343 | P62: 422 | Q62: 311 | R62: 498 | S62: 683 | T62: 636 | U62: 449 | Y62: 485 | Z62: 186 | AA62: 190 | AB62: 343 | AC62: 683
C63: Deferred tax liabilities | K63: 733 | L63: 716 | M63: 689 | N63: 654 | O63: 628 | P63: 594 | Q63: 572 | R63: 561 | S63: 527 | T63: 547 | U63: 522 | Y63: 787 | Z63: 701 | AA63: 733 | AB63: 628 | AC63: 527
C64: Other liabilities | K64: 1240 | L64: 1703 | M64: 1187 | N64: 844 | O64: 955 | P64: 690 | Q64: 1383 | R64: 930 | S64: 1151 | T64: 665 | U64: 855 | Y64: 810 | Z64: 1128 | AA64: 1240 | AB64: 955 | AC64: 1151
C65: Accrued expenses and deferred income | K65: 393 | L65: 475 | M65: 541 | N65: 674 | O65: 543 | P65: 561 | Q65: 653 | R65: 890 | S65: 486 | T65: 565 | U65: 664 | Y65: 476 | Z65: 459 | AA65: 393 | AB65: 543 | AC65: 486
C66: Subordinated liabilities | K66: 1729 | L66: 2199 | M66: 1843 | N66: 1831 | O66: 1840 | P66: 1812 | Q66: 1821 | R66: 1822 | S66: 1804 | T66: 1836 | U66: 1845 | Y66: 1733 | Z66: 1531 | AA66: 1729 | AB66: 1840 | AC66: 1804
C67: Total debt | D67: =SUM(D58:D66) -> 0 | E67: =SUM(E58:E66) -> 0 | F67: =SUM(F58:F66) -> 0 | G67: =SUM(G58:G66) -> 0 | H67: =SUM(H58:H66) -> 0 | I67: =SUM(I58:I66) -> 0 | J67: =SUM(J58:J66) -> 0 | K67: =SUM(K58:K66) -> 118074 | ... N67: =SUM(N58:N66) -> 128690 | O67: 136465 | P67: =SUM(P58:P66) -> 135149 | Q67: =SUM(Q58:Q66) -> 138724 | R67: =SUM(R58:R66) -> 141763 | S67: =SUM(S58:S66) -> 136656 | T67: =SUM(T58:T66) -> 143567 | U67: =SUM(U58:U66) -> 148506 | Y67: 89627 | Z67: 99571 | AA67: 118074 | AB67: 136465 | AC67: 136656
C68: Share Capital | K68: 73 | L68: 73 | M68: 73 | N68: 73 | O68: 73 | P68: 73 | Q68: 73 | R68: 73 | S68: 73 | T68: 73 | U68: 73 | Y68: 73 | Z68: 73 | AA68: 73 | AB68: 73 | AC68: 73
C69: Other contributed capital | K69: 4476 | L69: 4476 | M69: 4476 | N69: 4476 | O69: 4476 | P69: 4476 | Q69: 4476 | R69: 4534 | S69: 4533 | T69: 4542 | U69: 4544 | Y69: 4476 | Z69: 4476 | AA69: 4476 | AB69: 4476 | AC69: 4533
C70: Other funds | K70: -537 | L70: -580 | M70: -518 | N70: -886 | O70: -837 | P70: -997 | Q70: -1245 | R70: -1231 | S70: -1499 | T70: -1027 | U70: -1079 | Y70: 147 | Z70: 158 | AA70: -537 | AB70: -837 | AC70: -1499
C71: Tier 1 capital instruments | K71: 1354 | L71: 2157 | M71: 2154 | N71: 2159 | O71: 2163 | P71: 2168 | Q71: 2173 | R71: 2177 | S71: 2928 | T71: 2933 | U71: 3682 | Y71: 1757 | Z71: 1470 | AA71: 1354 | AB71: 2163 | AC71: 2928
C72: Retained earnings | K72: 13438 | L72: 14589 | M72: 14526 | N72: 14661 | O72: 14601 | P72: 16747 | Q72: 16702 | R72: 16658 | S72: 16607 | T72: 20155 | U72: 18542 | Y72: 12523 | Z72: 12604 | AA72: 13438 | AB72: 14601 | AC72: 16607
C73: Profit for the year | K73: 1187 | L73: 405 | M73: 983 | N73: 1580 | O73: 2202 | P73: 820 | Q73: 1703 | R73: 2606 | S73: 3611 | T73: 1003 | U73: 2112 | Y73: -23 | Z73: 973 | AA73: 1187 | AB73: 2202 | AC73: 3611
C74: Total Equity | D74: =SUM(D68:D73) -> 0 | E74: =SUM(E68:E73) -> 0 | F74: =SUM(F68:F73) -> 0 | G74: =SUM(G68:G73) -> 0 | H74: =SUM(H68:H73) -> 0 | I74: =SUM(I68:I73) -> 0 | J74: =SUM(J68:J73) -> 0 | K74: =SUM(K68:K73) -> 19991 | ... U74: =SUM(U68:U73) -> 27874 | Y74: 18953 | Z74: 19754 | AA74: 19991 | AB74: 22678 | AC74: 26253
C75: Total E/D | D75: =D67+D74 -> 0 | E75: =E67+E74 -> 0 | F75: =F67+F74 -> 0 | G75: =G67+G74 -> 0 | H75: =H67+H74 -> 0 | I75: =I67+I74 -> 0 | J75: =J67+J74 -> 0 | K75: =K67+K74 -> 138065 | ... U75: =U67+U74 -> 176380 | Y75: =Y67+Y74 -> 108580 | Z75: =Z67+Z74 -> 119325 | AA75: =AA67+AA74 -> 138065 | AB75: =AB67+AB74 -> 159143 | AC75: =AC67+AC74 -> 162909
C77: Cash flow SEKm
C78: Model OP | D78: =D18 -> 0 | E78: =E18 -> 0 | F78: =F18 -> 0 | G78: =G18 -> 77 | H78: =H18 -> 0 | I78: =I18 -> 0 | J78: =J18 -> 373 | K78: =K18 -> 249 | ... U78: =U18 -> 1435 | Y78: =Y18 -> -33 | Z78: =Z18 -> 1329 | AA78: =AA18 -> 1515 | AB78: =AB18 -> 2878 | AC78: =AC18 -> 4610
C79: Reported OP | L79: 535 | M79: 765 | N79: 808 | O79: 770 | P79: 1048 | Q79: 1131 | R79: 1161 | S79: 1270 | T79: 1330 | U79: =2766-T79 -> 1436 | Y79: -33 | Z79: 1329 | AA79: 1515 | AB79: 2878 | AC79: 4610
C80: Non-cash | L80: 1260 | M80: 1208 | N80: 1612 | O80: 1379 | P80: 1284 | Q80: 1427 | R80: 1260 | S80: 1297 | T80: 1260 | U80: =2515-T80 -> 1255 | Y80: 1263 | Z80: 3502 | AA80: 4554 | AB80: 5459 | AC80: 5268
C81: Paid income tax | L81: -200 | M81: -234 | N81: -69 | O81: -52 | P81: -185 | Q81: -324 | R81: -80 | S81: -80 | T81: -379 | U81: =-887-T81 -> -508 | Y81: -202 | Z81: -696 | AA81: -335 | AB81: -555 | AC81: -669
C82: Change in operating assets and liabilities | L82: -2418 | M82: -617 | N82: -3474 | O82: 5577 | P82: -6814 | Q82: -1267 | R82: -3086 | S82: -4097 | T82: -2345 | U82: =-2425-T82 -> -80 | Y82: -563 | Z82: -12646 | AA82: -8414 | AB82: -932 | AC82: -15264
C83: CFFO | D83: =SUM(D79:D82) -> 0 | E83: =SUM(E79:E82) -> 0 | F83: =SUM(F79:F82) -> 0 | G83: =SUM(G79:G82) -> 0 | H83: =SUM(H79:H82) -> 0 | I83: =SUM(I79:I82) -> 0 | J83: =SUM(J79:J82) -> 0 | K83: =SUM(K79:K82) -> 0 | ... U83: =SUM(U79:U82) -> 2103 | Y83: =SUM(Y79:Y82) -> 465 | Z83: =SUM(Z79:Z82) -> -8511 | AA83: =SUM(AA79:AA82) -> -2680 | AB83: =SUM(AB79:AB82) -> 6850 | AC83: =SUM(AC79:AC82) -> -6055
C85: Sales of shares | S85: 33 | T85: -397 | U85: =-397-T85 -> 0 | Y85: -14096 | Z85: 10301 | AC85: 33
C86: Capex | L86: -17 | M86: -21 | N86: -67 | O86: -29 | P86: -52 | Q86: -64 | R86: -39 | S86: -59 | T86: -62 | U86: =-132-T86 -> -70 | Y86: -10 | Z86: -41 | AA86: -75 | AB86: -134 | AC86: -214
C87: CFFI | D87: =SUM(D85:D86) -> 0 | E87: =SUM(E85:E86) -> 0 | F87: =SUM(F85:F86) -> 0 | G87: =SUM(G85:G86) -> 0 | H87: =SUM(H85:H86) -> 0 | I87: =SUM(I85:I86) -> 0 | J87: =SUM(J85:J86) -> 0 | K87: =SUM(K85:K86) -> 0 | ... U87: =SUM(U85:U86) -> -70 | Y87: =SUM(Y85:Y86) -> -14106 | Z87: =SUM(Z85:Z86) -> 10260 | AA87: =SUM(AA85:AA86) -> -75 | AB87: =SUM(AB85:AB86) -> -134 | AC87: =SUM(AC85:AC86) -> -181
C89: Dividends | D89: 0 | E89: 0 | F89: 0 | G89: 0 | H89: 0 | I89: 0 | J89: 0 | K89: 0 | L89: 0 | M89: 0 | N89: 0 | O89: 0 | P89: 0 | Q89: 0 | R89: 0 | S89: 0 | T89: 0 | U89: -1550
C90: Issued ordinated loans | L90: 459 | M90: 0 | N90: 0 | O90: -1 | P90: 0 | Q90: 0 | R90: 0 | S90: 0 | T90: 0 | U90: 0 | Y90: 619 | Z90: -241 | AA90: 755 | AB90: 458 | AC90: 0
C91: Repayment of subordinated loans | L91: 0 | M91: -357 | N91: 0 | O91: 0 | P91: 0 | Q91: 0 | R91: 0 | S91: 0 | T91: 0 | U91: 0 | Y91: 5371 | Z91: 562 | AA91: -561 | AB91: -357 | AC91: 0
C92: Issued Tier 1 capital instruments | L92: 800 | M92: -9 | N92: 0 | O92: 0 | P92: 0 | Q92: 0 | R92: 0 | S92: 747 | T92: 0 | U92: =744-T92 -> 744 | Y92: 1310 | Z92: 0 | AA92: 0 | AB92: 791 | AC92: 747
C93: Paid interest Tier 1 capital instruments | L93: -31 | M93: -59 | N93: -57 | O93: -55 | P93: -51 | Q93: -49 | R93: -48 | S93: -48 | T93: -58 | U93: =-117-T93 -> -59 | Y93: 0 | Z93: -81 | AA93: -121 | AB93: -202 | AC93: -196
C94: Warrants issue | L94: 0 | M94: 0 | N94: 0 | O94: 0 | P94: 0 | Q94: 0 | R94: 0 | S94: 58 | T94: 8 | U94: =10-T94 -> 2 | Y94: 9450 | Z94: 202 | AA94: -129 | AB94: 0 | AC94: 58
C95: Repurchase of warrants | L95: 0 | M95: 0 | N95: 0 | O95: 0 | P95: 0 | Q95: 0 | R95: 0 | S95: -1 | T95: 0 | U95: =0-T95 -> 0 | Y95: 0 | Z95: -311 | AA95: 0 | AB95: 0 | AC95: -1
C96: CFFF | D96: =SUM(D90:D95) -> 0 | E96: =SUM(E90:E95) -> 0 | F96: =SUM(F90:F95) -> 0 | G96: =SUM(G90:G95) -> 0 | H96: =SUM(H90:H95) -> 0 | I96: =SUM(I90:I95) -> 0 | J96: =SUM(J90:J95) -> 0 | K96: =SUM(K90:K95) -> 0 | ... T96: =SUM(T90:T95) -> -50 | U96: =SUM(U89:U95) -> -863 | Y96: =SUM(Y89:Y95) -> 16750 | Z96: =SUM(Z89:Z95) -> 131 | AA96: =SUM(AA89:AA95) -> -56 | AB96: =SUM(AB89:AB95) -> 690 | AC96: =SUM(AC89:AC95) -> 608
C98: FX | L98: 124 | M98: 24 | N98: -30 | O98: 56 | P98: -27 | Q98: -70 | R98: 15 | S98: -101 | T98: 56 | U98: =109-T98 -> 53 | Y98: 1829 | Z98: 5004 | AA98: 94 | AB98: 174 | AC98: -183
C100: CIC | D100: =D83+D87+D96 -> 0 | E100: =E83+E87+E96 -> 0 | F100: =F83+F87+F96 -> 0 | G100: =G83+G87+G96 -> 0 | H100: =H83+H87+H96 -> 0 | I100: =I83+I87+I96 -> 0 | J100: =J83+J87+J96 -> 0 | K100: =K83+K87+K96 -> 0 | ... U100: =U83+U87+U96 -> 1170 | Y100: =Y83+Y87+Y96 -> 3109 | Z100: =Z83+Z87+Z96 -> 1880 | AA100: =AA83+AA87+AA96 -> -2811 | AB100: =AB83+AB87+AB96 -> 7406 | AC100: =AC83+AC87+AC96 -> -5628

Sheet Segementer
B4: SEKm | C4: Q122 | D4: Q222 | E4: Q322 | F4: Q422 | G4: 2022 | H4: Q123 | I4: Q223 | J4: Q323 | K4: Q423 | L4: 2023 | M4: Q124 | N4: Q224 | O4: Q324 | P4: Q424 | Q4: 2024 | R4: Q125 | S4: Q225 | T4: Q325 | U4: Q425 | V4: 2025 | W4: Q126 | X4: Q226 | Y4: Q326 | Z4: Q426 | AA4: 2026
B5: Private loans
B6: Lending (SEKb) | J6: 75.1 | K6: 76.2 | M6: 79.2 | N6: 81 | O6: 84.4 | P6: 87.4 | R6: 86.8 | S6: 89.7 | T6: 92.5 | U6: 93 | W6: 96.9 | X6: 99.9
B7: y/y | H7: =(H6-C6)/C6 -> #DIV/0! | I7: =(I6-D6)/D6 -> #DIV/0! | J7: =(J6-E6)/E6 -> #DIV/0! | K7: =(K6-F6)/F6 -> #DIV/0! | M7: =(M6-H6)/H6 -> #DIV/0! | N7: =(N6-I6)/I6 -> #DIV/0! | O7: =(O6-J6)/J6 -> 0.12383489 | P7: =(P6-K6)/K6 -> 0.14698163 | R7: =(R6-M6)/M6 -> 0.095959596 | S7: =(S6-N6)/N6 -> 0.10740741 | T7: =(T6-O6)/O6 -> 0.095971564 | U7: =(U6-P6)/P6 -> 0.064073227 | W7: =(W6-R6)/R6 -> 0.11635945 | X7: =(X6-S6)/S6 -> 0.11371237
B8: Net interest margin (%) | J8: 0.084 | K8: 0.084 | M8: 0.082 | N8: 0.083 | O8: 0.085 | P8: 0.087 | R8: 0.086 | S8: 0.085 | T8: 0.088 | U8: 0.087 | W8: 0.084 | X8: 0.086
B9: Credit losses (%) | J9: 0.049 | K9: 0.051 | M9: 0.047 | N9: 0.038 | O9: 0.039 | P9: 0.046 | R9: 0.04 | S9: 0.033 | T9: 0.033 | U9: 0.033 | W9: 0.032 | X9: 0.029
B10: Income (SEKm) | J10: 1597 | K10: 1651 | M10: 1644 | N10: 1707 | O10: 1798 | P10: 1916 | Q10: =SUM(M10:P10) -> 7065 | R10: 1943 | S10: 1901 | T10: 2056 | U10: 2101 | V10: =SUM(R10:U10) -> 8001 | W10: 2104 | X10: 2190 | AA10: =SUM(W10:Z10) -> 4294
B11: C/I ratio (%) | J11: 0.25 | K11: 0.2 | M11: 0.22 | N11: 0.21 | O11: 0.2 | P11: 0.21 | R11: 0.2 | S11: 0.22 | T11: 0.21 | U11: 0.21 | W11: 0.21 | X11: 0.21
B12: Credit cards
B13: Lending (SEKb) | J13: 14 | K13: 15.2 | M13: 16.4 | N13: 173 | O13: 18 | P13: 18.2 | R13: 18.3 | S13: 18.8 | T13: 19.5 | U13: 19.6 | W13: 20.5 | X13: 21.1
B14: y/y | H14: =(H13-C13)/C13 -> #DIV/0! | I14: =(I13-D13)/D13 -> #DIV/0! | J14: =(J13-E13)/E13 -> #DIV/0! | K14: =(K13-F13)/F13 -> #DIV/0! | M14: =(M13-H13)/H13 -> #DIV/0! | N14: =(N13-I13)/I13 -> #DIV/0! | O14: =(O13-J13)/J13 -> 0.28571429 | P14: =(P13-K13)/K13 -> 0.19736842 | R14: =(R13-M13)/M13 -> 0.11585366 | S14: =(S13-N13)/N13 -> -0.89132948 | T14: =(T13-O13)/O13 -> 0.083333333 | U14: =(U13-P13)/P13 -> 0.076923077 | W14: =(W13-R13)/R13 -> 0.12021858 | X14: =(X13-S13)/S13 -> 0.12234043
B15: Net interest margin (%) | J15: 0.104 | K15: 0.098 | M15: 0.096 | N15: 0.094 | O15: 0.097 | P15: 0.106 | R15: 0.104 | S15: 0.104 | T15: 0.105 | U15: 0.11 | W15: 0.105 | X15: 0.104
B16: Credit losses (%) | J16: 0.04 | K16: 0.036 | M16: 0.035 | N16: 0.03 | O16: 0.03 | P16: 0.029 | R16: 0.029 | S16: 0.03 | T16: 0.029 | U16: 0.038 | W16: 0.031 | X16: 0.03
B17: Income (SEKm) | J17: 432 | K17: 414 | M17: 454 | N17: 501 | O17: 538 | P17: 578 | Q17: =SUM(M17:P17) -> 2071 | R17: 602 | S17: 610 | T17: 662 | U17: 636 | V17: =SUM(R17:U17) -> 2510 | W17: 642 | X17: 659 | AA17: =SUM(W17:Z17) -> 1301
B18: C/I ratio (%) | J18: 0.49 | K18: 0.45 | M18: 0.33 | N18: 0.34 | O18: 0.33 | P18: 0.31 | R18: 0.25 | S18: 0.22 | T18: 0.24 | U18: 0.28 | W18: 0.24 | X18: 0.27
B19: Secured
B20: Lending (SEKb) | J20: 17.3 | K20: 17.5 | M20: 17.7 | N20: 17.8 | O20: 17.8 | P20: 18 | R20: 18 | S20: 18.4 | T20: 18.8 | U20: 19.2 | W20: 20.1 | X20: 20.7
B21: y/y | H21: =(H20-C20)/C20 -> #DIV/0! | I21: =(I20-D20)/D20 -> #DIV/0! | J21: =(J20-E20)/E20 -> #DIV/0! | K21: =(K20-F20)/F20 -> #DIV/0! | M21: =(M20-H20)/H20 -> #DIV/0! | N21: =(N20-I20)/I20 -> #DIV/0! | O21: =(O20-J20)/J20 -> 0.028901734 | P21: =(P20-K20)/K20 -> 0.028571429 | R21: =(R20-M20)/M20 -> 0.016949153 | S21: =(S20-N20)/N20 -> 0.033707865 | T21: =(T20-O20)/O20 -> 0.056179775 | U21: =(U20-P20)/P20 -> 0.066666667 | W21: =(W20-R20)/R20 -> 0.11666667 | X21: =(X20-S20)/S20 -> 0.125
B22: Net interest margin (%) | J22: 0.038 | K22: 0.037 | M22: 0.036 | N22: 0.039 | O22: 0.038 | P22: 0.04 | R22: 0.038 | S22: 0.039 | T22: 0.039 | U22: 0.038 | W22: 0.034 | X22: 0.035
B23: Credit losses (%) | J23: 0.006 | K23: 0.001 | M23: 0.001 | N23: 0.004 | O23: 0.002 | P23: -0.001 | R23: 0.002 | S23: 0.004 | T23: 0.003 | U23: 0.004 | W23: 0 | X23: 0.002
B24: Income (SEKm) | J24: 161 | K24: 164 | M24: 159 | N24: 169 | O24: 168 | P24: 179 | Q24: =SUM(M24:P24) -> 675 | R24: 173 | S24: 175 | T24: 181 | U24: 179 | V24: =SUM(R24:U24) -> 708 | W24: 168 | X24: 174 | AA24: =SUM(W24:Z24) -> 342
B25: C/I ratio (%) | J25: 0.31 | K25: 0.31 | M25: 0.25 | N25: 0.24 | O25: 0.22 | P25: 0.26 | R25: 0.22 | S25: 0.24 | T25: 0.22 | U25: 0.26 | W25: 0.27 | X25: 0.29

Sheet Segmenter P L
B4: SEKm | C4: Q122 | D4: Q222 | E4: Q322 | F4: Q422 | G4: 2022 | H4: Q123 | I4: Q223 | J4: Q323 | K4: Q423 | L4: 2023 | M4: Q124 | N4: Q224 | O4: Q324 | P4: Q424 | Q4: 2024 | R4: Q125 | S4: Q225 | T4: Q325 | U4: Q425 | V4: 2025 | W4: Q126 | X4: Q226 | Y4: Q326 | Z4: Q426 | AA4: 2026
B5: Private loans
B6: Interest income | I6: 1960 | J6: 2234 | M6: 2425 | N6: 2526 | O6: 2618 | P6: 2688 | Q6: =SUM(M6:P6) -> 10257 | R6: 2614 | S6: 2540 | T6: 2651 | U6: 2636 | V6: =SUM(R6:U6) -> 10441 | W6: 2624 | X6: 2784 | AA6: =SUM(W6:Z6) -> 5408
B7: Interest expenses | I7: -530 | J7: -701 | M7: -836 | N7: -866 | O7: -868 | P7: -828 | Q7: =SUM(M7:P7) -> -3398 | R7: -748 | S7: -666 | T7: -639 | U7: -618 | V7: =SUM(R7:U7) -> -2671 | W7: -621 | X7: -668 | AA7: =SUM(W7:Z7) -> -1289
B8: Total net interest income | C8: =SUM(C6:C7) -> 0 | D8: =SUM(D6:D7) -> 0 | E8: =SUM(E6:E7) -> 0 | F8: =SUM(F6:F7) -> 0 | G8: =SUM(G6:G7) -> 0 | H8: =SUM(H6:H7) -> 0 | I8: =SUM(I6:I7) -> 1430 | J8: =SUM(J6:J7) -> 1533 | ... AA8: =SUM(AA6:AA7) -> 4119
B9: Commission income | I9: 52 | J9: 58 | M9: 65 | N9: 71 | O9: 64 | P9: 73 | Q9: =SUM(M9:P9) -> 273 | R9: 86 | S9: 70 | T9: 75 | U9: 99 | V9: =SUM(R9:U9) -> 330 | W9: 97 | X9: 103 | AA9: =SUM(W9:Z9) -> 200
B10: Commision expenses | I10: 0 | J10: 0 | M10: -5 | N10: -8 | O10: -6 | P10: -6 | Q10: =SUM(M10:P10) -> -25 | R10: -7 | S10: -7 | T10: -6 | U10: -6 | V10: =SUM(R10:U10) -> -26 | W10: -5 | X10: -7 | AA10: =SUM(W10:Z10) -> -12
B11: net profit from finaancial trans | I11: -11 | J11: 5 | M11: -6 | N11: -16 | O11: -11 | P11: -11 | Q11: =SUM(M11:P11) -> -44 | R11: -1 | S11: -37 | T11: -25 | U11: -10 | V11: =SUM(R11:U11) -> -73 | W11: 9 | X11: -22 | AA11: =SUM(W11:Z11) -> -13
B12: Total operating income | C12: =SUM(C8:C11) -> 0 | D12: =SUM(D8:D11) -> 0 | E12: =SUM(E8:E11) -> 0 | F12: =SUM(F8:F11) -> 0 | G12: =SUM(G8:G11) -> 0 | H12: =SUM(H8:H11) -> 0 | I12: =SUM(I8:I11) -> 1471 | J12: =SUM(J8:J11) -> 1596 | ... AA12: =SUM(AA8:AA11) -> 4294
B13: General admin expenses | I13: -255 | J13: -240 | M13: -286 | N13: -318 | O13: -240 | P13: -300 | Q13: =SUM(M13:P13) -> -1144 | R13: -273 | S13: -301 | T13: -313 | U13: -337 | V13: =SUM(R13:U13) -> -1224 | W13: -337 | X13: -335 | AA13: =SUM(W13:Z13) -> -672
B14: D/A/I | I14: -9 | J14: -10 | M14: -11 | N14: -13 | O14: -10 | P14: -12 | Q14: =SUM(M14:P14) -> -46 | R14: -13 | S14: -13 | T14: -15 | U14: -16 | V14: =SUM(R14:U14) -> -57 | W14: -18 | X14: -20 | AA14: =SUM(W14:Z14) -> -38
B15: Other operating expenses | I15: -138 | J15: -145 | M15: -115 | N15: -105 | O15: -114 | P15: -95 | Q15: =SUM(M15:P15) -> -429 | R15: -97 | S15: -96 | T15: -104 | U15: -92 | V15: =SUM(R15:U15) -> -389 | W15: -96 | X15: -98 | AA15: =SUM(W15:Z15) -> -194
B16: Profit before credit losses | C16: =SUM(C12:C15) -> 0 | D16: =SUM(D12:D15) -> 0 | E16: =SUM(E12:E15) -> 0 | F16: =SUM(F12:F15) -> 0 | G16: =SUM(G12:G15) -> 0 | H16: =SUM(H12:H15) -> 0 | I16: =SUM(I12:I15) -> 1069 | J16: =SUM(J12:J15) -> 1201 | ... AA16: =SUM(AA12:AA15) -> 3390
B17: Net credit losses | I17: -679 | J17: -896 | M17: -915 | N17: -759 | O17: -815 | P17: -985 | Q17: =SUM(M17:P17) -> -3474 | R17: -865 | S17: -728 | T17: -744 | U17: -763 | V17: =SUM(R17:U17) -> -3100 | W17: -748 | X17: -703 | AA17: =SUM(W17:Z17) -> -1451
B18: operating profit | C18: =SUM(C16:C17) -> 0 | D18: =SUM(D16:D17) -> 0 | E18: =SUM(E16:E17) -> 0 | F18: =SUM(F16:F17) -> 0 | G18: =SUM(G16:G17) -> 0 | H18: =SUM(H16:H17) -> 0 | I18: =SUM(I16:I17) -> 390 | J18: =SUM(J16:J17) -> 305 | ... AA18: =SUM(AA16:AA17) -> 1939
B19: Tax | P19: -101 | R19: -151 | S19: -168 | T19: -195 | U19: -187 | V19: =SUM(R19:U19) -> -701 | W19: -223 | X19: -235 | AA19: =SUM(W19:Z19) -> -458
B20: Profit attributable to Tier 1 cap | P20: -41 | R20: -37 | S20: -37 | T20: -37 | U20: -41 | V20: =SUM(R20:U20) -> -152 | W20: -44 | X20: -46 | AA20: =SUM(W20:Z20) -> -90
B21: Net income | R21: =SUM(R18:R20) -> 508 | S21: =SUM(S18:S20) -> 557 | T21: =SUM(T18:T20) -> 648 | U21: =SUM(U18:U20) -> 665 | V21: =SUM(V18:V20) -> 2378 | W21: =SUM(W18:W20) -> 638 | X21: =SUM(X18:X20) -> 753 | Y21: =SUM(Y18:Y20) -> 0 | ... AA21: =SUM(AA18:AA20) -> 1391
B22: Shares | R22: 500 | S22: 500 | T22: 500 | U22: 500 | V22: 500 | W22: 500 | X22: 500 | Y22: 500 | Z22: 500 | AA22: 500
B23: EPS | R23: =R21/R22 -> 1.016 | S23: =S21/S22 -> 1.114 | T23: =T21/T22 -> 1.296 | U23: =U21/U22 -> 1.33 | V23: =V21/V22 -> 4.756 | W23: =W21/W22 -> 1.276 | X23: =X21/X22 -> 1.506 | Y23: =Y21/Y22 -> 0 | ... AA23: =AA21/AA22 -> 2.782
B25: NIM | J25: 0.084 | O25: 0.085 | P25: 0.087 | R25: 0.086 | S25: 0.085 | T25: 0.088 | U25: 0.087 | W25: 0.084 | X25: 0.086
B26: C/I | J26: 0.247 | O26: 0.202 | P26: 0.213 | R26: 0.197 | S26: 0.216 | T26: 0.21 | U26: 0.212 | W26: 0.214 | X26: 0.207
B27: Cost of risk | J27: 0.049 | O27: 0.039 | P27: 0.046 | R27: 0.04 | S27: 0.033 | T27: 0.033 | U27: 0.033 | W27: 0.032 | X27: 0.029
B28: ROTE | J28: 0.12 | O28: 0.188 | P28: 0.164 | R28: 0.205 | S28: 0.212 | T28: 0.232 | U28: 0.224 | W28: 0.204 | X28: 0.239
B30: Credit cards
B31: Interest income | I31: 398 | J31: 445 | M31: 511 | N31: 536 | O31: 574 | P31: 626 | Q31: =SUM(M31:P31) -> 2247 | R31: 632 | S31: 634 | T31: 652 | U31: 680 | V31: =SUM(R31:U31) -> 2598 | W31: 669 | X31: 700 | AA31: =SUM(W31:Z31) -> 1369
B32: Interest expenses | I32: -71 | J32: -97 | M32: -134 | N32: -140 | O32: -145 | P32: -145 | Q32: =SUM(M32:P32) -> -564 | R32: -159 | S32: -151 | T32: -148 | U32: -145 | V32: =SUM(R32:U32) -> -603 | W32: -144 | X32: -157 | AA32: =SUM(W32:Z32) -> -301
B33: Total net interest income | C33: =SUM(C31:C32) -> 0 | D33: =SUM(D31:D32) -> 0 | E33: =SUM(E31:E32) -> 0 | F33: =SUM(F31:F32) -> 0 | G33: =SUM(G31:G32) -> 0 | H33: =SUM(H31:H32) -> 0 | I33: =SUM(I31:I32) -> 327 | J33: =SUM(J31:J32) -> 348 | ... AA33: =SUM(AA31:AA32) -> 1068
B34: Commission income | I34: 141 | J34: 141 | M34: 139 | N34: 175 | O34: 173 | P34: 169 | Q34: =SUM(M34:P34) -> 656 | R34: 195 | S34: 214 | T34: 230 | U34: 184 | V34: =SUM(R34:U34) -> 823 | W34: 198 | X34: 213 | AA34: =SUM(W34:Z34) -> 411
B35: Commision expenses | I35: -46 | J35: -58 | M35: -61 | N35: -69 | O35: -63 | P35: -70 | Q35: =SUM(M35:P35) -> -263 | R35: -66 | S35: -79 | T35: -67 | U35: -80 | V35: =SUM(R35:U35) -> -292 | W35: -84 | X35: -91 | AA35: =SUM(W35:Z35) -> -175
B36: net profit from finaancial trans | I36: -2 | J36: 1 | M36: -1 | N36: -1 | O36: -2 | P36: -3 | Q36: =SUM(M36:P36) -> -7 | R36: 0 | S36: -8 | T36: -5 | U36: -3 | V36: =SUM(R36:U36) -> -16 | W36: 2 | X36: -5 | AA36: =SUM(W36:Z36) -> -3
B37: Total operating income | C37: =SUM(C33:C36) -> 0 | D37: =SUM(D33:D36) -> 0 | E37: =SUM(E33:E36) -> 0 | F37: =SUM(F33:F36) -> 0 | G37: =SUM(G33:G36) -> 0 | H37: =SUM(H33:H36) -> 0 | I37: =SUM(I33:I36) -> 420 | J37: =SUM(J33:J36) -> 432 | ... AA37: =SUM(AA33:AA36) -> 1301
B38: General admin expenses | I38: -57 | J38: -53 | M38: -64 | N38: -61 | O38: -61 | P38: -75 | Q38: =SUM(M38:P38) -> -261 | R38: -67 | S38: -57 | T38: -54 | U38: -63 | V38: =SUM(R38:U38) -> -241 | W38: -61 | X38: -67 | AA38: =SUM(W38:Z38) -> -128
B39: D/A/I | I39: -22 | J39: -4 | M39: -3 | N39: -2 | O39: -6 | P39: -4 | Q39: =SUM(M39:P39) -> -15 | R39: -5 | S39: -4 | T39: -5 | U39: -5 | V39: =SUM(R39:U39) -> -19 | W39: -5 | X39: -6 | AA39: =SUM(W39:Z39) -> -11
B40: Other operating expenses | I40: -127 | J40: -155 | M40: -81 | N40: -110 | O40: -112 | P40: -97 | Q40: =SUM(M40:P40) -> -400 | R40: -97 | S40: -70 | T40: -111 | U40: -110 | V40: =SUM(R40:U40) -> -388 | W40: -86 | X40: -106 | AA40: =SUM(W40:Z40) -> -192
B41: Profit before credit losses | C41: =SUM(C37:C40) -> 0 | D41: =SUM(D37:D40) -> 0 | E41: =SUM(E37:E40) -> 0 | F41: =SUM(F37:F40) -> 0 | G41: =SUM(G37:G40) -> 0 | H41: =SUM(H37:H40) -> 0 | I41: =SUM(I37:I40) -> 214 | J41: =SUM(J37:J40) -> 220 | ... AA41: =SUM(AA37:AA40) -> 970
B42: Net credit losses | I42: -90 | J42: -135 | M42: -137 | N42: -128 | O42: -131 | P42: -130 | Q42: =SUM(M42:P42) -> -526 | R42: -133 | S42: -137 | T42: -140 | U42: -185 | V42: =SUM(R42:U42) -> -595 | W42: -155 | X42: -155 | AA42: =SUM(W42:Z42) -> -310
B43: operating profit | C43: =SUM(C41:C42) -> 0 | D43: =SUM(D41:D42) -> 0 | E43: =SUM(E41:E42) -> 0 | F43: =SUM(F41:F42) -> 0 | G43: =SUM(G41:G42) -> 0 | H43: =SUM(H41:H42) -> 0 | I43: =SUM(I41:I42) -> 124 | J43: =SUM(J41:J42) -> 85 | ... AA43: =SUM(AA41:AA42) -> 660
B44: Tax | P44: -52 | R44: -65 | S44: -75 | T44: -78 | U44: -57 | V44: =SUM(R44:U44) -> -275 | W44: -83 | X44: -74 | AA44: =SUM(W44:Z44) -> -157
B45: Profit attributable to Tier 1 cap | P45: -8 | R45: -8 | S45: -8 | T45: -8 | U45: -9 | V45: =SUM(R45:U45) -> -33 | W45: -9 | X45: -9 | AA45: =SUM(W45:Z45) -> -18
B46: Net income | R46: =SUM(R43:R45) -> 227 | S46: =SUM(S43:S45) -> 259 | T46: =SUM(T43:T45) -> 266 | U46: =SUM(U43:U45) -> 207 | V46: =SUM(V43:V45) -> 959 | W46: =SUM(W43:W45) -> 242 | X46: =SUM(X43:X45) -> 243 | Y46: =SUM(Y43:Y45) -> 0 | ... AA46: =SUM(AA43:AA45) -> 485
B47: Shares | R47: 500 | S47: 500 | T47: 500 | U47: 500 | V47: 500 | W47: 500 | X47: 500 | Y47: 500 | Z47: 500 | AA47: 500
B48: EPS | R48: =R46/R47 -> 0.454 | S48: =S46/S47 -> 0.518 | T48: =T46/T47 -> 0.532 | U48: =U46/U47 -> 0.414 | V48: =V46/V47 -> 1.918 | W48: =W46/W47 -> 0.484 | X48: =X46/X47 -> 0.486 | Y48: =Y46/Y47 -> 0 | ... AA48: =AA46/AA47 -> 0.97
B50: NIM | J50: 0.104 | O50: 0.097 | P50: 0.106 | R50: 0.104 | S50: 0.104 | T50: 0.105 | U50: 0.11 | W50: 0.105 | X50: 0.104
B51: C/I | J51: 0.492 | O51: 0.332 | P51: 0.306 | R51: 0.279 | S51: 0.216 | T51: 0.256 | U51: 0.279 | W51: 0.236 | X51: 0.272
B52: Cost of risk | J52: 0.04 | O52: 0.03 | P52: 0.029 | R52: 0.029 | S52: 0.03 | T52: 0.029 | U52: 0.038 | W52: 0.031 | X52: 0.03
B53: ROTE | J53: 0.187 | O53: 0.345 | P53: 0.435 | R53: 0.447 | S53: 0.476 | T53: 0.461 | U53: 0.337 | W53: 0.385 | X53: 0.388
B55: Secured
B56: Interest income | I56: 321 | J56: 358 | M56: 381 | N56: 391 | O56: 379 | P56: 365 | Q56: =SUM(M56:P56) -> 1516 | R56: 331 | S56: 325 | T56: 326 | U56: 321 | V56: =SUM(R56:U56) -> 1303 | W56: 312 | X56: 338 | AA56: =SUM(W56:Z56) -> 650
B57: Interest expenses | I57: -163 | J57: -198 | M57: -222 | N57: -221 | O57: -210 | P57: -188 | Q57: =SUM(M57:P57) -> -841 | R57: -159 | S57: -148 | T57: -144 | U57: -143 | V57: =SUM(R57:U57) -> -594 | W57: -145 | X57: -161 | AA57: =SUM(W57:Z57) -> -306
B58: Total net interest income | C58: =SUM(C56:C57) -> 0 | D58: =SUM(D56:D57) -> 0 | E58: =SUM(E56:E57) -> 0 | F58: =SUM(F56:F57) -> 0 | G58: =SUM(G56:G57) -> 0 | H58: =SUM(H56:H57) -> 0 | I58: =SUM(I56:I57) -> 158 | J58: =SUM(J56:J57) -> 160 | ... AA58: =SUM(AA56:AA57) -> 344
B59: Commission income | I59: 1 | J59: 1 | M59: 1 | N59: 1 | O59: 1 | P59: 3 | Q59: =SUM(M59:P59) -> 6 | R59: 1 | S59: 1 | T59: 1 | U59: 3 | V59: =SUM(R59:U59) -> 6 | W59: 1 | X59: 1 | AA59: =SUM(W59:Z59) -> 2
B60: Commision expenses | I60: 0 | J60: 0 | M60: 0 | N60: -1 | O60: 0 | P60: -1 | Q60: =SUM(M60:P60) -> -2 | R60: 0 | S60: 0 | T60: 0 | U60: 0 | V60: =SUM(R60:U60) -> 0 | W60: 0 | X60: 0 | AA60: =SUM(W60:Z60) -> 0
B61: net profit from finaancial trans | I61: -1 | J61: 1 | M61: -1 | N61: -2 | O61: -1 | P61: -1 | Q61: =SUM(M61:P61) -> -5 | R61: 0 | S61: -3 | T61: -2 | U61: -2 | V61: =SUM(R61:U61) -> -7 | W61: 0 | X61: -3 | AA61: =SUM(W61:Z61) -> -3
B62: Total operating income | C62: =SUM(C58:C61) -> 0 | D62: =SUM(D58:D61) -> 0 | E62: =SUM(E58:E61) -> 0 | F62: =SUM(F58:F61) -> 0 | G62: =SUM(G58:G61) -> 0 | H62: =SUM(H58:H61) -> 0 | I62: =SUM(I58:I61) -> 158 | J62: =SUM(J58:J61) -> 162 | ... AA62: =SUM(AA58:AA61) -> 343
B63: General admin expenses | I63: -39 | J63: -35 | M63: -37 | N63: -41 | O63: -33 | P63: -39 | Q63: =SUM(M63:P63) -> -150 | R63: -31 | S63: -34 | T63: -31 | U63: -37 | V63: =SUM(R63:U63) -> -133 | W63: -36 | X63: -39 | AA63: =SUM(W63:Z63) -> -75
B64: D/A/I | I64: -1 | J64: 0 | M64: -1 | N64: -1 | O64: -1 | P64: -1 | Q64: =SUM(M64:P64) -> -4 | R64: -1 | S64: -1 | T64: -1 | U64: -1 | V64: =SUM(R64:U64) -> -4 | W64: -1 | X64: -2 | AA64: =SUM(W64:Z64) -> -3
B65: Other operating expenses | I65: -19 | J65: -15 | M65: -8 | N65: -6 | O65: -4 | P65: -7 | Q65: =SUM(M65:P65) -> -25 | R65: -7 | S65: -6 | T65: -7 | U65: -8 | V65: =SUM(R65:U65) -> -28 | W65: -8 | X65: -9 | AA65: =SUM(W65:Z65) -> -17
B66: Profit before credit losses | C66: =SUM(C62:C65) -> 0 | D66: =SUM(D62:D65) -> 0 | E66: =SUM(E62:E65) -> 0 | F66: =SUM(F62:F65) -> 0 | G66: =SUM(G62:G65) -> 0 | H66: =SUM(H62:H65) -> 0 | I66: =SUM(I62:I65) -> 99 | J66: =SUM(J62:J65) -> 112 | ... AA66: =SUM(AA62:AA65) -> 248
B67: Net credit losses | I67: -5 | J67: -23 | M67: -2 | N67: -16 | O67: -8 | P67: 3 | Q67: =SUM(M67:P67) -> -23 | R67: -8 | S67: -20 | T67: -16 | U67: -20 | V67: =SUM(R67:U67) -> -64 | W67: -2 | X67: -12 | AA67: =SUM(W67:Z67) -> -14
B68: operating profit | C68: =SUM(C66:C67) -> 0 | D68: =SUM(D66:D67) -> 0 | E68: =SUM(E66:E67) -> 0 | F68: =SUM(F66:F67) -> 0 | G68: =SUM(G66:G67) -> 0 | H68: =SUM(H66:H67) -> 0 | I68: =SUM(I66:I67) -> 94 | J68: =SUM(J66:J67) -> 89 | ... AA68: =SUM(AA66:AA67) -> 234
B69: Tax | R69: -27 | S69: -25 | T69: -28 | U69: -24 | V69: =SUM(R69:U69) -> -104 | W69: -30 | X69: -25 | AA69: =SUM(W69:Z69) -> -55
B70: Profit attributable to Tier 1 cap | R70: -4 | S70: -3 | T70: -3 | U70: -3 | V70: =SUM(R70:U70) -> -13 | W70: -3 | X70: -4 | AA70: =SUM(W70:Z70) -> -7
B71: Net income | R71: =SUM(R68:R70) -> 95 | S71: =SUM(S68:S70) -> 86 | T71: =SUM(T68:T70) -> 95 | U71: =SUM(U68:U70) -> 86 | V71: =SUM(V68:V70) -> 362 | W71: =SUM(W68:W70) -> 88 | X71: =SUM(X68:X70) -> 84 | Y71: =SUM(Y68:Y70) -> 0 | ... AA71: =SUM(AA68:AA70) -> 172
B72: Shares | R72: 500 | S72: 500 | T72: 500 | U72: 500 | V72: 500 | W72: 500 | X72: 500 | Y72: 500 | Z72: 500 | AA72: 500
B73: EPS | R73: =R71/R72 -> 0.19 | S73: =S71/S72 -> 0.172 | T73: =T71/T72 -> 0.19 | U73: =U71/U72 -> 0.172 | V73: =V71/V72 -> 0.724 | W73: =W71/W72 -> 0.176 | X73: =X71/X72 -> 0.168 | Y73: =Y71/Y72 -> 0 | ... AA73: =AA71/AA72 -> 0.344
B75: NIM | J75: 0.038 | O75: 0.038 | P75: 0.04 | R75: 0.038 | S75: 0.039 | T75: 0.039 | U75: 0.038 | W75: 0.034 | X75: 0.035
B76: C/I | J76: 0.312 | O76: 0.222 | P76: 0.258 | R76: 0.222 | S76: 0.237 | T76: 0.216 | U76: 0.257 | W76: 0.272 | X76: 0.288
B77: Cost of risk | J77: 0.006 | O77: 0.002 | P77: -0.001 | R77: 0.002 | S77: 0.004 | T77: 0.003 | U77: 0.004 | W77: 0 | X77: 0.002
B78: ROTE | J78: 0.325 | O78: 0.38 | P78: 0.453 | R78: 0.446 | S78: 0.43 | T78: 0.457 | U78: 0.388 | W78: 0.366 | X78: 0.343

Sheet Kapitalbro
A1: Kapitalbro — kan NOBA finansiere veksten selv?
B3: SEKm
B4: Forutsetninger | C4: FY2025 | D4: FY2026 | E4: FY2027 | F4: FY2028 | G4: FY2029 | H4: FY2030 | I4: FY2031 | J4: FY2032 | K4: FY2033 | L4: FY2034 | M4: FY2035
B5: Utlånsvekst | D5: =Modell!AD40 -> 0.123 | E5: =Modell!AE40 -> 0.12 | F5: =Modell!AF40 -> 0.12 | G5: =Modell!AG40 -> 0.12 | H5: =Modell!AH40 -> 0.12 | I5: =Modell!AI40 -> 0.1 | J5: =Modell!AJ40 -> 0.1 | K5: =Modell!AK40 -> 0.1 | ... M5: =Modell!AM40 -> 0.1
B6: Mål CET1-ratio | D6: 0.135 | E6: 0.135 | F6: 0.135 | G6: 0.135 | H6: 0.135 | I6: 0.135 | J6: 0.135 | K6: 0.135 | L6: 0.135 | M6: 0.135
B7: Resultat til aksjonærer | D7: =Modell!AD20 -> 4176.784 | E7: =Modell!AE20 -> 5071.0624 | F7: =Modell!AF20 -> 5755.3346 | G7: =Modell!AG20 -> 6416.7237 | H7: =Modell!AH20 -> 7184.7191 | I7: =Modell!AI20 -> 8031.4889 | J7: =Modell!AJ20 -> 8929.3507 | K7: =Modell!AK20 -> 9792.5656 | ... M7: =Modell!AM20 -> 11782.825
B8: REA / utlån | D8: 0.787 | E8: 0.787 | F8: 0.787 | G8: 0.787 | H8: 0.787 | I8: 0.787 | J8: 0.787 | K8: 0.787 | L8: 0.787 | M8: 0.787
B10: Beregnet
B11: Utlån til publikum | C11: 132341 | D11: =C11*(1+D5) -> 148618.94 | E11: =D11*(1+E5) -> 166453.22 | F11: =E11*(1+F5) -> 186427.6 | G11: =F11*(1+G5) -> 208798.91 | H11: =G11*(1+H5) -> 233854.78 | I11: =H11*(1+I5) -> 257240.26 | J11: =I11*(1+J5) -> 282964.29 | K11: =J11*(1+K5) -> 311260.72 | ... M11: =L11*(1+M5) -> 376625.47
B12: REA | C12: 104237 | D12: =D11*D8 -> 116963.11 | E12: =E11*E8 -> 130998.68 | F12: =F11*F8 -> 146718.52 | G12: =G11*G8 -> 164324.75 | H12: =H11*H8 -> 184043.72 | I12: =I11*I8 -> 202448.09 | J12: =J11*J8 -> 222692.9 | K12: =K11*K8 -> 244962.18 | ... M12: =M11*M8 -> 296404.24
B13: Endring REA | D13: =D12-C12 -> 12726.108 | E13: =E12-D12 -> 14035.573 | F13: =F12-E12 -> 15719.842 | G13: =G12-F12 -> 17606.223 | H13: =H12-G12 -> 19718.969 | I13: =I12-H12 -> 18404.372 | J13: =J12-I12 -> 20244.809 | K13: =K12-J12 -> 22269.29 | ... M13: =M12-L12 -> 26945.84
B14: Nødvendig CET1-kapital | C14: 14246 | D14: =D12*D6 -> 15790.02 | E14: =E12*E6 -> 17684.822 | F14: =F12*F6 -> 19807.001 | G14: =G12*G6 -> 22183.841 | H14: =H12*H6 -> 24845.902 | I14: =I12*I6 -> 27330.492 | J14: =J12*J6 -> 30063.541 | K14: =K12*K6 -> 33069.895 | ... M14: =M12*M6 -> 40014.573
B15: CET1-ratio (kontroll) | C15: =C14/C12 -> 0.13666932 | D15: =D14/D12 -> 0.135 | E15: =E14/E12 -> 0.135 | F15: =F14/F12 -> 0.135 | G15: =G14/G12 -> 0.135 | H15: =H14/H12 -> 0.135 | I15: =I14/I12 -> 0.135 | J15: =J14/J12 -> 0.135 | ... M15: =M14/M12 -> 0.135
B16: Må holdes tilbake | D16: =D14-C14 -> 1544.0196 | E16: =E14-D14 -> 1894.8024 | F16: =F14-E14 -> 2122.1786 | G16: =G14-F14 -> 2376.8401 | H16: =H14-G14 -> 2662.0609 | I16: =I14-H14 -> 2484.5902 | J16: =J14-I14 -> 2733.0492 | K16: =K14-J14 -> 3006.3541 | ... M16: =M14-L14 -> 3637.6884
B17: Kan deles ut | D17: =D7-D16 -> 2632.7644 | E17: =E7-E16 -> 3176.26 | F17: =F7-F16 -> 3633.1559 | G17: =G7-G16 -> 4039.8837 | H17: =H7-H16 -> 4522.6582 | I17: =I7-I16 -> 5546.8988 | J17: =J7-J16 -> 6196.3015 | K17: =K7-K16 -> 6786.2115 | ... M17: =M7-M16 -> 8145.1363
B18: Maks Utbyttekapasistet | D18: =D17/D7 -> 0.63033291 | E18: =E17/E7 -> 0.62635002 | F18: =F17/F7 -> 0.63126755 | G18: =G17/G7 -> 0.62958666 | H18: =H17/H7 -> 0.62948296 | I18: =I17/I7 -> 0.69064389 | J18: =J17/J7 -> 0.69392521 | K18: =K17/K7 -> 0.69299628 | ... M18: =M17/M7 -> 0.69127195
B20: Potensial yield% | D20: =D17/Modell!$B$6 -> 0.061227079 | E20: =E17/Modell!$B$6 -> 0.073866513 | F20: =F17/Modell!$B$6 -> 0.084491998 | G20: =G17/Modell!$B$6 -> 0.093950783 | H20: =H17/Modell!$B$6 -> 0.1051781 | I20: =I17/Modell!$B$6 -> 0.12899765 | J20: =J17/Modell!$B$6 -> 0.14410003 | K20: =K17/Modell!$B$6 -> 0.15781887 | ... M20: =M17/Modell!$B$6 -> 0.18942177

Sheet Kvalitet bok (Gross)
A1: Gross
A2: Fordeling av låneboken
B4: SEKm | C4: Q122 | D4: Q222 | E4: Q322 | F4: Q422 | G4: Q123 | H4: Q223 | I4: Q323 | J4: Q423 | K4: Q124 | L4: Q224 | M4: Q324 | N4: Q424 | O4: Q125 | P4: Q225 | Q4: Q325 | R4: Q425 | S4: Q126 | T4: Q226 | U4: Q326 | V4: Q426
B5: Sweden
B6: Stage 1 | J6: 41662 | K6: 41849 | L6: 42633 | M6: 44048 | N6: 45074 | O6: 45643 | P6: 46963 | Q6: 48945 | R6: 50413 | S6: 52514 | T6: 53686
B7: stage 2 | J7: 2068 | K7: 2382 | L7: 2241 | M7: 2289 | N7: 2351 | O7: 2310 | P7: 2370 | Q7: 2417 | R7: 2437 | S7: 2589 | T7: 2675
B8: stage 3 | J8: 4334 | K8: 5072 | L8: 5516 | M8: 6039 | N8: 6481 | O8: 6289 | P8: 6549 | Q8: 6889 | R8: 7109 | S8: 7311 | T8: 7527
B9: Finland
B10: Stage 1 | J10: 25283 | K10: 26927 | L10: 26881 | M10: 27812 | N10: 28858 | O10: 27899 | P10: 29280 | Q10: 29705 | R10: 29529 | S10: 30343 | T10: 31197
B11: stage 2 | J11: 2213 | K11: 2263 | L11: 2192 | M11: 2049 | N11: 2274 | O11: 2183 | P11: 2183 | Q11: 1986 | R11: 1979 | S11: 1970 | T11: 1888
B12: stage 3 | J12: 4805 | K12: 5747 | L12: 6406 | M12: 7044 | N12: 7638 | O12: 7469 | P12: 8276 | Q12: 8736 | R12: 8367 | S12: 9044 | T12: 9712
B13: Norway
B14: Stage 1 | J14: 21864 | K14: 22147 | L14: 23051 | M14: 23552 | N14: 24287 | O14: 23945 | P14: 24108 | Q14: 24579 | R14: 24184 | S14: 26076 | T14: 27021
B15: stage 2 | J15: 1552 | K15: 1630 | L15: 1641 | M15: 1533 | N15: 1627 | O15: 1599 | P15: 1431 | Q15: 1568 | R15: 1413 | S15: 1559 | T15: 1530
B16: stage 3 | J16: 3289 | K16: 3550 | L16: 3683 | M16: 3711 | N16: 3856 | O16: 4023 | P16: 3554 | Q16: 3592 | R16: 3689 | S16: 4080 | T16: 4199
B17: Denmark
B18: Stage 1 | J18: 6634 | K18: 6922 | L18: 7307 | M18: 7820 | N18: 7942 | O18: 8100 | P18: 8760 | Q18: 9287 | R18: 9184 | S18: 9930 | T18: 10474
B19: stage 2 | J19: 312 | K19: 292 | L19: 307 | M19: 479 | N19: 503 | O19: 530 | P19: 543 | Q19: 430 | R19: 434 | S19: 471 | T19: 472
B20: stage 3 | J20: 722 | K20: 797 | L20: 695 | M20: 744 | N20: 798 | O20: 815 | P20: 716 | Q20: 781 | R20: 821 | S20: 899 | T20: 920
B21: Germany/Spain
B22: Stage 1 | J22: 2551 | K22: 2836 | L22: 2848 | M22: 2899 | N22: 2151 | O22: 2060 | P22: 2136 | Q22: 2275 | R22: 2235 | S22: 2283 | T22: 2314
B23: stage 2 | J23: 101 | K23: 98 | L23: 95 | M23: 108 | N23: 83 | O23: 86 | P23: 84 | Q23: 80 | R23: 75 | S23: 81 | T23: 96
B24: stage 3 | J24: 542 | K24: 580 | L24: 563 | M24: 554 | N24: 538 | O24: 491 | P24: 468 | Q24: 442 | R24: 444 | S24: 484 | T24: 534
B26: Stage 1 total | C26: =C6+C10+C14+C18+C22 -> 0 | D26: =D6+D10+D14+D18+D22 -> 0 | E26: =E6+E10+E14+E18+E22 -> 0 | F26: =F6+F10+F14+F18+F22 -> 0 | G26: =G6+G10+G14+G18+G22 -> 0 | H26: =H6+H10+H14+H18+H22 -> 0 | I26: =I6+I10+I14+I18+I22 -> 0 | J26: =J6+J10+J14+J18+J22 -> 97994 | ... T26: =T6+T10+T14+T18+T22 -> 124692
B27: Stage 2 total | C27: =C7+C11+C15+C19+C23 -> 0 | D27: =D7+D11+D15+D19+D23 -> 0 | E27: =E7+E11+E15+E19+E23 -> 0 | F27: =F7+F11+F15+F19+F23 -> 0 | G27: =G7+G11+G15+G19+G23 -> 0 | H27: =H7+H11+H15+H19+H23 -> 0 | I27: =I7+I11+I15+I19+I23 -> 0 | J27: =J7+J11+J15+J19+J23 -> 6246 | ... T27: =T7+T11+T15+T19+T23 -> 6661
B28: Stage 3 total | C28: =C8+C12+C16+C20+C24 -> 0 | D28: =D8+D12+D16+D20+D24 -> 0 | E28: =E8+E12+E16+E20+E24 -> 0 | F28: =F8+F12+F16+F20+F24 -> 0 | G28: =G8+G12+G16+G20+G24 -> 0 | H28: =H8+H12+H16+H20+H24 -> 0 | I28: =I8+I12+I16+I20+I24 -> 0 | J28: =J8+J12+J16+J20+J24 -> 13692 | ... T28: =T8+T12+T16+T20+T24 -> 22892
B29: SUM | C29: =SUM(C26:C28) -> 0 | D29: =SUM(D26:D28) -> 0 | E29: =SUM(E26:E28) -> 0 | F29: =SUM(F26:F28) -> 0 | G29: =SUM(G26:G28) -> 0 | H29: =SUM(H26:H28) -> 0 | I29: =SUM(I26:I28) -> 0 | J29: =SUM(J26:J28) -> 117932 | ... T29: =SUM(T26:T28) -> 154245
B30: Stage 1 % | C30: =C26/C29 -> #DIV/0! | D30: =D26/D29 -> #DIV/0! | E30: =E26/E29 -> #DIV/0! | F30: =F26/F29 -> #DIV/0! | G30: =G26/G29 -> #DIV/0! | H30: =H26/H29 -> #DIV/0! | I30: =I26/I29 -> #DIV/0! | J30: =J26/J29 -> 0.83093647 | ... T30: =T26/T29 -> 0.80840222
B31: Stage 2 % | C31: =C27/C29 -> #DIV/0! | D31: =D27/D29 -> #DIV/0! | E31: =E27/E29 -> #DIV/0! | F31: =F27/F29 -> #DIV/0! | G31: =G27/G29 -> #DIV/0! | H31: =H27/H29 -> #DIV/0! | I31: =I27/I29 -> #DIV/0! | J31: =J27/J29 -> 0.052962724 | ... T31: =T27/T29 -> 0.043184544
B32: Stage 3 % | C32: =C28/C29 -> #DIV/0! | D32: =D28/D29 -> #DIV/0! | E32: =E28/E29 -> #DIV/0! | F32: =F28/F29 -> #DIV/0! | G32: =G28/G29 -> #DIV/0! | H32: =H28/H29 -> #DIV/0! | I32: =I28/I29 -> #DIV/0! | J32: =J28/J29 -> 0.1161008 | ... T32: =T28/T29 -> 0.14841324
B33: SUM | C33: =SUM(C30:C32) -> #DIV/0! | D33: =SUM(D30:D32) -> #DIV/0! | E33: =SUM(E30:E32) -> #DIV/0! | F33: =SUM(F30:F32) -> #DIV/0! | G33: =SUM(G30:G32) -> #DIV/0! | H33: =SUM(H30:H32) -> #DIV/0! | I33: =SUM(I30:I32) -> #DIV/0! | J33: =SUM(J30:J32) -> 1 | ... T33: =SUM(T30:T32) -> 1
B37: SEKm
B38: Private loans
B39: Stage 1 | J39: 68055 | K39: 69874 | L39: 71174 | M39: 74098 | N39: 76267 | O39: 75738 | P39: 78537 | Q39: 81109 | R39: 81540 | S39: 84651 | T39: 87266
B40: stage 2 | J40: 5048 | K40: 5392 | L40: 5152 | M40: 5046 | N40: 5328 | O40: 5215 | P40: 5125 | Q40: 4915 | R40: 4811 | S40: 5030 | T40: 4998
B41: stage 3 | J41: 12141 | K41: 13854 | L41: 14889 | M41: 15962 | N41: 17098 | O41: 16733 | P41: 17233 | Q41: 18046 | R41: 17998 | S41: 18979 | T41: 19930
B42: Secured
B43: Stage 1 | J43: 15671 | K43: 15456 | L43: 15323 | M43: 15228 | N43: 15240 | O43: 15111 | P43: 15369 | Q43: 15706 | R43: 16009 | S43: 16644 | T43: 17014
B44: stage 2 | J44: 568 | K44: 617 | L44: 629 | M44: 607 | N44: 630 | O44: 608 | P44: 628 | Q44: 673 | R44: 601 | S44: 676 | T44: 749
B45: stage 3 | J45: 485 | K45: 659 | L45: 667 | M45: 695 | N45: 606 | O45: 665 | P45: 575 | Q45: 508 | R45: 524 | S45: 587 | T45: 559
B46: Credit Cards
B47: Stage 1 | J47: 14268 | K47: 15351 | L47: 16222 | M47: 16805 | N47: 16807 | O47: 16797 | P47: 17340 | Q47: 17975 | R47: 17995 | S47: 18850 | T47: 19414
B48: stage 2 | J48: 630 | K48: 656 | L48: 695 | M48: 806 | N48: 881 | O48: 886 | P48: 858 | Q48: 894 | R48: 926 | S48: 930 | T48: 888
B49: stage 3 | J49: 1066 | K49: 1233 | L49: 1308 | M49: 1434 | N49: 1606 | O49: 1688 | P49: 1754 | Q49: 1887 | R49: 1910 | S49: 2072 | T49: 2212
B50: Corporate loans
B51: Stage 1 | S51: 1002 | T51: 998
B52: stage 2 | S52: 35 | T52: 26
B53: stage 3 | S53: 180 | T53: 193
B55: Stage 1 total | C55: =C39+C43+C47+C51 -> 0 | D55: =D39+D43+D47+D51 -> 0 | E55: =E39+E43+E47+E51 -> 0 | F55: =F39+F43+F47+F51 -> 0 | G55: =G39+G43+G47+G51 -> 0 | H55: =H39+H43+H47+H51 -> 0 | I55: =I39+I43+I47+I51 -> 0 | J55: =J39+J43+J47+J51 -> 97994 | ... V55: =V39+V43+V47+V51 -> 0
B56: Stage 2 total | C56: =C40+C44+C48+C52 -> 0 | D56: =D40+D44+D48+D52 -> 0 | E56: =E40+E44+E48+E52 -> 0 | F56: =F40+F44+F48+F52 -> 0 | G56: =G40+G44+G48+G52 -> 0 | H56: =H40+H44+H48+H52 -> 0 | I56: =I40+I44+I48+I52 -> 0 | J56: =J40+J44+J48+J52 -> 6246 | ... V56: =V40+V44+V48+V52 -> 0
B57: Stage 3 total | C57: =C41+C45+C49+C53 -> 0 | D57: =D41+D45+D49+D53 -> 0 | E57: =E41+E45+E49+E53 -> 0 | F57: =F41+F45+F49+F53 -> 0 | G57: =G41+G45+G49+G53 -> 0 | H57: =H41+H45+H49+H53 -> 0 | I57: =I41+I45+I49+I53 -> 0 | J57: =J41+J45+J49+J53 -> 13692 | ... V57: =V41+V45+V49+V53 -> 0
B58: SUM | C58: =SUM(C55:C57) -> 0 | D58: =SUM(D55:D57) -> 0 | E58: =SUM(E55:E57) -> 0 | F58: =SUM(F55:F57) -> 0 | G58: =SUM(G55:G57) -> 0 | H58: =SUM(H55:H57) -> 0 | I58: =SUM(I55:I57) -> 0 | J58: =SUM(J55:J57) -> 117932 | ... V58: =SUM(V55:V57) -> 0
B59: Stage 1 % | C59: =C55/C58 -> #DIV/0! | D59: =D55/D58 -> #DIV/0! | E59: =E55/E58 -> #DIV/0! | F59: =F55/F58 -> #DIV/0! | G59: =G55/G58 -> #DIV/0! | H59: =H55/H58 -> #DIV/0! | I59: =I55/I58 -> #DIV/0! | J59: =J55/J58 -> 0.83093647 | ... V59: =V55/V58 -> #DIV/0!
B60: Stage 2 % | C60: =C56/C58 -> #DIV/0! | D60: =D56/D58 -> #DIV/0! | E60: =E56/E58 -> #DIV/0! | F60: =F56/F58 -> #DIV/0! | G60: =G56/G58 -> #DIV/0! | H60: =H56/H58 -> #DIV/0! | I60: =I56/I58 -> #DIV/0! | J60: =J56/J58 -> 0.052962724 | ... V60: =V56/V58 -> #DIV/0!
B61: Stage 3 % | C61: =C57/C58 -> #DIV/0! | D61: =D57/D58 -> #DIV/0! | E61: =E57/E58 -> #DIV/0! | F61: =F57/F58 -> #DIV/0! | G61: =G57/G58 -> #DIV/0! | H61: =H57/H58 -> #DIV/0! | I61: =I57/I58 -> #DIV/0! | J61: =J57/J58 -> 0.1161008 | ... V61: =V57/V58 -> #DIV/0!
B62: SUM | C62: =SUM(C59:C61) -> #DIV/0! | D62: =SUM(D59:D61) -> #DIV/0! | E62: =SUM(E59:E61) -> #DIV/0! | F62: =SUM(F59:F61) -> #DIV/0! | G62: =SUM(G59:G61) -> #DIV/0! | H62: =SUM(H59:H61) -> #DIV/0! | I62: =SUM(I59:I61) -> #DIV/0! | J62: =SUM(J59:J61) -> 1 | ... V62: =SUM(V59:V61) -> #DIV/0!

Sheet Kvalitet bok (provisons)
A1: Provisons
A2: Andelen av beløpet som er avsatt til tap
B4: SEKm | C4: Q122 | D4: Q222 | E4: Q322 | F4: Q422 | G4: Q123 | H4: Q223 | I4: Q323 | J4: Q423 | K4: Q124 | L4: Q224 | M4: Q324 | N4: Q424 | O4: Q125 | P4: Q225 | Q4: Q325 | R4: Q425 | S4: Q126 | T4: Q226 | U4: Q326 | V4: Q426
B5: Sweden
B6: Stage 1 | J6: -789 | K6: -759 | L6: -779 | M6: -732 | N6: -729 | O6: -717 | P6: -722 | Q6: -718 | R6: -697 | S6: -669 | T6: -688
B7: % avsatt bok | C7: =-C6/'Kvalitet bok (Gross)'!C6 -> #DIV/0! | D7: =-D6/'Kvalitet bok (Gross)'!D6 -> #DIV/0! | E7: =-E6/'Kvalitet bok (Gross)'!E6 -> #DIV/0! | F7: =-F6/'Kvalitet bok (Gross)'!F6 -> #DIV/0! | G7: =-G6/'Kvalitet bok (Gross)'!G6 -> #DIV/0! | H7: =-H6/'Kvalitet bok (Gross)'!H6 -> #DIV/0! | I7: =-I6/'Kvalitet bok (Gross)'!I6 -> #DIV/0! | J7: =-J6/'Kvalitet bok (Gross)'!J6 -> 0.018938121 | ... T7: =-T6/'Kvalitet bok (Gross)'!T6 -> 0.012815259
B8: stage 2 | J8: -364 | K8: -398 | L8: -384 | M8: -426 | N8: -445 | O8: -448 | P8: -413 | Q8: -416 | R8: -434 | S8: -443 | T8: -436
B9: % avsatt bok | C9: =-C8/'Kvalitet bok (Gross)'!C7 -> #DIV/0! | D9: =-D8/'Kvalitet bok (Gross)'!D7 -> #DIV/0! | E9: =-E8/'Kvalitet bok (Gross)'!E7 -> #DIV/0! | F9: =-F8/'Kvalitet bok (Gross)'!F7 -> #DIV/0! | G9: =-G8/'Kvalitet bok (Gross)'!G7 -> #DIV/0! | H9: =-H8/'Kvalitet bok (Gross)'!H7 -> #DIV/0! | I9: =-I8/'Kvalitet bok (Gross)'!I7 -> #DIV/0! | J9: =-J8/'Kvalitet bok (Gross)'!J7 -> 0.17601547 | ... T9: =-T8/'Kvalitet bok (Gross)'!T7 -> 0.16299065
B10: stage 3 | J10: -2088 | K10: -2436 | L10: -2652 | M10: -2921 | N10: -3208 | O10: -3033 | P10: -3208 | Q10: -3451 | R10: -3621 | S10: -3700 | T10: -3820
B11: % avsatt bok | C11: =-C10/'Kvalitet bok (Gross)'!C8 -> #DIV/0! | D11: =-D10/'Kvalitet bok (Gross)'!D8 -> #DIV/0! | E11: =-E10/'Kvalitet bok (Gross)'!E8 -> #DIV/0! | F11: =-F10/'Kvalitet bok (Gross)'!F8 -> #DIV/0! | G11: =-G10/'Kvalitet bok (Gross)'!G8 -> #DIV/0! | H11: =-H10/'Kvalitet bok (Gross)'!H8 -> #DIV/0! | I11: =-I10/'Kvalitet bok (Gross)'!I8 -> #DIV/0! | J11: =-J10/'Kvalitet bok (Gross)'!J8 -> 0.48177204 | ... T11: =-T10/'Kvalitet bok (Gross)'!T8 -> 0.50750631
B12: Finland
B13: Stage 1 | J13: -524 | K13: -582 | L13: -588 | M13: -633 | N13: -671 | O13: -620 | P13: -698 | Q13: -661 | R13: -629 | S13: -630 | T13: -677
B14: % avsatt bok | C14: =-C13/'Kvalitet bok (Gross)'!C10 -> #DIV/0! | D14: =-D13/'Kvalitet bok (Gross)'!D10 -> #DIV/0! | E14: =-E13/'Kvalitet bok (Gross)'!E10 -> #DIV/0! | F14: =-F13/'Kvalitet bok (Gross)'!F10 -> #DIV/0! | G14: =-G13/'Kvalitet bok (Gross)'!G10 -> #DIV/0! | H14: =-H13/'Kvalitet bok (Gross)'!H10 -> #DIV/0! | I14: =-I13/'Kvalitet bok (Gross)'!I10 -> #DIV/0! | J14: =-J13/'Kvalitet bok (Gross)'!J10 -> 0.020725389 | ... T14: =-T13/'Kvalitet bok (Gross)'!T10 -> 0.021700805
B15: stage 2 | J15: -419 | K15: -435 | L15: -421 | M15: -393 | N15: -455 | O15: -418 | P15: -422 | Q15: -391 | R15: -388 | S15: -378 | T15: -372
B16: % avsatt bok | C16: =-C15/'Kvalitet bok (Gross)'!C11 -> #DIV/0! | D16: =-D15/'Kvalitet bok (Gross)'!D11 -> #DIV/0! | E16: =-E15/'Kvalitet bok (Gross)'!E11 -> #DIV/0! | F16: =-F15/'Kvalitet bok (Gross)'!F11 -> #DIV/0! | G16: =-G15/'Kvalitet bok (Gross)'!G11 -> #DIV/0! | H16: =-H15/'Kvalitet bok (Gross)'!H11 -> #DIV/0! | I16: =-I15/'Kvalitet bok (Gross)'!I11 -> #DIV/0! | J16: =-J15/'Kvalitet bok (Gross)'!J11 -> 0.18933574 | ... T16: =-T15/'Kvalitet bok (Gross)'!T11 -> 0.1970339
B17: stage 3 | J17: -1952 | K17: -2366 | L17: -2669 | M17: -2981 | N17: -3239 | O17: -3163 | P17: -3644 | Q17: -3923 | R17: -3661 | S17: -3987 | T17: -4316
B18: % avsatt bok | C18: =-C17/'Kvalitet bok (Gross)'!C12 -> #DIV/0! | D18: =-D17/'Kvalitet bok (Gross)'!D12 -> #DIV/0! | E18: =-E17/'Kvalitet bok (Gross)'!E12 -> #DIV/0! | F18: =-F17/'Kvalitet bok (Gross)'!F12 -> #DIV/0! | G18: =-G17/'Kvalitet bok (Gross)'!G12 -> #DIV/0! | H18: =-H17/'Kvalitet bok (Gross)'!H12 -> #DIV/0! | I18: =-I17/'Kvalitet bok (Gross)'!I12 -> #DIV/0! | J18: =-J17/'Kvalitet bok (Gross)'!J12 -> 0.4062435 | ... T18: =-T17/'Kvalitet bok (Gross)'!T12 -> 0.44439868
B19: Norway
B20: Stage 1 | J20: -198 | K20: -211 | L20: -218 | M20: -224 | N20: -231 | O20: -219 | P20: -209 | Q20: -210 | R20: -206 | S20: -214 | T20: -217
B21: % avsatt bok | C21: =-C20/'Kvalitet bok (Gross)'!C14 -> #DIV/0! | D21: =-D20/'Kvalitet bok (Gross)'!D14 -> #DIV/0! | E21: =-E20/'Kvalitet bok (Gross)'!E14 -> #DIV/0! | F21: =-F20/'Kvalitet bok (Gross)'!F14 -> #DIV/0! | G21: =-G20/'Kvalitet bok (Gross)'!G14 -> #DIV/0! | H21: =-H20/'Kvalitet bok (Gross)'!H14 -> #DIV/0! | I21: =-I20/'Kvalitet bok (Gross)'!I14 -> #DIV/0! | J21: =-J20/'Kvalitet bok (Gross)'!J14 -> 0.0090559824 | ... T21: =-T20/'Kvalitet bok (Gross)'!T14 -> 0.0080307909
B22: stage 2 | J22: -141 | K22: -151 | L22: -157 | M22: -150 | N22: -170 | O22: -170 | P22: -145 | Q22: -165 | R22: -145 | S22: -161 | T22: -145
B23: % avsatt bok | C23: =-C22/'Kvalitet bok (Gross)'!C15 -> #DIV/0! | D23: =-D22/'Kvalitet bok (Gross)'!D15 -> #DIV/0! | E23: =-E22/'Kvalitet bok (Gross)'!E15 -> #DIV/0! | F23: =-F22/'Kvalitet bok (Gross)'!F15 -> #DIV/0! | G23: =-G22/'Kvalitet bok (Gross)'!G15 -> #DIV/0! | H23: =-H22/'Kvalitet bok (Gross)'!H15 -> #DIV/0! | I23: =-I22/'Kvalitet bok (Gross)'!I15 -> #DIV/0! | J23: =-J22/'Kvalitet bok (Gross)'!J15 -> 0.090850515 | ... T23: =-T22/'Kvalitet bok (Gross)'!T15 -> 0.094771242
B24: stage 3 | J24: -1182 | K24: -1234 | L24: -1289 | M24: -1331 | N24: -1405 | O24: -1460 | P24: -1290 | Q24: -1343 | R24: -1365 | S24: -1500 | T24: -1571
B25: % avsatt bok | C25: =-C24/'Kvalitet bok (Gross)'!C16 -> #DIV/0! | D25: =-D24/'Kvalitet bok (Gross)'!D16 -> #DIV/0! | E25: =-E24/'Kvalitet bok (Gross)'!E16 -> #DIV/0! | F25: =-F24/'Kvalitet bok (Gross)'!F16 -> #DIV/0! | G25: =-G24/'Kvalitet bok (Gross)'!G16 -> #DIV/0! | H25: =-H24/'Kvalitet bok (Gross)'!H16 -> #DIV/0! | I25: =-I24/'Kvalitet bok (Gross)'!I16 -> #DIV/0! | J25: =-J24/'Kvalitet bok (Gross)'!J16 -> 0.35937975 | ... T25: =-T24/'Kvalitet bok (Gross)'!T16 -> 0.3741367
B26: Denmark
B27: Stage 1 | J27: -118 | K27: -122 | L27: -142 | M27: -120 | N27: -125 | O27: -148 | P27: -177 | Q27: -195 | R27: -185 | S27: -208 | T27: -225
B28: % avsatt bok | C28: =-C27/'Kvalitet bok (Gross)'!C18 -> #DIV/0! | D28: =-D27/'Kvalitet bok (Gross)'!D18 -> #DIV/0! | E28: =-E27/'Kvalitet bok (Gross)'!E18 -> #DIV/0! | F28: =-F27/'Kvalitet bok (Gross)'!F18 -> #DIV/0! | G28: =-G27/'Kvalitet bok (Gross)'!G18 -> #DIV/0! | H28: =-H27/'Kvalitet bok (Gross)'!H18 -> #DIV/0! | I28: =-I27/'Kvalitet bok (Gross)'!I18 -> #DIV/0! | J28: =-J27/'Kvalitet bok (Gross)'!J18 -> 0.017787157 | ... T28: =-T27/'Kvalitet bok (Gross)'!T18 -> 0.021481764
B29: stage 2 | J29: -47 | K29: -46 | L29: -50 | M29: -77 | N29: -81 | O29: -91 | P29: -101 | Q29: -95 | R29: -95 | S29: -104 | T29: -101
B30: % avsatt bok | C30: =-C29/'Kvalitet bok (Gross)'!C19 -> #DIV/0! | D30: =-D29/'Kvalitet bok (Gross)'!D19 -> #DIV/0! | E30: =-E29/'Kvalitet bok (Gross)'!E19 -> #DIV/0! | F30: =-F29/'Kvalitet bok (Gross)'!F19 -> #DIV/0! | G30: =-G29/'Kvalitet bok (Gross)'!G19 -> #DIV/0! | H30: =-H29/'Kvalitet bok (Gross)'!H19 -> #DIV/0! | I30: =-I29/'Kvalitet bok (Gross)'!I19 -> #DIV/0! | J30: =-J29/'Kvalitet bok (Gross)'!J19 -> 0.15064103 | ... T30: =-T29/'Kvalitet bok (Gross)'!T19 -> 0.21398305
B31: stage 3 | J31: -362 | K31: -404 | L31: -341 | M31: -371 | N31: -405 | O31: -409 | P31: -352 | Q31: -392 | R31: -415 | S31: -454 | T31: -462
B32: % avsatt bok | C32: =-C31/'Kvalitet bok (Gross)'!C20 -> #DIV/0! | D32: =-D31/'Kvalitet bok (Gross)'!D20 -> #DIV/0! | E32: =-E31/'Kvalitet bok (Gross)'!E20 -> #DIV/0! | F32: =-F31/'Kvalitet bok (Gross)'!F20 -> #DIV/0! | G32: =-G31/'Kvalitet bok (Gross)'!G20 -> #DIV/0! | H32: =-H31/'Kvalitet bok (Gross)'!H20 -> #DIV/0! | I32: =-I31/'Kvalitet bok (Gross)'!I20 -> #DIV/0! | J32: =-J31/'Kvalitet bok (Gross)'!J20 -> 0.50138504 | ... T32: =-T31/'Kvalitet bok (Gross)'!T20 -> 0.50217391
B33: Germany/Spain
B34: Stage 1 | J34: -84 | K34: -97 | L34: -94 | M34: -94 | N34: -68 | O34: -65 | P34: -67 | Q34: -68 | R34: -69 | S34: -75 | T34: -57
B35: % avsatt bok | C35: =-C34/'Kvalitet bok (Gross)'!C22 -> #DIV/0! | D35: =-D34/'Kvalitet bok (Gross)'!D22 -> #DIV/0! | E35: =-E34/'Kvalitet bok (Gross)'!E22 -> #DIV/0! | F35: =-F34/'Kvalitet bok (Gross)'!F22 -> #DIV/0! | G35: =-G34/'Kvalitet bok (Gross)'!G22 -> #DIV/0! | H35: =-H34/'Kvalitet bok (Gross)'!H22 -> #DIV/0! | I35: =-I34/'Kvalitet bok (Gross)'!I22 -> #DIV/0! | J35: =-J34/'Kvalitet bok (Gross)'!J22 -> 0.032928263 | ... T35: =-T34/'Kvalitet bok (Gross)'!T22 -> 0.024632671
B36: stage 2 | J36: -24 | K36: -24 | L36: -22 | M36: -25 | N36: -17 | O36: -18 | P36: -18 | Q36: -19 | R36: -19 | S36: -21 | T36: -25
B37: % avsatt bok | C37: =-C36/'Kvalitet bok (Gross)'!C23 -> #DIV/0! | D37: =-D36/'Kvalitet bok (Gross)'!D23 -> #DIV/0! | E37: =-E36/'Kvalitet bok (Gross)'!E23 -> #DIV/0! | F37: =-F36/'Kvalitet bok (Gross)'!F23 -> #DIV/0! | G37: =-G36/'Kvalitet bok (Gross)'!G23 -> #DIV/0! | H37: =-H36/'Kvalitet bok (Gross)'!H23 -> #DIV/0! | I37: =-I36/'Kvalitet bok (Gross)'!I23 -> #DIV/0! | J37: =-J36/'Kvalitet bok (Gross)'!J23 -> 0.23762376 | ... T37: =-T36/'Kvalitet bok (Gross)'!T23 -> 0.26041667
B38: stage 3 | J38: -397 | K38: -426 | L38: -416 | M38: -408 | N38: -389 | O38: -358 | P38: -337 | Q38: -317 | R38: -317 | S38: -347 | T38: -383
B39: % avsatt bok | C39: =-C38/'Kvalitet bok (Gross)'!C24 -> #DIV/0! | D39: =-D38/'Kvalitet bok (Gross)'!D24 -> #DIV/0! | E39: =-E38/'Kvalitet bok (Gross)'!E24 -> #DIV/0! | F39: =-F38/'Kvalitet bok (Gross)'!F24 -> #DIV/0! | G39: =-G38/'Kvalitet bok (Gross)'!G24 -> #DIV/0! | H39: =-H38/'Kvalitet bok (Gross)'!H24 -> #DIV/0! | I39: =-I38/'Kvalitet bok (Gross)'!I24 -> #DIV/0! | J39: =-J38/'Kvalitet bok (Gross)'!J24 -> 0.73247232 | ... T39: =-T38/'Kvalitet bok (Gross)'!T24 -> 0.71722846
B40: Stage 1 total | C40: =C6+C13+C20+C27+C34 -> 0 | D40: =D6+D13+D20+D27+D34 -> 0 | E40: =E6+E13+E20+E27+E34 -> 0 | F40: =F6+F13+F20+F27+F34 -> 0 | G40: =G6+G13+G20+G27+G34 -> 0 | H40: =H6+H13+H20+H27+H34 -> 0 | I40: =I6+I13+I20+I27+I34 -> 0 | J40: =J6+J13+J20+J27+J34 -> -1713 | ... T40: =T6+T13+T20+T27+T34 -> -1864
B41: Stage 2 total | C41: =C8+C15+C22+C29+C36 -> 0 | D41: =D8+D15+D22+D29+D36 -> 0 | E41: =E8+E15+E22+E29+E36 -> 0 | F41: =F8+F15+F22+F29+F36 -> 0 | G41: =G8+G15+G22+G29+G36 -> 0 | H41: =H8+H15+H22+H29+H36 -> 0 | I41: =I8+I15+I22+I29+I36 -> 0 | J41: =J8+J15+J22+J29+J36 -> -995 | ... T41: =T8+T15+T22+T29+T36 -> -1079
B42: Stage 3 total | C42: =C10+C17+C24+C31+C38 -> 0 | D42: =D10+D17+D24+D31+D38 -> 0 | E42: =E10+E17+E24+E31+E38 -> 0 | F42: =F10+F17+F24+F31+F38 -> 0 | G42: =G10+G17+G24+G31+G38 -> 0 | H42: =H10+H17+H24+H31+H38 -> 0 | I42: =I10+I17+I24+I31+I38 -> 0 | J42: =J10+J17+J24+J31+J38 -> -5981 | ... T42: =T10+T17+T24+T31+T38 -> -10552
B43: SUM | C43: =SUM(C40:C42) -> 0 | D43: =SUM(D40:D42) -> 0 | E43: =SUM(E40:E42) -> 0 | F43: =SUM(F40:F42) -> 0 | G43: =SUM(G40:G42) -> 0 | H43: =SUM(H40:H42) -> 0 | I43: =SUM(I40:I42) -> 0 | J43: =SUM(J40:J42) -> -8689 | ... T43: =SUM(T40:T42) -> -13495
B44: % avsatt bok total | C44: =-C43/'Kvalitet bok (Gross)'!C29 -> #DIV/0! | D44: =-D43/'Kvalitet bok (Gross)'!D29 -> #DIV/0! | E44: =-E43/'Kvalitet bok (Gross)'!E29 -> #DIV/0! | F44: =-F43/'Kvalitet bok (Gross)'!F29 -> #DIV/0! | G44: =-G43/'Kvalitet bok (Gross)'!G29 -> #DIV/0! | H44: =-H43/'Kvalitet bok (Gross)'!H29 -> #DIV/0! | I44: =-I43/'Kvalitet bok (Gross)'!I29 -> #DIV/0! | J44: =-J43/'Kvalitet bok (Gross)'!J29 -> 0.073678052 | ... T44: =-T43/'Kvalitet bok (Gross)'!T29 -> 0.08749068
B48: SEKm
B49: Private loans
B50: Stage 1 | J50: -1431 | K50: -1468 | L50: -1495 | M50: -1482 | N50: -1526 | O50: -1469 | P50: -1549 | Q50: -1510 | R50: -1425 | S50: -1427 | T50: -1487
B51: % avsatt bok | J51: =-J50/'Kvalitet bok (Gross)'!J39 -> 0.02102711 | K51: =-K50/'Kvalitet bok (Gross)'!K39 -> 0.021009245 | L51: =-L50/'Kvalitet bok (Gross)'!L39 -> 0.021004861 | M51: =-M50/'Kvalitet bok (Gross)'!M39 -> 0.02000054 | N51: =-N50/'Kvalitet bok (Gross)'!N39 -> 0.020008654 | O51: =-O50/'Kvalitet bok (Gross)'!O39 -> 0.019395812 | P51: =-P50/'Kvalitet bok (Gross)'!P39 -> 0.019723188 | Q51: =-Q50/'Kvalitet bok (Gross)'!Q39 -> 0.018616923 | ... T51: =-T50/'Kvalitet bok (Gross)'!T39 -> 0.017039855
B52: stage 2 | J52: -905 | K52: -960 | L52: -921 | M52: -942 | N52: -1029 | O52: -1006 | P52: -954 | Q52: -942 | R52: -929 | S52: -958 | T52: -915
B53: % avsatt bok | J53: =-J52/'Kvalitet bok (Gross)'!J40 -> 0.17927892 | K53: =-K52/'Kvalitet bok (Gross)'!K40 -> 0.17804154 | L53: =-L52/'Kvalitet bok (Gross)'!L40 -> 0.17876553 | M53: =-M52/'Kvalitet bok (Gross)'!M40 -> 0.18668252 | N53: =-N52/'Kvalitet bok (Gross)'!N40 -> 0.19313063 | O53: =-O52/'Kvalitet bok (Gross)'!O40 -> 0.19290508 | P53: =-P52/'Kvalitet bok (Gross)'!P40 -> 0.18614634 | Q53: =-Q52/'Kvalitet bok (Gross)'!Q40 -> 0.19165819 | ... T53: =-T52/'Kvalitet bok (Gross)'!T40 -> 0.18307323
B54: stage 3 | J54: -5494 | K54: -6292 | L54: -6763 | M54: -7341 | N54: -7885 | O54: -7622 | P54: -7984 | Q54: -8502 | R54: -8435 | S54: -8890 | T54: -9371
B55: % avsatt bok | J55: =-J54/'Kvalitet bok (Gross)'!J41 -> 0.45251627 | K55: =-K54/'Kvalitet bok (Gross)'!K41 -> 0.45416486 | L55: =-L54/'Kvalitet bok (Gross)'!L41 -> 0.45422795 | M55: =-M54/'Kvalitet bok (Gross)'!M41 -> 0.45990477 | N55: =-N54/'Kvalitet bok (Gross)'!N41 -> 0.46116505 | O55: =-O54/'Kvalitet bok (Gross)'!O41 -> 0.45550708 | P55: =-P54/'Kvalitet bok (Gross)'!P41 -> 0.46329716 | Q55: =-Q54/'Kvalitet bok (Gross)'!Q41 -> 0.47112934 | ... T55: =-T54/'Kvalitet bok (Gross)'!T41 -> 0.47019568
B56: Secured
B57: Stage 1 | J57: -87 | K57: -84 | L57: -97 | M57: -97 | N57: -90 | O57: -95 | P57: -110 | Q57: -123 | R57: -137 | S57: -134 | T57: -140
B58: % avsatt bok | J58: =-J57/'Kvalitet bok (Gross)'!J43 -> 0.0055516559 | K58: =-K57/'Kvalitet bok (Gross)'!K43 -> 0.0054347826 | L58: =-L57/'Kvalitet bok (Gross)'!L43 -> 0.0063303531 | M58: =-M57/'Kvalitet bok (Gross)'!M43 -> 0.006369845 | N58: =-N57/'Kvalitet bok (Gross)'!N43 -> 0.0059055118 | O58: =-O57/'Kvalitet bok (Gross)'!O43 -> 0.0062868109 | P58: =-P57/'Kvalitet bok (Gross)'!P43 -> 0.0071572646 | Q58: =-Q57/'Kvalitet bok (Gross)'!Q43 -> 0.007831402 | ... T58: =-T57/'Kvalitet bok (Gross)'!T43 -> 0.0082285177
B59: stage 2 | J59: -4 | K59: -5 | L59: -5 | M59: -5 | N59: -5 | O59: -5 | P59: -5 | Q59: -5 | R59: -5 | S59: -5 | T59: -6
B60: % avsatt bok | J60: =-J59/'Kvalitet bok (Gross)'!J44 -> 0.0070422535 | K60: =-K59/'Kvalitet bok (Gross)'!K44 -> 0.0081037277 | L60: =-L59/'Kvalitet bok (Gross)'!L44 -> 0.0079491256 | M60: =-M59/'Kvalitet bok (Gross)'!M44 -> 0.0082372323 | N60: =-N59/'Kvalitet bok (Gross)'!N44 -> 0.0079365079 | O60: =-O59/'Kvalitet bok (Gross)'!O44 -> 0.0082236842 | P60: =-P59/'Kvalitet bok (Gross)'!P44 -> 0.0079617834 | Q60: =-Q59/'Kvalitet bok (Gross)'!Q44 -> 0.0074294205 | ... T60: =-T59/'Kvalitet bok (Gross)'!T44 -> 0.0080106809
B61: stage 3 | J61: -28 | K61: -32 | L61: -35 | M61: -42 | N61: -46 | O61: -48 | P61: -53 | Q61: -54 | R61: -59 | S61: -66 | T61: -71
B62: % avsatt bok | J62: =-J61/'Kvalitet bok (Gross)'!J45 -> 0.057731959 | K62: =-K61/'Kvalitet bok (Gross)'!K45 -> 0.048558422 | L62: =-L61/'Kvalitet bok (Gross)'!L45 -> 0.052473763 | M62: =-M61/'Kvalitet bok (Gross)'!M45 -> 0.060431655 | N62: =-N61/'Kvalitet bok (Gross)'!N45 -> 0.075907591 | O62: =-O61/'Kvalitet bok (Gross)'!O45 -> 0.072180451 | P62: =-P61/'Kvalitet bok (Gross)'!P45 -> 0.092173913 | Q62: =-Q61/'Kvalitet bok (Gross)'!Q45 -> 0.10629921 | ... T62: =-T61/'Kvalitet bok (Gross)'!T45 -> 0.12701252
B63: Credit Cards
B64: Stage 1 | J64: -195 | K64: -219 | L64: -228 | M64: -224 | N64: -208 | O64: -203 | P64: -213 | Q64: -220 | R64: -224 | S64: -233 | T64: -234
B65: % avsatt bok | J65: =-J64/'Kvalitet bok (Gross)'!J47 -> 0.013666947 | K65: =-K64/'Kvalitet bok (Gross)'!K47 -> 0.014266172 | L65: =-L64/'Kvalitet bok (Gross)'!L47 -> 0.014054987 | M65: =-M64/'Kvalitet bok (Gross)'!M47 -> 0.013329366 | N65: =-N64/'Kvalitet bok (Gross)'!N47 -> 0.012375796 | O65: =-O64/'Kvalitet bok (Gross)'!O47 -> 0.012085491 | P65: =-P64/'Kvalitet bok (Gross)'!P47 -> 0.012283737 | Q65: =-Q64/'Kvalitet bok (Gross)'!Q47 -> 0.012239221 | ... T65: =-T64/'Kvalitet bok (Gross)'!T47 -> 0.012053158
B66: stage 2 | J66: -86 | K66: -89 | L66: -109 | M66: -124 | N66: -134 | O66: -134 | P66: -140 | Q66: -139 | R66: -146 | S66: -143 | T66: -158
B67: % avsatt bok | J67: =-J66/'Kvalitet bok (Gross)'!J48 -> 0.13650794 | K67: =-K66/'Kvalitet bok (Gross)'!K48 -> 0.13567073 | L67: =-L66/'Kvalitet bok (Gross)'!L48 -> 0.15683453 | M67: =-M66/'Kvalitet bok (Gross)'!M48 -> 0.15384615 | N67: =-N66/'Kvalitet bok (Gross)'!N48 -> 0.15209989 | O67: =-O66/'Kvalitet bok (Gross)'!O48 -> 0.15124153 | P67: =-P66/'Kvalitet bok (Gross)'!P48 -> 0.16317016 | Q67: =-Q66/'Kvalitet bok (Gross)'!Q48 -> 0.15548098 | ... T67: =-T66/'Kvalitet bok (Gross)'!T48 -> 0.17792793
B68: stage 3 | J68: -459 | K68: -542 | L68: -569 | M68: -629 | N68: -714 | O68: -753 | P68: -795 | Q68: -869 | R68: -886 | S68: -968 | T68: -1048
B69: % avsatt bok | J69: =-J68/'Kvalitet bok (Gross)'!J49 -> 0.43058161 | K69: =-K68/'Kvalitet bok (Gross)'!K49 -> 0.43957826 | L69: =-L68/'Kvalitet bok (Gross)'!L49 -> 0.43501529 | M69: =-M68/'Kvalitet bok (Gross)'!M49 -> 0.43863319 | N69: =-N68/'Kvalitet bok (Gross)'!N49 -> 0.44458281 | O69: =-O68/'Kvalitet bok (Gross)'!O49 -> 0.44609005 | P69: =-P68/'Kvalitet bok (Gross)'!P49 -> 0.45324971 | Q69: =-Q68/'Kvalitet bok (Gross)'!Q49 -> 0.46051934 | ... T69: =-T68/'Kvalitet bok (Gross)'!T49 -> 0.47377939
B70: Corporate loans
B71: Stage 1 | S71: -3 | T71: -3
B72: % avsatt bok | S72: =-S71/'Kvalitet bok (Gross)'!S51 -> 0.002994012 | T72: =-T71/'Kvalitet bok (Gross)'!T51 -> 0.003006012
B73: stage 2 | S73: 0 | T73: 0
B74: % avsatt bok | S74: =-S73/'Kvalitet bok (Gross)'!S52 -> 0 | T74: =-T73/'Kvalitet bok (Gross)'!T52 -> 0
B75: stage 3 | S75: -64 | T75: -62
B76: % avsatt bok | S76: =-S75/'Kvalitet bok (Gross)'!S53 -> 0.35555556 | T76: =-T75/'Kvalitet bok (Gross)'!T53 -> 0.32124352
B78: Stage 1 total | C78: =C50+C57+C64+C71 -> 0 | D78: =D50+D57+D64+D71 -> 0 | E78: =E50+E57+E64+E71 -> 0 | F78: =F50+F57+F64+F71 -> 0 | G78: =G50+G57+G64+G71 -> 0 | H78: =H50+H57+H64+H71 -> 0 | I78: =I50+I57+I64+I71 -> 0 | J78: =J50+J57+J64+J71 -> -1713 | ... V78: =V50+V57+V64+V71 -> 0
B79: Stage 2 total | C79: =C52+C59+C66+C73 -> 0 | D79: =D52+D59+D66+D73 -> 0 | E79: =E52+E59+E66+E73 -> 0 | F79: =F52+F59+F66+F73 -> 0 | G79: =G52+G59+G66+G73 -> 0 | H79: =H52+H59+H66+H73 -> 0 | I79: =I52+I59+I66+I73 -> 0 | J79: =J52+J59+J66+J73 -> -995 | ... V79: =V52+V59+V66+V73 -> 0
B80: Stage 3 total | C80: =C54+C61+C68+C75 -> 0 | D80: =D54+D61+D68+D75 -> 0 | E80: =E54+E61+E68+E75 -> 0 | F80: =F54+F61+F68+F75 -> 0 | G80: =G54+G61+G68+G75 -> 0 | H80: =H54+H61+H68+H75 -> 0 | I80: =I54+I61+I68+I75 -> 0 | J80: =J54+J61+J68+J75 -> -5981 | ... V80: =V54+V61+V68+V75 -> 0
B81: SUM | C81: =SUM(C78:C80) -> 0 | D81: =SUM(D78:D80) -> 0 | E81: =SUM(E78:E80) -> 0 | F81: =SUM(F78:F80) -> 0 | G81: =SUM(G78:G80) -> 0 | H81: =SUM(H78:H80) -> 0 | I81: =SUM(I78:I80) -> 0 | J81: =SUM(J78:J80) -> -8689 | ... V81: =SUM(V78:V80) -> 0
B82: % avsatt bok total | C82: =-C81/'Kvalitet bok (Gross)'!C58 -> #DIV/0! | D82: =-D81/'Kvalitet bok (Gross)'!D58 -> #DIV/0! | E82: =-E81/'Kvalitet bok (Gross)'!E58 -> #DIV/0! | F82: =-F81/'Kvalitet bok (Gross)'!F58 -> #DIV/0! | G82: =-G81/'Kvalitet bok (Gross)'!G58 -> #DIV/0! | H82: =-H81/'Kvalitet bok (Gross)'!H58 -> #DIV/0! | I82: =-I81/'Kvalitet bok (Gross)'!I58 -> #DIV/0! | J82: =-J81/'Kvalitet bok (Gross)'!J58 -> 0.073678052 | ... V82: =-V81/'Kvalitet bok (Gross)'!V58 -> #DIV/0!

Sheet Net credit losses
B3: SEKm | C3: Q122 | D3: Q222 | E3: Q322 | F3: Q422 | G3: Q123 | H3: Q223 | I3: Q323 | J3: Q423 | K3: Q124 | L3: Q224 | M3: Q324 | N3: Q424 | O3: Q125 | P3: Q225 | Q3: Q325 | R3: Q425 | S3: Q126 | T3: Q226 | U3: Q326 | V3: Q426
B5: Provisons stage 1 | G5: -178 | H5: -196 | I5: -286 | J5: -94 | K5: -28 | L5: -66 | M5: 10 | N5: -16 | O5: 8 | P5: -79 | Q5: 11 | R5: 40 | S5: 18 | T5: -71
B6: Provisons stage 2 | G6: -30 | H6: -49 | I6: -53 | J6: -125 | K6: -41 | L6: 12 | M6: -43 | N6: -92 | O6: -6 | P6: 56 | Q6: 11 | R6: -14 | S6: -14 | T6: 33
B7: Provisons stage 3 | G7: -561 | H7: -522 | I7: -674 | J7: -805 | K7: -952 | L7: -819 | M7: -887 | N7: -983 | O7: -968 | P7: -801 | Q7: -870 | R7: -834 | S7: -837 | T7: -796
B8: Total on-balance | C8: =SUM(C5:C7) -> 0 | D8: =SUM(D5:D7) -> 0 | E8: =SUM(E5:E7) -> 0 | F8: =SUM(F5:F7) -> 0 | G8: =SUM(G5:G7) -> -769 | H8: =SUM(H5:H7) -> -767 | I8: =SUM(I5:I7) -> -1013 | J8: =SUM(J5:J7) -> -1024 | ... T8: =SUM(T5:T7) -> -834
B10: Provisons stage 1 | G10: -9 | H10: -12 | I10: -29 | J10: 5 | K10: -5 | L10: 2 | M10: -3 | N10: 8 | O10: 0 | P10: -6 | Q10: 1 | R10: 1 | S10: -5 | T10: 14
B11: Provisons stage 2 | G11: 0 | H11: 0 | I11: 0 | J11: 0 | K11: 0 | L11: 0 | M11: 0 | N11: 0 | O11: 0 | P11: 0 | Q11: -1 | R11: 0 | S11: 0 | T11: -1
B12: Provisons stage 3 | G12: 0 | H12: 0 | I12: 0 | J12: 0 | K12: 0 | L12: 0 | M12: 0 | N12: 0 | O12: 0 | P12: 0 | Q12: 0 | R12: 0 | S12: 0 | T12: 0
B13: Total off-balance | C13: =SUM(C10:C12) -> 0 | D13: =SUM(D10:D12) -> 0 | E13: =SUM(E10:E12) -> 0 | F13: =SUM(F10:F12) -> 0 | G13: =SUM(G10:G12) -> -9 | H13: =SUM(H10:H12) -> -12 | I13: =SUM(I10:I12) -> -29 | J13: =SUM(J10:J12) -> 5 | ... T13: =SUM(T10:T12) -> 13
B15: Write-offs | G15: -45 | H15: -63 | I15: -67 | J15: -124 | K15: -70 | L15: -73 | M15: -73 | N15: -72 | O15: -73 | P15: -96 | Q15: -85 | R15: -144 | S15: -92 | T15: -87
B16: Recoveries | G16: 0 | H16: 3 | I16: 4 | J16: 4 | K16: 5 | L16: 12 | M16: 11 | N16: 14 | O16: 16 | P16: 17 | Q16: 15 | R16: 20 | S16: 17 | T16: 25
B17: SUM | C17: =SUM(C15:C16) -> 0 | D17: =SUM(D15:D16) -> 0 | E17: =SUM(E15:E16) -> 0 | F17: =SUM(F15:F16) -> 0 | G17: =SUM(G15:G16) -> -45 | H17: =SUM(H15:H16) -> -60 | I17: =SUM(I15:I16) -> -63 | J17: =SUM(J15:J16) -> -120 | ... T17: =SUM(T15:T16) -> -62
B19: Total net credit losses | C19: =C8+C13+C17 -> 0 | D19: =D8+D13+D17 -> 0 | E19: =E8+E13+E17 -> 0 | F19: =F8+F13+F17 -> 0 | G19: =G8+G13+G17 -> -823 | H19: =H8+H13+H17 -> -839 | I19: =I8+I13+I17 -> -1105 | J19: =J8+J13+J17 -> -1139 | ... T19: =T8+T13+T17 -> -883

Sheet Funding
A2: Q226
A3: Deposits
A25: Financing

Sheet Nøkkeltall
D4: 2026 | E4: 2027 | F4: 2028
C5: P/E | D5: =Modell!$B$4/Modell!AD22 -> 10.295002 | E5: =Modell!$B$4/Modell!AE22 -> 8.4794855 | F5: =Modell!$B$4/Modell!AF22 -> 7.4713293

Sheet Nedsideberegning
