Workbook

Sheet Info
A2: Orange book kan brukes for å søke opp patenter | I2: Pris pille (05.01.26)
I3: 1,5mg = 5$day/(149$month) | O3: Dividends | Q3: Buyback
A4: ADA: American Diabetes Association | I4: 4mg = 149$month through April 15 26, then 199$/month | O4: 2026 | Q4: =R4/Modell!B5 -> 3.3757173 | R4: 15000 | T4: Tilbakekjøpsprogram
I5: 25mg = 299$/month | O5: 2025 | P5: 11.7 | T5: Dato kjøp | U5: Antall aksjer | V5: Akummelert antall aksjer | W5: Kjøp DKK | X5: Akkumelert kjøp DKK
O6: 2024 | P6: 11.4 | T6: 46062 | U6: 750000 | V6: =U6 -> 750000 | W6: 222297903 | X6: =W6 -> 222297903
A7: GLP-1: | I7: Kan kjøpes i 1,5, 4, 9 og 25 mg doser | O7: 2023 | P7: 9.4 | T7: 46069 | U7: 1000000 | V7: =SUM(U6:U7) -> 1750000 | W7: =533796640-W6 -> 311498737 | X7: =SUM(W6:W7) -> 533796640
A8: Dette er medisiner som etterligner kroppens eget GLP-1 hormon: | O8: 2022 | P8: 6.2 | T8: 46076 | U8: 1000000 | V8: =SUM(U6:U8) -> 2750000 | W8: =841997435-X7 -> 308200795 | X8: =SUM(W6:W8) -> 841997435
A9: Øker insulinutskillelse når blodsukkeret er høyt | O9: 2021 | P9: 5.2 | T9: 46083 | U9: 1295000 | V9: =SUM(U6:U9) -> 4045000 | W9: =1160693639-X8 -> 318696204 | X9: =SUM(W6:W9) -> 1160693639
A10: Senker appetitten | J10: Q126 oppjusterre | O10: 2020 | P10: 4.55 | T10: 46090 | U10: 1289992 | V10: =SUM(U6:U10) -> 5334992 | W10: =1472797094-X9 -> 312103455 | X10: =SUM(W6:W10) -> 1472797094
T11: 46097 | U11: 1243000 | V11: =SUM(U6:U11) -> 6577992 | W11: =1783540174-X10 -> 310743080 | X11: =SUM(W6:W11) -> 1783540174
A12: Produktene her: | T12: 46104 | U12: 1270000 | V12: =SUM(U6:U12) -> 7847992 | W12: =2091696255-X11 -> 308156081 | X12: =SUM(W6:W12) -> 2091696255
A13: Ozempic: Brukes primært mot type 2-diabetes, men også kjent for å gi vekttap som bieffekt | T13: 46111 | U13: 1315000 | V13: =SUM(U6:U13) -> 9162992 | W13: =2399878368-X12 -> 308182113 | X13: =SUM(W6:W13) -> 2399878368
A14: Victoza: Også en GLP-1 medisin mot type 2, men en litt eldre versjon | T14: 46119 | U14: =9967992-9162992 -> 805000 | V14: =SUM(U6:U14) -> 9967992 | W14: =2586404548-2399878368 -> 186526180 | X14: =SUM(W6:W14) -> 2586404548
A15: Rybelsus: Dette er en tablettversjon av semaglutid | T15: 46125 | U15: =11007992-9967992 -> 1040000 | V15: =SUM(U$6:U15) -> 11007992 | W15: =2835176799-2586404548 -> 248772251 | X15: =SUM(W$6:W15) -> 2835176799
T16: 46132 | U16: =12257992-11007992 -> 1250000 | V16: =SUM(U$6:U16) -> 12257992 | W16: =3148710807-2835176799 -> 313534008 | X16: =SUM(W$6:W16) -> 3148710807
A17: Insulin: | T17: 46139 | U17: =13407992-12257992 -> 1150000 | V17: =SUM(U$6:U17) -> 13407992 | W17: =3438932195-3148710807 -> 290221388 | X17: =SUM(W$6:W17) -> 3438932195
A18: Dette er tradisjonelle insulinprodukter for folk med diabetes | T18: 46147 | U18: =14759179-13407992 -> 1351187 | V18: =SUM(U$6:U18) -> 14759179 | W18: =3799999990-3438931195 -> 361068795 | X18: =SUM(W$6:W18) -> 3800000990
A19: Long-acting insulin: Gir en jevn insulinfrigjøring hele døgnet (Levemir, Tresiba) | T19: 46160 | U19: 1239849 | V19: =SUM(U$6:U19) -> 15999028 | W19: 369728627 | X19: =SUM(W$6:W19) -> 4169729617
A20: Premix insulin: Blanding av rask- og langtidsvirkende insulin i en sprøyte, for enklere behandling | T20: 46168 | U20: 1060000 | V20: =SUM(U$6:U20) -> 17059028 | W20: =670560306-W19 -> 300831679 | X20: =SUM(W$6:W20) -> 4470561296
A21: Fast-acting insulin: tas rett før måltider for å håndtere blodsukkerstigningen som skjer når dub spsier | T21: 46174 | U21: 840151 | V21: =SUM(U$6:U21) -> 17899179 | W21: =913270696-670560306 -> 242710390 | X21: =SUM(W$6:W21) -> 4713271686
A22: Human insulin: Insulin som er identisk med det naturlige menneskeinsulinet, brukt før de nyere insulin-typene | T22: 46181 | U22: 840000 | V22: =SUM(U$6:U22) -> 18739179 | W22: =1158452492-913270696 -> 245181796 | X22: =SUM(W$6:W22) -> 4958453482
N23: Q226 oppjusterer | T23: 46188 | U23: 1125000 | V23: =SUM(U$6:U23) -> 19864179 | W23: =1469055829-1158452492 -> 310603337 | X23: =SUM(W$6:W23) -> 5269056819
A24: Obesity care: | N24: Adjusted sales growth: 0 to -6% at CER | T24: 46195 | U24: 1075000 | V24: =SUM(U$6:U24) -> 20939179 | W24: =1777005178-1469055829 -> 307949349 | X24: =SUM(W$6:W24) -> 5577006168
A25: Her handler alt om fedmebehandling, altså medisiner laget for vekttap | N25: Adjusted operating profit growth: 0 to -6% at CER | T25: 46202 | U25: 1050000 | V25: =SUM(U$6:U25) -> 21989179 | W25: =2098848921-1777005178 -> 321843743 | X25: =SUM(W$6:W25) -> 5898849911
T26: 46209 | U26: 1000000 | V26: =SUM(U$6:U26) -> 22989179 | W26: =2419775981-2098848921 -> 320927060 | X26: =SUM(W$6:W26) -> 6219776971
A27: Produktene her: | N27: LLY guider Revenues på 85-87 USDb | T27: 46216 | U27: 975000 | V27: =SUM(U$6:U27) -> 23964179 | W27: =2734545468-2419775981 -> 314769487 | X27: =SUM(W$6:W27) -> 6534546458
A28: Wegovy: Brukes spesifikt for fedmebehanling - inneholder semaglutid | N28: Oppjustert Q226 | T28: 46223 | U28: 975000 | V28: =SUM(U$6:U28) -> 24939179 | W28: =3053177399-2374545468 -> 678631931 | X28: =SUM(W$6:W28) -> 7213178389
A29: Saxenda: Et eldre vekttapsmiddel basert på et annet GLP-1 hormon (liraglutid) | T29: 46230 | U29: 960000 | V29: =SUM(U$6:U29) -> 25899179 | W29: =3362368903-3053177399 -> 309191504 | X29: =SUM(W$6:W29) -> 7522369893
T30: 46238 | U30: 1450000 | V30: =SUM(U6:U30) -> 27349179 | W30: =3733256468-3362368903 -> 370887565 | X30: =SUM(W6:W30) -> 7893257458
A31: Viktige medisiner: | E31: Hims and Hers | T31: 46244 | U31: 820000 | V31: =SUM(U6:U31) -> 28169179 | W31: =3980067920-3733256468 -> 246811452 | X31: =SUM(W6:W31) -> 8140068910
A32: CagriSema | E32: 07.02.26: Hims dropper å lanserer sine kopier | T32: 46251 | U32: 1000000 | V32: =SUM(U6:U32) -> 29169179 | W32: =4281660830-3980067920 -> 301592910 | X32: =SUM(W6:W32) -> 8441661820
A33: Amycretin | E33: 05.02.26: Lanserer egne compounded Semaglutide Pills til 49 USD/Month | T33: 46258 | U33: 1045000 | V33: =SUM(U6:U33) -> 30214179 | W33: =4590476842-4281660830 -> 308816012 | X33: =SUM(W6:W33) -> 8750477832
T34: 46265 | U34: 1050000 | V34: =SUM(U6:U34) -> 31264179 | W34: =4907673815-4590476842 -> 317196973 | X34: =SUM(W6:W34) -> 9067674805
T35: 46272 | U35: 1055000 | V35: =SUM(U6:U35) -> 32319179 | W35: =5221774293-4907673815 -> 314100478 | X35: =SUM(W6:W35) -> 9381775283
A36: Press release: | T36: 46279 | U36: 1050000 | V36: =SUM(U6:U36) -> 33369179 | W36: =5526186488-5221774293 -> 304412195 | X36: =SUM(W6:W36) -> 9686187478
A37: 21.09.26: Novo kjøper tilbake 1 090 000 B-aksjer | T37: 46286 | U37: 1090000 | V37: =SUM(U6:U37) -> 34459179 | W37: =5829922946-5526186488 -> 303736458 | X37: =SUM(W6:W37) -> 9989923936
A38: 14.09.26: Novo kjøper tilbake 1 050 00 B-aksjer
A39: 07.09.26: Novo kjøper tilbake 1 055 000 B-aksjer
A40: 31.08.26: Novo kjøper tilbake 1 050 000 B-aksjer
A41: 24.08.26: Novo kjøper tilbake 1 045 000 B-aksjer
A42: 17.08.26: Novo kjøper tilbake 1 000 000 B-aksjer
A43: 10.08.26: Novo kjøper tilbake 820 000 B-aksjer
A44: 04.08.26: Novo kjøper tilbake 1 145 000 B-aksjer
A45: 27.07.26: Novo kjøper tilbake 960 000 B-aksjer
A46: 20.07.26: Novo kjøper tilbake 975 000 B-aksjer
A47: 13.07.26: Novo kjøper tilbake 975 000 B-aksjer
A48: 06.07.26: Novo kjøper tilbake 1 000 000 B-aksjer
A49: 29.06.26: Novo kjøper tilbake 1 050 000 B-aksjer
... A113: 05.02.24: Novo Nordisk to acquire three fill-finish sites from Novo holdings basert på oppkjøpet av catalant. Oppkjøpet er forventet å øke Novo sin produskjon fra 26 og utover. Fabrikkene ligger i Italia, Belgia og Indiana (US)

Sheet Modell
A3: Kapitalstruktur | C3: DKK million | D3: Q122 | E3: Q222 | F3: Q322 | G3: Q422 | H3: Q123 | I3: Q223 | J3: Q323 | K3: Q423 | L3: Q124 | M3: Q224 | N3: Q324 | O3: Q424 | P3: Q125 | Q3: Q225 | R3: Q325 | S3: Q425 | T3: Q126 | U3: Q226 | V3: Q326 | W3: Q426 | AA3: FY 2015 | AB3: FY 2016 | AC3: FY 2017 | AD3: FY 2018 | AE3: FY 2019 | AF3: FY 2020 | AG3: FY 2021 | AH3: FY 2022 | AI3: FY 2023 | AJ3: FY 2024 | AK3: FY 2025 | AL3: FY 2026 | AM3: FY 2027 | AN3: FY 2028 | AO3: FY 2029 | AP3: FY 2030 | AQ3: FY 2031 | AR3: FY 2032 | AS3: FY 2033 | AT3: FY 2034 | AU3: FY 2035
A4: Price | B4: 246.7 | C4: GLP - 1 class | D4: =SUM(D5:D11) -> 26576.668 | E4: =SUM(E5:E11) -> 29861.684 | F4: =SUM(F5:F11) -> 33517.772 | G4: =SUM(G5:G11) -> 37666.304 | H4: =SUM(H5:H11) -> 44749.016 | I4: =SUM(I5:I11) -> 51365.392 | J4: =SUM(J5:J11) -> 57663.244 | K4: =SUM(K5:K11) -> 65199.072 | ... S4: =SUM(S5:S11) -> 133213.2 | T4: =SUM(T5:T12) -> 134692.36 | U4: =SUM(U5:U12) -> 156154.43 | V4: =SUM(V5:V12) -> 0 | W4: =SUM(W5:W12) -> 0
A5: S/O (m) | B5: 4443.5 | C5: Mounjaro | D5: 0 | E5: 0 | F5: =187.3*6.36 -> 1191.228 | G5: =3068.7-1191 -> 1877.7 | H5: =568.5*6.36 -> 3615.66 | I5: =979.7*6.36 -> 6230.892 | J5: =1409.3*6.36 -> 8963.148 | K5: =32837.3-H5-I5-J5 -> 14027.6 | L5: =1806.5*6.36 -> 11489.34 | M5: 19860 | N5: 20001 | O5: 22680 | P5: 24685 | Q5: 33404 | R5: 41861 | S5: =7409*6.36 -> 47121.24 | T5: 55263.56 | U5: 64331.21
A6: MC DKKm | B6: =B4*B5 -> 1096211.4 | C6: Zepbound | D6: 0 | E6: 0 | F6: 0 | G6: 0 | H6: 0 | I6: 0 | J6: 0 | K6: =175.8*6.36 -> 1118.088 | L6: =517.4*6.36 -> 3290.664 | M6: 7986 | N6: 8083 | O6: 12252 | P6: 14855 | Q6: 21723 | R6: 23053 | S6: =4261*6.36 -> 27099.96 | T6: 26540.8 | U6: 31884.16
A7: Cash DKKm | B7: =S92 -> 26464 | C7: Trulicity | D7: =1741.3*6.36 -> 11074.668 | E7: =1911.9*6.36 -> 12159.684 | F7: =1850.4*6.36 -> 11768.544 | G7: =47316.5-D7-E7-F7 -> 12313.604 | H7: =1977.1*6.36 -> 12574.356 | I7: =1812.5*6.36 -> 11527.5 | J7: =1673.6*6.36 -> 10644.096 | K7: =45363.336-H7-I7-J7 -> 10617.384 | L7: =1456.3*6.36 -> 9262.068 | M7: 8006 | N7: 8359 | O7: 8031 | P7: 7035 | Q7: 7016 | R7: 6759 | S7: 0 | T7: 0 | U7: 0
A8: Debt DKKm | B8: =S99+S105 -> 130958 | C8: Foundayo (Orfo pill) | D8: 0 | E8: 0 | F8: 0 | G8: 0 | H8: 0 | I8: 0 | J8: 0 | K8: 0 | L8: 0 | M8: 0 | N8: 0 | O8: 0 | P8: 0 | Q8: 0 | R8: 0 | S8: 0 | T8: 0 | U8: 634.06
A9: EV DKKm | B9: =B6-B7+B8 -> 1200705.4 | C9: Ozempic | D9: 12035 | E9: 14349 | F9: 16390 | G9: 16976 | H9: 19640 | I9: 22101 | J9: 23912 | K9: 23912 | L9: 27810 | M9: 28875 | N9: 29804 | O9: 33853 | P9: 32721 | Q9: 31799 | R9: 30744 | S9: 31825 | T9: 27825 | U9: 31375
C10: Rybelsus | D10: 2063 | E10: 2172 | F10: 3011 | G10: 4053 | H10: 4356 | I10: 3988 | J10: 4496 | K10: 5910 | L10: 5013 | M10: 5918 | N10: 5453 | O10: 6917 | P10: 5695 | Q10: 5653 | R10: 5442 | S10: 5303 | T10: 4572 | U10: 5228
A11: Gearing | C11: Wegovy injectable | D11: 1404 | E11: 1181 | F11: 1157 | G11: 2446 | H11: 4563 | I11: 7518 | J11: 9648 | K11: 9614 | L11: 9377 | M11: 11659 | N11: 17304 | O11: 19866 | P11: 17360 | Q11: 19528 | R11: 20354 | S11: 21864 | T11: 18235 | U11: 19484
A12: =(B8-B7)/U76 -> 0.73331181 | C12: Wegovy pill | D12: 0 | E12: 0 | F12: 0 | G12: 0 | H12: 0 | I12: 0 | J12: 0 | K12: 0 | L12: 0 | M12: 0 | N12: 0 | O12: 0 | P12: 0 | Q12: 0 | R12: 0 | S12: 0 | T12: 2256 | U12: 3218
C13: Class growth | H13: =(H4-D4)/D4 -> 0.68377074 | I13: =(I4-E4)/E4 -> 0.72011036 | J13: =(J4-F4)/F4 -> 0.72037819 | K13: =(K4-G4)/G4 -> 0.73096548 | L13: =(L4-H4)/H4 -> 0.48030232 | M13: =(M4-I4)/I4 -> 0.60232399 | N13: =(N4-J4)/J4 -> 0.54351358 | O13: =(O4-K4)/K4 -> 0.58896433 | ... W13: =(W4-S4)/S4 -> -1
C14: LLY growth | H14: =(SUM(H5:H7)-SUM(D5:D7))/SUM(D5:D7) -> 0.46189628 | I14: =(SUM(I5:I7)-SUM(E5:E7))/SUM(E5:E7) -> 0.46043203 | J14: =(SUM(J5:J7)-SUM(F5:F7))/SUM(F5:F7) -> 0.51293125 | K14: =(SUM(K5:K7)-SUM(G5:G7))/SUM(G5:G7) -> 0.81541259 | L14: =(SUM(L5:L7)-SUM(H5:H7))/SUM(H5:H7) -> 0.48499371 | M14: =(SUM(M5:M7)-SUM(I5:I7))/SUM(I5:I7) -> 1.0188765 | N14: =(SUM(N5:N7)-SUM(J5:J7))/SUM(J5:J7) -> 0.85864979 | O14: =(SUM(O5:O7)-SUM(K5:K7))/SUM(K5:K7) -> 0.66761945 | ... T14: =(SUM(T5:T7)-SUM(P5:P7))/SUM(P5:P7) -> 0.75640064 | U14: =(SUM(U5:U8)-SUM(Q5:Q7))/SUM(Q5:Q7) -> 0.55849299 | V14: =(SUM(V5:V8)-SUM(R5:R7))/SUM(R5:R7) -> -1 | W14: =(SUM(W5:W8)-SUM(S5:S7))/SUM(S5:S7) -> -1
C15: Novo growth | H15: =(SUM(H9:H11)-SUM(D9:D11))/SUM(D9:D11) -> 0.84227842 | I15: =(SUM(I9:I11)-SUM(E9:E11))/SUM(E9:E11) -> 0.89848605 | J15: =(SUM(J9:J11)-SUM(F9:F11))/SUM(F9:F11) -> 0.85115284 | K15: =(SUM(K9:K11)-SUM(G9:G11))/SUM(G9:G11) -> 0.6799148 | L15: =(SUM(L9:L11)-SUM(H9:H11))/SUM(H9:H11) -> 0.47764277 | M15: =(SUM(M9:M11)-SUM(I9:I11))/SUM(I9:I11) -> 0.38221204 | N15: =(SUM(N9:N11)-SUM(J9:J11))/SUM(J9:J11) -> 0.38114883 | O15: =(SUM(O9:O11)-SUM(K9:K11))/SUM(K9:K11) -> 0.53757988 | ... S15: =(SUM(S9:S11)-SUM(O9:O11))/SUM(O9:O11) -> -0.027112606 | T15: =(SUM(T9:T12)-SUM(P9:P11))/SUM(P9:P11) -> -0.051778543 | U15: =(SUM(U9:U12)-SUM(Q9:Q11))/SUM(Q9:Q11) -> 0.040803791 | V15: =(SUM(V9:V12)-SUM(R9:R11))/SUM(R9:R11) -> -1 | W15: =(SUM(W9:W12)-SUM(S9:S11))/SUM(S9:S11) -> -1
A17: USD/DKK | C17: Injectable GLP-1 | D17: =D18+D19 -> 15357 | E17: =E18+E19 -> 17059 | F17: =F18+F19 -> 19357 | G17: =G18+G19 -> 20299 | H17: =H18+H19 -> 22455 | I17: =I18+I19 -> 23937 | J17: =J18+J19 -> 26139 | K17: =K18+K19 -> 31851 | ... W17: =W18+W19 -> 0 | AA17: =AA18+AA19 -> 18027 | AB17: =AB18+AB19 -> 20046 | AC17: =AC18+AC19 -> 23173 | AD17: =AD18+AD19 -> 26129 | AE17: =AE18+AE19 -> 33171 | AF17: =AF18+AF19 -> 39958 | AG17: =AG18+AG19 -> 48759 | AH17: =AH18+AH19 -> 72072 | ... AK17: =AK18+AK19 -> 130109
A18: 6.47 | C18: Ozempic | D18: 12035 | E18: 14349 | F18: 16390 | G18: 16976 | H18: 19640 | I18: 22101 | J18: 23912 | K18: 30065 | L18: 27810 | M18: 28875 | N18: 29804 | O18: 33853 | P18: 32721 | Q18: 31799 | R18: 30744 | S18: 31825 | T18: 27825 | U18: 31375 | AA18: 0 | AB18: 0 | AC18: 0 | AD18: 1796 | AE18: 11237 | AF18: 21211 | AG18: 33705 | AH18: =SUM(D18:G18) -> 59750 | AI18: =SUM(H18:K18) -> 95718 | AJ18: =SUM(L18:O18) -> 120342 | AK18: =SUM(P18:S18) -> 127089
C19: Victoza | D19: 3322 | E19: 2710 | F19: 2967 | G19: 3323 | H19: 2815 | I19: 1836 | J19: 2227 | K19: 1786 | L19: 2159 | M19: 2242 | N19: -322 | O19: 1403 | P19: 1158 | Q19: 914 | R19: 549 | S19: 399 | T19: 334 | U19: 181 | AA19: 18027 | AB19: 20046 | AC19: 23173 | AD19: 24333 | AE19: 21934 | AF19: 18747 | AG19: 15054 | AH19: =SUM(D19:G19) -> 12322 | AI19: =SUM(H19:K19) -> 8664 | AJ19: =SUM(L19:O19) -> 5482 | AK19: =SUM(P19:S19) -> 3020
C20: Rybelsus | D20: 2063 | E20: 2172 | F20: 3011 | G20: 4053 | H20: 4356 | I20: 3988 | J20: 4496 | K20: 5910 | L20: 5013 | M20: 5918 | N20: 5453 | O20: 6917 | P20: 5695 | Q20: 5653 | R20: 5442 | S20: 5303 | T20: 4572 | U20: 5228 | AA20: 0 | AB20: 0 | AC20: 0 | AD20: 0 | AE20: 50 | AF20: 1873 | AG20: 4838 | AH20: =SUM(D20:G20) -> 11299 | AI20: =SUM(H20:K20) -> 18750 | AJ20: =SUM(L20:O20) -> 23301 | AK20: =SUM(P20:S20) -> 22093
C21: Total GLP-1 | D21: =D17+D20 -> 17420 | E21: =E17+E20 -> 19231 | F21: =F17+F20 -> 22368 | G21: =G17+G20 -> 24352 | H21: =H17+H20 -> 26811 | I21: =I17+I20 -> 27925 | J21: =J17+J20 -> 30635 | K21: =K17+K20 -> 37761 | ... W21: =W17+W20 -> 0 | AA21: =AA17+AA20 -> 18027 | AB21: =AB17+AB20 -> 20046 | AC21: =AC17+AC20 -> 23173 | AD21: =AD17+AD20 -> 26129 | AE21: =AE17+AE20 -> 33221 | AF21: =AF17+AF20 -> 41831 | AG21: =AG17+AG20 -> 53597 | AH21: =AH17+AH20 -> 83371 | ... AK21: =AK17+AK20 -> 152202
C22: Long-acting insulin | D22: =SUM(D23:D26) -> 4796 | E22: =SUM(E23:E26) -> 4104 | F22: =SUM(F23:F26) -> 3939 | G22: =SUM(G23:G26) -> 3902 | H22: =SUM(H23:H26) -> 4133 | I22: =SUM(I23:I26) -> 3354 | J22: =SUM(J23:J26) -> 3692 | K22: =SUM(K23:K26) -> 3726 | ... S22: =SUM(S23:S26) -> 4700 | T22: 4232 | U22: 4412 | V22: =SUM(V23:V26) -> 0 | W22: =SUM(W23:W26) -> 0 | AA22: =SUM(AA23:AA26) -> 19738 | AB22: =SUM(AB23:AB26) -> 21542 | AC22: =SUM(AC23:AC26) -> 22174 | AD22: =SUM(AD23:AD26) -> 20844 | AE22: =SUM(AE23:AE26) -> 20776 | AF22: =SUM(AF23:AF26) -> 18439 | AG22: =SUM(AG23:AG26) -> 18064 | AH22: =SUM(AH23:AH26) -> 16741 | ... AK22: =SUM(AK23:AK26) -> 18755
C23: Tresiba | D23: 2564 | E23: 2269 | F23: 2273 | G23: 2247 | H23: 2179 | I23: 1747 | J23: 1910 | K23: 1916 | L23: 2763 | M23: 2297 | N23: 2110 | O23: 2735 | P23: 3577 | Q23: 2800 | R23: 2624 | S23: 3048 | AA23: 1438 | AB23: 4459 | AC23: 7327 | AD23: 8035 | AE23: 9259 | AF23: 8968 | AG23: 9729 | AH23: =SUM(D23:G23) -> 9353 | AI23: =SUM(H23:K23) -> 7752 | AJ23: =SUM(L23:O23) -> 9905 | AK23: =SUM(P23:S23) -> 12049
C24: Xultophy | D24: 717 | E24: 691 | F24: 705 | G24: 696 | H24: 781 | I24: 854 | J24: 798 | K24: 786 | L24: 1123 | M24: 1067 | N24: 1039 | O24: 1274 | P24: 1209 | Q24: 1132 | R24: 1120 | S24: 1158 | AA24: 0 | AB24: 0 | AC24: 729 | AD24: 1614 | AE24: 2210 | AF24: 2444 | AG24: 2657 | AH24: =SUM(D24:G24) -> 2809 | AI24: =SUM(H24:K24) -> 3219 | AJ24: =SUM(L24:O24) -> 4503 | AK24: =SUM(P24:S24) -> 4619
C25: Levemir | D25: 1515 | E25: 1144 | F25: 961 | G25: 959 | H25: 1173 | I25: 753 | J25: 984 | K25: 1024 | L25: 1279 | M25: 1371 | N25: 879 | O25: 1139 | P25: 543 | Q25: 475 | R25: 314 | S25: 345 | AA25: 18300 | AB25: 17083 | AC25: 14118 | AD25: 11195 | AE25: 9307 | AF25: 7027 | AG25: 5678 | AH25: =SUM(D25:G25) -> 4579 | AI25: =SUM(H25:K25) -> 3934 | AJ25: =SUM(L25:O25) -> 4668 | AK25: =SUM(P25:S25) -> 1677
C26: Awiqli | M26: 2 | N26: 7 | O26: 10 | P26: 59 | Q26: 60 | R26: 142 | S26: 149 | AA26: 0 | AB26: 0 | AC26: 0 | AD26: 0 | AE26: 0 | AF26: 0 | AG26: 0 | AH26: =SUM(D26:G26) -> 0 | AI26: =SUM(H26:K26) -> 0 | AJ26: =SUM(L26:O26) -> 19 | AK26: =SUM(P26:S26) -> 410
C27: Premix insulin | D27: =SUM(D28:D29) -> 3012 | E27: =SUM(E28:E29) -> 2501 | F27: =SUM(F28:F29) -> 2706 | G27: =SUM(G28:G29) -> 2343 | H27: =SUM(H28:H29) -> 2776 | I27: =SUM(I28:I29) -> 2456 | J27: =SUM(J28:J29) -> 2219 | K27: =SUM(K28:K29) -> 2123 | ... S27: =SUM(S28:S29) -> 2509 | T27: 2395 | U27: 2790 | V27: =SUM(V28:V29) -> 0 | W27: =SUM(W28:W29) -> 0 | AA27: =SUM(AA28:AA29) -> 11144 | AB27: =SUM(AB28:AB29) -> 10482 | AC27: =SUM(AC28:AC29) -> 10749 | AD27: =SUM(AD28:AD29) -> 10194 | AE27: =SUM(AE28:AE29) -> 10578 | AF27: =SUM(AF28:AF29) -> 10925 | AG27: =SUM(AG28:AG29) -> 11203 | AH27: =SUM(AH28:AH29) -> 10562 | ... AK27: =SUM(AK28:AK29) -> 10315
C28: Ryzodeg | D28: 637 | E28: 715 | F28: 807 | G28: 730 | H28: 971 | I28: 986 | J28: 864 | K28: 909 | L28: 1267 | M28: 1163 | N28: 1153 | O28: 1346 | P28: 1432 | Q28: 1363 | R28: 1289 | S28: 1298 | AA28: 0 | AB28: 0 | AC28: 492 | AD28: 714 | AE28: 993 | AF28: 1291 | AG28: 1711 | AH28: =SUM(D28:G28) -> 2889 | AI28: =SUM(H28:K28) -> 3730 | AJ28: =SUM(L28:O28) -> 4929 | AK28: =SUM(P28:S28) -> 5382
C29: Novomix | D29: 2375 | E29: 1786 | F29: 1899 | G29: 1613 | H29: 1805 | I29: 1470 | J29: 1355 | K29: 1214 | L29: 1701 | M29: 1273 | N29: 1365 | O29: 1521 | P29: 1381 | Q29: 1273 | R29: 1068 | S29: 1211 | AA29: 11144 | AB29: 10482 | AC29: 10257 | AD29: 9480 | AE29: 9585 | AF29: 9634 | AG29: 9492 | AH29: =SUM(D29:G29) -> 7673 | AI29: =SUM(H29:K29) -> 5844 | AJ29: =SUM(L29:O29) -> 5860 | AK29: =SUM(P29:S29) -> 4933
C30: Fast-acting insulin | D30: =SUM(D31:D32) -> 4842 | E30: =SUM(E31:E32) -> 3887 | F30: =SUM(F31:F32) -> 4263 | G30: =SUM(G31:G32) -> 4471 | H30: =SUM(H31:H32) -> 4488 | I30: =SUM(I31:I32) -> 3511 | J30: =SUM(J31:J32) -> 3808 | K30: =SUM(K31:K32) -> 4142 | ... S30: =SUM(S31:S32) -> 4880 | T30: 3955 | U30: 4691 | V30: =SUM(V31:V32) -> 0 | W30: =SUM(W31:W32) -> 0 | AA30: =SUM(AA31:AA32) -> 20720 | AB30: =SUM(AB31:AB32) -> 19945 | AC30: =SUM(AC31:AC32) -> 20124 | AD30: =SUM(AD31:AD32) -> 19353 | AE30: =SUM(AE31:AE32) -> 19303 | AF30: =SUM(AF31:AF32) -> 18313 | AG30: =SUM(AG31:AG32) -> 17687 | AH30: =SUM(AH31:AH32) -> 17463 | ... AK30: =SUM(AK31:AK32) -> 18583
C31: Fiasp | D31: 497 | E31: 516 | F31: 485 | G31: 505 | H31: 518 | I31: 447 | J31: 574 | K31: 634 | L31: 567 | M31: 565 | N31: 394 | O31: 343 | P31: 834 | Q31: 515 | R31: 632 | S31: 837 | AB31: 0 | AC31: 99 | AD31: 590 | AE31: 1243 | AF31: 1385 | AG31: 1748 | AH31: =SUM(D31:G31) -> 2003 | AI31: =SUM(H31:K31) -> 2173 | AJ31: =SUM(L31:O31) -> 1869 | AK31: =SUM(P31:S31) -> 2818
C32: NovoRapid | D32: 4345 | E32: 3371 | F32: 3778 | G32: 3966 | H32: 3970 | I32: 3064 | J32: 3234 | K32: 3508 | L32: 3920 | M32: 3303 | N32: 3756 | O32: 5674 | P32: 4218 | Q32: 4027 | R32: 3477 | S32: 4043 | AA32: 20720 | AB32: 19945 | AC32: 20025 | AD32: 18763 | AE32: 18060 | AF32: 16928 | AG32: 15939 | AH32: =SUM(D32:G32) -> 15460 | AI32: =SUM(H32:K32) -> 13776 | AJ32: =SUM(L32:O32) -> 16653 | AK32: =SUM(P32:S32) -> 15765
C33: Human insulin | D33: 2312 | E33: 1851 | F33: 2053 | G33: 1970 | H33: 2012 | I33: 1967 | J33: 1626 | K33: 1989 | L33: 1745 | M33: 1571 | N33: 1806 | O33: 1845 | P33: 1744 | Q33: 1101 | R33: 1327 | S33: 1312 | T33: 1063 | U33: 1048 | AA33: 11231 | AB33: 11090 | AC33: 9793 | AD33: 9265 | AE33: 9036 | AF33: 0 | AG33: 9052 | AH33: =SUM(D33:G33) -> 8186 | AI33: =SUM(H33:K33) -> 7594 | AJ33: =SUM(L33:O33) -> 6967 | AK33: =SUM(P33:S33) -> 5484
C34: Total insulin | D34: =D22+D27+D30+D33 -> 14962 | E34: =E22+E27+E30+E33 -> 12343 | F34: =F22+F27+F30+F33 -> 12961 | G34: =G22+G27+G30+G33 -> 12686 | H34: =H22+H27+H30+H33 -> 13409 | I34: =I22+I27+I30+I33 -> 11288 | J34: =J22+J27+J30+J33 -> 11345 | K34: =K22+K27+K30+K33 -> 11980 | ... W34: =W22+W27+W30+W33 -> 0 | AA34: =AA22+AA27+AA30+AA33 -> 62833 | AB34: =AB22+AB27+AB30+AB33 -> 63059 | AC34: =AC22+AC27+AC30+AC33 -> 62840 | AD34: =AD22+AD27+AD30+AD33 -> 59656 | AE34: =AE22+AE27+AE30+AE33 -> 59693 | AF34: =AF22+AF27+AF30+AF33 -> 47677 | AG34: =AG22+AG27+AG30+AG33 -> 56006 | AH34: =AH22+AH27+AH30+AH33 -> 52952 | ... AK34: =AK22+AK27+AK30+AK33 -> 53137
C35: Other diabetes care | D35: 884 | E35: 830 | F35: 798 | G35: 713 | H35: 729 | I35: 667 | J35: 594 | K35: 322 | L35: 583 | M35: 533 | N35: 492 | O35: 512 | P35: 473 | Q35: 454 | R35: 421 | S35: 422 | T35: 560 | U35: 704 | AA35: 4270 | AB35: 4267 | AC35: 4302 | AD35: 4250 | AE35: 4247 | AF35: 4031 | AG35: 3594 | AH35: =SUM(D35:G35) -> 3225 | AI35: =SUM(H35:K35) -> 2312 | AJ35: =SUM(L35:O35) -> 2120 | AK35: =SUM(P35:S35) -> 1770
C36: Total diabetes care | D36: =D21+D34+D35 -> 33266 | E36: =E21+E34+E35 -> 32404 | F36: =F21+F34+F35 -> 36127 | G36: =G21+G34+G35 -> 37751 | H36: =H21+H34+H35 -> 40949 | I36: =I21+I34+I35 -> 39880 | J36: =J21+J34+J35 -> 42574 | K36: =K21+K34+K35 -> 50063 | ... W36: =W21+W34+W35 -> 0 | AA36: =AA21+AA34+AA35 -> 85130 | AB36: =AB21+AB34+AB35 -> 87372 | AC36: =AC21+AC34+AC35 -> 90315 | AD36: =AD21+AD34+AD35 -> 90035 | AE36: =AE21+AE34+AE35 -> 97161 | AF36: =AF21+AF34+AF35 -> 93539 | AG36: =AG21+AG34+AG35 -> 113197 | AH36: =AH21+AH34+AH35 -> 139548 | ... AK36: =AK21+AK34+AK35 -> 207109
C37: Wegovy injectable | D37: 1404 | E37: 1181 | F37: 1157 | G37: 2446 | H37: 4563 | I37: 7518 | J37: 9648 | K37: 9614 | L37: 9377 | M37: 11659 | N37: 17304 | O37: 19866 | P37: 17360 | Q37: 19528 | R37: 20354 | S37: 21864 | T37: 18235 | U37: 19484 | AA37: 0 | AB37: 0 | AC37: 0 | AD37: 0 | AE37: 0 | AF37: 0 | AG37: 0 | AH37: =SUM(D37:G37) -> 6188 | AI37: =SUM(H37:K37) -> 31343 | AJ37: =SUM(L37:O37) -> 58206 | AK37: =SUM(P37:S37) -> 79106
C38: Wegovy pill | T38: 2256 | U38: 3218
C39: Saxenda | D39: 1998 | E39: 2462 | F39: 3174 | G39: 3042 | H39: 3279 | I39: 2788 | J39: 2607 | K39: 1615 | L39: 1658 | M39: 2245 | N39: 1497 | O39: 1540 | P39: 1064 | Q39: 844 | R39: 752 | S39: 581 | T39: 421 | U39: 450 | AA39: 460 | AB39: 1577 | AC39: 2562 | AD39: 3869 | AE39: 5679 | AF39: 5608 | AG39: 8400 | AH39: =SUM(D39:G39) -> 10676 | AI39: =SUM(H39:K39) -> 10289 | AJ39: =SUM(L39:O39) -> 6940 | AK39: =SUM(P39:S39) -> 3241
C40: Total obesity care | D40: =SUM(D37:D39) -> 3402 | E40: =SUM(E37:E39) -> 3643 | F40: =SUM(F37:F39) -> 4331 | G40: =SUM(G37:G39) -> 5488 | H40: =SUM(H37:H39) -> 7842 | I40: =SUM(I37:I39) -> 10306 | J40: =SUM(J37:J39) -> 12255 | K40: =SUM(K37:K39) -> 11229 | ... W40: =SUM(W37:W39) -> 0 | AA40: =SUM(AA37:AA39) -> 460 | AB40: =SUM(AB37:AB39) -> 1577 | AC40: =SUM(AC37:AC39) -> 2562 | AD40: =SUM(AD37:AD39) -> 3869 | AE40: =SUM(AE37:AE39) -> 5679 | AF40: =SUM(AF37:AF39) -> 5608 | AG40: =SUM(AG37:AG39) -> 8400 | AH40: =SUM(AH37:AH39) -> 16864 | ... AK40: =SUM(AK37:AK39) -> 82347
C41: Diabetes and obesity care total | D41: =D36+D40 -> 36668 | E41: =E36+E40 -> 36047 | F41: =F36+F40 -> 40458 | G41: =G36+G40 -> 43239 | H41: =H36+H40 -> 48791 | I41: =I36+I40 -> 50186 | J41: =J36+J40 -> 54829 | K41: =K36+K40 -> 61292 | ... W41: =W36+W40 -> 0 | AA41: =AA36+AA40 -> 85590 | AB41: =AB36+AB40 -> 88949 | AC41: =AC36+AC40 -> 92877 | AD41: =AD36+AD40 -> 93904 | AE41: =AE36+AE40 -> 102840 | AF41: =AF36+AF40 -> 99147 | AG41: =AG36+AG40 -> 121597 | AH41: =AH36+AH40 -> 156412 | ... AK41: =AK36+AK40 -> 289456
C42: Rare blood disorders | D42: =SUM(D43:D46) -> 3077 | E42: =SUM(E43:E46) -> 2863 | F42: =SUM(F43:F46) -> 2885 | G42: =SUM(G43:G46) -> 2881 | H42: =SUM(H43:H46) -> 3049 | I42: =SUM(I43:I46) -> 2836 | J42: =SUM(J43:J46) -> 2957 | K42: =SUM(K43:K46) -> 2934 | ... S42: =SUM(S43:S46) -> 3293 | T42: 2633 | U42: 2896 | V42: =SUM(V43:V46) -> 0 | W42: =SUM(W43:W46) -> 0 | AA42: =SUM(AA43:AA46) -> 22337 | AB42: =SUM(AB43:AB46) -> 22831 | AC42: =SUM(AC43:AC46) -> 12164 | AD42: =SUM(AD43:AD46) -> 11093 | AE42: =SUM(AE43:AE46) -> 11906 | AF42: =SUM(AF43:AF46) -> 9662 | AG42: =SUM(AG43:AG46) -> 10217 | AH42: =SUM(AH43:AH46) -> 11706 | ... AK42: =SUM(AK43:AK46) -> 12386
C43: Haemophilia A | D43: 565 | E43: 619 | F43: 512 | G43: 642 | H43: 660 | I43: 688 | J43: 549 | K43: 525 | L43: 603 | M43: 613 | N43: 568 | O43: 670 | P43: 554 | Q43: 584 | R43: 638 | S43: 638 | AA43: 10647 | AB43: 10472 | AC43: 160 | AD43: 341 | AE43: 3687 | AF43: 0 | AG43: 2112 | AH43: =SUM(D43:G43) -> 2338 | AI43: =SUM(H43:K43) -> 2422 | AJ43: =SUM(L43:O43) -> 2454 | AK43: =SUM(P43:S43) -> 2414
C44: Haemophilia B | D44: 177 | E44: 162 | F44: 194 | G44: 226 | H44: 197 | I44: 250 | J44: 285 | K44: 329 | L44: 262 | M44: 361 | N44: 305 | O44: 378 | P44: 342 | Q44: 338 | R44: 376 | S44: 356 | AA44: 0 | AB44: 0 | AC44: 0 | AD44: 0 | AE44: 0 | AF44: 1462 | AG44: 637 | AH44: =SUM(D44:G44) -> 759 | AI44: =SUM(H44:K44) -> 1061 | AJ44: =SUM(L44:O44) -> 1306 | AK44: =SUM(P44:S44) -> 1412
C45: NovoSeven | D45: 2271 | E45: 2018 | F45: 2108 | G45: 1911 | H45: 2101 | I45: 1794 | J45: 2078 | K45: 1985 | L45: 1952 | M45: 1802 | N45: 2003 | O45: =+N45 -> 2003 | P45: 1879 | Q45: 1991 | R45: 1653 | S45: 1803 | AA45: 7820 | AB45: 8770 | AC45: =9206+1103 -> 10309 | AD45: =7881+1354 -> 9235 | AE45: =8119-1525 -> 6594 | AF45: 7203 | AG45: 7221 | AH45: =SUM(D45:G45) -> 8308 | AI45: =SUM(H45:K45) -> 7958 | AJ45: =SUM(L45:O45) -> 7760 | AK45: =SUM(P45:S45) -> 7326
C46: Other rare blood | D46: =3077-SUM(D43:D45) -> 64 | E46: =2863-E45-E44-E43 -> 64 | F46: =2885-F45-F44-F43 -> 71 | G46: =2881-G45-G44-G43 -> 102 | H46: =3049-H45-H44-H43 -> 91 | I46: =2836-I45-I44-I43 -> 104 | J46: =2957-J45-J44-J43 -> 45 | K46: =2934-K45-K44-K43 -> 95 | L46: =4384-L47-L45-L44-L43 -> 71 | M46: =3976-M47-M45-M44-M43 -> 88 | N46: =4574-N47-N45-N44-N43 -> 112 | O46: =5705-O47-O45-O44-O43 -> 347 | P46: 146 | Q46: 183 | R46: 409 | S46: 496 | AA46: 3870 | AB46: 3589 | AC46: 1695 | AD46: 1517 | AE46: 1625 | AF46: 997 | AG46: 247 | AH46: =SUM(D46:G46) -> 301 | AI46: =SUM(H46:K46) -> 335 | AJ46: =SUM(L46:O46) -> 618 | AK46: =SUM(P46:S46) -> 1234
C47: Rare endocrine disorders + other rare | D47: =1820+466 -> 2286 | E47: =1923+432 -> 2355 | F47: =430+1793 -> 2223 | G47: =370+1602 -> 1972 | H47: =399+1128 -> 1527 | I47: =902+376 -> 1278 | J47: =542+403 -> 945 | K47: =1264+373 -> 1637 | L47: =1113+383 -> 1496 | M47: =730+382 -> 1112 | N47: =1227+359 -> 1586 | O47: =384+1923 -> 2307 | P47: =1312+386 -> 1698 | Q47: =1420+403 -> 1823 | R47: =1393+252 -> 1645 | S47: =1834+222 -> 2056 | T47: =1147+435 -> 1582 | U47: =1538+473 -> 2011 | AA47: 0 | AB47: 0 | AC47: 6655 | AD47: 6834 | AE47: 7275 | AF47: 9264 | AG47: 8986 | AH47: =SUM(D47:G47) -> 8836 | AI47: =SUM(H47:K47) -> 5387 | AJ47: =SUM(L47:O47) -> 6501 | AK47: =SUM(P47:S47) -> 7222
C48: Rare disease total | D48: =D42+D47 -> 5363 | E48: =E42+E47 -> 5218 | F48: =F42+F47 -> 5108 | G48: =G42+G47 -> 4853 | H48: =H42+H47 -> 4576 | I48: =I42+I47 -> 4114 | J48: =J42+J47 -> 3902 | K48: =K42+K47 -> 4571 | ... W48: =W42+W47 -> 0 | AA48: =AA42+AA47 -> 22337 | AB48: =AB42+AB47 -> 22831 | AC48: =AC42+AC47 -> 18819 | AD48: =AD42+AD47 -> 17927 | AE48: =AE42+AE47 -> 19181 | AF48: =AF42+AF47 -> 18926 | AG48: =AG42+AG47 -> 19203 | AH48: =AH42+AH47 -> 20542 | ... AK48: =AK42+AK47 -> 19608
C49: Revenue | D49: 42031 | E49: 41265 | F49: 45566 | G49: 48092 | H49: 53367 | I49: 54300 | J49: 58731 | K49: 65863 | L49: 65349 | M49: 68060 | N49: 71311 | O49: 85683 | P49: 78087 | Q49: 76857 | R49: 74976 | S49: 79144 | T49: =T41+T48 -> 70063 | U49: =U41+U48 -> 78488 | AA49: 107927 | AB49: 111780 | AC49: 111696 | AD49: 111831 | AE49: 122021 | AF49: 126946 | AG49: 140800 | AH49: 176954 | AI49: 232261 | AJ49: 290403 | AK49: 309064 | AL49: =AK49*0.95 -> 293610.8 | AM49: =AL49*1.05 -> 308291.34 | AN49: =AM49*1.07 -> 329871.73 | AO49: =AN49*1.07 -> 352962.76 | AP49: =AO49*1.07 -> 377670.15 | AQ49: =AP49*1.07 -> 404107.06 | AR49: =AQ49*1.07 -> 432394.55 | AS49: =AR49*1.07 -> 462662.17 | AT49: =AS49*1.07 -> 495048.52 | AU49: =AT49*1.07 -> 529701.92
C50: COGS | D50: =D51-D49 -> -6917 | E50: =E51-E49 -> -6069 | F50: =F51-F49 -> -7200 | G50: =G51-G49 -> -8262 | H50: =H51-H49 -> -8182 | I50: =I51-I49 -> -7856 | J50: =J51-J49 -> -9713 | K50: =K51-K49 -> -10014 | ... P50: =P51-P49 -> -12890 | Q50: -12846 | R50: -17904 | S50: =S51-S49 -> -15148 | T50: -13598 | U50: -17100 | AA50: -16188 | AB50: -17183 | AC50: -17632 | AD50: -17617 | AE50: -20088 | AF50: -20932 | AG50: -23658 | AH50: -28448 | AI50: -35765 | AJ50: -44522 | AK50: -58788 | AL50: =AL51-AL49 -> -61658.268 | AM50: =AM51-AM49 -> -58575.355 | AN50: =AN51-AN49 -> -62675.629 | AO50: =AO51-AO49 -> -67062.923 | AP50: =AP51-AP49 -> -71757.328 | AQ50: =AQ51-AQ49 -> -76780.341 | AR50: =AR51-AR49 -> -82154.965 | AS50: =AS51-AS49 -> -87905.813 | ... AU50: =AU51-AU49 -> -100643.36
C51: Gross profit | D51: 35114 | E51: 35196 | F51: 38366 | G51: 39830 | H51: 45185 | I51: 46444 | J51: 49018 | K51: 55849 | L51: 55433 | M51: 57786 | N51: 60003 | O51: 72659 | P51: 65197 | Q51: 64011 | R51: 57072 | S51: 63996 | T51: =SUM(T49:T50) -> 56465 | U51: =SUM(U49:U50) -> 61388 | AA51: =SUM(AA49:AA50) -> 91739 | AB51: =SUM(AB49:AB50) -> 94597 | AC51: =SUM(AC49:AC50) -> 94064 | AD51: =SUM(AD49:AD50) -> 94214 | AE51: =SUM(AE49:AE50) -> 101933 | AF51: =SUM(AF49:AF50) -> 106014 | AG51: =SUM(AG49:AG50) -> 117142 | AH51: =SUM(AH49:AH50) -> 148506 | ... AK51: =SUM(AK49:AK50) -> 250276 | AL51: =AL49*0.79 -> 231952.53 | AM51: =AM49*0.81 -> 249715.99 | AN51: =AN49*0.81 -> 267196.1 | AO51: =AO49*0.81 -> 285899.83 | AP51: =AP49*0.81 -> 305912.82 | AQ51: =AQ49*0.81 -> 327326.72 | AR51: =AR49*0.81 -> 350239.59 | AS51: =AS49*0.81 -> 374756.36 | AT51: =AT49*0.81 -> 400989.3 | AU51: =AU49*0.81 -> 429058.55
C52: Sales and distribution costs | D52: -10183 | E52: -10840 | F52: -11451 | G52: -13743 | H52: -12412 | I52: -14342 | J52: -12819 | K52: -17170 | L52: -13256 | M52: -14934 | N52: -15210 | O52: -18701 | P52: -14892 | Q52: -17533 | R52: -15996 | S52: -15889 | T52: -12077 | U52: -14997 | AA52: -28312 | AB52: -28377 | AC52: -28340 | AD52: -29397 | AE52: -31823 | AF52: -32928 | AG52: -37008 | AH52: -46217 | AI52: -56743 | AJ52: -62101 | AK52: -64310 | AL52: =AK52*0.9 -> -57879 | AM52: =AL52*1.03 -> -59615.37 | AN52: =AM52*1.07 -> -63788.446 | AO52: =AN52*1.07 -> -68253.637 | AP52: =AO52*1.07 -> -73031.392 | AQ52: =AP52*1.07 -> -78143.589 | AR52: =AQ52*1.07 -> -83613.64 | AS52: =AR52*1.07 -> -89466.595 | AT52: =AS52*1.07 -> -95729.257 | AU52: =AT52*1.07 -> -102430.3
C53: R&D | D53: -5206 | E53: -5123 | F53: -5633 | G53: -8085 | H53: -6728 | I53: -7127 | J53: -8128 | K53: -10460 | L53: -8606 | M53: -16166 | N53: -9488 | O53: -13802 | P53: -10308 | Q53: -11690 | R53: -15393 | S53: -14648 | T53: -10284 | U53: -17787 | AA53: -13608 | AB53: -14563 | AC53: -14014 | AD53: -14805 | AE53: -14220 | AF53: -15462 | AG53: -17772 | AH53: -24047 | AI53: -32443 | AJ53: -48062 | AK53: -52039 | AL53: =AK53*0.9 -> -46835.1 | AM53: =AL53*1.06 -> -49645.206 | AN53: =AM53*1.07 -> -53120.37 | AO53: =AN53*1.07 -> -56838.796 | AP53: =AO53*1.07 -> -60817.512 | AQ53: =AP53*1.07 -> -65074.738 | AR53: =AQ53*1.07 -> -69629.97 | AS53: =AR53*1.07 -> -74504.067 | AT53: =AS53*1.07 -> -79719.352 | AU53: =AT53*1.07 -> -85299.707
C54: Admin cost | D54: -970 | E54: -991 | F54: -1158 | G54: -1348 | H54: -1071 | I54: -1072 | J54: -1256 | K54: -1456 | L54: -1157 | M54: -1157 | N54: -1382 | O54: -1580 | P54: -1220 | Q54: -1316 | R54: -1884 | S54: -1549 | T54: -1140 | U54: -1309 | AA54: -3857 | AB54: -3962 | AC54: -3784 | AD54: -3916 | AE54: -4007 | AF54: -3958 | AG54: -4050 | AH54: -4467 | AI54: -4855 | AJ54: -5276 | AK54: -5969 | AL54: =AK54*0.9 -> -5372.1 | AM54: =AL54*1.06 -> -5694.426 | AN54: =AM54*1.07 -> -6093.0358 | AO54: =AN54*1.07 -> -6519.5483 | AP54: =AO54*1.07 -> -6975.9167 | AQ54: =AP54*1.07 -> -7464.2309 | AR54: =AQ54*1.07 -> -7986.727 | AS54: =AR54*1.07 -> -8545.7979 | AT54: =AS54*1.07 -> -9144.0038 | AU54: =AT54*1.07 -> -9784.0841
C55: Other operating income/expense | D55: 392 | E55: 149 | F55: 60 | G55: 433 | H55: 33 | I55: -15 | J55: 98 | K55: 3 | L55: -568 | M55: 405 | N55: -101 | O55: -1839 | P55: 14 | Q55: -23 | R55: -117 | S55: -174 | T55: -106 | U55: -234 | AA55: 3482 | AB55: 737 | AC55: 1041 | AD55: 1152 | AE55: 600 | AF55: 460 | AG55: 332 | AH55: 1034 | AI55: 119 | AJ55: -2103 | AK55: -300 | AL55: =AK55*0.9 -> -270 | AM55: =AL55*1.06 -> -286.2 | AN55: =AM55*1.07 -> -306.234 | AO55: =AN55*1.07 -> -327.67038 | AP55: =AO55*1.07 -> -350.60731 | AQ55: =AP55*1.07 -> -375.14982 | AR55: =AQ55*1.07 -> -401.41031 | AS55: =AR55*1.07 -> -429.50903 | AT55: =AS55*1.07 -> -459.57466 | AU55: =AT55*1.07 -> -491.74488
C56: Operating profit EBIT | D56: =SUM(D51:D55) -> 19147 | E56: =SUM(E51:E55) -> 18391 | F56: =SUM(F51:F55) -> 20184 | G56: =SUM(G51:G55) -> 17087 | H56: =SUM(H51:H55) -> 25007 | I56: =SUM(I51:I55) -> 23888 | J56: =SUM(J51:J55) -> 26913 | K56: =SUM(K51:K55) -> 26766 | ... U56: =SUM(U51:U55) -> 27061 | AA56: =SUM(AA51:AA55) -> 49444 | AB56: =SUM(AB51:AB55) -> 48432 | AC56: =SUM(AC51:AC55) -> 48967 | AD56: =SUM(AD51:AD55) -> 47248 | AE56: =SUM(AE51:AE55) -> 52483 | AF56: =SUM(AF51:AF55) -> 54126 | AG56: =SUM(AG51:AG55) -> 58644 | AH56: =SUM(AH51:AH55) -> 74809 | ... AU56: =SUM(AU51:AU55) -> 231052.71
C57: Financial income | D57: 210 | E57: 1656 | F57: 1573 | G57: -3200 | H57: 0 | I57: -281 | J57: 3318 | K57: -944 | L57: 2146 | M57: 960 | N57: -821 | O57: 3913 | P57: 3425 | Q57: 5314 | R57: 307 | S57: 614 | T57: 6.053 | U57: 1314 | AA57: 85 | AB57: 92 | AC57: 1246 | AD57: 2122 | AE57: 65 | AF57: 1628 | AG57: 2887 | AH57: 239 | AI57: 2945 | AJ57: 6198 | AK57: 9660 | AL57: =AK57*1.03 -> 9949.8 | AM57: =AL57*1.03 -> 10248.294 | AN57: =AM57*1.03 -> 10555.743 | AO57: =AN57*1.03 -> 10872.415 | AP57: =AO57*1.03 -> 11198.588 | AQ57: =AP57*1.03 -> 11534.545 | AR57: =AQ57*1.03 -> 11880.582 | AS57: =AR57*1.03 -> 12236.999 | ... AU57: =AT57*1.03 -> 12982.232
C58: Financial expense | D58: -1438 | E58: -3252 | F58: -3725 | G58: 2429 | H58: -270 | I58: 647 | J58: -2168 | K58: 1798 | L58: -2074 | M58: -1562 | N58: 1383 | O58: -5093 | P58: -5183 | Q58: -4958 | R58: 1528 | S58: 1835 | T58: -13615 | U58: -1500 | AA58: -6046 | AB58: -726 | AC58: -1533 | AD58: -1755 | AE58: -3995 | AF58: -2624 | AG58: -2451 | AH58: -5986 | AI58: -845 | AJ58: -7346 | AK58: -6778 | AL58: =AK58*1.03 -> -6981.34 | AM58: =AL58*1.03 -> -7190.7802 | AN58: =AM58*1.03 -> -7406.5036 | AO58: =AN58*1.03 -> -7628.6987 | AP58: =AO58*1.03 -> -7857.5597 | AQ58: =AP58*1.03 -> -8093.2865 | AR58: =AQ58*1.03 -> -8336.0851 | AS58: =AR58*1.03 -> -8586.1676 | ... AU58: =AT58*1.03 -> -9109.0652
C59: PTP | D59: =SUM(D56:D58) -> 17919 | E59: =SUM(E56:E58) -> 16795 | F59: =SUM(F56:F58) -> 18032 | G59: =SUM(G56:G58) -> 16316 | H59: =SUM(H56:H58) -> 24737 | I59: =SUM(I56:I58) -> 24254 | J59: =SUM(J56:J58) -> 28063 | K59: =SUM(K56:K58) -> 27620 | ... U59: =SUM(U56:U58) -> 26875 | AA59: =SUM(AA56:AA58) -> 43483 | AB59: =SUM(AB56:AB58) -> 47798 | AC59: =SUM(AC56:AC58) -> 48680 | AD59: =SUM(AD56:AD58) -> 47615 | AE59: =SUM(AE56:AE58) -> 48553 | AF59: =SUM(AF56:AF58) -> 53130 | AG59: =SUM(AG56:AG58) -> 59080 | AH59: =SUM(AH56:AH58) -> 69062 | ... AU59: =SUM(AU56:AU58) -> 234925.88
C60: Tax | D60: -3709 | E60: -3477 | F60: -3627 | G60: -2724 | H60: -4923 | I60: -4826 | J60: -5585 | K60: -5657 | L60: -6511 | M60: -5282 | N60: -7083 | O60: -7327 | P60: -7999 | Q60: -7302 | R60: -5511 | S60: -7294 | T60: -13615 | U60: -5886 | AA60: -8623 | AB60: -9873 | AC60: -10550 | AD60: -8987 | AE60: -9602 | AF60: -10992 | AG60: -11323 | AH60: -13537 | AI60: -20991 | AJ60: -26203 | AK60: -28106 | AL60: =AL59*-0.2 -> -24912.958 | AM60: =AM59*-0.2 -> -27506.459 | AN60: =AN59*-0.2 -> -29407.451 | AO60: =AO59*-0.2 -> -31440.779 | AP60: =AP59*-0.2 -> -33615.684 | AQ60: =AQ59*-0.2 -> -35942.054 | AR60: =AR59*-0.2 -> -38430.467 | AS60: =AS59*-0.2 -> -41092.244 | ... AU60: =AU59*-0.2 -> -46985.176
C61: Net income | D61: =SUM(D59:D60) -> 14210 | E61: =SUM(E59:E60) -> 13318 | F61: =SUM(F59:F60) -> 14405 | G61: =SUM(G59:G60) -> 13592 | H61: =SUM(H59:H60) -> 19814 | I61: =SUM(I59:I60) -> 19428 | J61: =SUM(J59:J60) -> 22478 | K61: =SUM(K59:K60) -> 21963 | ... U61: =SUM(U59:U60) -> 20989 | AA61: =SUM(AA59:AA60) -> 34860 | AB61: =SUM(AB59:AB60) -> 37925 | AC61: =SUM(AC59:AC60) -> 38130 | AD61: =SUM(AD59:AD60) -> 38628 | AE61: =SUM(AE59:AE60) -> 38951 | AF61: =SUM(AF59:AF60) -> 42138 | AG61: =SUM(AG59:AG60) -> 47757 | AH61: =SUM(AH59:AH60) -> 55525 | ... AU61: =SUM(AU59:AU60) -> 187940.71 | AV61: =AU61*(1+$AX$67) -> 186061.3 | AW61: =AV61*(1+$AX$67) -> 184200.69 | AX61: =AW61*(1+$AX$67) -> 182358.68 | AY61: =AX61*(1+$AX$67) -> 180535.09 | AZ61: =AY61*(1+$AX$67) -> 178729.74 | BA61: =AZ61*(1+$AX$67) -> 176942.44 | BB61: =BA61*(1+$AX$67) -> 175173.02 | BC61: =BB61*(1+$AX$67) -> 173421.29 | ... EU61: =ET61*(1+$AX$67) -> 66081.682
C62: EPS | D62: =D61/D63 -> 3.1117243 | E62: =E61/E63 -> 2.9256184 | F62: =F61/F63 -> 3.1750055 | G62: =G61/G63 -> 3.005218 | H62: =H61/H63 -> 4.3902331 | I62: =I61/I63 -> 4.3148403 | J62: =J61/J63 -> 5.0073513 | K62: =K61/K63 -> 4.9053022 | ... U62: =U61/U63 -> 4.7180075 | AA62: =AA61/AA63 -> 14.655064 | AB62: =AB61/AB63 -> 15.943583 | AC62: =AC61/AC63 -> 16.029764 | AD62: =AD61/AD63 -> 16.239122 | AE62: =AE61/AE63 -> 16.374911 | AF62: =AF61/AF63 -> 18.007692 | AG62: =AG61/AG63 -> 20.735965 | AH62: =AH61/AH63 -> 12.441183 | ... AU62: =AU61/AU63 -> 42.295646
C63: Shares | D63: 4566.6 | E63: 4552.2 | F63: 4537 | G63: 4522.8 | H63: 4513.2 | I63: 4502.6 | J63: 4489 | K63: 4477.4 | L63: 4470.5 | M63: 4465.4 | N63: 4460.5 | O63: 4455.5 | P63: 4446.4 | Q63: 4443 | R63: 4443.5 | S63: 4443.5 | T63: 4448.7 | U63: 4448.7 | AA63: 2378.7 | AB63: 2378.7 | AC63: 2378.7 | AD63: 2378.7 | AE63: 2378.7 | AF63: 2340 | AG63: 2303.1 | AH63: 4463 | AI63: 4463 | AJ63: 4463 | AK63: 4443.5 | AL63: 4443.5 | AM63: 4443.5 | AN63: 4443.5 | AO63: 4443.5 | AP63: 4443.5 | AQ63: 4443.5 | AR63: 4443.5 | AS63: 4443.5 | AT63: 4443.5 | AU63: 4443.5
C65: Revenue y/y | D65: 0.243 | E65: 0.249 | F65: 0.279 | G65: 0.255 | H65: =(H49-D49)/D49 -> 0.26970569 | I65: =(I49-E49)/E49 -> 0.31588513 | J65: =(J49-F49)/F49 -> 0.28892156 | K65: =(K49-G49)/G49 -> 0.36952092 | L65: =(L49-H49)/H49 -> 0.22452077 | M65: =(M49-I49)/I49 -> 0.253407 | N65: =(N49-J49)/J49 -> 0.21419693 | O65: =(O49-K49)/K49 -> 0.30092768 | ... W65: =(W49-S49)/S49 -> -1 | AB65: =(AB49-AA49)/AA49 -> 0.035700057 | AC65: =(AC49-AB49)/AB49 -> -0.00075147611 | AD65: =(AD49-AC49)/AC49 -> 0.0012086377 | AE65: =(AE49-AD49)/AD49 -> 0.091119636 | AF65: =(AF49-AE49)/AE49 -> 0.040361905 | AG65: =(AG49-AF49)/AF49 -> 0.10913302 | AH65: =(AH49-AG49)/AG49 -> 0.25677557 | AI65: =(AI49-AH49)/AH49 -> 0.31255015 | ... AU65: =(AU49-AT49)/AT49 -> 0.07
C66: Revenue LC | D66: 0.18 | E66: 0.15 | F66: 0.15 | G66: 0.18 | H66: 0.25 | I66: 0.36 | J66: 0.38 | K66: 0.43 | L66: 0.24 | M66: 0.25 | N66: 0.23 | O66: 0.3 | P66: 0.18 | Q66: 0.18 | R66: 0.11 | S66: -0.02 | T66: -0.04 | U66: 0.03 | AA66: 0.084 | AB66: 0.055 | AC66: 0.023 | AD66: 0.046 | AE66: 0.056 | AF66: 0.067 | AG66: 0.138 | AH66: 0.164 | AI66: 0.356 | AJ66: 0.25 | AK66: 0.1 | AL66: -0.04 | AW66: Discount | AX66: 0.08
C67: Ozempic y/y | D67: 0.81 | E67: 0.93 | F67: 0.84 | G67: 0.58 | H67: =(H18-D18)/D18 -> 0.63190694 | I67: =(I18-E18)/E18 -> 0.54024671 | J67: =(J18-F18)/F18 -> 0.45893838 | K67: =(K18-G18)/G18 -> 0.77102969 | L67: =(L18-H18)/H18 -> 0.41598778 | M67: =(M18-I18)/I18 -> 0.30650197 | N67: =(N18-J18)/J18 -> 0.24640348 | O67: =(O18-K18)/K18 -> 0.12599368 | ... W67: =(W18-S18)/S18 -> -1 | AG67: =(AG18-AF18)/AF18 -> 0.58903399 | AH67: =(AH18-AG18)/AG18 -> 0.77273402 | AI67: =(AI18-AH18)/AH18 -> 0.6019749 | AJ67: =(AJ18-AI18)/AI18 -> 0.25725569 | AK67: =(AK18-AJ18)/AJ18 -> 0.056065214 | AL67: =(AL18-AK18)/AK18 -> -1 | AM67: =(AM18-AL18)/AL18 -> #DIV/0! | AN67: =(AN18-AM18)/AM18 -> #DIV/0! | ... AU67: =(AU18-AT18)/AT18 -> #DIV/0! | AW67: TV | AX67: -0.01
C68: GLP y/y | D68: 0.62 | E68: 0.63 | F68: 0.64 | G68: 0.58 | H68: =((H21+H37+H39)-(D21+D37+D39))/(D21+D37+D39) -> 0.66424935 | I68: =((I21+I37+I39)-(E21+E37+E39))/(E21+E37+E39) -> 0.67137361 | J68: =((J21+J37+J39)-(F21+F37+F39))/(F21+F37+F39) -> 0.60642721 | K68: =((K21+K37+K39)-(G21+G37+G39))/(G21+G37+G39) -> 0.64175603 | L68: =((L21+L37+L39)-(H21+H37+H39))/(H21+H37+H39) -> 0.32793698 | M68: =((M21+M37+M39)-(I21+I37+I39))/(I21+I37+I39) -> 0.33240041 | N68: =((N21+N37+N39)-(J21+J37+J39))/(J21+J37+J39) -> 0.25287946 | O68: =((O21+O37+O39)-(K21+K37+K39))/(K21+K37+K39) -> 0.29779547 | ... W68: =((W21+W37+W39)-(S21+S37+S39))/(S21+S37+S39) -> -1 | AG68: =((AG21+AG37+AG39)-(AF21+AF37+AF39))/(AF21+AF37+AF39) -> 0.30687831 | AH68: =((AH21+AH37+AH39)-(AG21+AG37+AG39))/(AG21+AG37+AG39) -> 0.61677178 | AI68: =((AI21+AI37+AI39)-(AH21+AH37+AH39))/(AH21+AH37+AH39) -> 0.64377712 | AJ68: =((AJ21+AJ37+AJ39)-(AI21+AI37+AI39))/(AI21+AI37+AI39) -> 0.30047219 | AK68: =((AK21+AK37+AK39)-(AJ21+AJ37+AJ39))/(AJ21+AJ37+AJ39) -> 0.094637165 | AL68: =((AL21+AL37+AL39)-(AK21+AK37+AK39))/(AK21+AK37+AK39) -> -1 | AM68: =((AM21+AM37+AM39)-(AL21+AL37+AL39))/(AL21+AL37+AL39) -> #DIV/0! | AN68: =((AN21+AN37+AN39)-(AM21+AM37+AM39))/(AM21+AM37+AM39) -> #DIV/0! | ... AU68: =((AU21+AU37+AU39)-(AT21+AT37+AT39))/(AT21+AT37+AT39) -> #DIV/0! | AW68: NPV | AX68: =NPV(AX66,AK61:EU61) -> 1822136
C69: Insulin y/y | D69: 0.01 | E69: -0.06 | F69: -0.07 | G69: -0.09 | H69: =(H34-D34)/D34 -> -0.10379628 | I69: =(I34-E34)/E34 -> -0.085473548 | J69: =(J34-F34)/F34 -> -0.12468174 | K69: =(K34-G34)/G34 -> -0.0556519 | L69: =(L34-H34)/H34 -> 0.071295399 | M69: =(M34-I34)/I34 -> 0.1172927 | N69: =(N34-J34)/J34 -> 0.10260026 | O69: =(O34-K34)/K34 -> 0.32612688 | ... W69: =(W34-S34)/S34 -> -1 | AG69: =(AG34-AF34)/AF34 -> 0.17469639 | AH69: =(AH34-AG34)/AG34 -> -0.054529872 | AI69: =(AI34-AH34)/AH34 -> -0.093103188 | AJ69: =(AJ34-AI34)/AI34 -> 0.15307567 | AK69: =(AK34-AJ34)/AJ34 -> -0.040380691 | AL69: =(AL34-AK34)/AK34 -> -1 | AM69: =(AN34-AL34)/AL34 -> #DIV/0! | AN69: =(AO34-AM34)/AM34 -> #DIV/0! | AO69: =(AP34-AN34)/AN34 -> #DIV/0! | AP69: =(AP34-AO34)/AO34 -> #DIV/0! | AQ69: =(AQ34-AP34)/AP34 -> #DIV/0! | AR69: =(AR34-AQ34)/AQ34 -> #DIV/0! | AS69: =(AS34-AR34)/AR34 -> #DIV/0! | AT69: =(AT34-AS34)/AS34 -> #DIV/0! | AU69: =(AU34-AT34)/AT34 -> #DIV/0! | AW69: S/O | AX69: 4455.5
C70: Gross margin | D70: =D51/D49 -> 0.83543099 | E70: =E51/E49 -> 0.85292621 | F70: =F51/F49 -> 0.84198745 | G70: =G51/G49 -> 0.82820428 | H70: =H51/H49 -> 0.84668428 | I70: =I51/I49 -> 0.85532228 | J70: =J51/J49 -> 0.83461886 | K70: =K51/K49 -> 0.84795712 | ... U70: =U51/U49 -> 0.7821323 | V70: =W51/V49 -> #DIV/0! | W70: =X51/W49 -> #DIV/0! | AA70: =AA51/AA49 -> 0.85000973 | AB70: =AB51/AB49 -> 0.8462784 | AC70: =AC51/AC49 -> 0.84214296 | AD70: =AD51/AD49 -> 0.84246765 | AE70: =AE51/AE49 -> 0.8353726 | AF70: =AF51/AF49 -> 0.83511099 | AG70: =AG51/AG49 -> 0.83197443 | AH70: =AH51/AH49 -> 0.83923506 | ... AU70: =AU51/AU49 -> 0.81 | AW70: NPV/Share | AX70: =AX68/AX69 -> 408.96331
C71: EBIT margin | D71: =D56/D49 -> 0.45554472 | E71: =E56/E49 -> 0.44568036 | F71: =F56/F49 -> 0.44296186 | G71: =G56/G49 -> 0.35529818 | H71: =H56/H49 -> 0.46858546 | I71: =I56/I49 -> 0.43992634 | J71: =J56/J49 -> 0.45824181 | K71: =K56/K49 -> 0.40638902 | ... U71: =U56/U49 -> 0.34477882 | V71: =W56/V49 -> #DIV/0! | W71: =X56/W49 -> #DIV/0! | AA71: =AA56/AA49 -> 0.45812447 | AB71: =AB56/AB49 -> 0.43327966 | AC71: =AC56/AC49 -> 0.43839529 | AD71: =AD56/AD49 -> 0.42249466 | AE71: =AE56/AE49 -> 0.43011449 | AF71: =AF56/AF49 -> 0.42637027 | AG71: =AG56/AG49 -> 0.41650568 | AH71: =AH56/AH49 -> 0.42275959 | ... AU71: =AU56/AU49 -> 0.43619384 | AW71: Opp/nedside | AX71: =(AX70-B4)/B4 -> 0.65773534
C72: ROIC | AA72: 0.799 | AB72: 0.822 | AC72: 0.802 | AD72: 0.76 | AE72: 0.712 | AF72: 0.828 | AG72: 0.69 | AH72: 0.736 | AI72: 0.885 | AJ72: 0.639
C74: EBITDA | D74: =D56+D119 -> 20797 | E74: =E56+E119 -> 20027 | F74: =F56+F119 -> 22225 | G74: =G56+G119 -> 19122 | H74: =H56+H119 -> 26726 | I74: =I56+I119 -> 26065 | J74: =J56+J119 -> 29438 | K74: =K56+K119 -> 29758 | ... U74: =U56+U119 -> 37365 | AA74: =AA56+AA119 -> 52403 | AB74: =AB56+AB119 -> 51625 | AC74: =AC56+AC119 -> 52149 | AD74: =AD56+AD119 -> 51173 | AE74: =AE56+AE119 -> 58044 | AF74: =AF56+AF119 -> 59879 | AG74: =AG56+AG119 -> 64669 | AH74: =AH56+AH119 -> 82171 | ... AK74: =AK56+AK119 -> 149640
C75: EBITDA margin | D75: =D74/D49 -> 0.49480146 | E75: =E74/E49 -> 0.48532655 | F75: =F74/F49 -> 0.48775403 | G75: =G74/G49 -> 0.39761291 | H75: =H74/H49 -> 0.50079637 | I75: =I74/I49 -> 0.48001842 | J75: =J74/J49 -> 0.50123444 | K75: =K74/K49 -> 0.45181665 | ... U75: =U74/U49 -> 0.47606003 | AA75: =AA74/AA49 -> 0.48554115 | AB75: =AB74/AB49 -> 0.46184469 | AC75: =AC74/AC49 -> 0.46688333 | AD75: =AD74/AD49 -> 0.45759226 | AE75: =AE74/AE49 -> 0.47568861 | AF75: =AF74/AF49 -> 0.47168875 | AG75: =AG74/AG49 -> 0.45929687 | AH75: =AH74/AH49 -> 0.46436362 | ... AK75: =AK74/AK49 -> 0.48417156
C76: EBITDA LTM | G76: =SUM(D74:G74) -> 82171 | H76: =SUM(E74:H74) -> 88100 | I76: =SUM(F74:I74) -> 94138 | J76: =SUM(G74:J74) -> 101351 | K76: =SUM(H74:K74) -> 111987 | L76: =SUM(I74:L74) -> 120021 | M76: =SUM(J74:M74) -> 128635 | N76: =SUM(K74:N74) -> 143434 | ... U76: =SUM(R74:U74) -> 142496
C78: Balanse DKKm
C79: Intangible assets | D79: 43344 | E79: 44590 | F79: 46924 | G79: 51416 | H79: 60406 | I79: 60406 | J79: 60406 | K79: 60406 | L79: 59640 | M79: 55501 | N79: 54488 | O79: 111090 | P79: 109379 | Q79: 107866 | R79: 106587 | S79: =110208+19845 -> 130053 | T79: 129910 | U79: 102167 | AH79: 51416 | AI79: 60406 | AJ79: 111090 | AK79: 129910
C80: Goodwill | D80: 0 | E80: 0 | F80: 0 | G80: 0 | H80: 0 | I80: 0 | J80: 0 | K80: 0 | L80: 0 | M80: 0 | N80: 0 | O80: 0 | P80: 0 | Q80: 0 | R80: 0 | S80: 0 | T80: 0 | U80: 19890 | AH80: 0 | AI80: 0 | AJ80: 0 | AK80: 0
C81: PP&E | D81: 56399 | E81: 59556 | F81: 63641 | G81: 66671 | H81: 90961 | I81: 90961 | J81: 90961 | K81: 90961 | L81: 98230 | M81: 109980 | N81: 119832 | O81: 162488 | P81: 172376 | Q81: 180758 | R81: 193244 | S81: 208378 | T81: 219974 | U81: 231758 | AH81: 66671 | AI81: 90961 | AJ81: 162488 | AK81: 219974
C82: Investments in associated companies | D82: 466 | E82: 463 | F82: 458 | G82: 327 | H82: 410 | I82: 410 | J82: 410 | K82: 410 | L82: 407 | M82: 412 | N82: 404 | O82: 400 | P82: 394 | Q82: 390 | R82: 390 | S82: 366 | T82: 207 | U82: 207 | AH82: 327 | AI82: 410 | AJ82: 400 | AK82: 207
C83: Deferred income tax assets | D83: 9338 | E83: 10309 | F83: 11303 | G83: 13427 | H83: 20380 | I83: 20380 | J83: 20380 | K83: 20380 | L83: 20967 | M83: 22565 | N83: 23458 | O83: 24627 | P83: 26275 | Q83: 23747 | R83: 22772 | S83: 23647 | T83: 23787 | U83: 23672 | AH83: 13427 | AI83: 20380 | AJ83: 24627 | AK83: 23787
C84: Other receivables and prepayments | D84: 239 | E84: 252 | F84: 247 | G84: 206 | H84: 1430 | I84: 1430 | J84: 1430 | K84: 1430 | L84: 2012 | M84: 2178 | N84: 2456 | O84: 4016 | P84: 4037 | Q84: 4439 | R84: 5077 | S84: 5864 | T84: 5992 | U84: 6428 | AH84: 206 | AI84: 1430 | AJ84: 4016 | AK84: 5992
C85: Other financial assets | D85: 813 | E85: 779 | F85: 781 | G85: 1016 | H85: 1253 | I85: 1253 | J85: 1253 | K85: 1253 | L85: 1244 | M85: 1247 | N85: 1643 | O85: 2277 | P85: 2306 | Q85: 2248 | R85: 2335 | S85: 2141 | T85: 2034 | U85: 2123 | AH85: 1016 | AI85: 1253 | AJ85: 2277 | AK85: 2034
C86: Inventories | D86: 20289 | E86: 21706 | F86: 23222 | G86: 24388 | H86: 31811 | I86: 31811 | J86: 31811 | K86: 31811 | L86: 33600 | M86: 36356 | N86: 37944 | O86: 40849 | P86: 42853 | Q86: 45652 | R86: 47504 | S86: 49623 | T86: 51352 | U86: 51352 | AH86: 24388 | AI86: 31811 | AJ86: 40849 | AK86: 51352
C87: Trade receivables | D87: 36241 | E87: 40826 | F87: 45563 | G87: 50560 | H87: 64770 | I87: 64770 | J87: 64770 | K87: 64770 | L87: 56999 | M87: 63565 | N87: 66299 | O87: 71949 | P87: 69459 | Q87: 69575 | R87: 75421 | S87: 70856 | T87: 82565 | U87: 88949 | AH87: 50560 | AI87: 64770 | AJ87: 71949 | AK87: 82565
C88: Tax receivables | D88: 3101 | E88: 1168 | F88: 2541 | G88: 940 | H88: 2423 | I88: 2423 | J88: 2423 | K88: 2423 | L88: 6108 | M88: 2898 | N88: 3198 | O88: 2853 | P88: 2983 | Q88: 2995 | R88: 4576 | S88: 4848 | T88: 5238 | U88: 4952 | AH88: 940 | AI88: 2423 | AJ88: 2853 | AK88: 5238
C89: Other receivables and prepayments | D89: 4824 | E89: 4645 | F89: 5406 | G89: 6005 | H89: 8068 | I89: 8068 | J89: 8068 | K89: 8068 | L89: 8643 | M89: 9667 | N89: 10132 | O89: 12612 | P89: 13924 | Q89: 13273 | R89: 12376 | S89: 13482 | T89: 12465 | U89: 14611 | AH89: 6005 | AI89: 8068 | AJ89: 12612 | AK89: 12465
C90: Marketable securities | D90: 6752 | E90: 8279 | F90: 9008 | G90: 10921 | H90: 15838 | I90: 15838 | J90: 15838 | K90: 15838 | L90: 2979 | M90: 9833 | N90: 17863 | O90: 10653 | P90: 2612 | Q90: 499 | R90: 499 | S90: 498 | T90: 499 | U90: 500 | AH90: 10921 | AI90: 15838 | AJ90: 10653 | AK90: 499
C91: Derivative financial instruments | D91: 1936 | E91: 3597 | F91: 5277 | G91: 2727 | H91: 2344 | I91: 2344 | J91: 2344 | K91: 2344 | L91: 1768 | M91: 2360 | N91: 2706 | O91: 6326 | P91: 3626 | Q91: 12276 | R91: 9423 | S91: 6682 | T91: 4071 | U91: 3850 | AH91: 2727 | AI91: 2344 | AJ91: 6326 | AK91: 4071
C92: Cash | D92: 13394 | E92: 22758 | F92: 28465 | G92: 12653 | H92: 14392 | I92: 14392 | J92: 14392 | K92: 14392 | L92: 6324 | M92: 52821 | N92: 57018 | O92: 15655 | P92: 38938 | Q92: 18435 | R92: 32084 | S92: 26464 | T92: 21127 | U92: 44482 | AH92: 12653 | AI92: 14392 | AJ92: 15655 | AK92: 21127
C93: Total Assets | D93: =SUM(D79:D92) -> 197136 | E93: =SUM(E79:E92) -> 218928 | F93: =SUM(F79:F92) -> 242836 | G93: =SUM(G79:G92) -> 241257 | H93: =SUM(H79:H92) -> 314486 | I93: =SUM(I79:I92) -> 314486 | J93: =SUM(J79:J92) -> 314486 | K93: =SUM(K79:K92) -> 314486 | ... U93: =SUM(U79:U92) -> 594941 | AH93: =SUM(AH79:AH92) -> 241257 | AI93: =SUM(AI79:AI92) -> 314486 | AJ93: =SUM(AJ79:AJ92) -> 465795 | AK93: =SUM(AK79:AK92) -> 559221
C94: Share capital | D94: 462 | E94: 456 | F94: 456 | G94: 456 | H94: 451 | I94: 451 | J94: 451 | K94: 451 | L94: 451 | M94: 446 | N94: 446 | O94: 446 | P94: 446 | Q94: 446 | R94: 446 | S94: 446 | T94: 446 | U94: 446 | AH94: 456 | AI94: 451 | AJ94: 446 | AK94: 446
C95: Treasury shares | D95: -7 | E95: -3 | F95: -4 | G95: -6 | H95: -5 | I95: -5 | J95: -5 | K95: -5 | L95: -5 | M95: -1 | N95: -1 | O95: -2 | P95: -2 | Q95: -2 | R95: -2 | S95: -2 | T95: -2 | U95: -4 | AH95: -6 | AI95: -5 | AJ95: -2 | AK95: -2
C96: Retained earnings | D96: 66612 | E96: 73166 | F96: 73673 | G96: 80587 | H96: 104839 | I96: 104839 | J96: 104839 | K96: 104839 | L96: 99050 | M96: 112150 | N96: 121670 | O96: 144448 | P96: 137319 | Q96: 164453 | R96: 168529 | S96: 195298 | T96: 206420 | U96: 224164 | AH96: 80587 | AI96: 104839 | AJ96: 144448 | AK96: 206420
C97: Other reserves | D97: -517 | E97: 833 | F97: 2555 | G97: 2449 | H97: 1276 | I97: 1276 | J97: 1276 | K97: 1276 | L97: -585 | M97: -73 | N97: -1593 | O97: -1406 | P97: 777 | Q97: 3169 | R97: 923 | S97: -1695 | T97: -3799 | U97: -3329 | AH97: 2449 | AI97: 1276 | AJ97: -1406 | AK97: -3799
C98: Total equity | D98: =SUM(D94:D97) -> 66550 | E98: =SUM(E94:E97) -> 74452 | F98: =SUM(F94:F97) -> 76680 | G98: =SUM(G94:G97) -> 83486 | H98: =SUM(H94:H97) -> 106561 | I98: =SUM(I94:I97) -> 106561 | J98: =SUM(J94:J97) -> 106561 | K98: =SUM(K94:K97) -> 106561 | ... U98: =SUM(U94:U97) -> 221277 | AH98: =SUM(AH94:AH97) -> 83486 | AI98: =SUM(AI94:AI97) -> 106561 | AJ98: =SUM(AJ94:AJ97) -> 143486 | AK98: =SUM(AK94:AK97) -> 203065
C99: Borrowings | D99: 24084 | E99: 24178 | F99: 24136 | G99: 24318 | H99: 20528 | I99: 20528 | J99: 20528 | K99: 20528 | L99: 16764 | M99: 51608 | N99: 51452 | O99: 89674 | P99: 96310 | Q99: 87305 | R99: 89180 | S99: 118941 | T99: 119172 | U99: 121794 | AH99: 24318 | AI99: 20528 | AJ99: 89674 | AK99: 119172
C100: Deferred income tax liabilties | D100: 5305 | E100: 5217 | F100: 5640 | G100: 7061 | H100: 10162 | I100: 10162 | J100: 10162 | K100: 10162 | L100: 9664 | M100: 9037 | N100: 8655 | O100: 5426 | P100: 8705 | Q100: 9796 | R100: 9268 | S100: 6611 | T100: 5008 | U100: 4271 | AH100: 7061 | AI100: 10162 | AJ100: 5426 | AK100: 5008
C101: Retirement benefit obligations | D101: 950 | E101: 617 | F101: 583 | G101: 762 | H101: 742 | I101: 742 | J101: 742 | K101: 742 | L101: 784 | M101: 763 | N101: 793 | O101: 903 | P101: 836 | Q101: 810 | R101: 751 | S101: 861 | T101: 824 | U101: 787 | AH101: 762 | AI101: 742 | AJ101: 903 | AK101: 824
C102: Other liabilities | D102: 257 | E102: 167 | F102: 240 | G102: 100 | H102: 189 | I102: 189 | J102: 189 | K102: 189 | L102: 15 | M102: 16 | N102: 16 | O102: 23 | P102: 21 | Q102: 17 | R102: 19 | S102: 0 | T102: 0 | U102: 0 | AH102: 100 | AI102: 189 | AJ102: 23 | AK102: 0
C103: Provisions | D103: 4388 | E103: 4642 | F103: 5300 | G103: 4590 | H103: 6649 | I103: 6649 | J103: 6649 | K103: 6649 | L103: 7177 | M103: 7528 | N103: 7645 | O103: 8755 | P103: 8633 | Q103: 8637 | R103: 8816 | S103: 5730 | T103: 4623 | U103: 6200 | AH103: 4590 | AI103: 6649 | AJ103: 8755 | AK103: 4623
C104: Sales deduction and product returns | D104: 0 | E104: 0 | F104: 0 | G104: 0 | H104: 0 | J104: 0 | K104: 0 | L104: 0 | N104: 0 | O104: 0 | P104: 0 | Q104: 0 | R104: 0 | S104: 1051 | T104: 1371 | U104: 1529 | AH104: 0 | AI104: 0 | AJ104: 0 | AK104: 1371
C105: Borrowings | D105: 1396 | E105: 1256 | F105: 1833 | G105: 1466 | H105: 6478 | I105: 6478 | J105: 6478 | K105: 6478 | L105: 10164 | M105: 5452 | N105: 5520 | O105: 13113 | P105: 22413 | Q105: 11963 | R105: 12034 | S105: 12017 | T105: 27210 | U105: 18333 | AH105: 1466 | AI105: 6478 | AJ105: 13113 | AK105: 27210
C106: Trade payable | D106: 6679 | E106: 14654 | F106: 8310 | G106: 15587 | H106: 25606 | I106: 25606 | J106: 25606 | K106: 25606 | L106: 13006 | M106: 29759 | N106: 24079 | O106: 28846 | P106: 19576 | Q106: 28206 | R106: 23904 | S106: 19758 | T106: 14803 | U106: 14591 | AH106: 15587 | AI106: 25606 | AJ106: 28846 | AK106: 14803
...

Sheet Salg geografisk
B4: DKK million | C4: Q122 | D4: Q222 | E4: Q322 | F4: Q422 | G4: 2022 | H4: Q123 | I4: Q223 | J4: Q323 | K4: Q423 | L4: 2023 | M4: Q124 | N4: Q224 | O4: Q324 | P4: Q424 | Q4: 2024 | R4: Q125 | S4: Q225 | T4: Q325 | U4: Q425 | V4: 2025 | W4: Q126 | X4: Q226 | Y4: Q326 | Z4: Q426 | AA4: 2026
B5: US operations | G5: =SUM(C5:F5) -> 0 | L5: =SUM(H5:K5) -> 0 | Q5: =SUM(M5:P5) -> 0 | R5: 44316 | S5: 42963 | T5: 41144 | U5: 44743 | V5: =SUM(R5:U5) -> 173166 | W5: 35385 | X5: 40869 | AA5: =SUM(W5:Z5) -> 76254
B6: y/y | R6: 0.2 | S6: 0.12 | T6: 0.03 | U6: -0.15 | W6: -0.2 | X6: 0.01
B7: y/y CER | R7: 0.17 | S7: 0.18 | T7: 0.1 | U7: -0.07 | W7: -0.11 | X7: 0.04
B8: International operations | C8: =C9+C12+C15+C18 -> 0 | D8: =D9+D12+D15+D18 -> 0 | E8: =E9+E12+E15+E18 -> 0 | F8: =F9+F12+F15+F18 -> 0 | G8: =G9+G12+G15+G18 -> 0 | H8: =H9+H12+H15+H18 -> 0 | I8: =I9+I12+I15+I18 -> 0 | J8: =J9+J12+J15+J18 -> 0 | ... AA8: =AA9+AA12+AA15+AA18 -> 72297
B9: EUCAN | G9: =SUM(C9:F9) -> 0 | L9: =SUM(H9:K9) -> 0 | Q9: =SUM(M9:P9) -> 0 | R9: 14765 | S9: 16447 | T9: 16767 | U9: 18112 | V9: =SUM(R9:U9) -> 66091 | W9: 17918 | X9: 19206 | AA9: =SUM(W9:Z9) -> 37124
B10: y/y | R10: 0.13 | S10: 0.18 | T10: 0.19 | U10: 0.1 | W10: 0.21 | X10: 0.17
B11: y/y CER | R11: 0.13 | S11: 0.2 | T11: 0.21 | U11: 0.12 | W11: 0.23 | X11: 0.17
B12: Emerging markets | G12: =SUM(C12:F12) -> 0 | L12: =SUM(H12:K12) -> 0 | Q12: =SUM(M12:P12) -> 0 | R12: 8790 | S12: 7544 | T12: 6635 | U12: 7467 | V12: =SUM(R12:U12) -> 30436 | W12: 6861 | X12: 8413 | AA12: =SUM(W12:Z12) -> 15274
B13: y/y | R13: 0.21 | S13: 0.12 | T13: -0.2 | U13: 0.04 | W13: -0.22 | X13: 0.12
B14: y/y CER | R14: 0.24 | S14: 0.2 | T14: -0.15 | U14: 0.09 | W14: -0.18 | X14: 0.05
B15: APAC | G15: =SUM(C15:F15) -> 0 | L15: =SUM(H15:K15) -> 0 | Q15: =SUM(M15:P15) -> 0 | R15: 4594 | S15: 5615 | T15: 5466 | U15: 5038 | V15: =SUM(R15:U15) -> 20713 | W15: 5125 | X15: 5030 | AA15: =SUM(W15:Z15) -> 10155
B16: y/y | R16: 0.24 | S16: 0.4 | T16: 0.26 | U16: -0.06 | W16: 0.12 | X16: -0.1
B17: y/y CER | R17: 0.25 | S17: 0.45 | T17: 0.35 | U17: 0.03 | W17: 0.22 | X17: -0.06
B18: Region China | G18: =SUM(C18:F18) -> 0 | L18: =SUM(H18:K18) -> 0 | Q18: =SUM(M18:P18) -> 0 | R18: 5622 | S18: 4288 | T18: 4964 | U18: 3784 | V18: =SUM(R18:U18) -> 18658 | W18: 4774 | X18: 4970 | AA18: =SUM(W18:Z18) -> 9744
B19: y/y | R19: 0.25 | S19: -0.14 | T19: 0.05 | U19: -0.01 | W19: -0.15 | X19: 0.16
B20: y/y CER | R20: 0.22 | S20: -0.09 | T20: 0.12 | U20: -0.06 | W20: -0.1 | X20: 0.13
B21: Total | G21: =G5+G8 -> 0 | L21: =L5+L8 -> 0 | Q21: =Q5+Q8 -> 0 | R21: =R5+R8 -> 78087 | S21: =S5+S8 -> 76857 | T21: =T5+T8 -> 74976 | U21: =U5+U8 -> 79144 | V21: =V5+V8 -> 309064 | W21: =W5+W8 -> 70063 | X21: =X5+X8 -> 78488 | ... AA21: =AA5+AA8 -> 148551

Sheet Nøkkeltall
D4: 2026 | E4: 2027 | F4: 2028
C5: EV/EBIT | D5: =Modell!$B$9/Modell!AL56 -> 9.8745203 | E5: =Modell!$B$9/Modell!AM56 -> 8.9288521 | F5: =Modell!$B$9/Modell!AN56 -> 8.3447216
C6: P/E | D6: =Modell!$B$4/Modell!AL62 -> 11.000414 | E6: =Modell!$B$4/Modell!AM62 -> 9.9632184 | F6: =Modell!$B$4/Modell!AN62 -> 9.319164

Sheet Nedsidebergning
A3: Nedside | D3: FY 2019 | E3: FY 2020 | F3: FY 2021 | G3: FY 2022 | H3: FY 2023 | I3: FY 2024 | J3: FY 2025 | K3: FY 2026 | L3: FY 2027 | M3: FY 2028 | N3: FY 2029 | O3: FY 2030 | P3: FY 2031 | Q3: FY 2032 | R3: FY 2033 | S3: FY 2034 | T3: FY 2035
A4: Nullvekst og konstante marginer | C4: Revenue | D4: 122021 | E4: 126946 | F4: 140800 | G4: 176954 | H4: 232261 | I4: 290403 | J4: 309064 | K4: =J4*0.94 -> 290520.16 | L4: =K4*1 -> 290520.16 | M4: =L4*1 -> 290520.16 | N4: =M4*1 -> 290520.16 | O4: =N4*1 -> 290520.16 | P4: =O4*1 -> 290520.16 | Q4: =P4*1 -> 290520.16 | R4: =Q4*1 -> 290520.16 | S4: =R4*1 -> 290520.16 | T4: =S4*1 -> 290520.16
A5: =W25 -> 260.40482 | C5: COGS | D5: -20088 | E5: -20932 | F5: -23658 | G5: -28448 | H5: -35765 | I5: -44522 | J5: -58788 | K5: =K6-K4 -> -61009.234 | L5: =L6-L4 -> -61009.234 | M5: =M6-M4 -> -61009.234 | N5: =N6-N4 -> -61009.234 | O5: =O6-O4 -> -61009.234 | P5: =P6-P4 -> -61009.234 | Q5: =Q6-Q4 -> -61009.234 | R5: =R6-R4 -> -61009.234 | ... T5: =T6-T4 -> -61009.234
A6: =W26 -> 0.055552561 | C6: Gross profit | D6: =SUM(D4:D5) -> 101933 | E6: =SUM(E4:E5) -> 106014 | F6: =SUM(F4:F5) -> 117142 | G6: =SUM(G4:G5) -> 148506 | H6: =SUM(H4:H5) -> 196496 | I6: =SUM(I4:I5) -> 245881 | J6: =SUM(J4:J5) -> 250276 | K6: =K4*0.79 -> 229510.93 | L6: =L4*0.79 -> 229510.93 | M6: =M4*0.79 -> 229510.93 | N6: =N4*0.79 -> 229510.93 | O6: =O4*0.79 -> 229510.93 | P6: =P4*0.79 -> 229510.93 | Q6: =Q4*0.79 -> 229510.93 | R6: =R4*0.79 -> 229510.93 | ... T6: =T4*0.79 -> 229510.93
C7: Sales and distribution costs | D7: -31823 | E7: -32928 | F7: -37008 | G7: -46217 | H7: -56743 | I7: -62101 | J7: -64310 | K7: =J7*0.88 -> -56592.8 | L7: =K7 -> -56592.8 | M7: =L7 -> -56592.8 | N7: =M7 -> -56592.8 | O7: =N7 -> -56592.8 | P7: =O7 -> -56592.8 | Q7: =P7 -> -56592.8 | R7: =Q7 -> -56592.8 | S7: =R7 -> -56592.8 | T7: =S7 -> -56592.8
C8: R&D | D8: -14220 | E8: -15462 | F8: -17772 | G8: -24047 | H8: -32443 | I8: -48062 | J8: -52039 | K8: =J8*0.88 -> -45794.32 | L8: =K8 -> -45794.32 | M8: =L8 -> -45794.32 | N8: =M8 -> -45794.32 | O8: =N8 -> -45794.32 | P8: =O8 -> -45794.32 | Q8: =P8 -> -45794.32 | R8: =Q8 -> -45794.32 | S8: =R8 -> -45794.32 | T8: =S8 -> -45794.32
C9: Admin cost | D9: -4007 | E9: -3958 | F9: -4050 | G9: -4467 | H9: -4855 | I9: -5276 | J9: -5969 | K9: =J9*0.88 -> -5252.72 | L9: =K9 -> -5252.72 | M9: =L9 -> -5252.72 | N9: =M9 -> -5252.72 | O9: =N9 -> -5252.72 | P9: =O9 -> -5252.72 | Q9: =P9 -> -5252.72 | R9: =Q9 -> -5252.72 | S9: =R9 -> -5252.72 | T9: =S9 -> -5252.72
C10: Other operating income/expense | D10: 600 | E10: 460 | F10: 332 | G10: 1034 | H10: 119 | I10: -2103 | J10: -300 | K10: =J10*0.88 -> -264 | L10: =K10 -> -264 | M10: =L10 -> -264 | N10: =M10 -> -264 | O10: =N10 -> -264 | P10: =O10 -> -264 | Q10: =P10 -> -264 | R10: =Q10 -> -264 | S10: =R10 -> -264 | T10: =S10 -> -264
C11: Operating profit EBIT | D11: =SUM(D6:D10) -> 52483 | E11: =SUM(E6:E10) -> 54126 | F11: =SUM(F6:F10) -> 58644 | G11: =SUM(G6:G10) -> 74809 | H11: =SUM(H6:H10) -> 102574 | I11: =SUM(I6:I10) -> 128339 | J11: =SUM(J6:J10) -> 127658 | K11: =SUM(K6:K10) -> 121607.09 | ... T11: =SUM(T6:T10) -> 121607.09
C12: Financial income | D12: 65 | E12: 1628 | F12: 2887 | G12: 239 | H12: 2945 | I12: 6198 | J12: 9660 | K12: =J12*1.03 -> 9949.8 | L12: 0 | M12: 0 | N12: 0 | O12: 0 | P12: 0 | Q12: 0 | R12: 0 | S12: 0 | T12: 0
C13: Financial expense | D13: -3995 | E13: -2624 | F13: -2451 | G13: -5986 | H13: -845 | I13: -7346 | J13: -6778 | K13: =J13*1.03 -> -6981.34 | L13: 0 | M13: 0 | N13: 0 | O13: 0 | P13: 0 | Q13: 0 | R13: 0 | S13: 0 | T13: 0
C14: PTP | D14: =SUM(D11:D13) -> 48553 | E14: =SUM(E11:E13) -> 53130 | F14: =SUM(F11:F13) -> 59080 | G14: =SUM(G11:G13) -> 69062 | H14: =SUM(H11:H13) -> 104674 | I14: =SUM(I11:I13) -> 127191 | J14: =SUM(J11:J13) -> 130540 | K14: =SUM(K11:K13) -> 124575.55 | ... T14: =SUM(T11:T13) -> 121607.09
C15: Tax | D15: -9602 | E15: -10992 | F15: -11323 | G15: -13537 | H15: -20991 | I15: -26203 | J15: -28106 | K15: =K14*-0.2 -> -24915.109 | L15: =L14*-0.2 -> -24321.417 | M15: =M14*-0.2 -> -24321.417 | N15: =N14*-0.2 -> -24321.417 | O15: =O14*-0.2 -> -24321.417 | P15: =P14*-0.2 -> -24321.417 | Q15: =Q14*-0.2 -> -24321.417 | R15: =R14*-0.2 -> -24321.417 | ... T15: =T14*-0.2 -> -24321.417
C16: Net income | D16: =SUM(D14:D15) -> 38951 | E16: =SUM(E14:E15) -> 42138 | F16: =SUM(F14:F15) -> 47757 | G16: =SUM(G14:G15) -> 55525 | H16: =SUM(H14:H15) -> 83683 | I16: =SUM(I14:I15) -> 100988 | J16: =SUM(J14:J15) -> 102434 | K16: =SUM(K14:K15) -> 99660.437 | ... T16: =SUM(T14:T15) -> 97285.669 | U16: =T16*(1+$W$22) -> 96312.812 | V16: =U16*(1+$W$22) -> 95349.684 | W16: =V16*(1+$W$22) -> 94396.187 | X16: =W16*(1+$W$22) -> 93452.226 | Y16: =X16*(1+$W$22) -> 92517.703 | Z16: =Y16*(1+$W$22) -> 91592.526 | AA16: =Z16*(1+$W$22) -> 90676.601 | AB16: =AA16*(1+$W$22) -> 89769.835 | ... DT16: =DS16*(1+$W$22) -> 34206.537
C17: EPS | D17: =D16/D18 -> 16.374911 | E17: =E16/E18 -> 18.007692 | F17: =F16/F18 -> 20.735965 | G17: =G16/G18 -> 12.441183 | H17: =H16/H18 -> 18.750392 | I17: =I16/I18 -> 22.627829 | J17: =J16/J18 -> 23.052549 | K17: =K16/K18 -> 22.428364 | ... T17: =T16/T18 -> 21.744673
C18: Shares | D18: 2378.7 | E18: 2340 | F18: 2303.1 | G18: 4463 | H18: 4463 | I18: 4463 | J18: 4443.5 | K18: 4443.5 | L18: 4466 | M18: 4467 | N18: 4468 | O18: 4469 | P18: 4470 | Q18: 4471 | R18: 4472 | S18: 4473 | T18: 4474
C20: Revenue y/y | E20: =(E4-D4)/D4 -> 0.040361905 | F20: =(F4-E4)/E4 -> 0.10913302 | G20: =(G4-F4)/F4 -> 0.25677557 | H20: =(H4-G4)/G4 -> 0.31255015 | I20: =(I4-H4)/H4 -> 0.25033045 | J20: =(J4-I4)/I4 -> 0.064258978 | K20: =(K4-J4)/J4 -> -0.06 | L20: =(L4-K4)/K4 -> 0 | ... T20: =(T4-S4)/S4 -> 0
C21: Revenue LC | D21: 0.056 | E21: 0.067 | F21: 0.138 | G21: 0.164 | H21: 0.356 | I21: 0.25 | J21: 0.1 | K21: -0.06 | V21: Discount | W21: 0.08
C22: Ozempic y/y | V22: TV | W22: -0.01
C23: GLP y/y | V23: NPV | W23: =NPV(W21,J16:DT16) -> 1160233.7
C24: Insulin y/y | V24: S/O | W24: 4455.5
C25: Gross margin | D25: =D6/D4 -> 0.8353726 | E25: =E6/E4 -> 0.83511099 | F25: =F6/F4 -> 0.83197443 | G25: =G6/G4 -> 0.83923506 | H25: =H6/H4 -> 0.84601375 | I25: =I6/I4 -> 0.84668891 | J25: =J6/J4 -> 0.80978697 | K25: =K6/K4 -> 0.79 | ... T25: =T6/T4 -> 0.79 | V25: NPV/Share | W25: =W23/W24 -> 260.40482
A26: Nedside | C26: EBIT margin | D26: =D11/D4 -> 0.43011449 | E26: =E11/E4 -> 0.42637027 | F26: =F11/F4 -> 0.41650568 | G26: =G11/G4 -> 0.42275959 | H26: =H11/H4 -> 0.44163247 | I26: =I11/I4 -> 0.44193414 | J26: =J11/J4 -> 0.41304714 | K26: =K11/K4 -> 0.41858399 | ... T26: =T11/T4 -> 0.41858399 | V26: Opp/nedside | W26: =(W25-Modell!$B$4)/Modell!$B$4 -> 0.055552561
A27: 5% vekst og konstante marginer
A28: =W50 -> 357.58316 | D28: FY 2019 | E28: FY 2020 | F28: FY 2021 | G28: FY 2022 | H28: FY 2023 | I28: FY 2024 | J28: FY 2025 | K28: FY 2026 | L28: FY 2027 | M28: FY 2028 | N28: FY 2029 | O28: FY 2030 | P28: FY 2031 | Q28: FY 2032 | R28: FY 2033 | S28: FY 2034 | T28: FY 2035
A29: =W51 -> 0.44946559 | C29: Revenue | D29: 122021 | E29: 126946 | F29: 140800 | G29: 176954 | H29: 232261 | I29: 290403 | J29: 309064 | K29: =J29*0.94 -> 290520.16 | L29: =K29*1.05 -> 305046.17 | M29: =L29*1.05 -> 320298.48 | N29: =M29*1.05 -> 336313.4 | O29: =N29*1.05 -> 353129.07 | P29: =O29*1.05 -> 370785.52 | Q29: =P29*1.05 -> 389324.8 | R29: =Q29*1.05 -> 408791.04 | S29: =R29*1.05 -> 429230.59 | T29: =S29*1.05 -> 450692.12
C30: COGS | D30: -20088 | E30: -20932 | F30: -23658 | G30: -28448 | H30: -35765 | I30: -44522 | J30: -58788 | K30: =K31-K29 -> -61009.234 | L30: =L31-L29 -> -61009.234 | M30: =M31-M29 -> -64059.695 | N30: =N31-N29 -> -67262.68 | O30: =O31-O29 -> -70625.814 | P30: =P31-P29 -> -74157.105 | Q30: =Q31-Q29 -> -77864.96 | R30: =R31-R29 -> -81758.208 | ... T30: =T31-T29 -> -90138.424
C31: Gross profit | D31: =SUM(D29:D30) -> 101933 | E31: =SUM(E29:E30) -> 106014 | F31: =SUM(F29:F30) -> 117142 | G31: =SUM(G29:G30) -> 148506 | H31: =SUM(H29:H30) -> 196496 | I31: =SUM(I29:I30) -> 245881 | J31: =SUM(J29:J30) -> 250276 | K31: =K29*0.79 -> 229510.93 | L31: =L29*0.8 -> 244036.93 | M31: =M29*0.8 -> 256238.78 | N31: =N29*0.8 -> 269050.72 | O31: =O29*0.8 -> 282503.26 | P31: =P29*0.8 -> 296628.42 | Q31: =Q29*0.8 -> 311459.84 | R31: =R29*0.8 -> 327032.83 | S31: =S29*0.8 -> 343384.47 | T31: =T29*0.8 -> 360553.7
C32: Sales and distribution costs | D32: -31823 | E32: -32928 | F32: -37008 | G32: -46217 | H32: -56743 | I32: -62101 | J32: -64310 | K32: =J32*0.87 -> -55949.7 | L32: =K32*1.05 -> -58747.185 | M32: =L32*1.05 -> -61684.544 | N32: =M32*1.05 -> -64768.771 | O32: =N32*1.05 -> -68007.21 | P32: =O32*1.05 -> -71407.571 | Q32: =P32*1.05 -> -74977.949 | R32: =Q32*1.05 -> -78726.847 | S32: =R32*1.05 -> -82663.189 | T32: =S32*1.05 -> -86796.348
C33: R&D | D33: -14220 | E33: -15462 | F33: -17772 | G33: -24047 | H33: -32443 | I33: -48062 | J33: -52039 | K33: =J33*0.87 -> -45273.93 | L33: =K33*1.05 -> -47537.627 | M33: =L33*1.05 -> -49914.508 | N33: =M33*1.05 -> -52410.233 | O33: =N33*1.05 -> -55030.745 | P33: =O33*1.05 -> -57782.282 | Q33: =P33*1.05 -> -60671.396 | R33: =Q33*1.05 -> -63704.966 | S33: =R33*1.05 -> -66890.214 | T33: =S33*1.05 -> -70234.725
C34: Admin cost | D34: -4007 | E34: -3958 | F34: -4050 | G34: -4467 | H34: -4855 | I34: -5276 | J34: -5969 | K34: =J34*0.87 -> -5193.03 | L34: =K34*1.05 -> -5452.6815 | M34: =L34*1.05 -> -5725.3156 | N34: =M34*1.05 -> -6011.5814 | O34: =N34*1.05 -> -6312.1604 | P34: =O34*1.05 -> -6627.7684 | Q34: =P34*1.05 -> -6959.1569 | R34: =Q34*1.05 -> -7307.1147 | S34: =R34*1.05 -> -7672.4704 | T34: =S34*1.05 -> -8056.094
C35: Other operating income/expense | D35: 600 | E35: 460 | F35: 332 | G35: 1034 | H35: 119 | I35: -2103 | J35: -300 | K35: =J35*0.87 -> -261 | L35: =K35*1.05 -> -274.05 | M35: =L35*1.05 -> -287.7525 | N35: =M35*1.05 -> -302.14013 | O35: =N35*1.05 -> -317.24713 | P35: =O35*1.05 -> -333.10949 | Q35: =P35*1.05 -> -349.76496 | R35: =Q35*1.05 -> -367.25321 | S35: =R35*1.05 -> -385.61587 | T35: =S35*1.05 -> -404.89666
C36: Operating profit EBIT | D36: =SUM(D31:D35) -> 52483 | E36: =SUM(E31:E35) -> 54126 | F36: =SUM(F31:F35) -> 58644 | G36: =SUM(G31:G35) -> 74809 | H36: =SUM(H31:H35) -> 102574 | I36: =SUM(I31:I35) -> 128339 | J36: =SUM(J31:J35) -> 127658 | K36: =SUM(K31:K35) -> 122833.27 | ... T36: =SUM(T31:T35) -> 195061.63
C37: Financial income | D37: 65 | E37: 1628 | F37: 2887 | G37: 239 | H37: 2945 | I37: 6198 | J37: 9660 | K37: =J37*1.03 -> 9949.8 | L37: 0 | M37: 0 | N37: 0 | O37: 0 | P37: 0 | Q37: 0 | R37: 0 | S37: 0 | T37: 0
C38: Financial expense | D38: -3995 | E38: -2624 | F38: -2451 | G38: -5986 | H38: -845 | I38: -7346 | J38: -6778 | K38: =J38*1.03 -> -6981.34 | L38: 0 | M38: 0 | N38: 0 | O38: 0 | P38: 0 | Q38: 0 | R38: 0 | S38: 0 | T38: 0
C39: PTP | D39: =SUM(D36:D38) -> 48553 | E39: =SUM(E36:E38) -> 53130 | F39: =SUM(F36:F38) -> 59080 | G39: =SUM(G36:G38) -> 69062 | H39: =SUM(H36:H38) -> 104674 | I39: =SUM(I36:I38) -> 127191 | J39: =SUM(J36:J38) -> 130540 | K39: =SUM(K36:K38) -> 125801.73 | ... T39: =SUM(T36:T38) -> 195061.63
C40: Tax | D40: -9602 | E40: -10992 | F40: -11323 | G40: -13537 | H40: -20991 | I40: -26203 | J40: -28106 | K40: =K39*-0.2 -> -25160.345 | L40: =L39*-0.2 -> -26405.078 | M40: =M39*-0.2 -> -27725.332 | N40: =N39*-0.2 -> -29111.599 | O40: =O39*-0.2 -> -30567.179 | P40: =P39*-0.2 -> -32095.538 | Q40: =Q39*-0.2 -> -33700.315 | R40: =R39*-0.2 -> -35385.33 | ... T40: =T39*-0.2 -> -39012.327
C41: Net income | D41: =SUM(D39:D40) -> 38951 | E41: =SUM(E39:E40) -> 42138 | F41: =SUM(F39:F40) -> 47757 | G41: =SUM(G39:G40) -> 55525 | H41: =SUM(H39:H40) -> 83683 | I41: =SUM(I39:I40) -> 100988 | J41: =SUM(J39:J40) -> 102434 | K41: =SUM(K39:K40) -> 100641.38 | ... T41: =SUM(T39:T40) -> 156049.31 | U41: =T41*(1+$W$22) -> 154488.81 | V41: =U41*(1+$W$22) -> 152943.93 | W41: =V41*(1+$W$22) -> 151414.49 | X41: =W41*(1+$W$22) -> 149900.34 | Y41: =X41*(1+$W$22) -> 148401.34 | Z41: =Y41*(1+$W$22) -> 146917.32 | AA41: =Z41*(1+$W$22) -> 145448.15 | AB41: =AA41*(1+$W$22) -> 143993.67 | ... DT41: =DS41*(1+$W$22) -> 54868.373
C42: EPS | D42: =D41/D43 -> 16.374911 | E42: =E41/E43 -> 18.007692 | F42: =F41/F43 -> 20.735965 | G42: =G41/G43 -> 12.441183 | H42: =H41/H43 -> 18.750392 | I42: =I41/I43 -> 22.627829 | J42: =J41/J43 -> 23.052549 | K42: =K41/K43 -> 22.649124 | ... T42: =T41/T43 -> 34.879148
C43: Shares | D43: 2378.7 | E43: 2340 | F43: 2303.1 | G43: 4463 | H43: 4463 | I43: 4463 | J43: 4443.5 | K43: 4443.5 | L43: 4466 | M43: 4467 | N43: 4468 | O43: 4469 | P43: 4470 | Q43: 4471 | R43: 4472 | S43: 4473 | T43: 4474
C45: Revenue y/y | E45: =(E29-D29)/D29 -> 0.040361905 | F45: =(F29-E29)/E29 -> 0.10913302 | G45: =(G29-F29)/F29 -> 0.25677557 | H45: =(H29-G29)/G29 -> 0.31255015 | I45: =(I29-H29)/H29 -> 0.25033045 | J45: =(J29-I29)/I29 -> 0.064258978 | K45: =(K29-J29)/J29 -> -0.06 | L45: =(L29-K29)/K29 -> 0.05 | ... T45: =(T29-S29)/S29 -> 0.05
C46: Revenue LC | D46: 0.056 | E46: 0.067 | F46: 0.138 | G46: 0.164 | H46: 0.356 | I46: 0.25 | J46: 0.1 | V46: Discount | W46: 0.08
C47: Ozempic y/y | V47: TV | W47: -0.01
C48: GLP y/y | V48: NPV | W48: =NPV(W46,J41:DT41) -> 1593211.8
C49: Insulin y/y | V49: S/O | W49: 4455.5
C50: Gross margin | D50: =D31/D29 -> 0.8353726 | E50: =E31/E29 -> 0.83511099 | F50: =F31/F29 -> 0.83197443 | G50: =G31/G29 -> 0.83923506 | H50: =H31/H29 -> 0.84601375 | I50: =I31/I29 -> 0.84668891 | J50: =J31/J29 -> 0.80978697 | K50: =K31/K29 -> 0.79 | ... T50: =T31/T29 -> 0.8 | V50: NPV/Share | W50: =W48/W49 -> 357.58316
C51: EBIT margin | D51: =D36/D29 -> 0.43011449 | E51: =E36/E29 -> 0.42637027 | F51: =F36/F29 -> 0.41650568 | G51: =G36/G29 -> 0.42275959 | H51: =H36/H29 -> 0.44163247 | I51: =I36/I29 -> 0.44193414 | J51: =J36/J29 -> 0.41304714 | K51: =K36/K29 -> 0.42280462 | ... T51: =T36/T29 -> 0.43280462 | V51: Opp/nedside | W51: =(W50-Modell!$B$4)/Modell!$B$4 -> 0.44946559

Sheet Ozempic
A1: Info
B3: Brand | C3: Ozempic, fka NN9535
B4: Generic | C4: semaglutide
B5: IP | C5: 7762994 needle delivery expires 2024
C6: 8114833 formulation expires 2025
C7: 8129343 acylated GLP-1 expires 2031
C8: 8536122 acylated GLP-1 expires 2026
C9: 8579869 needle mounting expired 2023
C10: 8684969 injection device expires 2025
C11: 8920383 injection device expires 2026
C12: 9108002 injection device expires 2026
C13: 9132239 injection device expires 2032
C14: 9457154 injection device expires 2027
C15: 9616180 injection device expires 2026
C16: 9687611 injection device expires 2027
C17: 10335462 MOU 2033

Sheet Wegovy
A1: Info
BB3: Brand | BC3: Wegovy, fka NN9535
BB4: Generic | BC4: semaglutide
BB5: Administration | BC5: subcutaneous once-weekly
BB6: Dosage | BC6: 0.25mg, 0.5mg, 1.0mg, 1.7mg, 2.4mg
BB7: Indication | BC7: Obesity, CVOT in overweight/obese with established CV disease
BB8: MOA | BC8: GLP-1 agonist
BB9: Approval | BC9: 6/24/2021 FDA
BC10: 3/2023 Japan
BC11: 6/2024: China
BC12: 15 countries in International as of Q324
BC13: 9/2024: EU label update receives positive CHMP opinion on STEP-HFpEF and STEP-HFpEF-DM
BB14: IP | BC14: Q124: ANDA filed
BB15: Manufacturing | BC15: Second CM in April 2023.
BB16: Clinical Trials
BC17: Phase III "SELECT" CVOT
BC18: 2.4mg subcut reduced MACE by 20%
BC19: Positive CHMP opinion
I21: 15.08.25: | R21: 45884 | AA21: 29.07.25: (dunka ned 23%) | AJ21: 08.07.25: | AS21: 21.06.25:
A22: 22.12.25: | J22: 12.12.25: | BC22: Phase III "STEP" 52-week trial n=616 HFpEF, obesity, T2D
BC23: Dosage: 2.4mg qw
BC24: November 2023 results: KCCQ 16.6 vs 8.7 for placebo
BC25: -13.3% weight loss vs. -2.6% for placebo
BC26: submitted results 1/24 in EU+US, will resubmit in US in 2025 with FLOW data
BC28: Phase III "STEP 9" n=407 obesity in knee OA - 68-weeks
BC29: Dosing: 2.4mg qw
BC30: met WOMAC and weight loss primary endpoints
J60: Gjennomsnittlig vekttap: 20,7% (72 uker)
J61: 1/3 deltakerer gikk ned > 25%

Sheet Rybelsus
A1: Info
B17: 29.03.25:

Sheet Cagrisema
A1: Info
Y2: Målet er å nå et vekttap på mer enn 25% for CagriSema
Y3: Redefine 1 er den viktigste phase 3 studien for den sjekker
Y4: fedme, ikke bare folk med diabetes
V12: Main result (68 uker) | X12: Placebo | AC12: Main result (68 uker) | AE12: Placebo
V13: Subcutaneous (injisert) | W13: -0.137 | X13: -0.034 | AC13: Subcutaneous (injisert) | AD13: -0.204 | AE13: -0.0009
A14: 23.02.26: | I14: 18.12.25:
I15: Forventer svar innen 2026 | O15: 22.06.25: | V15: 45726 | AC15: 20.12.24: Her falt Novo 20%
AC49: Adherent population | AE49: Placebo
V50: Adherent population | X50: Placebo | AC50: Subcutaneous (injisert) | AD50: -0.227 | AE50: -0.003
V51: Subcutaneous (injisert) | W51: -0.157 | X51: -0.031
AC52: Kraftig vekttap 25%>= | AE52: Placebo
V53: Kraftig vekttap 5%>= | X53: Placebo | AC53: populasjon | AD53: 0.404 | AE53: 0.01
V54: populasjon | W54: 0.897 | X54: 0.303
AC55: Enkelte komponeneter
AC56: Cagrilientide | AD56: -0.116
AC57: Semaglutid | AD57: -0.149
AC58: Cagrisema (kombi) | AD58: -0.204
V65: Halvparten i testgruppen opplevde svimmelhet og 25% opplevde oppkast

Sheet Amycretin
A1: Info
H2: Phase 3 will commence in 2026
B22: Weightloss (25.11.25)
D23: Placebo
B24: Subcutaneous (injisert) | C24: -0.145 | D24: -0.025
B25: Oral | C25: -0.101 | D25: -0.026
A28: 25.11.25: | H28: 21.06.25: | N28: 12.06.25: | U28: 24.01.25:
