Workbook

Sheet Info
G3: Synsam lifestyle: Brilleabonnement som kunden betaler fast hver måned.
G4: Du får tilgang til 3 par briller, styrke, solbriller og sportsbriller
G5: Gratis synstest hvert år
G6: Mulighet til å bytte ett åar briller årlig
G7: Linser inkludert ved synsendring
N8: Tilbakekjøpsprogram
G9: Synsam EyeView: Synsams svar på optikermangel i Sverige og Norge | N9: Dato kjøp | O9: Antall aksjer | P9: Akummelert antall aksjer | Q9: Kjøp | R9: Akkumelert kjøp
G10: optiker kan gjennomføre synsundersøkelse delvus eller fullt ut på distanse. | N10: 45901 | O10: 100000 | P10: =O10 -> 100000 | Q10: =1147566+1117700+1136668+1149502+1167842 -> 5719278 | R10: =Q10 -> 5719278
G11: En tekniker er fysisk tilstede i butikken med pasienten og betjener utstyret, | N11: 45908 | O11: 100000 | P11: =SUM(O10:O11) -> 200000
G12: mens kvalifiserte optiker kan sitte et annet sted og tolke resultat digitalt.
G15: Finne info om egen prod og egne merker
G17: Tar 2 år for en nyetablert butikk til å bli like lønnsom som en etablert butikk
A26: Press releases:
A27: 28.09.26: Synsam kjøper tilbake 100 000 akskjer
A28: 21.09.26: Synsam kjøper tilbake 100 000 aksjer
A29: 14.09.26: Synsam inngår samarbeid med Carola og blir en ambasadør for Synsam. Hennes egen kolleksjon vil bli tilgjengligjort for salg tidlig 2027
A30: 14.09.26: Synsam kjøper tilbake 100 000 aksjer
A31: 07.09.26: Synsam kjøper tilbake 100 000 aksjer
A32: 31.08.26: Synsam kjøper tilbake 100 000 aksjer
A33: 24.08.26: Synsam kjøper tilbale 95 000 aksjer
A34: 17.08.26: Synsam kjøper tilbake 100 000 aksjer
A35: 10.08.26: Synsam kjøper tilbake 104 000 aksjer
A36: 03.08.26: Synsam kjøper tilbake 122 000 aksjer
A37: 27.07.26: Synsam kjøper tilbake 50 000 aksjer
... A78: 21.08.25: Synsam starter tilbakekjøpsprgram for å justerer kapitalstrukturen sin 160 SEKm

Sheet Modell
A3: Kapitalstruktur | C3: SEKm | D3: Q122 | E3: Q222 | F3: Q322 | G3: Q422 | H3: Q123 | I3: Q223 | J3: Q323 | K3: Q423 | L3: Q124 | M3: Q224 | N3: Q324 | O3: Q424 | P3: Q125 | Q3: Q225 | R3: Q325 | S3: Q425 | T3: Q126 | U3: Q226 | V3: Q326 | W3: Q426 | Z3: FY 2020 | AA3: FY 2021 | AB3: FY 2022 | AC3: FY 2023 | AD3: FY 2024 | AE3: FY 2025 | AF3: FY 2026 | AG3: FY 2027 | AH3: FY 2028 | AI3: FY 2029 | AJ3: FY 2030 | AK3: FY 2031 | AL3: FY 2032 | AM3: FY 2033 | AN3: FY 2034 | AO3: FY 2035
A4: Price | B4: 53 | C4: Revenue | D4: 1204 | E4: 1415 | F4: 1335 | G4: 1395 | H4: 1425 | I4: 1584 | J4: 1479 | K4: 1497 | L4: 1536 | M4: 1744 | N4: 1583 | O4: 1659 | P4: 1735 | Q4: 1877 | R4: 1753 | S4: 1834 | T4: 1801 | U4: 2081 | Z4: 3860 | AA4: 4728 | AB4: 5349 | AC4: 5985 | AD4: 6522 | AE4: 7200 | AF4: =AE4*1.073 -> 7725.6 | AG4: =AF4*1.06 -> 8189.136 | AH4: =AG4*1.06 -> 8680.4842 | AI4: =AH4*1.06 -> 9201.3132 | AJ4: =AI4*1.06 -> 9753.392 | AK4: =AJ4*1.06 -> 10338.596 | AL4: =AK4*1.06 -> 10958.911 | AM4: =AL4*1.06 -> 11616.446 | AN4: =AM4*1.06 -> 12313.433 | AO4: =AN4*1.06 -> 13052.239
A5: S/O | B5: 142.81814 | C5: Goods for resale | D5: -246 | E5: -368 | F5: -345 | G5: -319 | H5: -331 | I5: -407 | J5: -364 | K5: -345 | L5: -369 | M5: -443 | N5: -407 | O5: -371 | P5: -442 | Q5: -495 | R5: -465 | S5: -419 | T5: -429 | U5: -541 | Z5: -953 | AA5: -1088 | AB5: -1279 | AC5: -1447 | AD5: -1591 | AE5: -1821 | AF5: =AF4*-0.25 -> -1931.4 | AG5: =AG4*-0.25 -> -2047.284 | AH5: =AH4*-0.25 -> -2170.121 | AI5: =AI4*-0.25 -> -2300.3283 | AJ5: =AJ4*-0.25 -> -2438.348 | AK5: =AK4*-0.25 -> -2584.6489 | AL5: =AL4*-0.25 -> -2739.7278 | AM5: =AM4*-0.25 -> -2904.1115 | ... AO5: =AO4*-0.25 -> -3263.0597
A6: MC SEKm | B6: =B4*B5 -> 7569.3614 | C6: Gross profit | D6: =SUM(D4:D5) -> 958 | E6: =SUM(E4:E5) -> 1047 | F6: =SUM(F4:F5) -> 990 | G6: =SUM(G4:G5) -> 1076 | H6: =SUM(H4:H5) -> 1094 | I6: =SUM(I4:I5) -> 1177 | J6: =SUM(J4:J5) -> 1115 | K6: =SUM(K4:K5) -> 1152 | ... U6: =SUM(U4:U5) -> 1540 | Z6: =SUM(Z4:Z5) -> 2907 | AA6: =SUM(AA4:AA5) -> 3640 | AB6: =SUM(AB4:AB5) -> 4070 | AC6: =SUM(AC4:AC5) -> 4538 | AD6: =SUM(AD4:AD5) -> 4931 | AE6: =SUM(AE4:AE5) -> 5379 | AF6: =SUM(AF4:AF5) -> 5794.2 | AG6: =SUM(AG4:AG5) -> 6141.852 | ... AO6: =SUM(AO4:AO5) -> 9789.179
A7: Cash SEKm | B7: =U53 -> 648 | C7: Other external expenses | D7: -153 | E7: -168 | F7: -168 | G7: -179 | H7: -176 | I7: -169 | J7: -164 | K7: -173 | L7: -174 | M7: -178 | N7: -174 | O7: -186 | P7: -191 | Q7: -204 | R7: -188 | S7: -221 | T7: -210 | U7: -243 | Z7: -468 | AA7: -629 | AB7: -667 | AC7: -682 | AD7: -711 | AE7: -805 | AF7: =AE7*1.07 -> -861.35 | AG7: =AF7*1.055 -> -908.72425 | AH7: =AG7*1.055 -> -958.70408 | AI7: =AH7*1.06 -> -1016.2263 | AJ7: =AI7*1.06 -> -1077.1999 | AK7: =AJ7*1.06 -> -1141.8319 | AL7: =AK7*1.06 -> -1210.3418 | AM7: =AL7*1.06 -> -1282.9623 | AN7: =AM7*1.06 -> -1359.9401 | AO7: =AN7*1.06 -> -1441.5365
A8: Debt SEKm | B8: =U56+U61+U57+U62 -> 3653 | C8: Persnonnel costs | D8: -512 | E8: -531 | F8: -520 | G8: -624 | H8: -600 | I8: -607 | J8: -577 | K8: -631 | L8: -634 | M8: -654 | N8: -621 | O8: -715 | P8: -727 | Q8: -708 | R8: -682 | S8: -768 | T8: -762 | U8: -784 | Z8: -1505 | AA8: -1823 | AB8: -2186 | AC8: -2415 | AD8: -2624 | AE8: -2886 | AF8: =AE8*1.07 -> -3088.02 | AG8: =AF8*1.055 -> -3257.8611 | AH8: =AG8*1.055 -> -3437.0435 | AI8: =AH8*1.06 -> -3643.2661 | AJ8: =AI8*1.06 -> -3861.862 | AK8: =AJ8*1.06 -> -4093.5738 | AL8: =AK8*1.06 -> -4339.1882 | AM8: =AL8*1.06 -> -4599.5395 | AN8: =AM8*1.06 -> -4875.5118 | AO8: =AN8*1.06 -> -5168.0425
A9: EV SEKm | B9: =B6-B7+B8 -> 10574.361 | C9: EBITDA | D9: =SUM(D6:D8) -> 293 | E9: =SUM(E6:E8) -> 348 | F9: =SUM(F6:F8) -> 302 | G9: =SUM(G6:G8) -> 273 | H9: =SUM(H6:H8) -> 318 | I9: =SUM(I6:I8) -> 401 | J9: =SUM(J6:J8) -> 374 | K9: =SUM(K6:K8) -> 348 | ... U9: =SUM(U6:U8) -> 513 | Z9: =SUM(Z6:Z8) -> 934 | AA9: =SUM(AA6:AA8) -> 1188 | AB9: =SUM(AB6:AB8) -> 1217 | AC9: =SUM(AC6:AC8) -> 1441 | AD9: =SUM(AD6:AD8) -> 1596 | AE9: =SUM(AE6:AE8) -> 1688 | AF9: =SUM(AF6:AF8) -> 1844.83 | AG9: =SUM(AG6:AG8) -> 1975.2667 | ... AO9: =SUM(AO6:AO8) -> 3179.6
C10: Depreciation | D10: -116 | E10: -123 | F10: -134 | G10: -146 | H10: -147 | I10: -144 | J10: -151 | K10: -148 | L10: -153 | M10: -157 | N10: -161 | O10: -168 | P10: -168 | Q10: -171 | R10: -179 | S10: -180 | T10: -182 | U10: -187 | Z10: -445 | AA10: -464 | AB10: -556 | AC10: -622 | AD10: -649 | AE10: -702 | AF10: -740 | AG10: =AF10*1.06 -> -784.4 | AH10: =AG10*1.01 -> -792.244 | AI10: =AH10*1.01 -> -800.16644 | AJ10: =AI10*1.01 -> -808.1681 | AK10: =AJ10*1.01 -> -816.24979 | AL10: =AK10*1.01 -> -824.41228 | AM10: =AL10*1.01 -> -832.65641 | AN10: =AM10*1.01 -> -840.98297 | AO10: =AN10*1.01 -> -849.3928
C11: EBITA | D11: =SUM(D9:D10) -> 177 | E11: =SUM(E9:E10) -> 225 | F11: =SUM(F9:F10) -> 168 | G11: =SUM(G9:G10) -> 127 | H11: =SUM(H9:H10) -> 171 | I11: =SUM(I9:I10) -> 257 | J11: =SUM(J9:J10) -> 223 | K11: =SUM(K9:K10) -> 200 | ... U11: =SUM(U9:U10) -> 326 | Z11: =SUM(Z9:Z10) -> 489 | AA11: =SUM(AA9:AA10) -> 724 | AB11: =SUM(AB9:AB10) -> 661 | AC11: =SUM(AC9:AC10) -> 819 | AD11: =SUM(AD9:AD10) -> 947 | AE11: =SUM(AE9:AE10) -> 986 | AF11: =SUM(AF9:AF10) -> 1104.83 | AG11: =SUM(AG9:AG10) -> 1190.8666 | ... AO11: =SUM(AO9:AO10) -> 2330.2072
C12: Amortization | D12: -36 | E12: -36 | F12: -36 | G12: -37 | H12: -38 | I12: -38 | J12: -39 | K12: -39 | L12: -35 | M12: -37 | N12: -33 | O12: -33 | P12: -33 | Q12: -32 | R12: -32 | S12: -32 | T12: -32 | U12: -36 | Z12: -87 | AA12: -91 | AB12: -109 | AC12: -123 | AD12: -128 | AE12: -124 | AF12: -128 | AG12: =AF12*1.04 -> -133.12 | AH12: =AG12*1.01 -> -134.4512 | AI12: =AH12*1.01 -> -135.79571 | AJ12: =AI12*1.01 -> -137.15367 | AK12: =AJ12*1.01 -> -138.52521 | AL12: =AK12*1.01 -> -139.91046 | AM12: =AL12*1.01 -> -141.30956 | AN12: =AM12*1.01 -> -142.72266 | AO12: =AN12*1.01 -> -144.14988
A13: Gearing | B13: =(B8-B7)/AF9 -> 1.6288764 | C13: EBIT | D13: =SUM(D11:D12) -> 141 | E13: =SUM(E11:E12) -> 189 | F13: =SUM(F11:F12) -> 132 | G13: =SUM(G11:G12) -> 90 | H13: =SUM(H11:H12) -> 133 | I13: =SUM(I11:I12) -> 219 | J13: =SUM(J11:J12) -> 184 | K13: =SUM(K11:K12) -> 161 | ... U13: =SUM(U11:U12) -> 290 | Z13: =SUM(Z11:Z12) -> 402 | AA13: =SUM(AA11:AA12) -> 633 | AB13: =SUM(AB11:AB12) -> 552 | AC13: =SUM(AC11:AC12) -> 696 | AD13: =SUM(AD11:AD12) -> 819 | AE13: =SUM(AE11:AE12) -> 862 | AF13: =SUM(AF11:AF12) -> 976.83 | AG13: =SUM(AG11:AG12) -> 1057.7467 | ... AO13: =SUM(AO11:AO12) -> 2186.0573
C14: Fincial income | D14: 53 | E14: 19 | F14: 52 | G14: 60 | H14: 60 | I14: 69 | J14: 69 | K14: 75 | L14: 79 | M14: 84 | N14: 76 | O14: 87 | P14: 87 | Q14: 84 | R14: 77 | S14: 95 | T14: 120 | U14: 74 | Z14: 98 | AA14: 148 | AB14: 185 | AC14: 273 | AD14: 326 | AE14: 321 | AF14: =AE14*1.02 -> 327.42 | AG14: =AF14*1.02 -> 333.9684 | AH14: =AG14*1.02 -> 340.64777 | AI14: =AH14*1.02 -> 347.46072 | AJ14: =AI14*1.02 -> 354.40994 | AK14: =AJ14*1.02 -> 361.49814 | AL14: =AK14*1.02 -> 368.7281 | AM14: =AL14*1.02 -> 376.10266 | ... AO14: =AN14*1.02 -> 391.29721
A15: P/B | B15: =B6/+T55 -> 2.90459 | C15: Financial expenses | D15: -66 | E15: -79 | F15: -87 | G15: -91 | H15: -149 | I15: -124 | J15: -137 | K15: -144 | L15: -172 | M15: -147 | N15: -172 | O15: -160 | P15: -146 | Q15: -204 | R15: -119 | S15: -147 | T15: -142 | U15: -164 | Z15: -636 | AA15: -618 | AB15: -322 | AC15: -554 | AD15: -652 | AE15: -593 | AF15: =AE15*1.02 -> -604.86 | AG15: =AF15*1.02 -> -616.9572 | AH15: =AG15*1.02 -> -629.29634 | AI15: =AH15*1.02 -> -641.88227 | AJ15: =AI15*1.02 -> -654.71992 | AK15: =AJ15*1.02 -> -667.81431 | AL15: =AK15*1.02 -> -681.1706 | AM15: =AL15*1.02 -> -694.79401 | ... AO15: =AN15*1.02 -> -722.86369
C16: PTP | D16: =SUM(D13:D15) -> 128 | E16: =SUM(E13:E15) -> 129 | F16: =SUM(F13:F15) -> 97 | G16: =SUM(G13:G15) -> 59 | H16: =SUM(H13:H15) -> 44 | I16: =SUM(I13:I15) -> 164 | J16: =SUM(J13:J15) -> 116 | K16: =SUM(K13:K15) -> 92 | ... U16: =SUM(U13:U15) -> 200 | Z16: =SUM(Z13:Z15) -> -136 | AA16: =SUM(AA13:AA15) -> 163 | AB16: =SUM(AB13:AB15) -> 415 | AC16: =SUM(AC13:AC15) -> 415 | AD16: =SUM(AD13:AD15) -> 493 | AE16: =SUM(AE13:AE15) -> 590 | AF16: =SUM(AF13:AF15) -> 699.39 | AG16: =SUM(AG13:AG15) -> 774.75785 | ... AO16: =SUM(AO13:AO15) -> 1854.4908
C17: Tax | D17: -30 | E17: -31 | F17: -18 | G17: -8 | H17: -25 | I17: -24 | J17: -25 | K17: -30 | L17: -21 | M17: -44 | N17: -25 | O17: -37 | P17: -28 | Q17: -33 | R17: -35 | S17: -40 | T17: -34 | U17: -8 | Z17: -59 | AA17: -112 | AB17: -87 | AC17: -104 | AD17: -127 | AE17: -136 | AF17: =AF16*-0.2 -> -139.878 | AG17: =AG16*-0.2 -> -154.95157 | AH17: =AH16*-0.2 -> -179.85436 | AI17: =AI16*-0.2 -> -202.22176 | AJ17: =AJ16*-0.2 -> -226.07006 | AK17: =AK16*-0.2 -> -251.48996 | AL17: =AL16*-0.2 -> -278.57764 | AM17: =AM16*-0.2 -> -307.43507 | ... AO17: =AO16*-0.2 -> -370.89816
C18: Net income | D18: =SUM(D16:D17) -> 98 | E18: =SUM(E16:E17) -> 98 | F18: =SUM(F16:F17) -> 79 | G18: =SUM(G16:G17) -> 51 | H18: =SUM(H16:H17) -> 19 | I18: =SUM(I16:I17) -> 140 | J18: =SUM(J16:J17) -> 91 | K18: =SUM(K16:K17) -> 62 | ... U18: =SUM(U16:U17) -> 192 | Z18: =SUM(Z16:Z17) -> -195 | AA18: =SUM(AA16:AA17) -> 51 | AB18: =SUM(AB16:AB17) -> 328 | AC18: =SUM(AC16:AC17) -> 311 | AD18: =SUM(AD16:AD17) -> 366 | AE18: =SUM(AE16:AE17) -> 454 | AF18: =SUM(AF16:AF17) -> 559.512 | AG18: =SUM(AG16:AG17) -> 619.80628 | ... AO18: =SUM(AO16:AO17) -> 1483.5926 | AP18: =AO18*(1+$AR$22) -> 1468.7567 | AQ18: =AP18*(1+$AR$22) -> 1454.0691 | AR18: =AQ18*(1+$AR$22) -> 1439.5285 | AS18: =AR18*(1+$AR$22) -> 1425.1332 | AT18: =AS18*(1+$AR$22) -> 1410.8818 | AU18: =AT18*(1+$AR$22) -> 1396.773 | AV18: =AU18*(1+$AR$22) -> 1382.8053 | AW18: =AV18*(1+$AR$22) -> 1368.9772 | ... GW18: =GV18*(1+$AR$22) -> 285.42143
C19: Share | L19: 147.6 | M19: 146.64875 | N19: 147.82345 | O19: 146.64875 | P19: 144.51324 | Q19: 142.81814 | R19: 143.9736 | S19: 142.81814 | T19: 141.96249 | U19: 141.96249 | Z19: 37.181942 | AA19: 150 | AB19: 149.055 | AC19: 147.42368 | AD19: 146.64875 | AE19: 142.81814 | AF19: 141.96249 | AG19: 141.96249 | AH19: 141.96249 | AI19: 141.96249 | AJ19: 141.96249 | AK19: 141.96249 | AL19: 141.96249 | AM19: 141.96249 | AN19: 141.96249 | AO19: 141.96249
C20: EPS | D20: =D18/D19 -> #DIV/0! | E20: =E18/E19 -> #DIV/0! | F20: =F18/F19 -> #DIV/0! | G20: =G18/G19 -> #DIV/0! | H20: =H18/H19 -> #DIV/0! | I20: =I18/I19 -> #DIV/0! | J20: =J18/J19 -> #DIV/0! | K20: =K18/K19 -> #DIV/0! | ... U20: =U18/U19 -> 1.3524699 | Z20: =Z18/Z19 -> -5.2444813 | AA20: =AA18/AA19 -> 0.34 | AB20: =AB18/AB19 -> 2.20053 | AC20: =AC18/AC19 -> 2.1095662 | AD20: =AD18/AD19 -> 2.4957595 | AE20: =AE18/AE19 -> 3.1788679 | AF20: =AF18/AF19 -> 3.9412663 | AG20: =AG18/AG19 -> 4.3659861 | ... AO20: =AO18/AO19 -> 10.450596
AQ21: Discount | AR21: 0.08
C22: Revenue y/y | H22: =(H4-D4)/D4 -> 0.18355482 | I22: =(I4-E4)/E4 -> 0.11943463 | J22: =(J4-F4)/F4 -> 0.10786517 | K22: =(K4-G4)/G4 -> 0.07311828 | L22: =(L4-H4)/H4 -> 0.077894737 | M22: =(M4-I4)/I4 -> 0.1010101 | N22: =(N4-J4)/J4 -> 0.070317782 | O22: =(O4-K4)/K4 -> 0.10821643 | ... U22: =(U4-Q4)/Q4 -> 0.10868407 | AA22: =(AA4-Z4)/Z4 -> 0.22487047 | AB22: =(AB4-AA4)/AA4 -> 0.13134518 | AC22: =(AC4-AB4)/AB4 -> 0.11890073 | AD22: =(AD4-AC4)/AC4 -> 0.089724311 | AE22: =(AE4-AD4)/AD4 -> 0.10395584 | AF22: =(AF4-AE4)/AE4 -> 0.073 | AG22: =(AG4-AF4)/AF4 -> 0.06 | AH22: =(AH4-AG4)/AG4 -> 0.06 | ... AO22: =(AO4-AN4)/AN4 -> 0.06 | AQ22: TV | AR22: -0.01
C23: Organic growth | D23: 0.123 | E23: 0.137 | F23: 0.096 | G23: 0.068 | H23: 0.175 | I23: 0.102 | J23: 0.07 | K23: 0.074 | L23: 0.077 | M23: 0.095 | N23: 0.094 | O23: 0.101 | P23: 0.128 | Q23: 0.091 | R23: 0.124 | S23: 0.114 | T23: 0.056 | U23: 0.098 | Z23: 0.032 | AA23: 0.232 | AB23: 0.106 | AC23: 0.103 | AD23: 0.092 | AE23: 0.114 | AQ23: NPV | AR23: =NPV(AR21,AF18:GW18) -> 13702.005
C24: Like-for-like | D24: 0.081 | E24: 0.095 | F24: 0.055 | G24: 0.04 | H24: 0.14 | I24: 0.07 | J24: 0.039 | K24: 0.043 | L24: 0.051 | M24: 0.068 | N24: 0.063 | O24: 0.061 | P24: 0.089 | Q24: 0.056 | R24: 0.091 | S24: 0.091 | T24: 0.038 | U24: 0.08 | AQ24: S/O | AR24: 141.96249
AQ25: NPV/Share | AR25: =AR23/AR24 -> 96.518485
C26: Gross margin | D26: =D6/D4 -> 0.79568106 | E26: =E6/E4 -> 0.73992933 | F26: =F6/F4 -> 0.74157303 | G26: =G6/G4 -> 0.77132616 | H26: =H6/H4 -> 0.7677193 | I26: =I6/I4 -> 0.74305556 | J26: =J6/J4 -> 0.75388776 | K26: =K6/K4 -> 0.76953908 | ... U26: =U6/U4 -> 0.74002883 | Z26: =Z6/Z4 -> 0.75310881 | AA26: =AA6/AA4 -> 0.76988156 | AB26: =AB6/AB4 -> 0.76088989 | AC26: =AC6/AC4 -> 0.75822891 | AD26: =AD6/AD4 -> 0.75605642 | AE26: =AE6/AE4 -> 0.74708333 | AF26: =AF6/AF4 -> 0.75 | AG26: =AG6/AG4 -> 0.75 | ... AO26: =AO6/AO4 -> 0.75 | AQ26: Opp/nedside | AR26: =(AR25-B4)/B4 -> 0.82110349
C27: EBITDA margin | D27: =D9/D4 -> 0.24335548 | E27: =E9/E4 -> 0.2459364 | F27: =F9/F4 -> 0.22621723 | G27: =G9/G4 -> 0.19569892 | H27: =H9/H4 -> 0.22315789 | I27: =I9/I4 -> 0.25315657 | J27: =J9/J4 -> 0.25287356 | K27: =K9/K4 -> 0.23246493 | ... U27: =U9/U4 -> 0.2465161 | Z27: =Z9/Z4 -> 0.24196891 | AA27: =AA9/AA4 -> 0.25126904 | AB27: =AB9/AB4 -> 0.22751916 | AC27: =AC9/AC4 -> 0.24076859 | AD27: =AD9/AD4 -> 0.24471021 | AE27: =AE9/AE4 -> 0.23444444 | AF27: =AF9/AF4 -> 0.2387944 | AG27: =AG9/AG4 -> 0.24120575 | ... AO27: =AO9/AO4 -> 0.24360572
C28: EBITA margin | D28: =D11/D4 -> 0.14700997 | E28: =E11/E4 -> 0.1590106 | F28: =F11/F4 -> 0.1258427 | G28: =G11/G4 -> 0.091039427 | H28: =H11/H4 -> 0.12 | I28: =I11/I4 -> 0.16224747 | J28: =J11/J4 -> 0.15077755 | K28: =K11/K4 -> 0.13360053 | ... U28: =U11/U4 -> 0.15665545 | Z28: =Z11/Z4 -> 0.12668394 | AA28: =AA11/AA4 -> 0.15313029 | AB28: =AB11/AB4 -> 0.1235745 | AC28: =AC11/AC4 -> 0.13684211 | AD28: =AD11/AD4 -> 0.14520086 | AE28: =AE11/AE4 -> 0.13694444 | AF28: =AF11/AF4 -> 0.14300896 | AG28: =AG11/AG4 -> 0.1454203 | ... AO28: =AO11/AO4 -> 0.17852931
C29: EBIT margin | D29: =D13/D4 -> 0.11710963 | E29: =E13/E4 -> 0.1335689 | F29: =F13/F4 -> 0.098876404 | G29: =G13/G4 -> 0.064516129 | H29: =H13/H4 -> 0.093333333 | I29: =I13/I4 -> 0.13825758 | J29: =J13/J4 -> 0.12440838 | K29: =K13/K4 -> 0.10754843 | ... U29: =U13/U4 -> 0.13935608 | Z29: =Z13/Z4 -> 0.10414508 | AA29: =AA13/AA4 -> 0.13388325 | AB29: =AB13/AB4 -> 0.10319686 | AC29: =AC13/AC4 -> 0.11629073 | AD29: =AD13/AD4 -> 0.12557498 | AE29: =AE13/AE4 -> 0.11972222 | AF29: =AF13/AF4 -> 0.12644066 | AG29: =AG13/AG4 -> 0.12916462 | ... AO29: =AO13/AO4 -> 0.16748524
C30: ROE | AA30: =AA18/AA55 -> 0.020572812 | AB30: 0.129 | AC30: 0.122 | AD30: 0.145 | AE30: 0.184
C32: Active customers Synsam Lifestyle (thousand) | D32: 419 | E32: 449 | F32: 478 | G32: 511 | H32: 542 | I32: 572 | J32: 595 | K32: 620 | L32: 645 | M32: 667 | N32: 683 | O32: 703 | P32: 718 | Q32: 730 | R32: 741 | S32: 756 | T32: 770 | U32: 782 | AB32: 511 | AC32: 620 | AD32: 703 | AE32: 756
C33: q/q | E33: =(E32-D32)/D32 -> 0.071599045 | F33: =(F32-E32)/E32 -> 0.064587973 | G33: =(G32-F32)/F32 -> 0.069037657 | H33: =(H32-G32)/G32 -> 0.060665362 | I33: =(I32-H32)/H32 -> 0.055350554 | J33: =(J32-I32)/I32 -> 0.04020979 | K33: =(K32-J32)/J32 -> 0.042016807 | L33: =(L32-K32)/K32 -> 0.040322581 | ... U33: =(U32-T32)/T32 -> 0.015584416
C34: Churn | D34: 0.022 | E34: 0.0212 | F34: 0.0217 | G34: 0.0211 | H34: 0.0217 | I34: 0.0186 | J34: 0.0204 | K34: 0.0228 | L34: 0.0233 | M34: 0.0251 | N34: 0.026 | O34: 0.0269 | P34: 0.0284 | Q34: 0.0291 | R34: 0.0288 | S34: 0.0297 | T34: 0.0304 | U34: 0.0305 | AC34: =(AC32-AB32)/AB32 -> 0.21330724 | AD34: =(AD32-AC32)/AC32 -> 0.13387097 | AE34: =(AE32-AD32)/AD32 -> 0.075391181
C35: → Churnet (est.) | E35: =-E34*D32 -> -8.8828 | F35: =-F34*E32 -> -9.7433 | G35: =-G34*F32 -> -10.0858 | H35: =-H34*G32 -> -11.0887 | I35: =-I34*H32 -> -10.0812 | J35: =-J34*I32 -> -11.6688 | K35: =-K34*J32 -> -13.566 | L35: =-L34*K32 -> -14.446 | ... U35: =-U34*T32 -> -23.485
C36: → Brutto nye (est.) | E36: =E32-D32-E35 -> 38.8828 | F36: =F32-E32-F35 -> 38.7433 | G36: =G32-F32-G35 -> 43.0858 | H36: =H32-G32-H35 -> 42.0887 | I36: =I32-H32-I35 -> 40.0812 | J36: =J32-I32-J35 -> 34.6688 | K36: =K32-J32-K35 -> 38.566 | L36: =L32-K32-L35 -> 39.446 | ... U36: =U32-T32-U35 -> 35.485
C37: → Churn ex. Denmark | H37: 0.0197 | I37: 0.0184 | J37: 0.0185 | K37: 0.0207 | L37: 0.0213 | M37: 0.0231 | N37: 0.0237 | O37: 0.0258 | P37: 0.0267 | Q37: 0.0268 | R37: 0.0267 | S37: 0.0274 | T37: 0.0264 | U37: 0.0271
C38: Share of sales Synsam lifestyle | U38: 0.54
C40: Number of stores | D40: 509 | E40: 520 | F40: 520 | G40: 536 | H40: 537 | I40: 536 | J40: 542 | K40: 547 | L40: 553 | M40: 565 | N40: 574 | O40: 586 | P40: 588 | Q40: 598 | R40: 601 | S40: 603 | T40: 602 | U40: 604
C41: Directly owned | D41: 476 | E41: 487 | F41: 487 | G41: 503 | H41: 504 | I41: 504 | J41: 511 | K41: 517 | L41: 526 | M41: 538 | N41: 547 | O41: 560 | P41: 562 | Q41: 573 | R41: 576 | S41: 578 | T41: 579 | U41: 584
C42: Fanchised | D42: =D40-D41 -> 33 | E42: =E40-E41 -> 33 | F42: =F40-F41 -> 33 | G42: =G40-G41 -> 33 | H42: =H40-H41 -> 33 | I42: =I40-I41 -> 32 | J42: =J40-J41 -> 31 | K42: =K40-K41 -> 30 | ... U42: =U40-U41 -> 20
C44: Balanse SEKm
C45: Intangible non-current assets | D45: 4697 | E45: 4683 | F45: 4695 | G45: 4712 | H45: 4647 | I45: 4719 | J45: 4652 | K45: 4541 | L45: 4581 | M45: 4548 | N45: 4482 | O45: 4498 | P45: 4372 | Q45: 4385 | R45: 4351 | S45: 4273 | T45: 4319 | U45: 4376 | Z45: 4666 | AA45: 4665 | AB45: 4712 | AC45: 4541 | AD45: 4498 | AE45: 4273
C46: Tangible non-current assets | D46: 569 | E46: 646 | F46: 651 | G46: 699 | H46: 703 | I46: 703 | J46: 681 | K46: 680 | L46: 695 | M46: 722 | N46: 743 | O46: 787 | P46: 787 | Q46: 815 | R46: 792 | S46: 778 | T46: 791 | U46: 810 | Z46: 394 | AA46: 515 | AB46: 699 | AC46: 680 | AD46: 787 | AE46: 778
C47: Right of use assets | D47: 723 | E47: 850 | F47: 848 | G47: 878 | H47: 875 | I47: 867 | J47: 823 | K47: 779 | L47: 812 | M47: 794 | N47: 797 | O47: 818 | P47: 809 | Q47: 827 | R47: 792 | S47: 807 | T47: 910 | U47: 928 | Z47: 511 | AA47: 684 | AB47: 878 | AC47: 779 | AD47: 818 | AE47: 807
C48: Financial non-current assets | D48: 24 | E48: 24 | F48: 26 | G48: 27 | H48: 30 | I48: 31 | J48: 35 | K48: 32 | L48: 35 | M48: 34 | N48: 36 | O48: 37 | P48: 35 | Q48: 35 | R48: 33 | S48: 46 | T48: 45 | U48: 43 | Z48: 16 | AA48: 23 | AB48: 27 | AC48: 32 | AD48: 37 | AE48: 46
C49: Deferred tax assets | D49: 58 | E49: 59 | F49: 60 | G49: 60 | H49: 61 | I49: 72 | J49: 70 | K49: 72 | L49: 76 | M49: 74 | N49: 73 | O49: 71 | P49: 91 | Q49: 85 | R49: 77 | S49: 85 | T49: 87 | U49: 96 | Z49: 52 | AA49: 61 | AB49: 60 | AC49: 72 | AD49: 71 | AE49: 85
C50: Inventories | D50: 537 | E50: 557 | F50: 595 | G50: 597 | H50: 676 | I50: 705 | J50: 719 | K50: 707 | L50: 773 | M50: 784 | N50: 768 | O50: 832 | P50: 836 | Q50: 874 | R50: 871 | S50: 893 | T50: 971 | U50: 1092 | Z50: 383 | AA50: 451 | AB50: 597 | AC50: 707 | AD50: 832 | AE50: 893
C51: Account receivables | D51: 509 | E51: 376 | F51: 385 | G51: 414 | H51: 539 | I51: 482 | J51: 446 | K51: 486 | L51: 561 | M51: 559 | N51: 495 | O51: 607 | P51: 516 | Q51: 260 | R51: 212 | S51: 249 | T51: 342 | U51: 275 | Z51: 313 | AA51: 308 | AB51: 414 | AC51: 486 | AD51: 607 | AE51: 249
C52: Current receivables | D52: 169 | E52: 189 | F52: 188 | G52: 189 | H52: 203 | I52: 213 | J52: 210 | K52: 158 | L52: 206 | M52: 158 | N52: 182 | O52: 175 | P52: 185 | Q52: 203 | R52: 193 | S52: 214 | T52: 237 | U52: 237 | Z52: 114 | AA52: 141 | AB52: 188 | AC52: 157 | AD52: 174 | AE52: 214
C53: Cash | D53: 560 | E53: 423 | F53: 508 | G53: 444 | H53: 502 | I53: 479 | J53: 446 | K53: 582 | L53: 568 | M53: 543 | N53: 567 | O53: 420 | P53: 533 | Q53: 575 | R53: 562 | S53: 600 | T53: 736 | U53: 648 | Z53: 809 | AA53: 755 | AB53: 444 | AC53: 582 | AD53: 420 | AE53: 600
C54: Total assets | D54: =SUM(D45:D53) -> 7846 | E54: =SUM(E45:E53) -> 7807 | F54: =SUM(F45:F53) -> 7956 | G54: =SUM(G45:G53) -> 8020 | H54: =SUM(H45:H53) -> 8236 | I54: =SUM(I45:I53) -> 8271 | J54: =SUM(J45:J53) -> 8082 | K54: =SUM(K45:K53) -> 8037 | ... U54: =SUM(U45:U53) -> 8505 | Z54: =SUM(Z45:Z53) -> 7258 | AA54: =SUM(AA45:AA53) -> 7603 | AB54: =SUM(AB45:AB53) -> 8019 | AC54: =SUM(AC45:AC53) -> 8036 | AD54: =SUM(AD45:AD53) -> 8244 | AE54: =SUM(AE45:AE53) -> 7945
C55: Total equity | D55: 2628 | E55: 2447 | F55: 2553 | G55: 2584 | H55: 2556 | I55: 2474 | J55: 2558 | K55: 2516 | L55: 2577 | M55: 2478 | N55: 2507 | O55: 2555 | P55: 2475 | Q55: 2382 | R55: 2465 | S55: 2436 | T55: 2606 | U55: 2552 | Z55: -1575 | AA55: 2479 | AB55: 2584 | AC55: 2516 | AD55: 2555 | AE55: 2436
C56: Non-current loans from banks | D56: 2425 | E56: 2452 | F56: 2471 | G56: 2488 | H56: 2500 | I56: 2539 | J56: 2520 | K56: 2029 | L56: 2056 | M56: 2048 | N56: 2046 | O56: 2608 | P56: 2672 | Q56: 2793 | R56: 2737 | S56: 2718 | T56: 2728 | U56: 2741 | Z56: 2491 | AA56: 2416 | AB56: 2488 | AC56: 2029 | AD56: 2608 | AE56: 2718
C57: Non-current lease liabilities | D57: 470 | E57: 590 | F57: 584 | G57: 592 | H57: 576 | I57: 561 | J57: 518 | K57: 440 | L57: 440 | M57: 423 | N57: 418 | O57: 432 | P57: 423 | Q57: 432 | R57: 399 | S57: 417 | T57: 482 | U57: 508 | Z57: 304 | AA57: 443 | AB57: 592 | AC57: 440 | AD57: 432 | AE57: 417
C58: Other non-current liabilities, IB | D58: 30 | E58: 31 | F58: 32 | G58: 41 | H58: 42 | I58: 45 | J58: 44 | K58: 44 | L58: 46 | M58: 45 | N58: 45 | O58: 46 | P58: 33 | Q58: 34 | R58: 33 | S58: 33 | T58: 34 | U58: 34 | Z58: 3657 | AA58: 29 | AB58: 42 | AC58: 46 | AD58: 50 | AE58: 43
C59: Deferred tax liabilities | D59: 505 | E59: 500 | F59: 498 | G59: 514 | H59: 504 | I59: 506 | J59: 498 | K59: 513 | L59: 512 | M59: 508 | N59: 499 | O59: 516 | P59: 501 | Q59: 499 | R59: 493 | S59: 515 | T59: 516 | U59: 487 | Z59: 491 | AA59: 504 | AB59: 514 | AC59: 513 | AD59: 516 | AE59: 515
C60: Non-current liabilities, non IB | D60: 10 | E60: 6 | F60: 7 | G60: 6 | H60: 7 | I60: 7 | J60: 6 | K60: 6 | L60: 7 | M60: 8 | N60: 10 | O60: 8 | P60: 17 | Q60: 13 | R60: 14 | S60: 15 | T60: 17 | U60: 15 | Z60: 6 | AA60: 10 | AB60: 5 | AC60: 4 | AD60: 5 | AE60: 4
C61: Current loans from banks | D61: 0 | E61: 0 | F61: 0 | G61: 0 | H61: 0 | I61: 0 | J61: 0 | K61: 464 | L61: 470 | M61: 468 | N61: 468 | O61: 0 | P61: 0 | Q61: 0 | R61: 0 | S61: 0 | T61: 0 | U61: 0 | Z61: 405 | AA61: 0 | AB61: 0 | AC61: 464 | AD61: 0 | AE61: 0
C62: Current lease liabilities | D62: 283 | E62: 295 | F62: 303 | G62: 317 | H62: 330 | I62: 348 | J62: 346 | K62: 322 | L62: 348 | M62: 347 | N62: 360 | O62: 374 | P62: 376 | Q62: 385 | R62: 380 | S62: 379 | T62: 385 | U62: 404 | Z62: 222 | AA62: 267 | AB62: 317 | AC62: 322 | AD62: 374 | AE62: 379
C63: Other current liablities, IB | D63: 0 | E63: 0 | F63: 1 | G63: 1 | H63: 1 | I63: 1 | J63: 0 | K63: 0 | L63: 0 | M63: 0 | N63: 0 | O63: 0 | P63: 0 | Q63: 0 | R63: 1 | S63: 1 | T63: 1 | U63: 0 | Z63: 174 | AA63: 210 | AB63: 156 | AC63: 117 | AD63: 135 | AE63: 79
C64: Account payable | D64: 732 | E64: 803 | F64: 793 | G64: 728 | H64: 943 | I64: 974 | J64: 781 | K64: 892 | L64: 966 | M64: 1022 | N64: 960 | O64: 812 | P64: 720 | Q64: 649 | R64: 515 | S64: 545 | T64: 689 | U64: 723 | Z64: 458 | AA64: 703 | AB64: 728 | AC64: 892 | AD64: 812 | AE64: 545
C65: Other current liabilities, non IB | D65: 764 | E65: 684 | F65: 716 | G65: 748 | H65: 777 | I65: 816 | J65: 812 | K65: 811 | L65: 886 | M65: 869 | N65: 830 | O65: 893 | P65: 948 | Q65: 872 | R65: 846 | S65: 888 | T65: 981 | U65: 1039 | Z65: 625 | AA65: 542 | AB65: 593 | AC65: 693 | AD65: 757 | AE65: 809
C66: Total debt | D66: =SUM(D56:D65) -> 5219 | E66: =SUM(E56:E65) -> 5361 | F66: =SUM(F56:F65) -> 5405 | G66: =SUM(G56:G65) -> 5435 | H66: =SUM(H56:H65) -> 5680 | I66: =SUM(I56:I65) -> 5797 | J66: =SUM(J56:J65) -> 5525 | K66: =SUM(K56:K65) -> 5521 | ... U66: =SUM(U56:U65) -> 5951 | Z66: =SUM(Z56:Z65) -> 8833 | AA66: =SUM(AA56:AA65) -> 5124 | AB66: =SUM(AB56:AB65) -> 5435 | AC66: =SUM(AC56:AC65) -> 5520 | AD66: =SUM(AD56:AD65) -> 5689 | AE66: =SUM(AE56:AE65) -> 5509
C67: Total E/D | D67: =D55+D66 -> 7847 | E67: =E55+E66 -> 7808 | F67: =F55+F66 -> 7958 | G67: =G55+G66 -> 8019 | H67: =H55+H66 -> 8236 | I67: =I55+I66 -> 8271 | J67: =J55+J66 -> 8083 | K67: =K55+K66 -> 8037 | ... U67: =U55+U66 -> 8503 | Z67: =Z55+Z66 -> 7258 | AA67: =AA55+AA66 -> 7603 | AB67: =AB55+AB66 -> 8019 | AC67: =AC55+AC66 -> 8036 | AD67: =AD55+AD66 -> 8244 | AE67: =AE55+AE66 -> 7945
C69: Cash flow SEKm
C70: Model PTP | D70: =D16 -> 128 | E70: =E16 -> 129 | F70: =F16 -> 97 | G70: =G16 -> 59 | H70: =H16 -> 44 | I70: =I16 -> 164 | J70: =J16 -> 116 | K70: =K16 -> 92 | ... U70: =U16 -> 200 | Z70: =Z16 -> -136 | AA70: =AA16 -> 163 | AB70: =AB16 -> 415 | AC70: =AC16 -> 415 | AD70: =AD16 -> 493 | AE70: =AE16 -> 590
C71: Reported PTP | D71: 129 | E71: 129 | F71: 98 | G71: 59 | H71: 45 | I71: 164 | J71: 115 | K71: 92 | L71: 77 | M71: 212 | N71: 91 | O71: 112 | P71: 115 | Q71: 147 | R71: 165 | S71: 163 | T71: 164 | U71: 200 | Z71: -136 | AA71: 163 | AB71: 415 | AC71: 415 | AD71: 493 | AE71: 590
C72: Adjustment for non-cash | D72: -24 | E72: 12 | F72: -18 | G72: -4 | H72: 70 | I72: -1 | J72: -7 | K72: -2 | L72: 34 | M72: -13 | N72: 30 | O72: 6 | P72: 18 | Q72: 91 | R72: -21 | S72: -39 | T72: 22 | U72: 31 | Z72: 336 | AA72: 272 | AB72: -34 | AC72: 61 | AD72: 58 | AE72: 48
C73: D/A | D73: 152 | E73: 159 | F73: 170 | G73: 183 | H73: 185 | I73: 183 | J73: 190 | K73: 187 | L73: 188 | M73: 194 | N73: 194 | O73: 201 | P73: 201 | Q73: 202 | R73: 212 | S73: 212 | T73: 213 | U73: 223 | Z73: 532 | AA73: 555 | AB73: 665 | AC73: 744 | AD73: 777 | AE73: 827
C74: Income tax paid | D74: -90 | E74: -56 | F74: -15 | G74: 8 | H74: -69 | I74: -26 | J74: -18 | K74: -31 | L74: -55 | M74: -18 | N74: -17 | O74: -17 | P74: -92 | Q74: -39 | R74: -28 | S74: -32 | T74: -50 | U74: -40 | Z74: -19 | AA74: -86 | AB74: -153 | AC74: -144 | AD74: -107 | AE74: -191
C75: WC | D75: -220 | E75: 100 | F75: -22 | G75: -61 | H75: 26 | I75: 66 | J75: -176 | K75: 158 | L75: -27 | M75: 60 | N75: -61 | O75: -260 | P75: 68 | Q75: 12 | R75: -93 | S75: 6 | T75: 24 | U75: 20 | Z75: 185 | AA75: 76 | AB75: -203 | AC75: 74 | AD75: -288 | AE75: -8
C76: CFFO | D76: =SUM(D71:D75) -> -53 | E76: =SUM(E71:E75) -> 344 | F76: =SUM(F71:F75) -> 213 | G76: =SUM(G71:G75) -> 185 | H76: =SUM(H71:H75) -> 257 | I76: =SUM(I71:I75) -> 386 | J76: =SUM(J71:J75) -> 104 | K76: =SUM(K71:K75) -> 404 | ... U76: =SUM(U71:U75) -> 434 | Z76: =SUM(Z71:Z75) -> 898 | AA76: =SUM(AA71:AA75) -> 980 | AB76: =SUM(AB71:AB75) -> 690 | AC76: =SUM(AC71:AC75) -> 1150 | AD76: =SUM(AD71:AD75) -> 933 | AE76: =SUM(AE71:AE75) -> 1266
C78: Capex | D78: -95 | E78: -131 | F78: -50 | G78: -107 | H78: -72 | I78: -52 | J78: -48 | K78: -74 | L78: -72 | M78: -104 | N78: -92 | O78: -110 | P78: -91 | Q78: -93 | R78: -60 | S78: -74 | T78: -77 | U78: =-27-81 -> -108 | Z78: -160 | AA78: -272 | AB78: -382 | AC78: -248 | AD78: -377 | AE78: -317
C79: other investing activities | D79: -1 | E79: -1 | F79: -2 | G79: 0 | H79: -5 | I79: -15 | J79: 1 | K79: -4 | L79: -10 | M79: -1 | N79: -3 | O79: -7 | P79: 0 | Q79: -2 | R79: 2 | S79: 0 | T79: -1 | U79: -34 | Z79: -5 | AA79: -11 | AB79: -3 | AC79: -22 | AD79: -21 | AE79: -1
C80: CFFI | D80: =SUM(D78:D79) -> -96 | E80: =SUM(E78:E79) -> -132 | F80: =SUM(F78:F79) -> -52 | G80: =SUM(G78:G79) -> -107 | H80: =SUM(H78:H79) -> -77 | I80: =SUM(I78:I79) -> -67 | J80: =SUM(J78:J79) -> -47 | K80: =SUM(K78:K79) -> -78 | ... U80: =SUM(U78:U79) -> -142 | Z80: =SUM(Z78:Z79) -> -165 | AA80: =SUM(AA78:AA79) -> -283 | AB80: =SUM(AB78:AB79) -> -385 | AC80: =SUM(AC78:AC79) -> -270 | AD80: =SUM(AD78:AD79) -> -398 | AE80: =SUM(AE78:AE79) -> -318
C82: Buybacks | D82: 0 | E82: 0 | F82: 0 | G82: -47 | H82: 0 | I82: 0 | J82: 0 | K82: -30 | L82: -36 | M82: 0 | N82: 0 | O82: -50 | P82: -102 | Q82: 0 | R82: -32 | S82: -72 | T82: -56 | U82: -29 | Z82: 0 | AA82: 0 | AB82: -47 | AC82: -30 | AD82: -85 | AE82: -206
C83: Amortization of debt to banks | D83: 0 | E83: 0 | F83: 0 | G83: 0 | H83: 0 | I83: 0 | J83: 0 | K83: 0 | L83: 0 | M83: 0 | N83: 0 | O83: -470 | P83: 0 | Q83: -2697 | R83: -50 | S83: 0 | T83: 0 | U83: 0 | Z83: -342 | AA83: -3172 | AB83: 0 | AC83: 0 | AD83: -470 | AE83: -2747
C84: Amortization of lease | D84: -72 | E84: -73 | F84: -83 | G84: -100 | H84: -92 | I84: -93 | J84: -94 | K84: -149 | L84: -105 | M84: -100 | N84: -95 | O84: -101 | P84: -105 | Q84: -108 | R84: -112 | S84: -111 | T84: -148 | U84: -93 | Z84: 0 | AA84: 0 | AB84: -328 | AC84: -429 | AD84: -401 | AE84: -435
C85: Borrowings | D85: 0 | E85: 0 | F85: 0 | G85: 0 | H85: 0 | I85: 0 | J85: 0 | K85: 0 | L85: 0 | M85: 0 | N85: 0 | O85: 550 | P85: 100 | Q85: 2790 | R85: 0 | S85: 0 | T85: 0 | U85: 0 | Z85: 210 | AA85: 2392 | AB85: 0 | AC85: 0 | AD85: 550 | AE85: 2890
C86: Dividends | D86: 0 | E86: -255 | F86: 0 | G86: 0 | H86: 0 | I86: -253 | J86: 0 | K86: 0 | L86: 0 | M86: -266 | N86: 0 | O86: 0 | P86: 0 | Q86: -260 | R86: 0 | S86: 0 | T86: 0 | U86: -256 | Z86: 0 | AA86: 0 | AB86: -256 | AC86: -253 | AD86: -266 | AE86: -261
C87: CFFF | D87: =SUM(D82:D86) -> -72 | E87: =SUM(E82:E86) -> -328 | F87: =SUM(F82:F86) -> -83 | G87: =SUM(G82:G86) -> -147 | H87: =SUM(H82:H86) -> -92 | I87: =SUM(I82:I86) -> -346 | J87: =SUM(J82:J86) -> -94 | K87: =SUM(K82:K86) -> -179 | ... U87: =SUM(U82:U86) -> -378 | Z87: =SUM(Z82:Z86) -> -132 | AA87: =SUM(AA82:AA86) -> -780 | AB87: =SUM(AB82:AB86) -> -631 | AC87: =SUM(AC82:AC86) -> -712 | AD87: =SUM(AD82:AD86) -> -672 | AE87: =SUM(AE82:AE86) -> -759
C89: FX | D89: 26 | E89: -23 | F89: 6 | G89: 4 | H89: -29 | I89: 5 | J89: 5 | K89: -11 | L89: -10 | M89: 11 | N89: -23 | O89: -3 | P89: 1 | Q89: -1 | R89: 4 | S89: -14 | T89: 45 | U89: -2 | Z89: -15 | AA89: 29 | AB89: 15 | AC89: -30 | AD89: -25 | AE89: -9
C91: CIC | D91: =D76+D80+D87+D89 -> -195 | E91: =E76+E80+E87+E89 -> -139 | F91: =F76+F80+F87+F89 -> 84 | G91: =G76+G80+G87+G89 -> -65 | H91: =H76+H80+H87+H89 -> 59 | I91: =I76+I80+I87+I89 -> -22 | J91: =J76+J80+J87+J89 -> -32 | K91: =K76+K80+K87+K89 -> 136 | ... U91: =U76+U80+U87+U89 -> -88 | Z91: =Z76+Z80+Z87+Z89 -> 586 | AA91: =AA76+AA80+AA87+AA89 -> -54 | AB91: =AB76+AB80+AB87+AB89 -> -311 | AC91: =AC76+AC80+AC87+AC89 -> 138 | AD91: =AD76+AD80+AD87+AD89 -> -162 | AE91: =AE76+AE80+AE87+AE89 -> 180
C93: FCF | D93: =D76+D78+D84 -> -220 | E93: =E76+E78+E84 -> 140 | F93: =F76+F78+F84 -> 80 | G93: =G76+G78+G84 -> -22 | H93: =H76+H78+H84 -> 93 | I93: =I76+I78+I84 -> 241 | J93: =J76+J78+J84 -> -38 | K93: =K76+K78+K84 -> 181 | ... U93: =U76+U78+U84 -> 233 | Z93: =Z76+Z78+Z84 -> 738 | AA93: =AA76+AA78+AA84 -> 708 | AB93: =AB76+AB78+AB84 -> -20 | AC93: =AC76+AC78+AC84 -> 473 | AD93: =AD76+AD78+AD84 -> 155 | AE93: =AE76+AE78+AE84 -> 514

Sheet Segementer
B4: SEKm | C4: Q122 | D4: Q222 | E4: Q322 | F4: Q422 | G4: 2022 | H4: Q123 | I4: Q223 | J4: Q323 | K4: Q423 | L4: 2023 | M4: Q124 | N4: Q224 | O4: Q324 | P4: Q424 | Q4: 2024 | R4: Q125 | S4: Q225 | T4: Q325 | U4: Q425 | V4: 2025 | W4: Q126 | X4: Q226 | Y4: Q326 | Z4: Q426 | AA4: 2026
B5: Sweden
B6: Synsam Lifestyle | C6: 298 | D6: 359 | E6: 321 | F6: 396 | G6: =SUM(C6:F6) -> 1374 | H6: 378 | I6: 403 | J6: 370 | K6: 435 | L6: =SUM(H6:K6) -> 1586 | M6: 452 | N6: 468 | O6: 395 | P6: 484 | Q6: =SUM(M6:P6) -> 1799 | R6: 488 | S6: 536 | T6: 477 | U6: 556 | V6: =SUM(R6:U6) -> 2057 | W6: 532 | X6: 597 | AA6: =SUM(W6:Z6) -> 1129
B7: y/y | H7: =(H6-C6)/C6 -> 0.26845638 | I7: =(I6-D6)/D6 -> 0.12256267 | J7: =(J6-E6)/E6 -> 0.15264798 | K7: =(K6-F6)/F6 -> 0.098484848 | L7: =(L6-G6)/G6 -> 0.15429403 | M7: =(M6-H6)/H6 -> 0.1957672 | N7: =(N6-I6)/I6 -> 0.16129032 | O7: =(O6-J6)/J6 -> 0.067567568 | ... AA7: =(AA6-V6)/V6 -> -0.45114244
B8: Non-recurring rev | C8: 263 | D8: 323 | E8: 288 | F8: 286 | G8: =SUM(C8:F8) -> 1160 | H8: 292 | I8: 348 | J8: 306 | K8: 304 | L8: =SUM(H8:K8) -> 1250 | M8: 298 | N8: 352 | O8: 320 | P8: 323 | Q8: =SUM(M8:P8) -> 1293 | R8: 330 | S8: 379 | T8: 352 | U8: 349 | V8: =SUM(R8:U8) -> 1410 | W8: 340 | X8: 412 | AA8: =SUM(W8:Z8) -> 752
B9: y/y | H9: =(H8-C8)/C8 -> 0.11026616 | I9: =(I8-D8)/D8 -> 0.077399381 | J9: =(J8-E8)/E8 -> 0.0625 | K9: =(K8-F8)/F8 -> 0.062937063 | L9: =(L8-G8)/G8 -> 0.077586207 | M9: =(M8-H8)/H8 -> 0.020547945 | N9: =(N8-I8)/I8 -> 0.011494253 | O9: =(O8-J8)/J8 -> 0.045751634 | ... AA9: =(AA8-V8)/V8 -> -0.46666667
B10: Total revenue | C10: =C6+C8 -> 561 | D10: =D6+D8 -> 682 | E10: =E6+E8 -> 609 | F10: =F6+F8 -> 682 | G10: =G6+G8 -> 2534 | H10: =H6+H8 -> 670 | I10: =I6+I8 -> 751 | J10: =J6+J8 -> 676 | ... AA10: =AA6+AA8 -> 1881
B11: y/y | H11: =(H10-C10)/C10 -> 0.1942959 | I11: =(I10-D10)/D10 -> 0.10117302 | J11: =(J10-E10)/E10 -> 0.11001642 | K11: =(K10-F10)/F10 -> 0.083577713 | L11: =(L10-G10)/G10 -> 0.11917916 | M11: =(M10-H10)/H10 -> 0.11940299 | N11: =(N10-I10)/I10 -> 0.091877497 | O11: =(O10-J10)/J10 -> 0.057692308 | ... AA11: =(AA10-V10)/V10 -> -0.45745601
B12: Organic growth | C12: 0.106 | D12: 0.166 | E12: 0.107 | F12: 0.087 | H12: 0.194 | I12: 0.097 | J12: 0.104 | K12: 0.078 | L12: 0.115 | M12: 0.108 | N12: 0.084 | O12: 0.05 | P12: 0.088 | Q12: 0.083 | R12: 0.086 | S12: 0.109 | T12: 0.151 | U12: 0.112 | V12: 0.114 | W12: 0.065 | X12: 0.089
B13: Like-for-like | H13: 0.162 | I13: 0.069 | J13: 0.08 | K13: 0.056 | M13: 0.087 | N13: 0.065 | O13: 0.023 | P13: 0.059 | R13: 0.058 | S13: 0.086 | T13: 0.128 | U13: 0.094 | V13: 0.091 | W13: 0.047 | X13: 0.072
B14: Gross profit | C14: 444 | D14: 510 | E14: 473 | F14: 550 | G14: =SUM(C14:F14) -> 1977 | H14: 525 | I14: 570 | J14: 518 | K14: 580 | L14: =SUM(H14:K14) -> 2193 | M14: 588 | N14: 604 | O14: 543 | P14: 628 | Q14: =SUM(M14:P14) -> 2363 | R14: 610 | S14: 691 | T14: 622 | U14: 709 | V14: =SUM(R14:U14) -> 2632 | W14: 679 | X14: 773 | AA14: =SUM(W14:Z14) -> 1452
B15: Gross margin | C15: 0.785 | D15: 0.744 | E15: 0.771 | F15: 0.803 | G15: =G14/G10 -> 0.78018942 | H15: 0.78 | I15: 0.755 | J15: 0.763 | K15: 0.782 | L15: =L14/L10 -> 0.77327221 | M15: 0.78 | N15: 0.735 | O15: 0.75 | P15: 0.775 | Q15: =Q14/Q10 -> 0.76423027 | R15: 0.742 | S15: 0.751 | T15: 0.747 | U15: 0.78 | V15: =V14/V10 -> 0.75915777 | W15: 0.775 | X15: 0.763 | AA15: =AA14/AA10 -> 0.77192982
B16: EBITDA | C16: 152 | D16: 202 | E16: 191 | F16: 213 | G16: =SUM(C16:F16) -> 758 | H16: 196 | I16: 224 | J16: 223 | K16: 252 | L16: =SUM(H16:K16) -> 895 | M16: 257 | N16: 241 | O16: 222 | P16: 259 | Q16: =SUM(M16:P16) -> 979 | R16: 240 | S16: 276 | T16: 258 | U16: 286 | V16: =SUM(R16:U16) -> 1060 | W16: 267 | X16: 323 | AA16: =SUM(W16:Z16) -> 590
B17: EBITDA margin | C17: 0.269 | D17: 0.295 | E17: 0.312 | F17: 0.312 | G17: =G16/G10 -> 0.29913181 | H17: 0.292 | I17: 0.297 | J17: 0.328 | K17: 0.341 | L17: =L16/L10 -> 0.31558533 | M17: 0.341 | N17: 0.294 | O17: 0.308 | P17: 0.32 | Q17: =Q16/Q10 -> 0.31662354 | R17: 0.292 | S17: 0.301 | T17: 0.31 | U17: 0.315 | V17: =V16/V10 -> 0.30573983 | W17: 0.305 | X17: 0.319 | AA17: =AA16/AA10 -> 0.31366295
B18: EBIT | G18: =SUM(C18:F18) -> 0 | L18: =SUM(H18:K18) -> 0 | M18: 191 | N18: 175 | O18: 155 | P18: 189 | Q18: =SUM(M18:P18) -> 710 | R18: 168 | S18: 204 | T18: 182 | U18: 206 | V18: =SUM(R18:U18) -> 760 | W18: 185 | X18: 240 | AA18: =SUM(W18:Z18) -> 425
B19: EBIT margin | G19: =G18/G10 -> 0 | L19: =L18/L10 -> 0 | M19: =M18/M10 -> 0.25466667 | N19: =N18/N10 -> 0.21341463 | O19: 0.214 | P19: 0.234 | Q19: =Q18/Q10 -> 0.22962484 | R19: 0.205 | S19: =S18/S10 -> 0.22295082 | T19: 0.219 | U19: 0.227 | V19: =V18/V10 -> 0.21920969 | W19: 0.212 | X19: 0.237 | AA19: =AA18/AA10 -> 0.22594365
B20: Number of stores | C20: 231 | D20: 238 | E20: 238 | F20: 246 | H20: 245 | I20: 244 | J20: 246 | K20: 250 | M20: 251 | N20: 257 | O20: 258 | P20: 262 | R20: 263 | S20: 268 | T20: 269 | U20: 270 | W20: 269 | X20: 273
B21: Eyeview % | X21: 0.2
B22: Demark
B23: Synsam Lifestyle | C23: 118 | D23: 125 | E23: 125 | F23: 126 | G23: =SUM(C23:F23) -> 494 | H23: 152 | I23: 150 | J23: 133 | K23: 123 | L23: =SUM(H23:K23) -> 558 | M23: 141 | N23: 144 | O23: 139 | P23: 133 | Q23: =SUM(M23:P23) -> 557 | R23: 130 | S23: 113 | T23: 117 | U23: 105 | V23: =SUM(R23:U23) -> 465 | W23: 132 | X23: 146 | AA23: =SUM(W23:Z23) -> 278
B24: y/y | H24: =(H23-C23)/C23 -> 0.28813559 | I24: =(I23-D23)/D23 -> 0.2 | J24: =(J23-E23)/E23 -> 0.064 | K24: =(K23-F23)/F23 -> -0.023809524 | L24: =(L23-G23)/G23 -> 0.12955466 | M24: =(M23-H23)/H23 -> -0.072368421 | N24: =(N23-I23)/I23 -> -0.04 | O24: =(O23-J23)/J23 -> 0.045112782 | ... AA24: =(AA23-V23)/V23 -> -0.40215054
B25: Non-recurring rev | C25: 139 | D25: 161 | E25: 157 | F25: 140 | G25: =SUM(C25:F25) -> 597 | H25: 146 | I25: 172 | J25: 150 | K25: 154 | L25: =SUM(H25:K25) -> 622 | M25: 151 | N25: 185 | O25: 152 | P25: 155 | Q25: =SUM(M25:P25) -> 643 | R25: 156 | S25: 189 | T25: 171 | U25: 162 | V25: =SUM(R25:U25) -> 678 | W25: 153 | X25: 179 | AA25: =SUM(W25:Z25) -> 332
B26: y/y | H26: =(H25-C25)/C25 -> 0.050359712 | I26: =(I25-D25)/D25 -> 0.068322981 | J26: =(J25-E25)/E25 -> -0.044585987 | K26: =(K25-F25)/F25 -> 0.1 | L26: =(L25-G25)/G25 -> 0.041876047 | M26: =(M25-H25)/H25 -> 0.034246575 | N26: =(N25-I25)/I25 -> 0.075581395 | O26: =(O25-J25)/J25 -> 0.013333333 | ... AA26: =(AA25-V25)/V25 -> -0.51032448
B27: Total revenue | C27: =C23+C25 -> 257 | D27: =D23+D25 -> 286 | E27: =E23+E25 -> 282 | F27: =F23+F25 -> 266 | G27: =G23+G25 -> 1091 | H27: =H23+H25 -> 298 | I27: =I23+I25 -> 322 | J27: =J23+J25 -> 283 | ... AA27: =AA23+AA25 -> 610
B28: y/y | H28: =(H27-C27)/C27 -> 0.15953307 | I28: =(I27-D27)/D27 -> 0.12587413 | J28: =(J27-E27)/E27 -> 0.0035460993 | K28: =(K27-F27)/F27 -> 0.041353383 | L28: =(L27-G27)/G27 -> 0.081576535 | M28: =(M27-H27)/H27 -> -0.020134228 | N28: =(N27-I27)/I27 -> 0.02173913 | O28: =(O27-J27)/J27 -> 0.028268551 | ... AA28: =(AA27-V27)/V27 -> -0.46631671
B29: Organic growth | C29: 0.168 | D29: 0.032 | E29: 0.032 | F29: -0.053 | H29: 0.086 | I29: 0.031 | J29: -0.096 | K29: -0.004 | L29: 0.003 | M29: -0.026 | N29: 0.018 | O29: 0.056 | P29: 0.035 | Q29: 0.02 | R29: -0.016 | S29: -0.039 | T29: 0.023 | U29: -0.021 | V29: -0.014 | W29: 0.048 | X29: 0.088
B30: Like-for-like | H30: 0.083 | I30: 0.031 | J30: -0.097 | K30: -0.004 | M30: -0.026 | N30: 0.018 | O30: 0.051 | P30: 0.021 | R30: -0.037 | S30: -0.064 | T30: 0.002 | U30: -0.034 | V30: -0.034 | W30: 0.045 | X30: 0.088
B31: Gross profit | C31: 197 | D31: 222 | E31: 213 | F31: 204 | G31: =SUM(C31:F31) -> 836 | H31: 230 | I31: 240 | J31: 214 | K31: 209 | L31: =SUM(H31:K31) -> 893 | M31: 225 | N31: 244 | O31: 219 | P31: 220 | Q31: =SUM(M31:P31) -> 908 | R31: 217 | S31: 226 | T31: 213 | U31: 204 | V31: =SUM(R31:U31) -> 860 | W31: 202 | X31: 232 | AA31: =SUM(W31:Z31) -> 434
B32: Gross margin | C32: 0.766 | D32: 0.773 | E32: 0.749 | F32: 0.763 | G32: =G31/G27 -> 0.76626948 | H32: 0.773 | I32: 0.744 | J32: 0.752 | K32: 0.751 | L32: =L31/L27 -> 0.75677966 | M32: 0.77 | N32: 0.739 | O32: 0.755 | P32: 0.766 | Q32: =Q31/Q27 -> 0.75666667 | R32: 0.762 | S32: 0.748 | T32: 0.739 | U32: 0.752 | V32: =V31/V27 -> 0.75240595 | W32: 0.711 | X32: 0.714 | AA32: =AA31/AA27 -> 0.71147541
B33: EBITDA | C33: 61 | D33: 78 | E33: 80 | F33: 58 | G33: =SUM(C33:F33) -> 277 | H33: 79 | I33: 81 | J33: 69 | K33: 51 | L33: =SUM(H33:K33) -> 280 | M33: 70 | N33: 89 | O33: 74 | P33: 61 | Q33: =SUM(M33:P33) -> 294 | R33: 52 | S33: 63 | T33: 72 | U33: 48 | V33: =SUM(R33:U33) -> 235 | W33: 45 | X33: 64 | AA33: =SUM(W33:Z33) -> 109
B34: EBITDA margin | C34: 0.237 | D34: 0.271 | E34: 0.282 | F34: 0.218 | G34: =G33/G27 -> 0.25389551 | H34: 0.265 | I34: 0.251 | J34: 0.245 | K34: 0.183 | L34: =L33/L27 -> 0.23728814 | M34: 0.239 | N34: 0.271 | O34: 0.255 | P34: 0.213 | Q34: =Q33/Q27 -> 0.245 | R34: 0.182 | S34: 0.21 | T34: 0.251 | U34: 0.179 | V34: =V33/V27 -> 0.2055993 | W34: 0.158 | X34: 0.199 | AA34: =AA33/AA27 -> 0.17868852
B35: EBIT | G35: =SUM(C35:F35) -> 0 | L35: =SUM(H35:K35) -> 0 | M35: 45 | N35: 64 | O35: 48 | P35: 33 | Q35: =SUM(M35:P35) -> 190 | R35: 24 | S35: 34 | T35: 43 | U35: 20 | V35: =SUM(R35:U35) -> 121 | W35: 17 | X35: 36 | AA35: =SUM(W35:Z35) -> 53
B36: EBIT margin | G36: =G35/G27 -> 0 | L36: =L35/L27 -> 0 | M36: =M35/M27 -> 0.15410959 | N36: =N35/N27 -> 0.19452888 | O36: 0.166 | P36: 0.115 | Q36: =Q35/Q27 -> 0.15833333 | R36: 0.083 | S36: =S35/S27 -> 0.11258278 | T36: 0.148 | U36: 0.073 | V36: =V35/V27 -> 0.10586177 | W36: 0.059 | X36: 0.111 | AA36: =AA35/AA27 -> 0.086885246
B37: Number of stores | C37: 116 | D37: 116 | E37: 116 | F37: 116 | H37: 116 | I37: 116 | J37: 115 | K37: 114 | M37: 114 | N37: 114 | O37: 115 | P37: 115 | R37: 116 | S37: 117 | T37: 117 | U37: 115 | W37: 114 | X37: 114
B38: Norway
B39: Synsam Lifestyle | C39: 111 | D39: 121 | E39: 131 | F39: 143 | G39: =SUM(C39:F39) -> 506 | H39: 135 | I39: 130 | J39: 142 | K39: 139 | L39: =SUM(H39:K39) -> 546 | M39: 143 | N39: 159 | O39: 152 | P39: 166 | Q39: =SUM(M39:P39) -> 620 | R39: 171 | S39: 168 | T39: 171 | U39: 177 | V39: =SUM(R39:U39) -> 687 | W39: 177 | X39: 204
B40: y/y | H40: =(H39-C39)/C39 -> 0.21621622 | I40: =(I39-D39)/D39 -> 0.074380165 | J40: =(J39-E39)/E39 -> 0.083969466 | K40: =(K39-F39)/F39 -> -0.027972028 | L40: =(L39-G39)/G39 -> 0.079051383 | M40: =(M39-H39)/H39 -> 0.059259259 | N40: =(N39-I39)/I39 -> 0.22307692 | O40: =(O39-J39)/J39 -> 0.070422535 | ... AA40: =(AA39-V39)/V39 -> -1
B41: Non-recurring rev | C41: 146 | D41: 174 | E41: 161 | F41: 141 | G41: =SUM(C41:F41) -> 622 | H41: 149 | I41: 177 | J41: 166 | K41: 137 | L41: =SUM(H41:K41) -> 629 | M41: 144 | N41: 182 | O41: 164 | P41: 149 | Q41: =SUM(M41:P41) -> 639 | R41: 166 | S41: 192 | T41: 172 | U41: 148 | V41: =SUM(R41:U41) -> 678 | W41: 166 | X41: 213
B42: y/y | H42: =(H41-C41)/C41 -> 0.020547945 | I42: =(I41-D41)/D41 -> 0.017241379 | J42: =(J41-E41)/E41 -> 0.031055901 | K42: =(K41-F41)/F41 -> -0.028368794 | L42: =(L41-G41)/G41 -> 0.011254019 | M42: =(M41-H41)/H41 -> -0.033557047 | N42: =(N41-I41)/I41 -> 0.028248588 | O42: =(O41-J41)/J41 -> -0.012048193 | ... AA42: =(AA41-V41)/V41 -> -1
B43: Total revenue | C43: =C39+C41 -> 257 | D43: =D39+D41 -> 295 | E43: =E39+E41 -> 292 | F43: =F39+F41 -> 284 | G43: =G39+G41 -> 1128 | H43: =H39+H41 -> 284 | I43: =I39+I41 -> 307 | J43: =J39+J41 -> 308 | ... AA43: =AA39+AA41 -> 0
B44: y/y | H44: =(H43-C43)/C43 -> 0.10505837 | I44: =(I43-D43)/D43 -> 0.040677966 | J44: =(J43-E43)/E43 -> 0.054794521 | K44: =(K43-F43)/F43 -> -0.028169014 | L44: =(L43-G43)/G43 -> 0.041666667 | M44: =(M43-H43)/H43 -> 0.01056338 | N44: =(N43-I43)/I43 -> 0.11074919 | O44: =(O43-J43)/J43 -> 0.025974026 | ... AA44: =(AA43-V43)/V43 -> -1
B45: Organic growth | C45: 0.041 | D45: 0.061 | E45: 0.036 | F45: 0.056 | H45: 0.141 | I45: 0.101 | J45: 0.081 | K45: 0.038 | L45: 0.089 | M45: 0.042 | N45: 0.107 | O45: 0.088 | P45: 0.146 | Q45: 0.096 | R45: 0.207 | S45: 0.117 | T45: 0.123 | U45: 0.086 | V45: 0.131 | W45: 0.042 | X45: 0.1
B46: Like-for-like | H46: 0.104 | I46: 0.073 | J46: 0.052 | K46: 0.012 | M46: 0.023 | N46: 0.088 | O46: 0.063 | P46: 0.094 | R46: 0.152 | S46: 0.07 | T46: 0.084 | U46: 0.061 | V46: 0.09 | W46: 0.023 | X46: 0.073
B47: Gross profit | C47: 197 | D47: 208 | E47: 219 | F47: 224 | G47: =SUM(C47:F47) -> 848 | H47: 215 | I47: 209 | J47: 227 | K47: 210 | L47: =SUM(H47:K47) -> 861 | M47: 211 | N47: 237 | O47: 229 | P47: 235 | Q47: =SUM(M47:P47) -> 912 | R47: 244 | S47: 247 | T47: 237 | U47: 237 | V47: =SUM(R47:U47) -> 965 | W47: 249 | X47: 293 | AA47: =SUM(W47:Z47) -> 542
B48: Gross margin | C48: 0.761 | D48: 0.701 | E48: 0.748 | F48: 0.784 | G48: =G47/G43 -> 0.75177305 | H48: 0.756 | I48: 0.679 | J48: 0.736 | K48: 0.758 | L48: =L47/L43 -> 0.73276596 | M48: 0.736 | N48: 0.694 | O48: 0.719 | P48: 0.744 | Q48: =Q47/Q43 -> 0.72438443 | R48: 0.723 | S48: 0.683 | T48: 0.691 | U48: 0.723 | V48: =V47/V43 -> 0.70695971 | W48: 0.726 | X48: 0.703 | AA48: =AA47/AA43 -> #DIV/0!
B49: EBITDA | C49: 52 | D49: 79 | E49: 55 | F49: 53 | G49: =SUM(C49:F49) -> 239 | H49: 45 | I49: 83 | J49: 61 | K49: 48 | L49: =SUM(H49:K49) -> 237 | M49: 47 | N49: 92 | O49: 53 | P49: 49 | Q49: =SUM(M49:P49) -> 241 | R49: 62 | S49: 102 | T49: 51 | U49: 59 | V49: =SUM(R49:U49) -> 274 | W49: 57 | X49: 123 | AA49: =SUM(W49:Z49) -> 180
B50: EBITDA margin | C50: 0.2 | D50: 0.267 | E50: 0.189 | F50: 0.185 | G50: =G49/G43 -> 0.21187943 | H50: 0.157 | I50: 0.269 | J50: 0.196 | K50: 0.174 | L50: =L49/L43 -> 0.20170213 | M50: 0.165 | N50: 0.271 | O50: 0.166 | P50: 0.156 | Q50: =Q49/Q43 -> 0.19142176 | R50: 0.183 | S50: 0.283 | T50: 0.148 | U50: 0.18 | V50: =V49/V43 -> 0.2007326 | W50: 0.167 | X50: 0.294 | AA50: =AA49/AA43 -> #DIV/0!
B51: EBIT | G51: =SUM(C51:F51) -> 0 | L51: =SUM(H51:K51) -> 0 | M51: 20 | N51: 65 | O51: 25 | P51: 19 | Q51: =SUM(M51:P51) -> 129 | R51: 32 | S51: 73 | T51: 21 | U51: 29 | V51: =SUM(R51:U51) -> 155 | W51: 25 | X51: 88 | AA51: =SUM(W51:Z51) -> 113
B52: EBIT margin | G52: =G51/G43 -> 0 | L52: =L51/L43 -> 0 | M52: =M51/M43 -> 0.069686411 | N52: =N51/N43 -> 0.19061584 | O52: 0.08 | P52: 0.062 | Q52: =Q51/Q43 -> 0.10246227 | R52: 0.096 | S52: =S51/S43 -> 0.20277778 | T52: 0.063 | U52: 0.089 | V52: =V51/V43 -> 0.11355311 | W52: 0.072 | X52: 0.21 | AA52: =AA51/AA43 -> #DIV/0!
B53: Number of stores | C53: 112 | D53: 114 | E53: 113 | F53: 116 | H53: 118 | I53: 118 | J53: 119 | K53: 120 | M53: 121 | N53: 122 | O53: 127 | P53: 131 | R53: 132 | S53: 132 | T53: 134 | U53: 136 | W53: 136 | X53: 138
B54: Eyeview % | X54: 0.21
B55: Finland
B56: Synsam Lifestyle | C56: 37 | D56: 43 | E56: 52 | F56: 55 | G56: =SUM(C56:F56) -> 187 | H56: 62 | I56: 70 | J56: 79 | K56: 80 | L56: =SUM(H56:K56) -> 291 | M56: 78 | N56: 89 | O56: 88 | P56: 99 | Q56: =SUM(M56:P56) -> 354 | R56: 99 | S56: 108 | T56: 107 | U56: 121 | V56: =SUM(R56:U56) -> 435 | W56: 116 | X56: 129
B57: y/y | H57: =(H56-C56)/C56 -> 0.67567568 | I57: =(I56-D56)/D56 -> 0.62790698 | J57: =(J56-E56)/E56 -> 0.51923077 | K57: =(K56-F56)/F56 -> 0.45454545 | L57: =(L56-G56)/G56 -> 0.55614973 | M57: =(M56-H56)/H56 -> 0.25806452 | N57: =(N56-I56)/I56 -> 0.27142857 | O57: =(O56-J56)/J56 -> 0.11392405 | ... AA57: =(AA56-V56)/V56 -> -1
B58: Non-recurring rev | C58: 44 | D58: 57 | E58: 53 | F58: 52 | G58: =SUM(C58:F58) -> 206 | H58: 64 | I58: 86 | J58: 76 | K58: 74 | L58: =SUM(H58:K58) -> 300 | M58: 76 | N58: 105 | O58: 93 | P58: 82 | Q58: =SUM(M58:P58) -> 356 | R58: 94 | S58: 109 | T58: 113 | U58: 98 | V58: =SUM(R58:U58) -> 414 | W58: 102 | X58: 116
B59: y/y | H59: =(H58-C58)/C58 -> 0.45454545 | I59: =(I58-D58)/D58 -> 0.50877193 | J59: =(J58-E58)/E58 -> 0.43396226 | K59: =(K58-F58)/F58 -> 0.42307692 | L59: =(L58-G58)/G58 -> 0.45631068 | M59: =(M58-H58)/H58 -> 0.1875 | N59: =(N58-I58)/I58 -> 0.22093023 | O59: =(O58-J58)/J58 -> 0.22368421 | ... AA59: =(AA58-V58)/V58 -> -1
B60: Total revenue | C60: =C56+C58 -> 81 | D60: =D56+D58 -> 100 | E60: =E56+E58 -> 105 | F60: =F56+F58 -> 107 | G60: =G56+G58 -> 393 | H60: =H56+H58 -> 126 | I60: =I56+I58 -> 156 | J60: =J56+J58 -> 155 | ... AA60: =AA56+AA58 -> 0
B61: y/y | H61: =(H60-C60)/C60 -> 0.55555556 | I61: =(I60-D60)/D60 -> 0.56 | J61: =(J60-E60)/E60 -> 0.47619048 | K61: =(K60-F60)/F60 -> 0.43925234 | L61: =(L60-G60)/G60 -> 0.50381679 | M61: =(M60-H60)/H60 -> 0.22222222 | N61: =(N60-I60)/I60 -> 0.24358974 | O61: =(O60-J60)/J60 -> 0.16774194 | ... AA61: =(AA60-V60)/V60 -> -1
B62: Organic growth | C62: 0.361 | D62: 0.521 | E62: 0.439 | F62: 0.326 | H62: 0.445 | I62: 0.431 | J62: 0.342 | K62: 0.359 | L62: 0.391 | M62: 0.218 | N62: 0.243 | O62: 0.196 | P62: 0.176 | Q62: 0.208 | R62: 0.262 | S62: 0.166 | T62: 0.261 | U62: 0.271 | V62: 0.238 | W62: 0.187 | X62: 0.139
B63: Like-for-like | H63: 0.28 | I63: 0.261 | J63: 0.176 | K63: 0.189 | M63: 0.08 | N63: 0.111 | O63: 0.084 | P63: 0.062 | R63: 0.16 | S63: 0.086 | T63: 0.171 | U63: 0.212 | V63: 0.156 | W63: 0.141 | X63: 0.102
B64: Gross profit | C64: 59 | D64: 67 | E64: 72 | F64: 77 | G64: =SUM(C64:F64) -> 275 | H64: 88 | I64: 103 | J64: 108 | K64: 108 | L64: =SUM(H64:K64) -> 407 | M64: 108 | N64: 130 | O64: 120 | P64: 128 | Q64: =SUM(M64:P64) -> 486 | R64: 138 | S64: 155 | T64: 152 | U64: 158 | V64: =SUM(R64:U64) -> 603 | W64: 157 | X64: 174 | AA64: =SUM(W64:Z64) -> 331
B65: Gross margin | C65: 0.727 | D65: 0.671 | E65: 0.691 | F65: 0.717 | G65: =G64/G60 -> 0.69974555 | H65: 0.704 | I65: 0.662 | J65: 0.699 | K65: 0.703 | L65: =L64/L60 -> 0.68866328 | M65: 0.704 | N65: 0.668 | O65: 0.656 | P65: 0.706 | Q65: =Q64/Q60 -> 0.68450704 | R65: 0.711 | S65: 0.713 | T65: 0.685 | U65: 0.718 | V65: =V64/V60 -> 0.71024735 | W65: 0.716 | X65: 0.708 | AA65: =AA64/AA60 -> #DIV/0!
B66: EBITDA | C66: 8 | D66: 8 | E66: 14 | F66: 5 | G66: =SUM(C66:F66) -> 35 | H66: 13 | I66: 22 | J66: 25 | K66: 14 | L66: =SUM(H66:K66) -> 74 | M66: 13 | N66: 29 | O66: 20 | P66: 14 | Q66: =SUM(M66:P66) -> 76 | R66: 26 | S66: 33 | T66: 36 | U66: 24 | V66: =SUM(R66:U66) -> 119 | W66: 23 | X66: 31 | AA66: =SUM(W66:Z66) -> 54
B67: EBITDA margin | C67: 0.095 | D67: 0.083 | E67: 0.134 | F67: 0.048 | G67: =G66/G60 -> 0.089058524 | H67: 0.104 | I67: 0.14 | J67: 0.164 | K67: 0.092 | L67: =L66/L60 -> 0.12521151 | M67: 0.083 | N67: 0.147 | O67: 0.113 | P67: 0.079 | Q67: =Q66/Q60 -> 0.10704225 | R67: 0.133 | S67: 0.15 | T67: 0.164 | U67: 0.107 | V67: =V66/V60 -> 0.1401649 | W67: 0.106 | X67: 0.125 | AA67: =AA66/AA60 -> #DIV/0!
B68: EBIT | G68: =SUM(C68:F68) -> 0 | L68: =SUM(H68:K68) -> 0 | M68: -15 | N68: -2 | O68: -11 | P68: -18 | Q68: =SUM(M68:P68) -> -46 | R68: -6 | S68: 2 | T68: 4 | U68: -9 | V68: =SUM(R68:U68) -> -9 | W68: -7 | X68: 0 | AA68: =SUM(W68:Z68) -> -7
B69: EBIT margin | G69: =G68/G60 -> 0 | L69: =L68/L60 -> 0 | M69: =M68/M60 -> -0.097402597 | N69: =N68/N60 -> -0.010309278 | O69: -0.063 | P69: -0.099 | Q69: =Q68/Q60 -> -0.064788732 | R69: -0.029 | S69: =S68/S60 -> 0.0092165899 | T69: 0.019 | U69: -0.042 | V69: =V68/V60 -> -0.010600707 | W69: -0.03 | X69: 0 | AA69: =AA68/AA60 -> #DIV/0!
B70: Number of stores | C70: 43 | D70: 45 | E70: 45 | F70: 50 | H70: 51 | I70: 52 | J70: 54 | K70: 55 | M70: 59 | N70: 62 | O70: 64 | P70: 67 | R70: 68 | S70: 72 | T70: 72 | U70: 73 | W70: 75 | X70: 75

Sheet SOTP
A2: EBIT 26E
A3: =Modell!AF13 -> 976.83
C4: SEKm | D4: EBIT 26E | E4: EV/EBIT | F4: Value | G4: Value/Share
C5: Sweden | D5: 850 | E5: 13 | F5: =D5*E5 -> 11050 | G5: =F5/Modell!$B$5 -> 77.371124
C6: Denmark | D6: 90 | E6: 6 | F6: =D6*E6 -> 540 | G6: =F6/Modell!$B$5 -> 3.7810323
C7: Norway | D7: 120 | E7: 7 | F7: =D7*E7 -> 840 | G7: =F7/Modell!$B$5 -> 5.8816058
C8: Finland | D8: -20 | E8: 5 | F8: =D8*E8 -> -100 | G8: =F8/Modell!$B$5 -> -0.70019117
C9: Enterprise value | D9: =SUM(D5:D8) -> 1040 | F9: =SUM(F5:F8) -> 12330 | G9: =SUM(G5:G8) -> 86.333571
C11: Cash | F11: =Modell!B7 -> 648 | G11: =F11/Modell!$B$5 -> 4.5372388
C12: Debt | F12: =Modell!B8 -> 3653 | G12: =-F12/Modell!$B$5 -> -25.577983
C14: Equity value | F14: =F9+F11-F12 -> 9325 | G14: =SUM(G9:G12) -> 65.292826

Sheet Nøkkeltall
D4: 2026 | E4: 2027 | F4: 2028
C5: EV/EBITDA | D5: =Modell!$B$9/Modell!AF9 -> 5.7318893 | E5: =Modell!$B$9/Modell!AG9 -> 5.3533843 | F5: =Modell!$B$9/Modell!AH9 -> 5.000607
C6: EV/EBIT | D6: =Modell!$B$9/Modell!AF13 -> 10.825181 | E6: =Modell!$B$9/Modell!AG13 -> 9.9970644 | F6: =Modell!$B$9/Modell!AH13 -> 8.9015742
C7: P/E | D7: =Modell!$B$4/Modell!AF20 -> 13.447455 | E7: =Modell!$B$4/Modell!AG20 -> 12.139296 | F7: =Modell!$B$4/Modell!AH20 -> 10.458479

Sheet Nedsideberegning
A3: Nedside | D3: FY 2020 | E3: FY 2021 | F3: FY 2022 | G3: FY 2023 | H3: FY 2024 | I3: FY 2025 | J3: FY 2026 | K3: FY 2027 | L3: FY 2028 | M3: FY 2029 | N3: FY 2030 | O3: FY 2031 | P3: FY 2032 | Q3: FY 2033 | R3: FY 2034 | S3: FY 2035
A4: Nullvekst og dårligste marginene | C4: Revenue | D4: 3860 | E4: 4728 | F4: 5349 | G4: 5985 | H4: 6522 | I4: 7200 | J4: =I4*1.06 -> 7632 | K4: =J4*1 -> 7632 | L4: =K4*1 -> 7632 | M4: =L4*1 -> 7632 | N4: =M4*1 -> 7632 | O4: =N4*1 -> 7632 | P4: =O4*1 -> 7632 | Q4: =P4*1 -> 7632 | R4: =Q4*1 -> 7632 | S4: =R4*1 -> 7632
A5: =V25 -> 35.854091 | C5: Goods for resale | D5: -953 | E5: -1088 | F5: -1279 | G5: -1447 | H5: -1591 | I5: -1821 | J5: =J4*-0.24 -> -1831.68 | K5: =K4*-0.26 -> -1984.32 | L5: =L4*-0.26 -> -1984.32 | M5: =M4*-0.26 -> -1984.32 | N5: =N4*-0.26 -> -1984.32 | O5: =O4*-0.26 -> -1984.32 | P5: =P4*-0.26 -> -1984.32 | Q5: =Q4*-0.26 -> -1984.32 | R5: =R4*-0.26 -> -1984.32 | S5: =S4*-0.26 -> -1984.32
A6: =V26 -> -0.32350772 | C6: Gross profit | D6: =SUM(D4:D5) -> 2907 | E6: =SUM(E4:E5) -> 3640 | F6: =SUM(F4:F5) -> 4070 | G6: =SUM(G4:G5) -> 4538 | H6: =SUM(H4:H5) -> 4931 | I6: =SUM(I4:I5) -> 5379 | J6: =SUM(J4:J5) -> 5800.32 | K6: =SUM(K4:K5) -> 5647.68 | ... S6: =SUM(S4:S5) -> 5647.68
C7: Other external expenses | D7: -468 | E7: -629 | F7: -667 | G7: -682 | H7: -711 | I7: -805 | J7: =I7*1.08 -> -869.4 | K7: =J7*1 -> -869.4 | L7: =K7 -> -869.4 | M7: =L7*0.99 -> -860.706 | N7: =M7*0.99 -> -852.09894 | O7: =N7*0.99 -> -843.57795 | P7: =O7*0.99 -> -835.14217 | Q7: =P7*0.99 -> -826.79075 | R7: =Q7*0.99 -> -818.52284 | S7: =R7*0.99 -> -810.33761
C8: Persnonnel costs | D8: -1505 | E8: -1823 | F8: -2186 | G8: -2415 | H8: -2624 | I8: -2886 | J8: =I8*1.08 -> -3116.88 | K8: =J8*1 -> -3116.88 | L8: =K8 -> -3116.88 | M8: =L8 -> -3116.88 | N8: =M8 -> -3116.88 | O8: =N8 -> -3116.88 | P8: =O8 -> -3116.88 | Q8: =P8 -> -3116.88 | R8: =Q8 -> -3116.88 | S8: =R8 -> -3116.88
C9: EBITDA | D9: =SUM(D6:D8) -> 934 | E9: =SUM(E6:E8) -> 1188 | F9: =SUM(F6:F8) -> 1217 | G9: =SUM(G6:G8) -> 1441 | H9: =SUM(H6:H8) -> 1596 | I9: =SUM(I6:I8) -> 1688 | J9: =SUM(J6:J8) -> 1814.04 | K9: =SUM(K6:K8) -> 1661.4 | ... S9: =SUM(S6:S8) -> 1720.4624
C10: Depreciation | D10: -445 | E10: -464 | F10: -556 | G10: -622 | H10: -649 | I10: -702 | J10: -728 | K10: =J10*1 -> -728 | L10: =K10*1 -> -728 | M10: =L10*1.01 -> -735.28 | N10: =M10*1.01 -> -742.6328 | O10: =N10*1.01 -> -750.05913 | P10: =O10*1.01 -> -757.55972 | Q10: =P10*1.01 -> -765.13532 | R10: =Q10*1.01 -> -772.78667 | S10: =R10*1.01 -> -780.51454
C11: EBITA | D11: =SUM(D9:D10) -> 489 | E11: =SUM(E9:E10) -> 724 | F11: =SUM(F9:F10) -> 661 | G11: =SUM(G9:G10) -> 819 | H11: =SUM(H9:H10) -> 947 | I11: =SUM(I9:I10) -> 986 | J11: =SUM(J9:J10) -> 1086.04 | K11: =SUM(K9:K10) -> 933.4 | ... S11: =SUM(S9:S10) -> 939.94785
C12: Amortization | D12: -87 | E12: -91 | F12: -109 | G12: -123 | H12: -128 | I12: -124 | J12: -130 | K12: =J12*1 -> -130 | L12: =K12*1 -> -130 | M12: =L12*1 -> -130 | N12: =M12*1 -> -130 | O12: =N12*1 -> -130 | P12: =O12*1 -> -130 | Q12: =P12*1 -> -130 | R12: =Q12*1 -> -130 | S12: =R12*1 -> -130
C13: EBIT | D13: =SUM(D11:D12) -> 402 | E13: =SUM(E11:E12) -> 633 | F13: =SUM(F11:F12) -> 552 | G13: =SUM(G11:G12) -> 696 | H13: =SUM(H11:H12) -> 819 | I13: =SUM(I11:I12) -> 862 | J13: =SUM(J11:J12) -> 956.04 | K13: =SUM(K11:K12) -> 803.4 | ... S13: =SUM(S11:S12) -> 809.94785
C14: Fincial income | D14: 98 | E14: 148 | F14: 185 | G14: 273 | H14: 326 | I14: 321 | J14: =I14*1.02 -> 327.42 | K14: =J14*1 -> 327.42 | L14: =K14*1 -> 327.42 | M14: =L14*1 -> 327.42 | N14: =M14*1 -> 327.42 | O14: =N14*1 -> 327.42 | P14: =O14*1 -> 327.42 | Q14: =P14*1 -> 327.42 | R14: =Q14*1 -> 327.42 | S14: =R14*1 -> 327.42
C15: Financial expenses | D15: -636 | E15: -618 | F15: -322 | G15: -554 | H15: -652 | I15: -593 | J15: =I15*1.02 -> -604.86 | K15: =J15*1 -> -604.86 | L15: =K15*1 -> -604.86 | M15: =L15*1 -> -604.86 | N15: =M15*1 -> -604.86 | O15: =N15*1 -> -604.86 | P15: =O15*1 -> -604.86 | Q15: =P15*1 -> -604.86 | R15: =Q15*1 -> -604.86 | S15: =R15*1 -> -604.86
C16: PTP | D16: =SUM(D13:D15) -> -136 | E16: =SUM(E13:E15) -> 163 | F16: =SUM(F13:F15) -> 415 | G16: =SUM(G13:G15) -> 415 | H16: =SUM(H13:H15) -> 493 | I16: =SUM(I13:I15) -> 590 | J16: =SUM(J13:J15) -> 678.6 | K16: =SUM(K13:K15) -> 525.96 | ... S16: =SUM(S13:S15) -> 532.50785
C17: Tax | D17: -59 | E17: -112 | F17: -87 | G17: -104 | H17: -127 | I17: -136 | J17: =J16*-0.2 -> -135.72 | K17: =K16*-0.2 -> -105.192 | L17: =L16*-0.2 -> -105.192 | M17: =M16*-0.2 -> -105.4748 | N17: =N16*-0.2 -> -105.72565 | O17: =O16*-0.2 -> -105.94458 | P17: =P16*-0.2 -> -106.13162 | Q17: =Q16*-0.2 -> -106.28679 | ... S17: =S16*-0.2 -> -106.50157
C18: Net income | D18: =SUM(D16:D17) -> -195 | E18: =SUM(E16:E17) -> 51 | F18: =SUM(F16:F17) -> 328 | G18: =SUM(G16:G17) -> 311 | H18: =SUM(H16:H17) -> 366 | I18: =SUM(I16:I17) -> 454 | J18: =SUM(J16:J17) -> 542.88 | K18: =SUM(K16:K17) -> 420.768 | ... S18: =SUM(S16:S17) -> 426.00628 | T18: =S18*(1+$V$22) -> 421.74622 | U18: =T18*(1+$V$22) -> 417.52876 | V18: =U18*(1+$V$22) -> 413.35347 | W18: =V18*(1+$V$22) -> 409.21993 | X18: =W18*(1+$V$22) -> 405.12773 | Y18: =X18*(1+$V$22) -> 401.07646 | Z18: =Y18*(1+$V$22) -> 397.06569 | AA18: =Z18*(1+$V$22) -> 393.09503 | ... GS18: =GR18*(1+$V$22) -> 68.394538
C19: Share | D19: 37.181942 | E19: 150 | F19: 149.055 | G19: 147.42368 | H19: 146.64875 | I19: 142.81814 | J19: 141.96249 | K19: 142.81814 | L19: 142.81814 | M19: 142.81814 | N19: 142.81814 | O19: 142.81814 | P19: 142.81814 | Q19: 142.81814 | R19: 142.81814 | S19: 142.81814
C20: EPS | D20: =D18/D19 -> -5.2444813 | E20: =E18/E19 -> 0.34 | F20: =F18/F19 -> 2.20053 | G20: =G18/G19 -> 2.1095662 | H20: =H18/H19 -> 2.4957595 | I20: =I18/I19 -> 3.1788679 | J20: =J18/J19 -> 3.8241086 | K20: =K18/K19 -> 2.9461804 | ... S20: =S18/S19 -> 2.9828583
U21: Discount | V21: 0.08
C22: Revenue y/y | E22: =(E4-D4)/D4 -> 0.22487047 | F22: =(F4-E4)/E4 -> 0.13134518 | G22: =(G4-F4)/F4 -> 0.11890073 | H22: =(H4-G4)/G4 -> 0.089724311 | I22: =(I4-H4)/H4 -> 0.10395584 | J22: =(J4-I4)/I4 -> 0.06 | K22: =(K4-J4)/J4 -> 0 | L22: =(L4-K4)/K4 -> 0 | ... S22: =(S4-R4)/R4 -> 0 | U22: TV | V22: -0.01
C23: Organic growth | D23: 0.032 | E23: 0.232 | F23: 0.106 | G23: 0.103 | H23: 0.092 | I23: 0.114 | U23: NPV | V23: =NPV(V21,J18:GS18) -> 5120.6146
C24: Like-for-like | U24: S/O | V24: 142.81814
U25: NPV/Share | V25: =V23/V24 -> 35.854091
C26: Gross margin | D26: =D6/D4 -> 0.75310881 | E26: =E6/E4 -> 0.76988156 | F26: =F6/F4 -> 0.76088989 | G26: =G6/G4 -> 0.75822891 | H26: =H6/H4 -> 0.75605642 | I26: =I6/I4 -> 0.74708333 | J26: =J6/J4 -> 0.76 | K26: =K6/K4 -> 0.74 | ... S26: =S6/S4 -> 0.74 | U26: Opp/nedside | V26: =(V25-Modell!B4)/Modell!B4 -> -0.32350772
C27: EBITDA margin | D27: =D9/D4 -> 0.24196891 | E27: =E9/E4 -> 0.25126904 | F27: =F9/F4 -> 0.22751916 | G27: =G9/G4 -> 0.24076859 | H27: =H9/H4 -> 0.24471021 | I27: =I9/I4 -> 0.23444444 | J27: =J9/J4 -> 0.23768868 | K27: =K9/K4 -> 0.21768868 | ... S27: =S9/S4 -> 0.22542746
C28: EBITA margin | D28: =D11/D4 -> 0.12668394 | E28: =E11/E4 -> 0.15313029 | F28: =F11/F4 -> 0.1235745 | G28: =G11/G4 -> 0.13684211 | H28: =H11/H4 -> 0.14520086 | I28: =I11/I4 -> 0.13694444 | J28: =J11/J4 -> 0.14230084 | K28: =K11/K4 -> 0.12230084 | ... S28: =S11/S4 -> 0.12315879
C29: EBIT margin | D29: =D13/D4 -> 0.10414508 | E29: =E13/E4 -> 0.13388325 | F29: =F13/F4 -> 0.10319686 | G29: =G13/G4 -> 0.11629073 | H29: =H13/H4 -> 0.12557498 | I29: =I13/I4 -> 0.11972222 | J29: =J13/J4 -> 0.1252673 | K29: =K13/K4 -> 0.1052673 | ... S29: =S13/S4 -> 0.10612524
